Workbook
Name GEE_ALL: Annual!$X$79:$BB$91
Name GEE_ALL: #REF!
Name WEOGEE_Rwametric_Qdata: Quarterly!$D$79:$CD$91
Name WEOGEE_Rwametric_Qdata: #REF!

Sheet Definitions
A2: Rwanda
A3: Advanced economy partners
A5: Real GDP | B5: Real GDP, 2005=100, Weighted by trade exports to advanced economies. Source of the Real GDP is desk submitted data for Real GDP (NGDP_R). | C5: Real GDP, 2005=100, Weighted by trade exports to advanced economies. Source of the Real GDP is desk submitted data for Real GDP (NGDP_R). | D5: Real GDP, 2005=100, Weighted by trade exports to advanced economies. Source of the Real GDP is desk submitted data for Real GDP (NGDP_R). | E5: Real GDP, 2005=100, Weighted by trade exports to advanced economies. Source of the Real GDP is desk submitted data for Real GDP (NGDP_R). | F5: Real GDP, 2005=100, Weighted by trade exports to advanced economies. Source of the Real GDP is desk submitted data for Real GDP (NGDP_R). | G5: Real GDP, 2005=100, Weighted by trade exports to advanced economies. Source of the Real GDP is desk submitted data for Real GDP (NGDP_R). | H5: Real GDP, 2005=100, Weighted by trade exports to advanced economies. Source of the Real GDP is desk submitted data for Real GDP (NGDP_R). | I5: Real GDP, 2005=100, Weighted by trade exports to advanced economies. Source of the Real GDP is desk submitted data for Real GDP (NGDP_R). | J5: Real GDP, 2005=100, Weighted by trade exports to advanced economies. Source of the Real GDP is desk submitted data for Real GDP (NGDP_R). | K5: Real GDP, 2005=100, Weighted by trade exports to advanced economies. Source of the Real GDP is desk submitted data for Real GDP (NGDP_R).
A6: Real total dometic demand | B6: Real total domestic demand, 2005=100, Weighted by trade exports to advanced economies. Source of the Real total domestic demand is desk submitted data for (NTDD_R). | C6: Real total domestic demand, 2005=100, Weighted by trade exports to advanced economies. Source of the Real total domestic demand is desk submitted data for (NTDD_R). | D6: Real total domestic demand, 2005=100, Weighted by trade exports to advanced economies. Source of the Real total domestic demand is desk submitted data for (NTDD_R). | E6: Real total domestic demand, 2005=100, Weighted by trade exports to advanced economies. Source of the Real total domestic demand is desk submitted data for (NTDD_R). | F6: Real total domestic demand, 2005=100, Weighted by trade exports to advanced economies. Source of the Real total domestic demand is desk submitted data for (NTDD_R). | G6: Real total domestic demand, 2005=100, Weighted by trade exports to advanced economies. Source of the Real total domestic demand is desk submitted data for (NTDD_R). | H6: Real total domestic demand, 2005=100, Weighted by trade exports to advanced economies. Source of the Real total domestic demand is desk submitted data for (NTDD_R). | I6: Real total domestic demand, 2005=100, Weighted by trade exports to advanced economies. Source of the Real total domestic demand is desk submitted data for (NTDD_R). | J6: Real total domestic demand, 2005=100, Weighted by trade exports to advanced economies. Source of the Real total domestic demand is desk submitted data for (NTDD_R). | K6: Real total domestic demand, 2005=100, Weighted by trade exports to advanced economies. Source of the Real total domestic demand is desk submitted data for (NTDD_R). | L6: Real total domestic demand, 2005=100, Weighted by trade exports to advanced economies. Source of the Real total domestic demand is desk submitted data for (NTDD_R). | M6: Real total domestic demand, 2005=100, Weighted by trade exports to advanced economies. Source of the Real total domestic demand is desk submitted data for (NTDD_R).
A8: All countries
A10: Real GDP | B10: Real GDP, 2005=100, Weighted by trade exports to all partner countries. Source of the Real GDP is desk submitted data for Real GDP (NGDP_R). | C10: Real GDP, 2005=100, Weighted by trade exports to all partner countries. Source of the Real GDP is desk submitted data for Real GDP (NGDP_R). | D10: Real GDP, 2005=100, Weighted by trade exports to all partner countries. Source of the Real GDP is desk submitted data for Real GDP (NGDP_R). | E10: Real GDP, 2005=100, Weighted by trade exports to all partner countries. Source of the Real GDP is desk submitted data for Real GDP (NGDP_R). | F10: Real GDP, 2005=100, Weighted by trade exports to all partner countries. Source of the Real GDP is desk submitted data for Real GDP (NGDP_R). | G10: Real GDP, 2005=100, Weighted by trade exports to all partner countries. Source of the Real GDP is desk submitted data for Real GDP (NGDP_R). | H10: Real GDP, 2005=100, Weighted by trade exports to all partner countries. Source of the Real GDP is desk submitted data for Real GDP (NGDP_R). | I10: Real GDP, 2005=100, Weighted by trade exports to all partner countries. Source of the Real GDP is desk submitted data for Real GDP (NGDP_R). | J10: Real GDP, 2005=100, Weighted by trade exports to all partner countries. Source of the Real GDP is desk submitted data for Real GDP (NGDP_R). | K10: Real GDP, 2005=100, Weighted by trade exports to all partner countries. Source of the Real GDP is desk submitted data for Real GDP (NGDP_R).
A11: Real imports
A12: Goods and services | B12: Imports volume of goods and services, 2005=100, Weighted by trade exports to all partner countries. Source of the Volume of total imports of goods and services (TM_R) is desk submitted data.
A13: Goods | B13: Imports volume of goods, 2005=100, Weighted by trade exports to all partner countries. Source of the Volume of imports of goods (TMG_R) is desk submitted data. | C13: Imports volume of goods, 2005=100, Weighted by trade exports to all partner countries. Source of the Volume of imports of goods (TMG_R) is desk submitted data. | D13: Imports volume of goods, 2005=100, Weighted by trade exports to all partner countries. Source of the Volume of imports of goods (TMG_R) is desk submitted data. | E13: Imports volume of goods, 2005=100, Weighted by trade exports to all partner countries. Source of the Volume of imports of goods (TMG_R) is desk submitted data. | F13: Imports volume of goods, 2005=100, Weighted by trade exports to all partner countries. Source of the Volume of imports of goods (TMG_R) is desk submitted data. | G13: Imports volume of goods, 2005=100, Weighted by trade exports to all partner countries. Source of the Volume of imports of goods (TMG_R) is desk submitted data. | H13: Imports volume of goods, 2005=100, Weighted by trade exports to all partner countries. Source of the Volume of imports of goods (TMG_R) is desk submitted data. | I13: Imports volume of goods, 2005=100, Weighted by trade exports to all partner countries. Source of the Volume of imports of goods (TMG_R) is desk submitted data. | J13: Imports volume of goods, 2005=100, Weighted by trade exports to all partner countries. Source of the Volume of imports of goods (TMG_R) is desk submitted data. | K13: Imports volume of goods, 2005=100, Weighted by trade exports to all partner countries. Source of the Volume of imports of goods (TMG_R) is desk submitted data. | L13: Imports volume of goods, 2005=100, Weighted by trade exports to all partner countries. Source of the Volume of imports of goods (TMG_R) is desk submitted data.
A14: Excluding oil | B14: Imports volume of goods excl. oil, 2005=100, Weighted by trade exports to all partner countries. The Volume of non-oil imports is calculated by TMG_R-TMGO_R which are provided by desk. | C14: Imports volume of goods excl. oil, 2005=100, Weighted by trade exports to all partner countries. The Volume of non-oil imports is calculated by TMG_R-TMGO_R which are provided by desk. | D14: Imports volume of goods excl. oil, 2005=100, Weighted by trade exports to all partner countries. The Volume of non-oil imports is calculated by TMG_R-TMGO_R which are provided by desk. | E14: Imports volume of goods excl. oil, 2005=100, Weighted by trade exports to all partner countries. The Volume of non-oil imports is calculated by TMG_R-TMGO_R which are provided by desk. | F14: Imports volume of goods excl. oil, 2005=100, Weighted by trade exports to all partner countries. The Volume of non-oil imports is calculated by TMG_R-TMGO_R which are provided by desk. | G14: Imports volume of goods excl. oil, 2005=100, Weighted by trade exports to all partner countries. The Volume of non-oil imports is calculated by TMG_R-TMGO_R which are provided by desk. | H14: Imports volume of goods excl. oil, 2005=100, Weighted by trade exports to all partner countries. The Volume of non-oil imports is calculated by TMG_R-TMGO_R which are provided by desk. | I14: Imports volume of goods excl. oil, 2005=100, Weighted by trade exports to all partner countries. The Volume of non-oil imports is calculated by TMG_R-TMGO_R which are provided by desk. | J14: Imports volume of goods excl. oil, 2005=100, Weighted by trade exports to all partner countries. The Volume of non-oil imports is calculated by TMG_R-TMGO_R which are provided by desk. | K14: Imports volume of goods excl. oil, 2005=100, Weighted by trade exports to all partner countries. The Volume of non-oil imports is calculated by TMG_R-TMGO_R which are provided by desk. | L14: Imports volume of goods excl. oil, 2005=100, Weighted by trade exports to all partner countries. The Volume of non-oil imports is calculated by TMG_R-TMGO_R which are provided by desk. | M14: Imports volume of goods excl. oil, 2005=100, Weighted by trade exports to all partner countries. The Volume of non-oil imports is calculated by TMG_R-TMGO_R which are provided by desk. | N14: Imports volume of goods excl. oil, 2005=100, Weighted by trade exports to all partner countries. The Volume of non-oil imports is calculated by TMG_R-TMGO_R which are provided by desk. | O14: Imports volume of goods excl. oil, 2005=100, Weighted by trade exports to all partner countries. The Volume of non-oil imports is calculated by TMG_R-TMGO_R which are provided by desk.
A16: Real exports
A17: Goods and services | B17: Exports volume of goods and services, 2005=100, Weighted by trade imports from all partner countries. Source of the Volume of total exports of goods and services (TX_R) is desk submitted data.
A18: Goods | B18: Exports volume of goods, 2005=100, Weighted by trade imports from all partner countries. Source of the Volume of exports of goods (TXG_R) is desk submitted data. | C18: Imports volume of goods, 2005=100, Weighted by trade exports to all partner countries. Source of the Volume of imports of goods (TMG_R) is desk submitted data. | D18: Imports volume of goods, 2005=100, Weighted by trade exports to all partner countries. Source of the Volume of imports of goods (TMG_R) is desk submitted data. | E18: Imports volume of goods, 2005=100, Weighted by trade exports to all partner countries. Source of the Volume of imports of goods (TMG_R) is desk submitted data. | F18: Imports volume of goods, 2005=100, Weighted by trade exports to all partner countries. Source of the Volume of imports of goods (TMG_R) is desk submitted data. | G18: Imports volume of goods, 2005=100, Weighted by trade exports to all partner countries. Source of the Volume of imports of goods (TMG_R) is desk submitted data. | H18: Imports volume of goods, 2005=100, Weighted by trade exports to all partner countries. Source of the Volume of imports of goods (TMG_R) is desk submitted data. | I18: Imports volume of goods, 2005=100, Weighted by trade exports to all partner countries. Source of the Volume of imports of goods (TMG_R) is desk submitted data. | J18: Imports volume of goods, 2005=100, Weighted by trade exports to all partner countries. Source of the Volume of imports of goods (TMG_R) is desk submitted data. | K18: Imports volume of goods, 2005=100, Weighted by trade exports to all partner countries. Source of the Volume of imports of goods (TMG_R) is desk submitted data. | L18: Imports volume of goods, 2005=100, Weighted by trade exports to all partner countries. Source of the Volume of imports of goods (TMG_R) is desk submitted data.
A19: Excluding oil | B19: Exports volume of goods excl. oil, 2005=100, Weighted by trade imports from all partner countries. The Volume of non-oil imports is calculated by TXG_R-TMGO_R which are provided by desk. | C19: Imports volume of goods excl. oil, 2005=100, Weighted by trade exports to all partner countries. The Volume of non-oil imports is calculated by TMG_R-TMGO_R which are provided by desk. | D19: Imports volume of goods excl. oil, 2005=100, Weighted by trade exports to all partner countries. The Volume of non-oil imports is calculated by TMG_R-TMGO_R which are provided by desk. | E19: Imports volume of goods excl. oil, 2005=100, Weighted by trade exports to all partner countries. The Volume of non-oil imports is calculated by TMG_R-TMGO_R which are provided by desk. | F19: Imports volume of goods excl. oil, 2005=100, Weighted by trade exports to all partner countries. The Volume of non-oil imports is calculated by TMG_R-TMGO_R which are provided by desk. | G19: Imports volume of goods excl. oil, 2005=100, Weighted by trade exports to all partner countries. The Volume of non-oil imports is calculated by TMG_R-TMGO_R which are provided by desk. | H19: Imports volume of goods excl. oil, 2005=100, Weighted by trade exports to all partner countries. The Volume of non-oil imports is calculated by TMG_R-TMGO_R which are provided by desk. | I19: Imports volume of goods excl. oil, 2005=100, Weighted by trade exports to all partner countries. The Volume of non-oil imports is calculated by TMG_R-TMGO_R which are provided by desk. | J19: Imports volume of goods excl. oil, 2005=100, Weighted by trade exports to all partner countries. The Volume of non-oil imports is calculated by TMG_R-TMGO_R which are provided by desk. | K19: Imports volume of goods excl. oil, 2005=100, Weighted by trade exports to all partner countries. The Volume of non-oil imports is calculated by TMG_R-TMGO_R which are provided by desk. | L19: Imports volume of goods excl. oil, 2005=100, Weighted by trade exports to all partner countries. The Volume of non-oil imports is calculated by TMG_R-TMGO_R which are provided by desk. | M19: Imports volume of goods excl. oil, 2005=100, Weighted by trade exports to all partner countries. The Volume of non-oil imports is calculated by TMG_R-TMGO_R which are provided by desk. | N19: Imports volume of goods excl. oil, 2005=100, Weighted by trade exports to all partner countries. The Volume of non-oil imports is calculated by TMG_R-TMGO_R which are provided by desk. | O19: Imports volume of goods excl. oil, 2005=100, Weighted by trade exports to all partner countries. The Volume of non-oil imports is calculated by TMG_R-TMGO_R which are provided by desk.
A22: Foreign Prices and Costs | B22: Foreign Prices and Costs | C22: Foreign Prices and Costs | D22: Foreign Prices and Costs | E22: Foreign Prices and Costs | F22: Foreign Prices and Costs | G22: Foreign Prices and Costs | H22: Foreign Prices and Costs | I22: Foreign Prices and Costs | J22: Foreign Prices and Costs | K22: Foreign Prices and Costs | L22: Foreign Prices and Costs | M22: Foreign Prices and Costs | N22: Foreign Prices and Costs | O22: Foreign Prices and Costs
A23: Advanced economy partners
A25: GDP deflators
A26: In national currency | B26: GDP deflator, 2005=100, Weighted by trade imports from advanced economies. Source of the GDP deflator is desk submitted data for Nominal GDP (NGDP) divided by Real GDP (NGDP_R). | C26: GDP deflator, 2005=100, Weighted by trade imports from advanced economies. Source of the GDP deflator is desk submitted data for Nominal GDP (NGDP) divided by Real GDP (NGDP_R). | D26: GDP deflator, 2005=100, Weighted by trade imports from advanced economies. Source of the GDP deflator is desk submitted data for Nominal GDP (NGDP) divided by Real GDP (NGDP_R). | E26: GDP deflator, 2005=100, Weighted by trade imports from advanced economies. Source of the GDP deflator is desk submitted data for Nominal GDP (NGDP) divided by Real GDP (NGDP_R). | F26: GDP deflator, 2005=100, Weighted by trade imports from advanced economies. Source of the GDP deflator is desk submitted data for Nominal GDP (NGDP) divided by Real GDP (NGDP_R). | G26: GDP deflator, 2005=100, Weighted by trade imports from advanced economies. Source of the GDP deflator is desk submitted data for Nominal GDP (NGDP) divided by Real GDP (NGDP_R). | H26: GDP deflator, 2005=100, Weighted by trade imports from advanced economies. Source of the GDP deflator is desk submitted data for Nominal GDP (NGDP) divided by Real GDP (NGDP_R). | I26: GDP deflator, 2005=100, Weighted by trade imports from advanced economies. Source of the GDP deflator is desk submitted data for Nominal GDP (NGDP) divided by Real GDP (NGDP_R). | J26: GDP deflator, 2005=100, Weighted by trade imports from advanced economies. Source of the GDP deflator is desk submitted data for Nominal GDP (NGDP) divided by Real GDP (NGDP_R). | K26: GDP deflator, 2005=100, Weighted by trade imports from advanced economies. Source of the GDP deflator is desk submitted data for Nominal GDP (NGDP) divided by Real GDP (NGDP_R). | L26: GDP deflator, 2005=100, Weighted by trade imports from advanced economies. Source of the GDP deflator is desk submitted data for Nominal GDP (NGDP) divided by Real GDP (NGDP_R). | M26: GDP deflator, 2005=100, Weighted by trade imports from advanced economies. Source of the GDP deflator is desk submitted data for Nominal GDP (NGDP) divided by Real GDP (NGDP_R). | N26: GDP deflator, 2005=100, Weighted by trade imports from advanced economies. Source of the GDP deflator is desk submitted data for Nominal GDP (NGDP) divided by Real GDP (NGDP_R).
A27: In U.S. dollars | B27: GDP deflator, US$, 2005=100, Weighted by trade imports from advanced economies. Source of the GDP deflator is desk submitted data for Nominal GDP (NGDP) divided by Real GDP (NGDP_R) converted to US$. | C27: GDP deflator, US$, 2005=100, Weighted by trade imports from advanced economies. Source of the GDP deflator is desk submitted data for Nominal GDP (NGDP) divided by Real GDP (NGDP_R) converted to US$. | D27: GDP deflator, US$, 2005=100, Weighted by trade imports from advanced economies. Source of the GDP deflator is desk submitted data for Nominal GDP (NGDP) divided by Real GDP (NGDP_R) converted to US$. | E27: GDP deflator, US$, 2005=100, Weighted by trade imports from advanced economies. Source of the GDP deflator is desk submitted data for Nominal GDP (NGDP) divided by Real GDP (NGDP_R) converted to US$. | F27: GDP deflator, US$, 2005=100, Weighted by trade imports from advanced economies. Source of the GDP deflator is desk submitted data for Nominal GDP (NGDP) divided by Real GDP (NGDP_R) converted to US$. | G27: GDP deflator, US$, 2005=100, Weighted by trade imports from advanced economies. Source of the GDP deflator is desk submitted data for Nominal GDP (NGDP) divided by Real GDP (NGDP_R) converted to US$. | H27: GDP deflator, US$, 2005=100, Weighted by trade imports from advanced economies. Source of the GDP deflator is desk submitted data for Nominal GDP (NGDP) divided by Real GDP (NGDP_R) converted to US$. | I27: GDP deflator, US$, 2005=100, Weighted by trade imports from advanced economies. Source of the GDP deflator is desk submitted data for Nominal GDP (NGDP) divided by Real GDP (NGDP_R) converted to US$. | J27: GDP deflator, US$, 2005=100, Weighted by trade imports from advanced economies. Source of the GDP deflator is desk submitted data for Nominal GDP (NGDP) divided by Real GDP (NGDP_R) converted to US$. | K27: GDP deflator, US$, 2005=100, Weighted by trade imports from advanced economies. Source of the GDP deflator is desk submitted data for Nominal GDP (NGDP) divided by Real GDP (NGDP_R) converted to US$. | L27: GDP deflator, US$, 2005=100, Weighted by trade imports from advanced economies. Source of the GDP deflator is desk submitted data for Nominal GDP (NGDP) divided by Real GDP (NGDP_R) converted to US$. | M27: GDP deflator, US$, 2005=100, Weighted by trade imports from advanced economies. Source of the GDP deflator is desk submitted data for Nominal GDP (NGDP) divided by Real GDP (NGDP_R) converted to US$. | N27: GDP deflator, US$, 2005=100, Weighted by trade imports from advanced economies. Source of the GDP deflator is desk submitted data for Nominal GDP (NGDP) divided by Real GDP (NGDP_R) converted to US$. | O27: GDP deflator, US$, 2005=100, Weighted by trade imports from advanced economies. Source of the GDP deflator is desk submitted data for Nominal GDP (NGDP) divided by Real GDP (NGDP_R) converted to US$.
A29: Consumer prices
A30: In national currency | B30: CPI, 2005=100, Weighted by trade imports from advanced economies. Source of the consumer price index is desk submitted data (PCPI). | C30: CPI, 2005=100, Weighted by trade imports from advanced economies. Source of the consumer price index is desk submitted data (PCPI). | D30: CPI, 2005=100, Weighted by trade imports from advanced economies. Source of the consumer price index is desk submitted data (PCPI). | E30: CPI, 2005=100, Weighted by trade imports from advanced economies. Source of the consumer price index is desk submitted data (PCPI). | F30: CPI, 2005=100, Weighted by trade imports from advanced economies. Source of the consumer price index is desk submitted data (PCPI). | G30: CPI, 2005=100, Weighted by trade imports from advanced economies. Source of the consumer price index is desk submitted data (PCPI). | H30: CPI, 2005=100, Weighted by trade imports from advanced economies. Source of the consumer price index is desk submitted data (PCPI). | I30: CPI, 2005=100, Weighted by trade imports from advanced economies. Source of the consumer price index is desk submitted data (PCPI). | J30: CPI, 2005=100, Weighted by trade imports from advanced economies. Source of the consumer price index is desk submitted data (PCPI).
A31: In U.S. dollars | B31: CPI, US$, 2005=100, Weighted by trade imports from advanced economies. Source of the consumer price index is desk submitted data (PCPI) converted to US$. | C31: CPI, US$, 2005=100, Weighted by trade imports from advanced economies. Source of the consumer price index is desk submitted data (PCPI) converted to US$. | D31: CPI, US$, 2005=100, Weighted by trade imports from advanced economies. Source of the consumer price index is desk submitted data (PCPI) converted to US$. | E31: CPI, US$, 2005=100, Weighted by trade imports from advanced economies. Source of the consumer price index is desk submitted data (PCPI) converted to US$. | F31: CPI, US$, 2005=100, Weighted by trade imports from advanced economies. Source of the consumer price index is desk submitted data (PCPI) converted to US$. | G31: CPI, US$, 2005=100, Weighted by trade imports from advanced economies. Source of the consumer price index is desk submitted data (PCPI) converted to US$. | H31: CPI, US$, 2005=100, Weighted by trade imports from advanced economies. Source of the consumer price index is desk submitted data (PCPI) converted to US$. | I31: CPI, US$, 2005=100, Weighted by trade imports from advanced economies. Source of the consumer price index is desk submitted data (PCPI) converted to US$. | J31: CPI, US$, 2005=100, Weighted by trade imports from advanced economies. Source of the consumer price index is desk submitted data (PCPI) converted to US$. | K31: CPI, US$, 2005=100, Weighted by trade imports from advanced economies. Source of the consumer price index is desk submitted data (PCPI) converted to US$. | L31: CPI, US$, 2005=100, Weighted by trade imports from advanced economies. Source of the consumer price index is desk submitted data (PCPI) converted to US$. | M31: CPI, US$, 2005=100, Weighted by trade imports from advanced economies. Source of the consumer price index is desk submitted data (PCPI) converted to US$. | N31: CPI, US$, 2005=100, Weighted by trade imports from advanced economies. Source of the consumer price index is desk submitted data (PCPI) converted to US$. | O31: CPI, US$, 2005=100, Weighted by trade imports from advanced economies. Source of the consumer price index is desk submitted data (PCPI) converted to US$.
A33: All countries
A35: Export deflators in U.S. dollars
A36: Goods and services | B36: Exports deflator of goods and services, 2005=100, Weighted by trade imports from all partner countries. Source of the exports deflator of goods and services is WEO calculated data (TX_D). | C36: Exports deflator of goods and services, 2005=100, Weighted by trade imports from all partner countries. Source of the exports deflator of goods and services is WEO calculated data (TX_D). | D36: Exports deflator of goods and services, 2005=100, Weighted by trade imports from all partner countries. Source of the exports deflator of goods and services is WEO calculated data (TX_D). | E36: Exports deflator of goods and services, 2005=100, Weighted by trade imports from all partner countries. Source of the exports deflator of goods and services is WEO calculated data (TX_D). | F36: Exports deflator of goods and services, 2005=100, Weighted by trade imports from all partner countries. Source of the exports deflator of goods and services is WEO calculated data (TX_D). | G36: Exports deflator of goods and services, 2005=100, Weighted by trade imports from all partner countries. Source of the exports deflator of goods and services is WEO calculated data (TX_D). | H36: Exports deflator of goods and services, 2005=100, Weighted by trade imports from all partner countries. Source of the exports deflator of goods and services is WEO calculated data (TX_D). | I36: Exports deflator of goods and services, 2005=100, Weighted by trade imports from all partner countries. Source of the exports deflator of goods and services is WEO calculated data (TX_D). | J36: Exports deflator of goods and services, 2005=100, Weighted by trade imports from all partner countries. Source of the exports deflator of goods and services is WEO calculated data (TX_D). | K36: Exports deflator of goods and services, 2005=100, Weighted by trade imports from all partner countries. Source of the exports deflator of goods and services is WEO calculated data (TX_D). | L36: Exports deflator of goods and services, 2005=100, Weighted by trade imports from all partner countries. Source of the exports deflator of goods and services is WEO calculated data (TX_D). | M36: Exports deflator of goods and services, 2005=100, Weighted by trade imports from all partner countries. Source of the exports deflator of goods and services is WEO calculated data (TX_D). | N36: Exports deflator of goods and services, 2005=100, Weighted by trade imports from all partner countries. Source of the exports deflator of goods and services is WEO calculated data (TX_D). | O36: Exports deflator of goods and services, 2005=100, Weighted by trade imports from all partner countries. Source of the exports deflator of goods and services is WEO calculated data (TX_D).
A37: Goods | B37: Exports deflator of goods, 2005=100, Weighted by trade imports from all partner countries. Source of the exports deflator of goods is WEO calculated data (TXG_D). | C37: Exports deflator of goods, 2005=100, Weighted by trade imports from all partner countries. Source of the exports deflator of goods is WEO calculated data (TXG_D). | D37: Exports deflator of goods, 2005=100, Weighted by trade imports from all partner countries. Source of the exports deflator of goods is WEO calculated data (TXG_D). | E37: Exports deflator of goods, 2005=100, Weighted by trade imports from all partner countries. Source of the exports deflator of goods is WEO calculated data (TXG_D). | F37: Exports deflator of goods, 2005=100, Weighted by trade imports from all partner countries. Source of the exports deflator of goods is WEO calculated data (TXG_D). | G37: Exports deflator of goods, 2005=100, Weighted by trade imports from all partner countries. Source of the exports deflator of goods is WEO calculated data (TXG_D). | H37: Exports deflator of goods, 2005=100, Weighted by trade imports from all partner countries. Source of the exports deflator of goods is WEO calculated data (TXG_D). | I37: Exports deflator of goods, 2005=100, Weighted by trade imports from all partner countries. Source of the exports deflator of goods is WEO calculated data (TXG_D). | J37: Exports deflator of goods, 2005=100, Weighted by trade imports from all partner countries. Source of the exports deflator of goods is WEO calculated data (TXG_D). | K37: Exports deflator of goods, 2005=100, Weighted by trade imports from all partner countries. Source of the exports deflator of goods is WEO calculated data (TXG_D). | L37: Exports deflator of goods, 2005=100, Weighted by trade imports from all partner countries. Source of the exports deflator of goods is WEO calculated data (TXG_D).
A38: Excluding oil | B38: Exports deflator of goods excl. oil, 2005=100, Weighted by trade imports from all partner countries. Source of the exports deflator of goods excluding oil is WEO calculated data (TXGXO_D). | C38: Exports deflator of goods excl. oil, 2005=100, Weighted by trade imports from all partner countries. Source of the exports deflator of goods excluding oil is WEO calculated data (TXGXO_D). | D38: Exports deflator of goods excl. oil, 2005=100, Weighted by trade imports from all partner countries. Source of the exports deflator of goods excluding oil is WEO calculated data (TXGXO_D). | E38: Exports deflator of goods excl. oil, 2005=100, Weighted by trade imports from all partner countries. Source of the exports deflator of goods excluding oil is WEO calculated data (TXGXO_D). | F38: Exports deflator of goods excl. oil, 2005=100, Weighted by trade imports from all partner countries. Source of the exports deflator of goods excluding oil is WEO calculated data (TXGXO_D). | G38: Exports deflator of goods excl. oil, 2005=100, Weighted by trade imports from all partner countries. Source of the exports deflator of goods excluding oil is WEO calculated data (TXGXO_D). | H38: Exports deflator of goods excl. oil, 2005=100, Weighted by trade imports from all partner countries. Source of the exports deflator of goods excluding oil is WEO calculated data (TXGXO_D). | I38: Exports deflator of goods excl. oil, 2005=100, Weighted by trade imports from all partner countries. Source of the exports deflator of goods excluding oil is WEO calculated data (TXGXO_D). | J38: Exports deflator of goods excl. oil, 2005=100, Weighted by trade imports from all partner countries. Source of the exports deflator of goods excluding oil is WEO calculated data (TXGXO_D). | K38: Exports deflator of goods excl. oil, 2005=100, Weighted by trade imports from all partner countries. Source of the exports deflator of goods excluding oil is WEO calculated data (TXGXO_D). | L38: Exports deflator of goods excl. oil, 2005=100, Weighted by trade imports from all partner countries. Source of the exports deflator of goods excluding oil is WEO calculated data (TXGXO_D). | M38: Exports deflator of goods excl. oil, 2005=100, Weighted by trade imports from all partner countries. Source of the exports deflator of goods excluding oil is WEO calculated data (TXGXO_D). | N38: Exports deflator of goods excl. oil, 2005=100, Weighted by trade imports from all partner countries. Source of the exports deflator of goods excluding oil is WEO calculated data (TXGXO_D). | O38: Exports deflator of goods excl. oil, 2005=100, Weighted by trade imports from all partner countries. Source of the exports deflator of goods excluding oil is WEO calculated data (TXGXO_D).
A40: Import deflators in U.S. dollars
A41: Goods and services | B41: Imports deflator of goods and services, 2005=100, Weighted by trade exports to all partner countries. Source of the imports deflator of goods and services is WEO calculated data (TM_D). | C41: Exports deflator of goods and services, 2005=100, Weighted by trade imports from all partner countries. Source of the exports deflator of goods and services is WEO calculated data (TX_D). | D41: Exports deflator of goods and services, 2005=100, Weighted by trade imports from all partner countries. Source of the exports deflator of goods and services is WEO calculated data (TX_D). | E41: Exports deflator of goods and services, 2005=100, Weighted by trade imports from all partner countries. Source of the exports deflator of goods and services is WEO calculated data (TX_D). | F41: Exports deflator of goods and services, 2005=100, Weighted by trade imports from all partner countries. Source of the exports deflator of goods and services is WEO calculated data (TX_D). | G41: Exports deflator of goods and services, 2005=100, Weighted by trade imports from all partner countries. Source of the exports deflator of goods and services is WEO calculated data (TX_D). | H41: Exports deflator of goods and services, 2005=100, Weighted by trade imports from all partner countries. Source of the exports deflator of goods and services is WEO calculated data (TX_D). | I41: Exports deflator of goods and services, 2005=100, Weighted by trade imports from all partner countries. Source of the exports deflator of goods and services is WEO calculated data (TX_D). | J41: Exports deflator of goods and services, 2005=100, Weighted by trade imports from all partner countries. Source of the exports deflator of goods and services is WEO calculated data (TX_D). | K41: Exports deflator of goods and services, 2005=100, Weighted by trade imports from all partner countries. Source of the exports deflator of goods and services is WEO calculated data (TX_D). | L41: Exports deflator of goods and services, 2005=100, Weighted by trade imports from all partner countries. Source of the exports deflator of goods and services is WEO calculated data (TX_D). | M41: Exports deflator of goods and services, 2005=100, Weighted by trade imports from all partner countries. Source of the exports deflator of goods and services is WEO calculated data (TX_D). | N41: Exports deflator of goods and services, 2005=100, Weighted by trade imports from all partner countries. Source of the exports deflator of goods and services is WEO calculated data (TX_D). | O41: Exports deflator of goods and services, 2005=100, Weighted by trade imports from all partner countries. Source of the exports deflator of goods and services is WEO calculated data (TX_D).
A42: Goods | B42: Imports deflator of goods, 2005=100, Weighted by trade exports to all partner countries. Source of the imports deflator of goods is WEO calculated data (TMG_D). | C42: Exports deflator of goods, 2005=100, Weighted by trade imports from all partner countries. Source of the exports deflator of goods is WEO calculated data (TXG_D). | D42: Exports deflator of goods, 2005=100, Weighted by trade imports from all partner countries. Source of the exports deflator of goods is WEO calculated data (TXG_D). | E42: Exports deflator of goods, 2005=100, Weighted by trade imports from all partner countries. Source of the exports deflator of goods is WEO calculated data (TXG_D). | F42: Exports deflator of goods, 2005=100, Weighted by trade imports from all partner countries. Source of the exports deflator of goods is WEO calculated data (TXG_D). | G42: Exports deflator of goods, 2005=100, Weighted by trade imports from all partner countries. Source of the exports deflator of goods is WEO calculated data (TXG_D). | H42: Exports deflator of goods, 2005=100, Weighted by trade imports from all partner countries. Source of the exports deflator of goods is WEO calculated data (TXG_D). | I42: Exports deflator of goods, 2005=100, Weighted by trade imports from all partner countries. Source of the exports deflator of goods is WEO calculated data (TXG_D). | J42: Exports deflator of goods, 2005=100, Weighted by trade imports from all partner countries. Source of the exports deflator of goods is WEO calculated data (TXG_D). | K42: Exports deflator of goods, 2005=100, Weighted by trade imports from all partner countries. Source of the exports deflator of goods is WEO calculated data (TXG_D). | L42: Exports deflator of goods, 2005=100, Weighted by trade imports from all partner countries. Source of the exports deflator of goods is WEO calculated data (TXG_D).
A44: Advanced economy partners
A46: Unit labor costs in manufacturing | B46: Unit labor costs in manufacturing, US$, 2005=100, Weighted by trade exports to advanced economies. For advanced economies, unit labor costs in manufacturing is desk submitted data (LULCM). | C46: Unit labor costs in manufacturing, US$, 2005=100, Weighted by trade exports to advanced economies. For advanced economies, unit labor costs in manufacturing is desk submitted data (LULCM). | D46: Unit labor costs in manufacturing, US$, 2005=100, Weighted by trade exports to advanced economies. For advanced economies, unit labor costs in manufacturing is desk submitted data (LULCM). | E46: Unit labor costs in manufacturing, US$, 2005=100, Weighted by trade exports to advanced economies. For advanced economies, unit labor costs in manufacturing is desk submitted data (LULCM). | F46: Unit labor costs in manufacturing, US$, 2005=100, Weighted by trade exports to advanced economies. For advanced economies, unit labor costs in manufacturing is desk submitted data (LULCM). | G46: Unit labor costs in manufacturing, US$, 2005=100, Weighted by trade exports to advanced economies. For advanced economies, unit labor costs in manufacturing is desk submitted data (LULCM). | H46: Unit labor costs in manufacturing, US$, 2005=100, Weighted by trade exports to advanced economies. For advanced economies, unit labor costs in manufacturing is desk submitted data (LULCM). | I46: Unit labor costs in manufacturing, US$, 2005=100, Weighted by trade exports to advanced economies. For advanced economies, unit labor costs in manufacturing is desk submitted data (LULCM). | J46: Unit labor costs in manufacturing, US$, 2005=100, Weighted by trade exports to advanced economies. For advanced economies, unit labor costs in manufacturing is desk submitted data (LULCM). | K46: Unit labor costs in manufacturing, US$, 2005=100, Weighted by trade exports to advanced economies. For advanced economies, unit labor costs in manufacturing is desk submitted data (LULCM). | L46: Unit labor costs in manufacturing, US$, 2005=100, Weighted by trade exports to advanced economies. For advanced economies, unit labor costs in manufacturing is desk submitted data (LULCM). | M46: Unit labor costs in manufacturing, US$, 2005=100, Weighted by trade exports to advanced economies. For advanced economies, unit labor costs in manufacturing is desk submitted data (LULCM). | N46: Unit labor costs in manufacturing, US$, 2005=100, Weighted by trade exports to advanced economies. For advanced economies, unit labor costs in manufacturing is desk submitted data (LULCM). | O46: Unit labor costs in manufacturing, US$, 2005=100, Weighted by trade exports to advanced economies. For advanced economies, unit labor costs in manufacturing is desk submitted data (LULCM).
A49: World Prices
A50: Export unit value for manufactures (MUV) | B50: Deflator of exports of manufactures for the advanced economies. Source of the exports of manufactures is WEO calculated data (TXGM_D).
A51: Petroleum spot price (APSP) | B51: Crude Oil (petroleum), simple average of three spot prices; Dated Brent, West Texas Intermediate, and the Dubai Fateh, US$ per barrel
A53: Average of nonfuel commodity market prices weighted by the 2011-13 composition of nonfuel commodity trade of reporting country
A55: Nonfuel commodity export price | B55: Nonfuel commodity exports price, 2005=100, Average of nonfuel commodity market prices weighted by the 2011-13 composition of nonfuel commodity export trade of country | C55: Nonfuel commodity exports price, 2005=100, Average of nonfuel commodity market prices weighted by the 2008-10 composition of nonfuel commodity export trade of country | D55: Nonfuel commodity exports price, 2005=100, Average of nonfuel commodity market prices weighted by the 2008-10 composition of nonfuel commodity export trade of country | E55: Nonfuel commodity exports price, 2005=100, Average of nonfuel commodity market prices weighted by the 2008-10 composition of nonfuel commodity export trade of country | F55: Nonfuel commodity exports price, 2005=100, Average of nonfuel commodity market prices weighted by the 2008-10 composition of nonfuel commodity export trade of country | G55: Nonfuel commodity exports price, 2005=100, Average of nonfuel commodity market prices weighted by the 2008-10 composition of nonfuel commodity export trade of country | H55: Nonfuel commodity exports price, 2005=100, Average of nonfuel commodity market prices weighted by the 2008-10 composition of nonfuel commodity export trade of country | I55: Nonfuel commodity exports price, 2005=100, Average of nonfuel commodity market prices weighted by the 2008-10 composition of nonfuel commodity export trade of country | J55: Nonfuel commodity exports price, 2005=100, Average of nonfuel commodity market prices weighted by the 2008-10 composition of nonfuel commodity export trade of country | K55: Nonfuel commodity exports price, 2005=100, Average of nonfuel commodity market prices weighted by the 2008-10 composition of nonfuel commodity export trade of country | L55: Nonfuel commodity exports price, 2005=100, Average of nonfuel commodity market prices weighted by the 2008-10 composition of nonfuel commodity export trade of country | M55: Nonfuel commodity exports price, 2005=100, Average of nonfuel commodity market prices weighted by the 2008-10 composition of nonfuel commodity export trade of country | N55: Nonfuel commodity exports price, 2005=100, Average of nonfuel commodity market prices weighted by the 2008-10 composition of nonfuel commodity export trade of country | O55: Nonfuel commodity exports price, 2005=100, Average of nonfuel commodity market prices weighted by the 2008-10 composition of nonfuel commodity export trade of country
A56: Nonfuel commodity import price | B56: Nonfuel commodity imports price, 2005=100, Average of nonfuel commodity market prices weighted by the 2011-13 composition of nonfuel commodity import trade of country | C56: Nonfuel commodity imports price, 2005=100, Average of nonfuel commodity market prices weighted by the 2008-10 composition of nonfuel commodity import trade of country | D56: Nonfuel commodity imports price, 2005=100, Average of nonfuel commodity market prices weighted by the 2008-10 composition of nonfuel commodity import trade of country | E56: Nonfuel commodity imports price, 2005=100, Average of nonfuel commodity market prices weighted by the 2008-10 composition of nonfuel commodity import trade of country | F56: Nonfuel commodity imports price, 2005=100, Average of nonfuel commodity market prices weighted by the 2008-10 composition of nonfuel commodity import trade of country | G56: Nonfuel commodity imports price, 2005=100, Average of nonfuel commodity market prices weighted by the 2008-10 composition of nonfuel commodity import trade of country | H56: Nonfuel commodity imports price, 2005=100, Average of nonfuel commodity market prices weighted by the 2008-10 composition of nonfuel commodity import trade of country | I56: Nonfuel commodity imports price, 2005=100, Average of nonfuel commodity market prices weighted by the 2008-10 composition of nonfuel commodity import trade of country | J56: Nonfuel commodity imports price, 2005=100, Average of nonfuel commodity market prices weighted by the 2008-10 composition of nonfuel commodity import trade of country | K56: Nonfuel commodity imports price, 2005=100, Average of nonfuel commodity market prices weighted by the 2008-10 composition of nonfuel commodity import trade of country | L56: Nonfuel commodity imports price, 2005=100, Average of nonfuel commodity market prices weighted by the 2008-10 composition of nonfuel commodity import trade of country | M56: Nonfuel commodity imports price, 2005=100, Average of nonfuel commodity market prices weighted by the 2008-10 composition of nonfuel commodity import trade of country | N56: Nonfuel commodity imports price, 2005=100, Average of nonfuel commodity market prices weighted by the 2008-10 composition of nonfuel commodity import trade of country | O56: Nonfuel commodity imports price, 2005=100, Average of nonfuel commodity market prices weighted by the 2008-10 composition of nonfuel commodity import trade of country
A59: Component-Based Goods Trade Deflators
A60: Export deflator | B60: Component-based goods trade exports deflator, 2005=100 | C60: Please refer to introduction sheet for more information.
A61: Import deflator | B61: Component-based goods trade imports deflator, 2005=100 | C61: Please refer to introduction sheet for more information.

Sheet Introduction
A3: GEE data are group composites, based on weighted averages of selected WEO variables from the country databases. The latest GEE data are available for access from EcOS/EcXL and DMX.
A5: The GEE tables present three types of information:
A7: 1. A comparison of the current GEE data with that of the previous WEO.
A9: 2. Historical annual and quarterly GEE data and projections.
A11: 3. The weights used to calculate the GEE table group composites.
A13: For each country weighted averages of output, demand, prices, and costs are calculated by combining data for each of its trading partners with corresponding fixed-year weights that are proportional to the country's geographical distribution of exports (or origin of imports, as the case may be). The relative importance of trading partners currently reflects the average trade in 2011-13, the latest three years for which the IMF's Direction of Trade Statistics (DOTS) provides the highest coverage of trade statistics. The trade weights are generally updated every other year. It should be noted that the weights reflect trade in goods only; complete information on bilateral trade in services is not generally available.
A15: Given a reasonably stable geographic pattern of a country's foreign trade, composites of foreign demand and inflation calculated in this fashion tend to be more meaningful for purposes of analyzing effects on the country from economic developments outside its borders than the conventional WEO group composites based on GDP or total trade weights. An extreme example may clarify the point: in Canada with its foreign trade so concentrated on the United States, a major recession in Germany would tend to have a small impact relative to that on a country such as Austria whose export share to Germany is substantial.
A17: Foreign output and demand measured by GDP or imports may be particularly useful information to guide desks in their projections of exports. Similarly, the composites of partner country export prices may serve to guide the projections of a country's import prices. In general, consistent use of the GEE information will diminish any tendency for the WEO projections to generate inconsistencies at the global level.
A19: Data on non-fuel commodity prices, maintained by the Research Department’s, Commodities Unit, are used in the GEE tables to provide, for each country, an average of non-fuel commodity prices, weighted by its export as well as import composition of average 2011-13 non-fuel commodity trade. The GEE tables also include a set of "component-based" trade deflators. These pre-calculated average foreign trade prices are based on countries' 2011-13 composition of trade in manufactures, oil, and non-fuel commodities using world price indicators (also shown in the GEE tables). The indicators, which at most can be counted upon to approximate recorded trade prices or unit values, may nevertheless be of value for countries lacking reliable statistics on trade unit values, or for desks in their formulation of projections.
A21: Weighting Procedures
A23: 1). The trade weights are derived from the IMF’s Direction of Trade (DOT) database. Every country has four sets of trade weights, i.e., the imports and exports weights for all countries as partners, and the imports and exports weights for only the advanced economies. The weights are calculated from the GEE reporting country’s trade with partner which comprise 100% of the reporter’s total exports or imports. The GEE calculates a reporting country's series not from the reporting country's data but from the aggregated sum of the weighted percentage changes of its partners' data for a given WEO series. The following example demonstrates the process for the exports trade-weighted GEE data series.
A25: The calculation of GEE partner series Real Imports of Goods and Services, for the reporter i is approximately equal to the following:
... A87: The table below illustrates the series names of the variables in the GEE Live.
A88: EcOS: Current GEE Codes | B88: Previous Aremos Codes
A89: Series Description (Series Names)
A90: Foreign Output and Demand
A91: Advanced Economy Countries
A92: Export-weighted averages
A93: Real GDP (NGDP_R_WX) | B93: IcccNGDP_R
A94: Real total domestic demand (NTDD_R_WX) | B94: IcccNGDP_R
A95: All Countries
A96: Real GDP (NGDP_R_WX) | B96: IcccNGDP_R
A97: Real Imports
A98: Goods and Services (TM_R_WX) | B98: XcccTM_R
A99: Goods (TMG_R_WX) | B99: XcccTMG_R
A100: Excluding Oil (TMGXO_R_WX) | B100: XcccTMGXO_R
A101: Import-weighted averages
A102: Foreign Prices and Costs
A103: Advanced Economy Countries
A104: In national currency (NGDP_D_WM) | B104: McccNGDP_D
A105: In U.S. dollars (NGDP_D_USD_WM) | B105: McccNGDP_DUS
A106: Consumer Prices
A107: In national currency (PCPI_WM) | B107: McccPCPI
A108: In U.S. dollars (PCPI_USD_WM) | B108: McccPCPIUS
A109: Import-weighted averages
A110: All Countries
A111: Export deflators in U.S. dollars
A112: Goods and Services (TX_D_WM) | B112: McccTX_D
A113: Goods (TXG_D_WM) | B113: McccTXG_D
A114: Excluding Oil (TXGXO_D_WM) | B114: McccTXGXO_D
A115: Export-weighted averages
A116: Advanced Economy Countries
A117: Unit labor costs in manufacturing (LULCM_USD_WX) | B117: XcccLULCMUS
A119: World Prices
A120: Export unit value for manufactures - MUV (110TXGM_D001) | B120: W110TXGM_D
A121: Petroleum spot price (APSP) (001PZPIOIL) | B121: W001POILAPSP
A122: Export-weighted averages
A123: Non-fuel commodity export price1 (PXPNF_WX) | B123: XcccPNFUELW
A124: Import-weighted averages
A125: Non-fuel commodity import price1 (PMPNF_WM) | B125: McccPNFUELW
A127: Average of non-fuel commodity market prices weighted by the 2011-13 composition of non-fuel commodity trade of reporting country.
A129: Component-Based Goods Trade Deflators
A130: Export deflator (TXGCB_D) | B130: WcccTXG_DER
A131: Import deflator (TMGCB_D) | B131: WcccTMG_DER

Sheet EcOS indicators names
B3: GEE Code Map
B5: The GEE database is available in EcOS and DMX. Below is the reference guide to the GEE series codes. The GEE data codes complied with the Catalogue of Economic Time Series (CTS) standards. The "ccc" refers to the 3-digits IMF country code. Should you need assistance, please write to IMFEcOSSupport.
B7: Indicator | C7: Descriptor
B8: cccNGDP_R_WX110 | C8: Partner countries' real GDP, 2005=100, local currency, Weighted by trade exports to advanced economy
B9: cccNTDD_R_WX110 | C9: Partner countries' real total domestic demand, 2005=100, Weighted by trade exports to advanced economy
B10: cccNGDP_R_WX001 | C10: Partner countries' real GDP, 2005=100, local currency, Weighted by trade exports to all economies
B11: cccTM_R_WX001 | C11: Partner countries' imports volume of goods and services, 2005=100, Weighted by trade exports to all partner countries
B12: cccTMG_R_WX001 | C12: Partner countries' imports volume of goods, 2005=100, Weighted by trade exports to all partner countries
B13: cccTMGXO_R_WX001 | C13: Partner countries' imports volume of goods excl. oil, 2005=100, Weighted by trade exports to all partner countries
B14: cccTX_R_WM001 | C14: Partner countries' exports volume of goods and services, 2005=100, Weighted by trade imports from all partner countries
B15: cccTXG_R_WM001 | C15: Partner countries' exports volume of goods, 2005=100, Weighted by trade imports from all partner countries
B16: cccTXGXO_R_WM001 | C16: Partner countries' exports volume of goods excl. oil, 2005=100, Weighted by trade imports from all partner countries
B17: cccNGDP_D_WM110 | C17: Partner countries' GDP deflator, 2005=100, local currency, Weighted by trade imports from advanced economy
B18: cccNGDP_D_USD_WM110 | C18: Partner countries' GDP deflator, US$, 2005=100, Weighted by trade imports from advanced economy
... B31: cccTMGCB_D001 | C31: Component-based goods trade imports deflator, 2005=100

Sheet CompareDataSheet
D2: CURRENT | E2: 714 | F2: Rwanda
C4: Frequency | F4: 2012 | G4: 2013 | H4: 2014 | I4: 2015 | J4: 2016 | K4: 2017 | L4: 2018 | M4: 2019 | N4: 2020
A5: \\RES\GEE\GEE Live | B5: 714LULCM_USD_PCH_WX110.A | C5: Annual | D5: Advanced Economies | E5: LULCM_USD_PCH_WX | F5: -0.98557483 | G5: 1.8669117 | H5: 0.4655008 | I5: -7.6909845 | J5: 1.2531023 | K5: 2.1415024 | L5: 2.1017425 | M5: 1.8077852 | N5: 2.3428212
A6: \\RES\GEE\GEE Live | B6: 714NGDP_D_PCH_WM110.A | C6: Annual | E6: NGDP_D_PCH_WM | F6: 1.4498999 | G6: 1.347444 | H6: 1.1453251 | I6: 0.84705263 | J6: 1.3372 | K6: 1.4862499 | L6: 1.6658317 | M6: 1.7652251 | N6: 1.8079974
A7: \\RES\GEE\GEE Live | B7: 714NGDP_D_USD_PCH_WM110.A | C7: Annual | E7: NGDP_D_USD_PCH_WM | F7: -3.3156393 | G7: 2.3647717 | H7: 0.30301287 | I7: -11.4502 | J7: 1.416271 | K7: 2.3579 | L7: 2.399867 | M7: 2.3106745 | N7: 2.8904062
A8: \\RES\GEE\GEE Live | B8: 714NGDP_R_PCH_WX110.A | C8: Annual | E8: NGDP_R_PCH_WX | F8: 1.0636319 | G8: 1.2502207 | H8: 1.7440203 | I8: 1.9273075 | J8: 2.2413203 | K8: 2.1130838 | L8: 2.0325399 | M8: 1.9911378 | N8: 1.8914638
A9: \\RES\GEE\GEE Live | B9: 714NTDD_R_PCH_WX110.A | C9: Annual | E9: NTDD_R_PCH_WX | F9: 0.96590349 | G9: 1.0616452 | H9: 1.7366034 | I9: 2.2004724 | J9: 2.4334339 | K9: 2.2512916 | L9: 2.1665499 | M9: 2.1319712 | N9: 2.0313772
A10: \\RES\GEE\GEE Live | B10: 714PCPI_PCH_WM110.A | C10: Annual | E10: PCPI_PCH_WM | F10: 2.2015136 | G10: 1.4634036 | H10: 0.99119606 | I10: 0.33850563 | J10: 1.3347293 | K10: 1.6583138 | L10: 1.8172027 | M10: 1.9261979 | N10: 1.9674989
A11: \\RES\GEE\GEE Live | B11: 714PCPI_USD_PCH_WM110.A | C11: Annual | E11: PCPI_USD_PCH_WM | F11: -2.6055764 | G11: 2.4706153 | H11: 0.14682949 | I11: -11.90457 | J11: 1.4131868 | K11: 2.5323886 | L11: 2.5527735 | M11: 2.4730852 | N11: 3.0519011
A12: \\RES\GEE\GEE Live | B12: 714TM_D_PCH_WX110.A | C12: Annual | E12: TM_D_PCH_WX | F12: -1.567555 | G12: 0.8926962 | H12: -0.43134805 | I12: -11.134424 | J12: 0.19584133 | K12: 0.88130457 | L12: 0.80574123 | M12: 0.63271143 | N12: 1.1166566
A13: \\RES\GEE\GEE Live | B13: 714TM_R_PCH_WX110.A | C13: Annual | E13: TM_R_PCH_WX | F13: 1.0331273 | G13: 1.6732216 | H13: 2.9944281 | I13: 4.6657828 | J13: 4.7976499 | K13: 4.7667951 | L13: 4.8228975 | M13: 4.9708661 | N13: 5.0037765
A14: \\RES\GEE\GEE Live | B14: 714TMG_D_PCH_WX110.A | C14: Annual | E14: TMG_D_PCH_WX | F14: -1.8307519 | G14: 0.60537729 | H14: -1.2348248 | I14: -11.325628 | J14: 0.26641762 | K14: 0.86833557 | L14: 0.7997437 | M14: 0.60042266 | N14: 1.0374401
A15: \\RES\GEE\GEE Live | B15: 714TMG_R_PCH_WX110.A | C15: Annual | E15: TMG_R_PCH_WX | F15: 0.57273842 | G15: 1.3281048 | H15: 3.0937209 | I15: 4.5286887 | J15: 4.8992044 | K15: 4.9343136 | L15: 4.9866684 | M15: 5.1315873 | N15: 5.1795196
A16: \\RES\GEE\GEE Live | B16: 714TMGXO_D_PCH_WX110.A | C16: Annual | E16: TMGXO_D_PCH_WX | F16: -2.581096 | G16: 1.1289043 | H16: -0.19988255 | I16: -6.8269783 | J16: -0.37898525 | K16: 0.29950054 | L16: 0.30637417 | M16: 0.39402208 | N16: 1.0817565
A17: \\RES\GEE\GEE Live | B17: 714TMGXO_R_PCH_WX110.A | C17: Annual | E17: TMGXO_R_PCH_WX | F17: 1.2840104 | G17: 1.794893 | H17: 3.8867431 | I17: 3.5760386 | J17: 5.7547101 | K17: 5.4403154 | L17: 5.5076978 | M17: 5.4778191 | N17: 5.3679664
... A23: \\RES\GEE\GEE Live | B23: 714TXGXO_R_PCH_WM001.A | C23: Annual | E23: TXGXO_R_PCH_WM | F23: 1.3613039 | G23: 1.6433003 | H23: 3.0224367 | I23: 1.8825945 | J23: 4.0750275 | K23: 4.0934567 | L23: 4.183384 | M23: 4.3366668 | N23: 4.1769681
A24: \\RES\GEE\GEE Live | B24: 714LULCM_USD_PCH_WX001.A | C24: Annual | D24: World | E24: LULCM_USD_PCH_WX | F24: -1.0809918 | G24: 1.730205 | H24: 0.26881521 | I24: -7.9293131 | J24: 1.2649076 | K24: 2.2018988 | L24: 2.1594757 | M24: 1.8827494 | N24: 2.3955062
A25: \\RES\GEE\GEE Live | B25: 714NGDP_D_PCH_WM001.A | C25: Annual | E25: NGDP_D_PCH_WM | F25: 5.9841285 | G25: 3.225412 | H25: 3.1584376 | I25: 1.8628597 | J25: 3.76009 | K25: 3.5574661 | L25: 3.5459378 | M25: 3.4674574 | N25: 3.5259031
A26: \\RES\GEE\GEE Live | B26: 714NGDP_D_USD_PCH_WM001.A | C26: Annual | E26: NGDP_D_USD_PCH_WM | F26: 4.0674484 | G26: 1.3242872 | H26: 1.3522731 | I26: -7.5659238 | J26: 1.628054 | K26: 2.5095923 | L26: 2.4593594 | M26: 2.4990624 | N26: 2.9924632
A27: \\RES\GEE\GEE Live | B27: 714NGDP_R_PCH_WX001.A | C27: Annual | E27: NGDP_R_PCH_WX | F27: 4.7504048 | G27: 5.0131781 | H27: 5.3151313 | I27: 4.9559147 | J27: 4.8256485 | K27: 4.8536002 | L27: 4.7998265 | M27: 4.6614286 | N27: 4.4379531
A28: \\RES\GEE\GEE Live | B28: 714NTDD_R_PCH_WX001.A | C28: Annual | E28: NTDD_R_PCH_WX | F28: 5.3832785 | G28: 5.478228 | H28: 5.180167 | I28: 5.4324569 | J28: 4.8130244 | K28: 4.9285493 | L28: 4.9476908 | M28: 4.7481555 | N28: 4.5958427
A29: \\RES\GEE\GEE Live | B29: 714PCPI_PCH_WM001.A | C29: Annual | E29: PCPI_PCH_WM | F29: 6.7191248 | G29: 3.9884893 | H29: 3.7839932 | I29: 3.7022051 | J29: 3.8546731 | K29: 3.7101176 | L29: 3.6858241 | M29: 3.7256815 | N29: 3.7623841
A30: \\RES\GEE\GEE Live | B30: 714PCPI_USD_PCH_WM001.A | C30: Annual | E30: PCPI_USD_PCH_WM | F30: 4.7690615 | G30: 2.0567482 | H30: 2.0422141 | I30: -5.7408408 | J30: 1.7166454 | K30: 2.6619207 | L30: 2.5982742 | M30: 2.7561882 | N30: 3.2293345
A31: \\RES\GEE\GEE Live | B31: 714TM_D_PCH_WX001.A | C31: Annual | E31: TM_D_PCH_WX | F31: 0.4703814 | G31: -1.6097154 | H31: -2.0318041 | I31: -9.836507 | J31: 0.45408175 | K31: 1.7665519 | L31: 1.5788321 | M31: 1.2907938 | N31: 1.2328554
A32: \\RES\GEE\GEE Live | B32: 714TM_R_PCH_WX001.A | C32: Annual | E32: TM_R_PCH_WX | F32: 1.3648583 | G32: 5.3828373 | H32: 7.873037 | I32: 7.6238726 | J32: 4.9180281 | K32: 5.6670291 | L32: 5.6430817 | M32: 5.3655171 | N32: 5.3811063
A33: \\RES\GEE\GEE Live | B33: 714TMG_D_PCH_WX001.A | C33: Annual | E33: TMG_D_PCH_WX | F33: -0.016092963 | G33: -2.7948406 | H33: -2.1923363 | I33: -9.4620105 | J33: -0.11153088 | K33: 1.5185747 | L33: 1.3164747 | M33: 0.79634718 | N33: 0.55092311
A34: \\RES\GEE\GEE Live | B34: 714TMG_R_PCH_WX001.A | C34: Annual | E34: TMG_R_PCH_WX | F34: 1.5195069 | G34: 6.9148759 | H34: 6.7764161 | I34: 5.2105954 | J34: 4.8024203 | K34: 5.8732438 | L34: 5.8448798 | M34: 5.5792609 | N34: 5.6168606
A35: \\RES\GEE\GEE Live | B35: 714TMGXO_D_PCH_WX001.A | C35: Annual | E35: TMGXO_D_PCH_WX | F35: -0.39309747 | G35: -2.9648723 | H35: -1.5747081 | I35: -4.5562934 | J35: -0.39246589 | K35: 0.96712038 | L35: 0.87779512 | M35: 0.58388016 | N35: 0.44635836
A36: \\RES\GEE\GEE Live | B36: 714TMGXO_R_PCH_WX001.A | C36: Annual | E36: TMGXO_R_PCH_WX | F36: 1.510718 | G36: 6.9179515 | H36: 6.7268005 | I36: 4.3187755 | J36: 5.4361159 | K36: 6.2082582 | L36: 6.1839007 | M36: 5.8586954 | N36: 5.7897186
... A42: \\RES\GEE\GEE Live | B42: 714TXGXO_R_PCH_WM001.A | C42: Annual | E42: TXGXO_R_PCH_WM | F42: 6.8177888 | G42: 3.0952202 | H42: 4.571133 | I42: 5.9636983 | J42: 5.7877376 | K42: 7.5701631 | L42: 7.451315 | M42: 6.7527534 | N42: 6.5364295
F49: 2013Q1 | G49: 2013Q2 | H49: 2013Q3 | I49: 2013Q4 | J49: 2014Q1 | K49: 2014Q2 | L49: 2014Q3 | M49: 2014Q4 | N49: 2015Q1 | O49: 2015Q2 | P49: 2015Q3 | Q49: 2015Q4 | R49: 2016Q1 | S49: 2016Q2 | T49: 2016Q3 | U49: 2016Q4
A50: \\RES\GEE\GEE Live | B50: 714LULCM_USD_YOY_WX110.Q | C50: Quarterly | D50: Advanced Economies | E50: LULCM_USD_YOY_WX | F50: 1.98268 | G50: 1.0624199 | H50: 2.7469386 | I50: 1.8057311 | J50: 2.0705116 | K50: 3.2629395 | L50: 0.61213786 | M50: -3.8026466 | N50: -8.9394338 | O50: -9.6866813 | P50: -7.9113741 | Q50: -4.6496212 | R50: 0.22863394 | S50: 1.4177109 | T50: 1.7570951 | U50: 1.7663829
A51: \\RES\GEE\GEE Live | B51: 714NGDP_D_USD_YOY_WM110.Q | C51: Quarterly | E51: NGDP_D_USD_YOY_WM | F51: 1.2797407 | G51: 1.919192 | H51: 3.4832424 | I51: 2.6699822 | J51: 2.4111122 | K51: 3.8219396 | L51: 0.93807429 | M51: -5.7406275 | N51: -12.669571 | O51: -13.818823 | P51: -12.194317 | Q51: -7.2652929 | R51: 0.32596515 | S51: 1.3694483 | T51: 2.085394 | U51: 2.0434211
A52: \\RES\GEE\GEE Live | B52: 714NGDP_D_YOY_WM110.Q | C52: Quarterly | E52: NGDP_D_YOY_WM | F52: 1.233062 | G52: 1.5444258 | H52: 1.5075411 | I52: 1.1564323 | J52: 1.2828651 | K52: 1.0505531 | L52: 1.2164409 | M52: 1.0542719 | N52: 0.78017749 | O52: 0.87640368 | P52: 0.80188213 | Q52: 1.0693776 | R52: 1.5485508 | S52: 1.2758153 | T52: 1.3196164 | U52: 1.3407119
A53: \\RES\GEE\GEE Live | B53: 714NGDP_R_YOY_WX110.Q | C53: Quarterly | E53: NGDP_R_YOY_WX | F53: 0.67951245 | G53: 1.0555216 | H53: 1.3712422 | I53: 1.8884713 | J53: 1.7618572 | K53: 1.7459692 | L53: 1.778603 | M53: 1.6924943 | N53: 1.8071794 | O53: 1.9658726 | P53: 1.8833508 | Q53: 2.0577019 | R53: 2.3734945 | S53: 2.3099346 | T53: 2.2547407 | U53: 2.0529329
A54: \\RES\GEE\GEE Live | B54: 714NTDD_R_YOY_WX110.Q | C54: Quarterly | E54: NTDD_R_YOY_WX | F54: 0.33855031 | G54: 0.99371196 | H54: 1.2560391 | I54: 1.5940641 | J54: 1.6517689 | K54: 1.4522614 | L54: 1.8932204 | M54: 1.9714302 | N54: 2.085097 | O54: 2.1676368 | P54: 2.0275443 | Q54: 2.6222957 | R54: 2.8933624 | S54: 3.010023 | T54: 2.8437309 | U54: 1.1413058
A55: \\RES\GEE\GEE Live | B55: 714PCPI_USD_YOY_WM110.Q | C55: Quarterly | E55: PCPI_USD_YOY_WM | F55: 1.7297069 | G55: 1.8306029 | H55: 3.532681 | I55: 2.6643109 | J55: 2.1641333 | K55: 4.0037 | L55: 0.72430923 | M55: -6.0723301 | N55: -13.265905 | O55: -14.466409 | P55: -12.607928 | Q55: -7.5105165 | R55: 0.26132365 | S55: 1.3339846 | T55: 2.0606913 | U55: 2.014826
A56: \\RES\GEE\GEE Live | B56: 714PCPI_YOY_WM110.Q | C56: Quarterly | E56: PCPI_YOY_WM | F56: 1.6874764 | G56: 1.4602781 | H56: 1.5588888 | I56: 1.1521538 | J56: 1.0378742 | K56: 1.2248522 | L56: 0.99838243 | M56: 0.69811768 | N56: 0.090559076 | O56: 0.11979415 | P56: 0.33063257 | Q56: 0.80331443 | R56: 1.4857651 | S56: 1.2413885 | T56: 1.2952122 | U56: 1.3119918
A57: \\RES\GEE\GEE Live | B57: 714TM_D_YOY_WX110.Q | C57: Quarterly | E57: TM_D_YOY_WX | F57: 1.3706631 | G57: 1.0411524 | H57: 0.7127128 | I57: 0.38534083 | J57: 3.9122523 | K57: 0.96886751 | L57: -1.891144 | M57: -4.6701437 | N57: -15.089957 | O57: -12.477965 | P57: -9.785624 | Q57: -7.0104612 | R57: -0.06934235 | S57: 0.1018172 | T57: 0.2732699 | U57: 0.44501627
A58: \\RES\GEE\GEE Live | B58: 714TM_R_YOY_WX110.Q | C58: Quarterly | E58: TM_R_YOY_WX | F58: 1.1727104 | G58: 1.5008148 | H58: 1.8299832 | I58: 2.1602191 | J58: 2.3605904 | K58: 2.7732934 | L58: 3.1876604 | M58: 3.603698 | N58: 4.6034665 | O58: 4.6378166 | P58: 4.6721781 | Q58: 4.7065508 | R58: 4.8025619 | S58: 4.7957572 | T58: 4.7889529 | U58: 4.7821491
A59: \\RES\GEE\GEE Live | B59: 714TMG_D_YOY_WX110.Q | C59: Quarterly | E59: TMG_D_YOY_WX | F59: 1.2877915 | G59: 0.82497365 | H59: 0.36427053 | I59: -0.094327489 | J59: 2.8290685 | K59: 0.067278468 | L59: -2.6203352 | M59: -5.2357647 | N59: -15.356177 | O59: -12.691125 | P59: -9.9421619 | Q59: -7.1066464 | R59: 0.033639846 | S59: 0.18398756 | T59: 0.33456125 | U59: 0.48536124
A60: \\RES\GEE\GEE Live | B60: 714TMG_R_YOY_WX110.Q | C60: Quarterly | E60: TMG_R_YOY_WX | F60: 0.66158447 | G60: 1.0995582 | H60: 1.5394376 | I60: 1.9812309 | J60: 2.5634864 | K60: 2.9128612 | L60: 3.263426 | M60: 3.615185 | N60: 4.3567177 | O60: 4.4551129 | P60: 4.5536009 | Q60: 4.6521817 | R60: 4.8765493 | S60: 4.8865965 | T60: 4.8966446 | U60: 4.9066937
A61: \\RES\GEE\GEE Live | B61: 714TMGXO_D_YOY_WX110.Q | C61: Quarterly | E61: TMGXO_D_YOY_WX | F61: 1.6124228 | G61: 1.2817625 | H61: 0.95217815 | I61: 0.62366632 | J61: 2.429803 | K61: 0.66115663 | L61: -1.0769507 | M61: -2.7850463 | N61: -9.1910322 | O61: -7.6376281 | P61: -6.057651 | Q61: -4.4506464 | R61: -0.64269268 | S61: -0.47305113 | T61: -0.30311993 | U61: -0.1328986
A62: \\RES\GEE\GEE Live | B62: 714TMGXO_R_YOY_WX110.Q | C62: Quarterly | E62: TMGXO_R_YOY_WX | F62: 1.0036806 | G62: 1.5206198 | H62: 2.0402047 | I62: 2.5624489 | J62: 4.0438643 | K62: 3.9401041 | L62: 3.8364474 | M62: 3.732894 | N62: 2.6434194 | O62: 3.2054211 | P62: 3.7705 | Q62: 4.3386728 | R62: 5.8597274 | S62: 5.7833603 | T62: 5.7070483 | U62: 5.6307914
... A69: \\RES\GEE\GEE Live | B69: 714TXGXO_R_YOY_WM001.Q | C69: Quarterly | E69: TXGXO_R_YOY_WM | F69: 1.1182802 | G69: 1.4616311 | H69: 1.8061479 | I69: 2.1518346 | J69: 3.4505583 | K69: 3.1606737 | L69: 2.8716015 | M69: 2.5833393 | N69: 1.0405198 | O69: 1.5863505 | P69: 2.1351299 | Q69: 2.6868738 | R69: 4.0654058 | S69: 4.0700958 | T69: 4.0747861 | U69: 4.0794765
A70: \\RES\GEE\GEE Live | B70: 714LULCM_USD_YOY_WX001.Q | C70: Quarterly | D70: World | E70: LULCM_USD_YOY_WX | F70: 1.8857771 | G70: 0.97254672 | H70: 2.5590361 | I70: 1.6261109 | J70: 1.9656619 | K70: 3.0085114 | L70: 0.36581543 | M70: -3.9666715 | N70: -9.3533173 | O70: -9.9246825 | P70: -8.0765746 | Q70: -4.7974773 | R70: 0.25078672 | S70: 1.4132401 | T70: 1.7597526 | U70: 1.7891573
A71: \\RES\GEE\GEE Live | B71: 714NGDP_D_USD_YOY_WM001.Q | C71: Quarterly | E71: NGDP_D_USD_YOY_WM | F71: 0.68851175 | G71: 1.1602198 | H71: 1.88918 | I71: 1.6618097 | J71: 4.4218801 | K71: 3.3643296 | L71: 0.7846197 | M71: -2.7396415 | N71: -9.9396243 | O71: -8.9764744 | P71: -7.24425 | Q71: -4.336489 | R71: 1.0813104 | S71: 1.5519611 | T71: 1.8722513 | U71: 2.0082454
A72: \\RES\GEE\GEE Live | B72: 714NGDP_D_YOY_WM001.Q | C72: Quarterly | E72: NGDP_D_YOY_WM | F72: 3.0979628 | G72: 3.3099783 | H72: 3.3920285 | I72: 3.1264296 | J72: 3.9009062 | K72: 3.4613416 | L72: 2.8897099 | M72: 2.4002448 | N72: 1.0611589 | O72: 1.6336369 | P72: 2.0102171 | Q72: 2.6236701 | R72: 3.911159 | S72: 3.7727524 | T72: 3.6791441 | U72: 3.6228031
A73: \\RES\GEE\GEE Live | B73: 714NGDP_R_YOY_WX001.Q | C73: Quarterly | E73: NGDP_R_YOY_WX | F73: 4.8018063 | G73: 4.9091065 | H73: 5.1200319 | I73: 5.1413357 | J73: 5.379256 | K73: 5.3950532 | L73: 5.2314962 | M73: 5.1802917 | N73: 5.2040769 | O73: 5.0174468 | P73: 4.8416447 | Q73: 4.7020947 | R73: 4.5907624 | S73: 4.7468538 | T73: 4.8782673 | U73: 5.008143
A74: \\RES\GEE\GEE Live | B74: 714NTDD_R_YOY_WX001.Q | C74: Quarterly | E74: NTDD_R_YOY_WX | F74: 5.2797021 | G74: 5.9059704 | H74: 5.4650215 | I74: 5.3948221 | J74: 5.4152858 | K74: 4.596341 | L74: 5.0067495 | M74: 5.7540698 | N74: 6.0937206 | O74: 5.8169084 | P74: 5.3189497 | Q74: 4.6529305 | R74: 4.2275602 | S74: 4.6183738 | T74: 5.071659 | U74: 5.4239364
A75: \\RES\GEE\GEE Live | B75: 714PCPI_USD_YOY_WM001.Q | C75: Quarterly | E75: PCPI_USD_YOY_WM | F75: 1.4653746 | G75: 1.7507137 | H75: 2.5725356 | I75: 2.3776332 | J75: 4.3973193 | K75: 3.8395736 | L75: 1.6187841 | M75: -1.4733417 | N75: -7.6397144 | O75: -7.1241366 | P75: -5.6507963 | Q75: -3.1680372 | R75: 1.2203933 | S75: 1.5762211 | T75: 1.9708572 | U75: 2.0938791
A76: \\RES\GEE\GEE Live | B76: 714PCPI_YOY_WM001.Q | C76: Quarterly | E76: PCPI_YOY_WM | F76: 3.9156125 | G76: 3.9324589 | H76: 4.1084593 | I76: 3.8779081 | J76: 3.8351322 | K76: 3.8886248 | L76: 3.6837249 | M76: 3.6609815 | N76: 3.5569268 | O76: 3.6245658 | P76: 3.6951997 | Q76: 3.8254752 | R76: 4.0568676 | S76: 3.7994971 | T76: 3.7814878 | U76: 3.7114286
A77: \\RES\GEE\GEE Live | B77: 714TM_D_YOY_WX001.Q | C77: Quarterly | E77: TM_D_YOY_WX | F77: -1.4833623 | G77: -1.5814066 | H77: -1.6793534 | I77: -1.7772027 | J77: 1.0444245 | K77: -1.0406504 | L77: -3.0826994 | M77: -5.0826102 | N77: -13.401129 | O77: -11.023969 | P77: -8.5815554 | Q77: -6.0720971 | R77: -0.056424767 | S77: 0.27234809 | T77: 0.60220248 | U77: 0.93314196
A78: \\RES\GEE\GEE Live | B78: 714TM_R_YOY_WX001.Q | C78: Quarterly | E78: TM_R_YOY_WX | F78: 4.4983448 | G78: 5.0578784 | H78: 5.6204081 | I78: 6.1859498 | J78: 7.6988439 | K78: 7.6873994 | L78: 7.6759562 | M78: 7.6645141 | N78: 8.5999685 | O78: 7.9243007 | P78: 7.2528365 | Q78: 6.58555 | R78: 4.6207966 | S78: 4.8051951 | T78: 4.9899186 | U78: 5.1749676
A79: \\RES\GEE\GEE Live | B79: 714TMG_D_YOY_WX001.Q | C79: Quarterly | E79: TMG_D_YOY_WX | F79: -3.0777061 | G79: -2.9128047 | H79: -2.7476226 | I79: -2.5821596 | J79: 0.72569632 | K79: -1.2374127 | L79: -3.1622615 | M79: -5.0495956 | N79: -12.817605 | O79: -10.619639 | P79: -8.3662603 | Q79: -6.0560709 | R79: -0.74146104 | S79: -0.33292478 | T79: 0.077292965 | U79: 0.48919912
A80: \\RES\GEE\GEE Live | B80: 714TMG_R_YOY_WX001.Q | C80: Quarterly | E80: TMG_R_YOY_WX | F80: 6.944392 | G80: 6.8792635 | H80: 6.8141746 | I80: 6.7491254 | J80: 7.1723654 | K80: 6.8163116 | L80: 6.4614407 | M80: 6.1077489 | N80: 5.3229027 | O80: 5.2286875 | P80: 5.1345565 | Q80: 5.0405098 | R80: 4.3927646 | S80: 4.6536014 | T80: 4.9150899 | U80: 5.1772317
A81: \\RES\GEE\GEE Live | B81: 714TMGXO_D_YOY_WX001.Q | C81: Quarterly | E81: TMGXO_D_YOY_WX | F81: -3.549766 | G81: -3.188909 | H81: -2.8267018 | I81: -2.4631395 | J81: -0.3037945 | K81: -1.1274266 | L81: -1.9442543 | M81: -2.7543339 | N81: -6.2858597 | O81: -5.2218798 | P81: -4.14582 | Q81: -3.0575431 | R81: -0.9047354 | S81: -0.56702736 | T81: -0.22816844 | U81: 0.11184528
A82: \\RES\GEE\GEE Live | B82: 714TMGXO_R_YOY_WX001.Q | C82: Quarterly | E82: TMGXO_R_YOY_WX | F82: 6.9518111 | G82: 6.8794892 | H82: 6.8072163 | I82: 6.7349923 | J82: 7.4784616 | K82: 6.8998788 | L82: 6.3244108 | M82: 5.7520405 | N82: 3.8553719 | O82: 4.1401903 | P82: 4.4257898 | Q82: 4.7121726 | R82: 5.1281883 | S82: 5.3170093 | T82: 5.5061695 | U82: 5.6956694
... A89: \\RES\GEE\GEE Live | B89: 714TXGXO_R_YOY_WM001.Q | C89: Quarterly | E89: TXGXO_R_YOY_WM | F89: 2.4233659 | G89: 2.814449 | H89: 3.2070254 | I89: 3.6011007 | J89: 4.0280028 | K89: 4.3689839 | L89: 4.7110828 | M89: 5.0543029 | N89: 5.9682906 | O89: 5.9340065 | P89: 5.8997335 | Q89: 5.8654716 | R89: 5.1080419 | S89: 5.5394631 | T89: 5.9726552 | U89: 6.4076252
F96: 2012 | G96: 2013 | H96: 2014 | I96: 2015 | J96: 2016 | K96: 2017 | L96: 2018 | M96: 2019 | N96: 2020
A97: \\RES\GEE\GEE Live | B97: 714PMPNF_PCH_WM001.A | C97: Annual | E97: PMPNF_PCH_WM | F97: -8.121452 | G97: -3.033414 | H97: -7.2138345 | I97: -17.586013 | J97: -6.1221617 | K97: 0.99066482 | L97: 0.37838184 | M97: -0.37293567 | N97: -0.38265745
A98: \\RES\GEE\GEE Live | B98: 714PXPNF_PCH_WX001.A | C98: Annual | E98: PXPNF_PCH_WX | F98: -15.347391 | G98: -10.146088 | H98: -2.504969 | I98: -12.847093 | J98: -3.9316148 | K98: 1.6862304 | L98: 1.2030755 | M98: 0.24548669 | N98: 0.22102179
A99: \\RES\GEE\GEE Live | B99: 714TMGCB_D_PCH001.A | C99: Annual | E99: TMGCB_D_PCH | F99: -0.97714228 | G99: -1.4142921 | H99: -3.2263025 | I99: -14.803352 | J99: -1.3016194 | K99: 2.7405151 | L99: 2.1671131 | M99: 1.1515789 | N99: 0.56670033
A100: \\RES\GEE\GEE Live | B100: 714TXGCB_D_PCH001.A | C100: Annual | E100: TXGCB_D_PCH | F100: -9.3949428 | G100: -6.7591321 | H100: -1.7854912 | I100: -9.3392098 | J100: -2.2537023 | K100: 1.3725057 | L100: 1.0475506 | M100: 0.41608718 | N100: 0.37182576
A101: \\RES\GEE\GEE Live | B101: 110TXGM_D_PCH001.A | C101: Annual | E101: TXGM_D_PCH | F101: 0.56478821 | G101: -1.0920232 | H101: -0.58164945 | I101: -3.4697627 | J101: 0.55380768 | K101: 0.8475764 | L101: 0.78732376 | M101: 0.70153866 | N101: 0.62415337
A102: \\RES\GEE\GEE Live | B102: 001POILAPSP_PCH001.A | C102: Annual | E102: POILAPSP_PCH | F102: 0.96068657 | G102: -0.89328372 | H102: -7.516202 | I102: -46.364141 | J102: -2.4480189 | K102: 10.051601 | L102: 7.9689926 | M102: 3.9107585 | N102: 1.2681357
F103: 2013Q1 | G103: 2013Q2 | H103: 2013Q3 | I103: 2013Q4 | J103: 2014Q1 | K103: 2014Q2 | L103: 2014Q3 | M103: 2014Q4 | N103: 2015Q1 | O103: 2015Q2 | P103: 2015Q3 | Q103: 2015Q4 | R103: 2016Q1 | S103: 2016Q2 | T103: 2016Q3 | U103: 2016Q4
A104: \\RES\GEE\GEE Live | B104: 714PMPNF_YOY_WM001.Q | C104: Quarterly | E104: PMPNF_YOY_WM | F104: 2.4945465 | G104: 0.17587882 | H104: -6.3871409 | I104: -8.256431 | J104: -8.8841344 | K104: -4.6392797 | L104: -6.4800619 | M104: -8.854567 | N104: -15.438246 | O104: -18.963019 | P104: -19.001829 | Q104: -16.940598 | R104: -11.123926 | S104: -8.5947905 | T104: -3.3114677 | U104: -0.69754116
A105: \\RES\GEE\GEE Live | B105: 714PXPNF_YOY_WX001.Q | C105: Quarterly | E105: PXPNF_YOY_WX | F105: -6.7093941 | G105: -10.032232 | H105: -11.089105 | I105: -13.028067 | J105: -10.411022 | K105: -0.039693315 | L105: 1.5507367 | M105: -0.066077562 | N105: -10.526501 | O105: -13.087227 | P105: -14.288421 | Q105: -13.513401 | R105: -7.8838695 | S105: -6.4241005 | T105: -2.3789955 | U105: 1.3422147
A106: \\RES\GEE\GEE Live | B106: 714TMGCB_D_YOY001.Q | C106: Quarterly | E106: TMGCB_D_YOY | F106: -1.4205457 | G106: -1.3640572 | H106: -0.97405994 | I106: -1.583288 | J106: -2.0928214 | K106: 0.43762939 | L106: -2.8396487 | M106: -8.3125023 | N106: -16.011647 | O106: -14.68863 | P106: -17.45788 | Q106: -12.911244 | R106: -3.9491767 | S106: -5.0634691 | T106: 1.5467512 | U106: 3.9315671
A107: \\RES\GEE\GEE Live | B107: 714TXGCB_D_YOY001.Q | C107: Quarterly | E107: TXGCB_D_YOY | F107: -4.5548383 | G107: -6.7176749 | H107: -7.399654 | I107: -8.5991266 | J107: -6.6471458 | K107: -0.089512257 | L107: 0.79026043 | M107: -0.47653307 | N107: -7.672366 | O107: -9.6229729 | P107: -10.504449 | Q107: -9.8313311 | R107: -5.5519172 | S107: -4.038717 | T107: -0.94027411 | U107: 1.6969845
A108: \\RES\GEE\GEE Live | B108: 110TXGM_D_YOY001.Q | C108: Quarterly | E108: TXGM_D_YOY | F108: -0.97190333 | G108: -1.1969532 | H108: -1.1989575 | I108: -1.0001223 | J108: -0.34683693 | K108: -0.24550712 | L108: -0.51821336 | M108: -1.2182554 | N108: -2.831786 | O108: -3.6504421 | P108: -3.9417953 | Q108: -3.4582197 | R108: -1.5550585 | S108: 0.050697384 | T108: 1.4899361 | U108: 2.2764455
A109: \\RES\GEE\GEE Live | B109: 001POILAPSP_YOY001.Q | C109: Quarterly | E109: POILAPSP_YOY | F109: -6.5415194 | G109: -3.4649963 | H109: 4.4422958 | I109: 2.554692 | J109: -1.3313377 | K109: 7.0834521 | L109: -6.4828941 | M109: -28.671316 | N109: -50.110738 | O109: -43.199029 | P109: -52.02562 | Q109: -38.043297 | R109: -7.1048344 | S109: -17.632556 | T109: 6.2182391 | U109: 13.591655
D117: ARCHIVE
F118: 2012A1 | G118: 2013A1 | H118: 2014A1 | I118: 2015A1 | J118: 2016A1 | K118: 2017A1 | L118: 2018A1 | M118: 2019A1 | N118: 2020A1
A119: \\RES\GEE\GEE Production | B119: 714LULCM_USD_PCH_WX110.A | C119: Annual | D119: Advanced Economies | E119: LULCM_USD_PCH_WX | F119: -0.98557483 | G119: 1.8669117 | H119: 0.4655008 | I119: -7.383677 | J119: 1.518745 | K119: 2.1193704 | L119: 2.186499 | M119: 1.7634737 | N119: 2.4034979
A120: \\RES\GEE\GEE Production | B120: 714NGDP_D_PCH_WM110.A | C120: Annual | E120: NGDP_D_PCH_WM | F120: 1.4498999 | G120: 1.347444 | H120: 1.1453251 | I120: 0.84705263 | J120: 1.3372 | K120: 1.4862499 | L120: 1.6658317 | M120: 1.7652251 | N120: 1.8079974
A121: \\RES\GEE\GEE Production | B121: 714NGDP_D_USD_PCH_WM110.A | C121: Annual | E121: NGDP_D_USD_PCH_WM | F121: -3.3156393 | G121: 2.3647717 | H121: 0.30301287 | I121: -10.911659 | J121: 2.0477327 | K121: 2.3287858 | L121: 2.5876848 | M121: 2.3840617 | N121: 3.0967018
A122: \\RES\GEE\GEE Production | B122: 714NGDP_R_PCH_WX110.A | C122: Annual | E122: NGDP_R_PCH_WX | F122: 1.0636319 | G122: 1.2502207 | H122: 1.7440203 | I122: 1.9273075 | J122: 2.2413203 | K122: 2.1130838 | L122: 2.0325399 | M122: 1.9911378 | N122: 1.8914638
A123: \\RES\GEE\GEE Production | B123: 714NTDD_R_PCH_WX110.A | C123: Annual | E123: NTDD_R_PCH_WX | F123: 0.96590349 | G123: 1.0616452 | H123: 1.7366034 | I123: 2.2004724 | J123: 2.4334339 | K123: 2.2512916 | L123: 2.1665499 | M123: 2.1319712 | N123: 2.0313772
A124: \\RES\GEE\GEE Production | B124: 714PCPI_PCH_WM110.A | C124: Annual | E124: PCPI_PCH_WM | F124: 2.2015136 | G124: 1.4634036 | H124: 0.99119606 | I124: 0.33850563 | J124: 1.3347293 | K124: 1.6583138 | L124: 1.8172027 | M124: 1.9261979 | N124: 1.9674989
A125: \\RES\GEE\GEE Production | B125: 714PCPI_USD_PCH_WM110.A | C125: Annual | E125: PCPI_USD_PCH_WM | F125: -2.6055764 | G125: 2.4706153 | H125: 0.14682949 | I125: -11.366816 | J125: 2.0436732 | K125: 2.5031439 | L125: 2.7404409 | M125: 2.5462276 | N125: 3.2581719
A126: \\RES\GEE\GEE Production | B126: 714TM_D_PCH_WX110.A | C126: Annual | E126: TM_D_PCH_WX | F126: -1.1902821 | G126: 0.73325274 | H126: -0.43380625 | I126: -10.249883 | J126: 0.18579082 | K126: 0.82803161 | L126: 0.75569218 | M126: 0.59593863 | N126: 1.0379059
A127: \\RES\GEE\GEE Production | B127: 714TM_R_PCH_WX110.A | C127: Annual | E127: TM_R_PCH_WX | F127: 0.65975722 | G127: 1.8374502 | H127: 2.9970418 | I127: 3.8285781 | J127: 4.8080106 | K127: 4.8222506 | L127: 4.8751769 | M127: 5.0092319 | N127: 5.0859201
A128: \\RES\GEE\GEE Production | B128: 714TMG_D_PCH_WX110.A | C128: Annual | E128: TMG_D_PCH_WX | F128: -1.4525666 | G128: 0.4467198 | H128: -1.2372665 | I128: -10.440546 | J128: 0.25636095 | K128: 0.81502998 | L128: 0.74966398 | M128: 0.56362733 | N128: 0.95864118
A129: \\RES\GEE\GEE Production | B129: 714TMG_R_PCH_WX110.A | C129: Annual | E129: TMG_R_PCH_WX | F129: 0.20436521 | G129: 1.4897196 | H129: 3.096309 | I129: 3.6983694 | J129: 4.9095672 | K129: 4.989803 | L129: 5.0389799 | M129: 5.1699766 | N129: 5.2617136
A130: \\RES\GEE\GEE Production | B130: 714TMGXO_D_PCH_WX110.A | C130: Annual | E130: TMGXO_D_PCH_WX | F130: -2.1646302 | G130: 0.95361778 | H130: -0.20249966 | I130: -5.8347252 | J130: -0.39170648 | K130: 0.24087367 | L130: 0.25146495 | M130: 0.35343787 | N130: 0.99663633
A131: \\RES\GEE\GEE Production | B131: 714TMGXO_R_PCH_WX110.A | C131: Annual | E131: TMGXO_R_PCH_WX | F131: 0.87587415 | G131: 1.973752 | H131: 3.8895261 | I131: 2.6735435 | J131: 5.767884 | K131: 5.5016457 | L131: 5.5653167 | M131: 5.5202916 | N131: 5.4568896
... A137: \\RES\GEE\GEE Production | B137: 714TXGXO_R_PCH_WM001.A | C137: Annual | E137: TXGXO_R_PCH_WM | F137: 0.94304874 | G137: 1.8254833 | H137: 3.0252954 | I137: 0.94751479 | J137: 4.0867181 | K137: 4.1551831 | L137: 4.2415617 | M137: 4.3793781 | N137: 4.2682681
A138: \\RES\GEE\GEE Production | B138: 714LULCM_USD_PCH_WX001.A | C138: Annual | D138: World | E138: LULCM_USD_PCH_WX | F138: -1.0809918 | G138: 1.730205 | H138: 0.26881521 | I138: -7.6341153 | J138: 1.5200824 | K138: 2.180639 | L138: 2.2408923 | M138: 1.8401841 | N138: 2.453792
A139: \\RES\GEE\GEE Production | B139: 714NGDP_D_PCH_WM001.A | C139: Annual | E139: NGDP_D_PCH_WM | F139: 5.9841285 | G139: 3.225412 | H139: 3.1584376 | I139: 1.8628597 | J139: 3.76009 | K139: 3.5574661 | L139: 3.5459378 | M139: 3.4674574 | N139: 3.5259031
A140: \\RES\GEE\GEE Production | B140: 714NGDP_D_USD_PCH_WM001.A | C140: Annual | E140: NGDP_D_USD_PCH_WM | F140: 4.0674484 | G140: 1.3242872 | H140: 1.3522731 | I140: -7.4038553 | J140: 1.8180862 | K140: 2.5008307 | L140: 2.5158813 | M140: 2.5211475 | N140: 3.0545458
A141: \\RES\GEE\GEE Production | B141: 714NGDP_R_PCH_WX001.A | C141: Annual | E141: NGDP_R_PCH_WX | F141: 4.7504048 | G141: 5.0131781 | H141: 5.3151313 | I141: 4.9559147 | J141: 4.8256485 | K141: 4.8536002 | L141: 4.7998265 | M141: 4.6614286 | N141: 4.4379531
A142: \\RES\GEE\GEE Production | B142: 714NTDD_R_PCH_WX001.A | C142: Annual | E142: NTDD_R_PCH_WX | F142: 5.3832785 | G142: 5.478228 | H142: 5.180167 | I142: 5.4324569 | J142: 4.8130244 | K142: 4.9285493 | L142: 4.9476908 | M142: 4.7481555 | N142: 4.5958427
A143: \\RES\GEE\GEE Production | B143: 714PCPI_PCH_WM001.A | C143: Annual | E143: PCPI_PCH_WM | F143: 6.7191248 | G143: 3.9884893 | H143: 3.7839932 | I143: 3.7022051 | J143: 3.8546731 | K143: 3.7101176 | L143: 3.6858241 | M143: 3.7256815 | N143: 3.7623841
A144: \\RES\GEE\GEE Production | B144: 714PCPI_USD_PCH_WM001.A | C144: Annual | E144: PCPI_USD_PCH_WM | F144: 4.7690615 | G144: 2.0567482 | H144: 2.0422141 | I144: -5.5787488 | J144: 1.9063841 | K144: 2.6531198 | L144: 2.6547508 | M144: 2.7781996 | N144: 3.2914097
A145: \\RES\GEE\GEE Production | B145: 714TM_D_PCH_WX001.A | C145: Annual | E145: TM_D_PCH_WX | F145: 0.55066679 | G145: -1.6436457 | H145: -2.0323272 | I145: -9.6482726 | J145: 0.45194296 | K145: 1.7552152 | L145: 1.5681814 | M145: 1.2829683 | N145: 1.2160969
A146: \\RES\GEE\GEE Production | B146: 714TM_R_PCH_WX001.A | C146: Annual | E146: TM_R_PCH_WX | F146: 1.2854034 | G146: 5.4177859 | H146: 7.8735932 | I146: 7.4457116 | J146: 4.9202329 | K146: 5.6788303 | L146: 5.654207 | M146: 5.3736815 | N146: 5.3985868
A147: \\RES\GEE\GEE Production | B147: 714TMG_D_PCH_WX001.A | C147: Annual | E147: TMG_D_PCH_WX | F147: 0.064347814 | G147: -2.8285874 | H147: -2.1928557 | I147: -9.2737517 | J147: -0.11366995 | K147: 1.5072365 | L147: 1.3058227 | M147: 0.78852075 | N147: 0.53416241
A148: \\RES\GEE\GEE Production | B148: 714TMG_R_PCH_WX001.A | C148: Annual | E148: TMG_R_PCH_WX | F148: 1.4411532 | G148: 6.9492517 | H148: 6.7769666 | I148: 5.0339848 | J148: 4.8046245 | K148: 5.8850465 | L148: 5.8560065 | M148: 5.5874263 | N148: 5.6343434
...

Sheet Compare
A1: Refresh Step:
A2: This sheet is not refreshable. | D2: On EcXL Refresh tab, click on refresh WORKBOOK. Note that all worksheets will be updated simultaneously.
A3: Rwanda: Selected Composite Indicators of Trading Partners (GEE)
A4: (Current [S2015Rev] - [S2015Board])
A5: 42242.444
B6: 2012 | C6: 2013 | D6: 2014 | E6: 2015 | F6: 2016 | G6: 2017 | H6: 2018 | I6: 2019 | J6: 2020 | K6: 2013Q1 | L6: 2013Q2 | M6: 2013Q3 | N6: 2013Q4 | O6: 2014Q1 | P6: 2014Q2 | Q6: 2014Q3 | R6: 2014Q4 | S6: 2015Q1 | T6: 2015Q2 | U6: 2015Q3 | V6: 2015Q4 | W6: 2016Q1 | X6: 2016Q2 | Y6: 2016Q3 | Z6: 2016Q4
A7: 1) Foreign Output and Demand of Trading Partners 1/ | B7: Annual percent change | K7: Percent change from four quarters earlier
A9: Advanced economy partners | B9: Export-weighted averages
A11: Real GDP | B11: 0 | C11: 0 | D11: 0 | E11: 0 | F11: 0 | G11: 0 | H11: 0 | I11: 0 | J11: 0 | K11: 0 | L11: 0 | M11: 0 | N11: 0 | O11: 0 | P11: 0 | Q11: 0 | R11: 0 | S11: 0 | T11: 0 | U11: 0 | V11: 0 | W11: 0 | X11: 0 | Y11: 0 | Z11: 0
A12: Real total domestic demand | B12: 0 | C12: 0 | D12: 0 | E12: 0 | F12: 0 | G12: 0 | H12: 0 | I12: 0 | J12: 0 | K12: 0 | L12: 0 | M12: 0 | N12: 0 | O12: 0 | P12: 0 | Q12: 0 | R12: 0 | S12: 0 | T12: 0 | U12: 0 | V12: 0 | W12: 0 | X12: 0 | Y12: 0 | Z12: 0
A14: All countries 2/
A16: Real GDP | B16: 0 | C16: 0 | D16: 0 | E16: 0 | F16: 0 | G16: 0 | H16: 0 | I16: 0 | J16: 0 | K16: 0 | L16: 0 | M16: 0 | N16: 0 | O16: 0 | P16: 0 | Q16: 0 | R16: 0 | S16: 0 | T16: 0 | U16: 0 | V16: 0 | W16: 0 | X16: 0 | Y16: 0 | Z16: 0
A17: Real imports
A18: Goods and services | B18: 0.079454853 | C18: -0.034948591 | D18: -0.0005562163 | E18: 0.17816095 | F18: -0.0022047972 | G18: -0.011801185 | H18: -0.011125305 | I18: -0.0081644076 | J18: -0.017480544 | K18: -0.048380611 | L18: -0.039936074 | M18: -0.031400443 | N18: -0.022772987 | O18: -0.076227318 | P18: -0.027634136 | Q18: 0.020926817 | R18: 0.06945556 | S18: 0.26371846 | T18: 0.21309217 | U18: 0.16306349 | V18: 0.11362705 | W18: 0.0014043599 | X18: -0.00097596051 | Y18: -0.0033647304 | Z18: -0.0057619722
A19: Goods | B19: 0.07835371 | C19: -0.034375804 | D19: -0.00055049511 | E19: 0.17661057 | F19: -0.0022041807 | G19: -0.011802723 | H19: -0.011126754 | I19: -0.0081654714 | J19: -0.017482822 | K19: -0.048842892 | L19: -0.040026666 | M19: -0.031221882 | N19: -0.022428528 | O19: -0.075305819 | P19: -0.026693723 | Q19: 0.021574392 | R19: 0.069500358 | S19: 0.25711209 | T19: 0.20895333 | U19: 0.16085866 | V19: 0.11282801 | W19: 0.0014046243 | X19: -0.00097008336 | Y19: -0.0033567209 | Z19: -0.0057553333
A20: Excluding oil | B20: 0.08681139 | C20: -0.038043682 | D20: -0.0005919504 | E20: 0.19196248 | F20: -0.0028021071 | G20: -0.013045083 | H20: -0.01225567 | I20: -0.0090339809 | J20: -0.018914144 | K20: -0.053862124 | L20: -0.044121494 | M20: -0.034394893 | N20: -0.024682305 | O20: -0.081484536 | P20: -0.028705592 | Q20: 0.023482 | R20: 0.075083228 | S20: 0.27545671 | T20: 0.22482521 | U20: 0.17388845 | V20: 0.12264503 | W20: 0.0010526184 | X20: -0.0014937849 | Y20: -0.0040494005 | Z20: -0.0066142535
A22: Real exports | B22: Import-weighted averages
A23: Goods and services | B23: 0.12584747 | C23: -0.054338245 | D23: -0.00085283711 | E23: 0.27922566 | F23: -0.0034370653 | G23: -0.018374022 | H23: -0.0173217 | I23: -0.0127127 | J23: -0.02721658 | K23: -0.075768776 | L23: -0.061891194 | M23: -0.048131275 | N23: -0.034488266 | O23: -0.11364663 | P23: -0.042094598 | Q23: 0.030524732 | R23: 0.10422327 | S23: 0.40538254 | T23: 0.33034348 | U23: 0.25515293 | V23: 0.17981064 | W23: 0.0022147497 | X23: -0.0015350653 | Y23: -0.0052964661 | Z23: -0.0090694795
A24: Goods | B24: 0.12476819 | C24: -0.054302275 | D24: -0.00085210846 | E24: 0.27900468 | F24: -0.00344505 | G24: -0.018397588 | H24: -0.017343917 | I24: -0.012729005 | J24: -0.027251487 | K24: -0.074355296 | L24: -0.061184925 | M24: -0.047956803 | N24: -0.034670741 | O24: -0.11424475 | P24: -0.041675259 | Q24: 0.031579307 | R24: 0.1055238 | S24: 0.4047045 | T24: 0.32913093 | U24: 0.2536472 | V24: 0.17825321 | W24: 0.0022121804 | X24: -0.0014903168 | Y24: -0.0052230672 | Z24: -0.0089862561
A25: Excluding oil | B25: 0.12549476 | C25: -0.054662814 | D25: -0.00085771994 | E25: 0.28056464 | F25: -0.0035076835 | G25: -0.018520586 | H25: -0.017455843 | I25: -0.01281525 | J25: -0.027393968 | K25: -0.074763068 | L25: -0.061637436 | M25: -0.048412234 | N25: -0.035086899 | O25: -0.11532478 | P25: -0.041598335 | Q25: 0.032559934 | R25: 0.10715193 | S25: 0.40660395 | T25: 0.33091529 | U25: 0.25522149 | V25: 0.17952253 | W25: 0.0021766489 | X25: -0.0015470513 | Y25: -0.005301489 | Z25: -0.0090868543
A27: 2) Foreign Prices and Costs of Trading Partners 1/
A29: Advanced economy partners | B29: Import-weighted averages
A31: GDP deflators
A32: In national currency | B32: 0 | C32: 0 | D32: 0 | E32: 0 | F32: 0 | G32: 0 | H32: 0 | I32: 0 | J32: 0 | K32: 0 | L32: 0 | M32: 0 | N32: 0 | O32: 0 | P32: 0 | Q32: 0 | R32: 0 | S32: 0 | T32: 0 | U32: 0 | V32: 0 | W32: 0 | X32: 0 | Y32: 0 | Z32: 0
A33: In U.S. dollars | B33: 0 | C33: 0 | D33: 0 | E33: -0.53854087 | F33: -0.6314617 | G33: 0.029114196 | H33: -0.18781785 | I33: -0.073387252 | J33: -0.20629558 | K33: 0 | L33: 0 | M33: 0 | N33: 0 | O33: 0 | P33: 0 | Q33: 0 | R33: 0 | S33: 0 | T33: -0.00026707986 | U33: -1.1584427 | V33: -1.1076571 | W33: -1.274217 | X33: -1.2807472 | Y33: 0.07293577 | Z33: -0.040504996
A35: Consumer Prices
A36: In national currency | B36: 0 | C36: 0 | D36: 0 | E36: 0 | F36: 0 | G36: 0 | H36: 0 | I36: 0 | J36: 0 | K36: 0 | L36: 0 | M36: 0 | N36: 0 | O36: 0 | P36: 0 | Q36: 0 | R36: 0 | S36: 0 | T36: 0 | U36: 0 | V36: 0 | W36: 0 | X36: 0 | Y36: 0 | Z36: 0
A37: In U.S. dollars | B37: 0 | C37: 0 | D37: 0 | E37: -0.53775372 | F37: -0.63048638 | G37: 0.029244705 | H37: -0.18766739 | I37: -0.07314238 | J37: -0.2062708 | K37: 0 | L37: 0 | M37: 0 | N37: 0 | O37: 0 | P37: 0 | Q37: 0 | R37: 0 | S37: 0 | T37: -0.00026599085 | U37: -1.153647 | V37: -1.1052227 | W37: -1.2734179 | X37: -1.2798176 | Y37: 0.074262941 | Z37: -0.038884916
A39: All countries 2/
A41: Export deflators in U.S. dollars
A42: Goods and services | B42: -0.12443199 | C42: 0.053275618 | D42: 0.00082568037 | E42: -0.29998828 | F42: 0.0033054986 | G42: 0.017597147 | H42: 0.016522547 | I42: 0.012160685 | J42: 0.026062041 | K42: 0.071508298 | L42: 0.05882114 | M42: 0.046092654 | N42: 0.03332274 | O42: 0.10667374 | P42: 0.03030847 | Q42: -0.043177152 | R42: -0.1138653 | S42: -0.37217646 | T42: -0.31177325 | U42: -0.24871352 | V42: -0.18291322 | W42: -0.0020437617 | X42: 0.0014614827 | Y42: 0.0049880368 | Z42: 0.0085359978
A43: Goods | B43: -0.12477596 | C43: 0.05325963 | D43: 0.00082270831 | E43: -0.30037304 | F43: 0.0033097381 | G43: 0.017619716 | H43: 0.016543738 | I43: 0.012176281 | J43: 0.026095468 | K43: 0.07208267 | L43: 0.059062123 | M43: 0.046090673 | N43: 0.033168181 | O43: 0.10577258 | P43: 0.03025886 | Q43: -0.042701017 | R43: -0.11317236 | S43: -0.37174499 | T43: -0.31222963 | U43: -0.24978156 | V43: -0.18429738 | W43: -0.0020553327 | X43: 0.0014845751 | Y43: 0.0050386213 | Z43: 0.0086068481
A44: Excluding oil | B44: -0.12545905 | C44: 0.053578373 | D44: 0.00082914174 | E44: -0.30265343 | F44: 0.0033686879 | G44: 0.0177317 | H44: 0.016645393 | I44: 0.012256263 | J44: 0.026229181 | K44: 0.07242373 | L44: 0.059425736 | M44: 0.046445286 | N44: 0.033482362 | O44: 0.10664063 | P44: 0.03161953 | Q44: -0.041664556 | R44: -0.11324197 | S44: -0.38394347 | T44: -0.31966444 | U44: -0.25335753 | V44: -0.18497616 | W44: -0.0020111165 | X44: 0.0015307354 | Y44: 0.0050876067 | Z44: 0.0086595452
A46: Import deflators in U.S. dollars | B46: Export-weighted averages in U.S. dollars | V46: Export-weighted averages in U.S. dollars
A47: Goods and services | B47: -0.080285388 | C47: 0.033930292 | D47: 0.00052311492 | E47: -0.18823432 | F47: 0.0021387944 | G47: 0.011336728 | H47: 0.010650667 | I47: 0.0078254192 | J47: 0.016758508 | K47: 0.046016921 | L47: 0.037743999 | M47: 0.02948681 | N47: 0.021245333 | O47: 0.067773323 | P47: 0.019136012 | Q47: -0.027544973 | R47: -0.072329214 | S47: -0.23242286 | T47: -0.19585567 | U47: -0.15712703 | V47: -0.11614641 | W47: -0.0013329625 | X47: 0.00093880582 | Y47: 0.0032254831 | Z47: 0.0055271427
A48: Goods | B48: -0.080440777 | C48: 0.033746761 | D48: 0.00051935979 | E48: -0.18825885 | F48: 0.0021390731 | G48: 0.011338205 | H48: 0.010652054 | I48: 0.0078264387 | J48: 0.016760691 | K48: 0.045435805 | L48: 0.037381924 | M48: 0.029299824 | N48: 0.02118943 | O48: 0.067391658 | P48: 0.018963274 | Q48: -0.027625057 | R48: -0.072426244 | S48: -0.23344163 | T48: -0.19621114 | U48: -0.15697629 | V48: -0.11566021 | W48: -0.0013293918 | X48: 0.00092875435 | Y48: 0.0032054599 | Z48: 0.0055008393
A49: Excluding oil | B49: -0.088583108 | C49: 0.037283789 | D49: 0.00055666554 | E49: -0.2110542 | F49: 0.0027058306 | G49: 0.012470052 | H49: 0.011679299 | I49: 0.0086323412 | J49: 0.018105234 | K49: 0.049937127 | L49: 0.041169254 | M49: 0.032334242 | N49: 0.023431708 | O49: 0.072730663 | P49: 0.021501833 | Q49: -0.028911243 | R49: -0.078518349 | S49: -0.2696613 | T49: -0.22353859 | U49: -0.17635956 | V49: -0.12810644 | W49: -0.00098020728 | X49: 0.0014227546 | Y49: 0.0038420476 | Z49: 0.0062777549
A51: Advanced economy partners | B51: Export-weighted averages in U.S. dollars | V51: Export-weighted averages in U.S. dollars
A53: Unit labor costs in manufacturing | B53: 0 | C53: 0 | D53: 0 | E53: -0.30730745 | F53: -0.26564262 | G53: 0.022131951 | H53: -0.084756531 | I53: 0.044311458 | J53: -0.06067677 | K53: 0 | L53: 0 | M53: 0 | N53: 0 | O53: 0 | P53: 0 | Q53: 0 | R53: 0 | S53: 0 | T53: -0.00051387618 | U53: -0.73401183 | V53: -0.6216981 | W53: -0.64578666 | X53: -0.6381726 | Y53: 0.1799753 | Z53: 0.036958316
A55: 3) World Prices | B55: In U.S. dollars
A56: Export unit value for manufactures (MUV) | B56: -0.3468266 | C56: 0.22465852 | D56: 0.050422144 | E56: -0.39612081 | F56: -0.10109822 | G56: 0.14723937 | H56: 0.17319329 | I56: 0.15989524 | J56: 0.21560818 | K56: -0.13806516 | L56: 0.14142662 | M56: 0.38977351 | N56: 0.50609512 | O56: 0.40009541 | P56: 0.19070783 | Q56: -0.080491769 | R56: -0.31058091 | S56: -0.46679899 | T56: -0.46425127 | U56: -0.38008795 | V56: -0.27302253 | W56: -0.14965789 | X56: -0.10576434 | Y56: -0.086721455 | Z56: -0.058292771
A57: Petroleum spot price (APSP) | B57: 0 | C57: 0 | D57: 0 | E57: -4.7718525 | F57: -8.3900481 | G57: 3.8223791 | H57: 2.586976 | I57: 1.2684342 | J57: 0.423349 | K57: 0 | L57: 0 | M57: 0 | N57: 0 | O57: 0 | P57: 0 | Q57: 0 | R57: 0 | S57: 0 | T57: 0 | U57: -7.7679298 | V57: -14.183108 | W57: -19.232033 | X57: -15.408071 | Y57: -1.1271855 | Z57: 5.9797786
A59: Average of nonfuel commodity market prices weighted by the 2011-2013 composition of nonfuel commodity trade of reporting country.
A61: Nonfuel commodity export price | B61: 0 | C61: 0.0013748554 | D61: -0.0015071444 | E61: 1.0958228 | F61: -0.080810287 | G61: 0.13185541 | H61: 0.36000323 | I61: 0.060683398 | J61: 0.086457903 | K61: 0 | L61: 0 | M61: -0.00066597 | N61: 0.0062743795 | O61: -0.0013354548 | P61: -0.0057957164 | Q61: 0.0070685305 | R61: -0.0060621369 | S61: 0.0053806662 | T61: -0.024197198 | U61: 2.7306792 | V61: 1.7134232 | W61: 1.1014669 | X61: 0.95574558 | Y61: -2.0289411 | Z61: -0.67999912
A62: Nonfuel commodity import price | B62: 0 | C62: 0.00085147249 | D62: -0.0008235798 | E62: -1.5466795 | F62: -2.7804463 | G62: 1.0007328 | H62: 0.79941496 | I62: 0.054445225 | J62: 0.072188357 | K62: 0 | L62: 0 | M62: -0.00039652494 | N62: 0.0037721681 | O62: -0.0007967141 | P62: -0.0032577559 | Q62: 0.0039632752 | R62: -0.0030935381 | S62: 0.0036915214 | T62: -0.055452654 | U62: -2.5727556 | V62: -3.8381994 | W62: -4.5146135 | X62: -4.6789208 | Y62: -1.5603682 | Z62: 0.14460116
A64: Component-Based Goods Trade Deflators 3/
A66: Export deflators | B66: -0.12974133 | C66: 0.084901087 | D66: 0.017918629 | E66: 0.53771469 | F66: -0.08839962 | G66: 0.13761026 | H66: 0.29012113 | I66: 0.097796688 | J66: 0.1347706 | K66: -0.052445538 | L66: 0.052224078 | M66: 0.13998137 | N66: 0.18294705 | O66: 0.14345314 | P66: 0.069162007 | Q66: -0.026209263 | R66: -0.12183034 | S66: -0.16507646 | T66: -0.18149559 | U66: 1.6365946 | V66: 1.0024989 | W66: 0.63261134 | X66: 0.55434986 | Y66: -1.3089753 | Z66: -0.4448651
A67: Import deflators | B67: -0.21173195 | C67: 0.13730936 | D67: 0.030628084 | E67: -1.4982212 | F67: -2.282156 | G67: 1.0518086 | H67: 0.77956435 | I67: 0.3649702 | J67: 0.23094545 | K67: -0.086127512 | L67: 0.087201364 | M67: 0.238283 | N67: 0.30842681 | O67: 0.24105095 | P67: 0.11653327 | Q67: -0.047969073 | R67: -0.1824136 | S67: -0.25658529 | T67: -0.27143578 | U67: -2.9936216 | V67: -4.3514667 | W67: -4.4190164 | X67: -4.0069456 | Y67: -0.54786805 | Z67: 1.1458255
A70: 1/ Averages of percent changes of data for individual trading partners weighted by their share in total exports or imports, as applicable, of reporting country. Note that the relative importance of trading partners reflects trade in goods only; complete information on bilateral trade in services is not generally available.
A71: 2/ Based on data for partner countries that together account for 100 percent of trade of reporting country.
A72: 3/ Average of the export unit value for manufactures (MUV), the petroleum price (APSP), and the nonfuel commodity price, weighted by the 2011-13 composition of trade of reporting country.
A75: Current Vintage: S2015Rev

Sheet AnnualDataSheet
A2: ANNUAL
C4: 2000 | D4: 2001 | E4: 2002 | F4: 2003 | G4: 2004 | H4: 2005 | I4: 2006 | J4: 2007 | K4: 2008 | L4: 2009 | M4: 2010 | N4: 2011 | O4: 2012 | P4: 2013 | Q4: 2014 | R4: 2015 | S4: 2016 | T4: 2017 | U4: 2018 | V4: 2019 | W4: 2020
A5: Advanced Economies | B5: LULCM_USD_PCH_WX | C5: -6.9554754 | D5: -0.68871673 | E5: 1.884114 | F5: 9.9604798 | G5: 4.7272028 | H5: -0.22988558 | I5: 0.32348067 | J5: 5.4384198 | K5: 7.2315268 | L5: 2.8783892 | M5: -6.3447311 | N5: 4.0011139 | O5: -0.98557483 | P5: 1.8669117 | Q5: 0.4655008 | R5: -7.6909845 | S5: 1.2531023 | T5: 2.1415024 | U5: 2.1017425 | V5: 1.8077852 | W5: 2.3428212
B6: NGDP_D_PCH_WM | C6: 2.0192483 | D6: 2.209807 | E6: 1.9155716 | F6: 1.7744114 | G6: 1.8716788 | H6: 2.0135433 | I6: 2.103247 | J6: 2.4628902 | K6: 2.2830565 | L6: 0.84325918 | M6: 1.2679762 | N6: 1.5214752 | O6: 1.4498999 | P6: 1.347444 | Q6: 1.1453251 | R6: 0.84705263 | S6: 1.3372 | T6: 1.4862499 | U6: 1.6658317 | V6: 1.7652251 | W6: 1.8079974
B7: NGDP_D_USD_PCH_WM | C7: -6.2065468 | D7: -1.7382942 | E7: 5.5378263 | F7: 16.178893 | G7: 9.8051284 | H7: 2.7291776 | I7: 3.0086614 | J7: 9.2821187 | K7: 6.8290982 | L7: -4.0750778 | M7: 0.65218754 | N7: 6.404836 | O7: -3.3156393 | P7: 2.3647717 | Q7: 0.30301287 | R7: -11.4502 | S7: 1.416271 | T7: 2.3579 | U7: 2.399867 | V7: 2.3106745 | W7: 2.8904062
B8: NGDP_R_PCH_WX | C8: 4.1951162 | D8: 1.3230842 | E8: 1.4770955 | F8: 1.7429182 | G8: 3.4805245 | H8: 2.8168608 | I8: 3.2976305 | J8: 2.9474896 | K8: 0.44924881 | L8: -3.435452 | M8: 3.1218485 | N8: 2.2213748 | O8: 1.0636319 | P8: 1.2502207 | Q8: 1.7440203 | R8: 1.9273075 | S8: 2.2413203 | T8: 2.1130838 | U8: 2.0325399 | V8: 1.9911378 | W8: 1.8914638
B9: NTDD_R_PCH_WX | C9: 4.2435342 | D9: 0.99993762 | E9: 0.89992973 | F9: 1.8044261 | G9: 3.1249395 | H9: 2.5199807 | I9: 2.9245869 | J9: 2.6974294 | K9: 0.31807982 | L9: -3.0275039 | M9: 3.0459236 | N9: 2.2348846 | O9: 0.96590349 | P9: 1.0616452 | Q9: 1.7366034 | R9: 2.2004724 | S9: 2.4334339 | T9: 2.2512916 | U9: 2.1665499 | V9: 2.1319712 | W9: 2.0313772
B10: PCPI_PCH_WM | C10: 2.1936778 | D10: 2.6001864 | E10: 1.944799 | F10: 1.8191365 | G10: 1.7845186 | H10: 2.0818881 | I10: 2.1656247 | J10: 2.0778247 | K10: 3.4800532 | L10: 0.36875951 | M10: 1.603141 | N10: 2.8656453 | O10: 2.2015136 | P10: 1.4634036 | Q10: 0.99119606 | R10: 0.33850563 | S10: 1.3347293 | T10: 1.6583138 | U10: 1.8172027 | V10: 1.9261979 | W10: 1.9674989
B11: PCPI_USD_PCH_WM | C11: -6.0457699 | D11: -1.3610421 | E11: 5.5615563 | F11: 16.208776 | G11: 9.7031438 | H11: 2.7982567 | I11: 3.0699971 | J11: 8.8580214 | K11: 8.0933364 | L11: -4.526507 | M11: 0.96707468 | N11: 7.8122599 | O11: -2.6055764 | P11: 2.4706153 | Q11: 0.14682949 | R11: -11.90457 | S11: 1.4131868 | T11: 2.5323886 | U11: 2.5527735 | V11: 2.4730852 | W11: 3.0519011
B12: TM_D_PCH_WX | C12: -1.2232062 | D12: -2.6873276 | E12: 0.61484096 | F12: 9.2571824 | G12: 8.1673486 | H12: 4.9243562 | I12: 3.8931292 | J12: 7.1460321 | K12: 11.80884 | L12: -10.179495 | M12: 3.97414 | N12: 10.136013 | O12: -1.567555 | P12: 0.8926962 | Q12: -0.43134805 | R12: -11.134424 | S12: 0.19584133 | T12: 0.88130457 | U12: 0.80574123 | V12: 0.63271143 | W12: 1.1166566
B13: TM_R_PCH_WX | C13: 12.504519 | D13: -0.24975561 | E13: 3.6978141 | F13: 4.1489045 | G13: 9.5049294 | H13: 6.2034373 | I13: 7.2203347 | J13: 4.9549957 | K13: -0.46021701 | L13: -11.868361 | M13: 11.340355 | N13: 5.3606142 | O13: 1.0331273 | P13: 1.6732216 | Q13: 2.9944281 | R13: 4.6657828 | S13: 4.7976499 | T13: 4.7667951 | U13: 4.8228975 | V13: 4.9708661 | W13: 5.0037765
B14: TMG_D_PCH_WX | C14: -0.33782148 | D14: -3.2837285 | E14: 0.10556481 | F14: 8.5977673 | G14: 8.8047432 | H14: 5.4547485 | I14: 4.328467 | J14: 6.8518117 | K14: 11.850879 | L14: -11.945275 | M14: 4.8434853 | N14: 11.714548 | O14: -1.8307519 | P14: 0.60537729 | Q14: -1.2348248 | R14: -11.325628 | S14: 0.26641762 | T14: 0.86833557 | U14: 0.7997437 | V14: 0.60042266 | W14: 1.0374401
B15: TMG_R_PCH_WX | C15: 12.684379 | D15: -0.46226359 | E15: 3.8566739 | F15: 4.9535928 | G15: 9.3861126 | H15: 6.5110056 | I15: 7.4916234 | J15: 4.5793737 | K15: -0.94888686 | L15: -13.074796 | M15: 12.84731 | N15: 5.647428 | O15: 0.57273842 | P15: 1.3281048 | Q15: 3.0937209 | R15: 4.5286887 | S15: 4.8992044 | T15: 4.9343136 | U15: 4.9866684 | V15: 5.1315873 | W15: 5.1795196
B16: TMGXO_D_PCH_WX | C16: -3.794931 | D16: -2.0254949 | E16: -0.43861343 | F16: 8.0746013 | G16: 6.7769749 | H16: 2.1592271 | I16: 2.2265929 | J16: 6.3069626 | K16: 8.0289297 | L16: -7.1889656 | M16: 1.9221953 | N16: 8.6021632 | O16: -2.581096 | P16: 1.1289043 | Q16: -0.19988255 | R16: -6.8269783 | S16: -0.37898525 | T16: 0.29950054 | U16: 0.30637417 | V16: 0.39402208 | W16: 1.0817565
B17: TMGXO_R_PCH_WX | C17: 13.083889 | D17: -1.225523 | E17: 4.8494541 | F17: 4.4034543 | G17: 10.447292 | H17: 7.3644533 | I17: 8.3651941 | J17: 5.2962002 | K17: -1.1871457 | L17: -14.23071 | M17: 14.788848 | N17: 6.1709275 | O17: 1.2840104 | P17: 1.794893 | Q17: 3.8867431 | R17: 3.5760386 | S17: 5.7547101 | T17: 5.4403154 | U17: 5.5076978 | V17: 5.4778191 | W17: 5.3679664
... B23: TXGXO_R_PCH_WM | C23: 11.77271 | D23: 0.39200414 | E23: 3.079096 | F23: 2.8110915 | G23: 9.4776145 | H23: 6.1714438 | I23: 8.6994482 | J23: 6.0715856 | K23: 0.70518677 | L23: -13.82484 | M23: 13.320808 | N23: 5.5440297 | O23: 1.3613039 | P23: 1.6433003 | Q23: 3.0224367 | R23: 1.8825945 | S23: 4.0750275 | T23: 4.0934567 | U23: 4.183384 | V23: 4.3366668 | W23: 4.1769681
A24: World | B24: LULCM_USD_PCH_WX | C24: -7.0538333 | D24: -0.86721557 | E24: 1.5336541 | F24: 10.306129 | G24: 5.1347882 | H24: 0.22999775 | I24: 0.29708135 | J24: 5.5252774 | K24: 7.2178431 | L24: 2.5533598 | M24: -5.4751055 | N24: 4.0160947 | O24: -1.0809918 | P24: 1.730205 | Q24: 0.26881521 | R24: -7.9293131 | S24: 1.2649076 | T24: 2.2018988 | U24: 2.1594757 | V24: 1.8827494 | W24: 2.3955062
B25: NGDP_D_PCH_WM | C25: 12.149272 | D25: 3.2219976 | E25: 3.7274194 | F25: 4.8247504 | G25: 5.9040152 | H25: 5.6053744 | I25: 6.9658695 | J25: 6.5563528 | K25: 9.1496474 | L25: 4.0588983 | M25: 5.5689511 | N25: 8.3025504 | O25: 5.9841285 | P25: 3.225412 | Q25: 3.1584376 | R25: 1.8628597 | S25: 3.76009 | T25: 3.5574661 | U25: 3.5459378 | V25: 3.4674574 | W25: 3.5259031
B26: NGDP_D_USD_PCH_WM | C26: -2.5667471 | D26: -3.4246159 | E26: 2.0150472 | F26: 8.7465 | G26: 9.3301704 | H26: 6.6582185 | I26: 7.0028353 | J26: 11.961967 | K26: 10.084044 | L26: -3.6375508 | M26: 4.0884951 | N26: 4.9345932 | O26: 4.0674484 | P26: 1.3242872 | Q26: 1.3522731 | R26: -7.5659238 | S26: 1.628054 | T26: 2.5095923 | U26: 2.4593594 | V26: 2.4990624 | W26: 2.9924632
B27: NGDP_R_PCH_WX | C27: 3.7666417 | D27: 2.7463393 | E27: 4.5058312 | F27: 5.4396667 | G27: 6.4591566 | H27: 6.2701954 | I27: 6.5679144 | J27: 6.9839704 | K27: 4.873127 | L27: 1.7412603 | M27: 6.3323288 | N27: 5.2911687 | O27: 4.7504048 | P27: 5.0131781 | Q27: 5.3151313 | R27: 4.9559147 | S27: 4.8256485 | T27: 4.8536002 | U27: 4.7998265 | V27: 4.6614286 | W27: 4.4379531
B28: NTDD_R_PCH_WX | C28: 4.2452048 | D28: 3.6662943 | E28: 3.4528754 | F28: 5.5150374 | G28: 6.4616846 | H28: 7.5295595 | I28: 7.4075751 | J28: 7.6676634 | K28: 5.6761608 | L28: 2.4521054 | M28: 7.6630866 | N28: 5.8810541 | O28: 5.3832785 | P28: 5.478228 | Q28: 5.180167 | R28: 5.4324569 | S28: 4.8130244 | T28: 4.9285493 | U28: 4.9476908 | V28: 4.7481555 | W28: 4.5958427
B29: PCPI_PCH_WM | C29: 10.218142 | D29: 7.8456469 | E29: 2.8731896 | F29: 4.6389373 | G29: 4.1389161 | H29: 5.2619373 | I29: 5.1705386 | J29: 5.2986868 | K29: 9.0763509 | L29: 6.3996809 | M29: 3.8978763 | N29: 8.447386 | O29: 6.7191248 | P29: 3.9884893 | Q29: 3.7839932 | R29: 3.7022051 | S29: 3.8546731 | T29: 3.7101176 | U29: 3.6858241 | V29: 3.7256815 | W29: 3.7623841
B30: PCPI_USD_PCH_WM | C30: -4.5810231 | D30: -1.2148726 | E30: 1.209006 | F30: 8.5439187 | G30: 7.4922825 | H30: 6.3649503 | I30: 5.210442 | J30: 10.638436 | K30: 9.9973695 | L30: -1.3996941 | M30: 2.4408434 | N30: 4.9067565 | O30: 4.7690615 | P30: 2.0567482 | Q30: 2.0422141 | R30: -5.7408408 | S30: 1.7166454 | T30: 2.6619207 | U30: 2.5982742 | V30: 2.7561882 | W30: 3.2293345
B31: TM_D_PCH_WX | C31: 1.5875514 | D31: 19.984052 | E31: 12.712992 | F31: 11.148423 | G31: 10.590349 | H31: 6.1243697 | I31: 4.9242422 | J31: 7.5177886 | K31: 12.159416 | L31: -8.1757434 | M31: 8.1886006 | N31: 11.82035 | O31: 0.4703814 | P31: -1.6097154 | Q31: -2.0318041 | R31: -9.836507 | S31: 0.45408175 | T31: 1.7665519 | U31: 1.5788321 | V31: 1.2907938 | W31: 1.2328554
B32: TM_R_PCH_WX | C32: 18.133279 | D32: -5.2313076 | E32: 2.2142298 | F32: 11.524492 | G32: 15.610035 | H32: 15.085332 | I32: 10.178258 | J32: 19.892858 | K32: 3.6235536 | L32: -7.6039433 | M32: 20.492313 | N32: 5.8969855 | O32: 1.3648583 | P32: 5.3828373 | Q32: 7.873037 | R32: 7.6238726 | S32: 4.9180281 | T32: 5.6670291 | U32: 5.6430817 | V32: 5.3655171 | W32: 5.3811063
B33: TMG_D_PCH_WX | C33: 3.9446907 | D33: -3.0413259 | E33: -0.58352377 | F33: 8.3796694 | G33: 10.093198 | H33: 5.9953012 | I33: 5.0977994 | J33: 7.4019174 | K33: 12.155714 | L33: -8.2446772 | M33: 9.6377811 | N33: 12.19492 | O33: -0.016092963 | P33: -2.7948406 | Q33: -2.1923363 | R33: -9.4620105 | S33: -0.11153088 | T33: 1.5185747 | U33: 1.3164747 | V33: 0.79634718 | W33: 0.55092311
B34: TMG_R_PCH_WX | C34: 19.123397 | D34: 6.8201789 | E34: 12.288284 | F34: 12.701187 | G34: 16.837434 | H34: 14.393183 | I34: 10.78307 | J34: 19.258939 | K34: 2.8711971 | L34: -8.5086848 | M34: 20.326174 | N34: 6.8659374 | O34: 1.5195069 | P34: 6.9148759 | Q34: 6.7764161 | R34: 5.2105954 | S34: 4.8024203 | T34: 5.8732438 | U34: 5.8448798 | V34: 5.5792609 | W34: 5.6168606
B35: TMGXO_D_PCH_WX | C35: -2.2554655 | D35: -2.890336 | E35: -1.023247 | F35: 7.1977005 | G35: 8.376459 | H35: 2.5497909 | I35: 2.967434 | J35: 7.2703597 | K35: 8.6196564 | L35: -4.1091491 | M35: 7.7452198 | N35: 9.3127541 | O35: -0.39309747 | P35: -2.9648723 | Q35: -1.5747081 | R35: -4.5562934 | S35: -0.39246589 | T35: 0.96712038 | U35: 0.87779512 | V35: 0.58388016 | W35: 0.44635836
B36: TMGXO_R_PCH_WX | C36: 21.491633 | D36: 7.4967174 | E36: 13.808612 | F36: 12.698988 | G36: 18.209683 | H36: 15.496804 | I36: 10.657108 | J36: 20.79619 | K36: 2.9429546 | L36: -9.5125661 | M36: 21.248848 | N36: 7.4008843 | O36: 1.510718 | P36: 6.9179515 | Q36: 6.7268005 | R36: 4.3187755 | S36: 5.4361159 | T36: 6.2082582 | U36: 6.1839007 | V36: 5.8586954 | W36: 5.7897186
... B42: TXGXO_R_PCH_WM | C42: 11.194924 | D42: 11.095186 | E42: 10.391047 | F42: 8.1867739 | G42: 13.59282 | H42: 12.378609 | I42: 7.365323 | J42: 14.839894 | K42: 6.912595 | L42: -5.9998918 | M42: 6.9588078 | N42: 8.2881963 | O42: 6.8177888 | P42: 3.0952202 | Q42: 4.571133 | R42: 5.9636983 | S42: 5.7877376 | T42: 7.5701631 | U42: 7.451315 | V42: 6.7527534 | W42: 6.5364295
A43: WORLD PRICES
B44: 2000 | C44: 2001 | D44: 2002 | E44: 2003 | F44: 2004 | G44: 2005 | H44: 2006 | I44: 2007 | J44: 2008 | K44: 2009 | L44: 2010 | M44: 2011 | N44: 2012 | O44: 2013 | P44: 2014 | Q44: 2015 | R44: 2016 | S44: 2017 | T44: 2018 | U44: 2019 | V44: 2020
A45: PMPNF_PCH_WM | B45: 1.9973738 | C45: -3.7784237 | D45: 3.25357 | E45: 6.0057336 | F45: 16.055311 | G45: 6.5539897 | H45: 24.988696 | I45: 16.459544 | J45: 15.231602 | K45: -17.901435 | L45: 21.379802 | M45: 19.948315 | N45: -8.121452 | O45: -3.033414 | P45: -7.2138345 | Q45: -17.586013 | R45: -6.1221617 | S45: 0.99066482 | T45: 0.37838184 | U45: -0.37293567 | V45: -0.38265745
A46: PXPNF_PCH_WX | B46: 2.9847896 | C46: -13.770719 | D46: -2.6936736 | E46: 8.0748768 | F46: 20.372993 | G46: 17.739216 | H46: 30.962578 | I46: 12.105071 | J46: 4.5301857 | K46: -11.61501 | L46: 31.319964 | M46: 19.718485 | N46: -15.347391 | O46: -10.146088 | P46: -2.504969 | Q46: -12.847093 | R46: -3.9316148 | S46: 1.6862304 | T46: 1.2030755 | U46: 0.24548669 | V46: 0.22102179
A47: TMGCB_D_PCH | B47: 10.223722 | C47: -4.7311741 | D47: 1.193669 | E47: 9.1218725 | F47: 12.886417 | G47: 11.043202 | H47: 10.358165 | I47: 8.7161621 | J47: 13.986883 | K47: -14.161336 | L47: 11.149352 | M47: 13.989954 | N47: -0.97714228 | O47: -1.4142921 | P47: -3.2263025 | Q47: -14.803352 | R47: -1.3016194 | S47: 2.7405151 | T47: 2.1671131 | U47: 1.1515789 | V47: 0.56670033
A48: TXGCB_D_PCH | B48: 0.8195111 | C48: -9.3683868 | D48: -1.6430878 | E48: 7.9936361 | F48: 14.997139 | G48: 11.989097 | H48: 20.325006 | I48: 9.7090196 | J48: 5.1376326 | K48: -9.3845387 | L48: 20.5191 | M48: 14.705032 | N48: -9.3949428 | O48: -6.7591321 | P48: -1.7854912 | Q48: -9.3392098 | R48: -2.2537023 | S48: 1.3725057 | T48: 1.0475506 | U48: 0.41608718 | V48: 0.37182576
A49: TXGM_D_PCH | B49: -2.8034675 | C49: -2.0023343 | D49: 0.11476907 | E49: 7.8577029 | F49: 6.0021739 | G49: 2.3679047 | H49: 2.526052 | I49: 5.6999077 | J49: 6.1540225 | K49: -5.6524784 | L49: 2.4469205 | M49: 6.3164418 | N49: 0.56478821 | O49: -1.0920232 | P49: -0.58164945 | Q49: -3.4697627 | R49: 0.55380768 | S49: 0.8475764 | T49: 0.78732376 | U49: 0.70153866 | V49: 0.62415337
A50: POILAPSP_PCH | B50: 57.023683 | C50: -13.824858 | D50: 2.544782 | E50: 15.798263 | F50: 30.695125 | G50: 41.298111 | H50: 20.463881 | I50: 10.665526 | J50: 36.424027 | K50: -36.335406 | L50: 27.928227 | M50: 31.605762 | N50: 0.96068657 | O50: -0.89328372 | P50: -7.516202 | Q50: -46.364141 | R50: -2.4480189 | S50: 10.051601 | T50: 7.9689926 | U50: 3.9107585 | V50: 1.2681357

Sheet QuarterlyDataSheet
A2: QUARTERLY
C4: 2011Q1 | D4: 2011Q2 | E4: 2011Q3 | F4: 2011Q4 | G4: 2012Q1 | H4: 2012Q2 | I4: 2012Q3 | J4: 2012Q4 | K4: 2013Q1 | L4: 2013Q2 | M4: 2013Q3 | N4: 2013Q4 | O4: 2014Q1 | P4: 2014Q2 | Q4: 2014Q3 | R4: 2014Q4 | S4: 2015Q1 | T4: 2015Q2 | U4: 2015Q3 | V4: 2015Q4 | W4: 2016Q1 | X4: 2016Q2 | Y4: 2016Q3 | Z4: 2016Q4
A5: Advanced Economies | B5: LULCM_USD_YOY_WX | C5: 0.18753058 | D5: 8.6329068 | E5: 6.4252605 | F5: 1.3252699 | G5: 0.51882943 | H5: -2.7915839 | I5: -2.8989415 | J5: 1.4707676 | K5: 1.98268 | L5: 1.0624199 | M5: 2.7469386 | N5: 1.8057311 | O5: 2.0705116 | P5: 3.2629395 | Q5: 0.61213786 | R5: -3.8026466 | S5: -8.9394338 | T5: -9.6866813 | U5: -7.9113741 | V5: -4.6496212 | W5: 0.22863394 | X5: 1.4177109 | Y5: 1.7570951 | Z5: 1.7663829
B6: NGDP_D_USD_YOY_WM | C6: 2.9569204 | D6: 12.424891 | E6: 9.3879364 | F6: 1.4912686 | G6: -0.78102366 | H6: -6.0567252 | I6: -5.9808454 | J6: -0.30332 | K6: 1.2797407 | L6: 1.919192 | M6: 3.4832424 | N6: 2.6699822 | O6: 2.4111122 | P6: 3.8219396 | Q6: 0.93807429 | R6: -5.7406275 | S6: -12.669571 | T6: -13.818823 | U6: -12.194317 | V6: -7.2652929 | W6: 0.32596515 | X6: 1.3694483 | Y6: 2.085394 | Z6: 2.0434211
B7: NGDP_D_YOY_WM | C7: 1.6064659 | D7: 1.5086729 | E7: 1.5078848 | F7: 1.5164472 | G7: 1.6104458 | H7: 1.3794057 | I7: 1.2837115 | J7: 1.4970058 | K7: 1.233062 | L7: 1.5444258 | M7: 1.5075411 | N7: 1.1564323 | O7: 1.2828651 | P7: 1.0505531 | Q7: 1.2164409 | R7: 1.0542719 | S7: 0.78017749 | T7: 0.87640368 | U7: 0.80188213 | V7: 1.0693776 | W7: 1.5485508 | X7: 1.2758153 | Y7: 1.3196164 | Z7: 1.3407119
B8: NGDP_R_YOY_WX | C8: 3.206687 | D8: 2.2460513 | E8: 1.9035667 | F8: 1.595927 | G8: 1.3114454 | H8: 1.1003879 | I8: 1.1058688 | J8: 0.74305075 | K8: 0.67951245 | L8: 1.0555216 | M8: 1.3712422 | N8: 1.8884713 | O8: 1.7618572 | P8: 1.7459692 | Q8: 1.778603 | R8: 1.6924943 | S8: 1.8071794 | T8: 1.9658726 | U8: 1.8833508 | V8: 2.0577019 | W8: 2.3734945 | X8: 2.3099346 | Y8: 2.2547407 | Z8: 2.0529329
B9: NTDD_R_YOY_WX | C9: 3.0132759 | D9: 2.4697251 | E9: 2.3852287 | F9: 2.069197 | G9: 1.7711638 | H9: 0.9846071 | I9: 0.78679732 | J9: 0.39148894 | K9: 0.33855031 | L9: 0.99371196 | M9: 1.2560391 | N9: 1.5940641 | O9: 1.6517689 | P9: 1.4522614 | Q9: 1.8932204 | R9: 1.9714302 | S9: 2.085097 | T9: 2.1676368 | U9: 2.0275443 | V9: 2.6222957 | W9: 2.8933624 | X9: 3.010023 | Y9: 2.8437309 | Z9: 1.1413058
B10: PCPI_USD_YOY_WM | C10: 3.8265391 | D10: 13.964214 | E10: 11.185982 | F10: 2.8907274 | G10: 0.22918359 | H10: -5.3310569 | I10: -5.3246448 | J10: 0.20478259 | K10: 1.7297069 | L10: 1.8306029 | M10: 3.532681 | N10: 2.6643109 | O10: 2.1641333 | P10: 4.0037 | Q10: 0.72430923 | R10: -6.0723301 | S10: -13.265905 | T10: -14.466409 | U10: -12.607928 | V10: -7.5105165 | W10: 0.26132365 | X10: 1.3339846 | Y10: 2.0606913 | Z10: 2.014826
B11: PCPI_YOY_WM | C11: 2.4680241 | D11: 2.8940356 | E11: 3.1734067 | F11: 2.9174796 | G11: 2.642273 | H11: 2.1608441 | I11: 1.99094 | J11: 2.013998 | K11: 1.6874764 | L11: 1.4602781 | M11: 1.5588888 | N11: 1.1521538 | O11: 1.0378742 | P11: 1.2248522 | Q11: 0.99838243 | R11: 0.69811768 | S11: 0.090559076 | T11: 0.11979415 | U11: 0.33063257 | V11: 0.80331443 | W11: 1.4857651 | X11: 1.2413885 | Y11: 1.2952122 | Z11: 1.3119918
B12: TM_D_YOY_WX | C12: 14.934772 | D12: 11.744826 | E12: 8.6434154 | F12: 5.6280825 | G12: -2.4896411 | H12: -1.8824575 | I12: -1.271493 | J12: -0.65672416 | K12: 1.3706631 | L12: 1.0411524 | M12: 0.7127128 | N12: 0.38534083 | O12: 3.9122523 | P12: 0.96886751 | Q12: -1.891144 | R12: -4.6701437 | S12: -15.089957 | T12: -12.477965 | U12: -9.785624 | V12: -7.0104612 | W12: -0.06934235 | X12: 0.1018172 | Y12: 0.2732699 | Z12: 0.44501627
B13: TM_R_YOY_WX | C13: 7.0401898 | D13: 5.9210076 | E13: 4.8135273 | F13: 3.7176265 | G13: 0.77628817 | H13: 0.9374592 | I13: 1.098888 | J13: 1.260575 | K13: 1.1727104 | L13: 1.5008148 | M13: 1.8299832 | N13: 2.1602191 | O13: 2.3605904 | P13: 2.7732934 | Q13: 3.1876604 | R13: 3.603698 | S13: 4.6034665 | T13: 4.6378166 | U13: 4.6721781 | V13: 4.7065508 | W13: 4.8025619 | X13: 4.7957572 | Y13: 4.7889529 | Z13: 4.7821491
B14: TMG_D_YOY_WX | C14: 17.332973 | D14: 13.59548 | E14: 9.9770401 | F14: 6.4738609 | G14: -2.7561887 | H14: -2.1511212 | I14: -1.5422888 | J14: -0.92966824 | K14: 1.2877915 | L14: 0.82497365 | M14: 0.36427053 | N14: -0.094327489 | O14: 2.8290685 | P14: 0.067278468 | Q14: -2.6203352 | R14: -5.2357647 | S14: -15.356177 | T14: -12.691125 | U14: -9.9421619 | V14: -7.1066464 | W14: 0.033639846 | X14: 0.18398756 | Y14: 0.33456125 | Z14: 0.48536124
B15: TMG_R_YOY_WX | C15: 7.6305834 | D15: 6.310578 | E15: 5.0067614 | F15: 3.7189351 | G15: 0.2732557 | H15: 0.46251646 | I15: 0.65213444 | J15: 0.84211031 | K15: 0.66158447 | L15: 1.0995582 | M15: 1.5394376 | N15: 1.9812309 | O15: 2.5634864 | P15: 2.9128612 | Q15: 3.263426 | R15: 3.615185 | S15: 4.3567177 | T15: 4.4551129 | U15: 4.5536009 | V15: 4.6521817 | W15: 4.8765493 | X15: 4.8865965 | Y15: 4.8966446 | Z15: 4.9066937
B16: TMGXO_D_YOY_WX | C16: 13.15166 | D16: 10.114439 | E16: 7.1587427 | F16: 4.2823837 | G16: -3.9753531 | H16: -3.0632845 | I16: -2.1425529 | J16: -1.2130759 | K16: 1.6124228 | L16: 1.2817625 | M16: 0.95217815 | N16: 0.62366632 | O16: 2.429803 | P16: 0.66115663 | Q16: -1.0769507 | R16: -2.7850463 | S16: -9.1910322 | T16: -7.6376281 | U16: -6.057651 | V16: -4.4506464 | W16: -0.64269268 | X16: -0.47305113 | Y16: -0.30311993 | Z16: -0.1328986
B17: TMGXO_R_YOY_WX | C17: 8.0822915 | D17: 6.8085815 | E17: 5.5498816 | F17: 4.3060151 | G17: 1.0518135 | H17: 1.1847639 | I17: 1.3178893 | J17: 1.4511897 | K17: 1.0036806 | L17: 1.5206198 | M17: 2.0402047 | N17: 2.5624489 | O17: 4.0438643 | P17: 3.9401041 | Q17: 3.8364474 | R17: 3.732894 | S17: 2.6434194 | T17: 3.2054211 | U17: 3.7705 | V17: 4.3386728 | W17: 5.8597274 | X17: 5.7833603 | Y17: 5.7070483 | Z17: 5.6307914
... B24: TXGXO_R_YOY_WM | C24: 7.1420516 | D24: 6.0667987 | E24: 5.0023367 | F24: 3.9485575 | G24: 1.2400973 | H24: 1.3100524 | I24: 1.3800558 | J24: 1.4501076 | K24: 1.1182802 | L24: 1.4616311 | M24: 1.8061479 | N24: 2.1518346 | O24: 3.4505583 | P24: 3.1606737 | Q24: 2.8716015 | R24: 2.5833393 | S24: 1.0405198 | T24: 1.5863505 | U24: 2.1351299 | V24: 2.6868738 | W24: 4.0654058 | X24: 4.0700958 | Y24: 4.0747861 | Z24: 4.0794765
A25: World | B25: LULCM_USD_YOY_WX | C25: 0.47657202 | D25: 8.5119492 | E25: 6.311051 | F25: 1.3338489 | G25: 0.33305037 | H25: -2.8276444 | I25: -2.9122194 | J25: 1.3021376 | K25: 1.8857771 | L25: 0.97254672 | M25: 2.5590361 | N25: 1.6261109 | O25: 1.9656619 | P25: 3.0085114 | Q25: 0.36581543 | R25: -3.9666715 | S25: -9.3533173 | T25: -9.9246825 | U25: -8.0765746 | V25: -4.7974773 | W25: 0.25078672 | X25: 1.4132401 | Y25: 1.7597526 | Z25: 1.7891573
B26: NGDP_D_USD_YOY_WM | C26: 3.2298837 | D26: 6.52171 | E26: 6.1508931 | F26: 4.2357538 | G26: 6.4260666 | H26: 3.6175159 | I26: 2.5309942 | J26: 3.2433614 | K26: 0.68851175 | L26: 1.1602198 | M26: 1.88918 | N26: 1.6618097 | O26: 4.4218801 | P26: 3.3643296 | Q26: 0.7846197 | R26: -2.7396415 | S26: -9.9396243 | T26: -8.9764744 | U26: -7.24425 | V26: -4.336489 | W26: 1.0813104 | X26: 1.5519611 | Y26: 1.8722513 | Z26: 2.0082454
B27: NGDP_D_YOY_WM | C27: 9.1909594 | D27: 8.6143206 | E27: 8.0306301 | F27: 7.3985069 | G27: 7.0408517 | H27: 6.3077069 | I27: 5.5653932 | J27: 4.9468904 | K27: 3.0979628 | L27: 3.3099783 | M27: 3.3920285 | N27: 3.1264296 | O27: 3.9009062 | P27: 3.4613416 | Q27: 2.8897099 | R27: 2.4002448 | S27: 1.0611589 | T27: 1.6336369 | U27: 2.0102171 | V27: 2.6236701 | W27: 3.911159 | X27: 3.7727524 | Y27: 3.6791441 | Z27: 3.6228031
B28: NGDP_R_YOY_WX | C28: 5.5256792 | D28: 5.223937 | E28: 5.3451754 | F28: 5.0194342 | G28: 4.6434871 | H28: 4.6731416 | I28: 4.6992492 | J28: 4.955721 | K28: 4.8018063 | L28: 4.9091065 | M28: 5.1200319 | N28: 5.1413357 | O28: 5.379256 | P28: 5.3950532 | Q28: 5.2314962 | R28: 5.1802917 | S28: 5.2040769 | T28: 5.0174468 | U28: 4.8416447 | V28: 4.7020947 | W28: 4.5907624 | X28: 4.7468538 | Y28: 4.8782673 | Z28: 5.008143
B29: NTDD_R_YOY_WX | C29: 7.3132902 | D29: 5.3742554 | E29: 5.5823835 | F29: 5.6835014 | G29: 5.4516666 | H29: 5.8648681 | I29: 5.7342514 | J29: 4.7883108 | K29: 5.2797021 | L29: 5.9059704 | M29: 5.4650215 | N29: 5.3948221 | O29: 5.4152858 | P29: 4.596341 | Q29: 5.0067495 | R29: 5.7540698 | S29: 6.0937206 | T29: 5.8169084 | U29: 5.3189497 | V29: 4.6529305 | W29: 4.2275602 | X29: 4.6183738 | Y29: 5.071659 | Z29: 5.4239364
B30: PCPI_USD_YOY_WM | C30: 2.5946948 | D30: 6.378753 | E30: 6.4282206 | F30: 4.5956138 | G30: 7.1785201 | H30: 4.2132923 | I30: 3.1349366 | J30: 3.9458824 | K30: 1.4653746 | L30: 1.7507137 | M30: 2.5725356 | N30: 2.3776332 | O30: 4.3973193 | P30: 3.8395736 | Q30: 1.6187841 | R30: -1.4733417 | S30: -7.6397144 | T30: -7.1241366 | U30: -5.6507963 | V30: -3.1680372 | W30: 1.2203933 | X30: 1.5762211 | Y30: 1.9708572 | Z30: 2.0938791
B31: PCPI_YOY_WM | C31: 8.6122534 | D31: 8.5439244 | E31: 8.3653229 | F31: 7.8157323 | G31: 7.8072972 | H31: 6.927984 | I31: 6.2014372 | J31: 5.675664 | K31: 3.9156125 | L31: 3.9324589 | M31: 4.1084593 | N31: 3.8779081 | O31: 3.8351322 | P31: 3.8886248 | Q31: 3.6837249 | R31: 3.6609815 | S31: 3.5569268 | T31: 3.6245658 | U31: 3.6951997 | V31: 3.8254752 | W31: 4.0568676 | X31: 3.7994971 | Y31: 3.7814878 | Z31: 3.7114286
B32: TM_D_YOY_WX | C32: 16.430693 | D32: 13.360604 | E32: 10.371468 | F32: 7.4611508 | G32: 1.258296 | H32: 0.72885352 | I32: 0.20217927 | J32: -0.3217412 | K32: -1.4833623 | L32: -1.5814066 | M32: -1.6793534 | N32: -1.7772027 | O32: 1.0444245 | P32: -1.0406504 | Q32: -3.0826994 | R32: -5.0826102 | S32: -13.401129 | T32: -11.023969 | U32: -8.5815554 | V32: -6.0720971 | W32: -0.056424767 | X32: 0.27234809 | Y32: 0.60220248 | Z32: 0.93314196
B33: TM_R_YOY_WX | C33: 7.6724821 | D33: 6.4706681 | E33: 5.2822684 | F33: 4.1071333 | G33: -0.28376834 | H33: 0.73181613 | I33: 1.7577441 | J33: 2.7941208 | K33: 4.4983448 | L33: 5.0578784 | M33: 5.6204081 | N33: 6.1859498 | O33: 7.6988439 | P33: 7.6873994 | Q33: 7.6759562 | R33: 7.6645141 | S33: 8.5999685 | T33: 7.9243007 | U33: 7.2528365 | V33: 6.58555 | W33: 4.6207966 | X33: 4.8051951 | Y33: 4.9899186 | Z33: 5.1749676
B34: TMG_D_YOY_WX | C34: 17.192703 | D34: 13.864302 | E34: 10.63043 | F34: 7.4884049 | G34: 1.046142 | H34: 0.33008117 | I34: -0.38090537 | J34: -1.0868535 | K34: -3.0777061 | L34: -2.9128047 | M34: -2.7476226 | N34: -2.5821596 | O34: 0.72569632 | P34: -1.2374127 | Q34: -3.1622615 | R34: -5.0495956 | S34: -12.817605 | T34: -10.619639 | U34: -8.3662603 | V34: -6.0560709 | W34: -0.74146104 | X34: -0.33292478 | Y34: 0.077292965 | Z34: 0.48919912
B35: TMG_R_YOY_WX | C35: 8.8982111 | D35: 7.5095692 | E35: 6.1386349 | F35: 4.7851823 | G35: -0.54137549 | H35: 0.77975561 | I35: 2.1184356 | J35: 3.4748976 | K35: 6.944392 | L35: 6.8792635 | M35: 6.8141746 | N35: 6.7491254 | O35: 7.1723654 | P35: 6.8163116 | Q35: 6.4614407 | R35: 6.1077489 | S35: 5.3229027 | T35: 5.2286875 | U35: 5.1345565 | V35: 5.0405098 | W35: 4.3927646 | X35: 4.6536014 | Y35: 4.9150899 | Z35: 5.1772317
B36: TMGXO_D_YOY_WX | C36: 13.229474 | D36: 10.619712 | E36: 8.0701016 | F36: 5.5792555 | G36: 0.58451638 | H36: -0.073852524 | I36: -0.72791212 | J36: -1.3776906 | K36: -3.549766 | L36: -3.188909 | M36: -2.8267018 | N36: -2.4631395 | O36: -0.3037945 | P36: -1.1274266 | Q36: -1.9442543 | R36: -2.7543339 | S36: -6.2858597 | T36: -5.2218798 | U36: -4.14582 | V36: -3.0575431 | W36: -0.9047354 | X36: -0.56702736 | Y36: -0.22816844 | Z36: 0.11184528
B37: TMGXO_R_YOY_WX | C37: 9.6594855 | D37: 8.1243871 | E37: 6.6107782 | F37: 5.118358 | G37: -0.56626065 | H37: 0.75911848 | I37: 2.1021639 | J37: 3.4631112 | K37: 6.9518111 | L37: 6.8794892 | M37: 6.8072163 | N37: 6.7349923 | O37: 7.4784616 | P37: 6.8998788 | Q37: 6.3244108 | R37: 5.7520405 | S37: 3.8553719 | T37: 4.1401903 | U37: 4.4257898 | V37: 4.7121726 | W37: 5.1281883 | X37: 5.3170093 | Y37: 5.5061695 | Z37: 5.6956694
... B44: TXGXO_R_YOY_WM | C44: 8.683811 | D44: 8.3395563 | E44: 7.9963921 | F44: 7.6543148 | G44: 8.0275528 | H44: 7.1059453 | I44: 6.1922003 | J44: 5.2862506 | K44: 2.4233659 | L44: 2.814449 | M44: 3.2070254 | N44: 3.6011007 | O44: 4.0280028 | P44: 4.3689839 | Q44: 4.7110828 | R44: 5.0543029 | S44: 5.9682906 | T44: 5.9340065 | U44: 5.8997335 | V44: 5.8654716 | W44: 5.1080419 | X44: 5.5394631 | Y44: 5.9726552 | Z44: 6.4076252
B47: 2011Q1 | C47: 2011Q2 | D47: 2011Q3 | E47: 2011Q4 | F47: 2012Q1 | G47: 2012Q2 | H47: 2012Q3 | I47: 2012Q4 | J47: 2013Q1 | K47: 2013Q2 | L47: 2013Q3 | M47: 2013Q4 | N47: 2014Q1 | O47: 2014Q2 | P47: 2014Q3 | Q47: 2014Q4 | R47: 2015Q1 | S47: 2015Q2 | T47: 2015Q3 | U47: 2015Q4 | V47: 2016Q1 | W47: 2016Q2 | X47: 2016Q3 | Y47: 2016Q4
A48: PMPNF_YOY_WM | B48: 33.555511 | C48: 32.3208 | D48: 23.150919 | E48: -4.5735485 | F48: -12.407242 | G48: -13.72749 | H48: -8.0435593 | I48: 3.3168997 | J48: 2.4945465 | K48: 0.17587882 | L48: -6.3871409 | M48: -8.256431 | N48: -8.8841344 | O48: -4.6392797 | P48: -6.4800619 | Q48: -8.854567 | R48: -15.438246 | S48: -18.963019 | T48: -19.001829 | U48: -16.940598 | V48: -11.123926 | W48: -8.5947905 | X48: -3.3114677 | Y48: -0.69754116
A49: PXPNF_YOY_WX | B49: 35.204745 | C49: 30.675127 | D49: 22.835037 | E49: -5.2014779 | F49: -15.320427 | G49: -19.425434 | H49: -18.681538 | I49: -6.8102754 | J49: -6.7093941 | K49: -10.032232 | L49: -11.089105 | M49: -13.028067 | N49: -10.411022 | O49: -0.039693315 | P49: 1.5507367 | Q49: -0.066077562 | R49: -10.526501 | S49: -13.087227 | T49: -14.288421 | U49: -13.513401 | V49: -7.8838695 | W49: -6.4241005 | X49: -2.3789955 | Y49: 1.3422147
A50: TMGCB_D_YOY | B50: 16.892286 | C50: 18.456318 | D50: 15.175391 | E50: 6.0077877 | F50: 1.4975506 | G50: -3.2946173 | H50: -1.3757731 | I50: 0.11672004 | J50: -1.4205457 | K50: -1.3640572 | L50: -0.97405994 | M50: -1.583288 | N50: -2.0928214 | O50: 0.43762939 | P50: -2.8396487 | Q50: -8.3125023 | R50: -16.011647 | S50: -14.68863 | T50: -17.45788 | U50: -12.911244 | V50: -3.9491767 | W50: -5.0634691 | X50: 1.5467512 | Y50: 3.9315671
A51: TXGCB_D_YOY | B51: 24.580586 | C51: 21.734561 | D51: 16.529594 | E51: -1.4633694 | F51: -8.9940672 | G51: -12.1351 | H51: -11.916537 | I51: -4.4855388 | J51: -4.5548383 | K51: -6.7176749 | L51: -7.399654 | M51: -8.5991266 | N51: -6.6471458 | O51: -0.089512257 | P51: 0.79026043 | Q51: -0.47653307 | R51: -7.672366 | S51: -9.6229729 | T51: -10.504449 | U51: -9.8313311 | V51: -5.5519172 | W51: -4.038717 | X51: -0.94027411 | Y51: 1.6969845
A52: TXGM_D_YOY | B52: 7.9070545 | C52: 7.3768698 | D52: 5.9225706 | E52: 4.1800574 | F52: 2.0409719 | G52: 0.84743811 | H52: -1.7872078e-05 | I52: -0.59759245 | J52: -0.97190333 | K52: -1.1969532 | L52: -1.1989575 | M52: -1.0001223 | N52: -0.34683693 | O52: -0.24550712 | P52: -0.51821336 | Q52: -1.2182554 | R52: -2.831786 | S52: -3.6504421 | T52: -3.9417953 | U52: -3.4582197 | V52: -1.5550585 | W52: 0.050697384 | X52: 1.4899361 | Y52: 2.2764455
A53: POILAPSP_YOY | B53: 29.379747 | C53: 40.933257 | D53: 36.493292 | E53: 20.764326 | F53: 12.821252 | G53: -6.5713949 | H53: -0.26453391 | I53: -1.2354663 | J53: -6.5415194 | K53: -3.4649963 | L53: 4.4422958 | M53: 2.554692 | N53: -1.3313377 | O53: 7.0834521 | P53: -6.4828941 | Q53: -28.671316 | R53: -50.110738 | S53: -43.199029 | T53: -52.02562 | U53: -38.043297 | V53: -7.1048344 | W53: -17.632556 | X53: 6.2182391 | Y53: 13.591655

Sheet Annual
A1: Refresh Step:
A2: On EcXL Refresh tab, click on refresh WORKSHEEET. Note that all worksheets will be updated simultaneously.
C3: Rwanda: Selected Composite Indicators of Trading Partners (GEE)
A4: Vintage: | B4: \\RES\GEE\GEE Live | C4: (Annual Percent Change)
A6: DATASET | B6: Series_code | D6: 1980 | E6: 1981 | F6: 1982 | G6: 1983 | H6: 1984 | I6: 1985 | J6: 1986 | K6: 1987 | L6: 1988 | M6: 1989 | N6: 1990 | O6: 1991 | P6: 1992 | Q6: 1993 | R6: 1994 | S6: 1995 | T6: 1996 | U6: 1997 | V6: 1998 | W6: 1999 | X6: 2000 | Y6: 2001 | Z6: 2002 | AA6: 2003 | AB6: 2004 | AC6: 2005 | AD6: 2006 | AE6: 2007 | AF6: 2008 | AG6: 2009 | AH6: 2010 | AI6: 2011 | AJ6: 2012 | AK6: 2013 | AL6: 2014 | AM6: 2015 | AN6: 2016 | AO6: 2017 | AP6: 2018 | AQ6: 2019 | AR6: 2020 | AS6: 2021 | AT6: 2022 | AU6: 2023 | AV6: 2024 | AW6: 2025 | AX6: 2026 | AY6: 2027 | AZ6: 2028 | BA6: 2029 | BB6: 2030
C7: 1) Foreign Output and Demand of Tading Partners 1/
C9: Advanced economy partners | D9: Export-weighted averages | AT9: Export-weighted averages
A11: IMF.RES.GEE:GEE_LIVE | B11: RWA.NGDP_R_PCH_WX.G110.A | C11: Real GDP | D11: 3.7480062 | E11: 2.7345986 | F11: 1.0496061 | G11: 3.1543623 | H11: 4.7156231 | I11: 2.8127686 | J11: 4.7185082 | K11: 5.5937763 | L11: 5.4718568 | M11: 3.5874245 | N11: 3.0231927 | O11: 1.7813659 | P11: 2.072127 | Q11: 2.2005445 | R11: 3.8058507 | S11: 2.5795003 | T11: 2.8343682 | U11: 4.3003738 | V11: 1.5579222 | W11: 3.4767967 | X11: 5.229704 | Y11: 1.7177979 | Z11: 1.4494103 | AA11: 1.9202364 | AB11: 4.1165744 | AC11: 3.6496527 | AD11: 4.1028048 | AE11: 4.2086785 | AF11: 0.93365129 | AG11: -3.4349496 | AH11: 3.6495372 | AI11: 2.3267637 | AJ11: 0.88322274 | AK11: 1.6425245 | AL11: 2.5509341 | AM11: 2.6254816 | AN11: 2.1794577 | AO11: 2.8322718 | AP11: 2.3012221 | AQ11: 1.0766454 | AR11: -5.3186963 | AS11: 6.8699902 | AT11: 2.353009 | AU11: 0.998112 | AV11: 1.4426581 | AW11: 1.8368517 | AX11: 1.6158385 | AY11: 1.5939388 | AZ11: 1.6720278 | BA11: 1.5775596 | BB11: 1.6250545 | BC11: =BA11-AZ11 -> -0.094468219
A12: IMF.RES.GEE:GEE_LIVE | B12: RWA.NTDD_R_PCH_WX.G110.A | C12: Real total domestic demand | D12: 4.1102304 | E12: 1.5286815 | F12: 0.76414839 | G12: 2.6972234 | H12: 3.4764537 | I12: 2.6151897 | J12: 4.9263698 | K12: 5.4056308 | L12: 5.8369759 | M12: 3.5721507 | N12: 3.6151904 | O12: 2.0392062 | P12: 2.4615755 | Q12: 1.5506989 | R12: 4.6658019 | S12: 2.9539293 | T12: 2.516061 | U12: 4.0729296 | V12: 1.7162393 | W12: 2.6130232 | X12: 4.7638702 | Y12: 1.9452445 | Z12: 0.9811314 | AA12: 1.4747322 | AB12: 2.900353 | AC12: 2.7896306 | AD12: 3.3045069 | AE12: 4.0130554 | AF12: 0.66444499 | AG12: -2.2445783 | AH12: 3.2887229 | AI12: 2.5582239 | AJ12: 1.0260848 | AK12: 1.5111899 | AL12: 2.7209151 | AM12: 2.9935874 | AN12: 2.2546917 | AO12: 3.0376186 | AP12: 2.2744409 | AQ12: 1.6571291 | AR12: -5.7991707 | AS12: 5.2176281 | AT12: 2.6425376 | AU12: 1.7513309 | AV12: 1.0806373 | AW12: 1.9655702 | AX12: 1.5161111 | AY12: 1.4447248 | AZ12: 1.4886739 | BA12: 1.4804515 | BB12: 1.4821085 | BC12: =BA12-AZ12 -> -0.0082223285
C14: All countries 2/
A16: IMF.RES.GEE:GEE_LIVE | B16: RWA.NGDP_R_PCH_WX.G001.A | C16: Real GDP | D16: 2.4136552 | E16: 2.9218871 | F16: 0.13114695 | G16: 1.8033037 | H16: 4.7520086 | I16: 1.4700049 | J16: 1.6561739 | K16: 4.3423927 | L16: 2.5639667 | M16: 3.2435712 | N16: 1.479912 | O16: -2.5478864 | P16: -3.0277651 | Q16: -4.8424148 | R16: -0.27997885 | S16: 3.8776297 | T16: 1.6367911 | U16: -0.84260777 | V16: -0.40377937 | W16: 0.4250489 | X16: 0.046691946 | Y16: 0.7038586 | Z16: 3.1363067 | AA16: 5.9415569 | AB16: 7.1729234 | AC16: 7.8165171 | AD16: 6.2140821 | AE16: 6.8938444 | AF16: 5.5947678 | AG16: 0.26584671 | AH16: 7.0178978 | AI16: 6.2766948 | AJ16: 4.4986283 | AK16: 7.1520411 | AL16: 5.6631906 | AM16: 5.3216312 | AN16: 1.7331701 | AO16: 3.195243 | AP16: 4.4063575 | AQ16: 1.672628 | AR16: -1.8666893 | AS16: 6.0746524 | AT16: 6.4920203 | AU16: 5.5482947 | AV16: 3.748194 | AW16: 5.2390496 | AX16: 5.0355391 | AY16: 4.606158 | AZ16: 4.5664382 | BA16: 4.4862613 | BB16: 4.4239718 | BC16: =BA16-AZ16 -> -0.080176855
C17: Real imports | BB17: =BA17+BC17 -> 0 | BC17: =BA17-AZ17 -> 0
A18: IMF.RES.GEE:GEE_LIVE | B18: RWA.TM_R_PCH_WX.G001.A | C18: Goods and services | D18: 9.6140924 | E18: 1.5540434 | F18: -1.7041345 | G18: -1.4699568 | H18: -0.82166916 | I18: 5.1507592 | J18: 0.36013679 | K18: 13.788404 | L18: 10.371698 | M18: 11.290959 | N18: 6.7041242 | O18: 6.5719635 | P18: 8.3052605 | Q18: 8.4284937 | R18: 10.657813 | S18: 10.43388 | T18: 4.6590311 | U18: -6.5438029 | V18: 36.416057 | W18: 29.44365 | X18: 4.1058885 | Y18: -7.6409012 | Z18: 23.511824 | AA18: 56.79638 | AB18: 6.9240988 | AC18: 6.6632414 | AD18: 3.7962372 | AE18: 34.128913 | AF18: 10.268302 | AG18: -5.5540646 | AH18: 24.66659 | AI18: 4.1085621 | AJ18: -3.7895783 | AK18: 12.875079 | AL18: 10.090308 | AM18: -6.0761763 | AN18: 9.3236543 | AO18: 1.4103611 | AP18: 8.3719279 | AQ18: -7.7336348 | AR18: -5.3003065 | AS18: 27.288699 | AT18: 18.382751 | AU18: 1.8006595 | AV18: 7.3227254 | AW18: 6.2127832 | AX18: 5.7576763 | AY18: 5.150914 | AZ18: 5.4138611 | BA18: 4.8639319 | BB18: 4.9109316 | BC18: =BA18-AZ18 -> -0.54992919
A19: IMF.RES.GEE:GEE_LIVE | B19: RWA.TMG_R_PCH_WX.G001.A | C19: Goods | D19: 1.2878311 | E19: -1.3604862 | F19: 2.6705544 | G19: 5.2354593 | H19: 0.001148546 | I19: 1.6939092 | J19: 5.3027263 | K19: 6.1524333 | L19: -2.5689198 | M19: 12.981925 | N19: -4.5984394 | O19: -6.5605048 | P19: -10.578914 | Q19: -10.035902 | R19: 7.913223 | S19: 23.6714 | T19: 3.1169245 | U19: -5.8168154 | V19: 35.311013 | W19: 29.957922 | X19: 4.1410466 | Y19: -7.9096206 | Z19: 23.743882 | AA19: 57.42949 | AB19: 6.8102568 | AC19: 6.0207022 | AD19: 3.2577218 | AE19: 36.237141 | AF19: 11.051826 | AG19: -6.7485904 | AH19: 27.500031 | AI19: 3.3072066 | AJ19: -3.410745 | AK19: 14.181169 | AL19: 8.6737194 | AM19: -5.9638281 | AN19: 9.2540413 | AO19: 3.5295655 | AP19: 5.6389246 | AQ19: -8.020041 | AR19: -4.0485089 | AS19: 19.758814 | AT19: 14.156006 | AU19: 8.1514103 | AV19: 6.2819758 | AW19: 6.7930885 | AX19: 5.6457754 | AY19: 5.2978144 | AZ19: 5.4619419 | BA19: 4.9726211 | BB19: 4.9851558 | BC19: =BA19-AZ19 -> -0.48932076
A20: IMF.RES.GEE:GEE_LIVE | B20: RWA.TMGXO_R_PCH_WX.G001.A | C20: Excluding oil | D20: -1.7745437 | E20: -1.7240329 | F20: 2.5895464 | G20: 5.7923668 | H20: 0.076483161 | I20: 3.2414491 | J20: 2.7973947 | K20: 5.5414012 | L20: -3.6179004 | M20: 13.54145 | N20: -4.4953813 | O20: -8.1779813 | P20: -9.596901 | Q20: -9.6298334 | R20: 8.0464082 | S20: 24.517201 | T20: 5.4675171 | U20: -5.5660902 | V20: 35.217161 | W20: 31.239917 | X20: 1.8414241 | Y20: -8.7647612 | Z20: 24.805094 | AA20: 60.014342 | AB20: 7.302419 | AC20: 5.2378291 | AD20: 2.0658222 | AE20: 38.910608 | AF20: 11.687687 | AG20: -7.5430588 | AH20: 28.675199 | AI20: 3.6133704 | AJ20: -3.8899914 | AK20: 14.268376 | AL20: 8.4503636 | AM20: -9.163192 | AN20: 8.2726108 | AO20: 6.0584651 | AP20: 7.8702341 | AQ20: -9.3092503 | AR20: -6.3174301 | AS20: 23.714441 | AT20: 15.381166 | AU20: 6.3523514 | AV20: -1.0695421 | AW20: 6.7687078 | AX20: 5.8325346 | AY20: 5.3400439 | AZ20: 5.6148023 | BA20: 5.2667128 | BB20: 5.0625578 | BC20: =BA20-AZ20 -> -0.34808949
C22: Real exports | X22: Import-weighted averages | AT22: Export-weighted averages
A23: IMF.RES.GEE:GEE_LIVE | B23: RWA.TX_R_PCH_WM.G001.A | C23: Goods and services | D23: 5.3554691 | E23: 0.45857511 | F23: -2.5457746 | G23: -3.1457389 | H23: 3.9387982 | I23: 3.0461779 | J23: 4.3149585 | K23: 26.850186 | L23: 14.820568 | M23: 6.8172879 | N23: 12.15618 | O23: 5.1967382 | P23: 7.5519799 | Q23: 6.1164357 | R23: 10.720455 | S23: 14.475337 | T23: 8.7803477 | U23: 6.1402275 | V23: 3.3731468 | W23: 0.46109028 | X23: 15.089374 | Y23: 7.9726583 | Z23: 12.299088 | AA23: 13.386795 | AB23: 16.663966 | AC23: 11.684984 | AD23: 8.6997792 | AE23: 11.105466 | AF23: 4.8449057 | AG23: -7.4049928 | AH23: 10.76218 | AI23: 8.2323753 | AJ23: 5.3792926 | AK23: 4.5499677 | AL23: 4.499853 | AM23: 2.9991671 | AN23: 1.7563006 | AO23: 2.6480046 | AP23: 5.5449395 | AQ23: 2.9839879 | AR23: -6.5462825 | AS23: 9.8771117 | AT23: 5.3627526 | AU23: 4.056834 | AV23: 6.4921817 | AW23: 6.0252369 | AX23: 4.5019135 | AY23: 4.3701415 | AZ23: 4.5688753 | BA23: 3.8617683 | BB23: 4.0541266 | BC23: =BA23-AZ23 -> -0.70710696
A24: IMF.RES.GEE:GEE_LIVE | B24: RWA.TXG_R_PCH_WM.G001.A | C24: Goods | D24: 4.6799104 | E24: 4.727908 | F24: 1.2545504 | G24: -0.82628503 | H24: 5.0538517 | I24: 0.79023599 | J24: 4.4206197 | K24: 6.0278265 | L24: 7.5684235 | M24: 7.5553793 | N24: 12.228357 | O24: 5.635215 | P24: 7.2183834 | Q24: 5.7186442 | R24: 11.068175 | S24: 13.935006 | T24: 9.4958924 | U24: 5.8715932 | V24: 4.8581024 | W24: 1.2631616 | X24: 16.26043 | Y24: 8.1758175 | Z24: 13.317147 | AA24: 13.764 | AB24: 14.443682 | AC24: 11.258753 | AD24: 7.8199835 | AE24: 10.947676 | AF24: 4.4589133 | AG24: -7.6498483 | AH24: 10.365278 | AI24: 8.0315237 | AJ24: 5.197751 | AK24: 4.8870239 | AL24: 3.4622804 | AM24: 2.4668055 | AN24: 2.4120909 | AO24: 2.6105842 | AP24: 4.5000824 | AQ24: 3.4504595 | AR24: -2.9999776 | AS24: 9.0772064 | AT24: 1.8943806 | AU24: 4.2316156 | AV24: 6.2238806 | AW24: 6.2446899 | AX24: 4.4917086 | AY24: 4.3539346 | AZ24: 4.5187924 | BA24: 3.7587365 | BB24: 4.0205786 | BC24: =BA24-AZ24 -> -0.76005589
A25: IMF.RES.GEE:GEE_LIVE | B25: RWA.TXGXO_R_PCH_WM.G001.A | C25: Excluding oil | D25: 54.584644 | E25: -0.78488192 | F25: -1.4884234 | G25: 3.7523146 | H25: -28.849876 | I25: 7.6247064 | J25: -3.2740133 | K25: 18.206334 | L25: 2.4504821 | M25: 11.175933 | N25: 13.776876 | O25: 6.317115 | P25: 6.3915837 | Q25: 13.003582 | R25: 14.49485 | S25: 17.618187 | T25: 9.7482302 | U25: 8.3231749 | V25: 5.959644 | W25: 1.3650797 | X25: 15.598793 | Y25: 9.727417 | Z25: 16.1578 | AA25: 14.20486 | AB25: 16.278952 | AC25: 11.575115 | AD25: 8.5766821 | AE25: 13.207512 | AF25: 4.5077589 | AG25: -6.7789874 | AH25: 11.647752 | AI25: 7.9889017 | AJ25: 6.0151232 | AK25: 5.239548 | AL25: 4.6066735 | AM25: 2.6500598 | AN25: 2.4015298 | AO25: 2.902866 | AP25: 5.003611 | AQ25: 3.8256601 | AR25: -2.8959372 | AS25: 10.670446 | AT25: 1.521443 | AU25: 3.449181 | AV25: 7.9772864 | AW25: 7.3177619 | AX25: 4.1832614 | AY25: 4.039571 | AZ25: 4.7872516 | BA25: 4.0141818 | BB25: 4.3131672 | BC25: =BA25-AZ25 -> -0.77306983
C27: 2) Foreign Prices and Costs of Tading Partners 1/
C29: Advanced economy partners | X29: Import-weighted averages | AT29: Export-weighted averages
C31: GDP deflators
A32: IMF.RES.GEE:GEE_LIVE | B32: RWA.NGDP_D_PCH_WM.G110.A | C32: In national currency | D32: 14.342426 | E32: 11.332701 | F32: 9.5639686 | G32: 8.2557037 | H32: 11.346926 | I32: 8.3641227 | J32: 4.7820852 | K32: 3.5510056 | L32: 4.6180729 | M32: 5.0550313 | N32: 5.5425174 | O32: 7.5927157 | P32: 4.5350916 | Q32: 4.4736375 | R32: 3.8869529 | S32: 3.7487576 | T32: 2.322791 | U32: 3.6945234 | V32: 1.9903587 | W32: 0.25777394 | X32: 1.2899151 | Y32: 1.9974304 | Z32: 1.6577691 | AA32: 1.4530114 | AB32: 1.7249886 | AC32: 1.4622318 | AD32: 1.3369897 | AE32: 2.3780409 | AF32: 1.9339932 | AG32: 1.3619036 | AH32: 1.0390305 | AI32: 1.297034 | AJ32: 1.3437715 | AK32: 1.2335289 | AL32: 1.1781354 | AM32: 1.7249621 | AN32: 1.1332021 | AO32: 1.4475834 | AP32: 1.5262916 | AQ32: 1.2127928 | AR32: 1.4991581 | AS32: 2.8111126 | AT32: 5.1320798 | AU32: 3.9833792 | AV32: 3.0509587 | AW32: 2.2739971 | AX32: 1.9908673 | AY32: 1.9675927 | AZ32: 1.9767277 | BA32: 1.9852238 | BB32: 1.988691 | BC32: =BA32-AZ32 -> 0.0084961187
A33: IMF.RES.GEE:GEE_LIVE | B33: RWA.NGDP_D_USD_PCH_WM.G110.A | C33: In U.S. dollars | D33: 7.9744924 | E33: -5.055746 | F33: -2.9202772 | G33: -1.784272 | H33: -3.3099928 | I33: -0.26527565 | J33: 25.154917 | K33: 16.632923 | L33: 9.8874085 | M33: 2.0269279 | N33: 13.587786 | O33: 5.2541472 | P33: 6.7260146 | Q33: -1.8502877 | R33: 6.1375694 | S33: 12.191587 | T33: -1.488472 | U33: -8.7457934 | V33: -6.0586318 | W33: 1.8138363 | X33: -5.1011535 | Y33: -3.3024486 | Z33: 5.1583827 | AA33: 14.706651 | AB33: 9.2613894 | AC33: 3.5755189 | AD33: 2.8980815 | AE33: 8.6457498 | AF33: 5.0691331 | AG33: -3.9244575 | AH33: 1.7478387 | AI33: 6.8014937 | AJ33: -3.2802875 | AK33: 1.9651086 | AL33: 1.0858333 | AM33: -10.500372 | AN33: 1.0135633 | AO33: 2.7860653 | AP33: 4.7311761 | AQ33: -2.7529594 | AR33: 2.7071111 | AS33: 5.932699 | AT33: -5.084885 | AU33: 4.6799143 | AV33: 1.8282135 | AW33: 4.4943223 | AX33: 4.3901773 | AY33: 2.1174594 | AZ33: 2.0542574 | BA33: 2.0508777 | BB33: 2.0534167 | BC33: =BA33-AZ33 -> -0.0033796259
C35: Consumer Prices
A36: IMF.RES.GEE:GEE_LIVE | B36: RWA.PCPI_PCH_WM.G110.A | C36: In national currency | D36: 18.330642 | E36: 13.506625 | F36: 9.960087 | G36: 8.2022493 | H36: 11.219769 | I36: 9.0641691 | J36: 3.0680354 | K36: 2.8240511 | L36: 3.8818473 | M36: 4.9404306 | N36: 5.4140103 | O36: 6.3109806 | P36: 4.5246382 | Q36: 4.814707 | R36: 3.965794 | S36: 3.1424351 | T36: 3.0417034 | U36: 4.4913193 | V36: 2.3823829 | W36: 0.95709411 | X36: 1.8434583 | Y36: 2.2981036 | Z36: 1.6851865 | AA36: 1.7209552 | AB36: 1.8774669 | AC36: 1.9132495 | AD36: 1.9672861 | AE36: 2.0063213 | AF36: 3.7094253 | AG36: 0.73597965 | AH36: 1.7071144 | AI36: 2.9092739 | AJ36: 2.2294073 | AK36: 1.4266304 | AL36: 1.0949891 | AM36: 0.43809968 | AN36: 0.58241627 | AO36: 1.5139596 | AP36: 1.6430374 | AQ36: 1.1156168 | AR36: 0.35732322 | AS36: 2.375036 | AT36: 7.0441889 | AU36: 4.4269385 | AV36: 2.443452 | AW36: 2.1959984 | AX36: 1.9389071 | AY36: 1.9774599 | AZ36: 2.0474718 | BA36: 2.0092958 | BB36: 2.0039948 | BC36: =BA36-AZ36 -> -0.038175974
A37: IMF.RES.GEE:GEE_LIVE | B37: RWA.PCPI_USD_PCH_WM.G110.A | C37: In U.S. dollars | D37: 10.175225 | E37: -3.1278025 | F37: -2.5493638 | G37: -1.8001813 | H37: -3.3463808 | I37: -0.13156476 | J37: 23.045009 | K37: 15.808436 | L37: 9.1335296 | M37: 1.9054898 | N37: 13.45441 | O37: 3.8321778 | P37: 6.7887296 | Q37: -1.5415492 | R37: 6.2196687 | S37: 11.511621 | T37: -0.86790691 | U37: -8.2531688 | V37: -5.8270079 | W37: 2.5860959 | X37: -4.5848033 | Y37: -3.0215966 | Z37: 5.1809724 | AA37: 14.975003 | AB37: 9.4189651 | AC37: 4.0556758 | AD37: 3.5518247 | AE37: 8.2409831 | AF37: 6.9140408 | AG37: -4.523564 | AH37: 2.4113279 | AI37: 8.4956141 | AJ37: -2.4303116 | AK37: 2.148669 | AL37: 0.99639545 | AM37: -11.648414 | AN37: 0.46362245 | AO37: 2.8521538 | AP37: 4.8521448 | AQ37: -2.8440162 | AR37: 1.546018 | AS37: 5.4782492 | AT37: -3.4174581 | AU37: 5.1264361 | AV37: 1.2347851 | AW37: 4.4175478 | AX37: 4.3353382 | AY37: 2.1273 | AZ37: 2.1250177 | BA37: 2.0750696 | BB37: 2.0689366 | BC37: =BA37-AZ37 -> -0.049948077
C39: All countries 2/
C41: Export deflators in U.S. dollars
A42: IMF.RES.GEE:GEE_LIVE | B42: RWA.TX_D_PCH_WM.G001.A | C42: Goods and services | D42: 19.597721 | E42: 2.849448 | F42: -2.2882031 | G42: -1.5384423 | H42: 0.18888227 | I42: -4.044403 | J42: 1.7934529 | K42: 1.2847665 | L42: -2.7559858 | M42: 2.8709996 | N42: 17.038638 | O42: -2.6545546 | P42: -0.37392668 | Q42: -0.73318152 | R42: -0.28504562 | S42: 4.8686938 | T42: -0.74944593 | U42: -3.0982133 | V42: -6.7984977 | W42: 5.5591511 | X42: 3.6607672 | Y42: -5.0008779 | Z42: -0.72106825 | AA42: 7.5462974 | AB42: 9.7602577 | AC42: 9.1562326 | AD42: 9.3140928 | AE42: 9.5092727 | AF42: 13.739405 | AG42: -6.9399181 | AH42: 10.983056 | AI42: 11.661446 | AJ42: 0.32981985 | AK42: -0.70604633 | AL42: -2.8033443 | AM42: -11.371363 | AN42: -4.7253662 | AO42: 5.895697 | AP42: 4.3602875 | AQ42: -1.8965123 | AR42: -3.7985179 | AS42: 15.78032 | AT42: 10.331738 | AU42: -3.1796389 | AV42: 0.94801183 | AW42: 1.0733705 | AX42: 0.30696774 | AY42: 0.76981942 | AZ42: 0.42449531 | BA42: 1.1836776 | BB42: 1.1835377 | BC42: =BA42-AZ42 -> 0.75918233
A43: IMF.RES.GEE:GEE_LIVE | B43: RWA.TXG_D_PCH_WM.G001.A | C43: Goods | D43: 19.225701 | E43: -2.2541295 | F43: -6.3201784 | G43: -4.0088901 | H43: 1.2900861 | I43: -4.331733 | J43: -0.68804461 | K43: 9.634348 | L43: 2.8173453 | M43: 1.2290725 | N43: 4.8427381 | O43: -2.9215317 | P43: -2.0850383 | Q43: -1.5936508 | R43: 5.1852721 | S43: 8.5925306 | T43: -0.17919328 | U43: -3.4631868 | V43: -8.7878547 | W43: 3.317814 | X43: 3.2320192 | Y43: -5.6737648 | Z43: -0.61695135 | AA43: 8.4415783 | AB43: 10.975069 | AC43: 9.8990491 | AD43: 10.136616 | AE43: 10.15505 | AF43: 15.47979 | AG43: -7.3998272 | AH43: 12.167303 | AI43: 13.071377 | AJ43: -0.48169317 | AK43: -1.7717939 | AL43: -3.3223886 | AM43: -12.979291 | AN43: -5.9007602 | AO43: 5.4362289 | AP43: 3.9434206 | AQ43: -1.4631952 | AR43: -0.78849372 | AS43: 16.030521 | AT43: 9.6007067 | AU43: -5.1795986 | AV43: 0.59412289 | AW43: 1.4049209 | AX43: 0.55832712 | AY43: 0.67042323 | AZ43: 0.22047612 | BA43: 1.0723736 | BB43: 1.026576 | BC43: =BA43-AZ43 -> 0.8518975
A44: IMF.RES.GEE:GEE_LIVE | B44: RWA.TXGXO_D_PCH_WM.G001.A | C44: Excluding oil | D44: -22.65507 | E44: 16.821948 | F44: -9.650483 | G44: 20.970422 | H44: 0.39135797 | I44: -5.1080568 | J44: 17.100279 | K44: -0.45920878 | L44: 10.659455 | M44: -3.3005038 | N44: -1.5732012 | O44: -0.90418094 | P44: -2.9685716 | Q44: 0.090412665 | R44: 5.3723749 | S44: 7.4952578 | T44: -1.8792471 | U44: -3.8054471 | V44: -6.688612 | W44: -0.05098324 | X44: -1.1735879 | Y44: -4.8332074 | Z44: -1.7022316 | AA44: 7.7752179 | AB44: 9.1358578 | AC44: 6.6782683 | AD44: 8.1514593 | AE44: 9.9464278 | AF44: 14.478189 | AG44: -5.018332 | AH44: 10.575018 | AI44: 10.847636 | AJ44: -0.96569943 | AK44: -1.4206276 | AL44: -2.5785958 | AM44: -9.3609392 | AN44: -4.4621082 | AO44: 3.8795425 | AP44: 1.8971712 | AQ44: -1.1372241 | AR44: 2.5726534 | AS44: 11.819088 | AT44: 6.2923739 | AU44: -3.9722292 | AV44: 0.87020891 | AW44: 2.7639973 | AX44: 1.230463 | AY44: 0.95950761 | AZ44: 0.10892308 | BA44: 1.0985717 | BB44: 1.001426 | BC44: =BA44-AZ44 -> 0.98964865
C46: Import deflators in U.S. dollars | X46: Export-weighted averages in U.S. dollars | AT46: Export-weighted averages
A47: IMF.RES.GEE:GEE_LIVE | B47: RWA.TM_D_PCH_WX.G001.A | C47: Goods and services | D47: 16.069899 | E47: 0.73087123 | F47: -1.2417681 | G47: -1.2197391 | H47: 0.261668 | I47: -4.3770662 | J47: 9.6824945 | K47: 5.868985 | L47: 6.7514323 | M47: 0.3311326 | N47: 10.584636 | O47: 1.4851845 | P47: 2.960455 | Q47: 0.033731423 | R47: 3.5788902 | S47: 9.1199209 | T47: 0.96174408 | U47: -6.9319079 | V47: -13.846875 | W47: -32.270865 | X47: 9.8484499 | Y47: 22.883693 | Z47: -2.3741882 | AA47: -16.420789 | AB47: 25.906162 | AC47: 37.943179 | AD47: 5.470008 | AE47: 13.401143 | AF47: 12.624677 | AG47: -12.251635 | AH47: 8.7707619 | AI47: 10.458386 | AJ47: 4.3875062 | AK47: -0.45572719 | AL47: 0.69613531 | AM47: -5.4936517 | AN47: -4.6683272 | AO47: -1.9350172 | AP47: 11.467488 | AQ47: 1.0880425 | AR47: -1.8666334 | AS47: 7.0803431 | AT47: 7.5263549 | AU47: 3.8812541 | AV47: 1.383174 | AW47: 0.38977736 | AX47: 0.9407462 | AY47: 1.1482964 | AZ47: 1.1444001 | BA47: 1.4045666 | BB47: 1.3664537 | BC47: =BA47-AZ47 -> 0.26016658
A48: IMF.RES.GEE:GEE_LIVE | B48: RWA.TMG_D_PCH_WX.G001.A | C48: Goods | D48: 21.733973 | E48: -3.8869277 | F48: -7.9363091 | G48: -5.8167552 | H48: -3.1955732 | I48: 9.012278 | J48: 7.3868421 | K48: 13.378736 | L48: 6.6211791 | M48: 2.0169796 | N48: 7.546427 | O48: -2.4007984 | P48: 3.1073302 | Q48: -4.7076837 | R48: 2.8148674 | S48: 10.209775 | T48: -2.0928776 | U48: -7.9359847 | V48: -18.837409 | W48: -31.683326 | X48: 21.397329 | Y48: 25.491667 | Z48: -2.8807953 | AA48: -15.687003 | AB48: 27.832131 | AC48: 29.787077 | AD48: 10.530826 | AE48: 13.014136 | AF48: 12.435446 | AG48: -13.427717 | AH48: 8.6282624 | AI48: 12.050259 | AJ48: 6.2507963 | AK48: -0.64823624 | AL48: 0.3230805 | AM48: -4.9478711 | AN48: -3.1035855 | AO48: -3.1258413 | AP48: 12.036459 | AQ48: 1.7878649 | AR48: -3.6216792 | AS48: 13.820785 | AT48: 9.7918074 | AU48: -0.86337869 | AV48: 1.2992062 | AW48: 0.29928721 | AX48: 0.80519564 | AY48: 1.1138494 | AZ48: 1.1613403 | BA48: 1.3507601 | BB48: 1.2979032 | BC48: =BA48-AZ48 -> 0.18941975
A49: IMF.RES.GEE:GEE_LIVE | B49: RWA.TMGXO_D_PCH_WX.G001.A | C49: Excluding oil | D49: 18.98973 | E49: -3.0362247 | F49: -7.3892662 | G49: -5.7927858 | H49: -3.7854726 | I49: 8.866599 | J49: 12.006112 | K49: 11.086294 | L49: 18.871648 | M49: 0.88775061 | N49: 6.7557334 | O49: -1.3246896 | P49: 3.4302069 | Q49: -4.6048335 | R49: 2.9123512 | S49: 9.3034929 | T49: -2.2971124 | U49: -7.6593656 | V49: -18.260656 | W49: -32.686184 | X49: 17.332813 | Y49: 29.520498 | Z49: -3.236489 | AA49: -16.805957 | AB49: 26.596328 | AC49: 27.320839 | AD49: 8.0774752 | AE49: 15.752606 | AF49: 9.9904059 | AG49: -10.660695 | AH49: 7.2635638 | AI49: 10.385799 | AJ49: 6.0712266 | AK49: -0.7670567 | AL49: 1.0483453 | AM49: 0.56958822 | AN49: -1.2650775 | AO49: -5.5534823 | AP49: 10.230699 | AQ49: 2.6740376 | AR49: -0.2459392 | AS49: 9.917571 | AT49: 7.3043356 | AU49: 0.38251783 | AV49: 0.97256438 | AW49: 2.9181538 | AX49: 2.4131416 | AY49: 1.3191644 | AZ49: 1.1028728 | BA49: 1.2940758 | BB49: 1.3588006 | BC49: =BA49-AZ49 -> 0.19120304
C51: Advanced economy partners | X51: Export-weighted averages in U.S. dollars | AT51: Export-weighted averages
A53: IMF.RES.GEE:GEE_LIVE | B53: RWA.LULCM_USD_PCH_WX.G110.A | C53: Unit labor costs in manufacturing | D53: 14.736539 | E53: -8.461324 | F53: -5.2876894 | G53: -7.6577264 | H53: -10.120427 | I53: 2.1868463 | J53: 21.883818 | K53: 15.028625 | L53: 5.1375036 | M53: -1.7016433 | N53: 16.434789 | O53: 5.0199225 | P53: 4.7074822 | Q53: -7.0117733 | R53: 1.9792227 | S53: 5.9675046 | T53: 0.67448177 | U53: -3.6208496 | V53: 0.45124169 | W53: -2.2045879 | X53: -8.1011609 | Y53: -0.65604027 | Z53: 4.2405705 | AA53: 10.223995 | AB53: 4.5491248 | AC53: -0.99101511 | AD53: -0.4099269 | AE53: 5.6807679 | AF53: 7.4584132 | AG53: -0.50704682 | AH53: -5.0001857 | AI53: 7.1628446 | AJ53: -0.42707669 | AK53: 3.9752124 | AL53: 1.1983966 | AM53: -8.8352084 | AN53: -2.5095835 | AO53: 0.097561509 | AP53: 4.2049101 | AQ53: -0.29206991 | AR53: 5.6217174 | AS53: 0.68236552 | AT53: -4.0467682 | AU53: 5.3326586 | AV53: 2.9250306 | AW53: 4.7787394 | AX53: 5.2069165 | AY53: 1.935453 | AZ53: 1.8524198 | BA53: 1.8346645 | BB53: 1.8752649 | BC53: =BA53-AZ53 -> -0.017755345
C55: 3) World Prices | X55: In U.S. dollars | AT55: Export-weighted averages
A56: IMF.RES.GAS:GAS_LIVE | B56: G110.TXGM_D_PCH.A | C56: Export unit value for manufactures (MUV) | D56: 17.207079 | E56: 4.7422244 | F56: -3.7097662 | G56: -0.48177501 | H56: 0.77153706 | I56: -1.6826107 | J56: 5.7849048 | K56: 11.137639 | L56: 10.8638 | M56: 2.2864532 | N56: 1.8306982 | O56: 3.9753925 | P56: -0.59748652 | Q56: -0.33434128 | R56: 1.3594959 | S56: 4.221736 | T56: 1.3966741 | U56: -3.8618219 | V56: -4.3996951 | W56: -1.1011041 | X56: 0.21212314 | Y56: -3.3211254 | Z56: -1.9730175 | AA56: 2.8207618 | AB56: 6.557116 | AC56: 4.0601999 | AD56: 2.2664741 | AE56: 3.3049342 | AF56: 6.0514054 | AG56: -1.9391893 | AH56: 2.1131214 | AI56: 4.5356028 | AJ56: 2.4247539 | AK56: -2.9013171 | AL56: -0.54073717 | AM56: -3.0399231 | AN56: -5.0605676 | AO56: 0.14050709 | AP56: 2.0382204 | AQ56: 0.37675838 | AR56: -3.0921702 | AS56: 6.7429481 | AT56: 10.26443 | AU56: -1.7400624 | AV56: 1.1908605 | AW56: 0.6840894 | AX56: 0.048392498 | AY56: -0.17399505 | AZ56: 0.52612582 | BA56: 0.91794537 | BB56: 1.2295675 | BC56: =BA56-AZ56 -> 0.39181955
A57: IMF.RES.GAS:GAS_LIVE | B57: G001.PZPIOIL_PCH.A | C57: Petroleum spot price (APSP) | D57: 25.630434 | E57: -2.5575022 | F57: -10.829451 | G57: -8.6047642 | H57: -3.4939639 | I57: -4.3177986 | J57: -48.076369 | K57: 25.850524 | L57: -18.9133 | M57: 21.130711 | N57: 28.284675 | O57: -15.330324 | P57: -1.7852258 | Q57: -11.543426 | R57: -5.3252686 | S57: 8.1709224 | T57: 18.834408 | U57: -5.5803375 | V57: -31.604345 | W57: 37.349698 | X57: 56.612615 | Y57: -13.984177 | Z57: 2.0864315 | AA57: 15.63331 | AB57: 30.778655 | AC57: 41.525926 | AD57: 20.362484 | AE57: 10.539633 | AF57: 35.929889 | AG57: -36.44402 | AH57: 28.687138 | AI57: 31.491986 | AJ57: 0.98777641 | AK57: -0.8799537 | AL57: -7.531488 | AM57: -47.1463 | AN57: -15.022149 | AO57: 22.452431 | AP57: 29.361225 | AQ57: -10.36033 | AR57: -32.013819 | AS57: 65.806664 | AT57: 39.151032 | AU57: -16.362407 | AV57: -1.7669942 | AW57: -14.442214 | AX57: -4.4191815 | AY57: -2.804883 | AZ57: 0.81472913 | BA57: 1.5602293 | BB57: 1.1711425 | BC57: =BA57-AZ57 -> 0.7455002
C59: Average of nonfuel commodity market prices weighted by the 2011-13 composition of nonfuel commodity trade of reporting country.
A61: IMF.RES.GEE:GEE_LIVE | B61: RWA.PXPNF_PCH_WX.G001.A | C61: Nonfuel commodity export price | E61: -14.784151 | F61: -6.582333 | G61: 6.1159031 | H61: 2.7862444 | I61: -12.980296 | J61: 2.6763784 | K61: -2.4927335 | L61: 2.3387675 | M61: -3.4235382 | N61: -5.6165733 | O61: -4.4412745 | P61: -2.7093716 | Q61: -2.3559479 | R61: 17.563525 | S61: 5.7813579 | T61: -4.0088818 | U61: -2.3731095 | V61: -8.8925449 | W61: -5.4650681 | X61: 2.0670925 | Y61: -12.932837 | Z61: 9.5976651 | AA61: 12.086372 | AB61: 18.271849 | AC61: 8.0298753 | AD61: 31.871885 | AE61: 25.178039 | AF61: 3.9637112 | AG61: -7.5179331 | AH61: 26.380674 | AI61: 21.846161 | AJ61: -4.072448 | AK61: -12.076042 | AL61: -5.1259016 | AM61: -13.414441 | AN61: 1.6863531 | AO61: 6.2083712 | AP61: 1.084756 | AQ61: 3.9468404 | AR61: 12.135025 | AS61: 20.302393 | AT61: 3.4998094 | AU61: 3.8148838 | AV61: 11.59032 | AW61: 26.750885 | AX61: 27.357124 | AY61: 2.1096413 | AZ61: 0.6516066 | BA61: -0.11682905 | BB61: -0.018049232 | BC61: =BA61-AZ61 -> -0.76843565
A62: IMF.RES.GEE:GEE_LIVE | B62: RWA.PMPNF_PCH_WM.G001.A | C62: Nonfuel commodity import price | E62: -11.286166 | F62: -18.353684 | G62: 2.2982161 | H62: -1.2825299 | I62: -11.584342 | J62: -5.0781963 | K62: 9.7647775 | L62: 12.177247 | M62: -1.8207345 | N62: -3.0117794 | O62: -2.9676934 | P62: -1.7670187 | Q62: -1.5813635 | R62: 10.906378 | S62: 10.025369 | T62: 0.27410603 | U62: -9.3174998 | V62: -0.69753535 | W62: -14.948886 | X62: -2.6918689 | Y62: -4.3940696 | Z62: 12.82855 | AA62: 6.836479 | AB62: 11.662221 | AC62: 9.335148 | AD62: 16.357259 | AE62: 18.871359 | AF62: 33.722093 | AG62: -10.830119 | AH62: 24.604326 | AI62: 21.527524 | AJ62: -7.552777 | AK62: -7.3122705 | AL62: -11.197422 | AM62: -19.166829 | AN62: 3.9197921 | AO62: 3.0972867 | AP62: -0.85380826 | AQ62: 4.1140378 | AR62: 13.016448 | AS62: 27.553083 | AT62: 6.349581 | AU62: -5.8729475 | AV62: 1.930578 | AW62: 8.8450887 | AX62: 18.363197 | AY62: 2.2970908 | AZ62: 0.47755518 | BA62: -0.71291053 | BB62: -0.11095086 | BC62: =BA62-AZ62 -> -1.1904657
C64: Component-Based Goods Trade Deflators 3/
A66: IMF.RES.GEE:GEE_LIVE | B66: RWA.TXGCB_D_PCH.G001.A | C66: Export deflators | D66: 8.9026739 | E66: -4.6815092 | F66: -5.0961118 | G66: 2.7023674 | H66: 1.7438663 | I66: -7.1350498 | J66: 4.2846814 | K66: 4.5594085 | L66: 6.7494865 | M66: -0.46927775 | N66: -1.7634713 | O66: -0.086622343 | P66: -1.6167152 | Q66: -1.3100002 | R66: 9.179813 | S66: 4.9744339 | T66: -1.2121315 | U66: -3.1433461 | V66: -6.5680145 | W66: -3.2072213 | X66: 1.1073603 | Y66: -7.9598874 | Z66: 3.6111745 | AA66: 7.29249 | AB66: 12.210829 | AC66: 5.9760272 | AD66: 16.554508 | AE66: 13.861236 | AF66: 5.0438516 | AG66: -4.6315781 | AH66: 13.825021 | AI66: 12.889949 | AJ66: -0.71089713 | AK66: -7.3291827 | AL66: -2.7536091 | AM66: -8.0468272 | AN66: -1.8043984 | AO66: 3.068953 | AP66: 1.5780636 | AQ66: 2.0997357 | AR66: 4.2567118 | AS66: 13.286948 | AT66: 6.9997183 | AU66: 0.94084133 | AV66: 6.2098018 | AW66: 13.264332 | AX66: 13.228013 | AY66: 0.92812349 | AZ66: 0.5866848 | BA66: 0.41854708 | BB66: 0.62744821 | BC66: =BA66-AZ66 -> -0.16813772
A67: IMF.RES.GEE:GEE_LIVE | B67: RWA.TMGCB_D_PCH.G001.A | C67: Import deflators | D67: 11.020533 | E67: -3.3040434 | F67: -11.128944 | G67: -0.50176073 | H67: -0.76165869 | I67: -6.3707093 | J67: -7.0429013 | K67: 12.760915 | L67: 6.943619 | M67: 3.3477069 | N67: 3.7206027 | O67: -1.9439451 | P67: -1.2833598 | Q67: -2.5646637 | R67: 4.4887007 | S67: 7.3320748 | T67: 3.5392243 | U67: -6.485071 | V67: -6.8969188 | W67: -1.3048441 | X67: 7.4569394 | Y67: -5.3936903 | Z67: 5.0530992 | AA67: 6.4926136 | AB67: 12.42112 | AC67: 11.994565 | AD67: 11.100806 | AE67: 11.14121 | AF67: 22.546822 | AG67: -10.9941 | AH67: 15.865868 | AI67: 15.962944 | AJ67: -2.1155433 | AK67: -4.5080031 | AL67: -6.2126538 | AM67: -16.678041 | AN67: -2.6708889 | AO67: 4.785655 | AP67: 4.9043492 | AQ67: 0.37748772 | AR67: -0.47205781 | AS67: 24.665537 | AT67: 12.923067 | AU67: -5.7355417 | AV67: 1.0654674 | AW67: 1.9400475 | AX67: 7.3113531 | AY67: 0.50017608 | AZ67: 0.5485896 | BA67: 0.30806629 | BB67: 0.63986047 | BC67: =BA67-AZ67 -> -0.24052331
C70: 1/ Averages of percent changes of data for individual trading partners weighted by their share in total exports or imports, as applicable, of reporting country. Note that the relative importance of trading partners reflects trade in goods only; complete information on bilateral trade in services is not generally available.
C71: 2/ Based on data for partner countries that together account for 100 percent of trade of reporting country.
C72: 3/ Average of the export unit value for manufactures (MUV), the petroleum price (APSP), and the nonfuel commodity price, weighted by the 2011-13 composition of trade of reporting country.
C75: Current Vintage: S2015Rev | AK75: s
C77: =+B4 -> \\RES\GEE\GEE Live | AI77: kept this block intact/linked, range extended 2011-28; plse keep vintage labels up to date
C78: range GEE_ALL below this, updated Sept 2024 | AI78: from 2011 GEE_ALL
C79: GEE_ALL vintage IMF-WEO Oct 2023 | X79: =+X6 -> 2000 | Y79: =+Y6 -> 2001 | Z79: =+Z6 -> 2002 | AA79: =+AA6 -> 2003 | AB79: =+AB6 -> 2004 | AC79: =+AC6 -> 2005 | AD79: =+AD6 -> 2006 | AE79: =+AE6 -> 2007 | ... AS79: =+AS6 -> 2021 | AT79: 2022 | AU79: 2023 | AV79: 2024 | AW79: 2025 | AX79: 2026 | AY79: 2027 | AZ79: 2028 | BA79: 2029 | BB79: 2030 | BC79: 2031 | BD79: 2032 | BE79: 2033 | BF79: 2034 | BG79: 2035
C80: World growth (Rwa export weigthed 2011-13) | BC80: Naïve extrapolation
C81: Real GDP growth all trading partners (100% of trade of reporting country) | X81: =+X11/100 -> 0.05229704 | Y81: =+Y11/100 -> 0.017177979 | Z81: =+Z11/100 -> 0.014494103 | AA81: =+AA11/100 -> 0.019202364 | AB81: =+AB11/100 -> 0.041165744 | AC81: =+AC11/100 -> 0.036496527 | AD81: =+AD11/100 -> 0.041028048 | AE81: =+AE11/100 -> 0.042086785 | ... AG81: =+AG11/100 -> -0.034349496 | AH81: =+AH16/100 -> 0.070178978 | AI81: =+AI16/100 -> 0.062766948 | AJ81: =+AJ16/100 -> 0.044986283 | AK81: =+AK16/100 -> 0.071520411 | AL81: =+AL16/100 -> 0.056631906 | AM81: =+AM16/100 -> 0.053216312 | AN81: =+AN16/100 -> 0.017331701 | AO81: =+AO16/100 -> 0.03195243 | ... BB81: =+BB16/100 -> 0.044239718 | BC81: =BB81 -> 0.044239718 | BD81: =BC81 -> 0.044239718 | BE81: =BD81 -> 0.044239718 | BF81: =BE81 -> 0.044239718 | BG81: =BF81 -> 0.044239718
C82: Real imports, goods excl. oil all trading partners (100% of trade of reporting country) | X82: =+X20/100 -> 0.018414241 | Y82: =+Y20/100 -> -0.087647612 | Z82: =+Z20/100 -> 0.24805094 | AA82: =+AA20/100 -> 0.60014342 | AB82: =+AB20/100 -> 0.07302419 | AC82: =+AC20/100 -> 0.052378291 | AD82: =+AD20/100 -> 0.020658222 | AE82: =+AE20/100 -> 0.38910608 | ... BB82: =+BB20/100 -> 0.050625578 | BC82: =BB82 -> 0.050625578 | BD82: =BC82 -> 0.050625578 | BE82: =BD82 -> 0.050625578 | BF82: =BE82 -> 0.050625578 | BG82: =BF82 -> 0.050625578
C83: Rwanda's import prices (import weighted 2011-13)
C84: CPI of advanced economy trading partners in US $ (for RER calc) | X84: =+X37/100 -> -0.045848033 | Y84: =+Y37/100 -> -0.030215966 | Z84: =+Z37/100 -> 0.051809724 | AA84: =+AA37/100 -> 0.14975003 | AB84: =+AB37/100 -> 0.094189651 | AC84: =+AC37/100 -> 0.040556758 | AD84: =+AD37/100 -> 0.035518247 | AE84: =+AE37/100 -> 0.082409831 | ... BB84: =+BB37/100 -> 0.020689366 | BC84: =BB84 -> 0.020689366 | BD84: =BC84 -> 0.020689366 | BE84: =BD84 -> 0.020689366 | BF84: =BE84 -> 0.020689366 | BG84: =BF84 -> 0.020689366
C85: Export deflator goods (excluding oil) in US $ (PMnonoil) | X85: =+X44/100 -> -0.011735879 | Y85: =+Y44/100 -> -0.048332074 | Z85: =+Z44/100 -> -0.017022316 | AA85: =+AA44/100 -> 0.077752179 | AB85: =+AB44/100 -> 0.091358578 | AC85: =+AC44/100 -> 0.066782683 | AD85: =+AD44/100 -> 0.081514593 | AE85: =+AE44/100 -> 0.099464278 | ... BB85: =+BB44/100 -> 0.01001426 | BC85: =BB85 -> 0.01001426 | BD85: =BC85 -> 0.01001426 | BE85: =BD85 -> 0.01001426 | BF85: =BE85 -> 0.01001426 | BG85: =BF85 -> 0.01001426
C86: Export unit value for manuf (MUV) world in US $ (for PMmanuf or PEmanuf) | X86: =+X56/100 -> 0.0021212314 | Y86: =+Y56/100 -> -0.033211254 | Z86: =+Z56/100 -> -0.019730175 | AA86: =+AA56/100 -> 0.028207618 | AB86: =+AB56/100 -> 0.06557116 | AC86: =+AC56/100 -> 0.040601999 | AD86: =+AD56/100 -> 0.022664741 | AE86: =+AE56/100 -> 0.033049342 | ... BB86: =+BB56/100 -> 0.012295675 | BC86: =BB86 -> 0.012295675 | BD86: =BC86 -> 0.012295675 | BE86: =BD86 -> 0.012295675 | BF86: =BE86 -> 0.012295675 | BG86: =BF86 -> 0.012295675
C87: Petroleum spot price (APSP) in US $ (in % change) (PMoil) | X87: =+X57/100 -> 0.56612615 | Y87: =+Y57/100 -> -0.13984177 | Z87: =+Z57/100 -> 0.020864315 | AA87: =+AA57/100 -> 0.1563331 | AB87: =+AB57/100 -> 0.30778655 | AC87: =+AC57/100 -> 0.41525926 | AD87: =+AD57/100 -> 0.20362484 | AE87: =+AE57/100 -> 0.10539633 | ... BB87: =+BB57/100 -> 0.011711425 | BC87: =BB87 -> 0.011711425 | BD87: =BC87 -> 0.011711425 | BE87: =BD87 -> 0.011711425 | BF87: =BE87 -> 0.011711425 | BG87: =BF87 -> 0.011711425
C88: Rwanda's export prices (export weighted 2011-13)
C89: Import deflator goods (excluding oil) in US $ (PEnonoil) | X89: =+X49/100 -> 0.17332813 | Y89: =+Y49/100 -> 0.29520498 | Z89: =+Z49/100 -> -0.03236489 | AA89: =+AA49/100 -> -0.16805957 | AB89: =+AB49/100 -> 0.26596328 | AC89: =+AC49/100 -> 0.27320839 | AD89: =+AD49/100 -> 0.080774752 | AE89: =+AE49/100 -> 0.15752606 | ... BB89: =+BB49/100 -> 0.013588006 | BC89: =BB89 -> 0.013588006 | BD89: =BC89 -> 0.013588006 | BE89: =BD89 -> 0.013588006 | BF89: =BE89 -> 0.013588006 | BG89: =BF89 -> 0.013588006
C90: Nonfuel commodity export price in US $ (PEcommodity-nonoil) | X90: =+X61/100 -> 0.020670925 | Y90: =+Y61/100 -> -0.12932837 | Z90: =+Z61/100 -> 0.095976651 | AA90: =+AA61/100 -> 0.12086372 | AB90: =+AB61/100 -> 0.18271849 | AC90: =+AC61/100 -> 0.080298753 | AD90: =+AD61/100 -> 0.31871885 | AE90: =+AE61/100 -> 0.25178039 | ... BB90: =+BB61/100 -> -0.00018049232 | BC90: =BB90 -> -0.00018049232 | BD90: =BC90 -> -0.00018049232 | BE90: =BD90 -> -0.00018049232 | BF90: =BE90 -> -0.00018049232 | BG90: =BF90 -> -0.00018049232
C91: end of GEE_ALL
C94: range GEE_ALL below this, updated Oct 2023 | AI94: from 2011 GEE_ALL
C95: GEE_ALL IMF-WEO Feb, 2019 | X95: 2000 | Y95: 2001 | Z95: 2002 | AA95: 2003 | AB95: 2004 | AC95: 2005 | AD95: 2006 | AE95: 2007 | AF95: 2008 | AG95: 2009 | AH95: 2010 | AI95: 2011 | AJ95: 2012 | AK95: 2013 | AL95: 2014 | AM95: 2015 | AN95: 2016 | AO95: 2017 | AP95: 2018 | AQ95: 2019 | AR95: 2020 | AS95: 2021 | AT95: 2022 | AU95: 2023 | AV95: 2024 | AW95: 2025 | AX95: 2026 | AY95: 2027 | AZ95: 2028 | BA95: 2029 | BB95: 2030
C96: World growth (Rwa export weigthed 2011-13)
C97: Real GDP growth all trading partners (100% of trade of reporting country) | X97: 0.051927484 | Y97: 0.010403432 | Z97: 0.016361825 | AA97: 0.017868178 | AB97: 0.044250751 | AC97: 0.039361602 | AD97: 0.045535909 | AE97: 0.045356452 | AF97: 0.012087644 | AG97: -0.023601996 | AH97: 0.052780421 | AI97: 0.062787462 | AJ97: 0.039768152 | AK97: 0.064928762 | AL97: 0.052721599 | AM97: 0.057512691 | AN97: 0.027686708 | AO97: 0.028091269 | AP97: 0.033740163 | AQ97: 0.030327575 | AR97: -0.017279818 | AS97: 0.055215141 | AT97: 0.061993968 | AU97: 0.0427619 | AV97: 0.047117196 | AW97: 0.05021729 | AX97: 0.050970205 | AY97: 0.050365317 | AZ97: 0.049654624 | BA97: 0.049654624 | BB97: 0.049654624
C98: Real imports, goods excl. oil all trading partners (100% of trade of reporting country) | X98: 0.11599646 | Y98: 0.097595903 | Z98: 0.12366624 | AA98: 0.075106928 | AB98: 0.19143644 | AC98: 0.20852952 | AD98: 0.076998522 | AE98: 0.31802813 | AF98: 0.10437718 | AG98: -0.073427473 | AH98: 0.13275804 | AI98: 0.058406717 | AJ98: 0.038280732 | AK98: 0.14404267 | AL98: 0.099967158 | AM98: -0.0087045797 | AN98: 0.08417455 | AO98: -0.010567066 | AP98: 0.095688011 | AQ98: -0.044687061 | AR98: -0.077510986 | AS98: 0.16128728 | AT98: 0.099041892 | AU98: 0.026116939 | AV98: 0.072416357 | AW98: 0.050167778 | AX98: 0.058440794 | AY98: 0.054686831 | AZ98: 0.041012897 | BA98: 0.041012897 | BB98: 0.041012897
C99: Rwanda's import prices (import weighted 2011-13)
C100: CPI of advanced economy trading partners in US $ (for RER calc) | X100: -0.057615118 | Y100: -0.027358147 | Z100: 0.050442112 | AA100: 0.1556876 | AB100: 0.094574839 | AC100: 0.02113156 | AD100: 0.02218634 | AE100: 0.079903942 | AF100: 0.090021195 | AG100: -0.035849518 | AH100: 0.015908439 | AI100: 0.09061823 | AJ100: -0.030081204 | AK100: 0.022950478 | AL100: 0.0070795611 | AM100: -0.10880292 | AN100: 0.00172112 | AO100: 0.025005181 | AP100: 0.043855501 | AQ100: -0.021893926 | AR100: 0.022879244 | AS100: 0.055263694 | AT100: -0.020375173 | AU100: 0.062014132 | AV100: 0.037307097 | AW100: 0.02945756 | AX100: 0.025771748 | AY100: 0.0210555 | AZ100: 0.023016232 | BA100: 0.023016232 | BB100: 0.023016232
C101: Export deflator goods (excluding oil) in US $ (PMnonoil) | X101: -0.021869771 | Y101: -0.055799421 | Z101: -0.0066551261 | AA101: 0.089277688 | AB101: 0.098067123 | AC101: 0.062362976 | AD101: 0.073004973 | AE101: 0.097107688 | AF101: 0.11756081 | AG101: -0.050048312 | AH101: 0.079986692 | AI101: 0.10230625 | AJ101: -0.00096853522 | AK101: -0.015722111 | AL101: -0.027741094 | AM101: -0.078150618 | AN101: -0.041836172 | AO101: 0.040355024 | AP101: 0.018406649 | AQ101: -0.015728731 | AR101: 0.020059845 | AS101: 0.11433 | AT101: 0.058033701 | AU101: -0.0025058346 | AV101: 0.014450024 | AW101: 0.013049914 | AX101: 0.0083885679 | AY101: 0.0082702355 | AZ101: 0.016839881 | BA101: 0.016839881 | BB101: 0.016839881
C102: Export unit value for manuf (MUV) world in US $ (for PMmanuf or PEmanuf) | X102: 0.00038920153 | Y102: -0.033380178 | Z102: -0.018491836 | AA102: 0.029262782 | AB102: 0.065453995 | AC102: 0.038809694 | AD102: 0.02039273 | AE102: 0.032698997 | AF102: 0.058553092 | AG102: -0.015546913 | AH102: 0.018440977 | AI102: 0.043881595 | AJ102: 0.024787023 | AK102: -0.029269548 | AL102: -0.004895071 | AM102: -0.029697322 | AN102: -0.052171842 | AO102: 0.00086951481 | AP102: 0.020105682 | AQ102: 0.004981097 | AR102: -0.031559187 | AS102: 0.066295506 | AT102: 0.10087688 | AU102: -0.0048428088 | AV102: 0.029596 | AW102: 0.021112018 | AX102: 0.015298689 | AY102: 0.014785953 | AZ102: 0.020309707 | BA102: 0.020309707 | BB102: 0.020309707
C103: Petroleum spot price (APSP) in US $ (in % change) (PMoil) | X103: 0.57023683 | Y103: -0.13824858 | Z103: 0.02544782 | AA103: 0.1584487 | AB103: 0.30492486 | AC103: 0.41475991 | AD103: 0.20455217 | AE103: 0.10713776 | AF103: 0.36260807 | AG103: -0.36301068 | AH103: 0.27959416 | AI103: 0.31491986 | AJ103: 0.0098777641 | AK103: -0.008799537 | AL103: -0.07531488 | AM103: -0.471463 | AN103: -0.15022149 | AO103: 0.22452431 | AP103: 0.29361225 | AQ103: -0.1036033 | AR103: -0.32013819 | AS103: 0.65806664 | AT103: 0.39151032 | AU103: -0.16473186 | AV103: -0.0070108918 | AW103: -0.049424233 | AX103: -0.042662033 | AY103: -0.038672567 | AZ103: -0.034916029 | BA103: -0.034916029 | BB103: -0.034916029
C104: Rwanda's export prices (export weighted 2011-13)
C105: Import deflator goods (excluding oil) in US $ (PEnonoil) | X105: 0.00029387631 | Y105: -0.016356411 | Z105: -0.011079879 | AA105: 0.077893988 | AB105: 0.078994281 | AC105: 0.027223667 | AD105: 0.059294805 | AE105: 0.070766385 | AF105: 0.11346602 | AG105: -0.070107899 | AH105: 0.10785164 | AI105: 0.099320527 | AJ105: 0.00049841441 | AK105: -0.027973796 | AL105: -0.025560032 | AM105: -0.074103729 | AN105: -0.027573587 | AO105: 0.022894475 | AP105: 0.020635319 | AQ105: 0.0011067987 | AR105: 0.016561178 | AS105: 0.11031108 | AT105: 0.082429049 | AU105: 0.011194727 | AV105: 0.017941975 | AW105: 0.012559615 | AX105: 0.01107144 | AY105: 0.01097352 | AZ105: 0.015750799 | BA105: 0.015750799 | BB105: 0.015750799
C106: Nonfuel commodity export price in US $ (PEcommodity-nonoil) | X106: 0.036633468 | Y106: -0.17173315 | Z106: 0.024994997 | AA106: 0.16029762 | AB106: 0.18765997 | AC106: 0.089052926 | AD106: 0.30269662 | AE106: 0.27020651 | AF106: -0.050954193 | AG106: -0.12188172 | AH106: 0.23950544 | AI106: 0.22530921 | AJ106: -0.032117326 | AK106: -0.12758953 | AL106: -0.053395235 | AM106: -0.1110593 | AN106: 0.014569103 | AO106: 0.057687782 | AP106: -0.0033970931 | AQ106: 0.035039088 | AR106: 0.12735812 | AS106: 0.16643511 | AT106: 0.043570837 | AU106: 0.037461955 | AV106: -0.0083775077 | AW106: 0.023202761 | AX106: 0.015131803 | AY106: 0.0092531357 | AZ106: 0.008792898 | BA106: 0.008792898 | BB106: 0.008792898
C107: end of GEE_ALL
C109: range GEE_ALL below this, updated August 2016 | AI109: from 2011 GEE_ALL
C110: GEE_ALL Rwanda August 31, 2016 | X110: 2000 | Y110: 2001 | Z110: 2002 | AA110: 2003 | AB110: 2004 | AC110: 2005 | AD110: 2006 | AE110: 2007 | AF110: 2008 | AG110: 2009 | AH110: 2010 | AI110: 2011 | AJ110: 2012 | AK110: 2013 | AL110: 2014 | AM110: 2015 | AN110: 2016 | AO110: 2017 | AP110: 2018 | AQ110: 2019 | AR110: 2020 | AS110: 2021 | AT110: 2022 | AU110: 2023 | AV110: 2024
C111: World growth (Rwa export weigthed 2011-13)
C112: Real GDP growth all trading partners (100% of trade of reporting country) | X112: 0.040556584 | Y112: 0.013461145 | Z112: 0.014901814 | AA112: 0.016264999 | AB112: 0.032596128 | AC112: 0.026960935 | AD112: 0.031692297 | AE112: 0.028753575 | AF112: 0.0033940042 | AG112: -0.034379213 | AH112: 0.063449025 | AI112: 0.053381522 | AJ112: 0.049944717 | AK112: 0.05040599 | AL112: 0.052226403 | AM112: 0.042726328 | AN112: 0.035512528 | AO112: 0.037829586 | AP112: 0.040222003 | AQ112: 0.0405626 | AR112: 0.0412255 | AS112: 0.042609489
C113: Real imports, goods excl. oil all trading partners (100% of trade of reporting country) | X113: 0.15068554 | Y113: 0.079137762 | Z113: 0.13104586 | AA113: 0.13963166 | AB113: 0.17949454 | AC113: 0.16317934 | AD113: 0.10895153 | AE113: 0.20331352 | AF113: 0.03456594 | AG113: -0.091865821 | AH113: 0.21535807 | AI113: 0.07162331 | AJ113: 0.025454958 | AK113: 0.068826439 | AL113: 0.071675645 | AM113: -0.013992333 | AN113: -0.0093686712 | AO113: 0.062626853 | AP113: 0.060620747 | AQ113: 0.045980483 | AR113: 0.044445065 | AS113: 0.023131095
C114: Rwanda's import prices (import weighted 2011-13)
C115: CPI of advanced economy trading partners in US $ (for RER calc) | X115: -0.065295273 | Y115: -0.018121002 | Z115: 0.054704759 | AA115: 0.16853925 | AB115: 0.10062834 | AC115: 0.030183316 | AD115: 0.03178823 | AE115: 0.090294338 | AF115: 0.083205911 | AG115: -0.046512124 | AH115: 0.012946996 | AI115: 0.080254928 | AJ115: -0.02759647 | AK115: 0.024417309 | AL115: 0.00075079167 | AM115: -0.12738075 | AN115: 0.011299189 | AO115: 0.025429197 | AP115: 0.019527479 | AQ115: 0.02156308 | AR115: 0.022239225 | AS115: 0.014237988
C116: Export deflator goods (excluding oil) in US $ (PMnonoil) | X116: -0.047858192 | Y116: -0.063302303 | Z116: 0.0044174361 | AA116: 0.11001806 | AB116: 0.098034625 | AC116: 0.053737428 | AD116: 0.094179971 | AE116: 0.096479874 | AF116: 0.11359037 | AG116: -0.050691458 | AH116: 0.10858213 | AI116: 0.085583152 | AJ116: -0.017275455 | AK116: -0.011131742 | AL116: -0.0073570502 | AM116: -0.062817601 | AN116: -0.026279887 | AO116: 0.010097807 | AP116: 0.0081371653 | AQ116: 0.0080458006 | AR116: 0.0083877038 | AS116: 0.0087081304
C117: Export unit value for manuf (MUV) world in US $ (for PMmanuf or PEmanuf) | X117: -0.022876121 | Y117: -0.019258564 | Z117: 0.00039286715 | AA117: 0.073525132 | AB117: 0.057650521 | AC117: 0.024717858 | AD117: 0.026369495 | AE117: 0.05268187 | AF117: 0.061283214 | AG117: -0.052117246 | AH117: 0.025872283 | AI117: 0.063983432 | AJ117: 0.0092741956 | AK117: -0.014819885 | AL117: -0.0097424862 | AM117: -0.029228758 | AN117: -0.021983941 | AO117: 0.0097211128 | AP117: 0.0080924166 | AQ117: 0.007964557 | AR117: 0.0096188237 | AS117: 0.0050955787
C118: Petroleum spot price (APSP) in US $ (in % change) (PMoil) | X118: 0.57023683 | Y118: -0.13824858 | Z118: 0.02544782 | AA118: 0.15798263 | AB118: 0.30695125 | AC118: 0.41298111 | AD118: 0.20463881 | AE118: 0.10665526 | AF118: 0.36424027 | AG118: -0.36335406 | AH118: 0.27928227 | AI118: 0.31605762 | AJ118: 0.0096068657 | AK118: -0.0089328372 | AL118: -0.07516202 | AM118: -0.47226546 | AN118: -0.15422281 | AO118: 0.17888206 | AP118: 0.048320968 | AQ118: 0.025409369 | AR118: 0.033921841 | AS118: 0.024151929
C119: Rwanda's export prices (export weighted 2011-13)
C120: Import deflator goods (excluding oil) in US $ (PEnonoil) | X120: 0.024638961 | Y120: -0.026601473 | Z120: -0.0052144352 | AA120: 0.072354246 | AB120: 0.086762644 | AC120: 0.024127977 | AD120: 0.031207901 | AE120: 0.077125002 | AF120: 0.089773004 | AG120: -0.043231887 | AH120: 0.076852416 | AI120: 0.093129962 | AJ120: 0.0010651682 | AK120: -0.028779303 | AL120: -0.022715219 | AM120: -0.082917349 | AN120: -0.025540341 | AO120: 0.0077340581 | AP120: 0.003806236 | AQ120: 0.0063917942 | AR120: 0.0083456671 | AS120: 0.007243783
C121: Nonfuel commodity export price in US $ (PEcommodity-nonoil) | X121: 0.031964789 | Y121: -0.13094913 | Z121: -0.015689938 | AA121: 0.080767824 | AB121: 0.19668668 | AC121: 0.16688219 | AD121: 0.31649971 | AE121: 0.1273081 | AF121: 0.058202501 | AG121: -0.12421034 | AH121: 0.30259121 | AI121: 0.19630887 | AJ121: -0.14158283 | AK121: -0.097870346 | AL121: -0.038339572 | AM121: -0.13622833 | AN121: -0.074655853 | AO121: 0.033012976 | AP121: 0.014060875 | AQ121: 0.0020891752 | AR121: 0.0044344398 | AS121: 0.0046672097
C122: end of GEE_ALL
C123: end of GEE_ALL
C124: Previous Editions
C125: range GEE_ALL below this, updated March 2016 | AI125: from 2011 GEE_ALL
C126: GEE_ALL Rwanda March 2016 | X126: 2000 | Y126: 2001 | Z126: 2002 | AA126: 2003 | AB126: 2004 | AC126: 2005 | AD126: 2006 | AE126: 2007 | AF126: 2008 | AG126: 2009 | AH126: 2010 | AI126: 2011 | AJ126: 2012 | AK126: 2013 | AL126: 2014 | AM126: 2015 | AN126: 2016 | AO126: 2017 | AP126: 2018 | AQ126: 2019 | AR126: 2020 | AS126: 2021
C127: World growth (Rwa export weigthed 2011-13)
C128: Real GDP growth all trading partners (100% of trade of reporting country) | X128: 0.040601291 | Y128: 0.01349403 | Z128: 0.0149463 | AA128: 0.016165992 | AB128: 0.03255533 | AC128: 0.026988865 | AD128: 0.031792198 | AE128: 0.028809026 | AF128: 0.003492203 | AG128: -0.034315499 | AH128: 0.063390286 | AI128: 0.053404222 | AJ128: 0.049433063 | AK128: 0.049673277 | AL128: 0.051783517 | AM128: 0.044800772 | AN128: 0.042422849 | AO128: 0.043143399 | AP128: 0.043031761 | AQ128: 0.044691184 | AR128: 0.043275684 | AS128: 0.043480727
...

Sheet Quarterly
A1: Refresh Step:
A2: On EcXL Refresh tab, click on refresh WORKSHEET. Note that all worksheets will be updated simultaneously.
C3: Rwanda: Selected Composite Indicators of Trading Partners (GEE)
C4: (Percent change from four quarters earlier)
C5: 45175.161
A6: DATASET | B6: Series_code | D6: 2011Q1 | E6: 2011Q2 | F6: 2011Q3 | G6: 2011Q4 | H6: 2012Q1 | I6: 2012Q2 | J6: 2012Q3 | K6: 2012Q4 | L6: 2013Q1 | M6: 2013Q2 | N6: 2013Q3 | O6: 2013Q4 | P6: 2014Q1 | Q6: 2014Q2 | R6: 2014Q3 | S6: 2014Q4 | T6: 2015Q1 | U6: 2015Q2 | V6: 2015Q3 | W6: 2015Q4 | X6: 2016Q1 | Y6: 2016Q2 | Z6: 2016Q3 | AA6: 2016Q4 | AB6: 2017Q1 | AC6: 2017Q2 | AD6: 2017Q3 | AE6: 2017Q4 | AF6: 2018Q1 | AG6: 2018Q2 | AH6: 2018Q3 | AI6: 2018Q4 | AJ6: 2019Q1 | AK6: 2019Q2 | AL6: 2019Q3 | AM6: 2019Q4 | AN6: 2020Q1 | AO6: 2020Q2 | AP6: 2020Q3 | AQ6: 2020Q4 | AR6: 2021Q1 | AS6: 2021Q2 | AT6: 2021Q3 | AU6: 2021Q4 | AV6: 2022Q1 | AW6: 2022Q2 | AX6: 2022Q3 | AY6: 2022Q4 | AZ6: 2023Q1 | BA6: 2023Q2 | BB6: 2023Q3 | BC6: 2023Q4 | BD6: 2024Q1 | BE6: 2024Q2 | BF6: 2024Q3 | BG6: 2024Q4 | BH6: 2025Q1 | BI6: 2025Q2 | BJ6: 2025Q3 | BK6: 2025Q4 | BL6: 2026Q1 | BM6: 2026Q2 | BN6: 2026Q3 | BO6: 2026Q4 | BP6: 2027Q1 | BQ6: 2027Q2
C7: 1) Foreign Output and Demand of Trading Partners 1/
C9: Advanced economy partners | D9: Export-weighted averages | BH9: Export-weighted averages
A11: IMF.RES.GEE:GEE_LIVE | B11: RWA.NGDP_R_YOY_WX.G110.Q | C11: Real GDP | D11: 3.7088979 | E11: 2.4151907 | F11: 2.0693431 | G11: 1.1863702 | H11: 0.60867503 | I11: 0.75645902 | J11: 1.0258543 | K11: 1.2125803 | L11: 1.077944 | M11: 1.5335221 | N11: 1.7864259 | O11: 2.1993331 | P11: 2.6102472 | Q11: 2.3892892 | R11: 2.553744 | S11: 2.6903779 | T11: 2.7917213 | U11: 2.9143259 | V11: 2.4941019 | W11: 2.2342649 | X11: 1.7245074 | Y11: 1.9764592 | Z11: 2.224742 | AA11: 2.7035474 | AB11: 2.943878 | AC11: 2.7621204 | AD11: 2.8492247 | AE11: 2.9169694 | AF11: 3.0241371 | AG11: 2.7091133 | AH11: 2.1120321 | AI11: 1.4047926 | AJ11: 1.3400088 | AK11: 1.3247562 | AL11: 0.82858118 | AM11: 0.79464985 | AN11: -2.2517551 | AO11: -11.7763 | AP11: -3.537421 | AQ11: -3.0680661 | AR11: 1.3139131 | AS11: 14.520156 | AT11: 6.5023559 | AU11: 6.6169283 | AV11: 4.338366 | AW11: 3.0071215 | AX11: 1.429353 | AY11: 0.73759254 | AZ11: 1.6534685 | BA11: 0.66304784 | BB11: 0.92178132 | BC11: 0.860798 | BD11: 0.89642937 | BE11: 1.2757883 | BF11: 1.5692842 | BG11: 2.0154355 | BH11: 2.1620896 | BI11: 2.0451172 | BJ11: 1.9005987 | BK11: 1.2832631 | BL11: 1.1709868 | BM11: 1.399689 | BN11: 1.668627 | BO11: 2.1732236 | BP11: 1.8172647
A12: IMF.RES.GEE:GEE_LIVE | B12: RWA.NTDD_R_YOY_WX.G110.Q | C12: Real total domestic demand | D12: 2.3043688 | E12: 2.5833791 | F12: 3.6420021 | G12: 2.3539326 | H12: 1.7807112 | I12: 1.1987903 | J12: 0.98620443 | K12: 0.27523407 | L12: 1.2059313 | M12: 0.75490549 | N12: 1.6795146 | O12: 2.6665095 | P12: 2.4159473 | Q12: 2.5858946 | R12: 2.7651057 | S12: 3.5336361 | T12: 2.590347 | U12: 5.5458403 | V12: 2.1471933 | W12: 2.6189552 | X12: 3.0125655 | Y12: 0.65043561 | Z12: 3.8224072 | AA12: 2.4286459 | AB12: 3.2547152 | AC12: 4.8994764 | AD12: 3.1170006 | AE12: 3.2715004 | AF12: 3.1301977 | AG12: 1.8086159 | AH12: 2.9606588 | AI12: 2.8043752 | AJ12: 2.49038 | AK12: 3.045609 | AL12: 0.67055316 | AM12: 1.899072 | AN12: 0.23969659 | AO12: -13.291168 | AP12: -2.7002415 | AQ12: -2.1768875 | AR12: -1.7186743 | AS12: 15.262335 | AT12: 6.1716468 | AU12: 4.2702248 | AV12: 4.3360331 | AW12: 5.5383462 | AX12: 0.93924628 | AY12: 1.0096844 | AZ12: 3.6615675 | BA12: -0.28129514 | BB12: 2.0751432 | BC12: 2.1287819 | BD12: 0.35628523 | BE12: 0.37298583 | BF12: 2.2615658 | BG12: 1.8047375 | BH12: 1.6231516 | BI12: 3.1506985 | BJ12: 1.9117545 | BK12: 1.6581699 | BL12: 2.3551461 | BM12: 1.2445736 | BN12: 1.0872004 | BO12: 1.6372476 | BP12: 1.3378801
C14: All countries 2/
A16: IMF.RES.GEE:GEE_LIVE | B16: RWA.NGDP_R_YOY_WX.G001.Q | C16: Real GDP | D16: 6.7232326 | E16: 5.897303 | F16: 5.3719823 | G16: 4.6258937 | H16: 3.2061128 | I16: 3.9380161 | J16: 4.7805378 | K16: 5.4446554 | L16: 7.7354097 | M16: 7.4679977 | N16: 7.0854511 | O16: 6.7022152 | P16: 5.9226244 | Q16: 5.8258409 | R16: 5.5326039 | S16: 5.7043268 | T16: 6.768731 | U16: 5.8031562 | V16: 4.9641943 | W16: 4.0075693 | X16: 1.1807885 | Y16: 1.4844765 | Z16: 1.8037827 | AA16: 2.1760999 | AB16: 2.6795702 | AC16: 3.0340426 | AD16: 3.4609989 | AE16: 3.7146633 | AF16: 5.489851 | AG16: 4.8141676 | AH16: 3.9641894 | AI16: 3.170954 | AJ16: 2.3752887 | AK16: 1.9790449 | AL16: 1.3777213 | AM16: 0.95979908 | AN16: -3.4518142 | AO16: -3.9168894 | AP16: -0.51275222 | AQ16: 0.94824626 | AR16: 5.1315543 | AS16: 7.7478608 | AT16: 5.9311029 | AU16: 6.3110008 | AV16: 7.1742545 | AW16: 6.5132578 | AX16: 6.1818504 | AY16: 5.746582 | AZ16: 6.2660507 | BA16: 5.7326161 | BB16: 5.3564912 | BC16: 4.8353628 | BD16: 3.0954752 | BE16: 3.4748063 | BF16: 3.8878072 | BG16: 4.3789339 | BH16: 5.3785835 | BI16: 5.3344838 | BJ16: 5.2473334 | BK16: 5.0717087 | BL16: 5.0900943 | BM16: 5.0035629 | BN16: 5.0220186 | BO16: 5.0058176 | BP16: 4.6671729
C17: Real imports
A18: IMF.RES.GEE:GEE_LIVE | B18: RWA.TM_R_YOY_WX.G001.Q | C18: Goods and services | D18: 7.2835596 | E18: 5.0942825 | F18: 2.9496807 | G18: 0.84884271 | H18: -9.6350606 | I18: -5.8794058 | J18: -1.9676623 | K18: 2.1066571 | L18: 13.793399 | M18: 13.104708 | N18: 12.420185 | O18: 11.739805 | P18: 17.349257 | Q18: 12.567005 | R18: 7.9796402 | S18: 3.5792214 | T18: -11.734234 | U18: -8.170175 | V18: -4.4622033 | W18: -0.60450854 | X18: 12.340541 | Y18: 10.269657 | Z18: 8.236947 | AA18: 6.2417083 | AB18: -1.1799437 | AC18: 0.46505526 | AD18: 2.1374376 | AE18: 3.837659 | AF18: 15.321844 | AG18: 10.686454 | AH18: 6.2373837 | AI18: 1.9671454 | AJ18: -8.8418403 | AK18: -8.1850939 | AL18: -7.523616 | AM18: -6.8573724 | AN18: -15.225386 | AO18: -8.9185826 | AP18: -2.1425846 | AQ18: 5.1375135 | AR18: 29.43335 | AS18: 27.321685 | AT18: 25.244471 | AU18: 23.201147 | AV18: 25.293717 | AW18: 20.648348 | AX18: 16.17521 | AY18: 11.867918 | AZ18: -0.5869458 | BA18: 0.83050265 | BB18: 2.2681613 | BC18: 3.7263184 | BD18: 7.6803589 | BE18: 7.4117877 | BF18: 7.1438864 | BG18: 6.8766532 | BH18: 6.3453634 | BI18: 6.236019 | BJ18: 6.126787 | BK18: 6.0176673 | BL18: 5.9609712 | BM18: 5.811104 | BN18: 5.6614487 | BO18: 5.5120051 | BP18: 5.0320683
A19: IMF.RES.GEE:GEE_LIVE | B19: RWA.TMG_R_YOY_WX.G001.Q | C19: Goods | D19: 5.9323723 | E19: 4.0909287 | F19: 2.2814953 | G19: 0.50351564 | H19: -9.4471441 | I19: -5.5371887 | J19: -1.4584066 | K19: 2.7964921 | L19: 16.123206 | M19: 14.727109 | N19: 13.347797 | O19: 11.985068 | P19: 15.126271 | Q19: 10.851205 | R19: 6.7348883 | S19: 2.7714257 | T19: -11.545842 | U19: -8.0244015 | V19: -4.3627693 | W19: -0.5553641 | X19: 11.334538 | Y19: 9.8677858 | Z19: 8.4203567 | AA19: 6.9919965 | AB19: 2.6929198 | AC19: 3.1642937 | AD19: 3.6378312 | AE19: 4.1135424 | AF19: 11.282613 | AG19: 7.4529909 | AH19: 3.7551596 | AI19: 0.18458347 | AJ19: -9.7505121 | AK19: -8.7077001 | AL19: -7.6528388 | AM19: -6.5857887 | AN19: -11.698602 | AO19: -6.7659288 | AP19: -1.5577075 | AQ19: 3.9414543 | AR19: 21.388816 | AS19: 20.009073 | AT19: 18.645014 | AU19: 17.296458 | AV19: 16.404129 | AW19: 14.791858 | AX19: 13.201918 | AY19: 11.634 | AZ19: 8.3603196 | BA19: 8.0038939 | BB19: 7.6486406 | BC19: 7.2945558 | BD19: 6.0359686 | BE19: 6.1687362 | BF19: 6.30167 | BG19: 6.4347703 | BH19: 7.1680574 | BI19: 6.8867871 | BJ19: 6.606255 | BK19: 6.3264592 | BL19: 5.7433867 | BM19: 5.6600082 | BN19: 5.5766955 | BO19: 5.4934485 | BP19: 5.2136615
A20: IMF.RES.GEE:GEE_LIVE | B20: RWA.TMGXO_R_YOY_WX.G001.Q | C20: Excluding oil | D20: 6.5573911 | E20: 4.4991768 | F20: 2.480718 | G20: 0.50124688 | H20: -10.105108 | I20: -6.0857779 | J20: -1.8867376 | K20: 2.5000479 | L20: 16.356325 | M20: 14.875701 | N20: 13.413917 | O20: 11.970735 | P20: 16.461376 | Q20: 11.143353 | R20: 6.0681685 | S20: 1.2247346 | T20: -15.592823 | U20: -11.598941 | V20: -7.4160806 | W20: -3.0353007 | X20: 8.9501119 | Y20: 8.4092927 | Z20: 7.8711581 | AA20: 7.3356948 | AB20: 5.3831684 | AC20: 5.7451466 | AD20: 6.1083681 | AE20: 6.4728373 | AF20: 15.122987 | AG20: 10.196098 | AH20: 5.4800643 | AI20: 0.96586147 | AJ20: -10.839593 | AK20: -9.996022 | AL20: -9.1444693 | AM20: -8.2848599 | AN20: -15.470257 | AO20: -9.5237545 | AP20: -3.1589266 | AQ20: 3.6536546 | AR20: 26.282146 | AS20: 24.184702 | AT20: 22.122094 | AU20: 20.093745 | AV20: 18.87665 | AW20: 16.421225 | AX20: 14.016517 | AY20: 11.66148 | AZ20: 8.9213961 | BA20: 7.0528267 | BB20: 5.2163129 | BC20: 3.4113049 | BD20: -4.1448859 | BE20: -2.2409609 | BF20: -0.29921914 | BG20: 1.6810905 | BH20: 7.0489973 | BI20: 6.8225473 | BJ20: 6.5965764 | BK20: 6.3710835 | BL20: 5.9798928 | BM20: 5.8614075 | BN20: 5.7430546 | BO20: 5.624834 | BP20: 5.2127641
C22: Real exports | D22: Import-weighted averages | BH22: Import-weighted averages
A23: IMF.RES.GEE:GEE_LIVE | B23: RWA.TX_R_YOY_WM.G001.Q | C23: Goods and services | D23: 9.2699159 | E23: 8.5330008 | F23: 7.8010555 | G23: 7.0740464 | H23: 5.5977153 | I23: 5.4002071 | J23: 5.2030684 | K23: 5.0062984 | L23: 4.489982 | M23: 4.4889354 | N23: 4.4878889 | O23: 4.4868423 | P23: 5.0867503 | Q23: 4.6889186 | R23: 4.292593 | S23: 3.8977677 | T23: 3.3831114 | U23: 3.0880484 | V23: 2.7938274 | W23: 2.5004463 | X23: 1.413569 | Y23: 1.6181328 | Z23: 1.8231094 | AA23: 2.0284994 | AB23: 1.5250216 | AC23: 2.2442909 | AD23: 2.9686561 | AE23: 3.6981531 | AF23: 6.4887422 | AG23: 5.8242054 | AH23: 5.1638156 | AI23: 4.507547 | AJ23: 6.7645007 | AK23: 4.1928082 | AL23: 1.6830613 | AM23: -0.766232 | AN23: -12.072136 | AO23: -8.4557645 | AP23: -4.6906554 | AQ23: -0.77069172 | AR23: 11.561526 | AS23: 10.407956 | AT23: 9.2663139 | AU23: 8.1364769 | AV23: 5.8683618 | AW23: 5.5063749 | AX23: 5.1456256 | AY23: 4.7861099 | AZ23: 2.9178579 | BA23: 3.5405144 | BB23: 4.1669381 | BC23: 4.7971516 | BD23: 6.4351423 | BE23: 6.3541509 | BF23: 6.2732211 | BG23: 6.1923529 | BH23: 6.5068447 | BI23: 6.1348209 | BJ23: 5.7640966 | BK23: 5.3946672 | BL23: 4.49769 | BM23: 4.4743891 | BN23: 4.4510934 | BO23: 4.4278029
A24: IMF.RES.GEE:GEE_LIVE | B24: RWA.TXG_R_YOY_WM.G001.Q | C24: Goods | D24: 9.0741107 | E24: 8.3344241 | F24: 7.5997538 | G24: 6.8700656 | H24: 5.2447425 | I24: 5.1514447 | J24: 5.0582297 | K24: 4.9650973 | L24: 5.2635556 | M24: 4.9444469 | N24: 4.6263057 | O24: 4.3091289 | P24: 3.8469448 | Q24: 3.5806551 | R24: 3.3150482 | S24: 3.0501224 | T24: 2.3992305 | U24: 2.4027054 | V24: 2.4061805 | W24: 2.4096556 | X24: 2.31901 | Y24: 2.3524541 | Z24: 2.3859092 | AA24: 2.4193753 | AB24: 1.8548522 | AC24: 2.3242931 | AD24: 2.7958976 | AE24: 3.2696757 | AF24: 4.9476572 | AG24: 4.6358201 | AH24: 4.3249096 | AI24: 4.0149229 | AJ24: 5.6751916 | AK24: 4.0397575 | AL24: 2.4296333 | AM24: 0.84442754 | AN24: -7.1297473 | AO24: -4.4019406 | AP24: -1.5940121 | AQ24: 1.2963915 | AR24: 11.755413 | AS24: 9.9020566 | AT24: 8.0794365 | AU24: 6.2870429 | AV24: 1.2354629 | AW24: 1.7145637 | AX24: 2.1959318 | AY24: 2.679578 | AZ24: 3.0852774 | BA24: 3.6165433 | BB24: 4.1505473 | BC24: 4.6873033 | BD24: 5.8730892 | BE24: 5.9348496 | BF24: 5.9966459 | BG24: 6.0584783 | BH24: 6.7760324 | BI24: 6.3489794 | BJ24: 5.9236343 | BK24: 5.4999905 | BL24: 4.4586448 | BM24: 4.4402088 | BN24: 4.4217761 | BO24: 4.4033466
A25: IMF.RES.GEE:GEE_LIVE | B25: RWA.TXGXO_R_YOY_WM.G001.Q | C25: Excluding oil | D25: 8.7212498 | E25: 8.1974839 | F25: 7.6762413 | G25: 7.1575099 | H25: 6.2120451 | I25: 6.0076854 | J25: 5.8037189 | K25: 5.6001449 | L25: 5.2978425 | M25: 5.182876 | N25: 5.0680351 | O25: 4.9533195 | P25: 5.3907934 | Q25: 4.8671584 | R25: 4.346125 | S25: 3.8276805 | T25: 2.6362244 | U25: 2.5914017 | V25: 2.5465985 | W25: 2.5018148 | X25: 2.1786056 | Y25: 2.2896407 | Z25: 2.4007965 | AA25: 2.5120731 | AB25: 2.0540713 | AC25: 2.5756068 | AD25: 3.0998074 | AE25: 3.626687 | AF25: 5.4904941 | AG25: 5.146252 | AH25: 4.8031333 | AI25: 4.4611342 | AJ25: 6.2259241 | AK25: 4.4929185 | AL25: 2.7881858 | AM25: 1.1112646 | AN25: -7.5541993 | AO25: -4.5076681 | AP25: -1.360739 | AQ25: 1.8898963 | AR25: 14.102402 | AS25: 11.709183 | AT25: 9.3661593 | AU25: 7.0722793 | AV25: 0.93237198 | AW25: 1.3271847 | AX25: 1.7235417 | AY25: 2.1214492 | AZ25: 1.466557 | BA25: 2.5825231 | BB25: 3.710763 | BC25: 4.8514117 | BD25: 7.8336772 | BE25: 7.7248167 | BF25: 7.616066 | BG25: 7.5074252 | BH25: 8.3202275 | BI25: 7.5582274 | BJ25: 6.8015878 | BK25: 6.050271 | BL25: 4.2183918 | BM25: 4.1787077 | BN25: 4.1390387 | BO25: 4.0993847
C27: 2) Foreign Prices and Costs of Trading Partners 1/
C29: Advanced economy partners | D29: Import-weighted averages | BH29: Import-weighted averages
C31: GDP deflators
A32: IMF.RES.GEE:GEE_LIVE | B32: RWA.NGDP_D_YOY_WM.G110.Q | C32: In national currency | D32: 1.3045049 | E32: 1.276411 | F32: 1.2417963 | G32: 1.3490287 | H32: 1.5789996 | I32: 1.3391681 | J32: 1.2219555 | K32: 1.1215118 | L32: 0.99867422 | M32: 1.3357873 | N32: 1.3891862 | O32: 1.1574481 | P32: 1.1798783 | Q32: 1.1151406 | R32: 1.1425447 | S32: 1.2754628 | T32: 1.7346108 | U32: 1.8386569 | V32: 1.8132109 | W32: 1.6806122 | X32: 1.091672 | Y32: 1.3274096 | Z32: 1.0246132 | AA32: 1.1848216 | AB32: 1.561798 | AC32: 1.0844901 | AD32: 1.5599646 | AE32: 1.4247702 | AF32: 1.2109422 | AG32: 1.5887478 | AH32: 1.597049 | AI32: 1.6948262 | AJ32: 1.3857825 | AK32: 1.1975828 | AL32: 1.2025992 | AM32: 1.0806571 | AN32: 1.5096016 | AO32: 1.9416225 | AP32: 1.3278301 | AQ32: 1.5129946 | AR32: 1.7865441 | AS32: 1.9842238 | AT32: 3.3568118 | AU32: 4.017858 | AV32: 4.9518389 | AW32: 5.48145 | AX32: 4.9554387 | AY32: 5.1103553 | AZ32: 4.5433176 | BA32: 3.8022823 | BB32: 3.8378301 | BC32: 3.6678704 | BD32: 3.1882114 | BE32: 3.3360593 | BF32: 2.8424367 | BG32: 2.907733 | BH32: 2.4425571 | BI32: 2.3412716 | BJ32: 2.644138 | BK32: 1.636724 | BL32: 1.853154 | BM32: 1.7005719 | BN32: 2.0289397 | BO32: 2.4704127
A33: IMF.RES.GEE:GEE_LIVE | B33: RWA.NGDP_D_USD_YOY_WM.G110.Q | C33: In U.S. dollars | D33: 3.1524385 | E33: 12.728283 | F33: 10.393686 | G33: 1.569644 | H33: -0.40104999 | I33: -5.9963386 | J33: -6.4407929 | K33: -0.17502472 | L33: 0.99270855 | M33: 1.174229 | N33: 2.8891228 | O33: 2.4126635 | P33: 2.448746 | Q33: 5.1852535 | R33: 2.2396693 | S33: -5.3107242 | T33: -10.732103 | U33: -12.320721 | V33: -11.47372 | W33: -7.3655686 | X33: -1.9233097 | Y33: 2.1116673 | Z33: 3.1897812 | AA33: 0.85468082 | AB33: 0.39694538 | AC33: -0.36725602 | AD33: 3.7459401 | AE33: 7.3916113 | AF33: 12.07621 | AG33: 7.3665255 | AH33: 0.86844182 | AI33: -0.68600401 | AJ33: -4.3896725 | AK33: -3.6616685 | AL33: -2.1005857 | AM33: -0.79366379 | AN33: -0.96435458 | AO33: 0.059170885 | AP33: 4.7607265 | AQ33: 7.4667042 | AR33: 9.293011 | AS33: 9.8346675 | AT33: 4.4723626 | AU33: 0.33076522 | AV33: -1.1938898 | AW33: -5.110796 | AX33: -8.264208 | AY33: -5.9904148 | AZ33: -0.45049479 | BA33: 3.7957863 | BB33: 8.5063483 | BC33: 7.1267991 | BD33: 2.29993 | BE33: 0.80593332 | BF33: 2.7518353 | BG33: 1.5064767 | BH33: -1.1167516 | BI33: 6.1932771 | BJ33: 6.4819093 | BK33: 6.4934255 | BL33: 9.2690784 | BM33: 3.3230924 | BN33: 1.7169478 | BO33: 3.5150519
C35: Consumer Prices
A36: IMF.RES.GEE:GEE_LIVE | B36: RWA.PCPI_YOY_WM.G110.Q | C36: In national currency | D36: 2.6092316 | E36: 2.929009 | F36: 3.1247164 | G36: 2.9316639 | H36: 2.6506837 | I36: 2.2733012 | J36: 2.0224425 | K36: 1.9647378 | L36: 1.6480038 | M36: 1.3659795 | N36: 1.4780231 | O36: 1.2058202 | P36: 1.1303397 | Q36: 1.3369082 | R36: 1.1125585 | S36: 0.79986453 | T36: 0.35047944 | U36: 0.52116002 | V36: 0.4251456 | W36: 0.4514119 | X36: 0.47018062 | Y36: 0.36071345 | Z36: 0.53810259 | AA36: 0.95844442 | AB36: 1.6597156 | AC36: 1.4768054 | AD36: 1.5275462 | AE36: 1.4137619 | AF36: 1.29927 | AG36: 1.599748 | AH36: 1.8831446 | AI36: 1.7919104 | AJ36: 1.2354051 | AK36: 1.3374846 | AL36: 0.91283122 | AM36: 0.97915382 | AN36: 1.0646722 | AO36: 0.17144915 | AP36: 0.20044868 | AQ36: -0.0017762376 | AR36: 0.97884255 | AS36: 1.9075838 | AT36: 2.5576001 | AU36: 4.0501027 | AV36: 5.1926038 | AW36: 6.8754328 | AX36: 7.8348808 | AY36: 8.1129594 | AZ36: 6.5183441 | BA36: 4.8754079 | BB36: 3.8836767 | BC36: 2.5665475 | BD36: 2.5954878 | BE36: 2.5801631 | BF36: 2.3022943 | BG36: 2.2955669 | BH36: 2.4468777 | BI36: 2.1947462 | BJ36: 2.1128721 | BK36: 2.1187703 | BL36: 1.8544595 | BM36: 1.9967616 | BN36: 2.0195077 | BO36: 1.9564787
A37: IMF.RES.GEE:GEE_LIVE | B37: RWA.PCPI_USD_YOY_WM.G110.Q | C37: In U.S. dollars | D37: 4.4767111 | E37: 14.561172 | F37: 12.44518 | G37: 3.1602594 | H37: 0.65584304 | I37: -5.1250045 | J37: -5.6960914 | K37: 0.65820764 | L37: 1.6377989 | M37: 1.1991478 | N37: 2.9716307 | O37: 2.4558121 | P37: 2.3944625 | Q37: 5.4198794 | R37: 2.2154869 | S37: -5.747306 | T37: -11.953235 | U37: -13.467499 | V37: -12.701036 | W37: -8.5079247 | X37: -2.5255584 | Y37: 1.1400406 | Z37: 2.7053008 | AA37: 0.63703491 | AB37: 0.49304974 | AC37: 0.01625504 | AD37: 3.7181611 | AE37: 7.3904905 | AF37: 12.184088 | AG37: 7.3892442 | AH37: 1.1537559 | AI37: -0.59028974 | AJ37: -4.5280458 | AK37: -3.525363 | AL37: -2.3780691 | AM37: -0.88934809 | AN37: -1.3975098 | AO37: -1.670481 | AP37: 3.6118902 | AQ37: 5.8809057 | AR37: 8.4430745 | AS37: 9.763861 | AT37: 3.6711706 | AU37: 0.35961228 | AV37: -0.97158544 | AW37: -3.8774575 | AX37: -5.7728706 | AY37: -3.3209471 | AZ37: 1.4102332 | BA37: 4.8641324 | BB37: 8.5537147 | BC37: 5.9816244 | BD37: 1.7158307 | BE37: 0.07598631 | BF37: 2.2162118 | BG37: 0.90698147 | BH37: -1.1135385 | BI37: 6.034565 | BJ37: 5.9226845 | BK37: 6.9926493 | BL37: 9.267784 | BM37: 3.6239784 | BN37: 1.7094832 | BO37: 2.9961632
C39: All countries 2/
C41: Export deflators in U.S. dollars
A42: IMF.RES.GEE:GEE_LIVE | B42: RWA.TX_D_YOY_WM.G001.Q | C42: Goods and services | D42: 16.172816 | E42: 13.127411 | F42: 10.16184 | G42: 7.2740102 | H42: 0.68896684 | I42: 0.43061387 | J42: 0.17292379 | K42: -0.084105086 | L42: 0.048723376 | M42: -0.47788011 | N42: -1.0017118 | O42: -1.5227864 | P42: 0.79940888 | Q42: -1.6181477 | R42: -3.9777221 | S42: -6.2807048 | T42: -14.12083 | U42: -12.466707 | V42: -10.780724 | W42: -9.0622674 | X42: -8.4603918 | Y42: -6.0026983 | Z42: -3.4790196 | AA42: -0.88758417 | AB42: 6.4843788 | AC42: 6.0638347 | AD42: 5.6449515 | AE42: 5.2277226 | AF42: 6.659435 | AG42: 5.0667574 | AH42: 3.4978622 | AI42: 1.9523943 | AJ42: -1.0013915 | AK42: -1.5640841 | AL42: -2.1235784 | AM42: -2.6798926 | AN42: -10.318419 | AO42: -6.0669207 | AP42: -1.6138738 | AQ42: 3.0502768 | AR42: 17.606118 | AS42: 16.226025 | AT42: 14.862127 | AU42: 13.514235 | AV42: 15.771035 | AW42: 12.070496 | AX42: 8.4882412 | AY42: 5.0204911 | AZ42: -4.8214182 | BA42: -3.8076614 | BB42: -2.783107 | BC42: -1.74764 | BD42: 0.78756248 | BE42: 0.82963615 | BF42: 0.8717274 | BG42: 0.91383621 | BH42: 1.278183 | BI42: 1.0980146 | BJ42: 0.91816665 | BK42: 0.73863868 | BL42: 0.10634283 | BM42: 0.22581303 | BN42: 0.34542581 | BO42: 0.46518135
A43: IMF.RES.GEE:GEE_LIVE | B43: RWA.TXG_D_YOY_WM.G001.Q | C43: Goods | D43: 18.564645 | E43: 14.858772 | F43: 11.26873 | G43: 7.7908992 | H43: -0.039856724 | I43: -0.35724567 | J43: -0.67362686 | K43: -0.98900349 | L43: -1.2166551 | M43: -1.6073545 | N43: -1.9965087 | O43: -2.3841236 | P43: 0.73493918 | Q43: -2.0024991 | R43: -4.6655483 | S43: -7.2562301 | T43: -15.869805 | U43: -14.120062 | V43: -12.333927 | W43: -10.510644 | X43: -9.8266154 | Y43: -7.229495 | Z43: -4.5575738 | AA43: -1.8086975 | AB43: 5.9372488 | AC43: 5.5228239 | AD43: 5.1100202 | AE43: 4.6988313 | AF43: 5.9009666 | AG43: 4.5432067 | AH43: 3.2028547 | AI43: 1.8796874 | AJ43: -1.6210933 | AK43: -1.5348936 | AL43: -1.4486185 | AM43: -1.3622677 | AN43: -6.4553276 | AO43: -2.7319068 | AP43: 1.1397198 | AQ43: 5.1654513 | AR43: 18.082763 | AS43: 16.47146 | AT43: 14.882144 | AU43: 13.314515 | AV43: 15.602908 | AW43: 11.531567 | AX43: 7.6036123 | AY43: 3.8139934 | AZ43: -7.2879127 | BA43: -5.9209171 | BB43: -4.5337658 | BC43: -3.1261616 | BD43: 0.12910176 | BE43: 0.33731535 | BF43: 0.54596191 | BG43: 0.75504234 | BH43: 1.5520013 | BI43: 1.364678 | BJ43: 1.1777003 | BK43: 0.99106743 | BL43: 0.46508401 | BM43: 0.50258409 | BN43: 0.54009817 | BO43: 0.57762625
A44: IMF.RES.GEE:GEE_LIVE | B44: RWA.TXGXO_D_YOY_WM.G001.Q | C44: Excluding oil | D44: 15.63013 | E44: 12.421314 | F44: 9.3015441 | G44: 6.2683502 | H44: -0.83272799 | I44: -0.94095435 | J44: -1.0490626 | K44: -1.1570529 | L44: -1.0251196 | M44: -1.3119928 | N44: -1.5980345 | O44: -1.8832472 | P44: 0.12889265 | Q44: -1.701279 | R44: -3.4979984 | S44: -5.2618772 | T44: -11.232317 | U44: -10.032551 | V44: -8.8165692 | W44: -7.5841526 | X44: -7.4369332 | Y44: -5.4786791 | Z44: -3.4789964 | AA44: -1.4370086 | AB44: 4.6213475 | AC44: 4.0892207 | AD44: 3.5598003 | AE44: 3.0330727 | AF44: 2.9895358 | AG44: 2.2391844 | AH44: 1.4942998 | AI44: 0.75484228 | AJ44: -2.532339 | AK44: -1.6521371 | AL44: -0.76398648 | AM44: 0.13218481 | AN44: -0.71689327 | AO44: 1.4343415 | AP44: 3.6321885 | AQ44: 5.8776577 | AR44: 13.794031 | AS44: 12.382196 | AT44: 10.987877 | AU44: 9.6108571 | AV44: 10.368146 | AW44: 7.6161984 | AX44: 4.9328687 | AY44: 2.3164458 | AZ44: -5.737555 | BA44: -4.5980094 | BB44: -3.4446878 | BC44: -2.2774237 | BD44: -0.04625971 | BE44: 0.44257565 | BF44: 0.93380172 | BG44: 1.4274302 | BH44: 3.2040039 | BI44: 2.8377554 | BJ44: 2.4728067 | BK44: 2.1091531 | BL44: 1.2990761 | BM44: 1.2313566 | BN44: 1.1636824 | BO44: 1.0960533
C46: Import deflators in U.S. dollars | D46: Export-weighted averages in U.S. dollars | BH46: Export-weighted averages in U.S. dollars
A47: IMF.RES.GEE:GEE_LIVE | B47: RWA.TM_D_YOY_WX.G001.Q | C47: Goods and services | D47: 12.904371 | E47: 11.300016 | F47: 9.7184592 | G47: 8.1593759 | H47: 6.1717037 | I47: 4.9382084 | J47: 3.7190438 | K47: 2.5140434 | L47: -0.88772211 | M47: -0.61183902 | N47: -0.33518799 | O47: -0.057766903 | P47: 3.1469495 | Q47: 1.4760024 | R47: -0.16787591 | S47: -1.7851239 | T47: -5.9988089 | U47: -5.7433945 | V47: -5.487286 | W47: -5.2304817 | X47: -5.6088907 | Y47: -4.9685472 | Z47: -4.3238597 | AA47: -3.6747987 | AB47: -6.523351 | AC47: -3.4896667 | AD47: -0.35752747 | AE47: 2.876262 | AF47: 15.473124 | AG47: 12.722836 | AH47: 10.038053 | AI47: 7.4172142 | AJ47: 2.2379871 | AK47: 1.4695875 | AL47: 0.70696307 | AM47: -0.049929626 | AN47: -5.0683551 | AO47: -2.9848847 | AP47: -0.85568832 | AQ47: 1.3202377 | AR47: 6.7726777 | AS47: 6.9103393 | AT47: 7.0481784 | AU47: 7.1861953 | AV47: 9.0022925 | AW47: 8.0414996 | AX47: 7.0891754 | AY47: 6.1452455 | AZ47: 4.7057082 | BA47: 4.1017994 | BB47: 3.5013737 | BC47: 2.9044111 | BD47: 1.7656397 | BE47: 1.502386 | BF47: 1.2398132 | BG47: 0.97791965 | BH47: 0.10024938 | BI47: 0.25108544 | BJ47: 0.4021488 | BK47: 0.55343979 | BL47: 0.84322272 | BM47: 0.89922974 | BN47: 0.95526786 | BO47: 1.0113371
A48: IMF.RES.GEE:GEE_LIVE | B48: RWA.TMG_D_YOY_WX.G001.Q | C48: Goods | D48: 14.423572 | E48: 12.876237 | F48: 11.349826 | G48: 9.8440573 | H48: 8.8043131 | I48: 7.027555 | J48: 5.279811 | K48: 3.5606075 | L48: -1.0077683 | M48: -0.77763931 | N48: -0.54697534 | O48: -0.31577514 | P48: 2.417671 | Q48: 0.97769557 | R48: -0.44203402 | S48: -1.8418024 | T48: -5.9026741 | U48: -5.3837375 | V48: -4.861939 | W48: -4.3372628 | X48: -3.0127867 | Y48: -3.0518632 | Z48: -3.0909239 | AA48: -3.1299689 | AB48: -8.2623434 | AC48: -4.8736559 | AD48: -1.359794 | AE48: 2.2838661 | AF48: 15.938061 | AG48: 13.236073 | AH48: 10.597055 | AI48: 8.0195415 | AJ48: 3.9453667 | AK48: 2.5132768 | AL48: 1.1009173 | AM48: -0.29198359 | AN48: -9.571628 | AO48: -5.7129274 | AP48: -1.6895708 | AQ48: 2.5054679 | AR48: 15.359912 | AS48: 14.332138 | AT48: 13.31352 | AU48: 12.303978 | AV48: 14.080825 | AW48: 11.212243 | AX48: 8.4157927 | AY48: 5.6896593 | AZ48: -1.683201 | BA48: -1.1497074 | BB48: -0.61331894 | BC48: -0.07401988 | BD48: 1.6885833 | BE48: 1.4223556 | BF48: 1.1568249 | BG48: 0.89198943 | BH48: 0.016722347 | BI48: 0.15761219 | BJ48: 0.29870051 | BK48: 0.43998757 | BL48: 0.66586864 | BM48: 0.74794881 | BN48: 0.83009591 | BO48: 0.91230999
A49: IMF.RES.GEE:GEE_LIVE | B49: RWA.TMGXO_D_YOY_WX.G001.Q | C49: Excluding oil | D49: 12.153528 | E49: 10.998095 | F49: 9.854565 | G49: 8.722816 | H49: 8.5672745 | I49: 6.8170192 | J49: 5.0949804 | K49: 3.4007032 | L49: -1.4415377 | M49: -1.0063072 | N49: -0.56915469 | O49: -0.13007175 | P49: 1.3141664 | Q49: 1.1176672 | R49: 0.92154916 | S49: 0.72581146 | T49: 0.92430297 | U49: 0.54290736 | V49: 0.16295306 | W49: -0.21556539 | X49: 0.52909327 | Y49: -0.63835065 | Z49: -1.7922371 | AA49: -2.9327234 | AB49: -10.9073 | AC49: -7.378309 | AD49: -3.7095336 | AE49: 0.10456323 | AF49: 13.020734 | AG49: 11.066293 | AH49: 9.1456498 | AI49: 7.2582197 | AJ49: 3.8272312 | AK49: 3.0685686 | AL49: 2.3154495 | AM49: 1.5678335 | AN49: -3.9185305 | AO49: -1.5426847 | AP49: 0.89190956 | AQ49: 3.386705 | AR49: 10.902547 | AS49: 10.241542 | AT49: 9.5844776 | AU49: 8.9313292 | AV49: 10.019224 | AW49: 8.2029674 | AX49: 6.4166947 | AY49: 4.6599107 | AZ49: 0.15070645 | BA49: 0.29666285 | BB49: 0.44283197 | BC49: 0.58921411 | BD49: 0.22755694 | BE49: 0.70477183 | BF49: 1.1842589 | BG49: 1.6660289 | BH49: 3.0614733 | BI49: 2.9432723 | BJ49: 2.825207 | BK49: 2.707277 | BL49: 2.818137 | BM49: 2.5439248 | BN49: 2.2704439 | BO49: 1.9976924
C51: Advanced economy partners | D51: Export-weighted averages in U.S. dollars | BH51: Export-weighted averages in U.S. dollars
A53: IMF.RES.GEE:GEE_LIVE | B53: RWA.LULCM_USD_YOY_WX.G110.Q | C53: Unit labor costs in manufacturing | D53: 3.2884235 | E53: 12.687938 | F53: 9.7396239 | G53: 3.2261486 | H53: 1.341363 | I53: -2.0788521 | J53: -2.6709098 | K53: 1.7447144 | L53: 4.1123904 | M53: 2.8085338 | N53: 4.1926257 | O53: 4.8613652 | P53: 3.9672063 | Q53: 4.3922244 | R53: 1.5866457 | S53: -4.8172068 | T53: -10.497124 | U53: -10.616501 | V53: -8.8689978 | W53: -6.202067 | X53: -2.4217704 | Y53: -0.76287453 | Z53: -2.58631 | AA53: -4.5184925 | AB53: -4.4208866 | AC53: -3.1180043 | AD53: 2.2633087 | AE53: 5.9732287 | AF53: 10.690063 | AG53: 5.8052474 | AH53: 0.82364665 | AI53: 0.092769071 | AJ53: -2.6814916 | AK53: -0.60330492 | AL53: -0.088346836 | AM53: 2.1832504 | AN53: 3.8678406 | AO53: 5.5924136 | AP53: 6.9410503 | AQ53: 6.6321204 | AR53: 3.4598295 | AS53: 1.3893798 | AT53: 0.37016919 | AU53: -2.1883826 | AV53: -1.1341666 | AW53: -4.4689593 | AX53: -6.6843854 | AY53: -4.3620345 | AZ53: -0.47906257 | BA53: 5.3851426 | BB53: 9.5176923 | BC53: 7.5122786 | BD53: 4.3968226 | BE53: 1.5712059 | BF53: 3.1672443 | BG53: 2.6396179 | BH53: 0.28205895 | BI53: 6.9711563 | BJ53: 5.8186919 | BK53: 6.292733 | BL53: 9.4987223 | BM53: 4.1341284 | BN53: 3.1892691 | BO53: 4.2595713
C55: 3) World Prices | D55: In U.S. dollars | BH55: In U.S. dollars
A56: IMF.RES.GAS:GAS_LIVE | B56: G110.TXGM_D_YOY.Q | C56: Export unit value for manufactures (MUV) | D56: 4.7333219 | E56: 4.7465709 | F56: 4.5045723 | G56: 4.1691941 | H56: 3.8727128 | I56: 3.1690475 | J56: 2.0784404 | K56: 0.63033035 | L56: -1.6379507 | M56: -2.9268529 | N56: -3.5894935 | O56: -3.4508013 | P56: -1.8511119 | Q56: -0.72243882 | R56: 0.14772403 | S56: 0.29086752 | T56: -0.82458217 | U56: -2.2536164 | V56: -3.8868934 | W56: -5.1937935 | X56: -6.0874233 | Y56: -5.82741 | Z56: -4.835662 | AA56: -3.4229493 | AB56: -1.3918363 | AC56: -0.14479762 | AD56: 0.75867958 | AE56: 1.3674512 | AF56: 1.6921851 | AG56: 2.0215231 | AH56: 2.2292365 | AI56: 2.2070326 | AJ56: 1.8857216 | AK56: 1.0846858 | AL56: -0.070197955 | AM56: -1.3649043 | AN56: -3.2787351 | AO56: -3.8057955 | AP56: -3.4068182 | AQ56: -1.860729 | AR56: 1.699643 | AS56: 5.1705189 | AT56: 8.7080943 | AU56: 11.410838 | AV56: 13.193087 | AW56: 12.301384 | AX56: 9.7201895 | AY56: 6.1993191 | AZ56: 0.9665977 | BA56: -1.7004002 | BB56: -3.0819963 | BC56: -3.0757095 | BD56: -0.82511515 | BE56: 0.7706993 | BF56: 2.1302079 | BG56: 2.7217587 | BH56: 2.0125291 | BI56: 1.1210901 | BJ56: 0.13516281 | BK56: -0.5043127 | BL56: -0.50722524 | BM56: -0.16947439 | BN56: 0.30083207 | BO56: 0.57305428
A57: IMF.RES.GAS:GAS_LIVE | B57: G001.PZPIOIL_YOY.Q | C57: Petroleum spot price (APSP) | D57: 29.422851 | E57: 40.90973 | F57: 36.372778 | G57: 20.423128 | H57: 12.619122 | I57: -6.5344178 | J57: -0.26921513 | K57: -0.97624091 | L57: -6.4144303 | M57: -3.5298755 | N57: 4.3278485 | O57: 2.6381548 | P57: -1.3320095 | Q57: 7.1229278 | R57: -6.4973366 | S57: -28.737057 | T57: -50.05165 | U57: -43.148062 | V57: -51.208261 | W57: -43.337562 | X57: -36.086475 | Y57: -25.16263 | Z57: -7.9808088 | AA57: 17.172408 | AB57: 60.513458 | AC57: 9.659345 | AD57: 11.607698 | AE57: 18.560806 | AF57: 21.718299 | AG57: 44.263856 | AH57: 45.606078 | AI57: 9.7505927 | AJ57: -6.2414841 | AK57: -9.2961873 | AL57: -18.502578 | AM57: -6.4194821 | AN57: -19.120314 | AO57: -51.60194 | AP57: -29.172117 | AQ57: -26.698553 | AR57: 21.493228 | AS57: 114.13966 | AT57: 69.470903 | AU57: 77.127836 | AV57: 59.858404 | AW57: 62.467886 | AX57: 33.144393 | AY57: 8.8181998 | AZ57: -16.561726 | BA57: -30.10927 | BB57: -11.047869 | BC57: -4.4390763 | BD57: 1.6222228 | BE57: 10.390772 | BF57: -7.8619444 | BG57: -10.141537 | BH57: -7.8341973 | BI57: -21.47131 | BJ57: -13.100081 | BK57: -15.069204 | BL57: -12.144957 | BM57: -1.0023751 | BN57: -5.3505715 | BO57: 2.2199523
C59: Average of nonfuel commodity market prices weighted by the 2019-2021 composition of nonfuel commodity trade of reporting country.
