Workbook
Name DATES_A: 'Complete DataSet A'!$E$2:$AE$2
Name DATES_Q: 'Complete DataSet Q'!$E$4:$AZ$4
Name DATES_Q: #REF!
Name NAMES_A: 'Complete DataSet A'!$C$5:$C$299
Name NAMES_Q: 'Complete DataSet Q'!$C$7:$C$267
Name NAMES_Q: #REF!
Name WEO_ALL: 'Complete DataSet A'!$F$304:$AL$334
Name WEO_ALL: #REF!
Name WEOGAS_Rwametric_Qdata: 'Complete DataSet Q'!$E$272:$CB$302
Name WEOGAS_Rwametric_Qdata: #REF!

Sheet ControlSheet
A2: Query1
B3: Driver | C3: AREMLG32
B4: OutputType | C4: Excel
B5: ResultSet | C5: Complete Data Set (Quarterly)
B6: StartRow | C6: 5
B7: From | C7: P:\WRK\GEE\GAS.BNK
B8: Where | C8: Frequency=Q,SeriesName in ("","","",W111NGDP_R,W163NGDP_R,W134NGDP_R,W132NGDP_R,W136NGDP_R,W184NGDP_R,W158NGDP_R,W112NGDP_R,W156NGDP_R,W203NGDP_R,"","",W111NGDP_D,W163NGDP_D,W134NGDP_D,W132NGDP_D,W136NGDP_D,W158NGDP_D,W112NGDP_D,W156NGDP_D,"","",W110TXGM
C9: _D,"","",W001PNRGW,W001POILAPSP,W001PNGASW,W001PCOALW,W001PNFUELW,W001PFOODW,W001PBEVEW,W001PRAWMW,W001PMETAW,"","",W001PALUM,W001PBANSOP,W001PBEEF,W001PCOCO,W001PCOIL,W001PCOFFOTM,W001PCOFFROB,W001PCOPP,W001PCOTTIND,W001PFISH,W001PLOGSK,W001PSAWMAL,W001
C10: PHIDE,W001PGOLD,W001PIORECR,W001PLAMB,W001PLEAD,W001PMAIZMT,W001PNGASEU,W001PNICK,W001PPOIL,W001PRICENPQ,W001PRUBB,W001PLOGORE,W001PSAWORE,W001PSMEA,W001PSOIL,W001PSOYB,W001PSUGAUSA,W001PSUGAEEC,W001PSUGAISA,W001PTEA,W001PTIN,W001PWHEAMT,W001PWOOLC,W001P
C11: WOOLF,W001PZINC,"","","","",W163EDNA,W134EDNA,W134EDNA_N,W132EDNA,W132EDNA_N,W136EDNA,W136EDNA_N,W158EDNA,W112EDNA,W156EDNA,"",W122EDNA,W122EDNA_N,W124EDNA,W124EDNA_N,W128EDNA,W137EDNA,W137EDNA_N,W138EDNA,W138EDNA_N,W142EDNA,W144EDNA,W146EDNA,W172EDNA,W1
C12: 72EDNA_N,W174EDNA,W174EDNA_N,W176EDNA,W178EDNA,W178EDNA_N,W182EDNA,W182EDNA_N,W184EDNA,W184EDNA_N,W193EDNA,W196EDNA,W436EDNA,W528EDNA,W532EDNA,W542EDNA,W576EDNA,"","",W163EDNE,W134EDNE,W134EDNE_N,W132EDNE,W132EDNE_N,W158EDNE,W112EDNE,W146EDNE,"",W111ESDA
C13: ,"","",W111ENULC,W163ENULC,W134ENULC,W132ENULC,W136ENULC,W158ENULC,W112ENULC,W156ENULC,"",W122ENULC,W124ENULC,W128ENULC,W137ENULC,W138ENULC,W142ENULC,W144ENULC,W146ENULC,W172ENULC,W174ENULC,W178ENULC,W182ENULC,W184ENULC,W193ENULC,W196ENULC,"","",W111EE,W
C14: 163EE,W134EE,W132EE,W136EE,W158EE,W112EE,W156EE,"",W122EE,W124EE,W128EE,W137EE,W138EE,W142EE,W144EE,W146EE,W172EE,W174EE,W178EE,W182EE,W184EE,W193EE,W196EE,"","","","",W111FLIBOR,W163FLIBOR,W158FLIBOR,W112FPIBOR),Period In (2001Q1,2001Q2,2001Q3,2001Q4,20
C15: 02Q1,2002Q2,2002Q3,2002Q4,2003Q1,2003Q2,2003Q3,2003Q4,2004Q1,2004Q2,2004Q3,2004Q4,2005Q1,2005Q2,2005Q3,2005Q4,2006Q1,2006Q2,2006Q3,2006Q4,2007Q1,2007Q2,2007Q3,2007Q4,2008Q1,2008Q2,2008Q3,2008Q4,2009Q1,2009Q2,2009Q3,2009Q4,2010Q1,2010Q2,2010Q3,2010Q4,2011
C16: Q1,2011Q2,2011Q3,2011Q4)
B17: CancelDialog | C17: *
B18: Select | C18: DATA
B19: ColumnLocations | C19: E
A26: Query1

Sheet Complete DataSet A
E1: 1997 | F1: =E1+1 -> 1998 | G1: =F1+1 -> 1999 | H1: =G1+1 -> 2000 | I1: =H1+1 -> 2001 | J1: =I1+1 -> 2002 | K1: =J1+1 -> 2003 | L1: =K1+1 -> 2004 | M1: =L1+1 -> 2005 | ... AN1: =AM1+1 -> 2032
B2: DATASET | C2: Series_Code | E2: 1997A1 | F2: 1998A1 | G2: 1999A1 | H2: 2000A1 | I2: 2001A1 | J2: 2002A1 | K2: 2003A1 | L2: 2004A1 | M2: 2005A1 | N2: 2006A1 | O2: 2007A1 | P2: 2008A1 | Q2: 2009A1 | R2: 2010A1 | S2: 2011A1 | T2: 2012A1 | U2: 2013A1 | V2: 2014A1 | W2: 2015A1 | X2: 2016A1 | Y2: 2017A1 | Z2: 2018A1 | AA2: 2019A1 | AB2: 2020A1 | AC2: 2021A1 | AD2: 2022A1 | AE2: 2023A1 | AF2: 2024A1 | AG2: 2025A1 | AH2: 2026A1 | AI2: 2027A1 | AJ2: 2028A1 | AK2: 2029A1 | AL2: 2030A1 | AM2: 2030A2 | AN2: 2030A3
A3: OUTPUT, DEMAND, INFLATION, AND TRADE
A4: IMF.RES.GAS:GAS_LIVE_2026_JAN_GAS1_VINTAGE | B4: IMF.RES.GAS:GAS_LIVE
A5: GDP in U.S. dollars -- advanced economies | B5: =B4 -> IMF.RES.GAS:GAS_LIVE | C5: G110.NGDP_USD.A | E5: 25172.195 | F5: 25222.819 | G5: 26566.424 | H5: 27054.307 | I5: 26772.695 | J5: 27930.45 | K5: 31323.946 | L5: 34748.092 | M5: 36574.547 | N5: 38473.794 | O5: 42037.24 | P5: 44426.372 | Q5: 41919.516 | R5: 43779.085 | S5: 47015.251 | T5: 46843.373 | U5: 47310.524 | V5: 48461.898 | W5: 45874.294 | X5: 47134.41 | Y5: 49207.56 | Z5: 52079.724 | AA5: 52632.771 | AB5: 51798.477 | AC5: 57936.31 | AD5: 59304.88 | AE5: 62685.047 | AF5: 65265.927 | AG5: 69112.019 | AH5: 72469.846 | AI5: 75209.689 | AJ5: 78155.255 | AK5: 81072.809 | AL5: 84146.622
A7: Real GDP
A8: World | B8: =$B$4 -> IMF.RES.GAS:GAS_LIVE | C8: G001.NGDP_R.A | E8: 74.463085 | F8: 76.408226 | G8: 79.137441 | H8: 82.936547 | I8: 84.994332 | J8: 87.398187 | K8: 90.72254 | L8: 95.498095 | M8: 100 | N8: 105.28336 | O8: 110.92693 | P8: 114.17652 | Q8: 113.78127 | R8: 119.76139 | S8: 124.65305 | T8: 128.87585 | U8: 133.2366 | V8: 137.99901 | W8: 142.74543 | X8: 147.34759 | Y8: 153.00836 | Z8: 158.58856 | AA8: 163.27929 | AB8: 158.85138 | AC8: 169.41276 | AD8: 175.80977 | AE8: 181.96228 | AF8: 188.03716 | AG8: 194.30623 | AH8: 200.64672 | AI8: 207.08403 | AJ8: 213.7325 | AK8: 220.46593 | AL8: 227.22784
A9: Advanced economies | B9: =$B$4 -> IMF.RES.GAS:GAS_LIVE | C9: G110.NGDP_R.A | E9: 80.634925 | F9: 82.85286 | G9: 85.826215 | H9: 89.424342 | I9: 90.817239 | J9: 92.312471 | K9: 94.175525 | L9: 97.228471 | M9: 100 | N9: 103.10026 | O9: 105.99483 | P9: 106.36205 | Q9: 102.7559 | R9: 105.95134 | S9: 107.77732 | T9: 109.05122 | U9: 110.66779 | V9: 113.05774 | W9: 115.78628 | X9: 117.91534 | Y9: 120.99274 | Z9: 123.78572 | AA9: 126.08737 | AB9: 121.13332 | AC9: 128.52734 | AD9: 132.44461 | AE9: 134.69532 | AF9: 137.13825 | AG9: 139.51913 | AH9: 142.04149 | AI9: 144.46656 | AJ9: 146.94074 | AK9: 149.27785 | AL9: 151.54926
A10: Major industrial countries, by country
A11: United States | B11: =$A$4 -> IMF.RES.GAS:GAS_LIVE_2026_JAN_GAS1_VINTAGE | C11: USA.NGDP_R.A | E11: 12370.3 | F11: 12924.875 | G11: 13543.775 | H11: 14096.025 | I11: 14230.725 | J11: 14472.7 | K11: 14877.325 | L11: 15449.775 | M11: 15987.95 | N11: 16433.15 | O11: 16762.45 | P11: 16781.5 | Q11: 16349.125 | R11: 16789.775 | S11: 17052.4 | T11: 17442.775 | U11: 17812.175 | V11: 18261.7 | W11: 18799.6 | X11: 19141.675 | Y11: 19612.1 | Z11: 20193.925 | AA11: 20715.65 | AB11: 20284.5 | AC11: 21532.375 | AD11: 22075.9 | AE11: 22723.725 | AF11: 23358.425 | AG11: 23829.45 | AH11: 24330.363 | AI11: 24830.38 | AJ11: 25349.963 | AK11: 25826.691 | AL11: 26279.467
A12: Euro Area | B12: =$A$4 -> IMF.RES.GAS:GAS_LIVE_2026_JAN_GAS1_VINTAGE | C12: G163.NGDP_R.A | E12: 8854.2428 | F12: 9116.0197 | G12: 9388.1257 | H12: 9750.2117 | I12: 9960.6607 | J12: 10051.549 | K12: 10124.016 | L12: 10356.55 | M12: 10538.132 | N12: 10887.327 | O12: 11213.56 | P12: 11259.449 | Q12: 10757.64 | R12: 10980.692 | S12: 11170.013 | T12: 11063.458 | U12: 11043.582 | V12: 11202.796 | W12: 11439.335 | X12: 11645.413 | Y12: 11950.632 | Z12: 12163.226 | AA12: 12360.414 | AB12: 11615.805 | AC12: 12359.43 | AD12: 12808.086 | AE12: 12859.906 | AF12: 12969.312 | AG12: 13124.616 | AH12: 13274.292 | AI12: 13456.47 | AJ12: 13632.836 | AK12: 13800.05 | AL12: 13955.281
A13: Germany | B13: =$A$4 -> IMF.RES.GAS:GAS_LIVE_2026_JAN_GAS1_VINTAGE | C13: DEU.NGDP_R.A | E13: 2634.54 | F13: 2689.92 | G13: 2747.13 | H13: 2826.22 | I13: 2872.56 | J13: 2865.83 | K13: 2850.64 | L13: 2883.86 | M13: 2909.49 | N13: 3021.7 | O13: 3109.09 | P13: 3136.71 | Q13: 2962.61 | R13: 3085.38 | S13: 3201.32 | T13: 3216.24 | U13: 3228.93 | V13: 3299.23 | W13: 3354.1 | X13: 3428.47 | Y13: 3524.66 | Z13: 3564.6 | AA13: 3599.28 | AB13: 3450.72 | AC13: 3585.73 | AD13: 3650.52 | AE13: 3618.69 | AF13: 3600.74 | AG13: 3607.6064 | AH13: 3641.6747 | AI13: 3695.2992 | AJ13: 3739.7603 | AK13: 3776.4078 | AL13: 3802.0599
A14: Italy | B14: =$A$4 -> IMF.RES.GAS:GAS_LIVE_2026_JAN_GAS1_VINTAGE | C14: ITA.NGDP_R.A | E14: 1646.334 | F14: 1676.04 | G14: 1704.163 | H14: 1770.32 | I14: 1805.84 | J14: 1810.715 | K14: 1811.92 | L14: 1838.629 | M14: 1852.647 | N14: 1885.985 | O14: 1913.564 | P14: 1893.985 | Q14: 1793.506 | R14: 1820.931 | S14: 1833.595 | T14: 1776.291 | U14: 1743.996 | V14: 1743.972 | W14: 1759.418 | X14: 1781.17 | Y14: 1809.733 | Z14: 1824.694 | AA14: 1832.525 | AB14: 1670.013 | AC14: 1819.162 | AD14: 1906.866 | AE14: 1920.508 | AF14: 1934.445 | AG14: 1944.9977 | AH14: 1959.7549 | AI14: 1970.884 | AJ14: 1984.3578 | AK14: 1998.625 | AL14: 2012.9856
A15: France | B15: =$A$4 -> IMF.RES.GAS:GAS_LIVE_2026_JAN_GAS1_VINTAGE | C15: FRA.NGDP_R.A | E15: 1747.084 | F15: 1807.639 | G15: 1866.581 | H15: 1948.082 | I15: 1983.982 | J15: 2006.255 | K15: 2026.132 | L15: 2077.272 | M15: 2118.498 | N15: 2180.574 | O15: 2234.758 | P15: 2240.62 | Q15: 2179.436 | R15: 2219.5 | S15: 2274.631 | T15: 2279.853 | U15: 2300.951 | V15: 2323.982 | W15: 2347.165 | X15: 2364.41 | Y15: 2418.034 | Z15: 2456.56 | AA15: 2507.915 | AB15: 2317.229 | AC15: 2474.653 | AD15: 2543.966 | AE15: 2585.16 | AF15: 2613.658 | AG15: 2631.2048 | AH15: 2655.1788 | AI15: 2686.639 | AJ15: 2720.7751 | AK15: 2754.6062 | AL15: 2787.9604
A16: Spain | B16: =$A$4 -> IMF.RES.GAS:GAS_LIVE_2026_JAN_GAS1_VINTAGE | C16: ESP.NGDP_R.A | E16: 808.88679 | F16: 845.03412 | G16: 885.13326 | H16: 929.85833 | I16: 966.30088 | J16: 992.92747 | K16: 1022.112 | L16: 1053.9462 | M16: 1091.3738 | N16: 1135.5026 | O16: 1175.6258 | P16: 1184.6451 | Q16: 1140.0065 | R16: 1141.0792 | S16: 1133.7771 | T16: 1101.2933 | U16: 1085.5738 | V16: 1102.0798 | W16: 1146.8334 | X16: 1180.2658 | Y16: 1214.4471 | Z16: 1243.5382 | AA16: 1267.9261 | AB16: 1129.214 | AC16: 1204.6811 | AD16: 1281.4233 | AE16: 1312.9577 | AF16: 1358.3228 | AG16: 1397.8206 | AH16: 1425.1836 | AI16: 1449.8587 | AJ16: 1473.055 | AK16: 1496.5956 | AL16: 1520.4
A17: Japan | B17: =$A$4 -> IMF.RES.GAS:GAS_LIVE_2026_JAN_GAS1_VINTAGE | C17: JPN.NGDP_R.A | E17: 477269.5 | F17: 471206.7 | G17: 469633.1 | H17: 482616.9 | I17: 484480.2 | J17: 484683.5 | K17: 492124.1 | L17: 502882.4 | M17: 511954 | N17: 518979.7 | O17: 526681.2 | P17: 520233.1 | Q17: 490615.1 | R17: 510720 | S17: 510841.6 | T17: 517864.4 | U17: 528248.1 | V17: 529812.7 | W17: 538081.2 | X17: 542137.5 | Y17: 551220 | Z17: 554766.6 | AA17: 552535.4 | AB17: 529501.4 | AC17: 543779.9 | AD17: 549002.4 | AE17: 555837.9 | AF17: 556417.7 | AG17: 562403.89 | AH17: 565961.74 | AI17: 569552.68 | AJ17: 572693.75 | AK17: 575692.69 | AL17: 578546.14
A18: United Kingdom | B18: =$A$4 -> IMF.RES.GAS:GAS_LIVE_2026_JAN_GAS1_VINTAGE | C18: GBR.NGDP_R.A | E18: 1615.678 | F18: 1670.654 | G18: 1721.748 | H18: 1796.5 | I18: 1842.72 | J18: 1875.809 | K18: 1934.941 | L18: 1982.5 | M18: 2036.675 | N18: 2085.162 | O18: 2139.895 | P18: 2134.571 | Q18: 2035.942 | R18: 2081.411 | S18: 2105.105 | T18: 2136.871 | U18: 2175.333 | V18: 2244.827 | W18: 2294.727 | X18: 2338.825 | Y18: 2400.956 | Z18: 2434.694 | AA18: 2474.245 | AB18: 2219.474 | AC18: 2409.815 | AD18: 2526.428 | AE18: 2536.46 | AF18: 2564.378 | AG18: 2597.9238 | AH18: 2630.7485 | AI18: 2671.2642 | AJ18: 2709.6944 | AK18: 2748.5094 | AL18: 2788.1621
A19: Canada | B19: =$A$4 -> IMF.RES.GAS:GAS_LIVE_2026_JAN_GAS1_VINTAGE | C19: CAN.NGDP_R.A | E19: 1338.011 | F19: 1390.0983 | G19: 1461.5632 | H19: 1536.6662 | I19: 1565.4803 | J19: 1612.433 | K19: 1641.5597 | L19: 1692.3228 | M19: 1746.654 | N19: 1792.7297 | O19: 1829.479 | P19: 1847.6898 | Q19: 1793.828 | R19: 1849.2718 | S19: 1907.287 | T19: 1940.7725 | U19: 1985.9113 | V19: 2042.9758 | W19: 2056.2545 | X19: 2077.6098 | Y19: 2140.641 | Z19: 2199.358 | AA19: 2241.3313 | AB19: 2128.4077 | AC19: 2255.0592 | AD19: 2349.5245 | AE19: 2385.4428 | AF19: 2422.5315 | AG19: 2450.4538 | AH19: 2488.216 | AI19: 2534.9856 | AJ19: 2577.6919 | AK19: 2622.3134 | AL19: 2665.1823
A20: Other advanced economies | B20: =$B$4 -> IMF.RES.GAS:GAS_LIVE | C20: GX123.NGDP_R.A | E20: 74.066188 | F20: 74.819166 | G20: 79.001161 | H20: 83.671603 | I20: 85.473353 | J20: 88.836946 | K20: 91.249975 | L20: 95.999601 | M20: 100 | N20: 104.84516 | O20: 110.2613 | P20: 112.27825 | Q20: 111.32106 | R20: 117.95943 | S20: 122.00814 | T20: 124.7619 | U20: 128.00149 | V20: 131.79557 | W20: 134.88772 | X20: 138.51244 | Y20: 142.96355 | Z20: 146.9632 | AA20: 149.97007 | AB20: 147.58994 | AC20: 156.20543 | AD20: 160.47246 | AE20: 163.42698 | AF20: 167.22769 | AG20: 170.31516 | AH20: 173.75238 | AI20: 177.44738 | AJ20: 181.28279 | AK20: 185.03205 | AL20: 188.86293
A21: European Union | B21: =$B$4 -> IMF.RES.GAS:GAS_LIVE | C21: G998.NGDP_R.A | E21: 82.568892 | F21: 84.995723 | G21: 87.480055 | H21: 90.941922 | I21: 92.990683 | J21: 94.165751 | K21: 95.248124 | L21: 97.87456 | M21: 100 | N21: 103.78948 | O21: 107.25309 | P21: 108.1952 | Q21: 103.67098 | R21: 105.77962 | S21: 107.90647 | T21: 107.13375 | U21: 107.10834 | V21: 108.97322 | W21: 111.73693 | X21: 113.93817 | Y21: 117.40356 | Z21: 120.08595 | AA21: 122.53889 | AB21: 115.77526 | AC21: 123.227 | AD21: 127.84542 | AE21: 128.59337 | AF21: 130.07952 | AG21: 132.05996 | AH21: 134.09913 | AI21: 136.23997 | AJ21: 138.33495 | AK21: 140.35389 | AL21: 142.31459
A22: Emerging market and developing economies | B22: =$B$4 -> IMF.RES.GAS:GAS_LIVE | C22: G200.NGDP_R.A | E22: 67.406488 | F22: 69.033935 | G22: 71.483186 | H22: 75.526589 | I22: 78.354249 | J22: 81.805674 | K22: 86.79318 | L22: 93.524169 | M22: 100 | N22: 107.76243 | O22: 116.51251 | P22: 123.01986 | Q22: 126.23149 | R22: 135.39636 | S22: 143.79923 | T22: 151.41214 | U22: 158.94246 | V22: 166.45942 | W22: 173.55565 | X22: 181.03781 | Y22: 189.70817 | Z22: 198.5206 | AA22: 205.99513 | AB22: 202.218 | AC22: 216.44093 | AD22: 225.71594 | AE22: 236.37509 | AF22: 246.65623 | AG22: 257.4293 | AH22: 268.19845 | AI22: 279.28974 | AJ22: 290.78147 | AK22: 302.61545 | AL22: 314.58926
A23: Net creditor countries | B23: =$B$4 -> IMF.RES.GAS:GAS_LIVE | C23: G209.NGDP_R.A | E23: 61.975571 | F23: 63.453212 | G23: 66.32525 | H23: 71.089757 | I23: 74.536027 | J23: 78.387566 | K23: 84.569936 | L23: 92.279415 | M23: 100 | N23: 109.36478 | O23: 120.48833 | P23: 128.69612 | Q23: 132.9934 | R23: 143.7533 | S23: 154.27178 | T23: 164.12594 | U23: 172.80533 | V23: 181.49422 | W23: 189.81392 | X23: 198.86492 | Y23: 208.60083 | Z23: 218.50362 | AA23: 227.77505 | AB23: 227.72943 | AC23: 244.06439 | AD23: 252.71701 | AE23: 264.00677 | AF23: 275.73404 | AG23: 287.07819 | AH23: 298.27423 | AI23: 309.03706 | AJ23: 319.91873 | AK23: 330.64673 | AL23: 341.01966
A24: Net debtor countries | B24: =$B$4 -> IMF.RES.GAS:GAS_LIVE | C24: G606.NGDP_R.A | E24: 72.204 | F24: 73.948489 | G24: 76.05663 | H24: 79.475581 | I24: 81.748192 | J24: 84.836156 | K24: 88.780243 | L24: 94.6381 | M24: 100 | N24: 106.337 | O24: 112.95366 | P24: 117.94878 | Q24: 120.17522 | R24: 127.95048 | S24: 134.47251 | T24: 140.09711 | U24: 146.61382 | V24: 153.09761 | W24: 159.11593 | X24: 165.21642 | Y24: 172.94525 | Z24: 180.79339 | AA24: 186.69343 | AB24: 179.66932 | AC24: 192.03381 | AD24: 201.78729 | AE24: 211.86608 | AF24: 220.87136 | AG24: 231.11369 | AH24: 241.47458 | AI24: 252.79324 | AJ24: 264.74749 | AK24: 277.45813 | AL24: 290.72209
A26: Real total domestic demand
A27: Advanced economies | B27: =$B$4 -> IMF.RES.GAS:GAS_LIVE | C27: G110.NTDD_R.A | E27: 79.685077 | F27: 82.204545 | G27: 85.580143 | H27: 89.199754 | I27: 90.567939 | J27: 92.076936 | K27: 94.148821 | L27: 97.130192 | M27: 100 | N27: 102.87535 | O27: 105.41449 | P27: 105.30625 | Q27: 101.51559 | R27: 104.53306 | S27: 105.99344 | T27: 106.83062 | U27: 108.16165 | V27: 110.57313 | W27: 113.60169 | X27: 115.88153 | Y27: 118.93214 | Z27: 121.78638 | AA27: 124.38254 | AB27: 119.61058 | AC27: 126.92891 | AD27: 131.3038 | AE27: 132.78032 | AF27: 135.18641 | AG27: 137.92873 | AH27: 140.33963 | AI27: 142.68672 | AJ27: 145.03792 | AK27: 147.33232 | AL27: 149.55378
A29: GDP deflator
A30: Advanced economies | B30: =$B$4 -> IMF.RES.GAS:GAS_LIVE | C30: G110.NGDP_D.A | E30: 87.677697 | F30: 88.907124 | G30: 89.716946 | H30: 91.197188 | I30: 92.975924 | J30: 94.428605 | K30: 95.996763 | L30: 97.935374 | M30: 100 | N30: 102.13947 | O30: 104.45489 | P30: 106.51628 | Q30: 107.32123 | R30: 108.31401 | S30: 109.84109 | T30: 111.22159 | U30: 112.68896 | V30: 114.26753 | W30: 115.67819 | X30: 116.79569 | Y30: 118.47315 | Z30: 120.48525 | AA30: 122.31362 | AB30: 124.33298 | AC30: 128.45145 | AD30: 135.90418 | AE30: 141.65836 | AF30: 145.72091 | AG30: 149.45681 | AH30: 152.4506 | AI30: 155.36305 | AJ30: 158.42485 | AK30: 161.56114 | AL30: 164.75576
A31: Major industrial countries, by country
A32: United States | B32: =$A$4 -> IMF.RES.GAS:GAS_LIVE_2026_JAN_GAS1_VINTAGE | C32: USA.NGDP_D.A | E32: 69.33987 | F32: 70.119247 | G32: 71.111452 | H32: 72.722275 | I32: 74.359704 | J32: 75.51528 | K32: 77.006115 | L32: 79.076718 | M32: 81.556422 | N32: 84.071526 | O32: 86.349251 | P32: 88.012693 | Q32: 88.555504 | R32: 89.631785 | S32: 91.481111 | T32: 93.184427 | U32: 94.770431 | V32: 96.421062 | W32: 97.3159 | X32: 98.240619 | Y32: 100 | Z32: 102.29079 | AA32: 103.97924 | AB32: 105.37738 | AC32: 110.18594 | AD32: 118.02282 | AE32: 122.38971 | AF32: 125.42808 | AG32: 128.4786 | AH32: 130.7884 | AI32: 132.98217 | AJ32: 135.14182 | AK32: 137.50825 | AL32: 140.08751
A33: Euro area | B33: =$A$4 -> IMF.RES.GAS:GAS_LIVE_2026_JAN_GAS1_VINTAGE | C33: G163.NGDP_D.A | E33: 69.503095 | F33: 70.250986 | G33: 71.412134 | H33: 72.414584 | I33: 74.236591 | J33: 76.092737 | K33: 77.791072 | L33: 79.311425 | M33: 80.847037 | N33: 82.492839 | O33: 84.54593 | P33: 86.32726 | Q33: 87.206488 | R33: 87.836566 | S33: 88.816586 | T33: 89.947049 | U33: 91.06738 | V33: 91.926485 | W33: 93.202229 | X33: 94.049439 | Y33: 95.126749 | Z33: 96.578487 | AA33: 98.219077 | AB33: 100 | AC33: 102.09789 | AD33: 107.41472 | AE33: 113.82416 | AF33: 117.20093 | AG33: 119.72419 | AH33: 122.08704 | AI33: 124.64975 | AJ33: 127.2258 | AK33: 129.87328 | AL33: 132.59959
A34: Germany | B34: =$A$4 -> IMF.RES.GAS:GAS_LIVE_2026_JAN_GAS1_VINTAGE | C34: DEU.NGDP_D.A | E34: 74.668823 | F34: 75.181046 | G34: 75.614914 | H34: 75.353653 | I34: 76.431128 | J34: 77.581713 | K34: 78.60726 | L34: 79.512875 | M34: 79.935315 | N34: 80.291889 | O34: 81.767334 | P34: 82.547637 | Q34: 84.181516 | R34: 84.762979 | S34: 85.805543 | T34: 87.035793 | U34: 88.774919 | V34: 90.459592 | W34: 92.037506 | X34: 93.196382 | Y34: 94.565433 | Z34: 96.337036 | AA34: 98.277433 | AB34: 100 | AC34: 102.69429 | AD34: 109.28279 | AE34: 116.59772 | AF34: 120.22445 | AG34: 123.0336 | AH34: 125.36169 | AI34: 127.82502 | AJ34: 130.57212 | AK34: 133.40186 | AL34: 136.36821
A35: Italy | B35: =$A$4 -> IMF.RES.GAS:GAS_LIVE_2026_JAN_GAS1_VINTAGE | C35: ITA.NGDP_D.A | E35: 66.51694 | F35: 68.092408 | G35: 69.098437 | H35: 70.311808 | I35: 72.466165 | J35: 74.861201 | K35: 77.232218 | L35: 79.263245 | M35: 80.915199 | N35: 82.708187 | O35: 84.748354 | P35: 86.786221 | Q35: 88.3246 | R35: 88.85257 | S35: 90.388663 | T35: 91.927449 | U35: 92.962484 | V35: 93.801391 | W35: 94.535693 | X35: 95.715513 | Y35: 96.395104 | Z35: 97.426966 | AA35: 98.447115 | AB35: 100 | AC35: 101.28334 | AD35: 104.78308 | AE35: 110.98053 | AF35: 113.32351 | AG35: 115.78129 | AH35: 118.11281 | AI35: 120.47507 | AJ35: 122.88457 | AK35: 125.34226 | AL35: 127.84911
A36: France | B36: =$A$4 -> IMF.RES.GAS:GAS_LIVE_2026_JAN_GAS1_VINTAGE | C36: FRA.NGDP_D.A | E36: 73.818374 | F36: 74.479362 | G36: 74.743502 | H36: 75.639372 | I36: 77.121214 | J36: 78.670458 | K36: 80.069462 | L36: 81.650742 | M36: 83.1744 | N36: 84.657572 | O36: 86.715251 | P36: 88.814703 | Q36: 88.82298 | R36: 89.933544 | S36: 90.658265 | T36: 91.597441 | U36: 92.151115 | V36: 92.674255 | W36: 93.789827 | X36: 94.392216 | Y36: 94.774557 | Z36: 95.88054 | AA36: 96.981237 | AB36: 100.04518 | AC36: 101.35166 | AD36: 104.32518 | AE36: 109.47887 | AF36: 111.76688 | AG36: 113.10489 | AH36: 114.83322 | AI36: 117.06101 | AJ36: 119.33094 | AK36: 121.64707 | AL36: 123.98089
A37: Japan | B37: =$A$4 -> IMF.RES.GAS:GAS_LIVE_2026_JAN_GAS1_VINTAGE | C37: JPN.NGDP_D.A | E37: 113.88645 | F37: 113.85606 | G37: 112.44308 | H37: 110.94054 | I37: 109.73697 | J37: 108.21055 | K37: 106.47085 | L37: 105.2733 | M37: 104.0163 | N37: 103.11968 | O37: 102.39243 | P37: 101.4591 | Q37: 100.8812 | R37: 98.983905 | S37: 97.378326 | T37: 96.642017 | U37: 96.299561 | V37: 97.923493 | W37: 99.990931 | X37: 100.4108 | Y37: 100.33616 | Z37: 100.33591 | AA37: 100.97288 | AB37: 101.9159 | AC37: 101.70812 | AD37: 102.11374 | AE37: 106.27291 | AF37: 109.34212 | AG37: 112.38423 | AH37: 114.58432 | AI37: 116.90007 | AJ37: 119.23784 | AK37: 121.59358 | AL37: 123.97493
A38: United Kingdom | B38: =$A$4 -> IMF.RES.GAS:GAS_LIVE_2026_JAN_GAS1_VINTAGE | C38: GBR.NGDP_D.A | E38: 59.009592 | F38: 59.767073 | G38: 60.592375 | H38: 61.272029 | I38: 62.198001 | J38: 63.516008 | K38: 65.032164 | L38: 66.715612 | M38: 68.678066 | N38: 70.595858 | O38: 72.182841 | P38: 74.656687 | Q38: 76.072992 | R38: 77.281854 | S38: 78.978958 | T38: 80.197401 | U38: 81.889118 | V38: 82.969155 | W38: 83.515425 | X38: 85.155794 | Y38: 86.735534 | Z38: 88.401417 | AA38: 90.286976 | AB38: 94.774077 | AC38: 94.837156 | AD38: 100 | AE38: 106.88854 | AF38: 111.17663 | AG38: 115.10398 | AH38: 117.79054 | AI38: 120.28061 | AJ38: 122.77302 | AK38: 125.46129 | AL38: 128.37017
A39: Canada | B39: =$A$4 -> IMF.RES.GAS:GAS_LIVE_2026_JAN_GAS1_VINTAGE | C39: CAN.NGDP_D.A | E39: 67.781655 | F39: 67.660541 | G39: 68.962257 | H39: 71.97861 | I39: 73.111302 | J39: 74.030611 | K39: 76.436267 | L39: 78.928857 | M39: 81.389331 | N39: 83.481852 | O39: 86.235535 | P39: 89.681777 | Q39: 87.596693 | R39: 90.092113 | S39: 93.015 | T39: 94.148129 | U39: 95.78711 | V39: 97.64668 | W39: 96.79935 | X39: 97.493526 | Y39: 100 | Z39: 101.65125 | AA39: 103.22272 | AB39: 104.32808 | AC39: 112.45017 | AD39: 121.34115 | AE39: 122.98807 | AF39: 126.82378 | AG39: 129.86364 | AH39: 133.02775 | AI39: 136.07692 | AJ39: 138.86798 | AK39: 141.69764 | AL39: 145.41865
A41: Switzerland | B41: =$A$4 -> IMF.RES.GAS:GAS_LIVE_2026_JAN_GAS1_VINTAGE | C41: CHE.NGDP_D.A | E41: 91.352505 | F41: 91.184197 | G41: 91.227692 | H41: 92.466775 | I41: 93.366462 | J41: 93.134527 | K41: 94.232051 | L41: 94.519719 | M41: 95.39019 | N41: 97.436982 | O41: 99.752517 | P41: 101.20049 | Q41: 101.67237 | R41: 101.98978 | S41: 101.96502 | T41: 102.02555 | U41: 101.9343 | V41: 101.27026 | W41: 100 | X41: 99.412885 | Y41: 99.045927 | Z41: 99.802165 | AA41: 99.6988 | AB41: 99.006906 | AC41: 100.30972 | AD41: 103.35696 | AE41: 104.27302 | AF41: 105.68621 | AG41: 105.77576 | AH41: 106.43196 | AI41: 107.15421 | AJ41: 107.90004 | AK41: 108.61692 | AL41: 109.34568
A42: European Union | B42: =$B$4 -> IMF.RES.GAS:GAS_LIVE | C42: G998.NGDP_D.A | E42: 79.76771 | F42: 82.7028 | G42: 84.717671 | H42: 87.039796 | I42: 90.108693 | J42: 92.845987 | K42: 95.353592 | L42: 97.820964 | M42: 100 | N42: 102.26631 | O42: 105.37467 | P42: 108.2513 | Q42: 109.72814 | R42: 110.78005 | S42: 112.2383 | T42: 113.8061 | U42: 115.1355 | V42: 116.31474 | W42: 118.0045 | X42: 119.14928 | Y42: 120.77717 | Z42: 122.90589 | AA42: 125.42365 | AB42: 128.24228 | AC42: 131.60134 | AD42: 139.764 | AE42: 148.98615 | AF42: 153.85593 | AG42: 157.73766 | AH42: 161.2715 | AI42: 164.76963 | AJ42: 168.47863 | AK42: 172.066 | AL42: 175.7294
A44: Consumer prices
A45: Advanced economies | B45: =$B$41 -> IMF.RES.GAS:GAS_LIVE_2026_JAN_GAS1_VINTAGE | C45: G110.PCPI.A | E45: 86.01928 | F45: 87.37389 | G45: 88.59606 | H45: 90.594702 | I45: 92.572886 | J45: 94.030436 | K45: 95.775339 | L45: 97.720559 | M45: 100 | N45: 102.36277 | O45: 104.60849 | P45: 108.21651 | Q45: 108.4212 | R45: 110.10371 | S45: 113.08414 | T45: 115.35285 | U45: 116.94667 | V45: 118.52827 | W45: 118.89044 | X45: 119.77868 | Y45: 121.82358 | Z45: 124.20966 | AA45: 125.94727 | AB45: 126.80507 | AC45: 130.7362 | AD45: 140.29448 | AE45: 146.78291 | AF45: 150.63185 | AG45: 154.33402 | AH45: 157.67663 | AI45: 160.98024 | AJ45: 164.32009 | AK45: 167.73867 | AL45: 171.21809
A47: Trade
A48: World trade volume (goods and services) | B48: =$B$4 -> IMF.RES.GAS:GAS_LIVE | C48: G001.TOTXM_R.A | E48: 61.127781 | F48: 64.084085 | G48: 67.355346 | H48: 75.76366 | I48: 76.21544 | J48: 79.165105 | K48: 83.700853 | L48: 92.765908 | M48: 100 | N48: 109.11841 | O48: 117.61625 | P48: 120.75624 | Q48: 108.43831 | R48: 121.38285 | S48: 129.84779 | T48: 133.73853 | U48: 138.61146 | V48: 144.28036 | W48: 148.77197 | X48: 152.41793 | Y48: 160.67253 | Z48: 167.09512 | AA48: 169.00932 | AB48: 154.99146 | AC48: 171.66226 | AD48: 181.73598 | AE48: 183.52858 | AF48: 190.17711 | AG48: 197.88433 | AH48: 202.98413 | AI48: 209.34332 | AJ48: 215.9245 | AK48: 222.53417 | AL48: 229.23353
A49: Volume of imports of goods and services
A50: Advanced economies | B50: =$B$4 -> IMF.RES.GAS:GAS_LIVE | C50: G110.TM_R.A | E50: 62.301501 | F50: 66.007968 | G50: 71.233116 | H50: 79.852412 | I50: 79.866679 | J50: 82.221448 | K50: 85.796705 | L50: 93.634204 | M50: 100 | N50: 107.84658 | O50: 113.69687 | P50: 114.09248 | Q50: 101.172 | R50: 112.75501 | S50: 118.71609 | T50: 120.18134 | U50: 123.28871 | V50: 128.29211 | W50: 134.46937 | X50: 138.04512 | Y50: 144.57491 | Z50: 150.03867 | AA50: 153.08409 | AB50: 140.63053 | AC50: 154.84578 | AD50: 166.33943 | AE50: 165.13931 | AF50: 168.62871 | AG50: 174.40213 | AH50: 177.5313 | AI50: 181.67442 | AJ50: 186.07754 | AK50: 190.62904 | AL50: 195.24171
A51: Emerging market and developing economies | B51: =$B$4 -> IMF.RES.GAS:GAS_LIVE | C51: G200.TM_R.A | E51: 54.371646 | F51: 55.799667 | G51: 54.494764 | H51: 62.158614 | I51: 64.102982 | J51: 68.631738 | K51: 76.681588 | L51: 88.962535 | M51: 100 | N51: 112.61603 | O51: 130.29084 | P51: 142.13795 | Q51: 128.75983 | R51: 147.4557 | S51: 164.47469 | T51: 173.7793 | U51: 183.17068 | V51: 191.12036 | W51: 189.77318 | X51: 193.23755 | Y51: 206.81926 | Z51: 217.6218 | AA51: 216.4821 | AB51: 195.70243 | AC51: 219.07567 | AD51: 228.1104 | AE51: 236.57971 | AF51: 250.45358 | AG51: 263.32392 | AH51: 272.93472 | AI51: 285.19339 | AJ51: 297.65228 | AK51: 310.10201 | AL51: 322.69852
A53: Trade prices (export price deflator)
A54: Total goods—advanced economies | B54: =$B$4 -> IMF.RES.GAS:GAS_LIVE | C54: G110.TXG_D.A | E54: 92.381243 | F54: 88.260288 | G54: 85.750281 | H54: 83.259081 | I54: 80.045365 | J54: 80.644235 | K54: 89.105919 | L54: 96.911201 | M54: 100 | N54: 103.43956 | O54: 111.08684 | P54: 121.50936 | Q54: 109.59192 | R54: 113.51598 | S54: 124.86102 | T54: 121.3922 | U54: 120.64033 | V54: 118.14437 | W54: 102.07993 | X54: 98.94348 | Y54: 103.15968 | Z54: 108.40698 | AA54: 104.51276 | AB54: 102.99874 | AC54: 116.35131 | AD54: 123.25355 | AE54: 119.84078 | AF54: 119.78489 | AG54: 123.21879 | AH54: 124.95555 | AI54: 125.02446 | AJ54: 125.58583 | AK54: 126.66996 | AL54: 128.04869
A55: Excluding oil—advanced economies | B55: =$B$4 -> IMF.RES.GAS:GAS_LIVE | C55: G110.TXGXO_D.A | E55: 95.620138 | F55: 92.149194 | G55: 88.350247 | H55: 84.671438 | I55: 81.786814 | J55: 82.269896 | K55: 90.86923 | L55: 98.117291 | M55: 100 | N55: 102.72055 | O55: 110.40376 | P55: 119.50439 | Q55: 109.63076 | R55: 112.43541 | S55: 122.33487 | T55: 118.57345 | U55: 117.9458 | V55: 115.858 | W55: 102.70942 | X55: 100.20411 | Y55: 103.72061 | Z55: 107.9008 | AA55: 104.49753 | AB55: 104.91124 | AC55: 115.96354 | AD55: 119.79022 | AE55: 118.25534 | AF55: 118.57086 | AG55: 123.77791 | AH55: 125.86228 | AI55: 125.99882 | AJ55: 126.59837 | AK55: 127.74952 | AL55: 129.24001
A56: Manufactures—advanced economies | B56: =$B$4 -> IMF.RES.GAS:GAS_LIVE | C56: G110.TXGM_D.A | E56: 97.679598 | F56: 93.381994 | G56: 92.353761 | H56: 92.549664 | I56: 89.475974 | J56: 87.710597 | K56: 90.184704 | L56: 96.09822 | M56: 100 | N56: 102.26647 | O56: 105.64631 | P56: 112.0394 | Q56: 109.86674 | R56: 112.18836 | S56: 117.27678 | T56: 120.12045 | U56: 116.63538 | V56: 116.00469 | W56: 112.47823 | X56: 106.7862 | Y56: 106.93624 | Z56: 109.11584 | AA56: 109.52694 | AB56: 106.14018 | AC56: 113.29716 | AD56: 124.92646 | AE56: 122.75267 | AF56: 124.21448 | AG56: 125.06422 | AH56: 125.12474 | AI56: 124.90703 | AJ56: 125.5642 | AK56: 126.71681 | AL56: 128.27487
A58: Total goods—Emerging market and developing economies | B58: =$A$4 -> IMF.RES.GAS:GAS_LIVE_2026_JAN_GAS1_VINTAGE | C58: G200.TXG_D.A | E58: 74.113504 | F58: 65.235117 | G58: 67.455957 | H58: 74.432548 | I58: 70.48808 | J58: 71.253158 | K58: 77.007434 | L58: 87.258373 | M58: 100 | N58: 111.44172 | O58: 123.38641 | P58: 146.4495 | Q58: 123.87293 | R58: 142.34096 | S58: 167.09745 | T58: 166.01669 | U58: 163.36985 | V58: 157.49532 | W58: 129.55944 | X58: 119.33975 | Y58: 128.04788 | Z58: 137.17958 | AA58: 133.87547 | AB58: 130.43911 | AC58: 153.88415 | AD58: 171.19761 | AE58: 159.93017 | AF58: 157.79345 | AG58: 154.19332 | AH58: 154.31062 | AI58: 154.81261 | AJ58: 155.79776 | AK58: 157.29949 | AL58: 158.74156
A60: Commodity price indices (except otherwise indicated)
A61: All Commodity | B61: =$B$4 -> IMF.RES.GAS:GAS_LIVE | C61: G001.PZPIW.A | E61: 56.122605 | F61: 75.67685 | G61: 70.949348 | H61: 69.051092 | I61: 64.058422 | J61: 82.580299 | K61: 68.88327 | L61: 83.478697 | M61: 103.89183 | N61: 121.29842 | O61: 137.65707 | P61: 173.57391 | Q61: 119.02888 | R61: 147.1583 | S61: 180.12312 | T61: 173.46638 | U61: 166.04784 | V61: 158.10038 | W61: 107.92443 | X61: 100 | Y61: 113.32566 | Z61: 127.72534 | AA61: 117.02246 | AB61: 105.86421 | AC61: 161.50262 | AD61: 215.91706 | AE61: 165.64825 | AF61: 164.81776 | AG61: 166.92989 | AH61: 180.6904 | AI61: 180.15547 | AJ61: 179.91589 | AK61: 179.57509 | AL61: 180.04521
A62: Fuel | B62: =$B$4 -> IMF.RES.GAS:GAS_LIVE | C62: G001.PZPINRGW.A | E62: 51.019194 | F62: 37.295675 | G62: 45.867667 | H62: 73.620516 | I62: 66.356472 | J62: 62.519301 | K62: 80.431197 | L62: 97.489736 | M62: 135.52178 | N62: 153.54752 | O62: 167.66301 | P62: 232.54704 | Q62: 142.7717 | R62: 178.52656 | S62: 231.51177 | T62: 228.12098 | U62: 225.87989 | V62: 212.3207 | W62: 118.98212 | X62: 100 | Y62: 123.3007 | Z62: 156.53476 | AA62: 129.28498 | AB62: 91.704893 | AC62: 183.08872 | AD62: 299.51108 | AE62: 189.50501 | AF62: 179.50369 | AG62: 163.13711 | AH62: 156.12265 | AI62: 150.56634 | AJ62: 148.87549 | AK62: 149.26214 | AL62: 150.46166
A63: Petroleum spot price (APSP; US$) | B63: =$B$4 -> IMF.RES.GAS:GAS_LIVE | C63: G001.PZPIOIL.A | E63: 19.35173 | F63: 13.235742 | G63: 18.179252 | H63: 28.471002 | I63: 24.489567 | J63: 25.000525 | K63: 28.908935 | L63: 37.806716 | M63: 53.506305 | N63: 64.401518 | O63: 71.189201 | P63: 96.767402 | Q63: 61.501471 | R63: 79.144482 | S63: 104.06865 | T63: 105.09662 | U63: 104.17182 | V63: 96.326128 | W63: 50.911922 | X63: 43.263857 | Y63: 52.977645 | Z63: 68.532531 | AA63: 61.432334 | AB63: 41.765498 | AC63: 69.249978 | AD63: 96.362059 | AE63: 80.594907 | AF63: 79.1708 | AG63: 67.736784 | AH63: 64.743372 | AI63: 62.927397 | AJ63: 63.440084 | AK63: 64.429895 | AL63: 65.184461
A64: Natural gas | B64: =$B$4 -> IMF.RES.GAS:GAS_LIVE | C64: G001.PZPINGASW.A | E64: 69.425184 | F64: 56.795122 | G64: 58.338939 | H64: 106.15428 | I64: 102.27736 | J64: 84.139106 | K64: 215.75149 | L64: 132.29925 | M64: 192.95376 | N64: 186.96864 | O64: 191.20447 | P64: 268.20047 | Q64: 152.89304 | R64: 162.2694 | S64: 203.06382 | T64: 208.98372 | U64: 212.04551 | V64: 212.11263 | W64: 139.38497 | X64: 100 | Y64: 115.8846 | Z64: 144.58183 | AA64: 91.525832 | AB64: 71.714193 | AC64: 253.67409 | AD64: 521.57852 | AE64: 193.85854 | AF64: 167.4317 | AG64: 192.83992 | AH64: 176.79748 | AI64: 162.22097 | AJ64: 147.76761 | AK64: 141.37712 | AL64: 141.21531
A65: Coal | B65: =$B$4 -> IMF.RES.GAS:GAS_LIVE | C65: G001.PZPICLW.A | E65: 49.373937 | F65: 41.686624 | G65: 37.312759 | H65: 39.351023 | I65: 49.337859 | J65: 39.494909 | K65: 43.287888 | L65: 82.918586 | M65: 71.922353 | N65: 76.881656 | O65: 98.372558 | P65: 192.18916 | Q65: 104.44515 | R65: 145.76858 | S65: 182.63867 | T65: 144.50004 | U65: 126.65148 | V65: 110.1486 | W65: 89.045001 | X65: 100 | Y65: 132.73894 | Z65: 156.79133 | AA65: 113.95485 | AB65: 94.845975 | AC65: 199.93913 | AD65: 484.50448 | AE65: 227.80832 | AF65: 184.20102 | AG65: 149.40252 | AH65: 164.38372 | AI65: 166.62286 | AJ65: 170.09996 | AK65: 170.26494 | AL65: 170.40423
A66: Propane
A67: Nonfuel | B67: =$B$4 -> IMF.RES.GAS:GAS_LIVE | C67: G001.PZPINFW.A | E67: 59.457186 | F67: 75.67685 | G67: 70.949348 | H67: 69.051092 | I67: 64.058422 | J67: 82.580299 | K67: 59.294887 | L67: 70.168015 | M67: 73.842936 | N67: 90.949219 | O67: 109.41887 | P67: 118.07509 | Q67: 96.684821 | R67: 117.73972 | S67: 138.07304 | T67: 130.07484 | U67: 121.89529 | V67: 118.08896 | W67: 100.27984 | X67: 100 | Y67: 106.42955 | Z67: 107.80835 | AA67: 108.54494 | AB67: 115.65306 | AC67: 146.57937 | AD67: 158.12549 | AE67: 149.15521 | AF67: 154.66485 | AG67: 169.55197 | AH67: 197.67497 | AI67: 200.91818 | AJ67: 201.71628 | AK67: 202.16012 | AL67: 200.49739
A68: Food | B68: =$B$4 -> IMF.RES.GAS:GAS_LIVE | C68: G001.PZPIFW.A | E68: 62.165952 | F68: 75.67685 | G68: 70.949348 | H68: 69.051092 | I68: 64.058422 | J68: 82.580299 | K68: 77.557048 | L68: 84.09519 | M68: 81.23957 | N68: 85.335527 | O68: 104.37831 | P68: 118.28187 | Q68: 96.792416 | R68: 109.15882 | S68: 122.46714 | T68: 119.74851 | U68: 120.46474 | V68: 118.60796 | W68: 98.550493 | X68: 100 | Y68: 103.76375 | Z68: 102.49812 | AA68: 99.366643 | AB68: 101.08529 | AC68: 128.36468 | AD68: 147.40254 | AE68: 137.42782 | AF68: 133.13716 | AG68: 127.06488 | AH68: 130.48941 | AI68: 131.76046 | AJ68: 131.99335 | AK68: 131.2716 | AL68: 130.75439
A69: Beverages | B69: =$B$4 -> IMF.RES.GAS:GAS_LIVE | C69: G001.PZPIBEVW.A | E69: 87.70308 | F69: 79.379787 | G69: 62.570409 | H69: 48.331012 | I69: 38.610448 | J69: 45.193399 | K69: 46.469961 | L69: 47.491992 | M69: 60.466765 | N69: 67.638015 | O69: 80.906928 | P69: 98.135428 | Q69: 90.144888 | R69: 105.45888 | S69: 131.97172 | T69: 105.28716 | U69: 92.291639 | V69: 111.30784 | W69: 103.04079 | X69: 100 | Y69: 96.206743 | Z69: 87.325649 | AA69: 82.362063 | AB69: 84.376444 | AC69: 103.31252 | AD69: 117.91599 | AE69: 122.62969 | AF69: 201.54283 | AG69: 236.62794 | AH69: 172.10916 | AI69: 162.20156 | AJ69: 159.77635 | AK69: 159.77635 | AL69: 159.77635
A70: Agricultural raw materials | B70: =$B$4 -> IMF.RES.GAS:GAS_LIVE | C70: G001.PZPIRAW.A | E70: 86.862244 | F70: 71.344442 | G70: 70.376412 | H70: 72.344672 | I70: 65.034155 | J70: 67.013161 | K70: 76.839026 | L70: 85.428395 | M70: 88.02988 | N70: 100.13326 | O70: 104.60559 | P70: 111.45537 | Q70: 96.58314 | R70: 128.44464 | S70: 162.7488 | T70: 128.29053 | U70: 122.25148 | V70: 112.90149 | W70: 100.17853 | X70: 100 | Y70: 105.38354 | Z70: 107.49071 | AA70: 101.66184 | AB70: 98.192673 | AC70: 113.38132 | AD70: 119.8929 | AE70: 101.23642 | AF70: 105.60835 | AG70: 103.55046 | AH70: 99.072595 | AI70: 101.37604 | AJ70: 101.57437 | AK70: 101.44816 | AL70: 101.44816
A71: Metals | B71: =$B$4 -> IMF.RES.GAS:GAS_LIVE | C71: G001.PZPIMETW.A | E71: 50.906027 | F71: 41.034975 | G71: 41.389527 | H71: 47.932398 | I71: 41.794201 | J71: 41.329813 | K71: 59.889724 | L71: 84.938246 | M71: 97.481983 | N71: 160.63418 | O71: 194.44956 | P71: 157.14353 | Q71: 111.86916 | R71: 157.18618 | S71: 174.313 | T71: 150.05316 | U71: 136.67488 | V71: 136.69901 | W71: 105.6045 | X71: 100 | Y71: 122.18869 | Z71: 130.28732 | AA71: 135.32033 | AB71: 140.01003 | AC71: 205.41254 | AD71: 193.89513 | AE71: 188.54757 | AF71: 184.94948 | AG71: 188.82544 | AH71: 217.49364 | AI71: 216.61678 | AJ71: 215.67934 | AK71: 214.30039 | AL71: 214.05085
A73: Agriculture | B73: =$B$4 -> IMF.RES.GAS:GAS_LIVE | C73: G001.PZPIAGRW.A | E73: 67.082094 | F73: 75.67685 | G73: 70.949348 | H73: 69.051092 | I73: 64.058422 | J73: 82.580299 | K73: 74.037985 | L73: 80.933736 | M73: 80.542192 | N73: 86.361374 | O73: 102.27454 | P73: 115.22215 | Q73: 96.147721 | R73: 112.36875 | S73: 128.96766 | T73: 119.94124 | U73: 118.78014 | V73: 117.3769 | W73: 99.065336 | X73: 100 | Y73: 103.45876 | Z73: 102.10994 | AA73: 98.506559 | AB73: 99.577177 | AC73: 124.7324 | AD73: 141.85566 | AE73: 131.7611 | AF73: 134.24082 | AG73: 131.48271 | AH73: 129.2719 | AI73: 129.8878 | AJ73: 129.93064 | AK73: 128.9302 | AL73: 128.95253
A74: Cereal | B74: =$B$4 -> IMF.RES.GAS:GAS_LIVE | C74: G001.PZPICERW.A | E74: 88.621356 | F74: 74.460011 | G74: 64.201021 | H74: 62.606684 | I74: 64.664827 | J74: 76.282558 | K74: 80.732805 | L74: 82.915215 | M74: 77.501345 | N74: 99.194306 | O74: 134.6672 | P74: 174.96361 | Q74: 119.97136 | R74: 127.33463 | S74: 180.64861 | T74: 182.37295 | U74: 170.4871 | V74: 140.83757 | W74: 115.00408 | X74: 100 | Y74: 100.98161 | Z74: 114.88056 | AA74: 109.88146 | AB74: 119.12132 | AC74: 167.56642 | AD74: 209.11418 | AE74: 169.70612 | AF74: 135.64523 | AG74: 119.97671 | AH74: 131.83692 | AI74: 143.88464 | AJ74: 145.61691 | AK74: 143.18896 | AL74: 143.18896
A75: Coffee | B75: =$B$4 -> IMF.RES.GAS:GAS_LIVE | C75: G001.PZPICFW.A | E75: 102.04558 | F75: 88.017493 | G75: 69.870641 | H75: 50.060811 | I75: 34.572151 | J75: 35.678698 | K75: 40.41313 | L75: 44.857292 | M75: 63.578782 | N75: 73.04483 | O75: 86.606785 | P75: 101.99155 | Q75: 85.930212 | R75: 104.25159 | S75: 144.37083 | T75: 114.92452 | U75: 95.671002 | V75: 117.80308 | W75: 98.471297 | X75: 100 | Y75: 102.9712 | Z75: 88.333501 | AA75: 81.350011 | AB75: 84.824065 | AC75: 113.14895 | AD75: 136.43272 | AE75: 130.0686 | AF75: 191.22394 | AG75: 241.17042 | AH75: 191.19903 | AI75: 174.44535 | AJ75: 170.56048 | AK75: 170.56048 | AL75: 170.56048
A76: Food and Beverage | B76: =$B$4 -> IMF.RES.GAS:GAS_LIVE | C76: G001.PZPIFBW.A | E76: 64.158084 | F76: 75.67685 | G76: 70.949348 | H76: 69.051092 | I76: 64.058422 | J76: 82.580299 | K76: 73.721145 | L76: 79.935197 | M76: 78.878718 | N76: 83.367146 | O76: 101.76774 | P76: 116.04111 | Q76: 96.053054 | R76: 108.7473 | S76: 123.26002 | T76: 118.61058 | U76: 118.26698 | V76: 118.03848 | W76: 98.900777 | X76: 100 | Y76: 103.17423 | Z76: 101.31453 | AA76: 98.040129 | AB76: 99.781842 | AC76: 126.41038 | AD76: 145.10231 | AE76: 136.27343 | AF76: 138.47343 | AG76: 135.61181 | AH76: 133.73613 | AI76: 134.10256 | AJ76: 134.19175 | AK76: 132.99275 | AL76: 133.01837
A77: Hardwood | B77: =$B$4 -> IMF.RES.GAS:GAS_LIVE | C77: G001.PZPITIHWW.A | E77: 88.797015 | F77: 63.78782 | G77: 77.638554 | H77: 77.762671 | I77: 63.900216 | J77: 66.943393 | K77: 72.646094 | L77: 76.762554 | M77: 84.95625 | N77: 97.429576 | O77: 105.89757 | P77: 116.44305 | Q77: 107.79583 | R77: 111.02456 | S77: 131.42128 | T77: 122.20634 | U77: 114.26329 | V77: 116.2506 | W77: 106.26305 | X77: 100 | Y77: 95.506776 | Z77: 98.457065 | AA77: 95.68969 | AB77: 96.952155 | AC77: 100.76587 | AD77: 88.980104 | AE77: 87.690656 | AF77: 87.914809 | AG77: 90.285183 | AH77: 91.144311 | AI77: 91.144311 | AJ77: 91.144311 | AK77: 91.144311 | AL77: 91.144311
A78: Industrial Inputs | B78: =$B$4 -> IMF.RES.GAS:GAS_LIVE | C78: G001.PZPIINDW.A | E78: 61.132865 | F78: 49.655737 | G78: 49.634115 | H78: 54.875853 | I78: 48.404219 | J78: 48.634793 | K78: 63.407045 | L78: 85.113871 | M78: 94.095201 | N78: 138.9561 | O78: 162.25758 | P78: 140.77301 | Q78: 106.39203 | R78: 146.65208 | S78: 170.07458 | T78: 142.0769 | U78: 131.28326 | V78: 127.80324 | W78: 104.06122 | X78: 100 | Y78: 117.40889 | Z78: 123.8034 | AA78: 125.74702 | AB78: 128.11614 | AC78: 179.23658 | AD78: 172.84706 | AE78: 163.71412 | AF78: 162.3829 | AG78: 164.57113 | AH78: 183.81176 | AI78: 183.83946 | AJ78: 183.22507 | AK78: 182.20242 | AL78: 182.02386
A79: Meat | B79: =$B$4 -> IMF.RES.GAS:GAS_LIVE | C79: G001.PZPIMTW.A | E79: 78.171316 | F79: 61.105869 | G79: 61.058964 | H79: 69.256174 | I79: 74.420935 | J79: 68.154286 | K79: 75.275056 | L79: 95.772521 | M79: 91.890202 | N79: 86.533001 | O79: 89.503931 | P79: 92.728241 | Q79: 84.438237 | R79: 102.69087 | S79: 114.48616 | T79: 110.08181 | U79: 112.97669 | V79: 134.01286 | W79: 109.55627 | X79: 100 | Y79: 109.89133 | Z79: 106.51295 | AA79: 111.86871 | AB79: 102.75987 | AC79: 136.32839 | AD79: 152.16312 | AE79: 129.37829 | AF79: 142.43974 | AG79: 159.67919 | AH79: 164.42345 | AI79: 161.57934 | AJ79: 161.04349 | AK79: 161.04349 | AL79: 161.04349
... A88: Wool | B88: =$B$4 -> IMF.RES.GAS:GAS_LIVE | C88: G001.PZPIWLW.A | E88: 55.901787 | F88: 41.370625 | G88: 41.40977 | H88: 46.765829 | I88: 44.348721 | J88: 56.755301 | K88: 62.902522 | L88: 64.347209 | M88: 60.820122 | N88: 64.324885 | O88: 87.411646 | P88: 86.967965 | Q88: 69.926507 | R88: 85.822721 | S88: 132.5653 | T88: 119.75536 | U88: 108.80199 | V88: 98.644792 | W88: 90.992376 | X88: 100 | Y88: 117.97623 | Z88: 149.44115 | AA88: 132.62554 | AB88: 86.598644 | AC88: 99.816197 | AD88: 95.177252 | AE88: 89.173208 | AF88: 84.929131 | AG88: 95.695584 | AH88: 44.540594 | AI88: 44.540594 | AJ88: 44.540594 | AK88: 44.540594 | AL88: 44.540594
A90: Nonfuel commodity prices
A91: Agriculture
A92: Agricultural Raw Materials
A93: Cotton | B93: =$B$4 -> IMF.RES.GAS:GAS_LIVE | C93: G001.PZPICOT.A | E93: 79.228666 | F93: 65.530375 | G93: 53.126085 | H93: 59.047715 | I93: 47.996912 | J93: 46.26013 | K93: 63.44535 | L93: 62.006 | M93: 55.168263 | N93: 58.052463 | O93: 63.283692 | P93: 71.399863 | Q93: 62.752034 | R93: 103.54372 | S93: 154.98313 | T93: 89.240967 | U93: 90.400613 | V93: 83.096741 | W93: 70.417182 | X93: 74.213819 | Y93: 83.598314 | Z93: 91.378536 | AA93: 77.879068 | AB93: 71.937989 | AC93: 101.18518 | AD93: 130.13901 | AE93: 95.0106 | AF93: 86.647668 | AG93: 77.435112 | AH93: 75.52297 | AI93: 80.867732 | AJ93: 81.669529 | AK93: 81.159294 | AL93: 81.159294
A94: Hides | B94: =$B$4 -> IMF.RES.GAS:GAS_LIVE | C94: G001.PZPIHIDE.A | E94: 86.194448 | F94: 75.989121 | G94: 61.65533 | H94: 65.571232 | I94: 70.677707 | J94: 66.82621 | K94: 69.041138 | L94: 67.983622 | M94: 64.937981 | N94: 68.732839 | O94: 72.750384 | P94: 65.06889 | Q94: 40.786568 | R94: 69.473906 | S94: 81.476561 | T94: 81.63978 | U94: 96.339617 | V94: 106.56916 | W94: 87.886698 | X94: 73.277292 | Y94: 69.203908 | Z94: 59.95053 | AA94: 40.807021 | AB94: 33.567213 | AC94: 47.418792 | AD94: 57.556472 | AE94: 58.633973 | AF94: 58.652686 | AG94: 57.765023 | AH94: 57.423233 | AI94: 57.423233 | AJ94: 57.423233 | AK94: 57.423233 | AL94: 57.423233
A95: Rubber | B95: =$B$4 -> IMF.RES.GAS:GAS_LIVE | C95: G001.PZPIRUB.A | E95: 46.159007 | F95: 32.735297 | G95: 28.832359 | H95: 30.298281 | I95: 26.086126 | J95: 34.702646 | K95: 48.646211 | L95: 58.118277 | M95: 67.494337 | N95: 94.275656 | O95: 102.60247 | P95: 117.41399 | Q95: 87.15774 | R95: 165.71913 | S95: 218.51463 | T95: 153.19015 | U95: 126.7587 | V95: 88.751255 | W95: 70.731279 | X95: 74.483558 | Y95: 90.790599 | Z95: 70.411335 | AA95: 74.83567 | AB95: 79.898455 | AC95: 94.520037 | AD95: 83.285834 | AE95: 71.79592 | AF95: 105.06818 | AG95: 100.39531 | AH95: 97.778106 | AI95: 98.746952 | AJ95: 98.746952 | AK95: 98.746952 | AL95: 98.746952
A96: Timber
A97: Hardwood
A98: Hardwood Logs | B98: =$B$4 -> IMF.RES.GAS:GAS_LIVE | C98: G001.PZPITIHWL.A | E98: 237.74239 | F98: 162.86001 | G98: 187.02536 | H98: 190.0628 | I98: 159.87595 | J98: 162.40345 | K98: 187.15181 | L98: 197.25557 | M98: 203.12028 | N98: 239.42915 | O98: 267.98066 | P98: 292.29698 | Q98: 287.20279 | R98: 278.17199 | S98: 390.5122 | T98: 360.5103 | U98: 305.43418 | V98: 282.04118 | W98: 246.01583 | X98: 274.37688 | Y98: 265.42943 | Z98: 269.70394 | AA98: 273.10311 | AB98: 278.99057 | AC98: 271.35119 | AD98: 227.99022 | AE98: 212.37619 | AF98: 196.74956 | AG98: 199.10008 | AH98: 189.99416 | AI98: 189.99416 | AJ98: 189.99416 | AK98: 189.99416 | AL98: 189.99416
A99: Hard Sawnwood | B99: =$B$4 -> IMF.RES.GAS:GAS_LIVE | C99: G001.PZPITIHWS.A | E99: 662.32882 | F99: 484.15459 | G99: 601.10723 | H99: 599.17646 | I99: 488.4618 | J99: 517.09539 | K99: 549.62052 | L99: 581.29371 | M99: 659.38228 | N99: 749.34344 | O99: 806.29677 | P99: 889.09163 | Q99: 805.52444 | R99: 848.27196 | S99: 939.44698 | T99: 876.34202 | U99: 852.79773 | V99: 897.942 | W99: 833.2505 | X99: 738.87921 | Y99: 702.10954 | Z99: 727.94287 | AA99: 695.88779 | AB99: 702.65667 | AC99: 749.95217 | AD99: 674.51017 | AE99: 677.73475 | AF99: 696.54179 | AG99: 718.44171 | AH99: 736.89447 | AI99: 736.89447 | AJ99: 736.89447 | AK99: 736.89447 | AL99: 736.89447
A100: Softwood
A101: Softwood Logs | B101: =$B$4 -> IMF.RES.GAS:GAS_LIVE | C101: G001.PZPITISWL.A | E101: 196.45696 | F101: 166.4395 | G101: 170.36783 | H101: 185.32787 | I101: 162.97904 | J101: 149.46919 | K101: 151.37733 | L101: 181.65748 | M101: 187.12834 | N101: 197.99324 | O101: 171.85861 | P101: 172.40436 | Q101: 148.29825 | R101: 155.01484 | S101: 170.90346 | T101: 161.17659 | U101: 175.47624 | V101: 184.22252 | W101: 181.08834 | X101: 182.81951 | Y101: 190.70759 | Z101: 211.41615 | AA101: 185.88833 | AB101: 199.77833 | AC101: 235.99917 | AD101: 270.89833 | AE101: 215.60583 | AF101: 194.94497 | AG101: 205.79967 | AH101: 219.27539 | AI101: 241.84917 | AJ101: 241.84917 | AK101: 241.84917 | AL101: 241.84917
A102: Sawn Softwood | B102: =$B$4 -> IMF.RES.GAS:GAS_LIVE | C102: G001.PZPITISWS.A | E102: 294.12803 | F102: 279.8145 | G102: 300.54671 | H102: 284.80663 | I102: 282.82808 | J102: 273.25117 | K102: 284.3035 | L102: 323.9735 | M102: 328.3355 | N102: 342.44058 | O102: 325.91083 | P102: 313.12308 | Q102: 315.42278 | R102: 309.67812 | S102: 299.30979 | T102: 316.84081 | U102: 332.53487 | V102: 332.85494 | W102: 317.97936 | X102: 325.14671 | Y102: 319.89608 | Z102: 344.57054 | AA102: 353.86667 | AB102: 347.81917 | AC102: 353.285 | AD102: 400.08083 | AE102: 318.38167 | AF102: 321.05645 | AG102: 314.57514 | AH102: 289.89221 | AI102: 289.89221 | AJ102: 289.89221 | AK102: 289.89221 | AL102: 289.89221
A103: Wool + Yarn
A104: Wool, Coarse | B104: =$B$4 -> IMF.RES.GAS:GAS_LIVE | C104: G001.PZPIWL_Type1.A | E104: 442.79361 | F104: 336.38913 | G104: 276.47131 | H104: 280.97889 | I104: 332.43175 | J104: 565.6516 | K104: 658.99135 | L104: 553.20076 | M104: 530.60979 | N104: 540.58431 | O104: 764.86796 | P104: 709.20833 | Q104: 611.36014 | R104: 818.84668 | S104: 1200.156 | T104: 1208.3139 | U104: 1118.3959 | V104: 1023.9588 | W104: 929.8654 | X104: 1017.1415 | Y104: 1089.2082 | Z104: 1519.1843 | AA104: 1393.3735 | AB104: 869.6199 | AC104: 908.67123 | AD104: 880.98492 | AE104: 882.48895 | AF104: 880.88179 | AG104: 998.44795 | AH104: 464.77897 | AI104: 464.77897 | AJ104: 464.77897 | AK104: 464.77897 | AL104: 464.77897
A105: Wool, Fine | B105: =$B$4 -> IMF.RES.GAS:GAS_LIVE | C105: G001.PZPIWL_Type2.A | E105: 759.84386 | F105: 552.81422 | G105: 619.24971 | H105: 733.54229 | I105: 623.4364 | J105: 644.40751 | K105: 700.09948 | L105: 716.17871 | M105: 676.92254 | N105: 715.93025 | O105: 972.88384 | P105: 967.94571 | Q105: 778.2758 | R105: 1014.3884 | S105: 1637.6281 | T105: 1343.5544 | U105: 1198.1257 | V105: 1075.3647 | W105: 1007.9835 | X105: 1112.9911 | Y105: 1434.2809 | Z105: 1664.1899 | AA105: 1427.5439 | AB105: 976.10246 | AC105: 1227.5915 | AD105: 1154.6247 | AE105: 1019.3301 | AF105: 926.61626 | AG105: 1037.6307 | AH105: 482.8886 | AI105: 482.8886 | AJ105: 482.8886 | AK105: 482.8886 | AL105: 482.8886
A106: Beverages
A107: Coffee
A108: Coffee, Arabica | B108: =$B$4 -> IMF.RES.GAS:GAS_LIVE | C108: G001.PZPICF_Type3.A | E108: 188.92811 | F108: 135.46927 | G108: 103.88442 | H108: 87.20411 | I108: 62.284133 | J108: 61.462068 | K108: 64.172862 | L108: 80.479525 | M108: 114.85392 | N108: 114.40886 | O108: 123.61388 | P108: 139.71247 | Q108: 143.75476 | R108: 196.04909 | S108: 271.10806 | T108: 186.44158 | U108: 139.48434 | V108: 200.3559 | W108: 159.90369 | X108: 163.83998 | Y108: 150.75595 | Z108: 132.71493 | AA108: 130.55576 | AB108: 150.83195 | AC108: 204.69403 | AD108: 255.4659 | AE108: 205.95975 | AF108: 255.44463 | AG108: 383.09798 | AH108: 300.25375 | AI108: 279.34127 | AJ108: 268.8451 | AK108: 268.8451 | AL108: 268.8451
A109: Coffee, Robusta | B109: =$B$4 -> IMF.RES.GAS:GAS_LIVE | C109: G001.PZPICF_Type2.A | E109: 78.672792 | F109: 82.724811 | G109: 67.645906 | H109: 41.558164 | I109: 27.585614 | J109: 29.991423 | K109: 36.916232 | L109: 35.97293 | M109: 50.561491 | N109: 67.579242 | O109: 86.636841 | P109: 105.19652 | Q109: 74.544038 | R109: 78.73103 | S109: 109.23837 | T109: 102.84351 | U109: 94.117763 | V109: 100.4194 | W109: 88.036527 | X109: 88.61686 | Y109: 100.95965 | Z109: 84.774638 | AA109: 73.565376 | AB109: 68.755699 | AC109: 89.824322 | AD109: 103.6298 | AE109: 119.12706 | AF109: 200.74982 | AG109: 220.2274 | AH109: 176.46957 | AI109: 158.08743 | AJ109: 156.87924 | AK109: 156.87924 | AL109: 156.87924
A110: Cocoa | B110: =$B$4 -> IMF.RES.GAS:GAS_LIVE | C110: G001.PZPICO.A | E110: 1618.7433 | F110: 1676.0035 | G110: 1135.0494 | H110: 903.90636 | I110: 1088.3758 | J110: 1779.0413 | K110: 1752.5035 | L110: 1551.0018 | M110: 1538.136 | N110: 1590.5378 | O110: 1954.3909 | P110: 2576.9941 | Q110: 2890.8813 | R110: 3130.5989 | S110: 2978.4933 | T110: 2393.439 | U110: 2439.0935 | V110: 3062.7681 | W110: 3135.1663 | X110: 2891.2566 | Y110: 2029.3379 | Z110: 2293.7391 | AA110: 2340.8215 | AB110: 2369.9582 | AC110: 2425.5182 | AD110: 2369.4029 | AE110: 3258.0444 | AF110: 7390.5643 | AG110: 7788.2665 | AH110: 4325.0088 | AI110: 4402.5483 | AJ110: 4406.9355 | AK110: 4406.9355 | AL110: 4406.9355
A111: Tea | B111: =$B$4 -> IMF.RES.GAS:GAS_LIVE | C111: G001.PZPITEA.A | E111: 237.18897 | F111: 238.56255 | G111: 232.35667 | H111: 248.11667 | I111: 198.12333 | J111: 179.1875 | K111: 194.32583 | L111: 198.15083 | M111: 216.37917 | N111: 241.7 | O111: 211.92917 | P111: 269.50583 | Q111: 313.95667 | R111: 316.73723 | S111: 346.16056 | T111: 348.91512 | U111: 265.60126 | V111: 237.85755 | W111: 340.38668 | X111: 287.42952 | Y111: 362.20146 | Z111: 298.26015 | AA111: 268.27633 | AB111: 253.93312 | AC111: 267.20341 | AD111: 277.94792 | AE111: 290.21567 | AF111: 328.02311 | AG111: 316.76504 | AH111: 309.80011 | AI111: 309.80011 | AJ111: 309.80011 | AK111: 309.80011 | AL111: 309.80011
A112: Food
A113: Cereals
A114: Barley | B114: =$B$4 -> IMF.RES.GAS:GAS_LIVE | C114: G001.PZPIBR.A | E114: 97.23718 | F114: 85.05402 | G114: 75.937005 | H114: 77.234862 | I114: 93.936141 | J114: 108.96744 | K114: 104.71754 | L114: 98.988548 | M114: 95.077129 | N114: 116.6151 | O114: 172.38122 | P114: 200.47616 | Q114: 128.38131 | R114: 158.37447 | S114: 207.21924 | T114: 238.58284 | U114: 200.83262 | V114: 132.50146 | W114: 100.278 | X114: 97.809375 | Y114: 101.65963 | Z114: 104.35974 | AA114: 110.43471 | AB114: 104.62608 | AC114: 178.08534 | AD114: 225.21077 | AE114: 166.91444 | AF114: 136.14724 | AG114: 115.3624 | AH114: 126.2593 | AI114: 125.01306 | AJ114: 125.01306 | AK114: 125.01306 | AL114: 125.01306
A115: Maize (Corn) | B115: =$B$4 -> IMF.RES.GAS:GAS_LIVE | C115: G001.PZPIMAIZ.A | E115: 117.17242 | F115: 101.61784 | G115: 90.294064 | H115: 88.219229 | I115: 89.609138 | J115: 99.333267 | K115: 105.24536 | L115: 111.89487 | M115: 98.507652 | N115: 121.64739 | O115: 163.60989 | P115: 223.36029 | Q115: 165.62835 | R115: 185.9565 | S115: 291.85408 | T115: 298.43755 | U115: 258.97947 | V115: 192.93923 | W115: 169.84464 | X115: 159.22097 | Y115: 154.59502 | Z115: 164.51083 | AA115: 170.16945 | AB115: 165.57839 | AC115: 259.39484 | AD115: 318.36103 | AE115: 251.45554 | AF115: 190.46165 | AG115: 203.00639 | AH115: 214.47484 | AI115: 228.70557 | AJ115: 232.52836 | AK115: 228.64537 | AL115: 228.64537
A116: Oats | B116: =$B$4 -> IMF.RES.GAS:GAS_LIVE | C116: G001.PZPIOAT.A | E116: 1.6471249 | F116: 1.2308876 | G116: 1.1138359 | H116: 1.0967084 | I116: 1.3951547 | J116: 1.9485102 | K116: 1.6308746 | L116: 1.5127041 | M116: 1.6184748 | N116: 2.0427759 | O116: 2.6978791 | P116: 3.3922365 | Q116: 2.1823512 | R116: 2.7426259 | S116: 3.5417851 | T116: 3.4688935 | U116: 3.6731463 | V116: 3.7441064 | W116: 2.5001391 | X116: 1.9663009 | Y116: 2.5204368 | Z116: 2.5616458 | AA116: 2.8663541 | AB116: 2.9684515 | AC116: 4.8216517 | AD116: 5.5441549 | AE116: 3.8134718 | AF116: 3.5600868 | AG116: 3.4316246 | AH116: 3.1966962 | AI116: 3.3584375 | AJ116: 3.305625 | AK116: 3.23875 | AL116: 3.23875
A117: Rice | B117: =$B$4 -> IMF.RES.GAS:GAS_LIVE | C117: G001.PZPIRIN.A | E117: 302.46945 | F117: 305.42361 | G117: 248.96805 | H117: 203.69487 | I117: 172.70505 | J117: 191.82625 | K117: 199.46148 | L117: 245.78338 | M117: 287.81127 | N117: 303.51526 | O117: 332.39319 | P117: 700.19961 | Q117: 589.37639 | R117: 520.49365 | S117: 551.7107 | T117: 580.23616 | U117: 519.30795 | V117: 426.47507 | W117: 380.04657 | X117: 388.26486 | Y117: 399.07462 | Z117: 403.08166 | AA117: 396.51368 | AB117: 477.83824 | AC117: 441.96272 | AD117: 419.0561 | AE117: 528.57205 | AF117: 565.17614 | AG117: 384.13371 | AH117: 440.9699 | AI117: 470.40572 | AJ117: 470.40572 | AK117: 470.40572 | AL117: 470.40572
A118: Sorghum | B118: =$B$4 -> IMF.RES.GAS:GAS_LIVE | C118: G001.PZPISORG.A | E118: 4.9644894 | F118: 4.4362518 | G118: 3.8234549 | H118: 3.9828593 | I118: 4.3343427 | J118: 4.5638903 | K118: 4.8211823 | L118: 4.9484539 | M118: 4.3379325 | N118: 5.5849417 | O118: 7.3729159 | P118: 9.6645417 | Q118: 6.9455314 | R118: 7.5971667 | S118: 12.162333 | T118: 12.729671 | U118: 12.1108 | V118: 8.798825 | W118: 9.1466417 | X118: 7.0665 | Y118: 7.359175 | Z118: 7.6483898 | AA118: 7.3260874 | AB118: 9.1799992 | AC118: 15.456458 | AD118: 16.807102 | AE118: 14.444742 | AF118: 10.763483 | AG118: 9.0460304 | AH118: 8.5226049 | AI118: 8.5226049 | AJ118: 8.5226049 | AK118: 8.5226049 | AL118: 8.5226049
A119: Wheat | B119: =$B$4 -> IMF.RES.GAS:GAS_LIVE | C119: G001.PZPIWHE.A | E119: 149.5128 | F119: 114.46476 | G119: 98.260947 | H119: 100.73902 | I119: 106.37298 | J119: 132.16746 | K119: 131.91876 | L119: 134.39089 | M119: 129.67383 | N119: 169.13864 | O119: 231.18494 | P119: 292.96747 | Q119: 192.10747 | R119: 195.2299 | S119: 280.28247 | T119: 276.33019 | U119: 265.68628 | V119: 242.89891 | W119: 185.86598 | X119: 143.20097 | Y119: 145.29359 | Z119: 186.12899 | AA119: 163.25767 | AB119: 185.51318 | AC119: 265.79317 | AD119: 360.17478 | AE119: 272.33217 | AF119: 201.19488 | AG119: 173.09195 | AH119: 196.79831 | AI119: 220.86223 | AJ119: 225.3291 | AK119: 222.88059 | AL119: 222.88059
...

Sheet Complete DataSet Q
A1: CONFIDENTIAL do not share outside the Fund without prior authorization
A2: IMF.RES.GAS:GAS_LIVE_2026_JAN_GAS1_VINTAGE | E2: 2012 | F2: =E2 -> 2012 | G2: =E2 -> 2012 | H2: =E2 -> 2012 | I2: =E2+1 -> 2013 | J2: =F2+1 -> 2013 | K2: =G2+1 -> 2013 | L2: =H2+1 -> 2013 | M2: =I2+1 -> 2014 | N2: =J2+1 -> 2014 | O2: =K2+1 -> 2014 | P2: =L2+1 -> 2014 | ... BT2: =BP2+1 -> 2028
E3: Q1 | F3: Q2 | G3: Q3 | H3: Q4 | I3: =E3 -> Q1 | J3: =F3 -> Q2 | K3: =G3 -> Q3 | L3: =H3 -> Q4 | M3: =I3 -> Q1 | N3: =J3 -> Q2 | O3: =K3 -> Q3 | P3: =L3 -> Q4 | ... BT3: =BP3 -> Q4
A4: IMF.RES.GAS:GAS_LIVE | B4: DATASET | C4: Series_Code | E4: 2012Q1 | F4: 2012Q2 | G4: 2012Q3 | H4: 2012Q4 | I4: 2013Q1 | J4: 2013Q2 | K4: 2013Q3 | L4: 2013Q4 | M4: 2014Q1 | N4: 2014Q2 | O4: 2014Q3 | P4: 2014Q4 | Q4: 2015Q1 | R4: 2015Q2 | S4: 2015Q3 | T4: 2015Q4 | U4: 2016Q1 | V4: 2016Q2 | W4: 2016Q3 | X4: 2016Q4 | Y4: 2017Q1 | Z4: 2017Q2 | AA4: 2017Q3 | AB4: 2017Q4 | AC4: 2018Q1 | AD4: 2018Q2 | AE4: 2018Q3 | AF4: 2018Q4 | AG4: 2019Q1 | AH4: 2019Q2 | AI4: 2019Q3 | AJ4: 2019Q4 | AK4: 2020Q1 | AL4: 2020Q2 | AM4: 2020Q3 | AN4: 2020Q4 | AO4: 2021Q1 | AP4: 2021Q2 | AQ4: 2021Q3 | AR4: 2021Q4 | AS4: 2022Q1 | AT4: 2022Q2 | AU4: 2022Q3 | AV4: 2022Q4 | AW4: 2023Q1 | AX4: 2023Q2 | AY4: 2023Q3 | AZ4: 2023Q4 | BA4: 2024Q1 | BB4: 2024Q2 | BC4: 2024Q3 | BD4: 2024Q4 | BE4: 2025Q1 | BF4: 2025Q2 | BG4: 2025Q3 | BH4: 2025Q4 | BI4: 2026Q1 | BJ4: 2026Q2 | BK4: 2026Q3 | BL4: 2026Q4 | BM4: 2027Q1 | BN4: 2027Q2 | BO4: 2027Q3 | BP4: 2027Q4 | BQ4: 2028Q1 | BR4: 2028Q2 | BS4: 2028Q3 | BT4: 2028Q4
A5: OUTPUT, DEMAND, INFLATION, AND TRADE
A7: Real GDP for G-7 countries
A8: United States | B8: =$A$2 -> IMF.RES.GAS:GAS_LIVE_2026_JAN_GAS1_VINTAGE | C8: USA.NGDP_R.Q | E8: 17367 | F8: 17444.5 | G8: 17469.7 | H8: 17489.9 | I8: 17662.4 | J8: 17709.7 | K8: 17860.5 | L8: 18016.1 | M8: 17954 | N8: 18185.9 | O8: 18406.9 | P8: 18500 | Q8: 18666.6 | R8: 18782.2 | S8: 18857.4 | T8: 18892.2 | U8: 19001.7 | V8: 19062.7 | W8: 19197.9 | X8: 19304.4 | Y8: 19398.3 | Z8: 19506.9 | AA8: 19660.8 | AB8: 19882.4 | AC8: 20044.1 | AD8: 20150.5 | AE8: 20276.2 | AF8: 20304.9 | AG8: 20431.6 | AH8: 20602.3 | AI8: 20843.3 | AJ8: 20985.4 | AK8: 20709.2 | AL8: 19078 | AM8: 20558.9 | AN8: 20791.9 | AO8: 21082.1 | AP8: 21440.9 | AQ8: 21617.8 | AR8: 21988.7 | AS8: 21932.7 | AT8: 21967 | AU8: 22125.6 | AV8: 22278.3 | AW8: 22439.6 | AX8: 22580.5 | AY8: 22841 | AZ8: 23033.8 | BA8: 23082.1 | BB8: 23286.5 | BC8: 23478.6 | BD8: 23586.5 | BE8: 23548.2 | BF8: 23771 | BG8: 23956.083 | BH8: 24042.515 | BI8: 24151.763 | BJ8: 24267.461 | BK8: 24389.692 | BL8: 24512.538 | BM8: 24770.795 | BN8: 24774.29 | BO8: 24831.148 | BP8: 24991.75
A9: Euro Area | B9: =$A$2 -> IMF.RES.GAS:GAS_LIVE_2026_JAN_GAS1_VINTAGE | C9: G163.NGDP_R.Q | E9: 2778.1288 | F9: 2768.7046 | G9: 2764.8182 | H9: 2753.3559 | I9: 2743.9248 | J9: 2761.8141 | K9: 2769.8961 | L9: 2776.0367 | M9: 2788.6404 | N9: 2795.3781 | O9: 2808.9647 | P9: 2819.8843 | Q9: 2840.6981 | R9: 2852.7294 | S9: 2864.9559 | T9: 2879.5295 | U9: 2892.9647 | V9: 2898.4784 | W9: 2912.6434 | X9: 2934.8098 | Y9: 2958.3911 | Z9: 2977.9179 | AA9: 3000.1045 | AB9: 3024.5315 | AC9: 3025.5798 | AD9: 3040.978 | AE9: 3043.7449 | AF9: 3060.2127 | AG9: 3081.7403 | AH9: 3092.8387 | AI9: 3099.5705 | AJ9: 3096.0218 | AK9: 2993.6474 | AL9: 2662.4523 | AM9: 2970.8374 | AN9: 2980.3075 | AO9: 3003.7649 | AP9: 3068.6383 | AQ9: 3123.6013 | AR9: 3148.1916 | AS9: 3170.8437 | AT9: 3200.4374 | AU9: 3215.2694 | AV9: 3213.848 | AW9: 3211.9732 | AX9: 3218.4514 | AY9: 3217.1067 | AZ9: 3218.6997 | BA9: 3227.6652 | BB9: 3234.1493 | BC9: 3247.2933 | BD9: 3260.2848 | BE9: 3278.566 | BF9: 3282.4749 | BG9: 3280.7244 | BH9: 3282.9229 | BI9: 3295.4005 | BJ9: 3311.4041 | BK9: 3327.4565 | BL9: 3340.1037 | BM9: 3312.3214 | BN9: 3340.5882 | BO9: 3374.8542 | BP9: 3398.2805
A10: Germany | B10: =$A$2 -> IMF.RES.GAS:GAS_LIVE_2026_JAN_GAS1_VINTAGE | C10: DEU.NGDP_R.Q | E10: 803.57 | F10: 804.43 | G10: 806.07 | H10: 803.65 | I10: 799.21 | J10: 808.53 | K10: 812.67 | L10: 813.87 | M10: 822.37 | N10: 822.2 | O10: 826.77 | P10: 833.07 | Q10: 831.26 | R10: 835.57 | S10: 840.06 | T10: 844.37 | U10: 851.79 | V10: 853.69 | W10: 856.71 | X10: 860.67 | Y10: 871.85 | Z10: 878.06 | AA10: 885.05 | AB10: 894.02 | AC10: 889.08 | AD10: 896.07 | AE10: 890.2 | AF10: 894.17 | AG10: 900.03 | AH10: 900.55 | AI10: 904 | AJ10: 900.98 | AK10: 882.69 | AL10: 804.36 | AM10: 874.15 | AN10: 882.61 | AO10: 877.17 | AP10: 897.79 | AQ10: 898.57 | AR10: 903.4 | AS10: 909.52 | AT10: 910.9 | AU10: 913.58 | AV10: 910.39 | AW10: 906.09 | AX10: 905.4 | AY10: 905.4 | AZ10: 902.9 | BA10: 901.93 | BB10: 899.6 | BC10: 899.78 | BD10: 901.41 | BE10: 904.18 | BF10: 901.67 | BG10: 902.92678 | BH10: 904.33093 | BI10: 906.05217 | BJ10: 908.18124 | BK10: 910.60851 | BL10: 913.34411 | BM10: 907.92822 | BN10: 914.73949 | BO10: 918.35559 | BP10: 922.44713
A11: France | B11: =$A$2 -> IMF.RES.GAS:GAS_LIVE_2026_JAN_GAS1_VINTAGE | C11: FRA.NGDP_R.Q | E11: 570.803 | F11: 568.561 | G11: 570.275 | H11: 570.214 | I11: 571.282 | J11: 576.301 | K11: 574.93 | L11: 578.438 | M11: 578.458 | N11: 579.909 | O11: 583.604 | P11: 582.011 | Q11: 585.375 | R11: 585.786 | S11: 587.286 | T11: 588.718 | U11: 590.553 | V11: 589.52 | W11: 590.302 | X11: 594.035 | Y11: 598.014 | Z11: 602.59 | AA11: 606.887 | AB11: 610.543 | AC11: 610.307 | AD11: 611.92 | AE11: 614.846 | AF11: 619.487 | AG11: 625.191 | AH11: 628.634 | AI11: 628.582 | AJ11: 625.508 | AK11: 593.757 | AL11: 521.351 | AM11: 601.406 | AN11: 600.715 | AO11: 603.162 | AP11: 610.51 | AQ11: 628.722 | AR11: 632.259 | AS11: 631.696 | AT11: 634.423 | AU11: 637.7 | AV11: 640.147 | AW11: 640.545 | AX11: 646.222 | AY11: 647.783 | AZ11: 650.61 | BA11: 651.405 | BB11: 652.617 | BC11: 655.015 | BD11: 654.621 | BE11: 655.373 | BF11: 657.57 | BG11: 658.46719 | BH11: 659.70854 | BI11: 661.01927 | BJ11: 662.94135 | BK11: 664.63913 | BL11: 666.49222 | BM11: 666.71419 | BN11: 668.35657 | BO11: 670.86892 | BP11: 673.34565
A12: Italy | B12: =$A$2 -> IMF.RES.GAS:GAS_LIVE_2026_JAN_GAS1_VINTAGE | C12: ITA.NGDP_R.Q | E12: 449.162 | F12: 445.757 | G12: 442.682 | H12: 439.553 | I12: 435.578 | J12: 435.555 | K12: 436.971 | L12: 436.608 | M12: 436.416 | N12: 436.627 | O12: 436.722 | P12: 436.269 | Q12: 437.801 | R12: 439.526 | S12: 439.695 | T12: 442.027 | U12: 442.808 | V12: 444.022 | W12: 447.174 | X12: 448.867 | Y12: 450.875 | Z12: 452.625 | AA12: 453.397 | AB12: 456.102 | AC12: 455.296 | AD12: 456.236 | AE12: 456.218 | AF12: 457.576 | AG12: 458.562 | AH12: 459.828 | AI12: 458.126 | AJ12: 456.423 | AK12: 429.875 | AL12: 376.881 | AM12: 431.182 | AN12: 430.917 | AO12: 438.548 | AP12: 449.303 | AQ12: 460.468 | AR12: 467.533 | AS12: 470.949 | AT12: 477.841 | AU12: 479.065 | AV12: 478.331 | AW12: 480.508 | AX12: 479.729 | AY12: 480.336 | AZ12: 481.133 | BA12: 481.897 | BB12: 482.933 | BC12: 482.951 | BD12: 483.91 | BE12: 485.416 | BF12: 485.046 | BG12: 485.9652 | BH12: 488.57249 | BI12: 488.76282 | BJ12: 490.13328 | BK12: 491.66824 | BL12: 489.19258 | BM12: 492.13271 | BN12: 495.27391 | BO12: 497.4382 | BP12: 489.81346
A13: Spain | B13: =$A$2 -> IMF.RES.GAS:GAS_LIVE_2026_JAN_GAS1_VINTAGE | C13: ESP.NGDP_R.Q | E13: 278.55084 | F13: 275.85089 | G13: 274.58419 | H13: 272.30742 | I13: 271.55903 | J13: 271.2804 | K13: 271.10932 | L13: 271.62509 | M13: 272.65183 | N13: 274.12432 | O13: 276.31613 | P13: 278.98756 | Q13: 282.38396 | R13: 285.54604 | S13: 288.16497 | T13: 290.73845 | U13: 292.75861 | V13: 293.72691 | W13: 296.04886 | X13: 297.73139 | Y13: 299.83935 | Z13: 302.97461 | AA13: 304.88863 | AB13: 306.74449 | AC13: 308.05635 | AD13: 310.06494 | AE13: 311.79603 | AF13: 313.62084 | AG13: 315.54361 | AH13: 316.45347 | AI13: 317.05986 | AJ13: 318.86914 | AK13: 302.36003 | AL13: 248.56908 | AM13: 288.09721 | AN13: 290.18767 | AO13: 293.67497 | AP13: 297.7009 | AQ13: 303.56914 | AR13: 309.73606 | AS13: 314.60438 | AT13: 319.95658 | AU13: 322.56675 | AV13: 324.29558 | AW13: 325.94988 | AX13: 326.41935 | AY13: 328.99735 | AZ13: 331.59115 | BA13: 335.2817 | BB13: 338.36305 | BC13: 340.95177 | BD13: 343.72625 | BE13: 345.91467 | BF13: 348.69479 | BG13: 350.80107 | BH13: 352.41008 | BI13: 353.83064 | BJ13: 355.42306 | BK13: 357.26853 | BL13: 358.66136 | BM13: 361.92777 | BN13: 362.28115 | BO13: 363.85522 | BP13: 365.02353
A14: Japan | B14: =$A$2 -> IMF.RES.GAS:GAS_LIVE_2026_JAN_GAS1_VINTAGE | C14: JPN.NGDP_R.Q | E14: 522781.1 | F14: 517866.4 | G14: 515836.5 | H14: 515391.7 | I14: 522631.9 | J14: 527382.9 | K14: 532360.6 | L14: 531674.2 | M14: 536079.8 | N14: 526459.3 | O14: 526816.9 | P14: 529228.1 | Q14: 537485.1 | R14: 538298.2 | S14: 538760.8 | T14: 537827.9 | U14: 541992.2 | V14: 541063.1 | W14: 542162.7 | X14: 542875.8 | Y14: 547149.2 | Z14: 549313.6 | AA14: 554075 | AB14: 554361.2 | AC14: 554797.9 | AD14: 556986.7 | AE14: 554216.5 | AF14: 552790.9 | AG14: 554140.6 | AH14: 556645.5 | AI14: 557714.9 | AJ14: 541536 | AK14: 544380.8 | AL14: 502967.4 | AM14: 530361.8 | AN14: 539394.9 | AO14: 540760.2 | AP14: 544268.2 | AQ14: 542375.9 | AR14: 548424.1 | AS14: 545878.2 | AT14: 550864.7 | AU14: 549094 | AV14: 550266.9 | AW14: 557450.2 | AX14: 558556.9 | AY14: 554032 | AZ14: 553403.6 | BA14: 552190.6 | BB14: 554839.2 | BC14: 558007.6 | BD14: 560846.8 | BE14: 561265.3 | BF14: 564278.8 | BG14: 562238.12 | BH14: 561833.34 | BI14: 563855.21 | BJ14: 565160.28 | BK14: 566928.21 | BL14: 567903.27 | BM14: 566457.07 | BN14: 566043.14 | BO14: 571657.42 | BP14: 574038.78
A15: United Kingdom | B15: =$A$2 -> IMF.RES.GAS:GAS_LIVE_2026_JAN_GAS1_VINTAGE | C15: GBR.NGDP_R.Q | E15: 532.3 | F15: 531.663 | G15: 536.72 | H15: 536.188 | I15: 537.974 | J15: 541.586 | K15: 546.064 | L15: 549.709 | M15: 554.183 | N15: 559.331 | O15: 563.694 | P15: 567.619 | Q15: 569.15 | R15: 572.673 | S15: 574.836 | T15: 578.068 | U15: 580.11 | V15: 583.383 | W15: 585.856 | X15: 589.476 | Y15: 594.423 | Z15: 598.176 | AA15: 601.961 | AB15: 606.396 | AC15: 606.785 | AD15: 607.775 | AE15: 609.653 | AF15: 610.481 | AG15: 614.936 | AH15: 616.853 | AI15: 621.227 | AJ15: 621.229 | AK15: 604.719 | AL15: 481.769 | AM15: 562.648 | AN15: 570.338 | AO15: 564.411 | AP15: 605.353 | AQ15: 615.459 | AR15: 624.592 | AS15: 629.149 | AT15: 631.258 | AU15: 631.977 | AV15: 634.044 | AW15: 634.428 | AX15: 634.694 | AY15: 634.327 | AZ15: 633.011 | BA15: 638.746 | BB15: 641.67 | BC15: 641.675 | BD15: 642.287 | BE15: 647.018 | BF15: 649.249 | BG15: 650.45062 | BH15: 651.20615 | BI15: 655.14608 | BJ15: 656.64379 | BK15: 658.74669 | BL15: 660.21197 | BM15: 663.37628 | BN15: 664.1228 | BO15: 667.14858 | BP15: 669.34234
A16: Canada | B16: =$A$2 -> IMF.RES.GAS:GAS_LIVE_2026_JAN_GAS1_VINTAGE | C16: CAN.NGDP_R.Q | E16: 1933.731 | F16: 1940.017 | G16: 1942.672 | H16: 1946.67 | I16: 1964.095 | J16: 1975.406 | K16: 1991.65 | L16: 2012.494 | M16: 2015.895 | N16: 2034.271 | O16: 2053.771 | P16: 2067.966 | Q16: 2056.452 | R16: 2050.838 | S16: 2058.182 | T16: 2059.546 | U16: 2071.732 | V16: 2061.412 | W16: 2082.805 | X16: 2094.49 | Y16: 2120.843 | Z16: 2143.166 | AA16: 2143.839 | AB16: 2154.716 | AC16: 2179.765 | AD16: 2196.768 | AE16: 2207.849 | AF16: 2213.05 | AG16: 2218.376 | AH16: 2242.662 | AI16: 2248.933 | AJ16: 2255.354 | AK16: 2211.376 | AL16: 1968.126 | AM16: 2146.901 | AN16: 2187.228 | AO16: 2224.489 | AP16: 2221.882 | AQ16: 2266.642 | AR16: 2307.224 | AS16: 2326.901 | AT16: 2348.717 | AU16: 2362.933 | AV16: 2359.547 | AW16: 2382.355 | AX16: 2387.28 | AY16: 2383.979 | AZ16: 2388.157 | BA16: 2400.862 | BB16: 2416.022 | BC16: 2430.425 | BD16: 2442.817 | BE16: 2455.138 | BF16: 2445.368 | BG16: 2446.4505 | BH16: 2454.8587 | BI16: 2466.5305 | BJ16: 2480.4517 | BK16: 2494.9386 | BL16: 2510.9433 | BM16: 2477.9759 | BN16: 2516.0387 | BO16: 2544.3877 | BP16: 2568.3092
A17: Newly Industrialized Asian economies
A19: GDP deflator
A20: United States | B20: =$A$2 -> IMF.RES.GAS:GAS_LIVE_2026_JAN_GAS1_VINTAGE | C20: USA.NGDP_D.Q | E20: 92.524904 | F20: 92.906647 | G20: 93.416029 | H20: 93.885042 | I20: 94.257859 | J20: 94.460663 | K20: 94.923434 | L20: 95.425758 | M20: 95.787568 | N20: 96.330124 | O20: 96.725684 | P20: 96.822162 | Q20: 96.769096 | R20: 97.325127 | S20: 97.582912 | T20: 97.580483 | U20: 97.496014 | V20: 98.158708 | W20: 98.409722 | X20: 98.886264 | Y20: 99.390668 | Z20: 99.649867 | AA20: 100.16174 | AB20: 100.77808 | AC20: 101.41937 | AD20: 102.13593 | AE20: 102.57691 | AF20: 103.01898 | AG20: 103.32818 | AH20: 103.8617 | AI20: 104.19271 | AJ20: 104.51647 | AK20: 105.03158 | AL20: 104.61422 | AM20: 105.5718 | AN20: 106.22983 | AO20: 107.58274 | AP20: 109.25801 | AQ20: 110.93821 | AR20: 112.84705 | AS20: 115.12627 | AT20: 117.72796 | AU20: 119.0309 | AV20: 120.16402 | AW20: 121.28737 | AX20: 121.9198 | AY20: 122.91406 | AZ20: 123.4043 | BA20: 124.3743 | BB20: 125.16694 | BC20: 125.69617 | BD20: 126.4503 | BE20: 127.57705 | BF20: 128.24744 | BG20: 128.67234 | BH20: 129.3971 | BI20: 130.00031 | BJ20: 130.5184 | BK20: 131.04611 | BL20: 131.57578 | BM20: 132.46959 | BN20: 132.82956 | BO20: 133.46367 | BP20: 133.79114
A21: Euro Area | B21: =$A$2 -> IMF.RES.GAS:GAS_LIVE_2026_JAN_GAS1_VINTAGE | C21: G163.NGDP_D.Q | E21: 89.538253 | F21: 89.77541 | G21: 90.153928 | H21: 90.323906 | I21: 90.834618 | J21: 91.04653 | K21: 91.162412 | L21: 91.223585 | M21: 91.64164 | N21: 91.830204 | O21: 91.984791 | P21: 92.246987 | Q21: 92.712788 | R21: 93.107815 | S21: 93.432859 | T21: 93.55146 | U21: 93.791767 | V21: 93.949981 | W21: 94.187043 | X21: 94.267482 | Y21: 94.636892 | Z21: 95.030488 | AA21: 95.240832 | AB21: 95.589363 | AC21: 96.022339 | AD21: 96.275284 | AE21: 96.772111 | AF21: 97.239162 | AG21: 97.576584 | AH21: 97.916603 | AI21: 98.401014 | AJ21: 98.980782 | AK21: 99.44259 | AL21: 100.61621 | AM21: 99.617892 | AN21: 100.39031 | AO21: 100.8992 | AP21: 101.2584 | AQ21: 102.49625 | AR21: 103.66455 | AS21: 105.19807 | AT21: 106.53888 | AU21: 107.87917 | AV21: 110.00803 | AW21: 112.16033 | AX21: 113.42052 | AY21: 114.266 | AZ21: 115.44454 | BA21: 116.20087 | BB21: 116.78978 | BC21: 117.43567 | BD21: 118.36341 | BE21: 118.84658 | BF21: 119.70532 | BG21: 119.78391 | BH21: 120.54667 | BI21: 121.27609 | BJ21: 122.24651 | BK21: 122.20298 | BL21: 122.60803 | BM21: 123.75527 | BN21: 124.84164 | BO21: 124.6709 | BP21: 124.70464
A22: Germany | B22: =$A$2 -> IMF.RES.GAS:GAS_LIVE_2026_JAN_GAS1_VINTAGE | C22: DEU.NGDP_D.Q | E22: 87.278296 | F22: 86.520723 | G22: 86.831279 | H22: 87.437067 | I22: 88.077949 | J22: 88.659758 | K22: 88.886838 | L22: 88.923827 | M22: 89.78858 | N22: 90.193167 | O22: 90.606291 | P22: 90.69797 | Q22: 91.359984 | R22: 91.776043 | S22: 92.428346 | T22: 92.876989 | U22: 92.285553 | V22: 94.192622 | W22: 93.418788 | X22: 93.473986 | Y22: 94.466201 | Z22: 94.319246 | AA22: 94.633646 | AB22: 94.288413 | AC22: 95.55246 | AD22: 96.216818 | AE22: 96.246433 | AF22: 96.72855 | AG22: 97.436818 | AH22: 97.929121 | AI22: 98.709898 | AJ22: 98.326508 | AK22: 100.14118 | AL22: 100.72806 | AM22: 99.701988 | AN22: 100.15291 | AO22: 101.40697 | AP22: 101.69401 | AQ22: 103.87097 | AR22: 104.77546 | AS22: 107.12266 | AT22: 109.09305 | AU22: 109.90587 | AV22: 111.80651 | AW22: 115.20731 | AX22: 115.87424 | AY22: 116.86831 | AZ22: 118.38269 | BA22: 118.75481 | BB22: 120.13968 | BC22: 120.72149 | BD22: 121.0689 | BE22: 121.32138 | BF22: 123.03518 | BG22: 123.80681 | BH22: 123.22349 | BI22: 124.04837 | BJ22: 125.12814 | BK22: 126.41974 | BL22: 126.32079 | BM22: 126.83665 | BN22: 127.25671 | BO22: 129.08781 | BP22: 129.49595
A23: France | B23: =$A$2 -> IMF.RES.GAS:GAS_LIVE_2026_JAN_GAS1_VINTAGE | C23: FRA.NGDP_D.Q | E23: 91.179969 | F23: 91.552885 | G23: 91.816229 | H23: 91.807813 | I23: 92.263891 | J23: 92.400673 | K23: 92.288279 | L23: 92.123961 | M23: 92.503691 | N23: 92.690232 | O23: 92.825615 | P23: 93.146178 | Q23: 93.424215 | R23: 93.690358 | S23: 94.056899 | T23: 94.217605 | U23: 94.366975 | V23: 94.241586 | W23: 94.373897 | X23: 94.386189 | Y23: 94.646446 | Z23: 94.879105 | AA23: 94.911079 | AB23: 95.08847 | AC23: 95.527825 | AD23: 95.643058 | AE23: 96.207018 | AF23: 96.392176 | AG23: 96.659421 | AH23: 96.954985 | AI23: 97.257637 | AJ23: 97.537681 | AK23: 98.857108 | AL23: 102.2739 | AM23: 99.118898 | AN23: 100.04894 | AO23: 100.62902 | AP23: 101.09728 | AQ23: 101.35306 | AR23: 101.77459 | AS23: 102.70621 | AT23: 103.27573 | AU23: 104.76886 | AV23: 106.33558 | AW23: 107.91982 | AX23: 109.38284 | AY23: 109.83138 | AZ23: 110.75744 | BA23: 111.20762 | BB23: 111.12153 | BC23: 112.35773 | BD23: 112.37602 | BE23: 112.85207 | BF23: 113.06781 | BG23: 113.14696 | BH23: 113.35271 | BI23: 113.95348 | BJ23: 114.55743 | BK23: 115.16459 | BL23: 115.65742 | BM23: 115.06563 | BN23: 116.06668 | BO23: 117.21819 | BP23: 118.00899
A24: Italy | B24: =$A$2 -> IMF.RES.GAS:GAS_LIVE_2026_JAN_GAS1_VINTAGE | C24: ITA.NGDP_D.Q | E24: 91.589671 | F24: 91.702205 | G24: 92.111267 | H24: 92.328343 | I24: 92.284275 | J24: 93.024073 | K24: 93.17552 | L24: 93.375751 | M24: 93.573334 | N24: 93.745691 | O24: 93.732626 | P24: 94.16736 | Q24: 94.285303 | R24: 94.496799 | S24: 94.783884 | T24: 94.589245 | U24: 95.658615 | V24: 95.636928 | W24: 95.772786 | X24: 95.810786 | Y24: 95.964513 | Z24: 96.313284 | AA24: 96.400506 | AB24: 96.902886 | AC24: 97.367647 | AD24: 97.352686 | AE24: 97.441136 | AF24: 97.554068 | AG24: 97.902574 | AH24: 98.074497 | AI24: 98.661285 | AJ24: 99.161085 | AK24: 98.973655 | AL24: 100.43223 | AM24: 100.06934 | AN24: 100.57645 | AO24: 100.29757 | AP24: 101.07233 | AQ24: 101.72607 | AR24: 101.97975 | AS24: 103.10543 | AT24: 104.46069 | AU24: 104.79079 | AV24: 106.7447 | AW24: 109.34761 | AX24: 111.10877 | AY24: 111.5007 | AZ24: 111.95657 | BA24: 112.82515 | BB24: 112.8991 | BC24: 113.44733 | BD24: 114.12721 | BE24: 114.41877 | BF24: 115.54244 | BG24: 116.2357 | BH24: 116.93311 | BI24: 117.3138 | BJ24: 117.69572 | BK24: 118.07889 | BL24: 118.46331 | BM24: 120.28208 | BN24: 119.88914 | BO24: 119.95132 | BP24: 120.01353
A25: Japan | B25: =$A$2 -> IMF.RES.GAS:GAS_LIVE_2026_JAN_GAS1_VINTAGE | C25: JPN.NGDP_D.Q | E25: 97.070265 | F25: 96.584389 | G25: 96.460972 | H25: 96.476136 | I25: 96.233525 | J25: 96.240208 | K25: 96.342592 | L25: 96.388879 | M25: 96.367742 | N25: 98.382002 | O25: 98.376058 | P25: 98.652169 | Q25: 99.486907 | R25: 99.98055 | S25: 100.21182 | T25: 100.27486 | U25: 100.61077 | V25: 100.4257 | W25: 100.26145 | X25: 100.30711 | Y25: 100.10257 | Z25: 100.22725 | AA25: 100.54888 | AB25: 100.43975 | AC25: 100.65804 | AD25: 100.33949 | AE25: 100.21122 | AF25: 100.12699 | AG25: 100.83916 | AH25: 100.75854 | AI25: 100.6797 | AJ25: 101.60457 | AK25: 101.84114 | AL25: 102.15767 | AM25: 101.89474 | AN25: 101.80563 | AO25: 101.86193 | AP25: 101.76382 | AQ25: 101.71195 | AR25: 101.52707 | AS25: 102.10126 | AT25: 101.69081 | AU25: 101.56596 | AV25: 103.08846 | AW25: 104.46659 | AX25: 106.04078 | AY25: 107.04766 | AZ25: 107.49439 | BA25: 107.74117 | BB25: 109.32777 | BC25: 109.69186 | BD25: 110.48046 | BE25: 111.37989 | BF25: 112.55716 | BG25: 112.45689 | BH25: 113.14115 | BI25: 113.91158 | BJ25: 114.21446 | BK25: 114.79407 | BL25: 115.41097 | BM25: 116.50081 | BN25: 115.89615 | BO25: 117.17983 | BP25: 117.72632
A26: United Kingdom | B26: =$A$2 -> IMF.RES.GAS:GAS_LIVE_2026_JAN_GAS1_VINTAGE | C26: GBR.NGDP_D.Q | E26: 79.755777 | F26: 79.926382 | G26: 80.295871 | H26: 80.805986 | I26: 81.469179 | J26: 81.629695 | K26: 82.188168 | L26: 82.258613 | M26: 82.586979 | N26: 82.518044 | O26: 83.489269 | P26: 83.270292 | Q26: 83.401564 | R26: 83.222188 | S26: 83.488856 | T26: 83.944449 | U26: 84.412094 | V26: 84.628794 | W26: 85.481927 | X26: 86.085099 | Y26: 86.439118 | Z26: 86.539079 | AA26: 86.593151 | AB26: 87.361229 | AC26: 87.531992 | AD26: 88.142322 | AE26: 88.608602 | AF26: 89.316621 | AG26: 89.28734 | AH26: 90.151787 | AI26: 90.626937 | AJ26: 91.070765 | AK26: 91.925506 | AL26: 98.835749 | AM26: 94.873882 | AN26: 94.26498 | AO26: 95.319191 | AP26: 93.915616 | AQ26: 94.531886 | AR26: 95.595525 | AS26: 97.01136 | AT26: 99.082625 | AU26: 100.72408 | AV26: 103.15719 | AW26: 104.97093 | AX26: 106.78532 | AY26: 107.79787 | AZ26: 108.0027 | BA26: 109.31231 | BB26: 110.09974 | BC26: 112.06374 | BD26: 113.22026 | BE26: 114.08632 | BF26: 114.5656 | BG26: 115.75345 | BH26: 116.04751 | BI26: 116.98783 | BJ26: 117.48691 | BK26: 118.29428 | BL26: 118.39806 | BM26: 119.96314 | BN26: 120.48271 | BO26: 120.89089 | BP26: 120.79621
A27: Canada | B27: =$A$2 -> IMF.RES.GAS:GAS_LIVE_2026_JAN_GAS1_VINTAGE | C27: CAN.NGDP_D.Q | E27: 93.86621 | F27: 93.76124 | G27: 94.232892 | H27: 94.729153 | I27: 95.5577 | J27: 95.504013 | K27: 96.022293 | L27: 96.056137 | M27: 97.398525 | N27: 97.745286 | O27: 98.053386 | P27: 97.387675 | Q27: 96.491433 | R27: 96.785802 | S27: 97.215115 | T27: 96.704808 | U27: 96.461318 | V27: 97.125271 | W27: 97.724943 | X27: 98.64683 | Y27: 99.391987 | Z27: 99.386608 | AA27: 99.902651 | AB27: 101.30542 | AC27: 101.25257 | AD27: 101.97108 | AE27: 102.31461 | AF27: 101.06468 | AG27: 102.27806 | AH27: 103.12209 | AI27: 103.27013 | AJ27: 104.20466 | AK27: 103.46572 | AL27: 102.42901 | AM27: 104.63845 | AN27: 106.60416 | AO27: 109.30097 | AP27: 111.97786 | AQ27: 113.08817 | AR27: 115.31451 | AS27: 119.26197 | AT27: 123.05374 | AU27: 121.5442 | AV27: 121.48349 | AW27: 121.02042 | AX27: 121.66231 | AY27: 123.79169 | AZ27: 125.474 | BA27: 125.15038 | BB27: 126.45795 | BC27: 127.25297 | BD27: 128.40323 | BE27: 129.32259 | BF27: 129.33105 | BG27: 129.82731 | BH27: 130.97149 | BI27: 131.83827 | BJ27: 132.73126 | BK27: 133.24778 | BL27: 134.27047 | BM27: 134.40288 | BN27: 136.22087 | BO27: 136.75837 | BP27: 137.65255
A29: Trade prices (export price deflator)
A30: Manufactures -- advanced economies | B30: IMF.RES.GAS:GAS_LIVE | C30: G110.TXGM_D.Q | E30: 120.03021 | F30: 120.45004 | G30: 120.33303 | H30: 119.66854 | I30: 118.06417 | J30: 116.92465 | K30: 116.01368 | L30: 115.53901 | M30: 115.87867 | N30: 116.07994 | O30: 116.18506 | P30: 115.87508 | Q30: 114.92316 | R30: 113.46394 | S30: 111.66907 | T30: 109.85677 | U30: 107.9273 | V30: 106.85193 | W30: 106.26914 | X30: 106.09643 | Y30: 106.42513 | Z30: 106.69721 | AA30: 107.07538 | AB30: 107.54724 | AC30: 108.22604 | AD30: 108.85412 | AE30: 109.46234 | AF30: 109.92085 | AG30: 110.26688 | AH30: 110.03485 | AI30: 109.3855 | AJ30: 108.42053 | AK30: 106.65152 | AL30: 105.84715 | AM30: 105.65894 | AN30: 106.40312 | AO30: 108.46421 | AP30: 111.31999 | AQ30: 114.85982 | AR30: 118.54461 | AS30: 122.77399 | AT30: 125.01389 | AU30: 126.02441 | AV30: 125.89356 | AW30: 123.96072 | AX30: 122.88815 | AY30: 122.14034 | AZ30: 122.02144 | BA30: 122.9379 | BB30: 123.83525 | BC30: 124.74218 | BD30: 125.34257 | BE30: 125.41207 | BF30: 125.22356 | BG30: 124.91079 | BH30: 124.71045 | BI30: 124.77594 | BJ30: 125.01134 | BK30: 125.28656 | BL30: 125.42511 | BM30: 125.25583 | BN30: 124.99864 | BO30: 124.73287 | BP30: 124.64078 | BQ30: 124.86865 | BR30: 125.29486 | BS30: 125.8203 | BT30: 126.27298
A32: Commodity price indices (except otherwise indicated)
A33: All Commodity | B33: IMF.RES.GAS:GAS_LIVE | C33: G001.PZPIW.Q | E33: 181.14527 | F33: 171.19786 | G33: 169.51642 | H33: 168.83725 | I33: 170.84336 | J33: 164.57403 | K33: 165.55191 | L33: 163.22204 | M33: 166.64347 | N33: 168.83417 | O33: 159.68558 | P33: 137.23829 | Q33: 114.84102 | R33: 116.13376 | S33: 104.51828 | T33: 96.204646 | U33: 88.608385 | V33: 100.42844 | W33: 103.0411 | X33: 107.92207 | Y33: 114.28626 | Z33: 108.56009 | AA33: 111.11139 | AB33: 119.3449 | AC33: 126.96418 | AD33: 130.85981 | AE33: 129.68508 | AF33: 123.39229 | AG33: 118.38246 | AH33: 119.09151 | AI33: 114.49437 | AJ33: 116.12151 | AK33: 107.38361 | AL33: 92.218 | AM33: 106.62546 | AN33: 117.22979 | AO33: 138.65061 | AP33: 153.72815 | AQ33: 166.53283 | AR33: 187.09889 | AS33: 211.87047 | AT33: 228.74345 | AU33: 230.47578 | AV33: 192.57855 | AW33: 175.16617 | AX33: 160.65113 | AY33: 162.59512 | AZ33: 164.18059 | BA33: 160.3445 | BB33: 168.6069 | BC33: 163.85906 | BD33: 166.46059 | BE33: 170.72407 | BF33: 163.05038 | BG33: 165.14633 | BH33: 168.79878 | BI33: 179.92766 | BJ33: 181.47937 | BK33: 180.73817 | BL33: 180.61639 | BM33: 181.63023 | BN33: 179.4904 | BO33: 179.27896 | BP33: 180.22228
A34: Fuel | B34: IMF.RES.GAS:GAS_LIVE | C34: G001.PZPINRGW.Q | E34: 242.8439 | F34: 225.08664 | G34: 223.085 | H34: 221.46836 | I34: 227.32101 | J34: 218.75754 | K34: 229.53352 | L34: 227.90751 | M34: 229.46451 | N34: 230.69254 | O34: 216.90771 | P34: 172.21802 | Q34: 127.99715 | R34: 134.0564 | S34: 113.73049 | T34: 100.14445 | U34: 81.029943 | V34: 100.24013 | W34: 103.26084 | X34: 115.46909 | Y34: 123.07229 | Z34: 113.86479 | AA34: 118.15622 | AB34: 138.1095 | AC34: 149.10555 | AD34: 159.27654 | AE34: 166.749 | AF34: 151.00793 | AG34: 135.05368 | AH34: 134.13927 | AI34: 121.76935 | AJ34: 126.17762 | AK34: 102.80853 | AL34: 68.766525 | AM34: 90.313763 | AN34: 104.93075 | AO34: 139.41591 | AP34: 156.21544 | AQ34: 192.6785 | AR34: 244.04504 | AS34: 277.7365 | AT34: 311.77721 | AU34: 350.12389 | AV34: 258.40674 | AW34: 203.67138 | AX34: 175.80579 | AY34: 189.25055 | AZ34: 189.29235 | BA34: 175.57064 | BB34: 185.81748 | BC34: 179.36104 | BD34: 177.2656 | BE34: 181.50722 | BF34: 160.24527 | BG34: 160.39838 | BH34: 150.39757 | BI34: 157.76916 | BJ34: 156.44936 | BK34: 155.17385 | BL34: 155.09821 | BM34: 154.71809 | BN34: 148.00997 | BO34: 148.62901 | BP34: 150.90831
A35: Petroleum spot price (APSP; US$) | B35: IMF.RES.GAS:GAS_LIVE | C35: G001.PZPIOIL.Q | E35: 112.41666 | F35: 103.00314 | G35: 102.99068 | H35: 101.97598 | I35: 105.20577 | J35: 99.367262 | K35: 107.44797 | L35: 104.66626 | M35: 103.80442 | N35: 106.44512 | O35: 100.46671 | P35: 74.588258 | Q35: 51.848596 | R35: 60.516114 | S35: 49.019454 | T35: 42.263526 | U35: 33.138265 | V35: 45.288668 | W35: 45.107305 | X35: 49.52119 | Y35: 53.191376 | Z35: 49.663256 | AA35: 50.343225 | AB35: 58.712722 | AC35: 64.743638 | AD35: 71.646128 | AE35: 73.302796 | AF35: 64.437561 | AG35: 60.702674 | AH35: 64.98577 | AI35: 59.739889 | AJ35: 60.301003 | AK35: 49.096132 | AL35: 31.451852 | AM35: 42.312499 | AN35: 44.201508 | AO35: 59.648475 | AP35: 67.35089 | AQ35: 71.707374 | AR35: 78.293174 | AS35: 95.353101 | AT35: 109.42357 | AU35: 95.474348 | AV35: 85.197222 | AW35: 79.560982 | AX35: 76.476929 | AY35: 84.926467 | AZ35: 81.415253 | BA35: 80.851638 | BB35: 84.423473 | BC35: 78.249595 | BD35: 73.158495 | BE35: 74.517561 | BF35: 66.296647 | BG35: 67.998835 | BH35: 62.134092 | BI35: 65.467436 | BJ35: 65.632106 | BK35: 64.360508 | BL35: 63.513439 | BM35: 63.001375 | BN35: 62.857268 | BO35: 62.866186 | BP35: 62.984757
A36: Natural gas | B36: IMF.RES.GAS:GAS_LIVE | C36: G001.PZPINGASW.Q | E36: 205.11234 | F36: 211.54948 | G36: 208.83975 | H36: 210.43333 | I36: 212.83817 | J36: 218.31395 | K36: 206.60483 | L36: 210.42508 | M36: 224.40682 | N36: 220.28925 | O36: 202.40896 | P36: 201.34548 | Q36: 172.98703 | R36: 135.18634 | S36: 130.35284 | T36: 119.01369 | U36: 98.199632 | V36: 90.752543 | W36: 101.41468 | X36: 109.63314 | Y36: 117.30493 | Z36: 104.8572 | AA36: 109.3018 | AB36: 132.07446 | AC36: 141.52086 | AD36: 132.8416 | AE36: 149.13802 | AF36: 154.82683 | AG36: 114.13851 | AH36: 87.050406 | AI36: 76.341962 | AJ36: 88.572449 | AK36: 65.048036 | AL36: 45.479157 | AM36: 64.224897 | AN36: 112.10468 | AO36: 136.69349 | AP36: 151.43635 | AQ36: 265.88276 | AR36: 460.68374 | AS36: 445.59039 | AT36: 453.80333 | AU36: 762.35354 | AV36: 424.56681 | AW36: 239.76338 | AX36: 164.89469 | AY36: 169.29397 | AZ36: 201.48212 | BA36: 135.54182 | BB36: 156.56951 | BC36: 173.66423 | BD36: 203.95126 | BE36: 223.71651 | BF36: 190.55182 | BG36: 177.86444 | BH36: 179.2269 | BI36: 178.33355 | BJ36: 171.58421 | BK36: 175.38663 | BL36: 181.88553 | BM36: 184.0272 | BN36: 150.52586 | BO36: 152.89809 | BP36: 161.43272
A37: Coal | B37: IMF.RES.GAS:GAS_LIVE | C37: G001.PZPICLW.Q | E37: 167.57347 | F37: 145.43636 | G37: 134.00529 | H37: 130.98505 | I37: 135.79715 | J37: 128.02544 | K37: 115.58627 | L37: 127.19707 | M37: 120.43406 | N37: 114.14747 | O37: 106.64203 | P37: 99.37082 | Q37: 96.084995 | R37: 92.728663 | S37: 87.193528 | T37: 80.172817 | U37: 79.196418 | V37: 81.869332 | W37: 101.18721 | X37: 137.74704 | Y37: 126.73339 | Z37: 119.8138 | AA37: 138.40422 | AB37: 146.00437 | AC37: 151.36715 | AD37: 156.56725 | AE37: 166.96863 | AF37: 152.26231 | AG37: 136.35597 | AH37: 111.99523 | AI37: 98.605194 | AJ37: 108.86301 | AK37: 111.69043 | AL37: 83.195327 | AM37: 79.886997 | AN37: 104.61115 | AO37: 136.7959 | AP37: 160.62722 | AQ37: 232.39691 | AR37: 269.93649 | AS37: 388.02049 | AT37: 527.00989 | AU37: 567.31841 | AV37: 455.66913 | AW37: 313.64136 | AX37: 210.35237 | AY37: 196.09792 | AZ37: 191.14164 | BA37: 170.46401 | BB37: 185.3403 | BC37: 190.60199 | BD37: 190.39781 | BE37: 154.10621 | BF37: 144.44369 | BG37: 151.54753 | BH37: 147.51266 | BI37: 167.46995 | BJ37: 162.65316 | BK37: 163.38376 | BL37: 164.02801 | BM37: 164.53584 | BN37: 163.89399 | BO37: 165.94423 | BP37: 172.11737
A38: Propane
A39: Nonfuel | B39: IMF.RES.GAS:GAS_LIVE | C39: G001.PZPINFW.Q | E39: 132.16131 | F39: 128.41432 | G39: 129.98594 | H39: 129.99858 | I39: 129.16616 | J39: 124.58978 | K39: 118.33724 | L39: 115.48796 | M39: 120.28523 | N39: 123.18632 | O39: 117.459 | P39: 111.4253 | Q39: 105.74571 | R39: 103.74319 | S39: 98.149543 | T39: 93.480918 | U39: 93.847636 | V39: 100.55863 | W39: 102.88919 | X39: 102.70454 | Y39: 108.21216 | Z39: 104.89276 | AA39: 106.24105 | AB39: 106.37225 | AC39: 111.65705 | AD39: 111.21429 | AE39: 104.06144 | AF39: 104.3006 | AG39: 106.85704 | AH39: 108.68845 | AI39: 109.46491 | AJ39: 109.16935 | AK39: 110.54653 | AL39: 108.43085 | AM39: 117.90232 | AN39: 125.73256 | AO39: 138.12153 | AP39: 152.00859 | AQ39: 148.45738 | AR39: 147.72996 | AS39: 166.3349 | AT39: 171.33921 | AU39: 147.75871 | AV39: 147.06915 | AW39: 155.4595 | AX39: 150.17416 | AY39: 144.16727 | AZ39: 146.81992 | BA39: 149.81811 | BB39: 156.70861 | BC39: 153.14197 | BD39: 158.99069 | BE39: 163.26929 | BF39: 164.98965 | BG39: 168.42875 | BH39: 181.5202 | BI39: 195.24663 | BJ39: 198.78352 | BK39: 198.41171 | BL39: 198.25804 | BM39: 200.23557 | BN39: 201.56335 | BO39: 200.77447 | BP39: 200.79425
A40: Food | B40: IMF.RES.GAS:GAS_LIVE | C40: G001.PZPIFW.Q | E40: 119.15155 | F40: 117.45989 | G40: 123.57622 | H40: 120.89542 | I40: 121.69744 | J40: 125.0627 | K40: 119.11932 | L40: 115.97952 | M40: 122.2892 | N40: 126.18476 | O40: 115.4001 | P40: 110.55776 | Q40: 101.79566 | R40: 100.60112 | S40: 97.833033 | T40: 93.972154 | U40: 94.271839 | V40: 101.7083 | W40: 102.56313 | X40: 101.45673 | Y40: 105.64111 | Z40: 104.13755 | AA40: 103.22624 | AB40: 102.05009 | AC40: 106.16362 | AD40: 106.40358 | AE40: 99.097788 | AF40: 98.327504 | AG40: 99.124545 | AH40: 99.944002 | AI40: 98.188328 | AJ40: 100.2097 | AK40: 101.27534 | AL40: 96.413059 | AM40: 98.723 | AN40: 107.92975 | AO40: 119.73265 | AP40: 131.76672 | AQ40: 129.80133 | AR40: 132.15801 | AS40: 150.49857 | AT40: 161.49221 | AU40: 140.03082 | AV40: 137.58855 | AW40: 142.40391 | AX40: 140.27353 | AY40: 133.02026 | AZ40: 134.01358 | BA40: 135.21307 | BB40: 135.31333 | BC40: 129.24169 | BD40: 132.78055 | BE40: 132.15977 | BF40: 126.75014 | BG40: 125.50523 | BH40: 123.84439 | BI40: 126.98048 | BJ40: 133.92533 | BK40: 131.37672 | BL40: 129.67509 | BM40: 132.63836 | BN40: 133.60241 | BO40: 130.75409 | BP40: 130.00338
A41: Beverages | B41: IMF.RES.GAS:GAS_LIVE | C41: G001.PZPIBEVW.Q | E41: 111.27697 | F41: 103.85914 | G41: 108.06683 | H41: 101.92771 | I41: 97.566147 | J41: 93.206315 | K41: 90.449409 | L41: 87.944686 | M41: 103.89683 | N41: 113.97999 | O41: 114.1418 | P41: 113.21275 | Q41: 105.50829 | R41: 102.60067 | S41: 103.0716 | T41: 100.9826 | U41: 93.38134 | V41: 97.830305 | W41: 104.00243 | X41: 104.78592 | Y41: 102.06722 | Z41: 95.972163 | AA41: 96.249517 | AB41: 90.53807 | AC41: 89.720745 | AD41: 91.279411 | AE41: 83.45079 | AF41: 84.851651 | AG41: 82.423688 | AH41: 80.662824 | AI41: 81.020514 | AJ41: 85.341227 | AK41: 84.911352 | AL41: 81.170297 | AM41: 85.962295 | AN41: 85.461831 | AO41: 89.004495 | AP41: 93.971053 | AQ41: 108.2616 | AR41: 122.01294 | AS41: 124.15053 | AT41: 119.81044 | AU41: 119.22664 | AV41: 108.47635 | AW41: 112.30988 | AX41: 122.96535 | AY41: 123.70794 | AZ41: 131.5356 | BA41: 161.44855 | BB41: 207.8829 | BC41: 206.07124 | BD41: 230.76864 | BE41: 267.20273 | BF41: 245.92422 | BG41: 217.70982 | BH41: 215.67499 | BI41: 183.31752 | BJ41: 170.9643 | BK41: 168.23483 | BL41: 165.92 | BM41: 164.19378 | BN41: 162.77631 | BO41: 161.44512 | BP41: 160.39104
A42: Agricultural raw materials | B42: IMF.RES.GAS:GAS_LIVE | C42: G001.PZPIRAW.Q | E42: 136.69638 | F42: 131.49743 | G42: 122.01124 | H42: 123.36946 | I42: 125.23646 | J42: 124.95402 | K42: 119.52231 | L42: 119.29315 | M42: 119.29124 | N42: 117.42837 | O42: 109.78593 | P42: 105.10042 | Q42: 104.09474 | R42: 104.66654 | S42: 97.545961 | T42: 94.406891 | U42: 94.569023 | V42: 100.58052 | W42: 101.84791 | X42: 103.00255 | Y42: 109.68414 | Z42: 106.63968 | AA42: 103.00232 | AB42: 102.20801 | AC42: 110.31557 | AD42: 110.1888 | AE42: 106.63199 | AF42: 102.82649 | AG42: 104.5209 | AH42: 105.26022 | AI42: 98.754405 | AJ42: 98.111809 | AK42: 98.870199 | AL42: 91.973478 | AM42: 95.308471 | AN42: 106.61854 | AO42: 112.06542 | AP42: 116.91769 | AQ42: 110.33635 | AR42: 114.20581 | AS42: 125.33964 | AT42: 132.83885 | AU42: 115.9734 | AV42: 105.41971 | AW42: 102.61115 | AX42: 100.77347 | AY42: 101.20746 | AZ42: 100.35358 | BA42: 108.13034 | BB42: 104.9274 | BC42: 104.64533 | BD42: 104.73033 | BE42: 104.70965 | BF42: 104.771 | BG42: 104.27878 | BH42: 100.44242 | BI42: 97.123861 | BJ42: 98.854746 | BK42: 99.72191 | BL42: 100.58986 | BM42: 101.27507 | BN42: 101.4597 | BO42: 101.56644 | BP42: 101.20295
A43: Metals | B43: IMF.RES.GAS:GAS_LIVE | C43: G001.PZPIMETW.Q | E43: 160.21553 | F43: 149.12728 | G43: 143.56007 | H43: 147.30975 | I43: 148.65162 | J43: 134.94337 | K43: 131.09004 | L43: 132.01451 | M43: 131.9759 | N43: 138.97013 | O43: 143.61827 | P43: 132.23173 | Q43: 116.43546 | R43: 113.35143 | S43: 101.19707 | T43: 91.434035 | U43: 90.500302 | V43: 96.636712 | W43: 100.89639 | X43: 111.9666 | Y43: 125.76864 | Z43: 112.80588 | AA43: 123.43509 | AB43: 126.74514 | AC43: 135.56567 | AD43: 134.51856 | AE43: 125.5108 | AF43: 125.55426 | AG43: 131.94421 | AH43: 140.0887 | AI43: 138.60658 | AJ43: 130.64184 | AK43: 126.76468 | AL43: 123.18215 | AM43: 147.01824 | AN43: 163.07507 | AO43: 193.60174 | AP43: 224.86068 | AQ43: 214.14888 | AR43: 189.03887 | AS43: 219.65549 | AT43: 213.26142 | AU43: 171.02276 | AV43: 171.64084 | AW43: 203.83515 | AX43: 184.23023 | AY43: 179.60958 | AZ43: 186.51532 | BA43: 184.56476 | BB43: 192.18493 | BC43: 179.17448 | BD43: 183.87374 | BE43: 184.93137 | BF43: 178.55897 | BG43: 187.19074 | BH43: 204.6207 | BI43: 218.61573 | BJ43: 217.0214 | BK43: 217.28745 | BL43: 217.04998 | BM43: 216.72058 | BN43: 216.78931 | BO43: 216.63311 | BP43: 216.32412
A45: Agriculture | B45: IMF.RES.GAS:GAS_LIVE | C45: G001.PZPIAGRW.Q | E45: 121.02891 | F45: 118.46647 | G45: 122.32061 | H45: 119.92495 | I45: 120.5132 | J45: 122.88366 | K45: 117.22273 | L45: 114.50095 | M45: 120.65311 | N45: 124.22758 | O45: 114.59155 | P45: 110.03536 | Q45: 102.34408 | R45: 101.26059 | S45: 98.152089 | T45: 94.504591 | U45: 94.249592 | V45: 101.2995 | W45: 102.56884 | X45: 101.88207 | Y45: 105.91891 | Z45: 103.90485 | AA45: 102.72325 | AB45: 101.28804 | AC45: 105.58083 | AD45: 105.86319 | AE45: 99.004687 | AF45: 97.991062 | AG45: 98.684494 | AH45: 99.318265 | AI45: 97.094461 | AJ45: 98.929016 | AK45: 99.853445 | AL45: 94.805358 | AM45: 97.416001 | AN45: 106.2339 | AO45: 116.65684 | AP45: 127.28566 | AQ45: 125.83059 | AR45: 129.15651 | AS45: 145.46773 | AT45: 154.96921 | AU45: 135.51862 | AV45: 131.46707 | AW45: 135.23383 | AX45: 134.01011 | AY45: 128.29028 | AZ45: 129.51019 | BA45: 133.50819 | BB45: 136.33202 | BC45: 131.29552 | BD45: 135.82756 | BE45: 137.80241 | BF45: 132.01888 | BG45: 129.038 | BH45: 127.07156 | BI45: 126.96414 | BJ45: 131.92595 | BK45: 129.80495 | BL45: 128.39258 | BM45: 130.74376 | BN45: 131.40393 | BO45: 129.05978 | BP45: 128.34372
A46: Cereal | B46: IMF.RES.GAS:GAS_LIVE | C46: G001.PZPICERW.Q | E46: 166.64047 | F46: 163.77792 | G46: 205.29164 | H46: 202.16197 | I46: 187.54128 | J46: 181.90265 | K46: 163.12545 | L46: 149.37903 | M46: 148.34634 | N46: 155.14471 | O46: 131.70889 | P46: 128.15034 | Q46: 123.68198 | R46: 118.32287 | S46: 112.27763 | T46: 105.73382 | U46: 104.00036 | V46: 108.16912 | W46: 96.048727 | X46: 91.781797 | Y46: 100.31391 | Z46: 102.60235 | AA46: 102.75542 | AB46: 98.254755 | AC46: 111.08228 | AD46: 118.76522 | AE46: 115.74768 | AF46: 113.92704 | AG46: 112.34788 | AH46: 111.27085 | AI46: 107.63331 | AJ46: 108.27379 | AK46: 114.3779 | AL46: 113.19655 | AM46: 116.25284 | AN46: 132.65799 | AO46: 154.9063 | AP46: 170.43817 | AQ46: 163.83143 | AR46: 181.08978 | AS46: 206.56467 | AT46: 233.91647 | AU46: 196.21653 | AV46: 199.75904 | AW46: 191.13541 | AX46: 181.07648 | AY46: 159.14267 | AZ46: 147.46994 | BA46: 144.67223 | BB46: 141.13833 | BC46: 127.15492 | BD46: 129.61543 | BE46: 128.68409 | BF46: 123.52084 | BG46: 112.24646 | BH46: 115.45546 | BI46: 124.88035 | BJ46: 130.33033 | BK46: 133.76813 | BL46: 138.36889 | BM46: 141.53589 | BN46: 144.1143 | BO46: 143.61086 | BP46: 145.21712
A47: Coffee | B47: IMF.RES.GAS:GAS_LIVE | C47: G001.PZPICFW.Q | E47: 124.25476 | F47: 114.55461 | G47: 115.272 | H47: 105.6167 | I47: 104.65824 | J47: 99.12309 | K47: 93.37835 | L47: 85.52433 | M47: 107.26821 | N47: 122.4826 | O47: 120.01383 | P47: 121.44767 | Q47: 108.08066 | R47: 99.806431 | S47: 94.386029 | T47: 91.612069 | U47: 88.104486 | V47: 95.334157 | W47: 105.0139 | X47: 111.54746 | Y47: 110.84026 | Z47: 102.83811 | AA47: 103.4414 | AB47: 94.765052 | AC47: 91.736248 | AD47: 90.580737 | AE47: 83.836808 | AF47: 87.180212 | AG47: 82.70113 | AH47: 78.836616 | AI47: 80.246764 | AJ47: 83.615533 | AK47: 82.176449 | AL47: 81.708066 | AM47: 88.542212 | AN47: 86.869533 | AO47: 91.291654 | AP47: 100.626 | AQ47: 120.97531 | AR47: 139.70283 | AS47: 143.14853 | AT47: 139.82469 | AU47: 141.01917 | AV47: 121.73847 | AW47: 124.66172 | AX47: 136.51755 | AY47: 127.99978 | AZ47: 131.09536 | BA47: 151.09744 | BB47: 183.22719 | BC47: 207.43535 | BD47: 223.13577 | BE47: 262.7841 | BF47: 245.26057 | BG47: 218.55813 | BH47: 238.07888 | BI47: 207.53773 | BJ47: 190.89641 | BK47: 185.56257 | BL47: 180.79939 | BM47: 177.59758 | BN47: 175.36974 | BO47: 173.28542 | BP47: 171.52865
A48: Food and Beverage | B48: IMF.RES.GAS:GAS_LIVE | C48: G001.PZPIFBW.Q | E48: 118.53192 | F48: 116.38967 | G48: 122.36634 | H48: 119.41577 | I48: 119.81498 | J48: 122.57761 | K48: 116.8828 | L48: 113.79254 | M48: 120.85443 | N48: 125.23268 | O48: 115.30194 | P48: 110.76487 | Q48: 102.08528 | R48: 100.7571 | S48: 98.24169 | T48: 94.519033 | U48: 94.202371 | V48: 101.40578 | W48: 102.67541 | X48: 101.71644 | Y48: 105.36232 | Z48: 103.50057 | AA48: 102.68199 | AB48: 101.15205 | AC48: 104.88092 | AD48: 105.22376 | AE48: 97.877177 | AF48: 97.276263 | AG48: 97.821724 | AH48: 98.439892 | AI48: 96.849079 | AJ48: 99.049821 | AK48: 99.998794 | AL48: 95.223982 | AM48: 97.727547 | AN48: 106.17704 | AO48: 117.33557 | AP48: 128.81831 | AQ48: 128.12104 | AR48: 131.3666 | AS48: 148.44318 | AT48: 158.24064 | AU48: 138.4079 | AV48: 135.31753 | AW48: 140.0563 | AX48: 138.92333 | AY48: 132.29381 | AZ48: 133.82028 | BA48: 137.25968 | BB48: 140.97443 | BC48: 135.2351 | BD48: 140.42452 | BE48: 142.69436 | BF48: 136.04682 | BG48: 132.69804 | BH48: 131.00803 | BI48: 131.37529 | BJ48: 136.81471 | BK48: 134.25199 | BL48: 132.50253 | BM48: 135.09998 | BN48: 135.83045 | BO48: 133.124 | BP48: 132.35582
A49: Hardwood | B49: IMF.RES.GAS:GAS_LIVE | C49: G001.PZPITIHWW.Q | E49: 124.14956 | F49: 122.98221 | G49: 120.47411 | H49: 121.21948 | I49: 115.27604 | J49: 112.38982 | K49: 113.1525 | L49: 116.23479 | M49: 117.43058 | N49: 119.1041 | O49: 117.87477 | P49: 110.59297 | Q49: 105.97262 | R49: 106.35001 | S49: 107.14875 | T49: 105.58083 | U49: 102.3661 | V49: 104.35748 | W49: 99.469486 | X49: 93.806939 | Y49: 92.496107 | Z49: 95.255254 | AA49: 96.870553 | AB49: 97.40519 | AC49: 101.96472 | AD49: 100.14706 | AE49: 96.466873 | AF49: 95.249606 | AG49: 96.734046 | AH49: 95.917774 | AI49: 93.773671 | AJ49: 96.333268 | AK49: 95.923786 | AL49: 94.237082 | AM49: 97.665919 | AN49: 99.981833 | AO49: 101.9163 | AP49: 102.01763 | AQ49: 100.77556 | AR49: 98.35401 | AS49: 97.426077 | AT49: 90.222089 | AU49: 84.479188 | AV49: 83.793063 | AW49: 87.458117 | AX49: 88.60602 | AY49: 88.248318 | AZ49: 86.450168 | BA49: 87.776567 | BB49: 86.499305 | BC49: 89.422378 | BD49: 87.960987 | BE49: 86.805741 | BF49: 91.927408 | BG49: 92.173469 | BH49: 90.234115 | BI49: 91.144311 | BJ49: 91.144311 | BK49: 91.144311 | BL49: 91.144311 | BM49: 91.144311 | BN49: 91.144311 | BO49: 91.144311 | BP49: 91.144311
A50: Industrial Inputs | B50: IMF.RES.GAS:GAS_LIVE | C50: G001.PZPIINDW.Q | E50: 151.59549 | F50: 142.66574 | G50: 135.50489 | H50: 138.36061 | I50: 139.89878 | J50: 131.20924 | K50: 126.7659 | L50: 127.25913 | M50: 127.23424 | N50: 130.91759 | O50: 130.97138 | P50: 122.08975 | Q50: 112.92545 | R50: 110.88123 | S50: 100.1586 | T50: 92.279589 | U50: 91.657547 | V50: 97.758429 | W50: 101.16702 | X50: 109.417 | Y50: 121.19381 | Z50: 111.05206 | AA50: 117.62351 | AB50: 119.76618 | AC50: 128.38392 | AD50: 127.59857 | AE50: 120.1412 | AF50: 119.08992 | AG50: 124.14434 | AH50: 130.18262 | AI50: 127.27163 | AJ50: 121.38949 | AK50: 118.8308 | AL50: 114.30563 | AM50: 132.3107 | AN50: 147.01744 | AO50: 170.41079 | AP50: 194.15902 | AQ50: 184.62203 | AR50: 167.75449 | AS50: 192.82973 | AT50: 190.38725 | AU50: 155.36536 | AV50: 152.80591 | AW50: 175.04454 | AX50: 160.49306 | AY50: 157.31008 | AZ50: 162.00879 | BA50: 162.82492 | BB50: 167.36673 | BC50: 157.97655 | BD50: 161.36339 | BE50: 162.11433 | BF50: 157.57184 | BG50: 163.60852 | BH50: 174.98982 | BI50: 184.06043 | BJ50: 183.41188 | BK50: 183.8489 | BL50: 183.92584 | BM50: 183.88502 | BN50: 183.98671 | BO50: 183.9053 | BP50: 183.58081
A51: Meat | B51: IMF.RES.GAS:GAS_LIVE | C51: G001.PZPIMTW.Q | E51: 113.62229 | F51: 110.28818 | G51: 108.00321 | H51: 108.41357 | I51: 110.59829 | J51: 113.19448 | K51: 116.21206 | L51: 111.90191 | M51: 119.97718 | N51: 133.87114 | O51: 146.61226 | P51: 135.59086 | Q51: 113.01603 | R51: 112.61498 | S51: 113.621 | T51: 98.973058 | U51: 96.509758 | V51: 105.40768 | W51: 103.78053 | X51: 94.302027 | Y51: 105.37181 | Z51: 115.70574 | AA51: 114.31785 | AB51: 104.16993 | AC51: 110.70504 | AD51: 113.62501 | AE51: 102.79199 | AF51: 98.929763 | AG51: 102.78577 | AH51: 119.08307 | AI51: 110.57628 | AJ51: 115.02972 | AK51: 106.47665 | AL51: 100.00022 | AM51: 98.741011 | AN51: 105.8216 | AO51: 114.9515 | AP51: 146.54254 | AQ51: 146.34307 | AR51: 137.47644 | AS51: 152.59691 | AT51: 165.71241 | AU51: 155.74513 | AV51: 134.59803 | AW51: 126.59447 | AX51: 134.90727 | AY51: 131.90504 | AZ51: 124.10639 | BA51: 129.90681 | BB51: 145.90791 | BC51: 146.99494 | BD51: 146.94929 | BE51: 151.04985 | BF51: 158.54253 | BG51: 167.91901 | BH51: 161.20534 | BI51: 149.85077 | BJ51: 171.55444 | BK51: 173.84171 | BL51: 162.44687 | BM51: 160.99379 | BN51: 163.2366 | BO51: 161.04349 | BP51: 161.04349
... A60: Wool | B60: IMF.RES.GAS:GAS_LIVE | C60: G001.PZPIWLW.Q | E60: 134.67843 | F60: 121.76177 | G60: 110.21506 | H60: 112.36617 | I60: 121.7202 | J60: 106.23871 | K60: 98.167432 | L60: 109.08161 | M60: 102.2684 | N60: 99.578192 | O60: 98.773306 | P60: 93.959274 | Q60: 86.365234 | R60: 96.538016 | S60: 91.351057 | T60: 89.715196 | U60: 93.099624 | V60: 98.713461 | W60: 104.5769 | X60: 103.61002 | Y60: 112.86395 | Z60: 113.87614 | AA60: 120.54692 | AB60: 124.61791 | AC60: 142.28861 | AD60: 151.10985 | AE60: 157.80232 | AF60: 146.56382 | AG60: 152.77419 | AH60: 142.97708 | AI60: 123.69358 | AJ60: 111.05733 | AK60: 107.81732 | AL60: 82.428595 | AM60: 71.497066 | AN60: 84.651596 | AO60: 97.920135 | AP60: 103.19415 | AQ60: 99.550314 | AR60: 98.600186 | AS60: 101.12053 | AT60: 101.30609 | AU60: 92.499528 | AV60: 85.782861 | AW60: 97.415642 | AX60: 89.923762 | AY60: 84.20107 | AZ60: 85.152359 | BA60: 85.955381 | BB60: 85.622708 | BC60: 83.874664 | BD60: 84.263772 | BE60: 87.11174 | BF60: 90.221907 | BG60: 94.657411 | BH60: 110.79128 | BI60: 44.540594 | BJ60: 44.540594 | BK60: 44.540594 | BL60: 44.540594 | BM60: 44.540594 | BN60: 44.540594 | BO60: 44.540594 | BP60: 44.540594
A62: Nonfuel commodity prices
A63: Agriculture
A64: Agricultural Raw Materials
A65: Cotton | B65: IMF.RES.GAS:GAS_LIVE | C65: G001.PZPICOT.Q | E65: 100.45469 | F65: 90.271013 | G65: 84.17197 | H65: 82.066195 | I65: 89.888106 | J65: 92.745909 | K65: 91.807453 | L65: 87.160982 | M65: 93.987085 | N65: 92.604206 | O65: 77.071258 | P65: 68.724413 | Q65: 68.848258 | R65: 72.305977 | S65: 70.968897 | T65: 69.545599 | U65: 66.92619 | V65: 71.219448 | W65: 79.729004 | X65: 78.980631 | Y65: 84.756187 | Z65: 86.812614 | AA65: 81.344589 | AB65: 81.479864 | AC65: 90.486677 | AD65: 94.807738 | AE65: 93.695606 | AF65: 86.524123 | AG65: 82.438023 | AH65: 81.678532 | AI65: 72.542409 | AJ65: 74.857308 | AK65: 74.440682 | AL65: 65.678377 | AM65: 69.779183 | AN65: 77.853716 | AO65: 90.482391 | AP65: 92.040463 | AQ65: 100.89553 | AR65: 121.32233 | AS65: 137.28786 | AT65: 157.9136 | AU65: 124.57844 | AV65: 100.77615 | AW65: 98.377556 | AX65: 93.811821 | AY65: 95.677916 | AZ65: 92.175108 | BA65: 97.007729 | BB65: 86.577134 | BC65: 81.289008 | BD65: 81.716802 | BE65: 77.990851 | BF65: 78.153644 | BG65: 78.485868 | BH65: 75.110086 | BI65: 73.104645 | BJ65: 74.056836 | BK65: 76.109435 | BL65: 78.820964 | BM65: 80.459545 | BN65: 81.205944 | BO65: 81.637457 | BP65: 80.167982
A66: Hides | B66: IMF.RES.GAS:GAS_LIVE | C66: G001.PZPIHIDE.Q | E66: 73.412675 | F66: 82.086142 | G66: 84.618181 | H66: 86.442121 | I66: 91.811544 | J66: 99.110718 | K66: 97.273733 | L66: 97.162474 | M66: 103.94416 | N66: 107.34932 | O66: 105.66363 | P66: 109.31953 | Q66: 99.431325 | R66: 100.46435 | S66: 79.590019 | T66: 72.061104 | U66: 72.735828 | V66: 72.949528 | W66: 73.360676 | X66: 74.063135 | Y66: 75.785743 | Z66: 74.4205 | AA66: 65.634699 | AB66: 60.974689 | AC66: 66.396122 | AD66: 62.481866 | AE66: 57.64953 | AF66: 53.274603 | AG66: 47.432609 | AH66: 42.707846 | AI66: 34.415877 | AJ66: 38.671752 | AK66: 39.226487 | AL66: 35.412097 | AM66: 29.525373 | AN66: 30.104897 | AO66: 37.904706 | AP66: 40.446767 | AQ66: 54.127627 | AR66: 57.196068 | AS66: 58.054543 | AT66: 57.702435 | AU66: 56.917119 | AV66: 57.55179 | AW66: 58.580296 | AX66: 59.757259 | AY66: 58.46858 | AZ66: 57.729759 | BA66: 58.410881 | BB66: 58.518443 | BC66: 59.416851 | BD66: 58.26457 | BE66: 58.40384 | BF66: 59.115151 | BG66: 59.129681 | BH66: 54.411421 | BI66: 57.423233 | BJ66: 57.423233 | BK66: 57.423233 | BL66: 57.423233 | BM66: 57.423233 | BN66: 57.423233 | BO66: 57.423233 | BP66: 57.423233
A67: Rubber | B67: IMF.RES.GAS:GAS_LIVE | C67: G001.PZPIRUB.Q | E67: 174.74851 | F67: 162.86708 | G67: 134.71572 | H67: 140.4293 | I67: 143.13616 | J67: 131.76974 | K67: 117.48256 | L67: 114.64633 | M67: 102.09656 | N67: 96.081598 | O67: 83.358661 | P67: 73.468198 | Q67: 78.590197 | R67: 81.217538 | S67: 66.104761 | T67: 57.01262 | U67: 59.335505 | V67: 75.217486 | W67: 76.088267 | X67: 87.292974 | Y67: 115.41295 | Z67: 93.20781 | AA67: 82.037864 | AB67: 72.503773 | AC67: 77.799933 | AD67: 74.637849 | AE67: 65.912407 | AF67: 63.295151 | AG67: 74.516633 | AH67: 83.030997 | AI67: 71.863504 | AJ67: 69.931548 | AK67: 71.748777 | AL67: 62.28615 | AM67: 79.086336 | AN67: 106.47256 | AO67: 105.9351 | AP67: 100.60403 | AQ67: 84.132354 | AR67: 87.408663 | AS67: 95.133998 | AT67: 95.714257 | AU67: 74.399814 | AV67: 67.895266 | AW67: 73.009102 | AX67: 70.060864 | AY67: 68.653462 | AZ67: 75.460253 | BA67: 97.470198 | BB67: 104.30965 | BC67: 108.51087 | BD67: 109.982 | BE67: 109.24994 | BF67: 99.989844 | BG67: 99.090103 | BH67: 93.251348 | BI67: 95.884588 | BJ67: 98.353839 | BK67: 98.444558 | BL67: 98.429438 | BM67: 98.746952 | BN67: 98.746952 | BO67: 98.746952 | BP67: 98.746952
A68: Timber
A69: Hardwood
A70: Hardwood Logs | B70: IMF.RES.GAS:GAS_LIVE | C70: G001.PZPITIHWL.Q | E70: 373.25909 | F70: 361.01186 | G70: 355.08083 | H70: 352.68943 | I70: 322.53138 | J70: 301.77548 | K70: 301.08866 | L70: 296.34121 | M70: 289.78477 | N70: 291.51483 | O70: 286.4732 | P70: 260.3919 | Q70: 249.89619 | R70: 245.38336 | S70: 243.58137 | T70: 245.20241 | U70: 258.23911 | V70: 275.74454 | W70: 290.71809 | X70: 272.8058 | Y70: 261.84352 | Z70: 268.00684 | AA70: 268.17071 | AB70: 263.69667 | AC70: 274.93933 | AD70: 272.8891 | AE70: 266.99235 | AF70: 263.99498 | AG70: 270.23139 | AH70: 270.88201 | AI70: 277.45359 | AJ70: 273.84546 | AK70: 273.29747 | AL70: 276.89299 | AM70: 280.61595 | AN70: 285.15588 | AO70: 281.12546 | AP70: 272.01262 | AQ70: 270.40937 | AR70: 261.85733 | AS70: 256.15595 | AT70: 229.71444 | AU70: 215.38915 | AV70: 210.70132 | AW70: 224.94922 | AX70: 217.01755 | AY70: 206.06682 | AZ70: 201.47119 | BA70: 200.54255 | BB70: 191.07712 | BC70: 200.00708 | BD70: 195.37148 | BE70: 195.31795 | BF70: 206.10359 | BG70: 201.84263 | BH70: 193.13617 | BI70: 189.99416 | BJ70: 189.99416 | BK70: 189.99416 | BL70: 189.99416 | BM70: 189.99416 | BN70: 189.99416 | BO70: 189.99416 | BP70: 189.99416
A71: Hard Sawnwood | B71: IMF.RES.GAS:GAS_LIVE | C71: G001.PZPITIHWS.Q | E71: 882.86782 | F71: 883.79307 | G71: 864.25747 | H71: 874.44973 | I71: 845.16081 | J71: 837.39045 | K71: 845.96079 | L71: 882.67887 | M71: 901.90233 | N71: 917.2895 | O71: 909.96833 | P71: 862.60783 | Q71: 826.1655 | R71: 834.81283 | S71: 844.93167 | T71: 827.092 | U71: 780.25833 | V71: 782.25667 | W71: 716.16633 | X71: 676.8355 | Y71: 674.928 | Z71: 696.80067 | AA71: 713.24283 | AB71: 723.46667 | AC71: 758.49467 | AD71: 741.963 | AE71: 710.33483 | AF71: 700.979 | AG71: 709.66267 | AH71: 700.57933 | AI71: 671.58533 | AJ71: 701.72383 | AK71: 698.0905 | AL71: 676.94403 | AM71: 708.2822 | AN71: 727.30997 | AO71: 751.46417 | AP71: 762.1295 | AQ71: 751.04633 | AR71: 735.16867 | AS71: 731.64433 | AT71: 685.46467 | AU71: 641.5195 | AV71: 639.41217 | AW71: 662.066 | AX71: 682.24917 | AY71: 690.1335 | AZ71: 676.49033 | BA71: 691.1145 | BB71: 687.97167 | BC71: 708.609 | BD71: 698.472 | BE71: 686.6455 | BF71: 727.93833 | BG71: 734.96883 | BH71: 724.21417 | BI71: 736.89447 | BJ71: 736.89447 | BK71: 736.89447 | BL71: 736.89447 | BM71: 736.89447 | BN71: 736.89447 | BO71: 736.89447 | BP71: 736.89447
A72: Softwood
A73: Softwood Logs | B73: IMF.RES.GAS:GAS_LIVE | C73: G001.PZPITISWL.Q | E73: 160.02072 | F73: 156.43022 | G73: 162.13574 | H73: 166.11967 | I73: 170.08195 | J73: 184.97058 | K73: 165.08928 | L73: 181.76315 | M73: 186.93172 | N73: 181.25502 | O73: 179.05088 | P73: 189.65247 | Q73: 189.06499 | R73: 178.99576 | S73: 180.39689 | T73: 175.8957 | U73: 186.84482 | V73: 178.7552 | W73: 179.66896 | X73: 186.00907 | Y73: 181.86712 | Z73: 188.41305 | AA73: 188.82946 | AB73: 203.72073 | AC73: 231.26898 | AD73: 214.75103 | AE73: 205.45458 | AF73: 194.19 | AG73: 187.26667 | AH73: 184.07 | AI73: 187.77667 | AJ73: 184.44 | AK73: 196.45333 | AL73: 189.98 | AM73: 195.4 | AN73: 217.28 | AO73: 220.15667 | AP73: 237.58333 | AQ73: 246.32667 | AR73: 239.93 | AS73: 269.95 | AT73: 283.27667 | AU73: 272.05 | AV73: 258.31667 | AW73: 225.69333 | AX73: 213.67 | AY73: 214.94 | AZ73: 208.12 | BA73: 207.14333 | BB73: 197.89667 | BC73: 187.25333 | BD73: 187.48656 | BE73: 199.13088 | BF73: 216.77638 | BG73: 208.34391 | BH73: 198.9475 | BI73: 192.05553 | BJ73: 219.6358 | BK73: 229.71657 | BL73: 235.69366 | BM73: 241.84917 | BN73: 241.84917 | BO73: 241.84917 | BP73: 241.84917
A74: Sawn Softwood | B74: IMF.RES.GAS:GAS_LIVE | C74: G001.PZPITISWS.Q | E74: 310.1242 | F74: 323.60878 | G74: 320.06167 | H74: 313.56858 | I74: 306.27913 | J74: 345.46263 | K74: 341.59395 | L74: 336.80377 | M74: 344.62645 | N74: 332.33409 | O74: 323.25643 | P74: 331.2028 | Q74: 336.7001 | R74: 325.00649 | S74: 304.21021 | T74: 306.00064 | U74: 319.07817 | V74: 328.62226 | W74: 325.77653 | X74: 327.10988 | Y74: 308.47858 | Z74: 321.24845 | AA74: 320.84327 | AB74: 329.01401 | AC74: 339.51902 | AD74: 345.27017 | AE74: 344.35962 | AF74: 349.13333 | AG74: 348.83 | AH74: 351.50333 | AI74: 362.76667 | AJ74: 352.36667 | AK74: 354.83 | AL74: 355.24333 | AM74: 334.35333 | AN74: 346.85 | AO74: 351.7 | AP74: 418.02 | AQ74: 331.37333 | AR74: 312.04667 | AS74: 377.29 | AT74: 430.35667 | AU74: 412.05333 | AV74: 380.62333 | AW74: 316.54333 | AX74: 318.79 | AY74: 325.77667 | AZ74: 312.41667 | BA74: 334.89 | BB74: 316.45 | BC74: 314.67333 | BD74: 318.21247 | BE74: 328.23031 | BF74: 326.90029 | BG74: 317.56561 | BH74: 285.60434 | BI74: 289.89221 | BJ74: 289.89221 | BK74: 289.89221 | BL74: 289.89221 | BM74: 289.89221 | BN74: 289.89221 | BO74: 289.89221 | BP74: 289.89221
A75: Wool + Yarn
A76: Wool, Coarse | B76: IMF.RES.GAS:GAS_LIVE | C76: G001.PZPIWL_Type1.Q | E76: 1337.727 | F76: 1239.2968 | G76: 1133.5186 | H76: 1122.713 | I76: 1229.6507 | J76: 1099.7881 | K76: 1017.6504 | L76: 1126.4944 | M76: 1062.3594 | N76: 1033.2152 | O76: 1033.181 | P76: 967.07954 | Q76: 890.73922 | R76: 971.85765 | S76: 940.92643 | T76: 915.93831 | U76: 959.73451 | V76: 1009.2894 | W76: 1083.1203 | X76: 1016.4216 | Y76: 1039.1122 | Z76: 1025.4848 | AA76: 1140.3344 | AB76: 1151.9015 | AC76: 1375.6531 | AD76: 1554.6145 | AE76: 1633.29 | AF76: 1513.1794 | AG76: 1585.9779 | AH76: 1486.6633 | AI76: 1352.2272 | AJ76: 1148.6256 | AK76: 1113.254 | AL76: 838.22467 | AM76: 716.26266 | AN76: 810.73829 | AO76: 910.27926 | AP76: 935.61522 | AQ76: 885.55034 | AR76: 903.2401 | AS76: 929.70142 | AT76: 927.80536 | AU76: 861.53659 | AV76: 804.89632 | AW76: 923.8414 | AX76: 879.29183 | AY76: 850.17555 | AZ76: 876.64704 | BA76: 888.09217 | BB76: 889.53112 | BC76: 872.34462 | BD76: 873.55926 | BE76: 912.18804 | BF76: 939.05763 | BG76: 989.43402 | BH76: 1153.1121 | BI76: 464.77897 | BJ76: 464.77897 | BK76: 464.77897 | BL76: 464.77897 | BM76: 464.77897 | BN76: 464.77897 | BO76: 464.77897 | BP76: 464.77897
A77: Wool, Fine | B77: IMF.RES.GAS:GAS_LIVE | C77: G001.PZPIWL_Type2.Q | E77: 1534.1311 | F77: 1354.3141 | G77: 1213.0326 | H77: 1272.7399 | I77: 1363.9438 | J77: 1161.429 | K77: 1071.6416 | L77: 1195.4883 | M77: 1114.0061 | N77: 1086.0133 | O77: 1068.1341 | P77: 1033.3051 | Q77: 947.79731 | R77: 1085.4791 | S77: 1003.8643 | T77: 994.79316 | U77: 1022.2066 | V77: 1092.945 | W77: 1142.6757 | X77: 1194.1371 | Y77: 1375.2991 | Z77: 1412.7419 | AA77: 1435.56 | AB77: 1513.5224 | AC77: 1662.0322 | AD77: 1662.5659 | AE77: 1725.4496 | AF77: 1606.7119 | AG77: 1665.2947 | AH77: 1555.8863 | AI77: 1273.7436 | AJ77: 1215.2509 | AK77: 1181.8336 | AL77: 917.63166 | AM77: 807.75279 | AN77: 997.19182 | AO77: 1183.626 | AP77: 1273.3012 | AQ77: 1246.9727 | AR77: 1206.4663 | AS77: 1233.6137 | AT77: 1239.8191 | AU77: 1116.3001 | AV77: 1028.766 | AW77: 1157.5559 | AX77: 1039.5356 | AY77: 944.00957 | AZ77: 936.21909 | BA77: 941.57055 | BB77: 932.59077 | BC77: 912.48568 | BD77: 919.81805 | BE77: 940.94436 | BF77: 980.77451 | BG77: 1024.3845 | BH77: 1204.4193 | BI77: 482.8886 | BJ77: 482.8886 | BK77: 482.8886 | BL77: 482.8886 | BM77: 482.8886 | BN77: 482.8886 | BO77: 482.8886 | BP77: 482.8886
A78: Beverages
A79: Coffee
A80: Coffee, Arabica | B80: IMF.RES.GAS:GAS_LIVE | C80: G001.PZPICF_Type3.Q | E80: 220.87345 | F80: 181.50001 | G80: 181.41575 | H80: 161.97712 | I80: 152.1015 | J80: 145.07747 | K80: 135.2743 | L80: 125.48408 | M80: 173.41614 | N80: 211.86259 | O80: 206.79561 | P80: 209.34925 | Q80: 176.41692 | R80: 160.74519 | S80: 152.50556 | T80: 149.94707 | U80: 150.2544 | V80: 158.28815 | W80: 171.86686 | X80: 174.95053 | Y80: 165.03805 | Z80: 149.59891 | AA80: 148.74691 | AB80: 139.63994 | AC80: 136.69956 | AD80: 134.66097 | AE80: 125.66317 | AF80: 133.83601 | AG80: 126.89999 | AH80: 123.75436 | AI80: 130.21476 | AJ80: 141.35394 | AK80: 142.25476 | AL80: 148.68888 | AM80: 158.80561 | AN80: 153.57854 | AO80: 164.76646 | AP80: 182.39201 | AQ80: 215.49076 | AR80: 256.12688 | AS80: 269.96947 | AT80: 266.53693 | AU80: 263.96081 | AV80: 221.3964 | AW80: 219.6433 | AX80: 219.15393 | AY80: 187.8101 | AZ80: 197.23167 | BA80: 207.19193 | BB80: 240.20466 | BC80: 265.76563 | BD80: 308.61629 | BE80: 389.22015 | BF80: 384.55458 | BG80: 360.65424 | BH80: 397.96296 | BI80: 313.4782 | BJ80: 303.43576 | BK80: 295.70915 | BL80: 288.39189 | BM80: 285.11704 | BN80: 282.45622 | BO80: 277.7742 | BP80: 272.01762
A81: Coffee, Robusta | B81: IMF.RES.GAS:GAS_LIVE | C81: G001.PZPICF_Type2.Q | E81: 100.75653 | F81: 104.86068 | G81: 106.17771 | H81: 99.579115 | I81: 103.22188 | J81: 97.210845 | K81: 92.331511 | L81: 83.70682 | M81: 96.319081 | N81: 102.48942 | O81: 100.85451 | P81: 102.01457 | Q81: 96.13597 | R81: 89.947684 | S81: 84.797512 | T81: 81.264942 | U81: 74.882091 | V81: 83.35026 | W81: 93.161654 | X81: 103.07343 | Y81: 107.18145 | Z81: 101.34957 | AA81: 102.87963 | AB81: 92.427951 | AC81: 88.650267 | AD81: 87.704934 | AE81: 80.619097 | AF81: 82.124254 | AG81: 77.93733 | AH81: 72.789496 | AI81: 71.794492 | AJ81: 71.740186 | AK81: 68.70241 | AL81: 64.392229 | AM81: 71.032758 | AN81: 70.895398 | AO81: 72.681625 | AP81: 79.692027 | AQ81: 97.855606 | AR81: 109.06803 | AS81: 107.68789 | AT81: 103.65348 | AU81: 107.16387 | AV81: 96.013968 | AW81: 102.14316 | AX81: 123.42038 | AY81: 125.27709 | AZ81: 125.6676 | BA81: 155.73079 | BB81: 194.8198 | BC81: 223.89955 | BD81: 228.54916 | BE81: 255.22281 | BF81: 226.68869 | BG81: 192.29005 | BH81: 206.70806 | BI81: 198.2745 | BJ81: 174.21216 | BK81: 168.93793 | BL81: 164.45368 | BM81: 160.55029 | BN81: 158.04096 | BO81: 156.87924 | BP81: 156.87924
A82: Cocoa | B82: IMF.RES.GAS:GAS_LIVE | C82: G001.PZPICO.Q | E82: 2341.0843 | F82: 2280.7103 | G82: 2494.1206 | H82: 2457.8408 | I82: 2208.8321 | J82: 2308.0109 | K82: 2469.3941 | L82: 2770.137 | M82: 2951.2876 | N82: 3084.9712 | O82: 3229.1915 | P82: 2985.6221 | Q82: 2918.5244 | R82: 3068.0518 | S82: 3252.8102 | T82: 3301.2788 | U82: 2980.7673 | V82: 3099.8775 | W82: 2987.8843 | X82: 2496.4973 | Y82: 2097.0015 | Z82: 1980.9625 | AA82: 1991.8107 | AB82: 2047.5769 | AC82: 2192.8587 | AD82: 2565.0357 | AE82: 2241.1815 | AF82: 2175.8804 | AG82: 2239.8749 | AH82: 2351.3115 | AI82: 2305.5233 | AJ82: 2466.5764 | AK82: 2552.5868 | AL82: 2272.1034 | AM82: 2302.7885 | AN82: 2352.3543 | AO82: 2415.7355 | AP82: 2380.7124 | AQ82: 2452.8481 | AR82: 2452.7769 | AS82: 2492.694 | AT82: 2381.4573 | AU82: 2243.2398 | AV82: 2360.2204 | AW82: 2597.4649 | AX82: 2951.0183 | AY82: 3470.0693 | AZ82: 4013.6251 | BA82: 5793.5204 | BB82: 8671.1437 | BC82: 6792.8025 | BD82: 8304.7907 | BE82: 9527.5219 | BF82: 8511.6529 | BG82: 7327.5134 | BH82: 5786.3776 | BI82: 4413.8142 | BJ82: 4223.6907 | BK82: 4293.5519 | BL82: 4368.9784 | BM82: 4401.5804 | BN82: 4401.258 | BO82: 4400.4192 | BP82: 4406.9355
A83: Tea | B83: IMF.RES.GAS:GAS_LIVE | C83: G001.PZPITEA.Q | E83: 339.75758 | F83: 341 | G83: 352.33234 | H83: 362.57058 | I83: 319.05469 | J83: 264.23268 | K83: 244.89698 | L83: 234.22068 | M83: 247.90083 | N83: 222.208 | O83: 233.70859 | P83: 247.61278 | Q83: 291.1768 | R83: 320.14176 | S83: 387.19324 | T83: 363.03492 | U83: 290.26497 | V83: 251.3854 | W83: 284.67111 | X83: 323.39659 | Y83: 369.23744 | Z83: 371.59877 | AA83: 365.19617 | AB83: 342.77347 | AC83: 334.74191 | AD83: 297.51696 | AE83: 282.0522 | AF83: 278.72951 | AG83: 272.995 | AH83: 262.04413 | AI83: 258.74442 | AJ83: 279.32178 | AK83: 269.302 | AL83: 244.44822 | AM83: 249.52036 | AN83: 252.46189 | AO83: 256.75033 | AP83: 237.31596 | AQ83: 258.67005 | AR83: 316.07732 | AS83: 302.96194 | AT83: 266.46616 | AU83: 265.15767 | AV83: 277.20591 | AW83: 269.39595 | AX83: 263.34444 | AY83: 302.48442 | AZ83: 325.63789 | BA83: 340.33414 | BB83: 308.76334 | BC83: 323.61325 | BD83: 339.3817 | BE83: 332.10265 | BF83: 313.59473 | BG83: 309.70066 | BH83: 311.66211 | BI83: 309.80011 | BJ83: 309.80011 | BK83: 309.80011 | BL83: 309.80011 | BM83: 309.80011 | BN83: 309.80011 | BO83: 309.80011 | BP83: 309.80011
A84: Food
A85: Cereals
A86: Barley | B86: IMF.RES.GAS:GAS_LIVE | C86: G001.PZPIBR.Q | E86: 215.54032 | F86: 234.18611 | G86: 253.33796 | H86: 251.26698 | I86: 237.40202 | J86: 226.23017 | K86: 189.80832 | L86: 149.88998 | M86: 147.5161 | N86: 153.01341 | O86: 122.09269 | P86: 107.38366 | Q86: 106.70961 | R86: 104.22341 | S86: 97.850893 | T86: 92.328068 | U86: 87.231732 | V86: 106.65978 | W86: 100.48968 | X86: 96.85631 | Y86: 102.17863 | Z86: 104.55678 | AA86: 104.44465 | AB86: 95.458461 | AC86: 105.33726 | AD86: 110.95737 | AE86: 97.771926 | AF86: 103.3724 | AG86: 104.41242 | AH86: 110.79378 | AI86: 114.04191 | AJ86: 112.49073 | AK86: 109.18814 | AL86: 99.434335 | AM86: 102.2537 | AN86: 107.62815 | AO86: 134.17505 | AP86: 179.15092 | AQ86: 175.17313 | AR86: 223.84227 | AS86: 252.1442 | AT86: 259.81835 | AU86: 211.09545 | AV86: 177.78509 | AW86: 182.49526 | AX86: 180.55793 | AY86: 160.19092 | AZ86: 144.41365 | BA86: 150.80411 | BB86: 134.139 | BC86: 137.41211 | BD86: 122.23373 | BE86: 112.39674 | BF86: 116.22558 | BG86: 117.80143 | BH86: 115.02586 | BI86: 121.85384 | BJ86: 126.64189 | BK86: 128.27073 | BL86: 128.27073 | BM86: 125.01306 | BN86: 125.01306 | BO86: 125.01306 | BP86: 125.01306
A87: Maize (Corn) | B87: IMF.RES.GAS:GAS_LIVE | C87: G001.PZPIMAIZ.Q | E87: 277.71651 | F87: 270.14437 | G87: 328.64608 | H87: 317.24323 | I87: 305.18325 | J87: 290.74858 | K87: 240.48074 | L87: 199.5053 | M87: 210.17364 | N87: 214.01311 | O87: 173.97033 | P87: 173.59986 | Q87: 174.28252 | R87: 168.43861 | S87: 169.47562 | T87: 167.1818 | U87: 160.01408 | V87: 171.12675 | W87: 153.51679 | X87: 152.22626 | Y87: 160.65125 | Z87: 157.70486 | AA87: 151.15664 | AB87: 148.86732 | AC87: 163.81815 | AD87: 173.30678 | AE87: 158.00718 | AF87: 162.91122 | AG87: 167.60795 | AH87: 176.00049 | AI87: 170.16314 | AJ87: 166.9062 | AK87: 167.57929 | AL87: 146.34793 | AM87: 156.19438 | AN87: 192.19195 | AO87: 241.02296 | AP87: 288.48124 | AQ87: 257.09404 | AR87: 250.98111 | AS87: 301.77382 | AT87: 343.04452 | AU87: 306.38632 | AV87: 322.23946 | AW87: 295.34757 | AX87: 275.42917 | AY87: 222.26517 | AZ87: 212.78026 | BA87: 192.64429 | BB87: 194.38682 | BC87: 176.90676 | BD87: 197.90871 | BE87: 214.45539 | BF87: 205.36554 | BG87: 190.54108 | BH87: 201.66354 | BI87: 206.69955 | BJ87: 213.35418 | BK87: 215.82244 | BL87: 222.0232 | BM87: 227.68214 | BN87: 230.57181 | BO87: 228.64537 | BP87: 227.92295
A88: Oats | B88: IMF.RES.GAS:GAS_LIVE | C88: G001.PZPIOAT.Q | E88: 3.1453258 | F88: 3.2295763 | G88: 3.7712919 | H88: 3.7293801 | I88: 3.7797596 | J88: 3.8825152 | K88: 3.5670682 | L88: 3.4632421 | M88: 4.364551 | N88: 3.775754 | O88: 3.5653878 | P88: 3.2707328 | Q88: 2.8372187 | R88: 2.4988938 | S88: 2.329531 | T88: 2.3349129 | U88: 1.9273078 | V88: 1.9377597 | W88: 1.8583503 | X88: 2.1417857 | Y88: 2.5051602 | Z88: 2.40936 | AA88: 2.6263786 | AB88: 2.5408485 | AC88: 2.562972 | AD88: 2.3601263 | AE88: 2.4684585 | AF88: 2.8550263 | AG88: 2.7697348 | AH88: 2.9461614 | AI88: 2.7246742 | AJ88: 3.024846 | AK88: 2.8777731 | AL88: 3.0817753 | AM88: 2.8399964 | AN88: 3.0742614 | AO88: 3.6276602 | AP88: 3.8077778 | AQ88: 4.8315963 | AR88: 7.0195725 | AS88: 6.9524854 | AT88: 6.8497547 | AU88: 4.603308 | AV88: 3.7710714 | AW88: 3.6459373 | AX88: 3.4560194 | AY88: 4.370509 | AZ88: 3.7814214 | BA88: 3.7075604 | BB88: 3.5576161 | BC88: 3.3638944 | BD88: 3.6112765 | BE88: 3.5369452 | BF88: 3.5805489 | BG88: 3.3724524 | BH88: 3.2365519 | BI88: 3.1180349 | BJ88: 3.1575 | BK88: 3.19125 | BL88: 3.32 | BM88: 3.355 | BN88: 3.415 | BO88: 3.29125 | BP88: 3.3725
A89: Rice | B89: IMF.RES.GAS:GAS_LIVE | C89: G001.PZPIRIN.Q | E89: 555.19349 | F89: 601.51001 | G89: 583.91107 | H89: 580.33007 | I89: 570.66059 | J89: 550.68808 | K89: 506.0112 | L89: 449.87195 | M89: 440.72878 | N89: 409.39958 | O89: 434.96032 | P89: 420.81159 | Q89: 406.63636 | R89: 381.79437 | S89: 374.02776 | T89: 357.72777 | U89: 367.71498 | V89: 401.84921 | W89: 418.15183 | X89: 365.34343 | Y89: 369.60935 | Z89: 407.36495 | AA89: 412.9158 | AB89: 406.40837 | AC89: 416.64236 | AD89: 426.24707 | AE89: 381.70553 | AF89: 387.73166 | AG89: 385.81066 | AH89: 394.65448 | AI89: 408.68897 | AJ89: 396.90062 | AK89: 443.48452 | AL89: 514.90693 | AM89: 480.27197 | AN89: 472.68954 | AO89: 518.85801 | AP89: 467.44228 | AQ89: 396.21212 | AR89: 385.33848 | AS89: 408.81159 | AT89: 425.07215 | AU89: 416.79378 | AV89: 425.5469 | AW89: 473.05053 | AX89: 487.83729 | AY89: 575.69979 | AZ89: 577.70058 | BA89: 613.44168 | BB89: 592.0527 | BC89: 561.97048 | BD89: 493.2397 | BE89: 433.42754 | BF89: 395.35931 | BG89: 355.97989 | BH89: 351.76812 | BI89: 435.67521 | BJ89: 427.92761 | BK89: 444.58569 | BL89: 455.69108 | BM89: 470.40572 | BN89: 470.40572 | BO89: 470.40572 | BP89: 470.40572
A90: Sorghum | B90: IMF.RES.GAS:GAS_LIVE | C90: G001.PZPISORG.Q | E90: 12.1582 | F90: 11.882 | G90: 13.935083 | H90: 12.9434 | I90: 13.3722 | J90: 14.372367 | K90: 11.930167 | L90: 8.7684667 | M90: 8.8992333 | N90: 9.6714667 | O90: 8.2046333 | P90: 8.4199667 | Q90: 9.9873667 | R90: 10.019233 | S90: 8.7691333 | T90: 7.8108333 | U90: 7.4140667 | V90: 7.3696 | W90: 6.8068333 | X90: 6.6755 | Y90: 7.0212333 | Z90: 7.1699333 | AA90: 7.4854333 | AB90: 7.7601 | AC90: 8.2709 | AD90: 7.8493 | AE90: 7.2088926 | AF90: 7.2644667 | AG90: 7.6026333 | AH90: 7.388881 | AI90: 6.910461 | AJ90: 7.4023744 | AK90: 7.480285 | AL90: 7.7602579 | AM90: 8.794074 | AN90: 12.68538 | AO90: 15.468774 | AP90: 16.856365 | AQ90: 14.918663 | AR90: 14.582029 | AS90: 16.445835 | AT90: 18.14543 | AU90: 15.887514 | AV90: 16.749628 | AW90: 16.470467 | AX90: 15.894344 | AY90: 12.867062 | AZ90: 12.547094 | BA90: 11.503053 | BB90: 11.273156 | BC90: 9.7541948 | BD90: 10.523528 | BE90: 10.64915 | BF90: 9.0727149 | BG90: 7.7343868 | BH90: 8.7278696 | BI90: 8.5226049 | BJ90: 8.5226049 | BK90: 8.5226049 | BL90: 8.5226049 | BM90: 8.5226049 | BN90: 8.5226049 | BO90: 8.5226049 | BP90: 8.5226049
A91: Wheat | B91: IMF.RES.GAS:GAS_LIVE | C91: G001.PZPIWHE.Q | E91: 244.39215 | F91: 232.97725 | G91: 314.3159 | H91: 313.63544 | I91: 274.41026 | J91: 269.0221 | K91: 257.96615 | L91: 261.34662 | M91: 249.46371 | N91: 275.31505 | O91: 226.293 | P91: 220.52389 | Q91: 205.8183 | R91: 196.32775 | S91: 178.93476 | T91: 162.38311 | U91: 162.65196 | V91: 159.21407 | W91: 128.28629 | X91: 122.65154 | Y91: 143.64623 | Z91: 147.36467 | AA91: 150.66554 | AB91: 139.49791 | AC91: 169.86533 | AD91: 188.71982 | AE91: 199.74752 | AF91: 186.18328 | AG91: 177.08943 | AH91: 164.00318 | AI91: 153.27008 | AJ91: 158.668 | AK91: 173.78254 | AL91: 174.80794 | AM91: 182.96464 | AN91: 210.49759 | AO91: 236.21273 | AP91: 252.38339 | AQ91: 262.74585 | AR91: 311.83069 | AS91: 353.74997 | AT91: 415.94526 | AU91: 330.43803 | AV91: 340.56587 | AW91: 320.64622 | AX91: 298.17586 | AY91: 249.8074 | AZ91: 220.69921 | BA91: 219.05254 | BB91: 213.6795 | BC91: 182.41377 | BD91: 189.63369 | BE91: 186.77961 | BF91: 181.61753 | BG91: 159.89657 | BH91: 164.0741 | BI91: 179.65392 | BJ91: 194.29258 | BK91: 201.66017 | BL91: 211.58656 | BM91: 217.32181 | BN91: 220.14532 | BO91: 220.18944 | BP91: 225.79233
A92: Meat
A93: Beef | B93: IMF.RES.GAS:GAS_LIVE | C93: G001.PZPIBE.Q | E93: 193.13023 | F93: 187.66494 | G93: 181.24802 | H93: 189.72842 | I93: 193.81734 | J93: 181.83959 | K93: 176.14776 | L93: 182.4431 | M93: 191.82281 | N93: 195.51948 | O93: 252.8842 | P93: 256.00725 | Q93: 216.56439 | R93: 202.89719 | S93: 206.27404 | T93: 176.24186 | U93: 168.85887 | V93: 179.27128 | W93: 185.41105 | X93: 179.29185 | Y93: 183.84888 | Z93: 199.81571 | AA93: 194.39545 | AB93: 187.98232 | AC93: 192.25919 | AD93: 188.11905 | AE93: 179.65563 | AF93: 174.19426 | AG93: 189.63789 | AH93: 203.74885 | AI93: 204.83283 | AJ93: 240.56862 | AK93: 203.92045 | AL93: 208.68795 | AM93: 199.1534 | AN93: 189.97995 | AO93: 202.33428 | AP93: 237.24928 | AQ93: 247.35606 | AR93: 256.89168 | AS93: 269.23439 | AT93: 267.77742 | AU93: 252.09999 | AV93: 227.71248 | AW93: 222.12609 | AX93: 239.40596 | AY93: 217.24293 | AZ93: 222.33225 | BA93: 234.8844 | BB93: 267.73831 | BC93: 271.77292 | BD93: 272.65616 | BE93: 286.60085 | BF93: 295.01912 | BG93: 308.09081 | BH93: 326.05072 | BI93: 284.0702 | BJ93: 334.30429 | BK93: 329.37334 | BL93: 329.42694 | BM93: 329.33761 | BN93: 322.70941 | BO93: 313.43707 | BP93: 313.43707
A94: Lamb | B94: IMF.RES.GAS:GAS_LIVE | C94: G001.PZPILAMB.Q | E94: 124.38074 | F94: 100.16845 | G94: 89.617673 | H94: 91.086323 | I94: 95.383613 | J94: 101.15577 | K94: 107.4105 | L94: 119.43111 | M94: 130.15492 | N94: 144.37738 | O94: 140.4737 | P94: 130.59799 | Q94: 117.69381 | R94: 109.0943 | S94: 99.504918 | T94: 91.655533 | U94: 86.667666 | V94: 91.456575 | W94: 92.219347 | X94: 95.050062 | Y94: 97.903071 | Z94: 111.95061 | AA94: 107.57043 | AB94: 116.67196 | AC94: 123.55274 | AD94: 121.21476 | AE94: 110.91484 | AF94: 107.12621 | AG94: 106.89698 | AH94: 111.71 | AI94: 114.90635 | AJ94: 129.85542 | AK94: 127.06441 | AL94: 111.06269 | AM94: 112.69993 | AN94: 113.82997 | AO94: 128.27172 | AP94: 146.87597 | AQ94: 150.73263 | AR94: 160.37973 | AS94: 166.83974 | AT94: 149.60329 | AU94: 131.538 | AV94: 106.12513 | AW94: 97.259367 | AX94: 107.9306 | AY94: 86.93982 | AZ94: 88.597653 | BA94: 96.295875 | BB94: 104.61441 | BC94: 123.8891 | BD94: 128.19217 | BE94: 133.56019 | BF94: 158.84929 | BG94: 163.34785 | BH94: 161.49276 | BI94: 168.55284 | BJ94: 168.55284 | BK94: 168.55284 | BL94: 168.55284 | BM94: 168.55284 | BN94: 168.55284 | BO94: 168.55284 | BP94: 168.55284
A95: Poultry | B95: IMF.RES.GAS:GAS_LIVE | C95: G001.PZPIPOULT.Q | E95: 91.444924 | F95: 93.944674 | G95: 95.129721 | H95: 96.713453 | I95: 100.25704 | J95: 104.10738 | K95: 106.36928 | L95: 104.73082 | M95: 104.70968 | N95: 108.88312 | O95: 112.94713 | P95: 113.86685 | Q95: 114.04482 | R95: 115.64851 | S95: 115.45417 | T95: 113.57254 | U95: 112.0708 | V95: 111.80014 | W95: 110.95216 | X95: 110.89892 | Y95: 117.99555 | Z95: 140.9388 | AA95: 127.71919 | AB95: 115.78978 | AC95: 128.28722 | AD95: 154.89925 | AE95: 125.09046 | AF95: 116.93907 | AG95: 126.42808 | AH95: 131.48297 | AI95: 110.63616 | AJ95: 108.61936 | AK95: 112.84831 | AL95: 90.365978 | AM95: 89.516062 | AN95: 101.88402 | AO95: 112.28192 | AP95: 140.08923 | AQ95: 141.6829 | AR95: 150.05733 | AS95: 181.0672 | AT95: 224.93251 | AU95: 180.33451 | AV95: 167.83176 | AW95: 166.53103 | AX95: 178.60709 | AY95: 152.53329 | AZ95: 160.67352 | BA95: 168.0669 | BB95: 171.0669 | BC95: 170.42745 | BD95: 173.65795 | BE95: 174.05218 | BF95: 176.57687 | BG95: 173.3502 | BH95: 162.95446 | BI95: 168.22078 | BJ95: 168.22078 | BK95: 168.22078 | BL95: 168.22078 | BM95: 168.22078 | BN95: 168.22078 | BO95: 168.22078 | BP95: 168.22078
A96: Swine (Pork) | B96: IMF.RES.GAS:GAS_LIVE | C96: G001.PZPIPORK.Q | E96: 85.073643 | F96: 83.625591 | G96: 83.205706 | H96: 79.210595 | I96: 79.740835 | J96: 88.404242 | K96: 95.432049 | L96: 82.608293 | M96: 92.805869 | N96: 115.35929 | O96: 112.79908 | P96: 90.29134 | Q96: 65.512859 | R96: 71.884394 | S96: 73.780959 | T96: 60.459364 | U96: 60.296233 | V96: 72.618687 | W96: 66.62745 | X96: 50.095873 | Y96: 67.178547 | Z96: 69.972667 | AA96: 75.194761 | AB96: 60.840243 | AC96: 66.396424 | AD96: 64.929192 | AE96: 59.50419 | AF96: 57.851111 | AG96: 54.854227 | AH96: 78.351106 | AI96: 67.831 | AJ96: 58.33069 | AK96: 57.439409 | AL96: 52.662833 | AM96: 54.730996 | AN96: 68.666606 | AO96: 75.247 | AP96: 109.31063 | AQ96: 102.96292 | AR96: 76.165556 | AS96: 88.48991 | AT96: 102.16797 | AU96: 108.41144 | AV96: 85.781746 | AW96: 74.131665 | AX96: 76.676076 | AY96: 93.71092 | AZ96: 72.431191 | BA96: 74.308773 | BB96: 88.533812 | BC96: 86.198901 | BD96: 83.884181 | BE96: 84.564135 | BF96: 90.984431 | BG96: 104.11866 | BH96: 86.136921 | BI96: 80.327133 | BJ96: 100.06012 | BK96: 106.99833 | BL96: 84.080481 | BM96: 81.203662 | BN96: 88.859063 | BO96: 88.859063 | BP96: 88.859063
A97: Seafood
A98: Shrimp | B98: IMF.RES.GAS:GAS_LIVE | C98: G001.PZPISHRI.Q | E98: 7.980464 | F98: 7.5840873 | G98: 7.1676383 | H98: 7.2382738 | I98: 7.5018427 | J98: 8.0326097 | K98: 8.4410448 | L98: 10.03873 | M98: 10.536293 | N98: 10.620073 | O98: 9.631186 | P98: 9.7771852 | Q98: 9.0437988 | R98: 8.5300393 | S98: 7.8185728 | T98: 8.3648533 | U98: 8.1504877 | V98: 8.6391817 | W98: 8.4635065 | X98: 8.9482685 | Y98: 8.6688128 | Z98: 8.9181048 | AA98: 9.304144 | AB98: 9.141216 | AC98: 8.8951493 | AD98: 8.4557958 | AE98: 8.3537057 | AF98: 8.18507 | AG98: 7.989106 | AH98: 7.6936057 | AI98: 7.7349365 | AJ98: 7.9052042 | AK98: 7.6900745 | AL98: 7.4834675 | AM98: 6.917247 | AN98: 7.2305089 | AO98: 7.1971011 | AP98: 7.2998598 | AQ98: 8.0472061 | AR98: 8.4039121 | AS98: 8.2865143 | AT98: 7.8210746 | AU98: 8.0994884 | AV98: 8.0093983 | AW98: 7.0321978 | AX98: 7.011126 | AY98: 6.8543664 | AZ98: 6.9385846 | BA98: 7.1699 | BB98: 7.0784873 | BC98: 7.3287904 | BD98: 8.1244021 | BE98: 7.3217934 | BF98: 6.7848117 | BG98: 6.9013377 | BH98: 6.9563278 | BI98: 7.2749658 | BJ98: 7.2749658 | BK98: 7.2749658 | BL98: 7.2749658 | BM98: 7.2749658 | BN98: 7.2749658 | BO98: 7.2749658 | BP98: 7.2749658
A99: Fish | B99: IMF.RES.GAS:GAS_LIVE | C99: G001.PZPISFI.Q | E99: 4.7244677 | F99: 4.8346701 | G99: 4.6331094 | H99: 4.7861947 | I99: 6.3842642 | J99: 7.1017296 | K99: 6.708221 | L99: 6.6687592 | M99: 7.7624504 | N99: 6.9409212 | O99: 5.9383941 | P99: 5.7591108 | Q99: 5.5596483 | R99: 5.1310985 | S99: 5.2535135 | T99: 5.2780695 | U99: 6.5007515 | V99: 7.3472233 | W99: 7.2451561 | X99: 7.4630151 | Y99: 7.9044343 | Z99: 7.8558859 | AA99: 7.5072795 | AB99: 6.5091667 | AC99: 7.6590845 | AD99: 8.5884141 | AE99: 6.9963512 | AF99: 6.8536203 | AG99: 7.4069933 | AH99: 7.542924 | AI99: 6.2770617 | AJ99: 6.4558495 | AK99: 7.321075 | AL99: 6.1007287 | AM99: 5.6357406 | AN99: 5.3419959 | AO99: 6.3665026 | AP99: 7.5593622 | AQ99: 6.6459098 | AR99: 6.8851909 | AS99: 8.7563185 | AT99: 10.281035 | AU99: 7.4816146 | AV99: 7.1752496 | AW99: 9.989106 | AX99: 10.06582 | AY99: 8.0051544 | AZ99: 7.7697034 | BA99: 10.209923 | BB99: 10.240012 | BC99: 7.2748087 | BD99: 7.3763127 | BE99: 8.7634146 | BF99: 7.6530228 | BG99: 6.7392068 | BH99: 8.1323491 | BI99: 9.2098414 | BJ99: 10.663557 | BK99: 7.8701421 | BL99: 7.6839145 | BM99: 9.8538714 | BN99: 10.202036 | BO99: 8.380244 | BP99: 7.7324956
A100: Sugar
A101: Sugar, U.S. | B101: IMF.RES.GAS:GAS_LIVE | C101: G001.PZPISUG_Type3.Q | E101: 34.274758 | F101: 30.396968 | G101: 27.767678 | H101: 23.142314 | I101: 21.991524 | J101: 20.21603 | K101: 21.134424 | L101: 21.516169 | M101: 22.395439 | N101: 25.25619 | O101: 26.459069 | P101: 25.338384 | Q101: 24.75378 | R101: 24.622214 | S101: 24.535837 | T101: 25.398227 | U101: 25.85321 | V101: 27.588723 | W101: 28.236018 | X101: 28.848413 | Y101: 29.979466 | Z101: 28.310375 | AA101: 26.251036 | AB101: 27.0917 | AC101: 25.660902 | AD101: 25.008968 | AE101: 25.533274 | AF101: 25.156425 | AG101: 25.852899 | AH101: 26.531652 | AI101: 25.695212 | AJ101: 26.393942 | AK101: 26.530178 | AL101: 25.965579 | AM101: 26.966537 | AN101: 28.360258 | AO101: 29.630153 | AP101: 32.252273 | AQ101: 35.691154 | AR101: 37.006991 | AS101: 35.729878 | AT101: 36.410411 | AU101: 35.102213 | AV101: 35.698398 | AW101: 37.084097 | AX101: 41.64636 | AY101: 40.559406 | AZ101: 42.976176 | BA101: 40.490573 | BB101: 38.249482 | BC101: 36.589778 | BD101: 37.559159 | BE101: 36.954267 | BF101: 36.497633 | BG101: 36.382855 | BH101: 33.843258 | BI101: 31.778182 | BJ101: 32.36 | BK101: 32.81 | BL101: 33.01 | BM101: 33.31 | BN101: 33.31 | BO101: 33.41 | BP101: 33.51
A102: Sugar, World | B102: IMF.RES.GAS:GAS_LIVE | C102: G001.PZPISUG_Type2.Q | E102: 23.741561 | F102: 20.94685 | G102: 21.174921 | H102: 19.634676 | I102: 18.464203 | J102: 17.348212 | K102: 17.319818 | L102: 17.701957 | M102: 16.826992 | N102: 18.232381 | O102: 17.666501 | P102: 15.782291 | Q102: 14.138505 | R102: 12.57603 | S102: 11.563514 | T102: 14.582515 | U102: 14.345169 | V102: 17.006551 | W102: 20.351243 | X102: 20.871746 | Y102: 19.667618 | Z102: 15.178644 | AA102: 13.948696 | AB102: 14.543662 | AC102: 13.45929 | AD102: 11.904488 | AE102: 10.798047 | AF102: 12.843555 | AG102: 12.69457 | AH102: 12.266738 | AI102: 11.61403 | AJ102: 12.826543 | AK102: 13.680906 | AL102: 10.840362 | AM102: 12.385844 | AN102: 14.629652 | AO102: 16.240831 | AP102: 16.885014 | AQ102: 18.787561 | AR102: 19.510837 | AS102: 18.590661 | AT102: 19.258016 | AU102: 18.196173 | AV102: 19.257287 | AW102: 20.769474 | AX102: 25.024613 | AY102: 24.921649 | AZ102: 25.452965 | BA102: 22.528578 | BB102: 19.538779 | BC102: 19.465349 | BD102: 21.440758 | BE102: 19.390563 | BF102: 17.276457 | BG102: 16.181435 | BH102: 15.038899 | BI102: 14.468637 | BJ102: 13.84 | BK102: 13.82 | BL102: 14.15 | BM102: 14.88 | BN102: 14.72 | BO102: 14.72 | BP102: 14.97
A103: Vegetable Oil Index
A104: Olive Oil | B104: IMF.RES.GAS:GAS_LIVE | C104: G001.PZPIOLOIL.Q | E104: 2807.2369 | F104: 2751.4781 | G104: 3052.3198 | H104: 3466.4353 | I104: 4093.9358 | J104: 3936.0941 | K104: 3857.88 | L104: 3689.921 | M104: 3576.2308 | N104: 3581.7246 | O104: 3927.1543 | P104: 4037.1142 | Q104: 4077.2264 | R104: 4216.4025 | S104: 4840.13 | T104: 4037.5806 | U104: 4085.708 | V104: 3897.5026 | W104: 3982.3331 | X104: 3948.3214 | Y104: 4336.866 | Z104: 4552.2364 | AA104: 4653.9037 | AB104: 4576.181 | AC104: 4656.9687 | AD104: 3789.2621 | AE104: 3613.2868 | AF104: 3587.3983 | AG104: 3441.8765 | AH104: 3188.1044 | AI104: 3119.5751 | AJ104: 2915.7778 | AK104: 2740.5052 | AL104: 2790.5682 | AM104: 2985.9541 | AN104: 1996.3406 | AO104: 3766.7749 | AP104: 4337.2238 | AQ104: 4409.0968 | AR104: 4225.9569 | AS104: 4293.9064 | AT104: 4137.913 | AU104: 4209.5098 | AV104: 5238.2114 | AW104: 5926.2831 | AX104: 6744.318 | AY104: 8999.5114 | AZ104: 9168.3576 | BA104: 10088.136 | BB104: 9118.3745 | BC104: 8827.9659 | BD104: 7406.8936 | BE104: 5339.885 | BF104: 5099.4206 | BG104: 5488.4505 | BH104: 5930.4214 | BI104: 6092.9287 | BJ104: 6092.9287 | BK104: 6092.9287 | BL104: 6092.9287 | BM104: 6092.9287 | BN104: 6092.9287 | BO104: 6092.9287 | BP104: 6092.9287
A105: Palm Oil | B105: IMF.RES.GAS:GAS_LIVE | C105: G001.PZPIPOIL.Q | E105: 1057.9887 | F105: 1038.7335 | G105: 920.89585 | H105: 741.71885 | I105: 780.26392 | J105: 760.96212 | K105: 726.16326 | L105: 789.39879 | M105: 813.68688 | N105: 794.69475 | O105: 695.91015 | P105: 653.34167 | Q105: 627.87674 | R105: 599.86298 | S105: 514.61568 | T105: 518.00428 | U105: 586.86264 | V105: 647.79777 | W105: 646.9913 | X105: 677.73416 | Y105: 698.86056 | Z105: 633.29996 | AA105: 633.53642 | AB105: 625.50776 | AC105: 633.53338 | AD105: 602.30683 | AE105: 532.47138 | AF105: 471.12493 | AG105: 511.37343 | AH105: 483.33665 | AI105: 493.89327 | AJ105: 607.2021 | AK105: 642.24686 | AL105: 530.05997 | AM105: 664.17344 | AN105: 827.74597 | AO105: 967.0397 | AP105: 1020.6137 | AQ105: 1064.6609 | AR105: 1241.7592 | AS105: 1468.1271 | AT105: 1512.1604 | AU105: 874.56815 | AV105: 853.14775 | AW105: 905.20119 | AX105: 846.1789 | AY105: 819.76578 | AZ105: 782.27108 | BA105: 846.49912 | BB105: 853.75601 | BC105: 897.13431 | BD105: 1098.234 | BE105: 1051.5034 | BF105: 939.48974 | BG105: 997.31792 | BH105: 998.85422 | BI105: 1034.7602 | BJ105: 1066.1262 | BK105: 1060.3834 | BL105: 1054.9785 | BM105: 1049.0246 | BN105: 1039.2703 | BO105: 1030.5295 | BP105: 1029.3894
A106: Rapeseed Oil | B106: IMF.RES.GAS:GAS_LIVE | C106: G001.PZPIROIL.Q | E106: 1279.6928 | F106: 1241.1237 | G106: 1232.999 | H106: 1202.5099 | I106: 1196.0494 | J106: 1121.4098 | K106: 993.20228 | L106: 1012.7862 | M106: 980.28261 | N106: 963.14079 | O106: 849.64812 | P106: 824.40156 | Q106: 755.06893 | R106: 772.60517 | S106: 772.68943 | T106: 798.0721 | U106: 774.73811 | V106: 797.74952 | W106: 810.62349 | X106: 904.69422 | Y106: 876.53961 | Z106: 829.03134 | AA106: 877.22013 | AB106: 905.00902 | AC106: 820.13265 | AD106: 806.05363 | AE106: 845.52222 | AF106: 846.81405 | AG106: 820.02874 | AH106: 815.59161 | AI106: 874.6471 | AJ106: 904.38836 | AK106: 874.49006 | AL106: 800.07855 | AM106: 917.93646 | AN106: 1019.9515 | AO106: 1218.2378 | AP106: 1507.9512 | AQ106: 1518.4507 | AR106: 1795.54 | AS106: 1908.5976 | AT106: 2186.8815 | AU106: 1641.7825 | AV106: 1315.9206 | AW106: 1119.9972 | AX106: 948.09055 | AY106: 1051.4318 | AZ106: 1036.3759 | BA106: 951.6234 | BB106: 1071.7197 | BC106: 1062.2852 | BD106: 1168.9857 | BE106: 1137.8527 | BF106: 1235.0265 | BG106: 1243.4113 | BH106: 1280.5175 | BI106: 1224.5046 | BJ106: 1224.5046 | BK106: 1224.5046 | BL106: 1224.5046 | BM106: 1224.5046 | BN106: 1224.5046 | BO106: 1224.5046 | BP106: 1224.5046
A107: Soybean | B107: IMF.RES.GAS:GAS_LIVE | C107: G001.PZPISOYB.Q | E107: 466.52641 | F107: 524.22542 | G107: 615.84723 | H107: 544.44829 | I107: 532.83484 | J107: 540.04888 | K107: 516.54502 | L107: 479.38637 | M107: 498.30075 | N107: 540.40797 | O107: 421.68956 | P107: 370.8558 | Q107: 363.9423 | R107: 354.56609 | S107: 347.6414 | T107: 323.27246 | U107: 323.42309 | V107: 387.84785 | W107: 372.20683 | X107: 367.34951 | Y107: 375.51922 | Z107: 345.9234 | AA107: 354.90793 | AB107: 358.94626 | AC107: 369.99832 | AD107: 365.35824 | AE107: 311.88454 | AF107: 322.87189 | AG107: 332.50562 | AH107: 318.72669 | AI107: 320.84989 | AJ107: 335.9261 | AK107: 327.28139 | AL107: 312.65627 | AM107: 342.63374 | AN107: 416.93856 | AO107: 510.6696 | AP107: 550.58068 | AQ107: 499.01722 | AR107: 460.13611 | AS107: 571.77995 | AT107: 618.81985 | AU107: 561.79254 | AV107: 526.37471 | AW107: 554.67466 | AX107: 527.17167 | AY107: 517.472 | AZ107: 482.58893 | BA107: 438.62678 | BB107: 435.46264 | BC107: 381.66904 | BD107: 365.08153 | BE107: 376.42706 | BF107: 383.07896 | BG107: 372.10214 | BH107: 391.0978 | BI107: 396.00652 | BJ107: 413.73369 | BK107: 411.7434 | BL107: 403.62918 | BM107: 407.25762 | BN107: 408.77329 | BO107: 406.56867 | BP107: 399.67923
A108: Soybean Oil | B108: IMF.RES.GAS:GAS_LIVE | C108: G001.PZPISOIL.Q | E108: 1166.1752 | F108: 1154.9851 | G108: 1192.3594 | H108: 1093.4877 | I108: 1119.2359 | J108: 1076.0396 | K108: 960.02483 | L108: 889.15009 | M108: 877.85058 | N108: 899.73342 | O108: 757.14493 | P108: 716.11235 | Q108: 696.41664 | R108: 715.40013 | S108: 638.26183 | T108: 638.58088 | U108: 686.88707 | V108: 719.72269 | W108: 701.40394 | X108: 776.64213 | Y108: 746.06887 | Z108: 704.73192 | AA108: 747.00577 | AB108: 743.30984 | AC108: 712.75843 | AD108: 677.33259 | AE108: 621.14276 | AF108: 623.2895 | AG108: 649.45361 | AH108: 613.71365 | AI108: 628.92598 | AJ108: 689.20368 | AK108: 662.60793 | AL108: 592.65492 | AM108: 695.05863 | AN108: 809.71183 | AO108: 1061.3071 | AP108: 1397.0917 | AQ108: 1361.5076 | AR108: 1289.8635 | AS108: 1495.2771 | AT108: 1754.9671 | AU108: 1466.4093 | AV108: 1547.6757 | AW108: 1323.6341 | AX108: 1172.9858 | AY108: 1447.3151 | AZ108: 1147.2058 | BA108: 1030.833 | BB108: 985.38917 | BC108: 952.51021 | BD108: 946.49556 | BE108: 971.2624 | BF108: 1097.2749 | BG108: 1146.2221 | BH108: 1092.3419 | BI108: 1120.2861 | BJ108: 1238.3379 | BK108: 1235.3984 | BL108: 1216.7325 | BM108: 1211.9926 | BN108: 1206.8117 | BO108: 1193.6575 | BP108: 1174.514
A109: Soybean Meal | B109: IMF.RES.GAS:GAS_LIVE | C109: G001.PZPISMEA.Q | E109: 372.4426 | F109: 454.68317 | G109: 565.94882 | H109: 500.06319 | I109: 464.64068 | J109: 475.55631 | K109: 496.5059 | L109: 472.49423 | M109: 493.26543 | N109: 531.89495 | O109: 435.98234 | P109: 406.72021 | Q109: 372.71763 | R109: 348.02795 | S109: 369.33529 | T109: 320.80633 | U109: 294.90893 | V109: 392.87147 | W109: 370.00296 | X109: 342.88706 | Y109: 364.32165 | Z109: 338.01699 | AA109: 341.08819 | AB109: 351.02784 | AC109: 390.07685 | AD109: 408.30828 | AE109: 353.81454 | AF109: 341.04927 | AG109: 340.13017 | AH109: 338.71487 | AI109: 327.75607 | AJ109: 331.64154 | AK109: 330.02684 | AL109: 317.30261 | AM109: 331.32066 | AN109: 425.85309 | AO109: 470.41602 | AP109: 440.87935 | AQ109: 387.06031 | AR109: 389.6245 | AS109: 494.15474 | AT109: 480.56804 | AU109: 507.31307 | AV109: 469.54406 | AW109: 534.04558 | AX109: 468.08484 | AY109: 463.10175 | AZ109: 464.57713 | BA109: 384.15161 | BB109: 393.68307 | BC109: 367.91943 | BD109: 330.85856 | BE109: 328.8561 | BF109: 318.01467 | BG109: 284.21388 | BH109: 307.48199 | BI109: 329.45574 | BJ109: 338.29934 | BK109: 343.88439 | BL109: 344.74786 | BM109: 347.94457 | BN109: 349.76338 | BO109: 351.1229 | BP109: 348.16503
A110: Sunflower Seed Oil | B110: IMF.RES.GAS:GAS_LIVE | C110: G001.PZPISUNO.Q | E110: 1478.4697 | F110: 1441 | G110: 1546.0838 | H110: 1492.3648 | I110: 1493.7997 | J110: 1459.4241 | K110: 1228.7474 | L110: 1182.9007 | M110: 1133.0808 | N110: 1121.4796 | O110: 1012.4719 | P110: 1054.2164 | Q110: 973.98955 | R110: 1062.2545 | S110: 1010.3989 | T110: 1042.0694 | U110: 1024.5454 | V110: 1028.6489 | W110: 982.03252 | X110: 1003.7134 | Y110: 961.53802 | Z110: 942.00866 | AA110: 963.86972 | AB110: 944.71187 | AC110: 944.68245 | AD110: 936.1942 | AE110: 892.94358 | AF110: 829.40477 | AG110: 838.53985 | AH110: 866.00077 | AI110: 908.62914 | AJ110: 920.87621 | AK110: 920.29893 | AL110: 914.08022 | AM110: 1065.3648 | AN110: 1326.2803 | AO110: 1725.6207 | AP110: 1814.2157 | AQ110: 1613.3924 | AR110: 1722.4051 | AS110: 2007.017 | AT110: 2396.6155 | AU110: 1747.1882 | AV110: 1585.8278 | AW110: 1399.7939 | AX110: 1168.7356 | AY110: 1173.3153 | AZ110: 1130.4295 | BA110: 1128.8372 | BB110: 1208.3381 | BC110: 1276.7821 | BD110: 1466.7037 | BE110: 1460.5929 | BF110: 1458.3714 | BG110: 1534.2132 | BH110: 1649.4847 | BI110: 1786.5125 | BJ110: 1786.5125 | BK110: 1786.5125 | BL110: 1786.5125 | BM110: 1786.5125 | BN110: 1786.5125 | BO110: 1786.5125 | BP110: 1786.5125
A111: Other Food
A112: Bananas | B112: IMF.RES.GAS:GAS_LIVE | C112: G001.PZPIBA.Q | E112: 1046.5149 | F112: 980.36749 | G112: 962.84731 | H112: 947.39691 | I112: 932.60164 | J112: 910.61044 | K112: 934.20391 | L112: 928.12151 | M112: 947.13348 | N112: 929.19129 | O112: 939.27419 | P112: 911.90248 | Q112: 974.80329 | R112: 978.3709 | S112: 948.92162 | T112: 932.73898 | U112: 1028.1667 | V112: 992.96037 | W112: 1023.1683 | X112: 965.42577 | Y112: 1029.792 | Z112: 1081.5518 | AA112: 1098.0663 | AB112: 1087.4929 | AC112: 1185.7784 | AD112: 1155.698 | AE112: 1121.4187 | AF112: 1128.1022 | AG112: 1156.0993 | AH112: 1142.4326 | AI112: 1134.8987 | AJ112: 1136.4091 | AK112: 1185.5979 | AL112: 1291.0079 | AM112: 1252.5438 | AN112: 1139.6483 | AO112: 1231.529 | AP112: 1229.2817 | AQ112: 1218.3995 | AR112: 1154.2815 | AS112: 1269.2541 | AT112: 1454.8205 | AU112: 1604.6433 | AV112: 1641.5736 | AW112: 1658.6096 | AX112: 1622.537 | AY112: 1560.7735 | AZ112: 1557.4251 | BA112: 1612.9813 | BB112: 1376.1747 | BC112: 1032.4531 | BD112: 921.6786 | BE112: 1186.9445 | BF112: 1050.234 | BG112: 1014.7184 | BH112: 1149.8118 | BI112: 1207.9357 | BJ112: 1207.9357 | BK112: 1207.9357 | BL112: 1207.9357 | BM112: 1207.9357 | BN112: 1207.9357 | BO112: 1207.9357 | BP112: 1207.9357
A113: Citrus Fruit + Orange Juice | B113: IMF.RES.GAS:GAS_LIVE | C113: G001.PZPIORA.Q | E113: 1.9000424 | F113: 1.2656649 | G113: 1.2214046 | H113: 1.1959532 | I113: 1.2415062 | J113: 1.4479864 | K113: 1.3630985 | L113: 1.3216328 | M113: 1.4696571 | N113: 1.5856984 | O113: 1.463368 | P113: 1.398488 | Q113: 1.3204709 | R113: 1.1662267 | S113: 1.232768 | T113: 1.3850098 | U113: 1.2972169 | V113: 1.4833647 | W113: 1.8779822 | X113: 2.073754 | Y113: 1.7454336 | Z113: 1.4708038 | AA113: 1.3873707 | AB113: 1.5469674 | AC113: 1.4285698 | AD113: 1.5628698 | AE113: 1.5965547 | AF113: 1.3849085 | AG113: 1.2023254 | AH113: 1.0325509 | AI113: 1.0048576 | AJ113: 0.98062478 | AK113: 1.0052415 | AL113: 1.182359 | AM113: 1.1851216 | AN113: 1.1932902 | AO113: 1.1403883 | AP113: 1.1519455 | AQ113: 1.3558835 | AR113: 1.2799138 | AS113: 1.4485163 | AT113: 1.7542392 | AU113: 1.7334455 | AV113: 2.06775 | AW113: 2.3590237 | AX113: 2.7080691 | AY113: 3.1551039 | AZ113: 3.8131739 | BA113: 3.5123485 | BB113: 4.0958691 | BC113: 4.642595 | BD113: 5.0159126 | BE113: 3.7353499 | BF113: 2.645974 | BG113: 2.5608044 | BH113: 1.7840997 | BI113: 1.8057349 | BJ113: 1.6175 | BK113: 1.6565 | BL113: 1.693 | BM113: 1.7175 | BN113: 1.695 | BO113: 1.6725 | BP113: 1.685
A114: Dairy Products (Milk) | B114: IMF.RES.GAS:GAS_LIVE | C114: G001.PZPIMILK.Q | E114: 16.297549 | F114: 15.522146 | G114: 17.735562 | H114: 20.166522 | I114: 17.404558 | J114: 18.051618 | K114: 17.833718 | L114: 18.690986 | M114: 22.231504 | N114: 22.706617 | O114: 22.552498 | P114: 21.356501 | Q114: 15.737468 | R114: 16.234894 | S114: 16.206632 | T114: 15.172002 | U114: 13.768606 | V114: 13.322626 | W114: 16.186315 | X114: 16.270407 | Y114: 16.501151 | Z114: 15.691541 | AA114: 16.087533 | AB114: 16.243732 | AC114: 13.929352 | AD114: 14.990504 | AE114: 15.23781 | AF114: 14.680395 | AG114: 14.387008 | AH114: 16.154992 | AI114: 17.659166 | AJ114: 19.480624 | AK114: 16.824972 | AL114: 15.081082 | AM114: 20.316897 | AN114: 20.08443 | AO114: 16.037762 | AP114: 16.17999 | AQ114: 18.171031 | AR114: 20.821799 | AS114: 26.763308 | AT114: 28.614838 | AU114: 28.30439 | AV114: 26.392785 | AW114: 21.647013 | AX114: 20.421598 | AY114: 21.017144 | AZ114: 23.012227 | BA114: 22.359116 | BB114: 23.240938 | BC114: 24.609857 | BD114: 23.727896 | BE114: 22.411436 | BF114: 20.517324 | BG114: 20.585656 | BH114: 15.769776 | BI114: 15.775948 | BJ114: 17.813333 | BK114: 17.98 | BL114: 17.913333 | BM114: 17.043333 | BN114: 17.186667 | BO114: 17.393333 | BP114: 17.24
...

Sheet Sheet1
