Workbook
Name Products: #REF!

Sheet Table A Q
B1: Table A
B2: Macro-economic aggregates
C3: 2024 | D3: 2006Q1 | E3: 2006Q2 | F3: 2006Q3 | G3: 2006Q4 | H3: 2007Q1 | I3: 2007Q2 | J3: 2007Q3 | K3: 2007Q4 | L3: 2008Q1 | M3: 2008Q2 | N3: 2008Q3 | O3: 2008Q4 | P3: 2009Q1 | Q3: 2009Q2 | R3: 2009Q3 | S3: 2009Q4 | T3: 2010Q1 | U3: 2010Q2 | V3: 2010Q3 | W3: 2010Q4 | X3: 2011Q1 | Y3: 2011Q2 | Z3: 2011Q3 | AA3: 2011Q4 | AB3: 2012Q1 | AC3: 2012Q2 | AD3: 2012Q3 | AE3: 2012Q4 | AF3: 2013Q1 | AG3: 2013Q2 | AH3: 2013Q3 | AI3: 2013Q4 | AJ3: 2014Q1 | AK3: 2014Q2 | AL3: 2014Q3 | AM3: 2014Q4 | AN3: 2015Q1 | AO3: 2015Q2 | AP3: 2015Q3 | AQ3: 2015Q4 | AR3: 2016Q1 | AS3: 2016Q2 | AT3: 2016Q3 | AU3: 2016Q4 | AV3: 2017Q1 | AW3: 2017Q2 | AX3: 2017Q3 | AY3: 2017Q4 | AZ3: 2018Q1 | BA3: 2018Q2 | BB3: 2018Q3 | BC3: 2018Q4 | BD3: 2019Q1 | BE3: 2019Q2 | BF3: 2019Q3 | BG3: 2019Q4 | BH3: 2020Q1 | BI3: 2020Q2 | BJ3: 2020Q3 | BK3: 2020Q4 | BL3: 2021Q1 | BM3: 2021Q2 | BN3: 2021Q3 | BO3: 2021Q4 | BP3: 2022Q1 | BQ3: 2022Q2 | BR3: 2022Q3 | BS3: 2022Q4 | BT3: 2023Q1 | BU3: 2023Q2 | BV3: 2023Q3 | BW3: 2023Q4 | BX3: 2024Q1 | BY3: 2024Q2 | BZ3: 2024Q3 | CA3: 2024Q4 | CB3: 2025Q1 | CC3: 2025Q2 | CD3: 2025Q3
B5: Gross Domestic Product (Frw billions)
B6: GDP at current prices | C6: 19918 | D6: 401 | E6: 452 | F6: 479 | G6: 499 | H6: 506 | I6: 547 | J6: 574 | K6: 599 | L6: 608 | M6: 687 | N6: 750 | O6: 788 | P6: 786 | Q6: 774 | R6: 809 | S6: 855 | T6: 853 | U6: 858 | V6: 906 | W6: 955 | X6: 963 | Y6: 1000 | Z6: 1074 | AA6: 1096 | AB6: 1114 | AC6: 1144 | AD6: 1210 | AE6: 1234 | AF6: 1214 | AG6: 1253 | AH6: 1261 | AI6: 1329 | AJ6: 1355 | AK6: 1394 | AL6: 1437 | AM6: 1436 | AN6: 1465 | AO6: 1500 | AP6: 1568 | AQ6: 1617 | AR6: 1661 | AS6: 1711 | AT6: 1696 | AU6: 1778 | AV6: 1846 | AW6: 1917 | AX6: 1944 | AY6: 1988 | AZ6: 2016 | BA6: 2132 | BB6: 1884 | BC6: 2277 | BD6: 2160 | BE6: 2468 | BF6: 2195 | BG6: 2637 | BH6: 2395 | BI6: 2413 | BJ6: 2221 | BK6: 2862 | BL6: 2574 | BM6: 2841 | BN6: 2598 | BO6: 3112 | BP6: 3101 | BQ6: 3549 | BR6: 3304 | BS6: 4210 | BT6: 4031 | BU6: 4255 | BV6: 3875 | BW6: 5016 | BX6: 4514 | BY6: 4965 | BZ6: 4659 | CA6: 5780 | CB6: 5276 | CC6: 5799 | CD6: 5525
B7: Growth rate | D7: 0 | E7: 0 | F7: 0 | G7: 0 | H7: 0.262 | I7: 0.211 | J7: 0.198 | K7: 0.2 | L7: 0.2 | M7: 0.256 | N7: 0.307 | O7: 0.316 | P7: 0.294 | Q7: 0.127 | R7: 0.079 | S7: 0.085 | T7: 0.085 | U7: 0.108 | V7: 0.12 | W7: 0.117 | X7: 0.129 | Y7: 0.165 | Z7: 0.186 | AA7: 0.147 | AB7: 0.156 | AC7: 0.144 | AD7: 0.126 | AE7: 0.127 | AF7: 0.089 | AG7: 0.096 | AH7: 0.042 | AI7: 0.076 | AJ7: 0.117 | AK7: 0.113 | AL7: 0.14 | AM7: 0.08 | AN7: 0.081 | AO7: 0.076 | AP7: 0.091 | AQ7: 0.127 | AR7: 0.133 | AS7: 0.14 | AT7: 0.082 | AU7: 0.099 | AV7: 0.111 | AW7: 0.12 | AX7: 0.146 | AY7: 0.118 | AZ7: 0.092 | BA7: 0.112 | BB7: -0.031 | BC7: 0.146 | BD7: 0.072 | BE7: 0.158 | BF7: 0.165 | BG7: 0.158 | BH7: 0.109 | BI7: -0.022 | BJ7: 0.012 | BK7: 0.085 | BL7: 0.075 | BM7: 0.177 | BN7: 0.169 | BO7: 0.087 | BP7: 0.205 | BQ7: 0.249 | BR7: 0.272 | BS7: 0.353 | BT7: 0.3 | BU7: 0.199 | BV7: 0.173 | BW7: 0.191 | BX7: 0.12 | BY7: 0.167 | BZ7: 0.202 | CA7: 0.152 | CB7: 0.169 | CC7: 0.168 | CD7: 0.186
B8: GDP at constant 2024 prices | C8: 19918 | D8: 813 | E8: 873 | F8: 960 | G8: 961 | H8: 922 | I8: 941 | J8: 995 | K8: 1024 | L8: 1009 | M8: 1067 | N8: 1113 | O8: 1127 | P8: 1133 | Q8: 1121 | R8: 1152 | S8: 1180 | T8: 1191 | U8: 1193 | V8: 1244 | W8: 1294 | X8: 1292 | Y8: 1263 | Z8: 1373 | AA8: 1386 | AB8: 1400 | AC8: 1399 | AD8: 1471 | AE8: 1503 | AF8: 1466 | AG8: 1510 | AH8: 1509 | AI8: 1561 | AJ8: 1554 | AK8: 1578 | AL8: 1643 | AM8: 1643 | AN8: 1678 | AO8: 1724 | AP8: 1776 | AQ8: 1808 | AR8: 1858 | AS8: 1872 | AT8: 1833 | AU8: 1841 | AV8: 1862 | AW8: 1904 | AX8: 1955 | AY8: 1973 | AZ8: 3264 | BA8: 3433 | BB8: 3026 | BC8: 3804 | BD8: 3468 | BE8: 3885 | BF8: 3383 | BG8: 4046 | BH8: 3621 | BI8: 3451 | BJ8: 3258 | BK8: 4042 | BL8: 3707 | BM8: 4070 | BN8: 3454 | BO8: 4350 | BP8: 4074 | BQ8: 4541 | BR8: 3852 | BS8: 4644 | BT8: 4386 | BU8: 4659 | BV8: 4261 | BW8: 5270 | BX8: 4741 | BY8: 5137 | BZ8: 4550 | CA8: 5489 | CB8: 5052 | CC8: 5540 | CD8: 5089
B9: Growth rate | D9: 0 | E9: 0 | F9: 0 | G9: 0 | H9: 0.134 | I9: 0.077 | J9: 0.037 | K9: 0.066 | L9: 0.094 | M9: 0.134 | N9: 0.118 | O9: 0.1 | P9: 0.122 | Q9: 0.05 | R9: 0.035 | S9: 0.047 | T9: 0.052 | U9: 0.064 | V9: 0.08 | W9: 0.097 | X9: 0.084 | Y9: 0.059 | Z9: 0.103 | AA9: 0.071 | AB9: 0.084 | AC9: 0.107 | AD9: 0.072 | AE9: 0.085 | AF9: 0.047 | AG9: 0.08 | AH9: 0.026 | AI9: 0.038 | AJ9: 0.06 | AK9: 0.045 | AL9: 0.089 | AM9: 0.053 | AN9: 0.08 | AO9: 0.093 | AP9: 0.081 | AQ9: 0.1 | AR9: 0.107 | AS9: 0.085 | AT9: 0.032 | AU9: 0.018 | AV9: 0.002 | AW9: 0.017 | AX9: 0.066 | AY9: 0.072 | AZ9: 0.753 | BA9: 0.803 | BB9: 0.548 | BC9: 0.928 | BD9: 0.063 | BE9: 0.132 | BF9: 0.118 | BG9: 0.064 | BH9: 0.044 | BI9: -0.112 | BJ9: -0.037 | BK9: -0.001 | BL9: 0.024 | BM9: 0.179 | BN9: 0.06 | BO9: 0.076 | BP9: 0.099 | BQ9: 0.116 | BR9: 0.115 | BS9: 0.068 | BT9: 0.077 | BU9: 0.026 | BV9: 0.106 | BW9: 0.135 | BX9: 0.081 | BY9: 0.103 | BZ9: 0.068 | CA9: 0.042 | CB9: 0.065 | CC9: 0.078 | CD9: 0.118
B10: Implicit GDP deflator | C10: 100 | D10: 49 | E10: 52 | F10: 50 | G10: 52 | H10: 55 | I10: 58 | J10: 58 | K10: 58 | L10: 60 | M10: 64 | N10: 67 | O10: 70 | P10: 69 | Q10: 69 | R10: 70 | S10: 72 | T10: 72 | U10: 72 | V10: 73 | W10: 74 | X10: 75 | Y10: 79 | Z10: 78 | AA10: 79 | AB10: 80 | AC10: 82 | AD10: 82 | AE10: 82 | AF10: 83 | AG10: 83 | AH10: 84 | AI10: 85 | AJ10: 87 | AK10: 88 | AL10: 87 | AM10: 87 | AN10: 87 | AO10: 87 | AP10: 88 | AQ10: 89 | AR10: 89 | AS10: 91 | AT10: 93 | AU10: 97 | AV10: 99 | AW10: 101 | AX10: 99 | AY10: 101 | AZ10: 62 | BA10: 62 | BB10: 62 | BC10: 60 | BD10: 62 | BE10: 64 | BF10: 65 | BG10: 65 | BH10: 66 | BI10: 70 | BJ10: 68 | BK10: 71 | BL10: 69 | BM10: 70 | BN10: 75 | BO10: 72 | BP10: 76 | BQ10: 78 | BR10: 86 | BS10: 91 | BT10: 92 | BU10: 91 | BV10: 91 | BW10: 95 | BX10: 95 | BY10: 97 | BZ10: 102 | CA10: 105 | CB10: 104 | CC10: 105 | CD10: 109
B11: Growth rate | D11: 0 | E11: 0 | F11: 0 | G11: 0 | H11: 0.112 | I11: 0.124 | J11: 0.155 | K11: 0.126 | L11: 0.097 | M11: 0.107 | N11: 0.168 | O11: 0.196 | P11: 0.153 | Q11: 0.073 | R11: 0.042 | S11: 0.036 | T11: 0.032 | U11: 0.041 | V11: 0.037 | W11: 0.018 | X11: 0.042 | Y11: 0.1 | Z11: 0.075 | AA11: 0.072 | AB11: 0.067 | AC11: 0.033 | AD11: 0.051 | AE11: 0.039 | AF11: 0.04 | AG11: 0.015 | AH11: 0.016 | AI11: 0.037 | AJ11: 0.053 | AK11: 0.065 | AL11: 0.047 | AM11: 0.026 | AN11: 0.001 | AO11: -0.015 | AP11: 0.009 | AQ11: 0.024 | AR11: 0.024 | AS11: 0.051 | AT11: 0.048 | AU11: 0.079 | AV11: 0.109 | AW11: 0.101 | AX11: 0.075 | AY11: 0.044 | AZ11: -0.376 | BA11: -0.385 | BB11: -0.371 | BC11: -0.407 | BD11: 0.008 | BE11: 0.023 | BF11: 0.042 | BG11: 0.089 | BH11: 0.062 | BI11: 0.101 | BJ11: 0.051 | BK11: 0.086 | BL11: 0.05 | BM11: -0.002 | BN11: 0.103 | BO11: 0.01 | BP11: 0.096 | BQ11: 0.12 | BR11: 0.14 | BS11: 0.267 | BT11: 0.207 | BU11: 0.169 | BV11: 0.06 | BW11: 0.05 | BX11: 0.036 | BY11: 0.058 | BZ11: 0.126 | CA11: 0.106 | CB11: 0.097 | CC11: 0.083 | CD11: 0.06
B13: GDP per head (in '000 Frw) | C13: 1449 | D13: 45 | E13: 51 | F13: 54 | G13: 55 | H13: 56 | I13: 60 | J13: 63 | K13: 65 | L13: 65 | M13: 73 | N13: 80 | O13: 83 | P13: 83 | Q13: 81 | R13: 84 | S13: 88 | T13: 87 | U13: 87 | V13: 91 | W13: 96 | X13: 96 | Y13: 99 | Z13: 106 | AA13: 107 | AB13: 108 | AC13: 110 | AD13: 116 | AE13: 118 | AF13: 115 | AG13: 118 | AH13: 118 | AI13: 124 | AJ13: 125 | AK13: 128 | AL13: 131 | AM13: 131 | AN13: 132 | AO13: 135 | AP13: 140 | AQ13: 144 | AR13: 147 | AS13: 150 | AT13: 148 | AU13: 154 | AV13: 159 | AW13: 164 | AX13: 166 | AY13: 168 | AZ13: 170 | BA13: 178 | BB13: 157 | BC13: 188 | BD13: 178 | BE13: 202 | BF13: 178 | BG13: 213 | BH13: 192 | BI13: 193 | BJ13: 176 | BK13: 226 | BL13: 202 | BM13: 222 | BN13: 202 | BO13: 240 | BP13: 238 | BQ13: 271 | BR13: 251 | BS13: 318 | BT13: 302 | BU13: 317 | BV13: 288 | BW13: 370 | BX13: 331 | BY13: 362 | BZ13: 338 | CA13: 417 | CB13: 379 | CC13: 414 | CD13: 392
B14: GDP per head (in current US dollars) | C14: 1098 | D14: 82 | E14: 92 | F14: 97 | G14: 101 | H14: 102 | I14: 110 | J14: 114 | K14: 119 | L14: 120 | M14: 135 | N14: 146 | O14: 151 | P14: 146 | Q14: 142 | R14: 147 | S14: 155 | T14: 152 | U14: 151 | V14: 155 | W14: 162 | X14: 160 | Y14: 165 | Z14: 176 | AA14: 178 | AB14: 179 | AC14: 181 | AD14: 189 | AE14: 187 | AF14: 182 | AG14: 185 | AH14: 182 | AI14: 186 | AJ14: 186 | AK14: 188 | AL14: 192 | AM14: 189 | AN14: 189 | AO14: 189 | AP14: 193 | AQ14: 194 | AR14: 193 | AS14: 193 | AT14: 185 | AU14: 189 | AV14: 193 | AW14: 198 | AX14: 199 | AY14: 200 | AZ14: 200 | BA14: 208 | BB14: 181 | BC14: 215 | BD14: 201 | BE14: 226 | BF14: 197 | BG14: 233 | BH14: 207 | BI14: 207 | BJ14: 186 | BK14: 234 | BL14: 207 | BM14: 226 | BN14: 203 | BO14: 239 | BP14: 235 | BQ14: 265 | BR14: 243 | BS14: 301 | BT14: 278 | BU14: 282 | BV14: 242 | BW14: 299 | BX14: 259 | BY14: 279 | BZ14: 255 | CA14: 305 | CB14: 270 | CC14: 291 | CD14: 272
B16: Proportions of GDP
B17: Total final consumption expenditure
B18: Government | C18: 0.17 | D18: 0.16 | E18: 0.18 | F18: 0.16 | G18: 0.14 | H18: 0.15 | I18: 0.13 | J18: 0.14 | K18: 0.15 | L18: 0.13 | M18: 0.12 | N18: 0.12 | O18: 0.12 | P18: 0.13 | Q18: 0.14 | R18: 0.13 | S18: 0.12 | T18: 0.13 | U18: 0.14 | V18: 0.13 | W18: 0.13 | X18: 0.1 | Y18: 0.12 | Z18: 0.13 | AA18: 0.14 | AB18: 0.13 | AC18: 0.15 | AD18: 0.11 | AE18: 0.12 | AF18: 0.12 | AG18: 0.14 | AH18: 0.12 | AI18: 0.13 | AJ18: 0.14 | AK18: 0.16 | AL18: 0.14 | AM18: 0.13 | AN18: 0.14 | AO18: 0.14 | AP18: 0.14 | AQ18: 0.13 | AR18: 0.16 | AS18: 0.14 | AT18: 0.16 | AU18: 0.15 | AV18: 0.14 | AW18: 0.15 | AX18: 0.16 | AY18: 0.15 | AZ18: 0.13 | BA18: 0.13 | BB18: 0.16 | BC18: 0.13 | BD18: 0.15 | BE18: 0.17 | BF18: 0.14 | BG18: 0.13 | BH18: 0.16 | BI18: 0.15 | BJ18: 0.16 | BK18: 0.14 | BL18: 0.17 | BM18: 0.18 | BN18: 0.2 | BO18: 0.16 | BP18: 0.19 | BQ18: 0.16 | BR18: 0.22 | BS18: 0.14 | BT18: 0.17 | BU18: 0.2 | BV18: 0.18 | BW18: 0.13 | BX18: 0.16 | BY18: 0.18 | BZ18: 0.17 | CA18: 0.17 | CB18: 0.16 | CC18: 0.16 | CD18: 0.16
B19: Private | C19: 0.63 | D19: 0.82 | E19: 0.77 | F19: 0.81 | G19: 0.81 | H19: 0.76 | I19: 0.79 | J19: 0.78 | K19: 0.78 | L19: 0.82 | M19: 0.8 | N19: 0.83 | O19: 0.8 | P19: 0.8 | Q19: 0.81 | R19: 0.84 | S19: 0.84 | T19: 0.83 | U19: 0.82 | V19: 0.82 | W19: 0.81 | X19: 0.82 | Y19: 0.84 | Z19: 0.81 | AA19: 0.79 | AB19: 0.8 | AC19: 0.81 | AD19: 0.85 | AE19: 0.76 | AF19: 0.78 | AG19: 0.75 | AH19: 0.8 | AI19: 0.8 | AJ19: 0.8 | AK19: 0.76 | AL19: 0.82 | AM19: 0.77 | AN19: 0.8 | AO19: 0.82 | AP19: 0.82 | AQ19: 0.79 | AR19: 0.74 | AS19: 0.81 | AT19: 0.8 | AU19: 0.76 | AV19: 0.74 | AW19: 0.74 | AX19: 0.74 | AY19: 0.73 | AZ19: 0.75 | BA19: 0.75 | BB19: 0.68 | BC19: 0.73 | BD19: 0.71 | BE19: 0.69 | BF19: 0.64 | BG19: 0.69 | BH19: 0.74 | BI19: 0.75 | BJ19: 0.7 | BK19: 0.76 | BL19: 0.7 | BM19: 0.7 | BN19: 0.88 | BO19: 0.69 | BP19: 0.61 | BQ19: 0.65 | BR19: 0.57 | BS19: 0.66 | BT19: 0.66 | BU19: 0.65 | BV19: 0.57 | BW19: 0.7 | BX19: 0.61 | BY19: 0.64 | BZ19: 0.62 | CA19: 0.66 | CB19: 0.61 | CC19: 0.68 | CD19: 0.6
B20: Gross capital formation | C20: 0.35 | D20: 0.15 | E20: 0.16 | F20: 0.14 | G20: 0.15 | H20: 0.17 | I20: 0.16 | J20: 0.17 | K20: 0.18 | L20: 0.18 | M20: 0.23 | N20: 0.21 | O20: 0.23 | P20: 0.24 | Q20: 0.22 | R20: 0.19 | S20: 0.19 | T20: 0.22 | U20: 0.19 | V20: 0.19 | W20: 0.22 | X20: 0.23 | Y20: 0.19 | Z20: 0.2 | AA20: 0.22 | AB20: 0.23 | AC20: 0.21 | AD20: 0.23 | AE20: 0.26 | AF20: 0.25 | AG20: 0.24 | AH20: 0.23 | AI20: 0.25 | AJ20: 0.24 | AK20: 0.23 | AL20: 0.19 | AM20: 0.26 | AN20: 0.25 | AO20: 0.24 | AP20: 0.22 | AQ20: 0.26 | AR20: 0.28 | AS20: 0.26 | AT20: 0.24 | AU20: 0.26 | AV20: 0.24 | AW20: 0.23 | AX20: 0.24 | AY20: 0.24 | AZ20: 0.18 | BA20: 0.15 | BB20: 0.19 | BC20: 0.2 | BD20: 0.19 | BE20: 0.19 | BF20: 0.27 | BG20: 0.22 | BH20: 0.19 | BI20: 0.17 | BJ20: 0.2 | BK20: 0.17 | BL20: 0.35 | BM20: 0.33 | BN20: 0.39 | BO20: 0.35 | BP20: 0.37 | BQ20: 0.38 | BR20: 0.44 | BS20: 0.33 | BT20: 0.36 | BU20: 0.35 | BV20: 0.49 | BW20: 0.34 | BX20: 0.4 | BY20: 0.34 | BZ20: 0.38 | CA20: 0.29 | CB20: 0.38 | CC20: 0.3 | CD20: 0.37
B21: Resource balance | C21: -0.15 | D21: -0.12 | E21: -0.11 | F21: -0.12 | G21: -0.11 | H21: -0.07 | I21: -0.08 | J21: -0.09 | K21: -0.1 | L21: -0.13 | M21: -0.15 | N21: -0.16 | O21: -0.15 | P21: -0.17 | Q21: -0.17 | R21: -0.15 | S21: -0.15 | T21: -0.17 | U21: -0.15 | V21: -0.14 | W21: -0.16 | X21: -0.14 | Y21: -0.15 | Z21: -0.14 | AA21: -0.14 | AB21: -0.16 | AC21: -0.17 | AD21: -0.18 | AE21: -0.15 | AF21: -0.16 | AG21: -0.13 | AH21: -0.16 | AI21: -0.18 | AJ21: -0.18 | AK21: -0.16 | AL21: -0.15 | AM21: -0.16 | AN21: -0.19 | AO21: -0.2 | AP21: -0.18 | AQ21: -0.18 | AR21: -0.18 | AS21: -0.2 | AT21: -0.2 | AU21: -0.17 | AV21: -0.12 | AW21: -0.12 | AX21: -0.14 | AY21: -0.12 | AZ21: -0.06 | BA21: -0.03 | BB21: -0.03 | BC21: -0.06 | BD21: -0.05 | BE21: -0.05 | BF21: -0.05 | BG21: -0.04 | BH21: -0.09 | BI21: -0.07 | BJ21: -0.06 | BK21: -0.06 | BL21: -0.23 | BM21: -0.21 | BN21: -0.48 | BO21: -0.2 | BP21: -0.16 | BQ21: -0.18 | BR21: -0.22 | BS21: -0.13 | BT21: -0.19 | BU21: -0.2 | BV21: -0.23 | BW21: -0.17 | BX21: -0.17 | BY21: -0.16 | BZ21: -0.16 | CA21: -0.11 | CB21: -0.16 | CC21: -0.13 | CD21: -0.13
B22: Value added by
B23: Agriculture | C23: 0.21 | D23: 0.29 | E23: 0.3 | F23: 0.3 | G23: 0.31 | H23: 0.28 | I23: 0.26 | J23: 0.26 | K23: 0.25 | L23: 0.25 | M23: 0.25 | N23: 0.24 | O23: 0.24 | P23: 0.25 | Q23: 0.26 | R23: 0.25 | S23: 0.26 | T23: 0.25 | U23: 0.25 | V23: 0.24 | W23: 0.24 | X23: 0.23 | Y23: 0.25 | Z23: 0.24 | AA23: 0.24 | AB23: 0.24 | AC23: 0.25 | AD23: 0.25 | AE23: 0.25 | AF23: 0.25 | AG23: 0.26 | AH23: 0.24 | AI23: 0.25 | AJ23: 0.25 | AK23: 0.25 | AL23: 0.24 | AM23: 0.24 | AN23: 0.24 | AO23: 0.24 | AP23: 0.24 | AQ23: 0.24 | AR23: 0.25 | AS23: 0.25 | AT23: 0.25 | AU23: 0.26 | AV23: 0.27 | AW23: 0.27 | AX23: 0.25 | AY23: 0.26 | AZ23: 0.24 | BA23: 0.26 | BB23: 0.16 | BC23: 0.26 | BD23: 0.21 | BE23: 0.24 | BF23: 0.15 | BG23: 0.26 | BH23: 0.23 | BI23: 0.28 | BJ23: 0.17 | BK23: 0.28 | BL23: 0.23 | BM23: 0.24 | BN23: 0.15 | BO23: 0.22 | BP23: 0.2 | BQ23: 0.24 | BR23: 0.16 | BS23: 0.27 | BT23: 0.22 | BU23: 0.27 | BV23: 0.16 | BW23: 0.26 | BX23: 0.22 | BY23: 0.23 | BZ23: 0.15 | CA23: 0.23 | CB23: 0.2 | CC23: 0.23 | CD23: 0.15
B24: Industry | C24: 0.22 | D24: 0.15 | E24: 0.15 | F24: 0.16 | G24: 0.16 | H24: 0.17 | I24: 0.16 | J24: 0.17 | K24: 0.17 | L24: 0.16 | M24: 0.16 | N24: 0.16 | O24: 0.16 | P24: 0.16 | Q24: 0.15 | R24: 0.15 | S24: 0.16 | T24: 0.16 | U24: 0.16 | V24: 0.16 | W24: 0.17 | X24: 0.18 | Y24: 0.17 | Z24: 0.18 | AA24: 0.19 | AB24: 0.18 | AC24: 0.17 | AD24: 0.18 | AE24: 0.2 | AF24: 0.18 | AG24: 0.18 | AH24: 0.18 | AI24: 0.17 | AJ24: 0.17 | AK24: 0.17 | AL24: 0.18 | AM24: 0.18 | AN24: 0.17 | AO24: 0.17 | AP24: 0.18 | AQ24: 0.18 | AR24: 0.17 | AS24: 0.17 | AT24: 0.16 | AU24: 0.17 | AV24: 0.17 | AW24: 0.17 | AX24: 0.17 | AY24: 0.18 | AZ24: 0.18 | BA24: 0.17 | BB24: 0.18 | BC24: 0.17 | BD24: 0.19 | BE24: 0.19 | BF24: 0.21 | BG24: 0.19 | BH24: 0.2 | BI24: 0.19 | BJ24: 0.19 | BK24: 0.19 | BL24: 0.21 | BM24: 0.19 | BN24: 0.23 | BO24: 0.22 | BP24: 0.24 | BQ24: 0.22 | BR24: 0.22 | BS24: 0.2 | BT24: 0.23 | BU24: 0.2 | BV24: 0.23 | BW24: 0.21 | BX24: 0.24 | BY24: 0.22 | BZ24: 0.22 | CA24: 0.21 | CB24: 0.24 | CC24: 0.21 | CD24: 0.22
B25: Services | C25: 0.52 | D25: 0.46 | E25: 0.46 | F25: 0.45 | G25: 0.44 | H25: 0.47 | I25: 0.49 | J25: 0.48 | K25: 0.49 | L25: 0.49 | M25: 0.5 | N25: 0.5 | O25: 0.49 | P25: 0.49 | Q25: 0.49 | R25: 0.5 | S25: 0.49 | T25: 0.5 | U25: 0.51 | V25: 0.5 | W25: 0.49 | X25: 0.48 | Y25: 0.47 | Z25: 0.48 | AA25: 0.48 | AB25: 0.49 | AC25: 0.49 | AD25: 0.48 | AE25: 0.48 | AF25: 0.49 | AG25: 0.49 | AH25: 0.5 | AI25: 0.51 | AJ25: 0.49 | AK25: 0.49 | AL25: 0.49 | AM25: 0.5 | AN25: 0.51 | AO25: 0.5 | AP25: 0.5 | AQ25: 0.49 | AR25: 0.49 | AS25: 0.49 | AT25: 0.5 | AU25: 0.49 | AV25: 0.47 | AW25: 0.47 | AX25: 0.49 | AY25: 0.48 | AZ25: 0.5 | BA25: 0.48 | BB25: 0.57 | BC25: 0.49 | BD25: 0.52 | BE25: 0.49 | BF25: 0.56 | BG25: 0.48 | BH25: 0.49 | BI25: 0.46 | BJ25: 0.56 | BK25: 0.46 | BL25: 0.5 | BM25: 0.5 | BN25: 0.57 | BO25: 0.5 | BP25: 0.51 | BQ25: 0.49 | BR25: 0.57 | BS25: 0.48 | BT25: 0.5 | BU25: 0.48 | BV25: 0.56 | BW25: 0.49 | BX25: 0.49 | BY25: 0.5 | BZ25: 0.57 | CA25: 0.52 | CB25: 0.51 | CC25: 0.5 | CD25: 0.57
B26: Adjustments | C26: 0.05 | D26: 0.09 | E26: 0.09 | F26: 0.09 | G26: 0.09 | H26: 0.09 | I26: 0.09 | J26: 0.09 | K26: 0.09 | L26: 0.1 | M26: 0.09 | N26: 0.1 | O26: 0.1 | P26: 0.1 | Q26: 0.1 | R26: 0.09 | S26: 0.09 | T26: 0.09 | U26: 0.09 | V26: 0.1 | W26: 0.1 | X26: 0.11 | Y26: 0.11 | Z26: 0.1 | AA26: 0.09 | AB26: 0.09 | AC26: 0.08 | AD26: 0.08 | AE26: 0.07 | AF26: 0.07 | AG26: 0.08 | AH26: 0.08 | AI26: 0.08 | AJ26: 0.08 | AK26: 0.09 | AL26: 0.09 | AM26: 0.08 | AN26: 0.08 | AO26: 0.09 | AP26: 0.09 | AQ26: 0.09 | AR26: 0.09 | AS26: 0.09 | AT26: 0.09 | AU26: 0.08 | AV26: 0.08 | AW26: 0.09 | AX26: 0.08 | AY26: 0.09 | AZ26: 0.08 | BA26: 0.08 | BB26: 0.09 | BC26: 0.08 | BD26: 0.09 | BE26: 0.09 | BF26: 0.08 | BG26: 0.08 | BH26: 0.08 | BI26: 0.08 | BJ26: 0.09 | BK26: 0.07 | BL26: 0.06 | BM26: 0.06 | BN26: 0.05 | BO26: 0.05 | BP26: 0.05 | BQ26: 0.06 | BR26: 0.06 | BS26: 0.05 | BT26: 0.05 | BU26: 0.05 | BV26: 0.06 | BW26: 0.04 | BX26: 0.05 | BY26: 0.05 | BZ26: 0.06 | CA26: 0.04 | CB26: 0.05 | CC26: 0.05 | CD26: 0.06
B28: National income and expenditure (Frw billions)
B29: Gross Domestic Product at current prices | C29: 19918 | D29: 401 | E29: 452 | F29: 479 | G29: 499 | H29: 506 | I29: 547 | J29: 574 | K29: 599 | L29: 608 | M29: 687 | N29: 750 | O29: 788 | P29: 786 | Q29: 774 | R29: 809 | S29: 855 | T29: 853 | U29: 858 | V29: 906 | W29: 955 | X29: 963 | Y29: 1000 | Z29: 1074 | AA29: 1096 | AB29: 1114 | AC29: 1144 | AD29: 1210 | AE29: 1234 | AF29: 1214 | AG29: 1253 | AH29: 1261 | AI29: 1329 | AJ29: 1355 | AK29: 1394 | AL29: 1437 | AM29: 1436 | AN29: 1465 | AO29: 1500 | AP29: 1568 | AQ29: 1617 | AR29: 1661 | AS29: 1711 | AT29: 1696 | AU29: 1778 | AV29: 1846 | AW29: 1917 | AX29: 1944 | AY29: 1988 | AZ29: 2016 | BA29: 2132 | BB29: 1884 | BC29: 2277 | BD29: 2160 | BE29: 2468 | BF29: 2195 | BG29: 2637 | BH29: 2395 | BI29: 2413 | BJ29: 2221 | BK29: 2862 | BL29: 2574 | BM29: 2841 | BN29: 2598 | BO29: 3112 | BP29: 3101 | BQ29: 3549 | BR29: 3304 | BS29: 4210 | BT29: 4031 | BU29: 4255 | BV29: 3875 | BW29: 5016 | BX29: 4514 | BY29: 4965 | BZ29: 4659 | CA29: 5780 | CB29: 5276 | CC29: 5799 | CD29: 5525
B30: Factor income from abroad, net | C30: -450 | D30: -4 | E30: -4 | F30: -4 | G30: -4 | H30: -2 | I30: -2 | J30: -2 | K30: -2 | L30: -5 | M30: -5 | N30: -5 | O30: -5 | P30: -5 | Q30: -5 | R30: -5 | S30: -5 | T30: -7 | U30: -7 | V30: -8 | W30: -8 | X30: -9 | Y30: -9 | Z30: -9 | AA30: -9 | AB30: -16 | AC30: -16 | AD30: -16 | AE30: -16 | AF30: -21 | AG30: -21 | AH30: -21 | AI30: -22 | AJ30: -32 | AK30: -32 | AL30: -32 | AM30: -33 | AN30: -24 | AO30: -33 | AP30: -25 | AQ30: -35 | AR30: -35 | AS30: -51 | AT30: -46 | AU30: -55 | AV30: -48 | AW30: -61 | AX30: -67 | AY30: -67 | AZ30: -73 | BA30: -80 | BB30: -72 | BC30: -72 | BD30: -79 | BE30: -76 | BF30: -76 | BG30: -65 | BH30: -53 | BI30: -48 | BJ30: -48 | BK30: -39 | BL30: -48 | BM30: -40 | BN30: -45 | BO30: -41 | BP30: -70 | BQ30: -45 | BR30: -76 | BS30: -58 | BT30: -58 | BU30: -75 | BV30: -94 | BW30: -93 | BX30: -106 | BY30: -111 | BZ30: -114 | CA30: -119 | CB30: -119 | CC30: -125 | CD30: -123
B31: Gross National Income | C31: 19468 | D31: 397 | E31: 448 | F31: 475 | G31: 495 | H31: 504 | I31: 545 | J31: 571 | K31: 597 | L31: 603 | M31: 682 | N31: 745 | O31: 783 | P31: 781 | Q31: 769 | R31: 804 | S31: 850 | T31: 846 | U31: 850 | V31: 898 | W31: 948 | X31: 955 | Y31: 991 | Z31: 1066 | AA31: 1087 | AB31: 1099 | AC31: 1128 | AD31: 1194 | AE31: 1218 | AF31: 1193 | AG31: 1232 | AH31: 1240 | AI31: 1307 | AJ31: 1323 | AK31: 1362 | AL31: 1405 | AM31: 1403 | AN31: 1441 | AO31: 1467 | AP31: 1543 | AQ31: 1582 | AR31: 1626 | AS31: 1660 | AT31: 1650 | AU31: 1722 | AV31: 1798 | AW31: 1856 | AX31: 1876 | AY31: 1921 | AZ31: 1944 | BA31: 2052 | BB31: 1812 | BC31: 2205 | BD31: 2081 | BE31: 2392 | BF31: 2119 | BG31: 2572 | BH31: 2342 | BI31: 2365 | BJ31: 2174 | BK31: 2824 | BL31: 2526 | BM31: 2801 | BN31: 2552 | BO31: 3071 | BP31: 3031 | BQ31: 3504 | BR31: 3228 | BS31: 4152 | BT31: 3973 | BU31: 4180 | BV31: 3782 | BW31: 4922 | BX31: 4408 | BY31: 4854 | BZ31: 4545 | CA31: 5661 | CB31: 5157 | CC31: 5673 | CD31: 5402
B32: Current transfers, net | C32: 1028 | D32: 45 | E32: 45 | F32: 45 | G32: 45 | H32: 63 | I32: 63 | J32: 63 | K32: 63 | L32: 71 | M32: 70 | N32: 71 | O32: 72 | P32: 85 | Q32: 85 | R32: 85 | S32: 85 | T32: 83 | U32: 84 | V32: 86 | W32: 86 | X32: 119 | Y32: 120 | Z32: 120 | AA32: 120 | AB32: 96 | AC32: 96 | AD32: 97 | AE32: 99 | AF32: 117 | AG32: 119 | AH32: 120 | AI32: 123 | AJ32: 97 | AK32: 98 | AL32: 99 | AM32: 100 | AN32: 46 | AO32: 66 | AP32: 77 | AQ32: 79 | AR32: 65 | AS32: 70 | AT32: 65 | AU32: 71 | AV32: 91 | AW32: 133 | AX32: 127 | AY32: 144 | AZ32: 130 | BA32: 124 | BB32: 155 | BC32: 166 | BD32: 136 | BE32: 98 | BF32: 129 | BG32: 161 | BH32: 141 | BI32: 136 | BJ32: 149 | BK32: 160 | BL32: 175 | BM32: 195 | BN32: 176 | BO32: 203 | BP32: 239 | BQ32: 366 | BR32: 186 | BS32: 218 | BT32: 173 | BU32: 384 | BV32: 242 | BW32: 231 | BX32: 205 | BY32: 335 | BZ32: 218 | CA32: 270 | CB32: 215 | CC32: 283 | CD32: 292
B33: Gross National Disposible Income | C33: 20496 | D33: 442 | E33: 492 | F33: 520 | G33: 540 | H33: 567 | I33: 608 | J33: 635 | K33: 660 | L33: 673 | M33: 752 | N33: 816 | O33: 855 | P33: 866 | Q33: 854 | R33: 889 | S33: 936 | T33: 929 | U33: 934 | V33: 984 | W33: 1033 | X33: 1074 | Y33: 1111 | Z33: 1185 | AA33: 1207 | AB33: 1194 | AC33: 1224 | AD33: 1291 | AE33: 1318 | AF33: 1310 | AG33: 1350 | AH33: 1360 | AI33: 1430 | AJ33: 1421 | AK33: 1461 | AL33: 1504 | AM33: 1503 | AN33: 1487 | AO33: 1533 | AP33: 1620 | AQ33: 1661 | AR33: 1691 | AS33: 1730 | AT33: 1714 | AU33: 1793 | AV33: 1889 | AW33: 1990 | AX33: 2004 | AY33: 2066 | AZ33: 2074 | BA33: 2176 | BB33: 1967 | BC33: 2371 | BD33: 2217 | BE33: 2491 | BF33: 2248 | BG33: 2732 | BH33: 2483 | BI33: 2501 | BJ33: 2322 | BK33: 2984 | BL33: 2701 | BM33: 2996 | BN33: 2728 | BO33: 3274 | BP33: 3270 | BQ33: 3870 | BR33: 3414 | BS33: 4370 | BT33: 4146 | BU33: 4564 | BV33: 4024 | BW33: 5153 | BX33: 4613 | BY33: 5189 | BZ33: 4763 | CA33: 5931 | CB33: 5372 | CC33: 5957 | CD33: 5695
B34: Less Final consumption expenditure | C34: -15959 | D34: -392 | E34: -429 | F34: -469 | G34: -476 | H34: -458 | I34: -502 | J34: -530 | K34: -555 | L34: -579 | M34: -633 | N34: -715 | O34: -727 | P34: -730 | Q34: -735 | R34: -781 | S34: -819 | T34: -812 | U34: -824 | V34: -862 | W34: -904 | X34: -881 | Y34: -956 | Z34: -1012 | AA34: -1015 | AB34: -1035 | AC34: -1095 | AD34: -1158 | AE34: -1097 | AF34: -1096 | AG34: -1118 | AH34: -1163 | AI34: -1238 | AJ34: -1274 | AK34: -1292 | AL34: -1375 | AM34: -1285 | AN34: -1378 | AO34: -1437 | AP34: -1506 | AQ34: -1491 | AR34: -1499 | AS34: -1613 | AT34: -1624 | AU34: -1613 | AV34: -1634 | AW34: -1709 | AX34: -1746 | AY34: -1743 | AZ34: -1785 | BA34: -1876 | BB34: -1591 | BC34: -1962 | BD34: -1851 | BE34: -2126 | BF34: -1723 | BG34: -2168 | BH34: -2144 | BI34: -2171 | BJ34: -1911 | BK34: -2561 | BL34: -2254 | BM34: -2498 | BN34: -2826 | BO34: -2632 | BP34: -2467 | BQ34: -2857 | BR34: -2584 | BS34: -3366 | BT34: -3319 | BU34: -3584 | BV34: -2896 | BW34: -4136 | BX34: -3471 | BY34: -4060 | BZ34: -3658 | CA34: -4770 | CB34: -4071 | CC34: -4828 | CD34: -4169
B35: Gross National Saving | C35: 4537 | D35: 51 | E35: 63 | F35: 51 | G35: 64 | H35: 110 | I35: 105 | J35: 105 | K35: 105 | L35: 95 | M35: 119 | N35: 100 | O35: 128 | P35: 136 | Q35: 119 | R35: 108 | S35: 116 | T35: 116 | U35: 111 | V35: 121 | W35: 130 | X35: 194 | Y35: 155 | Z35: 173 | AA35: 192 | AB35: 159 | AC35: 129 | AD35: 133 | AE35: 221 | AF35: 214 | AG35: 232 | AH35: 197 | AI35: 192 | AJ35: 147 | AK35: 168 | AL35: 129 | AM35: 218 | AN35: 109 | AO35: 96 | AP35: 114 | AQ35: 170 | AR35: 192 | AS35: 117 | AT35: 90 | AU35: 180 | AV35: 256 | AW35: 281 | AX35: 258 | AY35: 322 | AZ35: 289 | BA35: 300 | BB35: 377 | BC35: 409 | BD35: 366 | BE35: 364 | BF35: 525 | BG35: 565 | BH35: 339 | BI35: 330 | BJ35: 411 | BK35: 423 | BL35: 447 | BM35: 498 | BN35: -98 | BO35: 642 | BP35: 802 | BQ35: 1013 | BR35: 830 | BS35: 1004 | BT35: 827 | BU35: 979 | BV35: 1128 | BW35: 1017 | BX35: 1141 | BY35: 1129 | BZ35: 1106 | CA35: 1161 | CB35: 1302 | CC35: 1129 | CD35: 1526
B36: Less Gross capital formation | C36: -6916 | D36: -59 | E36: -72 | F36: -68 | G36: -77 | H36: -87 | I36: -86 | J36: -95 | K36: -106 | L36: -110 | M36: -157 | N36: -156 | O36: -182 | P36: -191 | Q36: -171 | R36: -153 | S36: -163 | T36: -186 | U36: -167 | V36: -174 | W36: -207 | X36: -221 | Y36: -194 | Z36: -211 | AA36: -238 | AB36: -258 | AC36: -244 | AD36: -273 | AE36: -321 | AF36: -306 | AG36: -300 | AH36: -296 | AI36: -333 | AJ36: -326 | AK36: -325 | AL36: -280 | AM36: -375 | AN36: -359 | AO36: -363 | AP36: -350 | AQ36: -419 | AR36: -466 | AS36: -442 | AT36: -403 | AU36: -461 | AV36: -442 | AW36: -436 | AX36: -470 | AY36: -487 | AZ36: -356 | BA36: -329 | BB36: -356 | BC36: -448 | BD36: -420 | BE36: -472 | BF36: -585 | BG36: -572 | BH36: -462 | BI36: -416 | BJ36: -446 | BK36: -475 | BL36: -908 | BM36: -936 | BN36: -1009 | BO36: -1089 | BP36: -1139 | BQ36: -1348 | BR36: -1458 | BS36: -1404 | BT36: -1468 | BU36: -1510 | BV36: -1886 | BW36: -1725 | BX36: -1809 | BY36: -1696 | BZ36: -1754 | CA36: -1656 | CB36: -2029 | CC36: -1743 | CD36: -2064
B37: Net lending to the rest of the world | C37: -2379 | D37: -8 | E37: -8 | F37: -17 | G37: -13 | H37: 23 | I37: 19 | J37: 10 | K37: -1 | L37: -15 | M37: -38 | N37: -56 | O37: -54 | P37: -55 | Q37: -52 | R37: -44 | S37: -46 | T37: -70 | U37: -56 | V37: -52 | W37: -77 | X37: -27 | Y37: -39 | Z37: -38 | AA37: -46 | AB37: -99 | AC37: -115 | AD37: -139 | AE37: -100 | AF37: -92 | AG37: -68 | AH37: -99 | AI37: -141 | AJ37: -179 | AK37: -157 | AL37: -151 | AM37: -157 | AN37: -250 | AO37: -267 | AP37: -235 | AQ37: -249 | AR37: -274 | AS37: -325 | AT37: -313 | AU37: -281 | AV37: -186 | AW37: -155 | AX37: -211 | AY37: -164 | AZ37: -67 | BA37: -28 | BB37: 21 | BC37: -38 | BD37: -54 | BE37: -108 | BF37: -61 | BG37: -7 | BH37: -123 | BI37: -86 | BJ37: -35 | BK37: -53 | BL37: -461 | BM37: -438 | BN37: -1107 | BO37: -447 | BP37: -337 | BQ37: -335 | BR37: -628 | BS37: -401 | BT37: -641 | BU37: -531 | BV37: -759 | BW37: -708 | BX37: -668 | BY37: -568 | BZ37: -649 | CA37: -494 | CB37: -727 | CC37: -614 | CD37: -538
B39: Memorandum items
B40: Total population (millions) | D40: 8.8 | E40: 8.9 | F40: 8.9 | G40: 9 | H40: 9.1 | I40: 9.1 | J40: 9.2 | K40: 9.2 | L40: 9.3 | M40: 9.3 | N40: 9.4 | O40: 9.5 | P40: 9.5 | Q40: 9.6 | R40: 9.7 | S40: 9.7 | T40: 9.8 | U40: 9.8 | V40: 9.9 | W40: 10 | X40: 10 | Y40: 10.1 | Z40: 10.2 | AA40: 10.2 | AB40: 10.3 | AC40: 10.4 | AD40: 10.4 | AE40: 10.5 | AF40: 10.5 | AG40: 10.6 | AH40: 10.7 | AI40: 10.7 | AJ40: 10.8 | AK40: 10.9 | AL40: 10.9 | AM40: 11 | AN40: 11.1 | AO40: 11.1 | AP40: 11.2 | AQ40: 11.3 | AR40: 11.3 | AS40: 11.4 | AT40: 11.5 | AU40: 11.5 | AV40: 11.6 | AW40: 11.7 | AX40: 11.7 | AY40: 11.8 | AZ40: 11.879655 | BA40: 11.949558 | BB40: 12.019581 | BC40: 12.089721 | BD40: 12.161228 | BE40: 12.232194 | BF40: 12.303252 | BG40: 12.374397 | BH40: 12.446965 | BI40: 12.518942 | BJ40: 12.590993 | BK40: 12.663116 | BL40: 12.736698 | BM40: 12.809655 | BN40: 12.882678 | BO40: 12.955763 | BP40: 13.030536 | BQ40: 13.104459 | BR40: 13.178373 | BS40: 13.252272 | BT40: 13.327927 | BU40: 13.402665 | BV40: 13.477369 | BW40: 13.552035 | BX40: 13.628523 | BY40: 13.704026 | BZ40: 13.779473 | CA40: 13.854858 | CB40: 13.932178 | CC40: 14.008398 | CD40: 14.084523
B41: Growth rate | D41: 0 | E41: 0 | F41: 0 | G41: 0 | H41: 0.026 | I41: 0.026 | J41: 0.026 | K41: 0.026 | L41: 0.026 | M41: 0.026 | N41: 0.026 | O41: 0.026 | P41: 0.026 | Q41: 0.026 | R41: 0.026 | S41: 0.026 | T41: 0.026 | U41: 0.026 | V41: 0.026 | W41: 0.026 | X41: 0.026 | Y41: 0.026 | Z41: 0.026 | AA41: 0.026 | AB41: 0.026 | AC41: 0.026 | AD41: 0.026 | AE41: 0.026 | AF41: 0.025 | AG41: 0.024 | AH41: 0.024 | AI41: 0.024 | AJ41: 0.024 | AK41: 0.024 | AL41: 0.024 | AM41: 0.024 | AN41: 0.024 | AO41: 0.024 | AP41: 0.024 | AQ41: 0.024 | AR41: 0.024 | AS41: 0.024 | AT41: 0.024 | AU41: 0.024 | AV41: 0.024 | AW41: 0.024 | AX41: 0.024 | AY41: 0.024 | AZ41: 0.024 | BA41: 0.021 | BB41: 0.027 | BC41: 0.025 | BD41: 0.024 | BE41: 0.024 | BF41: 0.024 | BG41: 0.024 | BH41: 0.023 | BI41: 0.023 | BJ41: 0.023 | BK41: 0.023 | BL41: 0.023 | BM41: 0.023 | BN41: 0.023 | BO41: 0.023 | BP41: 0.023 | BQ41: 0.023 | BR41: 0.023 | BS41: 0.023 | BT41: 0.023 | BU41: 0.023 | BV41: 0.023 | BW41: 0.023 | BX41: 0.023 | BY41: 0.022 | BZ41: 0.022 | CA41: 0.022 | CB41: 0.022 | CC41: 0.022 | CD41: 0.022
B42: Exchange rate: Frw per US dollar | D42: 554 | E42: 552 | F42: 551 | G42: 550 | H42: 548 | I42: 546 | J42: 548 | K42: 546 | L42: 544 | M42: 543 | N42: 547 | O42: 553 | P42: 566 | Q42: 568 | R42: 569 | S42: 570 | T42: 573 | U42: 579 | V42: 589 | W42: 592 | X42: 599 | Y42: 601 | Z42: 600 | AA42: 602 | AB42: 605 | AC42: 609 | AD42: 615 | AE42: 628 | AF42: 633 | AG42: 640 | AH42: 649 | AI42: 664 | AJ42: 675 | AK42: 681 | AL42: 684 | AM42: 691 | AN42: 702 | AO42: 713 | AP42: 725 | AQ42: 739 | AR42: 759 | AS42: 776 | AT42: 800 | AU42: 815 | AV42: 823 | AW42: 828 | AX42: 834 | AY42: 842 | AZ42: 849 | BA42: 856 | BB42: 864 | BC42: 875 | BD42: 884 | BE42: 893 | BF42: 904 | BG42: 916 | BH42: 927 | BI42: 933 | BJ42: 947 | BK42: 966 | BL42: 976 | BM42: 983 | BN42: 992 | BO42: 1004 | BP42: 1014 | BQ42: 1021 | BR42: 1032 | BS42: 1055 | BT42: 1088 | BU42: 1127 | BV42: 1187 | BW42: 1239 | BX42: 1279 | BY42: 1300 | BZ42: 1327 | CA42: 1367 | CB42: 1400 | CC42: 1420 | CD42: 1443
B43: Growth rate | D43: 0 | E43: 0 | F43: 0 | G43: 0 | H43: -0.01 | I43: -0.01 | J43: -0.01 | K43: -0.01 | L43: -0.01 | M43: -0.01 | N43: 0 | O43: 0.01 | P43: 0.04 | Q43: 0.05 | R43: 0.04 | S43: 0.03 | T43: 0.01 | U43: 0.02 | V43: 0.04 | W43: 0.04 | X43: 0.05 | Y43: 0.04 | Z43: 0.02 | AA43: 0.02 | AB43: 0.01 | AC43: 0.01 | AD43: 0.02 | AE43: 0.04 | AF43: 0.05 | AG43: 0.05 | AH43: 0.06 | AI43: 0.06 | AJ43: 0.07 | AK43: 0.06 | AL43: 0.05 | AM43: 0.04 | AN43: 0.04 | AO43: 0.05 | AP43: 0.06 | AQ43: 0.07 | AR43: 0.08 | AS43: 0.09 | AT43: 0.1 | AU43: 0.1 | AV43: 0.08 | AW43: 0.07 | AX43: 0.04 | AY43: 0.03 | AZ43: 0.03 | BA43: 0.03 | BB43: 0.04 | BC43: 0.04 | BD43: 0.04 | BE43: 0.04 | BF43: 0.05 | BG43: 0.05 | BH43: 0.05 | BI43: 0.04 | BJ43: 0.05 | BK43: 0.05 | BL43: 0.05 | BM43: 0.05 | BN43: 0.05 | BO43: 0.04 | BP43: 0.04 | BQ43: 0.04 | BR43: 0.04 | BS43: 0.05 | BT43: 0.07 | BU43: 0.1 | BV43: 0.15 | BW43: 0.17 | BX43: 0.18 | BY43: 0.15 | BZ43: 0.12 | CA43: 0.1 | CB43: 0.09 | CC43: 0.09 | CD43: 0.09
B45: Source: National Institute of Statistics of Rwanda
B46: 46007 | BL46: =BL36/BL29 -> -0.35275835 | BM46: =BM36/BM29 -> -0.32946146 | BN46: =BN36/BN29 -> -0.38837567 | BO46: =BO36/BO29 -> -0.34993573 | BP46: =BP36/BP29 -> -0.36730087 | BQ46: =BQ36/BQ29 -> -0.3798253 | BR46: =BR36/BR29 -> -0.44128329 | BS46: =BS36/BS29 -> -0.33349169 | ... CD46: =CD36/CD29 -> -0.37357466

Sheet QGDP_CP
B1: Table 1
B2: Gross Domestic Product by Kind of Activity
B3: at current prices
B4: (in billion Rwf) | D4: Base year
B5: Activity description | C5: ISIC4 | D5: =QGDP_KP!$D$5 -> 2024 | E5: 2006 Q1 | F5: 2006 Q2 | G5: 2006 Q3 | H5: 2006 Q4 | I5: 2007 Q1 | J5: 2007 Q2 | K5: 2007 Q3 | L5: 2007 Q4 | M5: 2008 Q1 | N5: 2008 Q2 | O5: 2008 Q3 | P5: 2008 Q4 | Q5: 2009 Q1 | R5: 2009 Q2 | S5: 2009 Q3 | T5: 2009 Q4 | U5: 2010 Q1 | V5: 2010 Q2 | W5: 2010 Q3 | X5: 2010 Q4 | Y5: 2011 Q1 | Z5: 2011 Q2 | AA5: 2011 Q3 | AB5: 2011 Q4 | AC5: 2012 Q1 | AD5: 2012 Q2 | AE5: 2012 Q3 | AF5: 2012 Q4 | AG5: 2013 Q1 | AH5: 2013 Q2 | AI5: 2013 Q3 | AJ5: 2013 Q4 | AK5: 2014 Q1 | AL5: 2014 Q2 | AM5: 2014 Q3 | AN5: 2014 Q4 | AO5: 2015 Q1 | AP5: 2015 Q2 | AQ5: 2015 Q3 | AR5: 2015 Q4 | AS5: 2016 Q1 | AT5: 2016 Q2 | AU5: 2016 Q3 | AV5: 2016 Q4 | AW5: 2017 Q1 | AX5: 2017 Q2 | AY5: 2017 Q3 | AZ5: 2017 Q4 | BA5: 2018 Q1 | BB5: 2018 Q2 | BC5: 2018 Q3 | BD5: 2018 Q4 | BE5: 2019 Q1 | BF5: 2019 Q2 | BG5: 2019 Q3 | BH5: 2019 Q4 | BI5: 2020 Q1 | BJ5: 2020 Q2 | BK5: 2020 Q3 | BL5: 2020 Q4 | BM5: 2021 Q1 | BN5: 2021 Q2 | BO5: 2021 Q3 | BP5: 2021 Q4 | BQ5: 2022 Q1 | BR5: 2022 Q2 | BS5: 2022 Q3 | BT5: 2022 Q4 | BU5: 2023 Q1 | BV5: 2023 Q2 | BW5: 2023 Q3 | BX5: 2023 Q4 | BY5: 2024 Q1 | BZ5: 2024 Q2 | CA5: 2024 Q3 | CB5: 2024 Q4 | CC5: 2025 Q1 | CD5: 2025 Q2 | CE5: 2025 Q3 | DD5: SUT
B7: GROSS DOMESTIC PRODUCT (GDP) | D7: 19918 | E7: 396 | F7: 446 | G7: 472 | H7: 492 | I7: 499 | J7: 540 | K7: 566 | L7: 592 | M7: 600 | N7: 679 | O7: 741 | P7: 779 | Q7: 777 | R7: 765 | S7: 799 | T7: 844 | U7: 842 | V7: 848 | W7: 895 | X7: 944 | Y7: 952 | Z7: 987 | AA7: 1062 | AB7: 1083 | AC7: 1100 | AD7: 1128 | AE7: 1195 | AF7: 1219 | AG7: 1196 | AH7: 1235 | AI7: 1245 | AJ7: 1312 | AK7: 1336 | AL7: 1403 | AM7: 1296 | AN7: 1513 | AO7: 1451 | AP7: 1511 | AQ7: 1418 | AR7: 1701 | AS7: 1617 | AT7: 1707 | AU7: 1538 | AV7: 1906 | AW7: 1830 | AX7: 1964 | AY7: 1722 | AZ7: 2105 | BA7: 2016 | BB7: 2132 | BC7: 1884 | BD7: 2277 | BE7: 2160 | BF7: 2468 | BG7: 2195 | BH7: 2637 | BI7: 2395 | BJ7: 2413 | BK7: 2221 | BL7: 2862 | BM7: 2574 | BN7: 2841 | BO7: 2598 | BP7: 3112 | BQ7: 3101 | BR7: 3549 | BS7: 3304 | BT7: 4210 | BU7: 4031 | BV7: 4255 | BW7: 3875 | BX7: 5016 | BY7: 4514 | BZ7: 4965 | CA7: 4659 | CB7: 5780 | CC7: 5276 | CD7: 5799 | CE7: 5525 | DD7: KP | DE7: Check KP=CP
B9: AGRICULTURE, FORESTRY & FISHING | C9: A | D9: 4142 | E9: 113 | F9: 129 | G9: 136 | H9: 147 | I9: 133 | J9: 133 | K9: 142 | L9: 143 | M9: 148 | N9: 164 | O9: 175 | P9: 183 | Q9: 184 | R9: 189 | S9: 194 | T9: 210 | U9: 200 | V9: 203 | W9: 210 | X9: 214 | Y9: 207 | Z9: 233 | AA9: 248 | AB9: 248 | AC9: 251 | AD9: 271 | AE9: 287 | AF9: 296 | AG9: 289 | AH9: 302 | AI9: 292 | AJ9: 308 | AK9: 323 | AL9: 356 | AM9: 209 | AN9: 426 | AO9: 339 | AP9: 376 | AQ9: 223 | AR9: 467 | AS9: 371 | AT9: 417 | AU9: 260 | AV9: 596 | AW9: 490 | AX9: 558 | AY9: 273 | AZ9: 633 | BA9: 477 | BB9: 554 | BC9: 300 | BD9: 603 | BE9: 456 | BF9: 583 | BG9: 319 | BH9: 682 | BI9: 558 | BJ9: 673 | BK9: 369 | BL9: 792 | BM9: 597 | BN9: 693 | BO9: 398 | BP9: 697 | BQ9: 614 | BR9: 846 | BS9: 514 | BT9: 1132 | BU9: 900 | BV9: 1150 | BW9: 629 | BX9: 1295 | BY9: 987 | BZ9: 1131 | CA9: 699 | CB9: 1324 | CC9: 1080 | CD9: 1341 | CE9: 812
B10: Food crops | C10: AA | D10: 2373 | E10: 49 | F10: 55 | G10: 68 | H10: 75 | I10: 70 | J10: 68 | K10: 72 | L10: 73 | M10: 72 | N10: 75 | O10: 81 | P10: 89 | Q10: 93 | R10: 93 | S10: 98 | T10: 113 | U10: 105 | V10: 99 | W10: 103 | X10: 107 | Y10: 110 | Z10: 125 | AA10: 121 | AB10: 129 | AC10: 139 | AD10: 153 | AE10: 150 | AF10: 150 | AG10: 168 | AH10: 175 | AI10: 158 | AJ10: 170 | AK10: 192 | AL10: 221 | AM10: 61 | AN10: 275 | AO10: 200 | AP10: 227 | AQ10: 64 | AR10: 313 | AS10: 211 | AT10: 262 | AU10: 93 | AV10: 422 | AW10: 330 | AX10: 389 | AY10: 81 | AZ10: 423 | BA10: 273 | BB10: 343 | BC10: 76 | BD10: 369 | BE10: 245 | BF10: 358 | BG10: 84 | BH10: 440 | BI10: 319 | BJ10: 434 | BK10: 116 | BL10: 535 | BM10: 333 | BN10: 431 | BO10: 108 | BP10: 413 | BQ10: 305 | BR10: 507 | BS10: 149 | BT10: 734 | BU10: 545 | BV10: 786 | BW10: 239 | BX10: 884 | BY10: 583 | BZ10: 722 | CA10: 205 | CB10: 863 | CC10: 600 | CD10: 814 | CE10: 223
B11: Export crops | C11: AB | D11: 351 | E11: 12 | F11: 15 | G11: 14 | H11: 16 | I11: 9 | J11: 9 | K11: 12 | L11: 11 | M11: 11 | N11: 16 | O11: 15 | P11: 13 | Q11: 11 | R11: 14 | S11: 14 | T11: 13 | U11: 13 | V11: 17 | W11: 19 | X11: 16 | Y11: 10 | Z11: 11 | AA11: 28 | AB11: 18 | AC11: 9 | AD11: 12 | AE11: 29 | AF11: 36 | AG11: 11 | AH11: 15 | AI11: 20 | AJ11: 22 | AK11: 13 | AL11: 17 | AM11: 28 | AN11: 29 | AO11: 14 | AP11: 22 | AQ11: 30 | AR11: 23 | AS11: 26 | AT11: 18 | AU11: 27 | AV11: 33 | AW11: 24 | AX11: 29 | AY11: 37 | AZ11: 48 | BA11: 31 | BB11: 28 | BC11: 38 | BD11: 47 | BE11: 25 | BF11: 28 | BG11: 36 | BH11: 36 | BI11: 29 | BJ11: 28 | BK11: 40 | BL11: 46 | BM11: 34 | BN11: 30 | BO11: 49 | BP11: 46 | BQ11: 39 | BR11: 52 | BS11: 82 | BT11: 88 | BU11: 53 | BV11: 52 | BW11: 71 | BX11: 83 | BY11: 70 | BZ11: 66 | CA11: 134 | CB11: 82 | CC11: 88 | CD11: 119 | CE11: 170
B12: Livestock & livestock products | C12: AC | D12: 581 | E12: 12 | F12: 12 | G12: 13 | H12: 13 | I12: 13 | J12: 13 | K12: 13 | L12: 14 | M12: 15 | N12: 16 | O12: 18 | P12: 19 | Q12: 20 | R12: 20 | S12: 20 | T12: 20 | U12: 20 | V12: 21 | W12: 21 | X12: 22 | Y12: 22 | Z12: 23 | AA12: 24 | AB12: 25 | AC12: 25 | AD12: 26 | AE12: 27 | AF12: 28 | AG12: 28 | AH12: 29 | AI12: 30 | AJ12: 30 | AK12: 31 | AL12: 32 | AM12: 33 | AN12: 34 | AO12: 34 | AP12: 35 | AQ12: 37 | AR12: 38 | AS12: 40 | AT12: 41 | AU12: 42 | AV12: 43 | AW12: 45 | AX12: 46 | AY12: 47 | AZ12: 48 | BA12: 51 | BB12: 51 | BC12: 52 | BD12: 52 | BE12: 53 | BF12: 58 | BG12: 61 | BH12: 69 | BI12: 68 | BJ12: 72 | BK12: 71 | BL12: 77 | BM12: 80 | BN12: 78 | BO12: 86 | BP12: 80 | BQ12: 91 | BR12: 99 | BS12: 100 | BT12: 110 | BU12: 108 | BV12: 114 | BW12: 123 | BX12: 132 | BY12: 132 | BZ12: 135 | CA12: 149 | CB12: 165 | CC12: 176 | CD12: 187 | CE12: 190
B13: Forestry | C13: AD | D13: 782 | E13: 38 | F13: 45 | G13: 40 | H13: 42 | I13: 40 | J13: 42 | K13: 43 | L13: 44 | M13: 48 | N13: 55 | O13: 58 | P13: 59 | Q13: 57 | R13: 60 | S13: 59 | T13: 61 | U13: 57 | V13: 63 | W13: 64 | X13: 66 | Y13: 61 | Z13: 70 | AA13: 71 | AB13: 72 | AC13: 73 | AD13: 75 | AE13: 77 | AF13: 78 | AG13: 77 | AH13: 79 | AI13: 79 | AJ13: 80 | AK13: 81 | AL13: 81 | AM13: 82 | AN13: 83 | AO13: 84 | AP13: 86 | AQ13: 86 | AR13: 87 | AS13: 88 | AT13: 90 | AU13: 91 | AV13: 91 | AW13: 84 | AX13: 87 | AY13: 101 | AZ13: 107 | BA13: 113 | BB13: 124 | BC13: 126 | BD13: 127 | BE13: 125 | BF13: 131 | BG13: 130 | BH13: 129 | BI13: 135 | BJ13: 132 | BK13: 135 | BL13: 127 | BM13: 143 | BN13: 146 | BO13: 145 | BP13: 149 | BQ13: 170 | BR13: 179 | BS13: 171 | BT13: 189 | BU13: 184 | BV13: 187 | BW13: 183 | BX13: 186 | BY13: 192 | BZ13: 194 | CA13: 196 | CB13: 201 | CC13: 203 | CD13: 207 | CE13: 214
B14: Fishing | C14: AE | D14: 54 | E14: 2 | F14: 2 | G14: 2 | H14: 2 | I14: 2 | J14: 2 | K14: 2 | L14: 2 | M14: 2 | N14: 2 | O14: 3 | P14: 3 | Q14: 3 | R14: 3 | S14: 3 | T14: 3 | U14: 3 | V14: 3 | W14: 3 | X14: 3 | Y14: 3 | Z14: 4 | AA14: 4 | AB14: 4 | AC14: 4 | AD14: 5 | AE14: 4 | AF14: 4 | AG14: 4 | AH14: 5 | AI14: 5 | AJ14: 6 | AK14: 5 | AL14: 5 | AM14: 6 | AN14: 6 | AO14: 6 | AP14: 6 | AQ14: 6 | AR14: 7 | AS14: 6 | AT14: 6 | AU14: 7 | AV14: 7 | AW14: 7 | AX14: 7 | AY14: 7 | AZ14: 8 | BA14: 8 | BB14: 8 | BC14: 8 | BD14: 7 | BE14: 7 | BF14: 8 | BG14: 8 | BH14: 8 | BI14: 6 | BJ14: 6 | BK14: 7 | BL14: 7 | BM14: 7 | BN14: 9 | BO14: 9 | BP14: 9 | BQ14: 9 | BR14: 10 | BS14: 11 | BT14: 12 | BU14: 10 | BV14: 11 | BW14: 11 | BX14: 11 | BY14: 11 | BZ14: 13 | CA14: 16 | CB14: 14 | CC14: 13 | CD14: 14 | CE14: 15
B15: INDUSTRY | C15: B-F | D15: 4396 | E15: 61 | F15: 70 | G15: 77 | H15: 82 | I15: 84 | J15: 89 | K15: 97 | L15: 102 | M15: 99 | N15: 112 | O15: 123 | P15: 127 | Q15: 126 | R15: 118 | S15: 125 | T15: 137 | U15: 139 | V15: 133 | W15: 146 | X15: 165 | Y15: 178 | Z15: 169 | AA15: 193 | AB15: 210 | AC15: 196 | AD15: 197 | AE15: 223 | AF15: 241 | AG15: 221 | AH15: 219 | AI15: 223 | AJ15: 228 | AK15: 236 | AL15: 238 | AM15: 259 | AN15: 254 | AO15: 254 | AP15: 256 | AQ15: 275 | AR15: 288 | AS15: 290 | AT15: 285 | AU15: 278 | AV15: 299 | AW15: 314 | AX15: 328 | AY15: 337 | AZ15: 351 | BA15: 372 | BB15: 370 | BC15: 339 | BD15: 379 | BE15: 400 | BF15: 463 | BG15: 464 | BH15: 492 | BI15: 476 | BJ15: 448 | BK15: 427 | BL15: 543 | BM15: 541 | BN15: 545 | BO15: 588 | BP15: 683 | BQ15: 730 | BR15: 779 | BS15: 719 | BT15: 853 | BU15: 910 | BV15: 836 | BW15: 874 | BX15: 1069 | BY15: 1087 | BZ15: 1069 | CA15: 1033 | CB15: 1206 | CC15: 1247 | CD15: 1242 | CE15: 1232
B16: Mining & quarrying | C16: B | D16: 354 | E16: 3 | F16: 5 | G16: 5 | H16: 6 | I16: 7 | J16: 9 | K16: 8 | L16: 10 | M16: 9 | N16: 13 | O16: 10 | P16: 9 | Q16: 7 | R16: 6 | S16: 7 | T16: 7 | U16: 5 | V16: 8 | W16: 10 | X16: 13 | Y16: 20 | Z16: 19 | AA16: 21 | AB16: 22 | AC16: 19 | AD16: 17 | AE16: 20 | AF16: 21 | AG16: 24 | AH16: 26 | AI16: 25 | AJ16: 26 | AK16: 27 | AL16: 26 | AM16: 38 | AN16: 28 | AO16: 26 | AP16: 24 | AQ16: 29 | AR16: 26 | AS16: 22 | AT16: 27 | AU16: 28 | AV16: 34 | AW16: 34 | AX16: 35 | AY16: 44 | AZ16: 53 | BA16: 47 | BB16: 48 | BC16: 43 | BD16: 39 | BE16: 35 | BF16: 33 | BG16: 30 | BH16: 24 | BI16: 28 | BJ16: 21 | BK16: 22 | BL16: 34 | BM16: 46 | BN16: 45 | BO16: 76 | BP16: 88 | BQ16: 88 | BR16: 86 | BS16: 68 | BT16: 67 | BU16: 63 | BV16: 67 | BW16: 72 | BX16: 81 | BY16: 89 | BZ16: 87 | CA16: 88 | CB16: 91 | CC16: 98 | CD16: 104 | CE16: 106
B17: TOTAL MANUFACTURING | C17: C | D17: 1618 | E17: 35 | F17: 39 | G17: 45 | H17: 46 | I17: 40 | J17: 41 | K17: 49 | L17: 51 | M17: 47 | N17: 54 | O17: 61 | P17: 63 | Q17: 59 | R17: 60 | S17: 66 | T17: 72 | U17: 69 | V17: 67 | W17: 77 | X17: 82 | Y17: 75 | Z17: 79 | AA17: 95 | AB17: 96 | AC17: 88 | AD17: 93 | AE17: 103 | AF17: 105 | AG17: 83 | AH17: 85 | AI17: 89 | AJ17: 87 | AK17: 90 | AL17: 93 | AM17: 100 | AN17: 100 | AO17: 100 | AP17: 101 | AQ17: 108 | AR17: 110 | AS17: 114 | AT17: 114 | AU17: 111 | AV17: 120 | AW17: 142 | AX17: 153 | AY17: 146 | AZ17: 149 | BA17: 153 | BB17: 158 | BC17: 140 | BD17: 178 | BE17: 174 | BF17: 204 | BG17: 170 | BH17: 219 | BI17: 198 | BJ17: 203 | BK17: 182 | BL17: 247 | BM17: 229 | BN17: 255 | BO17: 220 | BP17: 290 | BQ17: 284 | BR17: 345 | BS17: 284 | BT17: 389 | BU17: 382 | BV17: 362 | BW17: 313 | BX17: 416 | BY17: 390 | BZ17: 396 | CA17: 361 | CB17: 471 | CC17: 470 | CD17: 479 | CE17: 442
B18: Of which: Food | C18: CA | D18: 383 | E18: 6 | F18: 8 | G18: 11 | H18: 11 | I18: 7 | J18: 7 | K18: 11 | L18: 10 | M18: 10 | N18: 11 | O18: 14 | P18: 13 | Q18: 13 | R18: 14 | S18: 17 | T18: 15 | U18: 16 | V18: 16 | W18: 19 | X18: 18 | Y18: 14 | Z18: 17 | AA18: 25 | AB18: 26 | AC18: 17 | AD18: 18 | AE18: 26 | AF18: 28 | AG18: 25 | AH18: 23 | AI18: 23 | AJ18: 24 | AK18: 24 | AL18: 25 | AM18: 27 | AN18: 28 | AO18: 27 | AP18: 26 | AQ18: 26 | AR18: 29 | AS18: 33 | AT18: 30 | AU18: 26 | AV18: 35 | AW18: 51 | AX18: 58 | AY18: 50 | AZ18: 52 | BA18: 36 | BB18: 52 | BC18: 28 | BD18: 57 | BE18: 41 | BF18: 69 | BG18: 37 | BH18: 76 | BI18: 51 | BJ18: 71 | BK18: 36 | BL18: 76 | BM18: 53 | BN18: 77 | BO18: 48 | BP18: 93 | BQ18: 69 | BR18: 126 | BS18: 73 | BT18: 149 | BU18: 104 | BV18: 136 | BW18: 74 | BX18: 148 | BY18: 87 | BZ18: 110 | CA18: 63 | CB18: 123 | CC18: 96 | CD18: 143 | CE18: 85
B19: Beverages & tobacco | C19: CB | D19: 486 | E19: 7 | F19: 7 | G19: 10 | H19: 11 | I19: 8 | J19: 9 | K19: 11 | L19: 11 | M19: 10 | N19: 11 | O19: 15 | P19: 16 | Q19: 15 | R19: 16 | S19: 19 | T19: 22 | U19: 16 | V19: 17 | W19: 23 | X19: 22 | Y19: 18 | Z19: 19 | AA19: 24 | AB19: 22 | AC19: 22 | AD19: 23 | AE19: 27 | AF19: 27 | AG19: 25 | AH19: 27 | AI19: 29 | AJ19: 28 | AK19: 29 | AL19: 29 | AM19: 32 | AN19: 32 | AO19: 32 | AP19: 31 | AQ19: 35 | AR19: 33 | AS19: 34 | AT19: 34 | AU19: 37 | AV19: 35 | AW19: 39 | AX19: 39 | AY19: 40 | AZ19: 41 | BA19: 53 | BB19: 40 | BC19: 38 | BD19: 45 | BE19: 53 | BF19: 45 | BG19: 41 | BH19: 53 | BI19: 63 | BJ19: 40 | BK19: 44 | BL19: 62 | BM19: 77 | BN19: 49 | BO19: 51 | BP19: 73 | BQ19: 87 | BR19: 65 | BS19: 62 | BT19: 88 | BU19: 109 | BV19: 76 | BW19: 76 | BX19: 106 | BY19: 145 | BZ19: 99 | CA19: 99 | CB19: 143 | CC19: 180 | CD19: 119 | CE19: 120
B20: Textiles, clothing & leather goods | C20: CC | D20: 135 | E20: 12 | F20: 13 | G20: 12 | H20: 12 | I20: 12 | J20: 13 | K20: 14 | L20: 15 | M20: 15 | N20: 17 | O20: 16 | P20: 15 | Q20: 17 | R20: 15 | S20: 15 | T20: 15 | U20: 16 | V20: 16 | W20: 16 | X20: 19 | Y20: 21 | Z20: 19 | AA20: 20 | AB20: 21 | AC20: 22 | AD20: 24 | AE20: 21 | AF20: 21 | AG20: 5 | AH20: 5 | AI20: 5 | AJ20: 5 | AK20: 5 | AL20: 6 | AM20: 6 | AN20: 6 | AO20: 5 | AP20: 6 | AQ20: 6 | AR20: 6 | AS20: 6 | AT20: 6 | AU20: 6 | AV20: 7 | AW20: 8 | AX20: 9 | AY20: 8 | AZ20: 8 | BA20: 14 | BB20: 14 | BC20: 15 | BD20: 15 | BE20: 15 | BF20: 17 | BG20: 18 | BH20: 19 | BI20: 19 | BJ20: 18 | BK20: 20 | BL20: 21 | BM20: 20 | BN20: 22 | BO20: 22 | BP20: 24 | BQ20: 22 | BR20: 24 | BS20: 24 | BT20: 26 | BU20: 25 | BV20: 27 | BW20: 30 | BX20: 32 | BY20: 30 | BZ20: 35 | CA20: 36 | CB20: 33 | CC20: 31 | CD20: 32 | CE20: 34
... B26: Electricity | C26: D | D26: 147 | E26: 2 | F26: 2 | G26: 3 | H26: 4 | I26: 5 | J26: 7 | K26: 7 | L26: 6 | M26: 5 | N26: 4 | O26: 4 | P26: 4 | Q26: 5 | R26: 5 | S26: 5 | T26: 5 | U26: 5 | V26: 6 | W26: 6 | X26: 6 | Y26: 6 | Z26: 7 | AA26: 7 | AB26: 8 | AC26: 8 | AD26: 8 | AE26: 9 | AF26: 10 | AG26: 10 | AH26: 10 | AI26: 10 | AJ26: 11 | AK26: 11 | AL26: 11 | AM26: 11 | AN26: 12 | AO26: 12 | AP26: 12 | AQ26: 14 | AR26: 18 | AS26: 19 | AT26: 19 | AU26: 19 | AV26: 20 | AW26: 20 | AX26: 21 | AY26: 21 | AZ26: 22 | BA26: 20 | BB26: 20 | BC26: 27 | BD26: 28 | BE26: 27 | BF26: 27 | BG26: 28 | BH26: 27 | BI26: 28 | BJ26: 28 | BK26: 32 | BL26: 34 | BM26: 32 | BN26: 36 | BO26: 35 | BP26: 33 | BQ26: 29 | BR26: 27 | BS26: 26 | BT26: 25 | BU26: 24 | BV26: 27 | BW26: 29 | BX26: 30 | BY26: 32 | BZ26: 37 | CA26: 39 | CB26: 39 | CC26: 38 | CD26: 41 | CE26: 52
B27: Water & waste management | C27: E | D27: 78 | E27: 2 | F27: 2 | G27: 2 | H27: 3 | I27: 4 | J27: 6 | K27: 6 | L27: 5 | M27: 4 | N27: 3 | O27: 3 | P27: 3 | Q27: 4 | R27: 4 | S27: 4 | T27: 4 | U27: 4 | V27: 5 | W27: 5 | X27: 5 | Y27: 5 | Z27: 5 | AA27: 6 | AB27: 6 | AC27: 6 | AD27: 6 | AE27: 6 | AF27: 6 | AG27: 6 | AH27: 6 | AI27: 6 | AJ27: 6 | AK27: 6 | AL27: 7 | AM27: 7 | AN27: 7 | AO27: 7 | AP27: 7 | AQ27: 7 | AR27: 8 | AS27: 8 | AT27: 8 | AU27: 8 | AV27: 8 | AW27: 8 | AX27: 8 | AY27: 8 | AZ27: 8 | BA27: 8 | BB27: 8 | BC27: 9 | BD27: 9 | BE27: 13 | BF27: 15 | BG27: 16 | BH27: 15 | BI27: 16 | BJ27: 16 | BK27: 17 | BL27: 16 | BM27: 17 | BN27: 17 | BO27: 18 | BP27: 18 | BQ27: 18 | BR27: 18 | BS27: 19 | BT27: 18 | BU27: 18 | BV27: 18 | BW27: 19 | BX27: 19 | BY27: 19 | BZ27: 19 | CA27: 20 | CB27: 20 | CC27: 20 | CD27: 20 | CE27: 21 | CF27: =CF28/SUM(BY15:CB15) -> 0.5003413
B28: Construction | C28: F | D28: 2198 | E28: 19 | F28: 22 | G28: 22 | H28: 24 | I28: 28 | J28: 26 | K28: 27 | L28: 30 | M28: 34 | N28: 38 | O28: 44 | P28: 48 | Q28: 51 | R28: 44 | S28: 41 | T28: 49 | U28: 55 | V28: 47 | W28: 48 | X28: 58 | Y28: 71 | Z28: 59 | AA28: 64 | AB28: 78 | AC28: 75 | AD28: 73 | AE28: 84 | AF28: 99 | AG28: 97 | AH28: 92 | AI28: 92 | AJ28: 97 | AK28: 101 | AL28: 101 | AM28: 104 | AN28: 107 | AO28: 109 | AP28: 112 | AQ28: 117 | AR28: 126 | AS28: 127 | AT28: 117 | AU28: 112 | AV28: 118 | AW28: 111 | AX28: 111 | AY28: 117 | AZ28: 119 | BA28: 144 | BB28: 136 | BC28: 120 | BD28: 126 | BE28: 151 | BF28: 184 | BG28: 220 | BH28: 206 | BI28: 205 | BJ28: 181 | BK28: 175 | BL28: 212 | BM28: 218 | BN28: 192 | BO28: 239 | BP28: 253 | BQ28: 312 | BR28: 302 | BS28: 323 | BT28: 353 | BU28: 422 | BV28: 362 | BW28: 442 | BX28: 523 | BY28: 558 | BZ28: 531 | CA28: 525 | CB28: 585 | CC28: 620 | CD28: 598 | CE28: 611 | CF28: =SUM(BY28:CB28) -> 2199
B29: SERVICES | C29: G-T | D29: 10396 | E29: 186 | F29: 208 | G29: 216 | H29: 219 | I29: 236 | J29: 267 | K29: 277 | L29: 292 | M29: 296 | N29: 341 | O29: 372 | P29: 388 | Q29: 387 | R29: 383 | S29: 408 | T29: 419 | U29: 425 | V29: 434 | W29: 452 | X29: 470 | Y29: 465 | Z29: 474 | AA29: 517 | AB29: 524 | AC29: 551 | AD29: 565 | AE29: 585 | AF29: 597 | AG29: 599 | AH29: 619 | AI29: 629 | AJ29: 671 | AK29: 666 | AL29: 680 | AM29: 704 | AN29: 717 | AO29: 741 | AP29: 744 | AQ29: 780 | AR29: 794 | AS29: 814 | AT29: 842 | AU29: 852 | AV29: 866 | AW29: 870 | AX29: 908 | AY29: 956 | AZ29: 949 | BA29: 998 | BB29: 1029 | BC29: 1081 | BD29: 1117 | BE29: 1118 | BF29: 1210 | BG29: 1229 | BH29: 1256 | BI29: 1164 | BJ29: 1106 | BK29: 1235 | BL29: 1321 | BM29: 1289 | BN29: 1429 | BO29: 1471 | BP29: 1561 | BQ29: 1587 | BR29: 1727 | BS29: 1869 | BT29: 2020 | BU29: 2014 | BV29: 2045 | BW29: 2151 | BX29: 2436 | BY29: 2224 | BZ29: 2501 | CA29: 2668 | CB29: 3004 | CC29: 2688 | CD29: 2903 | CE29: 3161
B30: TRADE &TRANSPORT | C30: G-H | D30: 3594 | E30: 43 | F30: 53 | G30: 55 | H30: 56 | I30: 55 | J30: 63 | K30: 65 | L30: 76 | M30: 72 | N30: 93 | O30: 108 | P30: 103 | Q30: 102 | R30: 100 | S30: 104 | T30: 111 | U30: 112 | V30: 113 | W30: 121 | X30: 128 | Y30: 121 | Z30: 124 | AA30: 145 | AB30: 148 | AC30: 149 | AD30: 152 | AE30: 176 | AF30: 172 | AG30: 159 | AH30: 170 | AI30: 180 | AJ30: 190 | AK30: 182 | AL30: 183 | AM30: 192 | AN30: 197 | AO30: 202 | AP30: 201 | AQ30: 207 | AR30: 213 | AS30: 218 | AT30: 230 | AU30: 227 | AV30: 222 | AW30: 224 | AX30: 238 | AY30: 260 | AZ30: 269 | BA30: 280 | BB30: 294 | BC30: 315 | BD30: 334 | BE30: 323 | BF30: 352 | BG30: 367 | BH30: 382 | BI30: 334 | BJ30: 304 | BK30: 354 | BL30: 428 | BM30: 381 | BN30: 426 | BO30: 444 | BP30: 480 | BQ30: 489 | BR30: 570 | BS30: 579 | BT30: 648 | BU30: 602 | BV30: 623 | BW30: 667 | BX30: 771 | BY30: 713 | BZ30: 876 | CA30: 935 | CB30: 1070 | CC30: 948 | CD30: 1043 | CE30: 1140
B31: Maintenance & repair of motor vehicles | C31: GA | D31: 128 | E31: 2 | F31: 2 | G31: 2 | H31: 2 | I31: 2 | J31: 3 | K31: 3 | L31: 3 | M31: 3 | N31: 4 | O31: 5 | P31: 5 | Q31: 5 | R31: 5 | S31: 5 | T31: 5 | U31: 5 | V31: 5 | W31: 5 | X31: 6 | Y31: 6 | Z31: 6 | AA31: 6 | AB31: 6 | AC31: 7 | AD31: 7 | AE31: 7 | AF31: 7 | AG31: 7 | AH31: 7 | AI31: 7 | AJ31: 8 | AK31: 8 | AL31: 8 | AM31: 8 | AN31: 8 | AO31: 8 | AP31: 8 | AQ31: 8 | AR31: 9 | AS31: 9 | AT31: 9 | AU31: 10 | AV31: 10 | AW31: 10 | AX31: 10 | AY31: 10 | AZ31: 10 | BA31: 14 | BB31: 14 | BC31: 12 | BD31: 7 | BE31: 8 | BF31: 12 | BG31: 15 | BH31: 20 | BI31: 11 | BJ31: 15 | BK31: 19 | BL31: 20 | BM31: 19 | BN31: 21 | BO31: 21 | BP31: 22 | BQ31: 22 | BR31: 24 | BS31: 25 | BT31: 26 | BU31: 26 | BV31: 27 | BW31: 28 | BX31: 28 | BY31: 27 | BZ31: 31 | CA31: 32 | CB31: 38 | CC31: 42 | CD31: 43 | CE31: 46
B32: Wholesale & retail trade | C32: GB | D32: 1822 | E32: 27 | F32: 34 | G32: 34 | H32: 35 | I32: 34 | J32: 40 | K32: 41 | L32: 49 | M32: 46 | N32: 61 | O32: 72 | P32: 67 | Q32: 68 | R32: 64 | S32: 66 | T32: 69 | U32: 71 | V32: 71 | W32: 77 | X32: 82 | Y32: 77 | Z32: 79 | AA32: 93 | AB32: 95 | AC32: 95 | AD32: 95 | AE32: 111 | AF32: 107 | AG32: 97 | AH32: 106 | AI32: 112 | AJ32: 119 | AK32: 116 | AL32: 116 | AM32: 123 | AN32: 127 | AO32: 132 | AP32: 130 | AQ32: 132 | AR32: 135 | AS32: 143 | AT32: 146 | AU32: 141 | AV32: 130 | AW32: 135 | AX32: 145 | AY32: 156 | AZ32: 161 | BA32: 158 | BB32: 162 | BC32: 174 | BD32: 188 | BE32: 177 | BF32: 196 | BG32: 178 | BH32: 183 | BI32: 161 | BJ32: 163 | BK32: 177 | BL32: 212 | BM32: 190 | BN32: 220 | BO32: 242 | BP32: 247 | BQ32: 245 | BR32: 286 | BS32: 286 | BT32: 314 | BU32: 309 | BV32: 328 | BW32: 341 | BX32: 399 | BY32: 356 | BZ32: 462 | CA32: 452 | CB32: 552 | CC32: 477 | CD32: 549 | CE32: 559
B33: Transport | C33: HA | D33: 1644 | E33: 14 | F33: 16 | G33: 18 | H33: 19 | I33: 19 | J33: 20 | K33: 21 | L33: 24 | M33: 24 | N33: 28 | O33: 32 | P33: 31 | Q33: 29 | R33: 32 | S33: 33 | T33: 37 | U33: 36 | V33: 37 | W33: 39 | X33: 40 | Y33: 38 | Z33: 40 | AA33: 46 | AB33: 47 | AC33: 48 | AD33: 50 | AE33: 58 | AF33: 58 | AG33: 55 | AH33: 56 | AI33: 61 | AJ33: 63 | AK33: 59 | AL33: 59 | AM33: 62 | AN33: 62 | AO33: 63 | AP33: 63 | AQ33: 67 | AR33: 70 | AS33: 67 | AT33: 74 | AU33: 77 | AV33: 83 | AW33: 80 | AX33: 84 | AY33: 94 | AZ33: 98 | BA33: 108 | BB33: 117 | BC33: 129 | BD33: 138 | BE33: 138 | BF33: 144 | BG33: 174 | BH33: 179 | BI33: 162 | BJ33: 127 | BK33: 158 | BL33: 195 | BM33: 172 | BN33: 184 | BO33: 180 | BP33: 211 | BQ33: 223 | BR33: 260 | BS33: 268 | BT33: 307 | BU33: 267 | BV33: 268 | BW33: 299 | BX33: 343 | BY33: 330 | BZ33: 383 | CA33: 451 | CB33: 480 | CC33: 429 | CD33: 452 | CE33: 535
B34: OTHER SERVICES | C34: I-T | D34: 6802 | E34: 143 | F34: 154 | G34: 161 | H34: 163 | I34: 180 | J34: 205 | K34: 212 | L34: 217 | M34: 224 | N34: 248 | O34: 263 | P34: 285 | Q34: 285 | R34: 283 | S34: 304 | T34: 308 | U34: 313 | V34: 321 | W34: 331 | X34: 341 | Y34: 344 | Z34: 350 | AA34: 371 | AB34: 376 | AC34: 401 | AD34: 413 | AE34: 409 | AF34: 425 | AG34: 440 | AH34: 449 | AI34: 449 | AJ34: 482 | AK34: 484 | AL34: 497 | AM34: 512 | AN34: 520 | AO34: 539 | AP34: 543 | AQ34: 572 | AR34: 580 | AS34: 596 | AT34: 613 | AU34: 625 | AV34: 644 | AW34: 646 | AX34: 670 | AY34: 697 | AZ34: 680 | BA34: 719 | BB34: 735 | BC34: 766 | BD34: 784 | BE34: 795 | BF34: 858 | BG34: 862 | BH34: 874 | BI34: 830 | BJ34: 802 | BK34: 881 | BL34: 893 | BM34: 907 | BN34: 1004 | BO34: 1027 | BP34: 1082 | BQ34: 1098 | BR34: 1157 | BS34: 1290 | BT34: 1372 | BU34: 1412 | BV34: 1422 | BW34: 1484 | BX34: 1665 | BY34: 1511 | BZ34: 1624 | CA34: 1733 | CB34: 1934 | CC34: 1740 | CD34: 1860 | CE34: 2021
B35: Hotels & restaurants | C35: I | D35: 681 | E35: 11 | F35: 12 | G35: 13 | H35: 13 | I35: 13 | J35: 15 | K35: 15 | L35: 16 | M35: 18 | N35: 17 | O35: 18 | P35: 18 | Q35: 18 | R35: 18 | S35: 19 | T35: 20 | U35: 20 | V35: 21 | W35: 21 | X35: 22 | Y35: 22 | Z35: 22 | AA35: 23 | AB35: 23 | AC35: 24 | AD35: 24 | AE35: 24 | AF35: 24 | AG35: 23 | AH35: 24 | AI35: 26 | AJ35: 27 | AK35: 28 | AL35: 29 | AM35: 31 | AN35: 31 | AO35: 31 | AP35: 33 | AQ35: 34 | AR35: 35 | AS35: 37 | AT35: 39 | AU35: 41 | AV35: 37 | AW35: 36 | AX35: 34 | AY35: 35 | AZ35: 35 | BA35: 42 | BB35: 42 | BC35: 46 | BD35: 50 | BE35: 52 | BF35: 55 | BG35: 60 | BH35: 57 | BI35: 43 | BJ35: 30 | BK35: 31 | BL35: 34 | BM35: 34 | BN35: 43 | BO35: 46 | BP35: 59 | BQ35: 68 | BR35: 90 | BS35: 104 | BT35: 104 | BU35: 95 | BV35: 96 | BW35: 111 | BX35: 124 | BY35: 137 | BZ35: 161 | CA35: 187 | CB35: 196 | CC35: 196 | CD35: 204 | CE35: 241
B36: Information & communication | C36: J | D36: 433 | E36: 7 | F36: 8 | G36: 9 | H36: 9 | I36: 10 | J36: 11 | K36: 11 | L36: 13 | M36: 12 | N36: 14 | O36: 16 | P36: 16 | Q36: 15 | R36: 16 | S36: 17 | T36: 19 | U36: 18 | V36: 19 | W36: 20 | X36: 20 | Y36: 19 | Z36: 21 | AA36: 23 | AB36: 23 | AC36: 25 | AD36: 27 | AE36: 29 | AF36: 28 | AG36: 24 | AH36: 27 | AI36: 27 | AJ36: 29 | AK36: 24 | AL36: 30 | AM36: 32 | AN36: 32 | AO36: 33 | AP36: 32 | AQ36: 35 | AR36: 35 | AS36: 34 | AT36: 37 | AU36: 32 | AV36: 35 | AW36: 32 | AX36: 34 | AY36: 32 | AZ36: 36 | BA36: 36 | BB36: 38 | BC36: 38 | BD36: 40 | BE36: 42 | BF36: 52 | BG36: 53 | BH36: 61 | BI36: 50 | BJ36: 55 | BK36: 63 | BL36: 62 | BM36: 58 | BN36: 80 | BO36: 64 | BP36: 68 | BQ36: 58 | BR36: 65 | BS36: 71 | BT36: 72 | BU36: 77 | BV36: 80 | BW36: 82 | BX36: 101 | BY36: 90 | BZ36: 109 | CA36: 107 | CB36: 126 | CC36: 99 | CD36: 106 | CE36: 111
B37: Financial services | C37: K | D37: 498 | E37: 7 | F37: 12 | G37: 13 | H37: 12 | I37: 9 | J37: 15 | K37: 16 | L37: 14 | M37: 10 | N37: 18 | O37: 15 | P37: 17 | Q37: 17 | R37: 15 | S37: 15 | T37: 13 | U37: 19 | V37: 17 | W37: 19 | X37: 20 | Y37: 23 | Z37: 26 | AA37: 25 | AB37: 20 | AC37: 28 | AD37: 33 | AE37: 28 | AF37: 32 | AG37: 36 | AH37: 35 | AI37: 31 | AJ37: 42 | AK37: 33 | AL37: 37 | AM37: 34 | AN37: 42 | AO37: 39 | AP37: 40 | AQ37: 42 | AR37: 39 | AS37: 40 | AT37: 37 | AU37: 43 | AV37: 44 | AW37: 45 | AX37: 45 | AY37: 53 | AZ37: 48 | BA37: 49 | BB37: 48 | BC37: 61 | BD37: 58 | BE37: 63 | BF37: 67 | BG37: 57 | BH37: 63 | BI37: 61 | BJ37: 59 | BK37: 69 | BL37: 66 | BM37: 78 | BN37: 84 | BO37: 88 | BP37: 95 | BQ37: 96 | BR37: 109 | BS37: 111 | BT37: 159 | BU37: 124 | BV37: 147 | BW37: 118 | BX37: 138 | BY37: 128 | BZ37: 120 | CA37: 122 | CB37: 128 | CC37: 134 | CD37: 142 | CE37: 156
B38: Real estate activities | C38: L | D38: 1372 | E38: 33 | F38: 32 | G38: 34 | H38: 34 | I38: 41 | J38: 51 | K38: 54 | L38: 57 | M38: 58 | N38: 67 | O38: 71 | P38: 84 | Q38: 81 | R38: 79 | S38: 89 | T38: 91 | U38: 84 | V38: 88 | W38: 91 | X38: 93 | Y38: 96 | Z38: 93 | AA38: 93 | AB38: 93 | AC38: 100 | AD38: 97 | AE38: 87 | AF38: 86 | AG38: 93 | AH38: 89 | AI38: 93 | AJ38: 92 | AK38: 104 | AL38: 97 | AM38: 100 | AN38: 100 | AO38: 106 | AP38: 101 | AQ38: 114 | AR38: 108 | AS38: 116 | AT38: 117 | AU38: 124 | AV38: 131 | AW38: 142 | AX38: 133 | AY38: 143 | AZ38: 141 | BA38: 158 | BB38: 160 | BC38: 167 | BD38: 170 | BE38: 180 | BF38: 200 | BG38: 189 | BH38: 186 | BI38: 193 | BJ38: 190 | BK38: 205 | BL38: 221 | BM38: 217 | BN38: 225 | BO38: 237 | BP38: 247 | BQ38: 249 | BR38: 251 | BS38: 263 | BT38: 278 | BU38: 347 | BV38: 301 | BW38: 316 | BX38: 324 | BY38: 314 | BZ38: 309 | CA38: 319 | CB38: 430 | CC38: 320 | CD38: 323 | CE38: 349
B39: Professional, scientific & technical activities | C39: M | D39: 588 | E39: 8 | F39: 8 | G39: 9 | H39: 9 | I39: 11 | J39: 13 | K39: 14 | L39: 14 | M39: 15 | N39: 17 | O39: 18 | P39: 21 | Q39: 21 | R39: 20 | S39: 23 | T39: 23 | U39: 21 | V39: 22 | W39: 23 | X39: 24 | Y39: 23 | Z39: 24 | AA39: 24 | AB39: 25 | AC39: 27 | AD39: 27 | AE39: 26 | AF39: 27 | AG39: 26 | AH39: 31 | AI39: 28 | AJ39: 32 | AK39: 27 | AL39: 29 | AM39: 27 | AN39: 27 | AO39: 32 | AP39: 33 | AQ39: 30 | AR39: 33 | AS39: 33 | AT39: 37 | AU39: 36 | AV39: 38 | AW39: 38 | AX39: 41 | AY39: 41 | AZ39: 44 | BA39: 45 | BB39: 48 | BC39: 49 | BD39: 52 | BE39: 54 | BF39: 58 | BG39: 58 | BH39: 63 | BI39: 62 | BJ39: 64 | BK39: 68 | BL39: 73 | BM39: 75 | BN39: 81 | BO39: 82 | BP39: 88 | BQ39: 90 | BR39: 99 | BS39: 102 | BT39: 111 | BU39: 114 | BV39: 126 | BW39: 134 | BX39: 139 | BY39: 134 | BZ39: 146 | CA39: 146 | CB39: 162 | CC39: 167 | CD39: 178 | CE39: 187
B40: Administrative & support service activities | C40: N | D40: 840 | E40: 11 | F40: 11 | G40: 12 | H40: 12 | I40: 14 | J40: 18 | K40: 19 | L40: 19 | M40: 20 | N40: 23 | O40: 24 | P40: 29 | Q40: 28 | R40: 27 | S40: 30 | T40: 31 | U40: 29 | V40: 30 | W40: 31 | X40: 32 | Y40: 30 | Z40: 31 | AA40: 33 | AB40: 34 | AC40: 35 | AD40: 36 | AE40: 37 | AF40: 37 | AG40: 38 | AH40: 39 | AI40: 37 | AJ40: 43 | AK40: 44 | AL40: 45 | AM40: 45 | AN40: 49 | AO40: 47 | AP40: 52 | AQ40: 57 | AR40: 62 | AS40: 61 | AT40: 62 | AU40: 64 | AV40: 65 | AW40: 66 | AX40: 68 | AY40: 70 | AZ40: 72 | BA40: 75 | BB40: 77 | BC40: 82 | BD40: 79 | BE40: 77 | BF40: 82 | BG40: 96 | BH40: 105 | BI40: 99 | BJ40: 89 | BK40: 102 | BL40: 99 | BM40: 99 | BN40: 113 | BO40: 115 | BP40: 118 | BQ40: 119 | BR40: 129 | BS40: 152 | BT40: 153 | BU40: 158 | BV40: 159 | BW40: 185 | BX40: 195 | BY40: 172 | BZ40: 215 | CA40: 233 | CB40: 220 | CC40: 190 | CD40: 245 | CE40: 266
... B44: Cultural, domestic & other services | C44: R-T | D44: 640 | E44: 26 | F44: 28 | G44: 28 | H44: 29 | I44: 32 | J44: 32 | K44: 33 | L44: 33 | M44: 35 | N44: 35 | O44: 38 | P44: 38 | Q44: 36 | R44: 36 | S44: 38 | T44: 39 | U44: 40 | V44: 39 | W44: 41 | X44: 41 | Y44: 43 | Z44: 41 | AA44: 42 | AB44: 44 | AC44: 46 | AD44: 47 | AE44: 50 | AF44: 52 | AG44: 54 | AH44: 58 | AI44: 56 | AJ44: 59 | AK44: 62 | AL44: 68 | AM44: 72 | AN44: 69 | AO44: 77 | AP44: 84 | AQ44: 84 | AR44: 85 | AS44: 88 | AT44: 89 | AU44: 92 | AV44: 93 | AW44: 94 | AX44: 96 | AY44: 99 | AZ44: 101 | BA44: 102 | BB44: 104 | BC44: 104 | BD44: 111 | BE44: 107 | BF44: 111 | BG44: 110 | BH44: 114 | BI44: 105 | BJ44: 104 | BK44: 110 | BL44: 110 | BM44: 108 | BN44: 113 | BO44: 114 | BP44: 122 | BQ44: 116 | BR44: 121 | BS44: 127 | BT44: 130 | BU44: 119 | BV44: 120 | BW44: 128 | BX44: 237 | BY44: 136 | BZ44: 154 | CA44: 167 | CB44: 183 | CC44: 170 | CD44: 186 | CE44: 193
B46: Taxes less subsidies on products | D46: 985 | E46: 37 | F46: 40 | G46: 43 | H46: 44 | I46: 46 | J46: 50 | K46: 50 | L46: 55 | M46: 58 | N46: 61 | O46: 72 | P46: 82 | Q46: 80 | R46: 75 | S46: 73 | T46: 77 | U46: 78 | V46: 77 | W46: 87 | X46: 96 | Y46: 103 | Z46: 110 | AA46: 105 | AB46: 100 | AC46: 103 | AD46: 95 | AE46: 100 | AF46: 86 | AG46: 87 | AH46: 95 | AI46: 101 | AJ46: 104 | AK46: 112 | AL46: 129 | AM46: 123 | AN46: 116 | AO46: 117 | AP46: 134 | AQ46: 140 | AR46: 152 | AS46: 141 | AT46: 162 | AU46: 148 | AV46: 145 | AW46: 156 | AX46: 169 | AY46: 155 | AZ46: 172 | BA46: 170 | BB46: 179 | BC46: 165 | BD46: 178 | BE46: 186 | BF46: 212 | BG46: 183 | BH46: 208 | BI46: 197 | BJ46: 186 | BK46: 191 | BL46: 207 | BM46: 147 | BN46: 174 | BO46: 141 | BP46: 171 | BQ46: 170 | BR46: 197 | BS46: 202 | BT46: 205 | BU46: 208 | BV46: 224 | BW46: 221 | BX46: 215 | BY46: 216 | BZ46: 264 | CA46: 259 | CB46: 246 | CC46: 261 | CD46: 312 | CE46: 321
B48: Source: National Institute of Statistics of Rwanda
B49: ='Table A Q'!B46 -> 46007

Sheet QGDP_SH
B1: Table 1A
B2: Gross Domestic Product by Kind of Activity
B3: Shares at current prices
B4: (Percentages)
B5: Activity description | C5: ISIC4 | D5: =QGDP_KP!$D$5 -> 2024 | E5: 2006 Q1 | F5: 2006 Q2 | G5: 2006 Q3 | H5: 2006 Q4 | I5: 2007 Q1 | J5: 2007 Q2 | K5: 2007 Q3 | L5: 2007 Q4 | M5: 2008 Q1 | N5: 2008 Q2 | O5: 2008 Q3 | P5: 2008 Q4 | Q5: 2009 Q1 | R5: 2009 Q2 | S5: 2009 Q3 | T5: 2009 Q4 | U5: 2010 Q1 | V5: 2010 Q2 | W5: 2010 Q3 | X5: 2010 Q4 | Y5: 2011 Q1 | Z5: 2011 Q2 | AA5: 2011 Q3 | AB5: 2011 Q4 | AC5: 2012 Q1 | AD5: 2012 Q2 | AE5: 2012 Q3 | AF5: 2012 Q4 | AG5: 2013 Q1 | AH5: 2013 Q2 | AI5: 2013 Q3 | AJ5: 2013 Q4 | AK5: 2014 Q1 | AL5: 2014 Q2 | AM5: 2014 Q3 | AN5: 2014 Q4 | AO5: 2015 Q1 | AP5: 2015 Q2 | AQ5: 2015 Q3 | AR5: 2015 Q4 | AS5: 2016 Q1 | AT5: 2016 Q2 | AU5: 2016 Q3 | AV5: 2016 Q4 | AW5: 2017 Q1 | AX5: 2017 Q2 | AY5: 2017 Q3 | AZ5: 2017 Q4 | BA5: 2018 Q1 | BB5: 2018 Q2 | BC5: 2018 Q3 | BD5: 2018 Q4 | BE5: 2019 Q1 | BF5: 2019 Q2 | BG5: 2019 Q3 | BH5: 2019 Q4 | BI5: 2020 Q1 | BJ5: 2020 Q2 | BK5: 2020 Q3 | BL5: 2020 Q4 | BM5: 2021 Q1 | BN5: 2021 Q2 | BO5: 2021 Q3 | BP5: 2021 Q4 | BQ5: 2022 Q1 | BR5: 2022 Q2 | BS5: 2022 Q3 | BT5: 2022 Q4 | BU5: 2023 Q1 | BV5: 2023 Q2 | BW5: 2023 Q3 | BX5: 2023 Q4 | BY5: 2024 Q1 | BZ5: 2024 Q2 | CA5: 2024 Q3 | CB5: 2024 Q4 | CC5: 2025 Q1 | CD5: 2025 Q2 | CE5: 2025 Q3
B7: GROSS DOMESTIC PRODUCT (GDP) | D7: 1 | E7: 1 | F7: 1 | G7: 1 | H7: 1 | I7: 1 | J7: 1 | K7: 1 | L7: 1 | M7: 1 | N7: 1 | O7: 1 | P7: 1 | Q7: 1 | R7: 1 | S7: 1 | T7: 1 | U7: 1 | V7: 1 | W7: 1 | X7: 1 | Y7: 1 | Z7: 1 | AA7: 1 | AB7: 1 | AC7: 1 | AD7: 1 | AE7: 1 | AF7: 1 | AG7: 1 | AH7: 1 | AI7: 1 | AJ7: 1 | AK7: 1 | AL7: 1 | AM7: 1 | AN7: 1 | AO7: 1 | AP7: 1 | AQ7: 1 | AR7: 1 | AS7: 1 | AT7: 1 | AU7: 1 | AV7: 1 | AW7: 1 | AX7: 1 | AY7: 1 | AZ7: 1 | BA7: 1 | BB7: 1 | BC7: 1 | BD7: 1 | BE7: 1 | BF7: 1 | BG7: 1 | BH7: 1 | BI7: 1 | BJ7: 1 | BK7: 1 | BL7: 1 | BM7: 1 | BN7: 1 | BO7: 1 | BP7: 1 | BQ7: 1 | BR7: 1 | BS7: 1 | BT7: 1 | BU7: 1 | BV7: 1 | BW7: 1 | BX7: 1 | BY7: 1 | BZ7: 1 | CA7: 1 | CB7: 1 | CC7: 1 | CD7: 1 | CE7: 1
B9: AGRICULTURE, FORESTRY & FISHING | C9: A | D9: 0.21 | E9: 0.28 | F9: 0.29 | G9: 0.29 | H9: 0.3 | I9: 0.27 | J9: 0.25 | K9: 0.25 | L9: 0.24 | M9: 0.25 | N9: 0.24 | O9: 0.24 | P9: 0.23 | Q9: 0.24 | R9: 0.25 | S9: 0.24 | T9: 0.25 | U9: 0.24 | V9: 0.24 | W9: 0.23 | X9: 0.23 | Y9: 0.22 | Z9: 0.24 | AA9: 0.23 | AB9: 0.23 | AC9: 0.23 | AD9: 0.24 | AE9: 0.24 | AF9: 0.24 | AG9: 0.24 | AH9: 0.24 | AI9: 0.23 | AJ9: 0.24 | AK9: 0.24 | AL9: 0.25 | AM9: 0.16 | AN9: 0.28 | AO9: 0.23 | AP9: 0.25 | AQ9: 0.16 | AR9: 0.27 | AS9: 0.23 | AT9: 0.24 | AU9: 0.17 | AV9: 0.31 | AW9: 0.27 | AX9: 0.28 | AY9: 0.16 | AZ9: 0.3 | BA9: 0.24 | BB9: 0.26 | BC9: 0.16 | BD9: 0.26 | BE9: 0.21 | BF9: 0.24 | BG9: 0.15 | BH9: 0.26 | BI9: 0.23 | BJ9: 0.28 | BK9: 0.17 | BL9: 0.28 | BM9: 0.23 | BN9: 0.24 | BO9: 0.15 | BP9: 0.22 | BQ9: 0.2 | BR9: 0.24 | BS9: 0.16 | BT9: 0.27 | BU9: 0.22 | BV9: 0.27 | BW9: 0.16 | BX9: 0.26 | BY9: 0.22 | BZ9: 0.23 | CA9: 0.15 | CB9: 0.23 | CC9: 0.2 | CD9: 0.23 | CE9: 0.15
B10: Food crops | C10: AA | D10: 0.12 | E10: 0.12 | F10: 0.12 | G10: 0.14 | H10: 0.15 | I10: 0.14 | J10: 0.13 | K10: 0.13 | L10: 0.12 | M10: 0.12 | N10: 0.11 | O10: 0.11 | P10: 0.11 | Q10: 0.12 | R10: 0.12 | S10: 0.12 | T10: 0.13 | U10: 0.13 | V10: 0.12 | W10: 0.12 | X10: 0.11 | Y10: 0.12 | Z10: 0.13 | AA10: 0.11 | AB10: 0.12 | AC10: 0.13 | AD10: 0.14 | AE10: 0.13 | AF10: 0.12 | AG10: 0.14 | AH10: 0.14 | AI10: 0.13 | AJ10: 0.13 | AK10: 0.14 | AL10: 0.16 | AM10: 0.05 | AN10: 0.18 | AO10: 0.14 | AP10: 0.15 | AQ10: 0.05 | AR10: 0.18 | AS10: 0.13 | AT10: 0.15 | AU10: 0.06 | AV10: 0.22 | AW10: 0.18 | AX10: 0.2 | AY10: 0.05 | AZ10: 0.2 | BA10: 0.14 | BB10: 0.16 | BC10: 0.04 | BD10: 0.16 | BE10: 0.11 | BF10: 0.15 | BG10: 0.04 | BH10: 0.17 | BI10: 0.13 | BJ10: 0.18 | BK10: 0.05 | BL10: 0.19 | BM10: 0.13 | BN10: 0.15 | BO10: 0.04 | BP10: 0.13 | BQ10: 0.1 | BR10: 0.14 | BS10: 0.05 | BT10: 0.17 | BU10: 0.14 | BV10: 0.18 | BW10: 0.06 | BX10: 0.18 | BY10: 0.13 | BZ10: 0.15 | CA10: 0.04 | CB10: 0.15 | CC10: 0.11 | CD10: 0.14 | CE10: 0.04
B11: Export crops | C11: AB | D11: 0.02 | E11: 0.03 | F11: 0.03 | G11: 0.03 | H11: 0.03 | I11: 0.02 | J11: 0.02 | K11: 0.02 | L11: 0.02 | M11: 0.02 | N11: 0.02 | O11: 0.02 | P11: 0.02 | Q11: 0.01 | R11: 0.02 | S11: 0.02 | T11: 0.02 | U11: 0.02 | V11: 0.02 | W11: 0.02 | X11: 0.02 | Y11: 0.01 | Z11: 0.01 | AA11: 0.03 | AB11: 0.02 | AC11: 0.01 | AD11: 0.01 | AE11: 0.02 | AF11: 0.03 | AG11: 0.01 | AH11: 0.01 | AI11: 0.02 | AJ11: 0.02 | AK11: 0.01 | AL11: 0.01 | AM11: 0.02 | AN11: 0.02 | AO11: 0.01 | AP11: 0.01 | AQ11: 0.02 | AR11: 0.01 | AS11: 0.02 | AT11: 0.01 | AU11: 0.02 | AV11: 0.02 | AW11: 0.01 | AX11: 0.01 | AY11: 0.02 | AZ11: 0.02 | BA11: 0.02 | BB11: 0.01 | BC11: 0.02 | BD11: 0.02 | BE11: 0.01 | BF11: 0.01 | BG11: 0.02 | BH11: 0.01 | BI11: 0.01 | BJ11: 0.01 | BK11: 0.02 | BL11: 0.02 | BM11: 0.01 | BN11: 0.01 | BO11: 0.02 | BP11: 0.01 | BQ11: 0.01 | BR11: 0.01 | BS11: 0.02 | BT11: 0.02 | BU11: 0.01 | BV11: 0.01 | BW11: 0.02 | BX11: 0.02 | BY11: 0.02 | BZ11: 0.01 | CA11: 0.03 | CB11: 0.01 | CC11: 0.02 | CD11: 0.02 | CE11: 0.03
B12: Livestock & livestock products | C12: AC | D12: 0.03 | E12: 0.03 | F12: 0.03 | G12: 0.03 | H12: 0.03 | I12: 0.03 | J12: 0.02 | K12: 0.02 | L12: 0.02 | M12: 0.02 | N12: 0.02 | O12: 0.02 | P12: 0.02 | Q12: 0.03 | R12: 0.03 | S12: 0.02 | T12: 0.02 | U12: 0.02 | V12: 0.02 | W12: 0.02 | X12: 0.02 | Y12: 0.02 | Z12: 0.02 | AA12: 0.02 | AB12: 0.02 | AC12: 0.02 | AD12: 0.02 | AE12: 0.02 | AF12: 0.02 | AG12: 0.02 | AH12: 0.02 | AI12: 0.02 | AJ12: 0.02 | AK12: 0.02 | AL12: 0.02 | AM12: 0.03 | AN12: 0.02 | AO12: 0.02 | AP12: 0.02 | AQ12: 0.03 | AR12: 0.02 | AS12: 0.02 | AT12: 0.02 | AU12: 0.03 | AV12: 0.02 | AW12: 0.02 | AX12: 0.02 | AY12: 0.03 | AZ12: 0.02 | BA12: 0.03 | BB12: 0.02 | BC12: 0.03 | BD12: 0.02 | BE12: 0.02 | BF12: 0.02 | BG12: 0.03 | BH12: 0.03 | BI12: 0.03 | BJ12: 0.03 | BK12: 0.03 | BL12: 0.03 | BM12: 0.03 | BN12: 0.03 | BO12: 0.03 | BP12: 0.03 | BQ12: 0.03 | BR12: 0.03 | BS12: 0.03 | BT12: 0.03 | BU12: 0.03 | BV12: 0.03 | BW12: 0.03 | BX12: 0.03 | BY12: 0.03 | BZ12: 0.03 | CA12: 0.03 | CB12: 0.03 | CC12: 0.03 | CD12: 0.03 | CE12: 0.03
B13: Forestry | C13: AD | D13: 0.04 | E13: 0.1 | F13: 0.1 | G13: 0.08 | H13: 0.09 | I13: 0.08 | J13: 0.08 | K13: 0.08 | L13: 0.07 | M13: 0.08 | N13: 0.08 | O13: 0.08 | P13: 0.08 | Q13: 0.07 | R13: 0.08 | S13: 0.07 | T13: 0.07 | U13: 0.07 | V13: 0.07 | W13: 0.07 | X13: 0.07 | Y13: 0.06 | Z13: 0.07 | AA13: 0.07 | AB13: 0.07 | AC13: 0.07 | AD13: 0.07 | AE13: 0.06 | AF13: 0.06 | AG13: 0.06 | AH13: 0.06 | AI13: 0.06 | AJ13: 0.06 | AK13: 0.06 | AL13: 0.06 | AM13: 0.06 | AN13: 0.05 | AO13: 0.06 | AP13: 0.06 | AQ13: 0.06 | AR13: 0.05 | AS13: 0.05 | AT13: 0.05 | AU13: 0.06 | AV13: 0.05 | AW13: 0.05 | AX13: 0.04 | AY13: 0.06 | AZ13: 0.05 | BA13: 0.06 | BB13: 0.06 | BC13: 0.07 | BD13: 0.06 | BE13: 0.06 | BF13: 0.05 | BG13: 0.06 | BH13: 0.05 | BI13: 0.06 | BJ13: 0.05 | BK13: 0.06 | BL13: 0.04 | BM13: 0.06 | BN13: 0.05 | BO13: 0.06 | BP13: 0.05 | BQ13: 0.05 | BR13: 0.05 | BS13: 0.05 | BT13: 0.04 | BU13: 0.05 | BV13: 0.04 | BW13: 0.05 | BX13: 0.04 | BY13: 0.04 | BZ13: 0.04 | CA13: 0.04 | CB13: 0.03 | CC13: 0.04 | CD13: 0.04 | CE13: 0.04
B14: Fishing | C14: AE | D14: 0 | E14: 0 | F14: 0 | G14: 0 | H14: 0 | I14: 0 | J14: 0 | K14: 0 | L14: 0 | M14: 0 | N14: 0 | O14: 0 | P14: 0 | Q14: 0 | R14: 0 | S14: 0 | T14: 0 | U14: 0 | V14: 0 | W14: 0 | X14: 0 | Y14: 0 | Z14: 0 | AA14: 0 | AB14: 0 | AC14: 0 | AD14: 0 | AE14: 0 | AF14: 0 | AG14: 0 | AH14: 0 | AI14: 0 | AJ14: 0 | AK14: 0 | AL14: 0 | AM14: 0 | AN14: 0 | AO14: 0 | AP14: 0 | AQ14: 0 | AR14: 0 | AS14: 0 | AT14: 0 | AU14: 0 | AV14: 0 | AW14: 0 | AX14: 0 | AY14: 0 | AZ14: 0 | BA14: 0 | BB14: 0 | BC14: 0 | BD14: 0 | BE14: 0 | BF14: 0 | BG14: 0 | BH14: 0 | BI14: 0 | BJ14: 0 | BK14: 0 | BL14: 0 | BM14: 0 | BN14: 0 | BO14: 0 | BP14: 0 | BQ14: 0 | BR14: 0 | BS14: 0 | BT14: 0 | BU14: 0 | BV14: 0 | BW14: 0 | BX14: 0 | BY14: 0 | BZ14: 0 | CA14: 0 | CB14: 0 | CC14: 0 | CD14: 0 | CE14: 0
B15: INDUSTRY | C15: B-F | D15: 0.22 | E15: 0.15 | F15: 0.16 | G15: 0.16 | H15: 0.17 | I15: 0.17 | J15: 0.16 | K15: 0.17 | L15: 0.17 | M15: 0.16 | N15: 0.17 | O15: 0.17 | P15: 0.16 | Q15: 0.16 | R15: 0.15 | S15: 0.16 | T15: 0.16 | U15: 0.17 | V15: 0.16 | W15: 0.16 | X15: 0.17 | Y15: 0.19 | Z15: 0.17 | AA15: 0.18 | AB15: 0.19 | AC15: 0.18 | AD15: 0.17 | AE15: 0.19 | AF15: 0.2 | AG15: 0.18 | AH15: 0.18 | AI15: 0.18 | AJ15: 0.17 | AK15: 0.18 | AL15: 0.17 | AM15: 0.2 | AN15: 0.17 | AO15: 0.17 | AP15: 0.17 | AQ15: 0.19 | AR15: 0.17 | AS15: 0.18 | AT15: 0.17 | AU15: 0.18 | AV15: 0.16 | AW15: 0.17 | AX15: 0.17 | AY15: 0.2 | AZ15: 0.17 | BA15: 0.18 | BB15: 0.17 | BC15: 0.18 | BD15: 0.17 | BE15: 0.19 | BF15: 0.19 | BG15: 0.21 | BH15: 0.19 | BI15: 0.2 | BJ15: 0.19 | BK15: 0.19 | BL15: 0.19 | BM15: 0.21 | BN15: 0.19 | BO15: 0.23 | BP15: 0.22 | BQ15: 0.24 | BR15: 0.22 | BS15: 0.22 | BT15: 0.2 | BU15: 0.23 | BV15: 0.2 | BW15: 0.23 | BX15: 0.21 | BY15: 0.24 | BZ15: 0.22 | CA15: 0.22 | CB15: 0.21 | CC15: 0.24 | CD15: 0.21 | CE15: 0.22
B16: Mining & quarrying | C16: B | D16: 0.02 | E16: 0.01 | F16: 0.01 | G16: 0.01 | H16: 0.01 | I16: 0.01 | J16: 0.02 | K16: 0.01 | L16: 0.02 | M16: 0.02 | N16: 0.02 | O16: 0.01 | P16: 0.01 | Q16: 0.01 | R16: 0.01 | S16: 0.01 | T16: 0.01 | U16: 0.01 | V16: 0.01 | W16: 0.01 | X16: 0.01 | Y16: 0.02 | Z16: 0.02 | AA16: 0.02 | AB16: 0.02 | AC16: 0.02 | AD16: 0.02 | AE16: 0.02 | AF16: 0.02 | AG16: 0.02 | AH16: 0.02 | AI16: 0.02 | AJ16: 0.02 | AK16: 0.02 | AL16: 0.02 | AM16: 0.03 | AN16: 0.02 | AO16: 0.02 | AP16: 0.02 | AQ16: 0.02 | AR16: 0.02 | AS16: 0.01 | AT16: 0.02 | AU16: 0.02 | AV16: 0.02 | AW16: 0.02 | AX16: 0.02 | AY16: 0.03 | AZ16: 0.03 | BA16: 0.02 | BB16: 0.02 | BC16: 0.02 | BD16: 0.02 | BE16: 0.02 | BF16: 0.01 | BG16: 0.01 | BH16: 0.01 | BI16: 0.01 | BJ16: 0.01 | BK16: 0.01 | BL16: 0.01 | BM16: 0.02 | BN16: 0.02 | BO16: 0.03 | BP16: 0.03 | BQ16: 0.03 | BR16: 0.02 | BS16: 0.02 | BT16: 0.02 | BU16: 0.02 | BV16: 0.02 | BW16: 0.02 | BX16: 0.02 | BY16: 0.02 | BZ16: 0.02 | CA16: 0.02 | CB16: 0.02 | CC16: 0.02 | CD16: 0.02 | CE16: 0.02
B17: TOTAL MANUFACTURING | C17: C | D17: 0.08 | E17: 0.09 | F17: 0.09 | G17: 0.1 | H17: 0.09 | I17: 0.08 | J17: 0.08 | K17: 0.09 | L17: 0.09 | M17: 0.08 | N17: 0.08 | O17: 0.08 | P17: 0.08 | Q17: 0.08 | R17: 0.08 | S17: 0.08 | T17: 0.09 | U17: 0.08 | V17: 0.08 | W17: 0.09 | X17: 0.09 | Y17: 0.08 | Z17: 0.08 | AA17: 0.09 | AB17: 0.09 | AC17: 0.08 | AD17: 0.08 | AE17: 0.09 | AF17: 0.09 | AG17: 0.07 | AH17: 0.07 | AI17: 0.07 | AJ17: 0.07 | AK17: 0.07 | AL17: 0.07 | AM17: 0.08 | AN17: 0.07 | AO17: 0.07 | AP17: 0.07 | AQ17: 0.08 | AR17: 0.06 | AS17: 0.07 | AT17: 0.07 | AU17: 0.07 | AV17: 0.06 | AW17: 0.08 | AX17: 0.08 | AY17: 0.09 | AZ17: 0.07 | BA17: 0.08 | BB17: 0.07 | BC17: 0.07 | BD17: 0.08 | BE17: 0.08 | BF17: 0.08 | BG17: 0.08 | BH17: 0.08 | BI17: 0.08 | BJ17: 0.08 | BK17: 0.08 | BL17: 0.09 | BM17: 0.09 | BN17: 0.09 | BO17: 0.08 | BP17: 0.09 | BQ17: 0.09 | BR17: 0.1 | BS17: 0.09 | BT17: 0.09 | BU17: 0.09 | BV17: 0.08 | BW17: 0.08 | BX17: 0.08 | BY17: 0.09 | BZ17: 0.08 | CA17: 0.08 | CB17: 0.08 | CC17: 0.09 | CD17: 0.08 | CE17: 0.08
B18: Of which: Food | C18: CA | D18: 0.02 | E18: 0.02 | F18: 0.02 | G18: 0.02 | H18: 0.02 | I18: 0.01 | J18: 0.01 | K18: 0.02 | L18: 0.02 | M18: 0.02 | N18: 0.02 | O18: 0.02 | P18: 0.02 | Q18: 0.02 | R18: 0.02 | S18: 0.02 | T18: 0.02 | U18: 0.02 | V18: 0.02 | W18: 0.02 | X18: 0.02 | Y18: 0.01 | Z18: 0.02 | AA18: 0.02 | AB18: 0.02 | AC18: 0.02 | AD18: 0.02 | AE18: 0.02 | AF18: 0.02 | AG18: 0.02 | AH18: 0.02 | AI18: 0.02 | AJ18: 0.02 | AK18: 0.02 | AL18: 0.02 | AM18: 0.02 | AN18: 0.02 | AO18: 0.02 | AP18: 0.02 | AQ18: 0.02 | AR18: 0.02 | AS18: 0.02 | AT18: 0.02 | AU18: 0.02 | AV18: 0.02 | AW18: 0.03 | AX18: 0.03 | AY18: 0.03 | AZ18: 0.02 | BA18: 0.02 | BB18: 0.02 | BC18: 0.01 | BD18: 0.03 | BE18: 0.02 | BF18: 0.03 | BG18: 0.02 | BH18: 0.03 | BI18: 0.02 | BJ18: 0.03 | BK18: 0.02 | BL18: 0.03 | BM18: 0.02 | BN18: 0.03 | BO18: 0.02 | BP18: 0.03 | BQ18: 0.02 | BR18: 0.04 | BS18: 0.02 | BT18: 0.04 | BU18: 0.03 | BV18: 0.03 | BW18: 0.02 | BX18: 0.03 | BY18: 0.02 | BZ18: 0.02 | CA18: 0.01 | CB18: 0.02 | CC18: 0.02 | CD18: 0.02 | CE18: 0.02
B19: Beverages & tobacco | C19: CB | D19: 0.02 | E19: 0.02 | F19: 0.02 | G19: 0.02 | H19: 0.02 | I19: 0.02 | J19: 0.02 | K19: 0.02 | L19: 0.02 | M19: 0.02 | N19: 0.02 | O19: 0.02 | P19: 0.02 | Q19: 0.02 | R19: 0.02 | S19: 0.02 | T19: 0.03 | U19: 0.02 | V19: 0.02 | W19: 0.03 | X19: 0.02 | Y19: 0.02 | Z19: 0.02 | AA19: 0.02 | AB19: 0.02 | AC19: 0.02 | AD19: 0.02 | AE19: 0.02 | AF19: 0.02 | AG19: 0.02 | AH19: 0.02 | AI19: 0.02 | AJ19: 0.02 | AK19: 0.02 | AL19: 0.02 | AM19: 0.02 | AN19: 0.02 | AO19: 0.02 | AP19: 0.02 | AQ19: 0.02 | AR19: 0.02 | AS19: 0.02 | AT19: 0.02 | AU19: 0.02 | AV19: 0.02 | AW19: 0.02 | AX19: 0.02 | AY19: 0.02 | AZ19: 0.02 | BA19: 0.03 | BB19: 0.02 | BC19: 0.02 | BD19: 0.02 | BE19: 0.02 | BF19: 0.02 | BG19: 0.02 | BH19: 0.02 | BI19: 0.03 | BJ19: 0.02 | BK19: 0.02 | BL19: 0.02 | BM19: 0.03 | BN19: 0.02 | BO19: 0.02 | BP19: 0.02 | BQ19: 0.03 | BR19: 0.02 | BS19: 0.02 | BT19: 0.02 | BU19: 0.03 | BV19: 0.02 | BW19: 0.02 | BX19: 0.02 | BY19: 0.03 | BZ19: 0.02 | CA19: 0.02 | CB19: 0.02 | CC19: 0.03 | CD19: 0.02 | CE19: 0.02
B20: Textiles, clothing & leather goods | C20: CC | D20: 0.01 | E20: 0.03 | F20: 0.03 | G20: 0.03 | H20: 0.03 | I20: 0.03 | J20: 0.02 | K20: 0.02 | L20: 0.03 | M20: 0.02 | N20: 0.02 | O20: 0.02 | P20: 0.02 | Q20: 0.02 | R20: 0.02 | S20: 0.02 | T20: 0.02 | U20: 0.02 | V20: 0.02 | W20: 0.02 | X20: 0.02 | Y20: 0.02 | Z20: 0.02 | AA20: 0.02 | AB20: 0.02 | AC20: 0.02 | AD20: 0.02 | AE20: 0.02 | AF20: 0.02 | AG20: 0 | AH20: 0 | AI20: 0 | AJ20: 0 | AK20: 0 | AL20: 0 | AM20: 0 | AN20: 0 | AO20: 0 | AP20: 0 | AQ20: 0 | AR20: 0 | AS20: 0 | AT20: 0 | AU20: 0 | AV20: 0 | AW20: 0 | AX20: 0 | AY20: 0 | AZ20: 0 | BA20: 0.01 | BB20: 0.01 | BC20: 0.01 | BD20: 0.01 | BE20: 0.01 | BF20: 0.01 | BG20: 0.01 | BH20: 0.01 | BI20: 0.01 | BJ20: 0.01 | BK20: 0.01 | BL20: 0.01 | BM20: 0.01 | BN20: 0.01 | BO20: 0.01 | BP20: 0.01 | BQ20: 0.01 | BR20: 0.01 | BS20: 0.01 | BT20: 0.01 | BU20: 0.01 | BV20: 0.01 | BW20: 0.01 | BX20: 0.01 | BY20: 0.01 | BZ20: 0.01 | CA20: 0.01 | CB20: 0.01 | CC20: 0.01 | CD20: 0.01 | CE20: 0.01
... B44: Cultural, domestic & other services | C44: R-T | D44: 0.03 | E44: 0.07 | F44: 0.06 | G44: 0.06 | H44: 0.06 | I44: 0.06 | J44: 0.06 | K44: 0.06 | L44: 0.06 | M44: 0.06 | N44: 0.05 | O44: 0.05 | P44: 0.05 | Q44: 0.05 | R44: 0.05 | S44: 0.05 | T44: 0.05 | U44: 0.05 | V44: 0.05 | W44: 0.05 | X44: 0.04 | Y44: 0.05 | Z44: 0.04 | AA44: 0.04 | AB44: 0.04 | AC44: 0.04 | AD44: 0.04 | AE44: 0.04 | AF44: 0.04 | AG44: 0.05 | AH44: 0.05 | AI44: 0.04 | AJ44: 0.04 | AK44: 0.05 | AL44: 0.05 | AM44: 0.06 | AN44: 0.05 | AO44: 0.05 | AP44: 0.06 | AQ44: 0.06 | AR44: 0.05 | AS44: 0.05 | AT44: 0.05 | AU44: 0.06 | AV44: 0.05 | AW44: 0.05 | AX44: 0.05 | AY44: 0.06 | AZ44: 0.05 | BA44: 0.05 | BB44: 0.05 | BC44: 0.06 | BD44: 0.05 | BE44: 0.05 | BF44: 0.04 | BG44: 0.05 | BH44: 0.04 | BI44: 0.04 | BJ44: 0.04 | BK44: 0.05 | BL44: 0.04 | BM44: 0.04 | BN44: 0.04 | BO44: 0.04 | BP44: 0.04 | BQ44: 0.04 | BR44: 0.03 | BS44: 0.04 | BT44: 0.03 | BU44: 0.03 | BV44: 0.03 | BW44: 0.03 | BX44: 0.05 | BY44: 0.03 | BZ44: 0.03 | CA44: 0.04 | CB44: 0.03 | CC44: 0.03 | CD44: 0.03 | CE44: 0.03
B46: Taxes less subsidies on products | D46: 0.05 | E46: 0.09 | F46: 0.09 | G46: 0.09 | H46: 0.09 | I46: 0.09 | J46: 0.09 | K46: 0.09 | L46: 0.09 | M46: 0.1 | N46: 0.09 | O46: 0.1 | P46: 0.1 | Q46: 0.1 | R46: 0.1 | S46: 0.09 | T46: 0.09 | U46: 0.09 | V46: 0.09 | W46: 0.1 | X46: 0.1 | Y46: 0.11 | Z46: 0.11 | AA46: 0.1 | AB46: 0.09 | AC46: 0.09 | AD46: 0.08 | AE46: 0.08 | AF46: 0.07 | AG46: 0.07 | AH46: 0.08 | AI46: 0.08 | AJ46: 0.08 | AK46: 0.08 | AL46: 0.09 | AM46: 0.1 | AN46: 0.08 | AO46: 0.08 | AP46: 0.09 | AQ46: 0.1 | AR46: 0.09 | AS46: 0.09 | AT46: 0.09 | AU46: 0.1 | AV46: 0.08 | AW46: 0.09 | AX46: 0.09 | AY46: 0.09 | AZ46: 0.08 | BA46: 0.08 | BB46: 0.08 | BC46: 0.09 | BD46: 0.08 | BE46: 0.09 | BF46: 0.09 | BG46: 0.08 | BH46: 0.08 | BI46: 0.08 | BJ46: 0.08 | BK46: 0.09 | BL46: 0.07 | BM46: 0.06 | BN46: 0.06 | BO46: 0.05 | BP46: 0.05 | BQ46: 0.05 | BR46: 0.06 | BS46: 0.06 | BT46: 0.05 | BU46: 0.05 | BV46: 0.05 | BW46: 0.06 | BX46: 0.04 | BY46: 0.05 | BZ46: 0.05 | CA46: 0.06 | CB46: 0.04 | CC46: 0.05 | CD46: 0.05 | CE46: 0.06
B48: =QGDP_CP!B48 -> Source: National Institute of Statistics of Rwanda
B49: =QGDP_CP!B49 -> 46007

Sheet QGDP_KP
B1: Table 2
B2: Gross Domestic Product by Kind of Activity
B3: =" at constant "&QGDP_KP!$D$5&" prices" -> at constant 2024 prices
B4: (in billion Frw) | D4: Base year
B5: Activity description | C5: ISIC4 | D5: 2024 | E5: 2006 Q1 | F5: 2006 Q2 | G5: 2006 Q3 | H5: 2006 Q4 | I5: 2007 Q1 | J5: 2007 Q2 | K5: 2007 Q3 | L5: 2007 Q4 | M5: 2008 Q1 | N5: 2008 Q2 | O5: 2008 Q3 | P5: 2008 Q4 | Q5: 2009 Q1 | R5: 2009 Q2 | S5: 2009 Q3 | T5: 2009 Q4 | U5: 2010 Q1 | V5: 2010 Q2 | W5: 2010 Q3 | X5: 2010 Q4 | Y5: 2011 Q1 | Z5: 2011 Q2 | AA5: 2011 Q3 | AB5: 2011 Q4 | AC5: 2012 Q1 | AD5: 2012 Q2 | AE5: 2012 Q3 | AF5: 2012 Q4 | AG5: 2013 Q1 | AH5: 2013 Q2 | AI5: 2013 Q3 | AJ5: 2013 Q4 | AK5: 2014 Q1 | AL5: 2014 Q2 | AM5: 2014 Q3 | AN5: 2014 Q4 | AO5: 2015 Q1 | AP5: 2015 Q2 | AQ5: 2015 Q3 | AR5: 2015 Q4 | AS5: 2016 Q1 | AT5: 2016 Q2 | AU5: 2016 Q3 | AV5: 2016 Q4 | AW5: 2017 Q1 | AX5: 2017 Q2 | AY5: 2017 Q3 | AZ5: 2017 Q4 | BA5: 2018 Q1 | BB5: 2018 Q2 | BC5: 2018 Q3 | BD5: 2018 Q4 | BE5: 2019 Q1 | BF5: 2019 Q2 | BG5: 2019 Q3 | BH5: 2019 Q4 | BI5: 2020 Q1 | BJ5: 2020 Q2 | BK5: 2020 Q3 | BL5: 2020 Q4 | BM5: 2021 Q1 | BN5: 2021 Q2 | BO5: 2021 Q3 | BP5: 2021 Q4 | BQ5: 2022 Q1 | BR5: 2022 Q2 | BS5: 2022 Q3 | BT5: 2022 Q4 | BU5: 2023 Q1 | BV5: 2023 Q2 | BW5: 2023 Q3 | BX5: 2023 Q4 | BY5: 2024 Q1 | BZ5: 2024 Q2 | CA5: 2024 Q3 | CB5: 2024 Q4 | CC5: 2025 Q1 | CD5: 2025 Q2 | CE5: 2025 Q3
B7: GROSS DOMESTIC PRODUCT (GDP) | D7: 19918 | E7: 1323 | F7: 1421 | G7: 1561 | H7: 1564 | I7: 1500 | J7: 1531 | K7: 1619 | L7: 1666 | M7: 1642 | N7: 1736 | O7: 1810 | P7: 1833 | Q7: 1842 | R7: 1824 | S7: 1874 | T7: 1920 | U7: 1937 | V7: 1940 | W7: 2024 | X7: 2105 | Y7: 2101 | Z7: 2055 | AA7: 2234 | AB7: 2254 | AC7: 2277 | AD7: 2275 | AE7: 2393 | AF7: 2445 | AG7: 2384 | AH7: 2456 | AI7: 2455 | AJ7: 2539 | AK7: 2504 | AL7: 2610 | AM7: 2368 | AN7: 2910 | AO7: 2723 | AP7: 2858 | AQ7: 2569 | AR7: 3164 | AS7: 2955 | AT7: 3059 | AU7: 2689 | AV7: 3251 | AW7: 3016 | AX7: 3214 | AY7: 2808 | AZ7: 3479 | BA7: 3264 | BB7: 3433 | BC7: 3026 | BD7: 3804 | BE7: 3468 | BF7: 3885 | BG7: 3383 | BH7: 4046 | BI7: 3621 | BJ7: 3451 | BK7: 3258 | BL7: 4042 | BM7: 3707 | BN7: 4070 | BO7: 3454 | BP7: 4350 | BQ7: 4074 | BR7: 4541 | BS7: 3852 | BT7: 4644 | BU7: 4386 | BV7: 4659 | BW7: 4261 | BX7: 5270 | BY7: 4741 | BZ7: 5137 | CA7: 4550 | CB7: 5489 | CC7: 5052 | CD7: 5540 | CE7: 5089
B9: AGRICULTURE, FORESTRY & FISHING | C9: A | D9: 4142 | E9: 431 | F9: 435 | G9: 506 | H9: 509 | I9: 463 | J9: 463 | K9: 502 | L9: 501 | M9: 503 | N9: 509 | O9: 521 | P9: 520 | Q9: 542 | R9: 545 | S9: 563 | T9: 562 | U9: 564 | V9: 567 | W9: 597 | X9: 594 | Y9: 589 | Z9: 591 | AA9: 634 | AB9: 610 | AC9: 627 | AD9: 636 | AE9: 652 | AF9: 673 | AG9: 668 | AH9: 682 | AI9: 658 | AJ9: 666 | AK9: 678 | AL9: 757 | AM9: 420 | AN9: 958 | AO9: 724 | AP9: 802 | AQ9: 441 | AR9: 973 | AS9: 734 | AT9: 803 | AU9: 469 | AV9: 1014 | AW9: 792 | AX9: 929 | AY9: 441 | AZ9: 1095 | BA9: 819 | BB9: 965 | BC9: 472 | BD9: 1145 | BE9: 855 | BF9: 1050 | BG9: 513 | BH9: 1130 | BI9: 871 | BJ9: 1069 | BK9: 547 | BL9: 1181 | BM9: 892 | BN9: 1112 | BO9: 595 | BP9: 1210 | BQ9: 888 | BR9: 1121 | BS9: 606 | BT9: 1211 | BU9: 924 | BV9: 1138 | BW9: 658 | BX9: 1293 | BY9: 978 | BZ9: 1180 | CA9: 677 | CB9: 1307 | CC9: 1014 | CD9: 1269 | CE9: 747
B10: Food crops | C10: AA | D10: 2373 | E10: 259 | F10: 259 | G10: 312 | H10: 312 | I10: 284 | J10: 284 | K10: 310 | L10: 310 | M10: 310 | N10: 310 | O10: 320 | P10: 320 | Q10: 339 | R10: 339 | S10: 351 | T10: 351 | U10: 352 | V10: 352 | W10: 371 | X10: 371 | Y10: 378 | Z10: 378 | AA10: 372 | AB10: 372 | AC10: 419 | AD10: 419 | AE10: 393 | AF10: 393 | AG10: 448 | AH10: 448 | AI10: 396 | AJ10: 396 | AK10: 444 | AL10: 510 | AM10: 151 | AN10: 680 | AO10: 477 | AP10: 535 | AQ10: 152 | AR10: 680 | AS10: 454 | AT10: 535 | AU10: 174 | AV10: 709 | AW10: 514 | AX10: 639 | AY10: 140 | AZ10: 765 | BA10: 511 | BB10: 661 | BC10: 152 | BD10: 799 | BE10: 533 | BF10: 722 | BG10: 160 | BH10: 770 | BI10: 543 | BJ10: 745 | BK10: 189 | BL10: 804 | BM10: 543 | BN10: 750 | BO10: 195 | BP10: 801 | BQ10: 537 | BR10: 723 | BS10: 203 | BT10: 778 | BU10: 554 | BV10: 736 | BW10: 242 | BX10: 831 | BY10: 574 | BZ10: 752 | CA10: 219 | CB10: 828 | CC10: 583 | CD10: 777 | CE10: 228
B11: Export crops | C11: AB | D11: 351 | E11: 59 | F11: 74 | G11: 68 | H11: 77 | I11: 44 | J11: 46 | K11: 56 | L11: 51 | M11: 52 | N11: 74 | O11: 68 | P11: 60 | Q11: 44 | R11: 57 | S11: 61 | T11: 54 | U11: 51 | V11: 62 | W11: 75 | X11: 58 | Y11: 39 | Z11: 43 | AA11: 105 | AB11: 67 | AC11: 32 | AD11: 41 | AE11: 91 | AF11: 112 | AG11: 38 | AH11: 54 | AI11: 81 | AJ11: 89 | AK11: 39 | AL11: 51 | AM11: 84 | AN11: 83 | AO11: 42 | AP11: 65 | AQ11: 98 | AR11: 90 | AS11: 71 | AT11: 51 | AU11: 89 | AV11: 91 | AW11: 54 | AX11: 63 | AY11: 82 | AZ11: 107 | BA11: 75 | BB11: 62 | BC11: 86 | BD11: 104 | BE11: 70 | BF11: 67 | BG11: 106 | BH11: 99 | BI11: 59 | BJ11: 55 | BK11: 97 | BL11: 99 | BM11: 63 | BN11: 78 | BO11: 101 | BP11: 117 | BQ11: 47 | BR11: 84 | BS11: 96 | BT11: 119 | BU11: 57 | BV11: 83 | BW11: 85 | BX11: 120 | BY11: 63 | BZ11: 81 | CA11: 99 | CB11: 109 | CC11: 63 | CD11: 115 | CE11: 133
B12: Livestock & livestock products | C12: AC | D12: 581 | E12: 42 | F12: 42 | G12: 42 | H12: 43 | I12: 43 | J12: 43 | K12: 44 | L12: 44 | M12: 44 | N12: 44 | O12: 45 | P12: 45 | Q12: 45 | R12: 46 | S12: 46 | T12: 47 | U12: 47 | V12: 48 | W12: 48 | X12: 49 | Y12: 48 | Z12: 49 | AA12: 50 | AB12: 51 | AC12: 51 | AD12: 53 | AE12: 53 | AF12: 54 | AG12: 55 | AH12: 55 | AI12: 57 | AJ12: 57 | AK12: 58 | AL12: 60 | AM12: 62 | AN12: 63 | AO12: 64 | AP12: 65 | AQ12: 67 | AR12: 68 | AS12: 70 | AT12: 72 | AU12: 73 | AV12: 75 | AW12: 76 | AX12: 78 | AY12: 80 | AZ12: 82 | BA12: 84 | BB12: 86 | BC12: 89 | BD12: 91 | BE12: 93 | BF12: 96 | BG12: 98 | BH12: 101 | BI12: 101 | BJ12: 104 | BK12: 107 | BL12: 110 | BM12: 110 | BN12: 107 | BO12: 119 | BP12: 110 | BQ12: 117 | BR12: 123 | BS12: 116 | BT12: 120 | BU12: 119 | BV12: 122 | BW12: 130 | BX12: 139 | BY12: 137 | BZ12: 139 | CA12: 148 | CB12: 157 | CC12: 152 | CD12: 157 | CE12: 157
B13: Forestry | C13: AD | D13: 782 | E13: 95 | F13: 96 | G13: 97 | H13: 98 | I13: 98 | J13: 99 | K13: 100 | L13: 102 | M13: 102 | N13: 103 | O13: 104 | P13: 105 | Q13: 104 | R13: 105 | S13: 106 | T13: 108 | U13: 107 | V13: 108 | W13: 110 | X13: 112 | Y13: 112 | Z13: 110 | AA13: 112 | AB13: 114 | AC13: 115 | AD13: 115 | AE13: 117 | AF13: 119 | AG13: 118 | AH13: 119 | AI13: 120 | AJ13: 121 | AK13: 122 | AL13: 123 | AM13: 124 | AN13: 125 | AO13: 126 | AP13: 127 | AQ13: 129 | AR13: 130 | AS13: 131 | AT13: 132 | AU13: 134 | AV13: 134 | AW13: 135 | AX13: 136 | AY13: 138 | AZ13: 139 | BA13: 140 | BB13: 142 | BC13: 144 | BD13: 146 | BE13: 148 | BF13: 151 | BG13: 152 | BH13: 154 | BI13: 154 | BJ13: 154 | BK13: 158 | BL13: 160 | BM13: 162 | BN13: 162 | BO13: 166 | BP13: 168 | BQ13: 172 | BR13: 175 | BS13: 177 | BT13: 180 | BU13: 180 | BV13: 184 | BW13: 188 | BX13: 190 | BY13: 192 | BZ13: 194 | CA13: 197 | CB13: 200 | CC13: 202 | CD13: 205 | CE13: 209
B14: Fishing | C14: AE | D14: 54 | E14: 9 | F14: 9 | G14: 9 | H14: 9 | I14: 9 | J14: 9 | K14: 9 | L14: 9 | M14: 9 | N14: 10 | O14: 10 | P14: 10 | Q14: 10 | R14: 10 | S14: 10 | T14: 10 | U14: 10 | V14: 10 | W14: 10 | X14: 10 | Y14: 11 | Z14: 11 | AA14: 10 | AB14: 10 | AC14: 10 | AD14: 10 | AE14: 10 | AF14: 10 | AG14: 10 | AH14: 11 | AI14: 11 | AJ14: 11 | AK14: 11 | AL14: 11 | AM14: 11 | AN14: 11 | AO14: 11 | AP14: 11 | AQ14: 11 | AR14: 11 | AS14: 12 | AT14: 12 | AU14: 12 | AV14: 12 | AW14: 12 | AX14: 12 | AY14: 12 | AZ14: 13 | BA14: 13 | BB14: 13 | BC14: 13 | BD14: 13 | BE14: 13 | BF14: 13 | BG14: 13 | BH14: 14 | BI14: 14 | BJ14: 7 | BK14: 11 | BL14: 14 | BM14: 14 | BN14: 14 | BO14: 14 | BP14: 14 | BQ14: 14 | BR14: 14 | BS14: 14 | BT14: 14 | BU14: 14 | BV14: 14 | BW14: 14 | BX14: 13 | BY14: 12 | BZ14: 13 | CA14: 14 | CB14: 14 | CC14: 15 | CD14: 16 | CE14: 19
B15: INDUSTRY | C15: B-F | D15: 4396 | E15: 221 | F15: 251 | G15: 280 | H15: 293 | I15: 270 | J15: 264 | K15: 296 | L15: 308 | M15: 297 | N15: 321 | O15: 346 | P15: 347 | Q15: 340 | R15: 317 | S15: 323 | T15: 348 | U15: 365 | V15: 331 | W15: 353 | X15: 392 | Y15: 419 | Z15: 377 | AA15: 430 | AB15: 471 | AC15: 432 | AD15: 415 | AE15: 473 | AF15: 518 | AG15: 491 | AH15: 491 | AI15: 511 | AJ15: 516 | AK15: 491 | AL15: 493 | AM15: 555 | AN15: 522 | AO15: 522 | AP15: 538 | AQ15: 582 | AR15: 603 | AS15: 608 | AT15: 603 | AU15: 586 | AV15: 598 | AW15: 592 | AX15: 596 | AY15: 612 | AZ15: 631 | BA15: 616 | BB15: 644 | BC15: 674 | BD15: 708 | BE15: 707 | BF15: 781 | BG15: 782 | BH15: 808 | BI15: 721 | BJ15: 633 | BK15: 771 | BL15: 823 | BM15: 790 | BN15: 731 | BO15: 736 | BP15: 842 | BQ15: 943 | BR15: 1015 | BS15: 849 | BT15: 960 | BU15: 966 | BV15: 989 | BW15: 982 | BX15: 1152 | BY15: 1136 | BZ15: 1120 | CA15: 993 | CB15: 1147 | CC15: 1193 | CD15: 1198 | CE15: 1159
B16: Mining & quarrying | C16: B | D16: 354 | E16: 24 | F16: 34 | G16: 37 | H16: 42 | I16: 50 | J16: 48 | K16: 43 | L16: 54 | M16: 38 | N16: 49 | O16: 39 | P16: 39 | Q16: 35 | R16: 33 | S16: 38 | T16: 30 | U16: 20 | V16: 34 | W16: 34 | X16: 33 | Y16: 44 | Z16: 38 | AA16: 47 | AB16: 52 | AC16: 43 | AD16: 37 | AE16: 42 | AF16: 46 | AG16: 47 | AH16: 49 | AI16: 51 | AJ16: 53 | AK16: 55 | AL16: 52 | AM16: 87 | AN16: 58 | AO16: 53 | AP16: 53 | AQ16: 67 | AR16: 66 | AS16: 60 | AT16: 68 | AU16: 68 | AV16: 69 | AW16: 70 | AX16: 72 | AY16: 84 | AZ16: 92 | BA16: 68 | BB16: 77 | BC16: 89 | BD16: 94 | BE16: 78 | BF16: 88 | BG16: 77 | BH16: 82 | BI16: 58 | BJ16: 42 | BK16: 58 | BL16: 67 | BM16: 60 | BN16: 54 | BO16: 61 | BP16: 63 | BQ16: 74 | BR16: 81 | BS16: 72 | BT16: 78 | BU16: 73 | BV16: 78 | BW16: 83 | BX16: 93 | BY16: 94 | BZ16: 86 | CA16: 87 | CB16: 87 | CC16: 94 | CD16: 96 | CE16: 99
B17: TOTAL MANUFACTURING | C17: C | D17: 1618 | E17: 120 | F17: 136 | G17: 168 | H17: 170 | I17: 131 | J17: 135 | K17: 167 | L17: 165 | M17: 142 | N17: 155 | O17: 169 | P17: 164 | Q17: 147 | R17: 156 | S17: 171 | T17: 174 | U17: 170 | V17: 164 | W17: 185 | X17: 189 | Y17: 171 | Z17: 176 | AA17: 213 | AB17: 209 | AC17: 187 | AD17: 189 | AE17: 219 | AF17: 219 | AG17: 205 | AH17: 210 | AI17: 224 | AJ17: 212 | AK17: 176 | AL17: 182 | AM17: 194 | AN17: 192 | AO17: 193 | AP17: 196 | AQ17: 208 | AR17: 208 | AS17: 218 | AT17: 219 | AU17: 211 | AV17: 212 | AW17: 225 | AX17: 232 | AY17: 225 | AZ17: 233 | BA17: 251 | BB17: 264 | BC17: 257 | BD17: 268 | BE17: 268 | BF17: 304 | BG17: 291 | BH17: 293 | BI17: 283 | BJ17: 266 | BK17: 310 | BL17: 321 | BM17: 307 | BN17: 342 | BO17: 274 | BP17: 349 | BQ17: 338 | BR17: 383 | BS17: 296 | BT17: 373 | BU17: 391 | BV17: 387 | BW17: 329 | BX17: 418 | BY17: 388 | BZ17: 427 | CA17: 356 | CB17: 448 | CC17: 422 | CD17: 459 | CE17: 406
B18: Of which: Food | C18: CA | D18: 383 | E18: 18 | F18: 22 | G18: 29 | H18: 30 | I18: 20 | J18: 20 | K18: 28 | L18: 26 | M18: 23 | N18: 25 | O18: 28 | P18: 26 | Q18: 25 | R18: 27 | S18: 30 | T18: 27 | U18: 27 | V18: 28 | W18: 33 | X18: 30 | Y18: 25 | Z18: 25 | AA18: 36 | AB18: 37 | AC18: 25 | AD18: 27 | AE18: 35 | AF18: 37 | AG18: 34 | AH18: 33 | AI18: 34 | AJ18: 34 | AK18: 34 | AL18: 35 | AM18: 37 | AN18: 37 | AO18: 36 | AP18: 35 | AQ18: 34 | AR18: 38 | AS18: 42 | AT18: 41 | AU18: 34 | AV18: 38 | AW18: 43 | AX18: 43 | AY18: 41 | AZ18: 45 | BA18: 51 | BB18: 54 | BC18: 42 | BD18: 49 | BE18: 50 | BF18: 56 | BG18: 48 | BH18: 50 | BI18: 56 | BJ18: 56 | BK18: 52 | BL18: 55 | BM18: 60 | BN18: 89 | BO18: 52 | BP18: 92 | BQ18: 65 | BR18: 107 | BS18: 58 | BT18: 103 | BU18: 79 | BV18: 109 | BW18: 63 | BX18: 125 | BY18: 82 | BZ18: 115 | CA18: 67 | CB18: 119 | CC18: 86 | CD18: 127 | CE18: 75
B19: Beverages & tobacco | C19: CB | D19: 486 | E19: 65 | F19: 65 | G19: 92 | H19: 91 | I19: 67 | J19: 68 | K19: 86 | L19: 87 | M19: 73 | N19: 75 | O19: 86 | P19: 83 | Q19: 75 | R19: 75 | S19: 91 | T19: 90 | U19: 75 | V19: 74 | W19: 96 | X19: 92 | Y19: 83 | Z19: 86 | AA19: 101 | AB19: 94 | AC19: 90 | AD19: 88 | AE19: 102 | AF19: 98 | AG19: 91 | AH19: 97 | AI19: 106 | AJ19: 99 | AK19: 102 | AL19: 99 | AM19: 111 | AN19: 110 | AO19: 108 | AP19: 107 | AQ19: 120 | AR19: 111 | AS19: 114 | AT19: 115 | AU19: 122 | AV19: 110 | AW19: 111 | AX19: 108 | AY19: 104 | AZ19: 100 | BA19: 103 | BB19: 106 | BC19: 118 | BD19: 112 | BE19: 111 | BF19: 125 | BG19: 128 | BH19: 123 | BI19: 117 | BJ19: 110 | BK19: 134 | BL19: 132 | BM19: 122 | BN19: 98 | BO19: 76 | BP19: 115 | BQ19: 137 | BR19: 122 | BS19: 86 | BT19: 117 | BU19: 139 | BV19: 117 | BW19: 88 | BX19: 116 | BY19: 142 | BZ19: 125 | CA19: 92 | CB19: 127 | CC19: 146 | CD19: 121 | CE19: 99
B20: Textiles, clothing & leather goods | C20: CC | D20: 135 | E20: 28 | F20: 30 | G20: 29 | H20: 29 | I20: 29 | J20: 31 | K20: 32 | L20: 35 | M20: 30 | N20: 34 | O20: 31 | P20: 30 | Q20: 31 | R20: 30 | S20: 31 | T20: 32 | U20: 31 | V20: 32 | W20: 32 | X20: 33 | Y20: 33 | Z20: 29 | AA20: 30 | AB20: 32 | AC20: 34 | AD20: 36 | AE20: 32 | AF20: 32 | AG20: 7 | AH20: 7 | AI20: 8 | AJ20: 8 | AK20: 8 | AL20: 8 | AM20: 8 | AN20: 8 | AO20: 8 | AP20: 8 | AQ20: 8 | AR20: 8 | AS20: 9 | AT20: 9 | AU20: 9 | AV20: 10 | AW20: 12 | AX20: 14 | AY20: 12 | AZ20: 12 | BA20: 18 | BB20: 20 | BC20: 21 | BD20: 22 | BE20: 20 | BF20: 22 | BG20: 25 | BH20: 28 | BI20: 22 | BJ20: 19 | BK20: 24 | BL20: 26 | BM20: 22 | BN20: 25 | BO20: 25 | BP20: 27 | BQ20: 24 | BR20: 27 | BS20: 28 | BT20: 30 | BU20: 27 | BV20: 30 | BW20: 32 | BX20: 35 | BY20: 30 | BZ20: 36 | CA20: 36 | CB20: 34 | CC20: 30 | CD20: 32 | CE20: 34
... B44: Cultural, domestic & other services | C44: R-T | D44: 640 | E44: 40 | F44: 42 | G44: 42 | H44: 44 | I44: 47 | J44: 47 | K44: 49 | L44: 48 | M44: 49 | N44: 47 | O44: 50 | P44: 49 | Q44: 45 | R44: 45 | S44: 46 | T44: 48 | U44: 49 | V44: 48 | W44: 50 | X44: 50 | Y44: 50 | Z44: 47 | AA44: 48 | AB44: 50 | AC44: 52 | AD44: 52 | AE44: 55 | AF44: 58 | AG44: 58 | AH44: 62 | AI44: 60 | AJ44: 63 | AK44: 66 | AL44: 71 | AM44: 75 | AN44: 71 | AO44: 79 | AP44: 86 | AQ44: 85 | AR44: 87 | AS44: 88 | AT44: 88 | AU44: 91 | AV44: 93 | AW44: 93 | AX44: 93 | AY44: 96 | AZ44: 97 | BA44: 99 | BB44: 101 | BC44: 102 | BD44: 110 | BE44: 107 | BF44: 111 | BG44: 113 | BH44: 116 | BI44: 107 | BJ44: 107 | BK44: 114 | BL44: 114 | BM44: 114 | BN44: 120 | BO44: 121 | BP44: 131 | BQ44: 122 | BR44: 126 | BS44: 132 | BT44: 135 | BU44: 130 | BV44: 132 | BW44: 143 | BX44: 261 | BY44: 143 | BZ44: 157 | CA44: 164 | CB44: 176 | CC44: 166 | CD44: 182 | CE44: 185
B46: Taxes less subsidies on products | D46: 985 | E46: 99 | F46: 91 | G46: 101 | H46: 103 | I46: 114 | J46: 95 | K46: 97 | L46: 105 | M46: 120 | N46: 102 | O46: 121 | P46: 116 | Q46: 121 | R46: 119 | S46: 126 | T46: 137 | U46: 124 | V46: 133 | W46: 134 | X46: 137 | Y46: 129 | Z46: 131 | AA46: 138 | AB46: 139 | AC46: 138 | AD46: 133 | AE46: 147 | AF46: 127 | AG46: 119 | AH46: 132 | AI46: 135 | AJ46: 141 | AK46: 138 | AL46: 140 | AM46: 144 | AN46: 148 | AO46: 154 | AP46: 163 | AQ46: 164 | AR46: 170 | AS46: 170 | AT46: 178 | AU46: 169 | AV46: 162 | AW46: 161 | AX46: 162 | AY46: 167 | AZ46: 172 | BA46: 176 | BB46: 176 | BC46: 178 | BD46: 192 | BE46: 191 | BF46: 218 | BG46: 207 | BH46: 215 | BI46: 209 | BJ46: 199 | BK46: 199 | BL46: 210 | BM46: 215 | BN46: 252 | BO46: 192 | BP46: 244 | BQ46: 230 | BR46: 261 | BS46: 235 | BT46: 224 | BU46: 220 | BV46: 244 | BW46: 231 | BX46: 217 | BY46: 229 | BZ46: 273 | CA46: 253 | CB46: 230 | CC46: 245 | CD46: 288 | CE46: 305
B48: =QGDP_CP!B48 -> Source: National Institute of Statistics of Rwanda
B49: =QGDP_CP!B49 -> 46007

Sheet QGDP_Gr
B1: Table 2A
B2: Gross Domestic Product by Kind of Activity
B3: ="Growthrates at constant "&QGDP_KP!$D$5&" prices" -> Growthrates at constant 2024 prices
B4: (Percentage change from the previous year)
B5: Activity description | C5: ISIC4 | E5: 2006 Q1 | F5: 2006 Q2 | G5: 2006 Q3 | H5: 2006 Q4 | I5: 2007 Q1 | J5: 2007 Q2 | K5: 2007 Q3 | L5: 2007 Q4 | M5: 2008 Q1 | N5: 2008 Q2 | O5: 2008 Q3 | P5: 2008 Q4 | Q5: 2009 Q1 | R5: 2009 Q2 | S5: 2009 Q3 | T5: 2009 Q4 | U5: 2010 Q1 | V5: 2010 Q2 | W5: 2010 Q3 | X5: 2010 Q4 | Y5: 2011 Q1 | Z5: 2011 Q2 | AA5: 2011 Q3 | AB5: 2011 Q4 | AC5: 2012 Q1 | AD5: 2012 Q2 | AE5: 2012 Q3 | AF5: 2012 Q4 | AG5: 2013 Q1 | AH5: 2013 Q2 | AI5: 2013 Q3 | AJ5: 2013 Q4 | AK5: 2014 Q1 | AL5: 2014 Q2 | AM5: 2014 Q3 | AN5: 2014 Q4 | AO5: 2015 Q1 | AP5: 2015 Q2 | AQ5: 2015 Q3 | AR5: 2015 Q4 | AS5: 2016 Q1 | AT5: 2016 Q2 | AU5: 2016 Q3 | AV5: 2016 Q4 | AW5: 2017 Q1 | AX5: 2017 Q2 | AY5: 2017 Q3 | AZ5: 2017 Q4 | BA5: 2018 Q1 | BB5: 2018 Q2 | BC5: 2018 Q3 | BD5: 2018 Q4 | BE5: 2019 Q1 | BF5: 2019 Q2 | BG5: 2019 Q3 | BH5: 2019 Q4 | BI5: 2020 Q1 | BJ5: 2020 Q2 | BK5: 2020 Q3 | BL5: 2020 Q4 | BM5: 2021 Q1 | BN5: 2021 Q2 | BO5: 2021 Q3 | BP5: 2021 Q4 | BQ5: 2022 Q1 | BR5: 2022 Q2 | BS5: 2022 Q3 | BT5: 2022 Q4 | BU5: 2023 Q1 | BV5: 2023 Q2 | BW5: 2023 Q3 | BX5: 2023 Q4 | BY5: 2024 Q1 | BZ5: 2024 Q2 | CA5: 2024 Q3 | CB5: 2024 Q4 | CC5: 2025 Q1 | CD5: 2025 Q2 | CE5: 2025 Q3
B7: GROSS DOMESTIC PRODUCT (GDP) | I7: 0.134 | J7: 0.077 | K7: 0.037 | L7: 0.066 | M7: 0.094 | N7: 0.134 | O7: 0.118 | P7: 0.1 | Q7: 0.122 | R7: 0.05 | S7: 0.035 | T7: 0.047 | U7: 0.052 | V7: 0.064 | W7: 0.08 | X7: 0.097 | Y7: 0.084 | Z7: 0.059 | AA7: 0.103 | AB7: 0.071 | AC7: 0.084 | AD7: 0.107 | AE7: 0.072 | AF7: 0.085 | AG7: 0.047 | AH7: 0.08 | AI7: 0.026 | AJ7: 0.038 | AK7: 0.05 | AL7: 0.062 | AM7: -0.036 | AN7: 0.146 | AO7: 0.088 | AP7: 0.095 | AQ7: 0.085 | AR7: 0.087 | AS7: 0.085 | AT7: 0.07 | AU7: 0.047 | AV7: 0.028 | AW7: 0.021 | AX7: 0.051 | AY7: 0.044 | AZ7: 0.07 | BA7: 0.082 | BB7: 0.068 | BC7: 0.078 | BD7: 0.093 | BE7: 0.063 | BF7: 0.132 | BG7: 0.118 | BH7: 0.064 | BI7: 0.044 | BJ7: -0.112 | BK7: -0.037 | BL7: -0.001 | BM7: 0.024 | BN7: 0.179 | BO7: 0.06 | BP7: 0.076 | BQ7: 0.099 | BR7: 0.116 | BS7: 0.115 | BT7: 0.068 | BU7: 0.077 | BV7: 0.026 | BW7: 0.106 | BX7: 0.135 | BY7: 0.081 | BZ7: 0.103 | CA7: 0.068 | CB7: 0.042 | CC7: 0.065 | CD7: 0.078 | CE7: 0.118
B9: AGRICULTURE, FORESTRY & FISHING | C9: A | I9: 0.07 | J9: 0.07 | K9: -0.01 | L9: -0.01 | M9: 0.09 | N9: 0.1 | O9: 0.04 | P9: 0.04 | Q9: 0.08 | R9: 0.07 | S9: 0.08 | T9: 0.08 | U9: 0.04 | V9: 0.04 | W9: 0.06 | X9: 0.06 | Y9: 0.04 | Z9: 0.04 | AA9: 0.06 | AB9: 0.03 | AC9: 0.07 | AD9: 0.08 | AE9: 0.03 | AF9: 0.1 | AG9: 0.06 | AH9: 0.07 | AI9: 0.01 | AJ9: -0.01 | AK9: 0.02 | AL9: 0.11 | AM9: -0.36 | AN9: 0.44 | AO9: 0.07 | AP9: 0.06 | AQ9: 0.05 | AR9: 0.02 | AS9: 0.01 | AT9: 0 | AU9: 0.06 | AV9: 0.04 | AW9: 0.08 | AX9: 0.16 | AY9: -0.06 | AZ9: 0.08 | BA9: 0.03 | BB9: 0.04 | BC9: 0.07 | BD9: 0.05 | BE9: 0.04 | BF9: 0.09 | BG9: 0.09 | BH9: -0.01 | BI9: 0.02 | BJ9: 0.02 | BK9: 0.07 | BL9: 0.05 | BM9: 0.02 | BN9: 0.04 | BO9: 0.09 | BP9: 0.02 | BQ9: 0 | BR9: 0.01 | BS9: 0.02 | BT9: 0 | BU9: 0.04 | BV9: 0.02 | BW9: 0.09 | BX9: 0.07 | BY9: 0.06 | BZ9: 0.04 | CA9: 0.03 | CB9: 0.01 | CC9: 0.04 | CD9: 0.08 | CE9: 0.1
B10: Food crops | C10: AA | I10: 0.1 | J10: 0.1 | K10: -0.01 | L10: -0.01 | M10: 0.09 | N10: 0.09 | O10: 0.03 | P10: 0.03 | Q10: 0.09 | R10: 0.09 | S10: 0.1 | T10: 0.1 | U10: 0.04 | V10: 0.04 | W10: 0.06 | X10: 0.06 | Y10: 0.07 | Z10: 0.07 | AA10: 0 | AB10: 0 | AC10: 0.11 | AD10: 0.11 | AE10: 0.06 | AF10: 0.06 | AG10: 0.07 | AH10: 0.07 | AI10: 0.01 | AJ10: 0.01 | AK10: -0.01 | AL10: 0.14 | AM10: -0.62 | AN10: 0.72 | AO10: 0.07 | AP10: 0.05 | AQ10: 0 | AR10: 0 | AS10: -0.05 | AT10: 0 | AU10: 0.15 | AV10: 0.04 | AW10: 0.13 | AX10: 0.2 | AY10: -0.2 | AZ10: 0.08 | BA10: 0 | BB10: 0.03 | BC10: 0.09 | BD10: 0.05 | BE10: 0.04 | BF10: 0.09 | BG10: 0.05 | BH10: -0.04 | BI10: 0.02 | BJ10: 0.03 | BK10: 0.18 | BL10: 0.04 | BM10: 0 | BN10: 0.01 | BO10: 0.03 | BP10: 0 | BQ10: -0.01 | BR10: -0.04 | BS10: 0.04 | BT10: -0.03 | BU10: 0.03 | BV10: 0.02 | BW10: 0.19 | BX10: 0.07 | BY10: 0.04 | BZ10: 0.02 | CA10: -0.1 | CB10: 0 | CC10: 0.01 | CD10: 0.03 | CE10: 0.04
B11: Export crops | C11: AB | I11: -0.25 | J11: -0.38 | K11: -0.19 | L11: -0.33 | M11: 0.18 | N11: 0.61 | O11: 0.22 | P11: 0.18 | Q11: -0.15 | R11: -0.23 | S11: -0.11 | T11: -0.11 | U11: 0.16 | V11: 0.09 | W11: 0.23 | X11: 0.08 | Y11: -0.24 | Z11: -0.31 | AA11: 0.4 | AB11: 0.16 | AC11: -0.19 | AD11: -0.04 | AE11: -0.13 | AF11: 0.67 | AG11: 0.2 | AH11: 0.33 | AI11: -0.11 | AJ11: -0.2 | AK11: 0.03 | AL11: -0.05 | AM11: 0.03 | AN11: -0.07 | AO11: 0.08 | AP11: 0.26 | AQ11: 0.17 | AR11: 0.07 | AS11: 0.7 | AT11: -0.22 | AU11: -0.1 | AV11: 0.02 | AW11: -0.24 | AX11: 0.25 | AY11: -0.07 | AZ11: 0.17 | BA11: 0.4 | BB11: -0.01 | BC11: 0.04 | BD11: -0.03 | BE11: -0.07 | BF11: 0.08 | BG11: 0.23 | BH11: -0.04 | BI11: -0.16 | BJ11: -0.19 | BK11: -0.08 | BL11: 0 | BM11: 0.07 | BN11: 0.43 | BO11: 0.04 | BP11: 0.18 | BQ11: -0.25 | BR11: 0.08 | BS11: -0.04 | BT11: 0.02 | BU11: 0.21 | BV11: -0.01 | BW11: -0.12 | BX11: 0 | BY11: 0.09 | BZ11: -0.03 | CA11: 0.17 | CB11: -0.09 | CC11: 0 | CD11: 0.42 | CE11: 0.35
B12: Livestock & livestock products | C12: AC | I12: 0.02 | J12: 0.02 | K12: 0.02 | L12: 0.02 | M12: 0.03 | N12: 0.03 | O12: 0.03 | P12: 0.03 | Q12: 0.03 | R12: 0.03 | S12: 0.03 | T12: 0.04 | U12: 0.04 | V12: 0.04 | W12: 0.05 | X12: 0.05 | Y12: 0.02 | Z12: 0.03 | AA12: 0.04 | AB12: 0.03 | AC12: 0.06 | AD12: 0.07 | AE12: 0.05 | AF12: 0.06 | AG12: 0.06 | AH12: 0.05 | AI12: 0.08 | AJ12: 0.07 | AK12: 0.07 | AL12: 0.08 | AM12: 0.09 | AN12: 0.09 | AO12: 0.1 | AP12: 0.09 | AQ12: 0.09 | AR12: 0.09 | AS12: 0.1 | AT12: 0.1 | AU12: 0.1 | AV12: 0.09 | AW12: 0.08 | AX12: 0.09 | AY12: 0.09 | AZ12: 0.09 | BA12: 0.1 | BB12: 0.11 | BC12: 0.11 | BD12: 0.11 | BE12: 0.12 | BF12: 0.11 | BG12: 0.11 | BH12: 0.11 | BI12: 0.08 | BJ12: 0.08 | BK12: 0.08 | BL12: 0.09 | BM12: 0.09 | BN12: 0.03 | BO12: 0.12 | BP12: 0 | BQ12: 0.07 | BR12: 0.16 | BS12: -0.03 | BT12: 0.09 | BU12: 0.01 | BV12: -0.02 | BW12: 0.12 | BX12: 0.16 | BY12: 0.15 | BZ12: 0.14 | CA12: 0.14 | CB12: 0.12 | CC12: 0.11 | CD12: 0.13 | CE12: 0.06
B13: Forestry | C13: AD | I13: 0.03 | J13: 0.03 | K13: 0.03 | L13: 0.04 | M13: 0.04 | N13: 0.04 | O13: 0.04 | P13: 0.03 | Q13: 0.03 | R13: 0.02 | S13: 0.02 | T13: 0.03 | U13: 0.03 | V13: 0.03 | W13: 0.04 | X13: 0.03 | Y13: 0.04 | Z13: 0.02 | AA13: 0.02 | AB13: 0.02 | AC13: 0.02 | AD13: 0.04 | AE13: 0.04 | AF13: 0.04 | AG13: 0.03 | AH13: 0.03 | AI13: 0.03 | AJ13: 0.02 | AK13: 0.03 | AL13: 0.04 | AM13: 0.03 | AN13: 0.04 | AO13: 0.03 | AP13: 0.04 | AQ13: 0.04 | AR13: 0.04 | AS13: 0.04 | AT13: 0.04 | AU13: 0.04 | AV13: 0.03 | AW13: 0.03 | AX13: 0.03 | AY13: 0.03 | AZ13: 0.04 | BA13: 0.04 | BB13: 0.04 | BC13: 0.04 | BD13: 0.05 | BE13: 0.05 | BF13: 0.06 | BG13: 0.06 | BH13: 0.05 | BI13: 0.04 | BJ13: 0.03 | BK13: 0.04 | BL13: 0.04 | BM13: 0.05 | BN13: 0.05 | BO13: 0.05 | BP13: 0.05 | BQ13: 0.06 | BR13: 0.08 | BS13: 0.07 | BT13: 0.07 | BU13: 0.05 | BV13: 0.05 | BW13: 0.06 | BX13: 0.06 | BY13: 0.07 | BZ13: 0.06 | CA13: 0.05 | CB13: 0.05 | CC13: 0.05 | CD13: 0.06 | CE13: 0.06
B14: Fishing | C14: AE | I14: 0.03 | J14: 0.03 | K14: 0.03 | L14: 0.03 | M14: 0.03 | N14: 0.03 | O14: 0.03 | P14: 0.03 | Q14: 0.03 | R14: 0.03 | S14: 0.03 | T14: 0.03 | U14: 0.03 | V14: 0.03 | W14: 0.03 | X14: 0.03 | Y14: 0.07 | Z14: 0.07 | AA14: -0.01 | AB14: -0.02 | AC14: -0.06 | AD14: -0.06 | AE14: 0.01 | AF14: 0.02 | AG14: 0.03 | AH14: 0.04 | AI14: 0.05 | AJ14: 0.06 | AK14: 0.05 | AL14: 0.04 | AM14: 0.03 | AN14: 0.02 | AO14: 0.03 | AP14: 0.03 | AQ14: 0.03 | AR14: 0.03 | AS14: 0.03 | AT14: 0.02 | AU14: 0.03 | AV14: 0.02 | AW14: 0.03 | AX14: 0.05 | AY14: 0.05 | AZ14: 0.08 | BA14: 0.08 | BB14: 0.06 | BC14: 0.05 | BD14: 0.02 | BE14: 0.02 | BF14: 0.03 | BG14: 0.04 | BH14: 0.05 | BI14: 0.05 | BJ14: -0.48 | BK14: -0.2 | BL14: 0.01 | BM14: 0.01 | BN14: 1.03 | BO14: 0.32 | BP14: 0.04 | BQ14: 0.04 | BR14: 0.02 | BS14: 0 | BT14: -0.01 | BU14: -0.05 | BV14: -0.01 | BW14: -0.02 | BX14: -0.1 | BY14: -0.1 | BZ14: -0.06 | CA14: 0.01 | CB14: 0.12 | CC14: 0.22 | CD14: 0.18 | CE14: 0.34
B15: INDUSTRY | C15: B-F | I15: 0.22 | J15: 0.05 | K15: 0.06 | L15: 0.05 | M15: 0.1 | N15: 0.21 | O15: 0.17 | P15: 0.12 | Q15: 0.14 | R15: -0.01 | S15: -0.07 | T15: 0 | U15: 0.07 | V15: 0.04 | W15: 0.09 | X15: 0.13 | Y15: 0.15 | Z15: 0.14 | AA15: 0.22 | AB15: 0.2 | AC15: 0.03 | AD15: 0.1 | AE15: 0.1 | AF15: 0.1 | AG15: 0.14 | AH15: 0.18 | AI15: 0.08 | AJ15: 0 | AK15: 0 | AL15: 0 | AM15: 0.09 | AN15: 0.01 | AO15: 0.06 | AP15: 0.09 | AQ15: 0.05 | AR15: 0.16 | AS15: 0.16 | AT15: 0.12 | AU15: 0.01 | AV15: -0.01 | AW15: -0.03 | AX15: -0.01 | AY15: 0.04 | AZ15: 0.05 | BA15: 0.04 | BB15: 0.08 | BC15: 0.1 | BD15: 0.12 | BE15: 0.15 | BF15: 0.21 | BG15: 0.16 | BH15: 0.14 | BI15: 0.02 | BJ15: -0.19 | BK15: -0.01 | BL15: 0.02 | BM15: 0.1 | BN15: 0.15 | BO15: -0.05 | BP15: 0.02 | BQ15: 0.19 | BR15: 0.39 | BS15: 0.15 | BT15: 0.14 | BU15: 0.02 | BV15: -0.03 | BW15: 0.16 | BX15: 0.2 | BY15: 0.18 | BZ15: 0.13 | CA15: 0.01 | CB15: -0.01 | CC15: 0.05 | CD15: 0.07 | CE15: 0.17
B16: Mining & quarrying | C16: B | I16: 1.09 | J16: 0.42 | K16: 0.16 | L16: 0.29 | M16: -0.23 | N16: 0.02 | O16: -0.11 | P16: -0.28 | Q16: -0.09 | R16: -0.33 | S16: -0.02 | T16: -0.23 | U16: -0.42 | V16: 0.03 | W16: -0.1 | X16: 0.1 | Y16: 1.18 | Z16: 0.14 | AA16: 0.37 | AB16: 0.58 | AC16: -0.03 | AD16: -0.02 | AE16: -0.1 | AF16: -0.12 | AG16: 0.11 | AH16: 0.32 | AI16: 0.2 | AJ16: 0.17 | AK16: 0.16 | AL16: 0.06 | AM16: 0.7 | AN16: 0.08 | AO16: -0.03 | AP16: 0.02 | AQ16: -0.23 | AR16: 0.15 | AS16: 0.12 | AT16: 0.27 | AU16: 0.02 | AV16: 0.04 | AW16: 0.17 | AX16: 0.06 | AY16: 0.24 | AZ16: 0.33 | BA16: -0.03 | BB16: 0.07 | BC16: 0.06 | BD16: 0.02 | BE16: 0.16 | BF16: 0.15 | BG16: -0.13 | BH16: -0.12 | BI16: -0.26 | BJ16: -0.53 | BK16: -0.24 | BL16: -0.19 | BM16: 0.03 | BN16: 0.3 | BO16: 0.05 | BP16: -0.05 | BQ16: 0.24 | BR16: 0.5 | BS16: 0.18 | BT16: 0.23 | BU16: -0.02 | BV16: -0.04 | BW16: 0.16 | BX16: 0.2 | BY16: 0.29 | BZ16: 0.1 | CA16: 0.04 | CB16: -0.07 | CC16: -0.01 | CD16: 0.12 | CE16: 0.14
B17: TOTAL MANUFACTURING | C17: C | I17: 0.09 | J17: -0.01 | K17: -0.01 | L17: -0.03 | M17: 0.09 | N17: 0.15 | O17: 0.01 | P17: 0 | Q17: 0.03 | R17: 0.01 | S17: 0.02 | T17: 0.06 | U17: 0.15 | V17: 0.06 | W17: 0.08 | X17: 0.09 | Y17: 0.01 | Z17: 0.07 | AA17: 0.15 | AB17: 0.1 | AC17: 0.09 | AD17: 0.07 | AE17: 0.03 | AF17: 0.05 | AG17: 0.09 | AH17: 0.11 | AI17: 0.02 | AJ17: -0.03 | AK17: -0.14 | AL17: -0.14 | AM17: -0.13 | AN17: -0.09 | AO17: 0.1 | AP17: 0.08 | AQ17: 0.07 | AR17: 0.08 | AS17: 0.13 | AT17: 0.12 | AU17: 0.01 | AV17: 0.02 | AW17: 0.03 | AX17: 0.06 | AY17: 0.07 | AZ17: 0.1 | BA17: 0.12 | BB17: 0.14 | BC17: 0.14 | BD17: 0.15 | BE17: 0.07 | BF17: 0.15 | BG17: 0.13 | BH17: 0.09 | BI17: 0.06 | BJ17: -0.13 | BK17: 0.06 | BL17: 0.1 | BM17: 0.08 | BN17: 0.29 | BO17: -0.12 | BP17: 0.09 | BQ17: 0.1 | BR17: 0.12 | BS17: 0.08 | BT17: 0.07 | BU17: 0.16 | BV17: 0.01 | BW17: 0.11 | BX17: 0.12 | BY17: -0.01 | BZ17: 0.1 | CA17: 0.08 | CB17: 0.07 | CC17: 0.09 | CD17: 0.08 | CE17: 0.14
B18: Of which: Food | C18: CA | I18: 0.12 | J18: -0.09 | K18: -0.02 | L18: -0.13 | M18: 0.13 | N18: 0.25 | O18: 0 | P18: -0.02 | Q18: 0.1 | R18: 0.07 | S18: 0.05 | T18: 0.04 | U18: 0.08 | V18: 0.05 | W18: 0.11 | X18: 0.12 | Y18: -0.09 | Z18: -0.11 | AA18: 0.1 | AB18: 0.24 | AC18: 0.04 | AD18: 0.05 | AE18: -0.03 | AF18: 0 | AG18: 0.35 | AH18: 0.24 | AI18: -0.05 | AJ18: -0.09 | AK18: -0.01 | AL18: 0.05 | AM18: 0.09 | AN18: 0.1 | AO18: 0.06 | AP18: 0.02 | AQ18: -0.06 | AR18: 0.02 | AS18: 0.17 | AT18: 0.17 | AU18: -0.02 | AV18: 0.01 | AW18: 0.03 | AX18: 0.06 | AY18: 0.22 | AZ18: 0.19 | BA18: 0.17 | BB18: 0.24 | BC18: 0.01 | BD18: 0.09 | BE18: -0.01 | BF18: 0.04 | BG18: 0.15 | BH18: 0.02 | BI18: 0.11 | BJ18: 0 | BK18: 0.08 | BL18: 0.1 | BM18: 0.07 | BN18: 0.58 | BO18: 0.01 | BP18: 0.67 | BQ18: 0.08 | BR18: 0.21 | BS18: 0.12 | BT18: 0.13 | BU18: 0.22 | BV18: 0.02 | BW18: 0.09 | BX18: 0.21 | BY18: 0.04 | BZ18: 0.05 | CA18: 0.06 | CB18: -0.05 | CC18: 0.05 | CD18: 0.1 | CE18: 0.12
B19: Beverages & tobacco | C19: CB | I19: 0.03 | J19: 0.04 | K19: -0.06 | L19: -0.04 | M19: 0.09 | N19: 0.11 | O19: 0 | P19: -0.05 | Q19: 0.03 | R19: 0 | S19: 0.06 | T19: 0.08 | U19: 0 | V19: -0.01 | W19: 0.06 | X19: 0.03 | Y19: 0.1 | Z19: 0.15 | AA19: 0.05 | AB19: 0.01 | AC19: 0.09 | AD19: 0.03 | AE19: 0.01 | AF19: 0.05 | AG19: 0.01 | AH19: 0.1 | AI19: 0.04 | AJ19: 0 | AK19: 0.11 | AL19: 0.02 | AM19: 0.05 | AN19: 0.12 | AO19: 0.07 | AP19: 0.09 | AQ19: 0.08 | AR19: 0 | AS19: 0.05 | AT19: 0.07 | AU19: 0.02 | AV19: 0 | AW19: -0.03 | AX19: -0.06 | AY19: -0.14 | AZ19: -0.1 | BA19: -0.07 | BB19: -0.02 | BC19: 0.13 | BD19: 0.13 | BE19: 0.08 | BF19: 0.19 | BG19: 0.08 | BH19: 0.09 | BI19: 0.06 | BJ19: -0.13 | BK19: 0.04 | BL19: 0.08 | BM19: 0.04 | BN19: -0.1 | BO19: -0.44 | BP19: -0.13 | BQ19: 0.12 | BR19: 0.24 | BS19: 0.14 | BT19: 0.02 | BU19: 0.01 | BV19: -0.04 | BW19: 0.02 | BX19: -0.01 | BY19: 0.02 | BZ19: 0.07 | CA19: 0.05 | CB19: 0.09 | CC19: 0.03 | CD19: -0.04 | CE19: 0.08
B20: Textiles, clothing & leather goods | C20: CC | I20: 0.04 | J20: 0.03 | K20: 0.1 | L20: 0.19 | M20: 0.04 | N20: 0.08 | O20: -0.03 | P20: -0.13 | Q20: 0.01 | R20: -0.12 | S20: -0.02 | T20: 0.05 | U20: -0.01 | V20: 0.06 | W20: 0.03 | X20: 0.02 | Y20: 0.08 | Z20: -0.07 | AA20: -0.06 | AB20: 0 | AC20: 0.02 | AD20: 0.24 | AE20: 0.09 | AF20: 0 | AG20: -0.8 | AH20: -0.79 | AI20: -0.77 | AJ20: -0.76 | AK20: 0.11 | AL20: 0.09 | AM20: 0.08 | AN20: 0.03 | AO20: 0.06 | AP20: 0.03 | AQ20: -0.01 | AR20: 0.04 | AS20: 0.12 | AT20: 0.06 | AU20: 0.06 | AV20: 0.15 | AW20: 0.31 | AX20: 0.58 | AY20: 0.43 | AZ20: 0.28 | BA20: 0.56 | BB20: 0.42 | BC20: 0.68 | BD20: 0.74 | BE20: 0.09 | BF20: 0.12 | BG20: 0.21 | BH20: 0.3 | BI20: 0.11 | BJ20: -0.13 | BK20: -0.05 | BL20: -0.08 | BM20: -0.02 | BN20: 0.29 | BO20: 0.07 | BP20: 0.07 | BQ20: 0.1 | BR20: 0.09 | BS20: 0.1 | BT20: 0.09 | BU20: 0.13 | BV20: 0.09 | BW20: 0.15 | BX20: 0.15 | BY20: 0.1 | BZ20: 0.2 | CA20: 0.11 | CB20: -0.02 | CC20: 0 | CD20: -0.09 | CE20: -0.05
... B44: Cultural, domestic & other services | C44: R-T | I44: 0.17 | J44: 0.12 | K44: 0.18 | L44: 0.1 | M44: 0.04 | N44: 0 | O44: 0.03 | P44: 0.02 | Q44: -0.07 | R44: -0.04 | S44: -0.08 | T44: -0.02 | U44: 0.09 | V44: 0.06 | W44: 0.08 | X44: 0.04 | Y44: 0.02 | Z44: -0.01 | AA44: -0.04 | AB44: 0 | AC44: 0.03 | AD44: 0.1 | AE44: 0.15 | AF44: 0.16 | AG44: 0.13 | AH44: 0.2 | AI44: 0.08 | AJ44: 0.09 | AK44: 0.13 | AL44: 0.15 | AM44: 0.24 | AN44: 0.13 | AO44: 0.2 | AP44: 0.2 | AQ44: 0.14 | AR44: 0.23 | AS44: 0.11 | AT44: 0.03 | AU44: 0.07 | AV44: 0.07 | AW44: 0.05 | AX44: 0.05 | AY44: 0.05 | AZ44: 0.04 | BA44: 0.07 | BB44: 0.09 | BC44: 0.07 | BD44: 0.14 | BE44: 0.08 | BF44: 0.09 | BG44: 0.1 | BH44: 0.05 | BI44: -0.01 | BJ44: -0.04 | BK44: 0.01 | BL44: -0.02 | BM44: 0.06 | BN44: 0.12 | BO44: 0.07 | BP44: 0.15 | BQ44: 0.08 | BR44: 0.06 | BS44: 0.09 | BT44: 0.03 | BU44: 0.06 | BV44: 0.05 | BW44: 0.08 | BX44: 0.92 | BY44: 0.1 | BZ44: 0.18 | CA44: 0.14 | CB44: -0.32 | CC44: 0.16 | CD44: 0.16 | CE44: 0.13
B46: Taxes less subsidies on products | I46: 0.15 | J46: 0.05 | K46: -0.04 | L46: 0.02 | M46: 0.05 | N46: 0.07 | O46: 0.25 | P46: 0.1 | Q46: 0.01 | R46: 0.17 | S46: 0.04 | T46: 0.19 | U46: 0.03 | V46: 0.11 | W46: 0.06 | X46: -0.01 | Y46: 0.04 | Z46: -0.02 | AA46: 0.03 | AB46: 0.02 | AC46: 0.08 | AD46: 0.02 | AE46: 0.07 | AF46: -0.09 | AG46: -0.14 | AH46: -0.01 | AI46: -0.08 | AJ46: 0.11 | AK46: 0.16 | AL46: 0.06 | AM46: 0.06 | AN46: 0.05 | AO46: 0.12 | AP46: 0.17 | AQ46: 0.14 | AR46: 0.14 | AS46: 0.1 | AT46: 0.09 | AU46: 0.03 | AV46: -0.04 | AW46: -0.05 | AX46: -0.09 | AY46: -0.01 | AZ46: 0.06 | BA46: 0.1 | BB46: 0.09 | BC46: 0.07 | BD46: 0.11 | BE46: 0.08 | BF46: 0.24 | BG46: 0.16 | BH46: 0.12 | BI46: 0.09 | BJ46: -0.09 | BK46: -0.04 | BL46: -0.02 | BM46: 0.03 | BN46: 0.26 | BO46: -0.03 | BP46: 0.16 | BQ46: 0.07 | BR46: 0.04 | BS46: 0.22 | BT46: -0.08 | BU46: -0.05 | BV46: -0.07 | BW46: -0.02 | BX46: -0.03 | BY46: 0.04 | BZ46: 0.12 | CA46: 0.09 | CB46: 0.06 | CC46: 0.07 | CD46: 0.05 | CE46: 0.21
B48: =QGDP_CP!B48 -> Source: National Institute of Statistics of Rwanda
B49: =QGDP_CP!B49 -> 46007

Sheet QGDP_Cont
B1: Table 2B
B2: Gross Domestic Product by Kind of Activity
B3: Contribution to the growth rates
B4: (Percentage point)
B5: Activity description | C5: ISIC4 | E5: 2006 Q1 | F5: 2006 Q2 | G5: 2006 Q3 | H5: 2006 Q4 | I5: 2007 Q1 | J5: 2007 Q2 | K5: 2007 Q3 | L5: 2007 Q4 | M5: 2008 Q1 | N5: 2008 Q2 | O5: 2008 Q3 | P5: 2008 Q4 | Q5: 2009 Q1 | R5: 2009 Q2 | S5: 2009 Q3 | T5: 2009 Q4 | U5: 2010 Q1 | V5: 2010 Q2 | W5: 2010 Q3 | X5: 2010 Q4 | Y5: 2011 Q1 | Z5: 2011 Q2 | AA5: 2011 Q3 | AB5: 2011 Q4 | AC5: 2012 Q1 | AD5: 2012 Q2 | AE5: 2012 Q3 | AF5: 2012 Q4 | AG5: 2013 Q1 | AH5: 2013 Q2 | AI5: 2013 Q3 | AJ5: 2013 Q4 | AK5: 2014 Q1 | AL5: 2014 Q2 | AM5: 2014 Q3 | AN5: 2014 Q4 | AO5: 2015 Q1 | AP5: 2015 Q2 | AQ5: 2015 Q3 | AR5: 2015 Q4 | AS5: 2016 Q1 | AT5: 2016 Q2 | AU5: 2016 Q3 | AV5: 2016 Q4 | AW5: 2017 Q1 | AX5: 2017 Q2 | AY5: 2017 Q3 | AZ5: 2017 Q4 | BA5: 2018 Q1 | BB5: 2018 Q2 | BC5: 2018 Q3 | BD5: 2018 Q4 | BE5: 2019 Q1 | BF5: 2019 Q2 | BG5: 2019 Q3 | BH5: 2019 Q4 | BI5: 2020 Q1 | BJ5: 2020 Q2 | BK5: 2020 Q3 | BL5: 2020 Q4 | BM5: 2021 Q1 | BN5: 2021 Q2 | BO5: 2021 Q3 | BP5: 2021 Q4 | BQ5: 2022 Q1 | BR5: 2022 Q2 | BS5: 2022 Q3 | BT5: 2022 Q4 | BU5: 2023 Q1 | BV5: 2023 Q2 | BW5: 2023 Q3 | BX5: 2023 Q4 | BY5: 2024 Q1 | BZ5: 2024 Q2 | CA5: 2024 Q3 | CB5: 2024 Q4 | CC5: 2025 Q1 | CD5: 2025 Q2 | CE5: 2025 Q3
B7: GROSS DOMESTIC PRODUCT (GDP) | I7: 12.4 | J7: 6.6 | K7: 4.1 | L7: 7.4 | M7: 9.4 | N7: 14.2 | O7: 11.8 | P7: 10 | Q7: 9.7 | R7: 2.6 | S7: 3.9 | T7: 4 | U7: 4.4 | V7: 7 | W7: 6.7 | X7: 7.6 | Y7: 8.3 | Z7: 4.5 | AA7: 9 | AB7: 6.3 | AC7: 8.2 | AD7: 10.6 | AE7: 7 | AF7: 8.9 | AG7: 3.7 | AH7: 6.7 | AI7: 1.7 | AJ7: 2.7 | AK7: 6.5 | AL7: 7.6 | AM7: -2 | AN7: 15.8 | AO7: 8.4 | AP7: 9 | AQ7: 8.8 | AR7: 8.8 | AS7: 8.8 | AT7: 7.1 | AU7: 4.5 | AV7: 2.8 | AW7: 2.2 | AX7: 5.3 | AY7: 4.3 | AZ7: 7 | BA7: 7.9 | BB7: 6.5 | BC7: 8.8 | BD7: 9.5 | BE7: 7.1 | BF7: 13.6 | BG7: 12.5 | BH7: 7.1 | BI7: 3.2 | BJ7: -15.4 | BK7: -8.1 | BL7: -2.4 | BM7: 1.3 | BN7: 20.9 | BO7: 6.6 | BP7: 7.4 | BQ7: 9.9 | BR7: 11.6 | BS7: 11.5 | BT7: 6.8 | BU7: 7.7 | BV7: 2.6 | BW7: 10.6 | BX7: 13.5 | BY7: 8.1 | BZ7: 10.3 | CA7: 6.8 | CB7: 4.2 | CC7: 6.5 | CD7: 7.8 | CE7: 11.8
B9: AGRICULTURE, FORESTRY & FISHING | C9: A | I9: 1.1 | J9: 0.1 | K9: -0.7 | L9: -1.4 | M9: 2.6 | N9: 3.9 | O9: 1.8 | P9: 1.4 | Q9: 1.5 | R9: 0.9 | S9: 1.5 | T9: 1.6 | U9: 1.4 | V9: 1.3 | W9: 2.2 | X9: 1.6 | Y9: 1 | Z9: 0.5 | AA9: 1.7 | AB9: 0.7 | AC9: 1.8 | AD9: 2.2 | AE9: 0.7 | AF9: 3.3 | AG9: 1.9 | AH9: 2.2 | AI9: 0.1 | AJ9: -0.6 | AK9: 0.2 | AL9: 2.8 | AM9: -9.5 | AN9: 11.4 | AO9: 1.8 | AP9: 1.8 | AQ9: 1.1 | AR9: 0.6 | AS9: 0.7 | AT9: -0.1 | AU9: 1 | AV9: 1.3 | AW9: 1.8 | AX9: 4.2 | AY9: -1.1 | AZ9: 2.6 | BA9: 1.1 | BB9: 1.1 | BC9: 1.1 | BD9: 1.4 | BE9: 1 | BF9: 2.5 | BG9: 1.5 | BH9: -0.4 | BI9: 0.4 | BJ9: 0.4 | BK9: 0.9 | BL9: 1.2 | BM9: 0.6 | BN9: 1.4 | BO9: 1 | BP9: 0.6 | BQ9: -0.1 | BR9: 0.2 | BS9: 0.3 | BT9: 0 | BU9: 0.9 | BV9: 0.4 | BW9: 1.3 | BX9: 1.8 | BY9: 1.2 | BZ9: 0.9 | CA9: 0.4 | CB9: 0.3 | CC9: 0.8 | CD9: 1.7 | CE9: 1.5
B10: Food crops | C10: AA | I10: 1.9 | J10: 1.8 | K10: -0.1 | L10: -0.1 | M10: 1.8 | N10: 1.7 | O10: 0.6 | P10: 0.6 | Q10: 1.7 | R10: 1.6 | S10: 1.7 | T10: 1.7 | U10: 0.7 | V10: 0.7 | W10: 1.1 | X10: 1.1 | Y10: 1.3 | Z10: 1.3 | AA10: 0 | AB10: 0 | AC10: 1.9 | AD10: 2 | AE10: 0.9 | AF10: 0.9 | AG10: 1.3 | AH10: 1.3 | AI10: 0.1 | AJ10: 0.1 | AK10: -0.2 | AL10: 2.6 | AM10: -10 | AN10: 11.2 | AO10: 1.3 | AP10: 0.9 | AQ10: 0 | AR10: 0 | AS10: -0.8 | AT10: 0 | AU10: 0.9 | AV10: 0.9 | AW10: 2 | AX10: 3.4 | AY10: -1.3 | AZ10: 1.7 | BA10: -0.1 | BB10: 0.7 | BC10: 0.4 | BD10: 1 | BE10: 0.7 | BF10: 1.8 | BG10: 0.3 | BH10: -0.8 | BI10: 0.3 | BJ10: 0.6 | BK10: 0.8 | BL10: 0.9 | BM10: 0 | BN10: 0.2 | BO10: 0.2 | BP10: -0.1 | BQ10: -0.2 | BR10: -0.7 | BS10: 0.2 | BT10: -0.5 | BU10: 0.4 | BV10: 0.3 | BW10: 1 | BX10: 1.1 | BY10: 0.5 | BZ10: 0.4 | CA10: -0.5 | CB10: -0.1 | CC10: 0.2 | CD10: 0.5 | CE10: 0.2
B11: Export crops | C11: AB | I11: -1.1 | J11: -2 | K11: -0.8 | L11: -1.6 | M11: 0.5 | N11: 1.8 | O11: 0.8 | P11: 0.5 | Q11: -0.5 | R11: -1 | S11: -0.4 | T11: -0.4 | U11: 0.4 | V11: 0.3 | W11: 0.8 | X11: 0.2 | Y11: -0.6 | Z11: -1 | AA11: 1.5 | AB11: 0.4 | AC11: -0.4 | AD11: -0.1 | AE11: -0.6 | AF11: 2 | AG11: 0.3 | AH11: 0.6 | AI11: -0.4 | AJ11: -0.9 | AK11: 0 | AL11: -0.1 | AM11: 0.1 | AN11: -0.2 | AO11: 0.1 | AP11: 0.5 | AQ11: 0.6 | AR11: 0.2 | AS11: 1.1 | AT11: -0.5 | AU11: -0.4 | AV11: 0 | AW11: -0.6 | AX11: 0.4 | AY11: -0.2 | AZ11: 0.5 | BA11: 0.7 | BB11: 0 | BC11: 0.1 | BD11: -0.1 | BE11: -0.2 | BF11: 0.1 | BG11: 0.6 | BH11: -0.1 | BI11: -0.3 | BJ11: -0.3 | BK11: -0.3 | BL11: 0 | BM11: 0.1 | BN11: 0.7 | BO11: 0.1 | BP11: 0.4 | BQ11: -0.4 | BR11: 0.1 | BS11: -0.1 | BT11: 0.1 | BU11: 0.2 | BV11: 0 | BW11: -0.3 | BX11: 0 | BY11: 0.1 | BZ11: 0 | CA11: 0.3 | CB11: -0.2 | CC11: 0 | CD11: 0.7 | CE11: 0.8
B12: Livestock & livestock products | C12: AC | I12: 0.1 | J12: 0.1 | K12: 0.1 | L12: 0.1 | M12: 0.1 | N12: 0.1 | O12: 0.1 | P12: 0.1 | Q12: 0.1 | R12: 0.1 | S12: 0.1 | T12: 0.1 | U12: 0.1 | V12: 0.1 | W12: 0.1 | X12: 0.1 | Y12: 0.1 | Z12: 0.1 | AA12: 0.1 | AB12: 0.1 | AC12: 0.1 | AD12: 0.2 | AE12: 0.1 | AF12: 0.1 | AG12: 0.1 | AH12: 0.1 | AI12: 0.2 | AJ12: 0.2 | AK12: 0.2 | AL12: 0.2 | AM12: 0.2 | AN12: 0.2 | AO12: 0.2 | AP12: 0.2 | AQ12: 0.2 | AR12: 0.2 | AS12: 0.2 | AT12: 0.2 | AU12: 0.2 | AV12: 0.2 | AW12: 0.2 | AX12: 0.2 | AY12: 0.3 | AZ12: 0.2 | BA12: 0.2 | BB12: 0.3 | BC12: 0.3 | BD12: 0.3 | BE12: 0.3 | BF12: 0.3 | BG12: 0.3 | BH12: 0.3 | BI12: 0.2 | BJ12: 0.2 | BK12: 0.2 | BL12: 0.2 | BM12: 0.2 | BN12: 0.1 | BO12: 0.4 | BP12: 0 | BQ12: 0.2 | BR12: 0.4 | BS12: -0.1 | BT12: 0.2 | BU12: 0 | BV12: 0 | BW12: 0.4 | BX12: 0.4 | BY12: 0.4 | BZ12: 0.4 | CA12: 0.4 | CB12: 0.3 | CC12: 0.3 | CD12: 0.3 | CE12: 0.2
B13: Forestry | C13: AD | I13: 0.2 | J13: 0.2 | K13: 0.2 | L13: 0.3 | M13: 0.2 | N13: 0.3 | O13: 0.2 | P13: 0.2 | Q13: 0.2 | R13: 0.1 | S13: 0.1 | T13: 0.2 | U13: 0.2 | V13: 0.2 | W13: 0.2 | X13: 0.2 | Y13: 0.2 | Z13: 0.1 | AA13: 0.1 | AB13: 0.1 | AC13: 0.1 | AD13: 0.2 | AE13: 0.2 | AF13: 0.2 | AG13: 0.2 | AH13: 0.2 | AI13: 0.2 | AJ13: 0.1 | AK13: 0.2 | AL13: 0.2 | AM13: 0.2 | AN13: 0.2 | AO13: 0.2 | AP13: 0.2 | AQ13: 0.2 | AR13: 0.2 | AS13: 0.2 | AT13: 0.2 | AU13: 0.2 | AV13: 0.1 | AW13: 0.1 | AX13: 0.1 | AY13: 0.1 | AZ13: 0.2 | BA13: 0.2 | BB13: 0.2 | BC13: 0.2 | BD13: 0.2 | BE13: 0.2 | BF13: 0.3 | BG13: 0.3 | BH13: 0.2 | BI13: 0.2 | BJ13: 0.1 | BK13: 0.2 | BL13: 0.2 | BM13: 0.2 | BN13: 0.2 | BO13: 0.2 | BP13: 0.2 | BQ13: 0.3 | BR13: 0.3 | BS13: 0.3 | BT13: 0.3 | BU13: 0.2 | BV13: 0.2 | BW13: 0.3 | BX13: 0.2 | BY13: 0.3 | BZ13: 0.2 | CA13: 0.2 | CB13: 0.2 | CC13: 0.2 | CD13: 0.2 | CE13: 0.3
B14: Fishing | C14: AE | I14: 0 | J14: 0 | K14: 0 | L14: 0 | M14: 0 | N14: 0 | O14: 0 | P14: 0 | Q14: 0 | R14: 0 | S14: 0 | T14: 0 | U14: 0 | V14: 0 | W14: 0 | X14: 0 | Y14: 0 | Z14: 0 | AA14: 0 | AB14: 0 | AC14: 0 | AD14: 0 | AE14: 0 | AF14: 0 | AG14: 0 | AH14: 0 | AI14: 0 | AJ14: 0 | AK14: 0 | AL14: 0 | AM14: 0 | AN14: 0 | AO14: 0 | AP14: 0 | AQ14: 0 | AR14: 0 | AS14: 0 | AT14: 0 | AU14: 0 | AV14: 0 | AW14: 0 | AX14: 0 | AY14: 0 | AZ14: 0 | BA14: 0 | BB14: 0 | BC14: 0 | BD14: 0 | BE14: 0 | BF14: 0 | BG14: 0 | BH14: 0 | BI14: 0 | BJ14: -0.2 | BK14: -0.1 | BL14: 0 | BM14: 0 | BN14: 0.2 | BO14: 0.1 | BP14: 0 | BQ14: 0 | BR14: 0 | BS14: 0 | BT14: 0 | BU14: 0 | BV14: 0 | BW14: 0 | BX14: 0 | BY14: 0 | BZ14: 0 | CA14: 0 | CB14: 0 | CC14: 0.1 | CD14: 0 | CE14: 0.1
B15: INDUSTRY | C15: B-F | I15: 4.4 | J15: 1.8 | K15: 0.9 | L15: 1.6 | M15: 1 | N15: 3.1 | O15: 2.1 | P15: 0.8 | Q15: 1.9 | R15: -1.1 | S15: -0.7 | T15: 0.1 | U15: 0.5 | V15: 0.7 | W15: 1.2 | X15: 1.9 | Y15: 3.5 | Z15: 2.5 | AA15: 3.3 | AB15: 3.6 | AC15: 0.8 | AD15: 2 | AE15: 1.9 | AF15: 1.9 | AG15: 1.2 | AH15: 1.7 | AI15: 0.3 | AJ15: -0.9 | AK15: 1.7 | AL15: 1.6 | AM15: 3.2 | AN15: 1.8 | AO15: 1.3 | AP15: 1.9 | AQ15: 1.7 | AR15: 2.8 | AS15: 3 | AT15: 2 | AU15: 0.1 | AV15: -0.3 | AW15: -0.9 | AX15: -0.7 | AY15: 0.3 | AZ15: 0.4 | BA15: 0.2 | BB15: 0.9 | BC15: 2.3 | BD15: 2.3 | BE15: 3.2 | BF15: 4.5 | BG15: 3.9 | BH15: 3.1 | BI15: 0.3 | BJ15: -4.1 | BK15: -0.6 | BL15: 0.1 | BM15: 2 | BN15: 3.2 | BO15: -1.2 | BP15: 0.3 | BQ15: 4.1 | BR15: 7 | BS15: 3.3 | BT15: 2.7 | BU15: 0.6 | BV15: -0.6 | BW15: 3.4 | BX15: 4.1 | BY15: 3.9 | BZ15: 2.8 | CA15: 0.3 | CB15: -0.1 | CC15: 1.2 | CD15: 1.5 | CE15: 3.7
B16: Mining & quarrying | C16: B | I16: 2 | J16: 1 | K16: 0.4 | L16: 0.8 | M16: -0.8 | N16: 0 | O16: -0.3 | P16: -0.9 | Q16: -0.2 | R16: -0.9 | S16: 0 | T16: -0.5 | U16: -0.8 | V16: 0 | W16: -0.2 | X16: 0.2 | Y16: 1.2 | Z16: 0.2 | AA16: 0.6 | AB16: 0.9 | AC16: -0.1 | AD16: 0 | AE16: -0.2 | AF16: -0.3 | AG16: 0.2 | AH16: 0.5 | AI16: 0.4 | AJ16: 0.3 | AK16: 0.3 | AL16: 0.1 | AM16: 1.5 | AN16: 0.2 | AO16: -0.1 | AP16: 0 | AQ16: -0.8 | AR16: 0.3 | AS16: 0.2 | AT16: 0.5 | AU16: 0.1 | AV16: 0.1 | AW16: 0.3 | AX16: 0.1 | AY16: 0.6 | AZ16: 0.7 | BA16: -0.1 | BB16: 0.2 | BC16: 0.2 | BD16: 0 | BE16: 0.3 | BF16: 0.3 | BG16: -0.4 | BH16: -0.3 | BI16: -0.6 | BJ16: -1.2 | BK16: -0.6 | BL16: -0.4 | BM16: 0.1 | BN16: 0.4 | BO16: 0.1 | BP16: -0.1 | BQ16: 0.4 | BR16: 0.7 | BS16: 0.3 | BT16: 0.3 | BU16: 0 | BV16: -0.1 | BW16: 0.3 | BX16: 0.3 | BY16: 0.5 | BZ16: 0.2 | CA16: 0.1 | CB16: -0.1 | CC16: 0 | CD16: 0.2 | CE16: 0.3
B17: TOTAL MANUFACTURING | C17: C | I17: 0.7 | J17: 0.2 | K17: -0.2 | L17: 0.1 | M17: 0.7 | N17: 1.1 | O17: 0.1 | P17: -0.4 | Q17: 0.3 | R17: -0.2 | S17: 0.2 | T17: 0.6 | U17: 0.8 | V17: 0.3 | W17: 0.7 | X17: 0.5 | Y17: 0.4 | Z17: 0.8 | AA17: 0.9 | AB17: 0.6 | AC17: 0.7 | AD17: 0.8 | AE17: 0.3 | AF17: 0.4 | AG17: -0.7 | AH17: -0.5 | AI17: -0.8 | AJ17: -1.1 | AK17: 0.6 | AL17: 0.4 | AM17: 0.6 | AN17: 0.9 | AO17: 0.7 | AP17: 0.6 | AQ17: 0.8 | AR17: 0.5 | AS17: 0.7 | AT17: 0.7 | AU17: 0.1 | AV17: 0.1 | AW17: 0.2 | AX17: 0.3 | AY17: 0.1 | AZ17: 0.3 | BA17: 0.5 | BB17: 0.6 | BC17: 1.4 | BD17: 1.1 | BE17: 0.7 | BF17: 1.4 | BG17: 1.1 | BH17: 0.7 | BI17: 0.4 | BJ17: -1.1 | BK17: 0.5 | BL17: 0.7 | BM17: 0.6 | BN17: 2.2 | BO17: -1.5 | BP17: 0.5 | BQ17: 0.9 | BR17: 1 | BS17: 0.6 | BT17: 0.6 | BU17: 1.3 | BV17: 0.1 | BW17: 0.9 | BX17: 1 | BY17: -0.1 | BZ17: 0.9 | CA17: 0.6 | CB17: 0.6 | CC17: 0.7 | CD17: 0.6 | CE17: 1.1
B18: Of which: Food | C18: CA | I18: 0.2 | J18: -0.1 | K18: 0 | L18: -0.2 | M18: 0.2 | N18: 0.3 | O18: 0 | P18: 0 | Q18: 0.1 | R18: 0.1 | S18: 0.1 | T18: 0.1 | U18: 0.1 | V18: 0.1 | W18: 0.2 | X18: 0.2 | Y18: -0.1 | Z18: -0.2 | AA18: 0.2 | AB18: 0.3 | AC18: 0 | AD18: 0.1 | AE18: 0 | AF18: 0 | AG18: 0.4 | AH18: 0.3 | AI18: -0.1 | AJ18: -0.1 | AK18: 0 | AL18: 0.1 | AM18: 0.1 | AN18: 0.1 | AO18: 0.1 | AP18: 0 | AQ18: -0.1 | AR18: 0 | AS18: 0.2 | AT18: 0.2 | AU18: 0 | AV18: 0 | AW18: 0 | AX18: 0.1 | AY18: 0.3 | AZ18: 0.2 | BA18: 0.2 | BB18: 0.3 | BC18: 0 | BD18: 0.1 | BE18: 0 | BF18: 0.1 | BG18: 0.2 | BH18: 0 | BI18: 0.2 | BJ18: 0 | BK18: 0.1 | BL18: 0.1 | BM18: 0.1 | BN18: 0.9 | BO18: 0 | BP18: 0.9 | BQ18: 0.1 | BR18: 0.5 | BS18: 0.2 | BT18: 0.3 | BU18: 0.3 | BV18: 0 | BW18: 0.1 | BX18: 0.5 | BY18: 0.1 | BZ18: 0.1 | CA18: 0.1 | CB18: -0.1 | CC18: 0.1 | CD18: 0.2 | CE18: 0.2
B19: Beverages & tobacco | C19: CB | I19: 0.2 | J19: 0.2 | K19: -0.4 | L19: -0.3 | M19: 0.4 | N19: 0.5 | O19: 0 | P19: -0.2 | Q19: 0.2 | R19: 0 | S19: 0.3 | T19: 0.3 | U19: 0 | V19: 0 | W19: 0.3 | X19: 0.1 | Y19: 0.4 | Z19: 0.6 | AA19: 0.2 | AB19: 0.1 | AC19: 0.4 | AD19: 0.1 | AE19: 0.1 | AF19: 0.2 | AG19: 0 | AH19: 0.4 | AI19: 0.2 | AJ19: 0 | AK19: 0.4 | AL19: 0.1 | AM19: 0.2 | AN19: 0.5 | AO19: 0.3 | AP19: 0.3 | AQ19: 0.4 | AR19: 0 | AS19: 0.2 | AT19: 0.3 | AU19: 0.1 | AV19: 0 | AW19: -0.1 | AX19: -0.2 | AY19: -0.6 | AZ19: -0.3 | BA19: -0.3 | BB19: -0.1 | BC19: 0.5 | BD19: 0.4 | BE19: 0.2 | BF19: 0.6 | BG19: 0.3 | BH19: 0.3 | BI19: 0.2 | BJ19: -0.4 | BK19: 0.2 | BL19: 0.2 | BM19: 0.1 | BN19: -0.3 | BO19: -1.8 | BP19: -0.4 | BQ19: 0.4 | BR19: 0.6 | BS19: 0.3 | BT19: 0.1 | BU19: 0 | BV19: -0.1 | BW19: 0 | BX19: 0 | BY19: 0.1 | BZ19: 0.2 | CA19: 0.1 | CB19: 0.2 | CC19: 0.1 | CD19: -0.1 | CE19: 0.2
B20: Textiles, clothing & leather goods | C20: CC | I20: 0.1 | J20: 0.1 | K20: 0.2 | L20: 0.4 | M20: 0.1 | N20: 0.2 | O20: -0.1 | P20: -0.3 | Q20: 0 | R20: -0.2 | S20: 0 | T20: 0.1 | U20: 0 | V20: 0.1 | W20: 0 | X20: 0 | Y20: 0.1 | Z20: -0.1 | AA20: -0.1 | AB20: 0 | AC20: 0 | AD20: 0.3 | AE20: 0.1 | AF20: 0 | AG20: -1.2 | AH20: -1.3 | AI20: -1 | AJ20: -1 | AK20: 0 | AL20: 0 | AM20: 0 | AN20: 0 | AO20: 0 | AP20: 0 | AQ20: 0 | AR20: 0 | AS20: 0 | AT20: 0 | AU20: 0 | AV20: 0 | AW20: 0.1 | AX20: 0.2 | AY20: 0.1 | AZ20: 0.1 | BA20: 0.2 | BB20: 0.2 | BC20: 0.3 | BD20: 0.3 | BE20: 0.1 | BF20: 0.1 | BG20: 0.1 | BH20: 0.2 | BI20: 0.1 | BJ20: -0.1 | BK20: 0 | BL20: -0.1 | BM20: 0 | BN20: 0.2 | BO20: 0 | BP20: 0 | BQ20: 0.1 | BR20: 0.1 | BS20: 0.1 | BT20: 0.1 | BU20: 0.1 | BV20: 0.1 | BW20: 0.1 | BX20: 0.1 | BY20: 0.1 | BZ20: 0.1 | CA20: 0.1 | CB20: 0 | CC20: 0 | CD20: -0.1 | CE20: 0
... B44: Cultural, domestic & other services | C44: R-T | I44: 0.5 | J44: 0.3 | K44: 0.5 | L44: 0.3 | M44: 0.1 | N44: 0 | O44: 0.1 | P44: 0 | Q44: -0.2 | R44: -0.1 | S44: -0.2 | T44: -0.1 | U44: 0.2 | V44: 0.2 | W44: 0.2 | X44: 0.1 | Y44: 0.1 | Z44: 0 | AA44: -0.1 | AB44: 0 | AC44: 0.1 | AD44: 0.2 | AE44: 0.3 | AF44: 0.4 | AG44: 0.3 | AH44: 0.5 | AI44: 0.2 | AJ44: 0.2 | AK44: 0.3 | AL44: 0.4 | AM44: 0.6 | AN44: 0.3 | AO44: 0.5 | AP44: 0.5 | AQ44: 0.4 | AR44: 0.5 | AS44: 0.3 | AT44: 0.1 | AU44: 0.2 | AV44: 0.2 | AW44: 0.2 | AX44: 0.1 | AY44: 0.2 | AZ44: 0.1 | BA44: 0.2 | BB44: 0.3 | BC44: 0.2 | BD44: 0.4 | BE44: 0.2 | BF44: 0.3 | BG44: 0.3 | BH44: 0.2 | BI44: 0 | BJ44: -0.1 | BK44: 0 | BL44: 0 | BM44: 0.2 | BN44: 0.4 | BO44: 0.2 | BP44: 0.4 | BQ44: 0.2 | BR44: 0.2 | BS44: 0.3 | BT44: 0.1 | BU44: 0.2 | BV44: 0.1 | BW44: 0.3 | BX44: 2.7 | BY44: 0.3 | BZ44: 0.5 | CA44: 0.5 | CB44: -1.6 | CC44: 0.5 | CD44: 0.5 | CE44: 0.5
B46: Taxes less subsidies on products | I46: 1.1 | J46: 0.3 | K46: -0.3 | L46: 0.1 | M46: 0.4 | N46: 0.4 | O46: 1.5 | P46: 0.6 | Q46: 0.1 | R46: 1 | S46: 0.3 | T46: 1.2 | U46: 0.2 | V46: 0.7 | W46: 0.4 | X46: 0 | Y46: 0.2 | Z46: -0.1 | AA46: 0.2 | AB46: 0.1 | AC46: 0.5 | AD46: 0.1 | AE46: 0.4 | AF46: -0.5 | AG46: -0.9 | AH46: 0 | AI46: -0.5 | AJ46: 0.6 | AK46: 0.8 | AL46: 0.3 | AM46: 0.3 | AN46: 0.3 | AO46: 0.6 | AP46: 0.9 | AQ46: 0.8 | AR46: 0.7 | AS46: 0.6 | AT46: 0.5 | AU46: 0.2 | AV46: -0.2 | AW46: -0.3 | AX46: -0.5 | AY46: -0.1 | AZ46: 0.3 | BA46: 0.5 | BB46: 0.4 | BC46: 0.4 | BD46: 0.6 | BE46: 0.5 | BF46: 1.2 | BG46: 0.9 | BH46: 0.6 | BI46: 0.5 | BJ46: -0.5 | BK46: -0.2 | BL46: -0.1 | BM46: 0.2 | BN46: 1.5 | BO46: -0.2 | BP46: 0.8 | BQ46: 0.4 | BR46: 0.2 | BS46: 1.2 | BT46: -0.5 | BU46: -0.3 | BV46: -0.4 | BW46: -0.1 | BX46: -0.2 | BY46: 0.2 | BZ46: 0.6 | CA46: 0.5 | CB46: 0.2 | CC46: 0.3 | CD46: 0.3 | CE46: 1.2
B48: =QGDP_CP!B48 -> Source: National Institute of Statistics of Rwanda
B49: =QGDP_CP!B49 -> 46007

Sheet QGDP_DF
B1: Table 3
B2: Gross Domestic Product by Kind of Activity
B3: Deflators
B4: =QGDP_KP!$D$5&"=100" -> 2024=100
B5: Activity description | C5: ISIC4 | D5: =QGDP_KP!$D$5 -> 2024 | E5: 2006 Q1 | F5: 2006 Q2 | G5: 2006 Q3 | H5: 2006 Q4 | I5: 2007 Q1 | J5: 2007 Q2 | K5: 2007 Q3 | L5: 2007 Q4 | M5: 2008 Q1 | N5: 2008 Q2 | O5: 2008 Q3 | P5: 2008 Q4 | Q5: 2009 Q1 | R5: 2009 Q2 | S5: 2009 Q3 | T5: 2009 Q4 | U5: 2010 Q1 | V5: 2010 Q2 | W5: 2010 Q3 | X5: 2010 Q4 | Y5: 2011 Q1 | Z5: 2011 Q2 | AA5: 2011 Q3 | AB5: 2011 Q4 | AC5: 2012 Q1 | AD5: 2012 Q2 | AE5: 2012 Q3 | AF5: 2012 Q4 | AG5: 2013 Q1 | AH5: 2013 Q2 | AI5: 2013 Q3 | AJ5: 2013 Q4 | AK5: 2014 Q1 | AL5: 2014 Q2 | AM5: 2014 Q3 | AN5: 2014 Q4 | AO5: 2015 Q1 | AP5: 2015 Q2 | AQ5: 2015 Q3 | AR5: 2015 Q4 | AS5: 2016 Q1 | AT5: 2016 Q2 | AU5: 2016 Q3 | AV5: 2016 Q4 | AW5: 2017 Q1 | AX5: 2017 Q2 | AY5: 2017 Q3 | AZ5: 2017 Q4 | BA5: 2018 Q1 | BB5: 2018 Q2 | BC5: 2018 Q3 | BD5: 2018 Q4 | BE5: 2019 Q1 | BF5: 2019 Q2 | BG5: 2019 Q3 | BH5: 2019 Q4 | BI5: 2020 Q1 | BJ5: 2020 Q2 | BK5: 2020 Q3 | BL5: 2020 Q4 | BM5: 2021 Q1 | BN5: 2021 Q2 | BO5: 2021 Q3 | BP5: 2021 Q4 | BQ5: 2022 Q1 | BR5: 2022 Q2 | BS5: 2022 Q3 | BT5: 2022 Q4 | BU5: 2023 Q1 | BV5: 2023 Q2 | BW5: 2023 Q3 | BX5: 2023 Q4 | BY5: 2024 Q1 | BZ5: 2024 Q2 | CA5: 2024 Q3 | CB5: 2024 Q4 | CC5: 2025 Q1 | CD5: 2025 Q2 | CE5: 2025 Q3
B7: GROSS DOMESTIC PRODUCT (GDP) | D7: 100 | E7: 30 | F7: 31 | G7: 30 | H7: 31 | I7: 33 | J7: 35 | K7: 35 | L7: 36 | M7: 37 | N7: 39 | O7: 41 | P7: 43 | Q7: 42 | R7: 42 | S7: 43 | T7: 44 | U7: 43 | V7: 44 | W7: 44 | X7: 45 | Y7: 45 | Z7: 48 | AA7: 48 | AB7: 48 | AC7: 48 | AD7: 50 | AE7: 50 | AF7: 50 | AG7: 50 | AH7: 50 | AI7: 51 | AJ7: 52 | AK7: 53 | AL7: 54 | AM7: 55 | AN7: 52 | AO7: 53 | AP7: 53 | AQ7: 55 | AR7: 54 | AS7: 55 | AT7: 56 | AU7: 57 | AV7: 59 | AW7: 61 | AX7: 61 | AY7: 61 | AZ7: 61 | BA7: 62 | BB7: 62 | BC7: 62 | BD7: 60 | BE7: 62 | BF7: 64 | BG7: 65 | BH7: 65 | BI7: 66 | BJ7: 70 | BK7: 68 | BL7: 71 | BM7: 69 | BN7: 70 | BO7: 75 | BP7: 72 | BQ7: 76 | BR7: 78 | BS7: 86 | BT7: 91 | BU7: 92 | BV7: 91 | BW7: 91 | BX7: 95 | BY7: 95 | BZ7: 97 | CA7: 102 | CB7: 105 | CC7: 104 | CD7: 105 | CE7: 109
B9: AGRICULTURE, FORESTRY & FISHING | C9: A | D9: 100 | E9: 26 | F9: 30 | G9: 27 | H9: 29 | I9: 29 | J9: 29 | K9: 28 | L9: 28 | M9: 29 | N9: 32 | O9: 34 | P9: 35 | Q9: 34 | R9: 35 | S9: 34 | T9: 37 | U9: 35 | V9: 36 | W9: 35 | X9: 36 | Y9: 35 | Z9: 39 | AA9: 39 | AB9: 41 | AC9: 40 | AD9: 43 | AE9: 44 | AF9: 44 | AG9: 43 | AH9: 44 | AI9: 44 | AJ9: 46 | AK9: 48 | AL9: 47 | AM9: 50 | AN9: 44 | AO9: 47 | AP9: 47 | AQ9: 51 | AR9: 48 | AS9: 51 | AT9: 52 | AU9: 55 | AV9: 59 | AW9: 62 | AX9: 60 | AY9: 62 | AZ9: 58 | BA9: 58 | BB9: 57 | BC9: 63 | BD9: 53 | BE9: 53 | BF9: 56 | BG9: 62 | BH9: 60 | BI9: 64 | BJ9: 63 | BK9: 67 | BL9: 67 | BM9: 67 | BN9: 62 | BO9: 67 | BP9: 58 | BQ9: 69 | BR9: 76 | BS9: 85 | BT9: 93 | BU9: 97 | BV9: 101 | BW9: 96 | BX9: 100 | BY9: 101 | BZ9: 96 | CA9: 103 | CB9: 101 | CC9: 107 | CD9: 106 | CE9: 109
B10: Food crops | C10: AA | D10: 100 | E10: 19 | F10: 21 | G10: 22 | H10: 24 | I10: 25 | J10: 24 | K10: 23 | L10: 24 | M10: 23 | N10: 24 | O10: 25 | P10: 28 | Q10: 27 | R10: 27 | S10: 28 | T10: 32 | U10: 30 | V10: 28 | W10: 28 | X10: 29 | Y10: 29 | Z10: 33 | AA10: 32 | AB10: 35 | AC10: 33 | AD10: 36 | AE10: 38 | AF10: 38 | AG10: 38 | AH10: 39 | AI10: 40 | AJ10: 43 | AK10: 43 | AL10: 43 | AM10: 40 | AN10: 40 | AO10: 42 | AP10: 43 | AQ10: 42 | AR10: 46 | AS10: 46 | AT10: 49 | AU10: 53 | AV10: 60 | AW10: 64 | AX10: 61 | AY10: 58 | AZ10: 55 | BA10: 53 | BB10: 52 | BC10: 50 | BD10: 46 | BE10: 46 | BF10: 50 | BG10: 52 | BH10: 57 | BI10: 59 | BJ10: 58 | BK10: 62 | BL10: 66 | BM10: 61 | BN10: 57 | BO10: 55 | BP10: 52 | BQ10: 57 | BR10: 70 | BS10: 73 | BT10: 94 | BU10: 98 | BV10: 107 | BW10: 99 | BX10: 106 | BY10: 101 | BZ10: 96 | CA10: 94 | CB10: 104 | CC10: 103 | CD10: 105 | CE10: 98
B11: Export crops | C11: AB | D11: 100 | E11: 20 | F11: 20 | G11: 21 | H11: 21 | I11: 20 | J11: 20 | K11: 21 | L11: 21 | M11: 21 | N11: 21 | O11: 22 | P11: 22 | Q11: 25 | R11: 25 | S11: 24 | T11: 25 | U11: 26 | V11: 27 | W11: 25 | X11: 27 | Y11: 26 | Z11: 26 | AA11: 27 | AB11: 27 | AC11: 29 | AD11: 30 | AE11: 32 | AF11: 32 | AG11: 29 | AH11: 27 | AI11: 25 | AJ11: 25 | AK11: 35 | AL11: 33 | AM11: 34 | AN11: 34 | AO11: 34 | AP11: 34 | AQ11: 30 | AR11: 25 | AS11: 37 | AT11: 36 | AU11: 31 | AV11: 36 | AW11: 45 | AX11: 46 | AY11: 45 | AZ11: 45 | BA11: 41 | BB11: 46 | BC11: 44 | BD11: 45 | BE11: 36 | BF11: 42 | BG11: 34 | BH11: 36 | BI11: 49 | BJ11: 52 | BK11: 41 | BL11: 47 | BM11: 54 | BN11: 38 | BO11: 49 | BP11: 40 | BQ11: 83 | BR11: 61 | BS11: 85 | BT11: 74 | BU11: 93 | BV11: 62 | BW11: 84 | BX11: 70 | BY11: 111 | BZ11: 82 | CA11: 135 | CB11: 75 | CC11: 140 | CD11: 103 | CE11: 128
B12: Livestock & livestock products | C12: AC | D12: 100 | E12: 29 | F12: 29 | G12: 30 | H12: 30 | I12: 30 | J12: 29 | K12: 31 | L12: 31 | M12: 33 | N12: 36 | O12: 39 | P12: 42 | Q12: 44 | R12: 44 | S12: 43 | T12: 44 | U12: 43 | V12: 43 | W12: 44 | X12: 45 | Y12: 46 | Z12: 47 | AA12: 48 | AB12: 49 | AC12: 49 | AD12: 50 | AE12: 51 | AF12: 51 | AG12: 52 | AH12: 52 | AI12: 52 | AJ12: 53 | AK12: 53 | AL12: 53 | AM12: 53 | AN12: 54 | AO12: 54 | AP12: 54 | AQ12: 55 | AR12: 56 | AS12: 56 | AT12: 57 | AU12: 58 | AV12: 58 | AW12: 59 | AX12: 59 | AY12: 59 | AZ12: 59 | BA12: 61 | BB12: 59 | BC12: 58 | BD12: 57 | BE12: 56 | BF12: 60 | BG12: 62 | BH12: 68 | BI12: 68 | BJ12: 70 | BK12: 66 | BL12: 70 | BM12: 72 | BN12: 73 | BO12: 72 | BP12: 73 | BQ12: 77 | BR12: 80 | BS12: 87 | BT12: 91 | BU12: 91 | BV12: 94 | BW12: 95 | BX12: 95 | BY12: 97 | BZ12: 97 | CA12: 100 | CB12: 105 | CC12: 116 | CD12: 119 | CE12: 121
B13: Forestry | C13: AD | D13: 100 | E13: 40 | F13: 46 | G13: 41 | H13: 43 | I13: 41 | J13: 42 | K13: 43 | L13: 43 | M13: 47 | N13: 53 | O13: 56 | P13: 56 | Q13: 55 | R13: 57 | S13: 55 | T13: 56 | U13: 53 | V13: 58 | W13: 58 | X13: 59 | Y13: 54 | Z13: 63 | AA13: 64 | AB13: 63 | AC13: 63 | AD13: 65 | AE13: 66 | AF13: 66 | AG13: 65 | AH13: 67 | AI13: 65 | AJ13: 66 | AK13: 66 | AL13: 66 | AM13: 66 | AN13: 66 | AO13: 67 | AP13: 67 | AQ13: 67 | AR13: 67 | AS13: 68 | AT13: 68 | AU13: 68 | AV13: 67 | AW13: 62 | AX13: 64 | AY13: 73 | AZ13: 76 | BA13: 81 | BB13: 87 | BC13: 88 | BD13: 87 | BE13: 84 | BF13: 87 | BG13: 86 | BH13: 84 | BI13: 88 | BJ13: 86 | BK13: 86 | BL13: 79 | BM13: 89 | BN13: 90 | BO13: 87 | BP13: 88 | BQ13: 99 | BR13: 102 | BS13: 97 | BT13: 105 | BU13: 102 | BV13: 102 | BW13: 98 | BX13: 98 | BY13: 100 | BZ13: 100 | CA13: 100 | CB13: 100 | CC13: 101 | CD13: 101 | CE13: 102
B14: Fishing | C14: AE | D14: 100 | E14: 18 | F14: 19 | G14: 18 | H14: 19 | I14: 19 | J14: 20 | K14: 20 | L14: 21 | M14: 21 | N14: 25 | O14: 28 | P14: 28 | Q14: 28 | R14: 29 | S14: 29 | T14: 30 | U14: 30 | V14: 32 | W14: 33 | X14: 33 | Y14: 33 | Z14: 35 | AA14: 39 | AB14: 43 | AC14: 44 | AD14: 45 | AE14: 44 | AF14: 42 | AG14: 43 | AH14: 46 | AI14: 50 | AJ14: 54 | AK14: 50 | AL14: 50 | AM14: 50 | AN14: 51 | AO14: 54 | AP14: 53 | AQ14: 53 | AR14: 57 | AS14: 54 | AT14: 55 | AU14: 56 | AV14: 56 | AW14: 55 | AX14: 56 | AY14: 57 | AZ14: 64 | BA14: 64 | BB14: 62 | BC14: 59 | BD14: 57 | BE14: 57 | BF14: 58 | BG14: 58 | BH14: 56 | BI14: 47 | BJ14: 92 | BK14: 61 | BL14: 51 | BM14: 54 | BN14: 61 | BO14: 64 | BP14: 61 | BQ14: 65 | BR14: 70 | BS14: 79 | BT14: 82 | BU14: 76 | BV14: 77 | BW14: 79 | BX14: 86 | BY14: 88 | BZ14: 100 | CA14: 113 | CB14: 97 | CC14: 86 | CD14: 90 | CE14: 82
B15: INDUSTRY | C15: B-F | D15: 100 | E15: 28 | F15: 28 | G15: 28 | H15: 28 | I15: 31 | J15: 34 | K15: 33 | L15: 33 | M15: 33 | N15: 35 | O15: 35 | P15: 37 | Q15: 37 | R15: 37 | S15: 39 | T15: 40 | U15: 38 | V15: 40 | W15: 41 | X15: 42 | Y15: 43 | Z15: 45 | AA15: 45 | AB15: 45 | AC15: 45 | AD15: 47 | AE15: 47 | AF15: 47 | AG15: 45 | AH15: 45 | AI15: 44 | AJ15: 44 | AK15: 48 | AL15: 48 | AM15: 47 | AN15: 49 | AO15: 49 | AP15: 48 | AQ15: 47 | AR15: 48 | AS15: 48 | AT15: 47 | AU15: 47 | AV15: 50 | AW15: 53 | AX15: 55 | AY15: 55 | AZ15: 56 | BA15: 60 | BB15: 57 | BC15: 50 | BD15: 54 | BE15: 57 | BF15: 59 | BG15: 59 | BH15: 61 | BI15: 66 | BJ15: 71 | BK15: 55 | BL15: 66 | BM15: 69 | BN15: 75 | BO15: 80 | BP15: 81 | BQ15: 77 | BR15: 77 | BS15: 85 | BT15: 89 | BU15: 94 | BV15: 85 | BW15: 89 | BX15: 93 | BY15: 96 | BZ15: 95 | CA15: 104 | CB15: 105 | CC15: 105 | CD15: 104 | CE15: 106
B16: Mining & quarrying | C16: B | D16: 100 | E16: 12 | F16: 13 | G16: 13 | H16: 14 | I16: 15 | J16: 18 | K16: 19 | L16: 19 | M16: 24 | N16: 27 | O16: 27 | P16: 23 | Q16: 20 | R16: 17 | S16: 19 | T16: 22 | U16: 25 | V16: 25 | W16: 29 | X16: 41 | Y16: 46 | Z16: 49 | AA16: 46 | AB16: 43 | AC16: 46 | AD16: 46 | AE16: 48 | AF16: 47 | AG16: 50 | AH16: 52 | AI16: 49 | AJ16: 49 | AK16: 49 | AL16: 49 | AM16: 43 | AN16: 49 | AO16: 50 | AP16: 46 | AQ16: 43 | AR16: 40 | AS16: 37 | AT16: 39 | AU16: 41 | AV16: 49 | AW16: 48 | AX16: 48 | AY16: 52 | AZ16: 58 | BA16: 70 | BB16: 62 | BC16: 49 | BD16: 41 | BE16: 45 | BF16: 37 | BG16: 39 | BH16: 29 | BI16: 49 | BJ16: 50 | BK16: 37 | BL16: 52 | BM16: 77 | BN16: 84 | BO16: 124 | BP16: 140 | BQ16: 118 | BR16: 106 | BS16: 94 | BT16: 86 | BU16: 87 | BV16: 86 | BW16: 86 | BX16: 88 | BY16: 94 | BZ16: 101 | CA16: 101 | CB16: 104 | CC16: 104 | CD16: 108 | CE16: 107
B17: TOTAL MANUFACTURING | C17: C | D17: 100 | E17: 29 | F17: 29 | G17: 27 | H17: 27 | I17: 30 | J17: 31 | K17: 30 | L17: 31 | M17: 33 | N17: 35 | O17: 36 | P17: 38 | Q17: 40 | R17: 38 | S17: 39 | T17: 41 | U17: 41 | V17: 41 | W17: 41 | X17: 43 | Y17: 44 | Z17: 45 | AA17: 45 | AB17: 46 | AC17: 47 | AD17: 49 | AE17: 47 | AF17: 48 | AG17: 41 | AH17: 41 | AI17: 40 | AJ17: 41 | AK17: 51 | AL17: 51 | AM17: 51 | AN17: 52 | AO17: 52 | AP17: 52 | AQ17: 52 | AR17: 53 | AS17: 52 | AT17: 52 | AU17: 53 | AV17: 57 | AW17: 63 | AX17: 66 | AY17: 65 | AZ17: 64 | BA17: 61 | BB17: 60 | BC17: 54 | BD17: 66 | BE17: 65 | BF17: 67 | BG17: 59 | BH17: 75 | BI17: 70 | BJ17: 76 | BK17: 59 | BL17: 77 | BM17: 75 | BN17: 75 | BO17: 80 | BP17: 83 | BQ17: 84 | BR17: 90 | BS17: 96 | BT17: 104 | BU17: 98 | BV17: 93 | BW17: 95 | BX17: 100 | BY17: 101 | BZ17: 93 | CA17: 102 | CB17: 105 | CC17: 111 | CD17: 104 | CE17: 109
B18: Of which: Food | C18: CA | D18: 100 | E18: 33 | F18: 36 | G18: 37 | H18: 36 | I18: 37 | J18: 36 | K18: 39 | L18: 39 | M18: 42 | N18: 45 | O18: 49 | P18: 50 | Q18: 53 | R18: 53 | S18: 56 | T18: 57 | U18: 58 | V18: 57 | W18: 58 | X18: 60 | Y18: 57 | Z18: 65 | AA18: 69 | AB18: 70 | AC18: 68 | AD18: 70 | AE18: 74 | AF18: 76 | AG18: 73 | AH18: 71 | AI18: 69 | AJ18: 72 | AK18: 71 | AL18: 74 | AM18: 74 | AN18: 76 | AO18: 74 | AP18: 75 | AQ18: 75 | AR18: 78 | AS18: 79 | AT18: 74 | AU18: 76 | AV18: 92 | AW18: 116 | AX18: 133 | AY18: 121 | AZ18: 114 | BA18: 72 | BB18: 98 | BC18: 66 | BD18: 116 | BE18: 82 | BF18: 125 | BG18: 76 | BH18: 152 | BI18: 92 | BJ18: 127 | BK18: 70 | BL18: 138 | BM18: 88 | BN18: 87 | BO18: 91 | BP18: 101 | BQ18: 106 | BR18: 117 | BS18: 125 | BT18: 145 | BU18: 132 | BV18: 125 | BW18: 117 | BX18: 119 | BY18: 106 | BZ18: 96 | CA18: 93 | CB18: 104 | CC18: 111 | CD18: 113 | CE18: 113
B19: Beverages & tobacco | C19: CB | D19: 100 | E19: 11 | F19: 11 | G19: 11 | H19: 12 | I19: 13 | J19: 13 | K19: 13 | L19: 13 | M19: 14 | N19: 15 | O19: 18 | P19: 19 | Q19: 20 | R19: 21 | S19: 21 | T19: 24 | U19: 21 | V19: 23 | W19: 24 | X19: 24 | Y19: 22 | Z19: 23 | AA19: 24 | AB19: 24 | AC19: 24 | AD19: 26 | AE19: 26 | AF19: 27 | AG19: 27 | AH19: 28 | AI19: 28 | AJ19: 28 | AK19: 29 | AL19: 29 | AM19: 29 | AN19: 29 | AO19: 29 | AP19: 29 | AQ19: 29 | AR19: 30 | AS19: 30 | AT19: 30 | AU19: 30 | AV19: 31 | AW19: 36 | AX19: 36 | AY19: 38 | AZ19: 41 | BA19: 52 | BB19: 38 | BC19: 32 | BD19: 40 | BE19: 47 | BF19: 36 | BG19: 32 | BH19: 44 | BI19: 54 | BJ19: 37 | BK19: 33 | BL19: 47 | BM19: 63 | BN19: 50 | BO19: 67 | BP19: 63 | BQ19: 64 | BR19: 53 | BS19: 72 | BT19: 75 | BU19: 78 | BV19: 65 | BW19: 86 | BX19: 92 | BY19: 102 | BZ19: 79 | CA19: 108 | CB19: 112 | CC19: 123 | CD19: 99 | CE19: 120
B20: Textiles, clothing & leather goods | C20: CC | D20: 100 | E20: 42 | F20: 42 | G20: 42 | H20: 42 | I20: 43 | J20: 43 | K20: 43 | L20: 44 | M20: 48 | N20: 50 | O20: 51 | P20: 51 | Q20: 55 | R20: 50 | S20: 48 | T20: 48 | U20: 52 | V20: 52 | W20: 52 | X20: 59 | Y20: 62 | Z20: 66 | AA20: 66 | AB20: 66 | AC20: 65 | AD20: 65 | AE20: 65 | AF20: 65 | AG20: 68 | AH20: 68 | AI20: 68 | AJ20: 68 | AK20: 68 | AL20: 68 | AM20: 68 | AN20: 68 | AO20: 68 | AP20: 68 | AQ20: 68 | AR20: 68 | AS20: 69 | AT20: 69 | AU20: 67 | AV20: 68 | AW20: 67 | AX20: 68 | AY20: 67 | AZ20: 66 | BA20: 75 | BB20: 72 | BC20: 72 | BD20: 72 | BE20: 75 | BF20: 74 | BG20: 71 | BH20: 70 | BI20: 83 | BJ20: 92 | BK20: 84 | BL20: 82 | BM20: 92 | BN20: 89 | BO20: 89 | BP20: 86 | BQ20: 91 | BR20: 87 | BS20: 87 | BT20: 86 | BU20: 94 | BV20: 92 | BW20: 94 | BX20: 93 | BY20: 102 | BZ20: 99 | CA20: 100 | CB20: 98 | CC20: 104 | CD20: 100 | CE20: 100
... B44: Cultural, domestic & other services | C44: R-T | D44: 100 | E44: 65 | F44: 66 | G44: 66 | H44: 67 | I44: 68 | J44: 68 | K44: 68 | L44: 69 | M44: 71 | N44: 74 | O44: 77 | P44: 78 | Q44: 80 | R44: 81 | S44: 81 | T44: 81 | U44: 82 | V44: 82 | W44: 82 | X44: 83 | Y44: 86 | Z44: 87 | AA44: 88 | AB44: 88 | AC44: 89 | AD44: 89 | AE44: 90 | AF44: 91 | AG44: 93 | AH44: 93 | AI44: 93 | AJ44: 93 | AK44: 94 | AL44: 95 | AM44: 97 | AN44: 97 | AO44: 97 | AP44: 98 | AQ44: 99 | AR44: 98 | AS44: 100 | AT44: 101 | AU44: 101 | AV44: 100 | AW44: 102 | AX44: 103 | AY44: 104 | AZ44: 104 | BA44: 103 | BB44: 102 | BC44: 102 | BD44: 100 | BE44: 100 | BF44: 100 | BG44: 98 | BH44: 98 | BI44: 99 | BJ44: 98 | BK44: 96 | BL44: 96 | BM44: 95 | BN44: 95 | BO44: 94 | BP44: 93 | BQ44: 95 | BR44: 96 | BS44: 96 | BT44: 96 | BU44: 92 | BV44: 91 | BW44: 90 | BX44: 91 | BY44: 95 | BZ44: 99 | CA44: 102 | CB44: 104 | CC44: 102 | CD44: 102 | CE44: 104
B46: Taxes less subsidies on products | D46: 100 | E46: 38 | F46: 44 | G46: 43 | H46: 43 | I46: 40 | J46: 53 | K46: 51 | L46: 52 | M46: 49 | N46: 60 | O46: 60 | P46: 70 | Q46: 66 | R46: 63 | S46: 58 | T46: 56 | U46: 63 | V46: 58 | W46: 65 | X46: 70 | Y46: 80 | Z46: 84 | AA46: 76 | AB46: 72 | AC46: 74 | AD46: 72 | AE46: 68 | AF46: 68 | AG46: 73 | AH46: 72 | AI46: 75 | AJ46: 74 | AK46: 81 | AL46: 92 | AM46: 86 | AN46: 78 | AO46: 76 | AP46: 83 | AQ46: 85 | AR46: 90 | AS46: 83 | AT46: 91 | AU46: 88 | AV46: 90 | AW46: 97 | AX46: 105 | AY46: 93 | AZ46: 100 | BA46: 96 | BB46: 102 | BC46: 93 | BD46: 93 | BE46: 97 | BF46: 97 | BG46: 89 | BH46: 97 | BI46: 94 | BJ46: 93 | BK46: 96 | BL46: 98 | BM46: 68 | BN46: 69 | BO46: 73 | BP46: 70 | BQ46: 74 | BR46: 75 | BS46: 86 | BT46: 91 | BU46: 95 | BV46: 92 | BW46: 96 | BX46: 99 | BY46: 94 | BZ46: 97 | CA46: 103 | CB46: 107 | CC46: 106 | CD46: 108 | CE46: 105
B48: =QGDP_CP!B48 -> Source: National Institute of Statistics of Rwanda
B49: =QGDP_CP!B49 -> 46007

Sheet T3 GDP XQ
B2: Table 4
B3: Expenditure on GDP
B4: ( in billion Frw)
C5: 2024 | D5: 2006 Q1 | E5: 2006 Q2 | F5: 2006 Q3 | G5: 2006 Q4 | H5: 2007 Q1 | I5: 2007 Q2 | J5: 2007 Q3 | K5: 2007 Q4 | L5: 2008 Q1 | M5: 2008 Q2 | N5: 2008 Q3 | O5: 2008 Q4 | P5: 2009 Q1 | Q5: 2009 Q2 | R5: 2009 Q3 | S5: 2009 Q4 | T5: 2010 Q1 | U5: 2010 Q2 | V5: 2010 Q3 | W5: 2010 Q4 | X5: 2011 Q1 | Y5: 2011 Q2 | Z5: 2011 Q3 | AA5: 2011 Q4 | AB5: 2012 Q1 | AC5: 2012 Q2 | AD5: 2012 Q3 | AE5: 2012 Q4 | AF5: 2013 Q1 | AG5: 2013 Q2 | AH5: 2013 Q3 | AI5: 2013 Q4 | AJ5: 2014Q1 | AK5: 2014Q2 | AL5: 2014Q3 | AM5: 2014Q4 | AN5: 2015Q1 | AO5: 2015Q2 | AP5: 2015Q3 | AQ5: 2015Q4 | AR5: 2016Q1 | AS5: 2016Q2 | AT5: 2016Q3 | AU5: 2016Q4 | AV5: 2017Q1 | AW5: 2017Q2 | AX5: 2017Q3 | AY5: 2017Q4 | AZ5: 2018Q1 | BA5: 2018Q2 | BB5: 2018Q3 | BC5: 2018Q4 | BD5: 2019Q1 | BE5: 2019Q2 | BF5: 2019Q3 | BG5: 2019Q4 | BH5: 2020Q1 | BI5: 2020Q2 | BJ5: 2020Q3 | BK5: 2020Q4 | BL5: 2021Q1 | BM5: 2021Q2 | BN5: 2021Q3 | BO5: 2021Q4 | BP5: 2022Q1 | BQ5: 2022Q2 | BR5: 2022Q3 | BS5: 2022Q4 | BT5: 2023Q1 | BU5: 2023Q2 | BV5: 2023Q3 | BW5: 2023Q4 | BX5: 2024Q1 | BY5: 2024Q2 | BZ5: 2024Q3 | CA5: 2024Q4 | CB5: 2025Q1 | CC5: 2025Q2 | CD5: 2025Q3
B6: In current prices
B7: Gross Domestic Product | C7: 19918 | D7: 396 | E7: 446 | F7: 472 | G7: 492 | H7: 499 | I7: 540 | J7: 566 | K7: 592 | L7: 600 | M7: 679 | N7: 741 | O7: 779 | P7: 777 | Q7: 765 | R7: 799 | S7: 844 | T7: 842 | U7: 848 | V7: 895 | W7: 944 | X7: 952 | Y7: 987 | Z7: 1062 | AA7: 1083 | AB7: 1100 | AC7: 1128 | AD7: 1195 | AE7: 1219 | AF7: 1196 | AG7: 1235 | AH7: 1245 | AI7: 1312 | AJ7: 1336 | AK7: 1403 | AL7: 1296 | AM7: 1513 | AN7: 1451 | AO7: 1511 | AP7: 1418 | AQ7: 1701 | AR7: 1617 | AS7: 1707 | AT7: 1538 | AU7: 1906 | AV7: 1830 | AW7: 1964 | AX7: 1722 | AY7: 2105 | AZ7: 2016 | BA7: 2132 | BB7: 1884 | BC7: 2277 | BD7: 2160 | BE7: 2468 | BF7: 2195 | BG7: 2637 | BH7: 2395 | BI7: 2413 | BJ7: 2221 | BK7: 2862 | BL7: 2574 | BM7: 2841 | BN7: 2598 | BO7: 3112 | BP7: 3101 | BQ7: 3549 | BR7: 3304 | BS7: 4210 | BT7: 4031 | BU7: 4255 | BV7: 3875 | BW7: 5016 | BX7: 4514 | BY7: 4965 | BZ7: 4659 | CA7: 5780 | CB7: 5276 | CC7: 5799 | CD7: 5525 | CE7: =SUM(CB7:CD7) -> 16600
B9: Total final consumption expenditure | C9: 15959 | D9: 386 | E9: 422 | F9: 461 | G9: 468 | H9: 450 | I9: 495 | J9: 522 | K9: 548 | L9: 571 | M9: 625 | N9: 707 | O9: 717 | P9: 720 | Q9: 726 | R9: 770 | S9: 808 | T9: 802 | U9: 815 | V9: 852 | W9: 892 | X9: 869 | Y9: 944 | Z9: 1001 | AA9: 1003 | AB9: 1020 | AC9: 1079 | AD9: 1143 | AE9: 1081 | AF9: 1080 | AG9: 1101 | AH9: 1146 | AI9: 1221 | AJ9: 1254 | AK9: 1301 | AL9: 1233 | AM9: 1362 | AN9: 1365 | AO9: 1448 | AP9: 1355 | AQ9: 1575 | AR9: 1456 | AS9: 1608 | AT9: 1466 | AU9: 1741 | AV9: 1618 | AW9: 1754 | AX9: 1524 | AY9: 1860 | AZ9: 1785 | BA9: 1876 | BB9: 1591 | BC9: 1962 | BD9: 1851 | BE9: 2126 | BF9: 1723 | BG9: 2168 | BH9: 2144 | BI9: 2171 | BJ9: 1911 | BK9: 2561 | BL9: 2254 | BM9: 2498 | BN9: 2826 | BO9: 2632 | BP9: 2467 | BQ9: 2857 | BR9: 2584 | BS9: 3366 | BT9: 3319 | BU9: 3584 | BV9: 2896 | BW9: 4136 | BX9: 3471 | BY9: 4060 | BZ9: 3658 | CA9: 4770 | CB9: 4071 | CC9: 4828 | CD9: 4169 | CE9: =SUM(CB9:CD9) -> 13068
B10: Government | C10: 3333 | D10: 64 | E10: 80 | F10: 78 | G10: 72 | H10: 75 | I10: 71 | J10: 81 | K10: 88 | L10: 81 | M10: 81 | N10: 90 | O10: 96 | P10: 100 | Q10: 105 | R10: 102 | S10: 104 | T10: 108 | U10: 119 | V10: 115 | W10: 126 | X10: 95 | Y10: 116 | Z10: 137 | AA10: 149 | AB10: 147 | AC10: 174 | AD10: 135 | AE10: 153 | AF10: 146 | AG10: 175 | AH10: 152 | AI10: 177 | AJ10: 192 | AK10: 229 | AL10: 198 | AM10: 184 | AN10: 207 | AO10: 212 | AP10: 218 | AQ10: 215 | AR10: 265 | AS10: 231 | AT10: 269 | AU10: 266 | AV10: 264 | AW10: 285 | AX10: 311 | AY10: 296 | AZ10: 267 | BA10: 275 | BB10: 309 | BC10: 306 | BD10: 317 | BE10: 415 | BF10: 317 | BG10: 343 | BH10: 376 | BI10: 359 | BJ10: 361 | BK10: 390 | BL10: 442 | BM10: 502 | BN10: 530 | BO10: 489 | BP10: 585 | BQ10: 552 | BR10: 713 | BS10: 596 | BT10: 666 | BU10: 838 | BV10: 691 | BW10: 640 | BX10: 715 | BY10: 881 | BZ10: 772 | CA10: 966 | CB10: 837 | CC10: 912 | CD10: 864 | CE10: =SUM(CB10:CD10) -> 2613
B11: Households and NGOs | C11: 12626 | D11: 322 | E11: 342 | F11: 383 | G11: 396 | H11: 375 | I11: 424 | J11: 441 | K11: 460 | L11: 490 | M11: 544 | N11: 617 | O11: 621 | P11: 620 | Q11: 621 | R11: 668 | S11: 704 | T11: 694 | U11: 696 | V11: 737 | W11: 766 | X11: 774 | Y11: 828 | Z11: 864 | AA11: 854 | AB11: 873 | AC11: 905 | AD11: 1008 | AE11: 928 | AF11: 934 | AG11: 926 | AH11: 994 | AI11: 1044 | AJ11: 1062 | AK11: 1072 | AL11: 1035 | AM11: 1178 | AN11: 1158 | AO11: 1236 | AP11: 1137 | AQ11: 1360 | AR11: 1191 | AS11: 1377 | AT11: 1197 | AU11: 1475 | AV11: 1354 | AW11: 1469 | AX11: 1213 | AY11: 1564 | AZ11: 1518 | BA11: 1601 | BB11: 1281 | BC11: 1656 | BD11: 1534 | BE11: 1711 | BF11: 1406 | BG11: 1824 | BH11: 1768 | BI11: 1812 | BJ11: 1550 | BK11: 2171 | BL11: 1812 | BM11: 1996 | BN11: 2296 | BO11: 2143 | BP11: 1882 | BQ11: 2305 | BR11: 1871 | BS11: 2771 | BT11: 2654 | BU11: 2747 | BV11: 2205 | BW11: 3496 | BX11: 2757 | BY11: 3179 | BZ11: 2886 | CA11: 3804 | CB11: 3234 | CC11: 3916 | CD11: 3305 | CE11: =SUM(CB11:CD11) -> 10455
B13: Gross capital formation | C13: 6916 | D13: 58 | E13: 72 | F13: 68 | G13: 77 | H13: 86 | I13: 86 | J13: 95 | K13: 106 | L13: 110 | M13: 157 | N13: 156 | O13: 182 | P13: 192 | Q13: 171 | R13: 153 | S13: 162 | T13: 186 | U13: 167 | V13: 174 | W13: 207 | X13: 221 | Y13: 194 | Z13: 211 | AA13: 237 | AB13: 258 | AC13: 244 | AD13: 273 | AE13: 321 | AF13: 305 | AG13: 300 | AH13: 296 | AI13: 333 | AJ13: 326 | AK13: 325 | AL13: 280 | AM13: 375 | AN13: 359 | AO13: 363 | AP13: 350 | AQ13: 419 | AR13: 466 | AS13: 443 | AT13: 402 | AU13: 462 | AV13: 442 | AW13: 437 | AX13: 470 | AY13: 487 | AZ13: 356 | BA13: 329 | BB13: 356 | BC13: 448 | BD13: 420 | BE13: 472 | BF13: 585 | BG13: 572 | BH13: 462 | BI13: 416 | BJ13: 446 | BK13: 475 | BL13: 908 | BM13: 936 | BN13: 1009 | BO13: 1089 | BP13: 1139 | BQ13: 1348 | BR13: 1458 | BS13: 1404 | BT13: 1468 | BU13: 1510 | BV13: 1886 | BW13: 1725 | BX13: 1809 | BY13: 1696 | BZ13: 1754 | CA13: 1656 | CB13: 2029 | CC13: 1743 | CD13: 2064 | CE13: =SUM(CB13:CD13) -> 5836
B14: Construction | C14: 4443 | D14: 46 | E14: 53 | F14: 54 | G14: 59 | H14: 66 | I14: 61 | J14: 66 | K14: 72 | L14: 81 | M14: 89 | N14: 105 | O14: 116 | P14: 122 | Q14: 101 | R14: 97 | S14: 116 | T14: 129 | U14: 108 | V14: 112 | W14: 137 | X14: 166 | Y14: 134 | Z14: 146 | AA14: 183 | AB14: 175 | AC14: 166 | AD14: 194 | AE14: 233 | AF14: 224 | AG14: 201 | AH14: 219 | AI14: 241 | AJ14: 249 | AK14: 216 | AL14: 197 | AM14: 283 | AN14: 284 | AO14: 258 | AP14: 257 | AQ14: 309 | AR14: 315 | AS14: 297 | AT14: 286 | AU14: 303 | AV14: 280 | AW14: 275 | AX14: 291 | AY14: 297 | AZ14: 226 | BA14: 230 | BB14: 258 | BC14: 278 | BD14: 296 | BE14: 322 | BF14: 344 | BG14: 361 | BH14: 313 | BI14: 260 | BJ14: 326 | BK14: 363 | BL14: 565 | BM14: 492 | BN14: 620 | BO14: 666 | BP14: 795 | BQ14: 741 | BR14: 768 | BS14: 846 | BT14: 1009 | BU14: 810 | BV14: 994 | BW14: 1136 | BX14: 1164 | BY14: 1076 | BZ14: 1050 | CA14: 1153 | CB14: 1251 | CC14: 1206 | CD14: 1184 | CE14: =SUM(CB14:CD14) -> 3641
B15: Other | C15: 2472 | D15: 12 | E15: 19 | F15: 14 | G15: 18 | H15: 20 | I15: 25 | J15: 29 | K15: 34 | L15: 29 | M15: 68 | N15: 51 | O15: 66 | P15: 70 | Q15: 70 | R15: 56 | S15: 46 | T15: 57 | U15: 59 | V15: 62 | W15: 70 | X15: 55 | Y15: 60 | Z15: 65 | AA15: 54 | AB15: 83 | AC15: 78 | AD15: 79 | AE15: 88 | AF15: 81 | AG15: 99 | AH15: 77 | AI15: 92 | AJ15: 77 | AK15: 109 | AL15: 83 | AM15: 92 | AN15: 75 | AO15: 105 | AP15: 93 | AQ15: 110 | AR15: 151 | AS15: 146 | AT15: 116 | AU15: 159 | AV15: 162 | AW15: 162 | AX15: 179 | AY15: 190 | AZ15: 130 | BA15: 99 | BB15: 98 | BC15: 170 | BD15: 124 | BE15: 151 | BF15: 241 | BG15: 210 | BH15: 149 | BI15: 156 | BJ15: 119 | BK15: 112 | BL15: 343 | BM15: 444 | BN15: 388 | BO15: 423 | BP15: 343 | BQ15: 606 | BR15: 690 | BS15: 558 | BT15: 459 | BU15: 700 | BV15: 892 | BW15: 589 | BX15: 645 | BY15: 621 | BZ15: 704 | CA15: 503 | CB15: 778 | CC15: 536 | CD15: 880 | CE15: =SUM(CB15:CD15) -> 2194
B17: Resource balance | C17: -2957 | D17: -48 | E17: -48 | F17: -57 | G17: -53 | H17: -37 | I17: -41 | J17: -51 | K17: -62 | L17: -81 | M17: -103 | N17: -122 | O17: -120 | P17: -135 | Q17: -132 | R17: -124 | S17: -126 | T17: -146 | U17: -134 | V17: -131 | W17: -155 | X17: -138 | Y17: -151 | Z17: -150 | AA17: -157 | AB17: -178 | AC17: -195 | AD17: -221 | AE17: -183 | AF17: -189 | AG17: -166 | AH17: -197 | AI17: -242 | AJ17: -244 | AK17: -223 | AL17: -217 | AM17: -224 | AN17: -273 | AO17: -300 | AP17: -287 | AQ17: -293 | AR17: -305 | AS17: -344 | AT17: -330 | AU17: -297 | AV17: -230 | AW17: -227 | AX17: -272 | AY17: -242 | AZ17: -125 | BA17: -72 | BB17: -62 | BC17: -132 | BD17: -111 | BE17: -130 | BF17: -113 | BG17: -103 | BH17: -211 | BI17: -174 | BJ17: -136 | BK17: -174 | BL17: -587 | BM17: -593 | BN17: -1237 | BO17: -609 | BP17: -505 | BQ17: -656 | BR17: -738 | BS17: -561 | BT17: -756 | BU17: -839 | BV17: -907 | BW17: -845 | BX17: -767 | BY17: -791 | BZ17: -752 | CA17: -646 | CB17: -824 | CC17: -772 | CD17: -707 | CE17: =SUM(CB17:CD17) -> -2303
B18: Exports of goods & services | C18: 5661 | D18: 41 | E18: 58 | F18: 50 | G18: 52 | H18: 69 | I18: 77 | J18: 81 | K18: 78 | L18: 70 | M18: 84 | N18: 82 | O18: 83 | P18: 81 | Q18: 78 | R18: 90 | S18: 85 | T18: 84 | U18: 91 | V18: 107 | W18: 101 | X18: 117 | Y18: 114 | Z18: 152 | AA18: 139 | AB18: 137 | AC18: 124 | AD18: 152 | AE18: 152 | AF18: 150 | AG18: 191 | AH18: 179 | AI18: 162 | AJ18: 174 | AK18: 187 | AL18: 213 | AM18: 206 | AN18: 199 | AO18: 199 | AP18: 210 | AQ18: 206 | AR18: 241 | AS18: 232 | AT18: 303 | AU18: 281 | AV18: 349 | AW18: 385 | AX18: 408 | AY18: 438 | AZ18: 403 | BA18: 430 | BB18: 511 | BC18: 453 | BD18: 438 | BE18: 470 | BF18: 583 | BG18: 593 | BH18: 467 | BI18: 329 | BJ18: 607 | BK18: 444 | BL18: 388 | BM18: 493 | BN18: 586 | BO18: 678 | BP18: 642 | BQ18: 763 | BR18: 851 | BS18: 832 | BT18: 896 | BU18: 1003 | BV18: 1089 | BW18: 1084 | BX18: 1103 | BY18: 1276 | BZ18: 1646 | CA18: 1635 | CB18: 1234 | CC18: 1114 | CD18: 1380 | CE18: =SUM(CB18:CD18) -> 3728
B19: Goods (fob) | C19: 4238 | D19: 12 | E19: 29 | F19: 21 | G19: 23 | H19: 19 | I19: 27 | J19: 31 | K19: 28 | L19: 30 | M19: 44 | N19: 42 | O19: 42 | P19: 28 | Q19: 25 | R19: 37 | S19: 32 | T19: 31 | U19: 38 | V19: 53 | W19: 46 | X19: 61 | Y19: 58 | Z19: 96 | AA19: 83 | AB19: 81 | AC19: 68 | AD19: 95 | AE19: 94 | AF19: 86 | AG19: 126 | AH19: 113 | AI19: 94 | AJ19: 87 | AK19: 100 | AL19: 125 | AM19: 117 | AN19: 99 | AO19: 97 | AP19: 106 | AQ19: 100 | AR19: 84 | AS19: 87 | AT19: 112 | AU19: 108 | AV19: 181 | AW19: 208 | AX19: 228 | AY19: 236 | AZ19: 224 | BA19: 232 | BB19: 230 | BC19: 224 | BD19: 214 | BE19: 244 | BF19: 287 | BG19: 310 | BH19: 277 | BI19: 249 | BJ19: 458 | BK19: 313 | BL19: 258 | BM19: 364 | BN19: 443 | BO19: 510 | BP19: 479 | BQ19: 535 | BR19: 585 | BS19: 578 | BT19: 650 | BU19: 761 | BV19: 712 | BW19: 742 | BX19: 821 | BY19: 963 | BZ19: 1188 | CA19: 1265 | CB19: 917 | CC19: 752 | CD19: 890 | CE19: =SUM(CB19:CD19) -> 2559
B20: Services | C20: 1423 | D20: 29 | E20: 29 | F20: 29 | G20: 29 | H20: 50 | I20: 50 | J20: 50 | K20: 50 | L20: 40 | M20: 40 | N20: 40 | O20: 41 | P20: 53 | Q20: 53 | R20: 53 | S20: 53 | T20: 53 | U20: 53 | V20: 54 | W20: 55 | X20: 56 | Y20: 56 | Z20: 56 | AA20: 56 | AB20: 56 | AC20: 56 | AD20: 57 | AE20: 58 | AF20: 64 | AG20: 65 | AH20: 66 | AI20: 68 | AJ20: 87 | AK20: 87 | AL20: 88 | AM20: 89 | AN20: 100 | AO20: 102 | AP20: 104 | AQ20: 106 | AR20: 157 | AS20: 145 | AT20: 191 | AU20: 173 | AV20: 168 | AW20: 177 | AX20: 180 | AY20: 202 | AZ20: 179 | BA20: 197 | BB20: 281 | BC20: 230 | BD20: 224 | BE20: 226 | BF20: 297 | BG20: 282 | BH20: 190 | BI20: 80 | BJ20: 149 | BK20: 130 | BL20: 130 | BM20: 130 | BN20: 144 | BO20: 167 | BP20: 164 | BQ20: 228 | BR20: 265 | BS20: 253 | BT20: 245 | BU20: 241 | BV20: 377 | BW20: 342 | BX20: 282 | BY20: 313 | BZ20: 458 | CA20: 370 | CB20: 317 | CC20: 362 | CD20: 490 | CE20: =SUM(CB20:CD20) -> 1169
B21: Imports of goods & services | C21: 8618 | D21: 89 | E21: 106 | F21: 107 | G21: 105 | H21: 106 | I21: 118 | J21: 132 | K21: 140 | L21: 151 | M21: 187 | N21: 204 | O21: 203 | P21: 216 | Q21: 210 | R21: 214 | S21: 211 | T21: 230 | U21: 225 | V21: 238 | W21: 256 | X21: 255 | Y21: 265 | Z21: 302 | AA21: 296 | AB21: 315 | AC21: 319 | AD21: 373 | AE21: 335 | AF21: 339 | AG21: 357 | AH21: 376 | AI21: 404 | AJ21: 418 | AK21: 410 | AL21: 430 | AM21: 430 | AN21: 472 | AO21: 499 | AP21: 497 | AQ21: 499 | AR21: 546 | AS21: 576 | AT21: 633 | AU21: 578 | AV21: 579 | AW21: 612 | AX21: 680 | AY21: 680 | AZ21: 528 | BA21: 502 | BB21: 574 | BC21: 586 | BD21: 549 | BE21: 600 | BF21: 697 | BG21: 695 | BH21: 677 | BI21: 503 | BJ21: 743 | BK21: 618 | BL21: 976 | BM21: 1086 | BN21: 1824 | BO21: 1287 | BP21: 1147 | BQ21: 1419 | BR21: 1588 | BS21: 1392 | BT21: 1652 | BU21: 1842 | BV21: 1996 | BW21: 1929 | BX21: 1870 | BY21: 2068 | BZ21: 2399 | CA21: 2282 | CB21: 2058 | CC21: 1886 | CD21: 2088 | CE21: =SUM(CB21:CD21) -> 6032
... B23: Services | C23: 1303 | D23: 44 | E23: 44 | F23: 44 | G23: 44 | H23: 48 | I23: 48 | J23: 48 | K23: 48 | L23: 69 | M23: 69 | N23: 69 | O23: 70 | P23: 74 | Q23: 75 | R23: 70 | S23: 71 | T23: 70 | U23: 72 | V23: 72 | W23: 75 | X23: 79 | Y23: 80 | Z23: 85 | AA23: 84 | AB23: 82 | AC23: 84 | AD23: 92 | AE23: 90 | AF23: 102 | AG23: 107 | AH23: 109 | AI23: 112 | AJ23: 127 | AK23: 126 | AL23: 131 | AM23: 130 | AN23: 190 | AO23: 184 | AP23: 184 | AQ23: 188 | AR23: 192 | AS23: 207 | AT23: 239 | AU23: 220 | AV23: 197 | AW23: 202 | AX23: 242 | AY23: 238 | AZ23: 192 | BA23: 173 | BB23: 208 | BC23: 200 | BD23: 194 | BE23: 173 | BF23: 224 | BG23: 200 | BH23: 172 | BI23: 70 | BJ23: 111 | BK23: 83 | BL23: 132 | BM23: 158 | BN23: 215 | BO23: 189 | BP23: 206 | BQ23: 213 | BR23: 207 | BS23: 279 | BT23: 239 | BU23: 258 | BV23: 281 | BW23: 307 | BX23: 276 | BY23: 308 | BZ23: 368 | CA23: 350 | CB23: 309 | CC23: 372 | CD23: 393 | CE23: =SUM(CB23:CD23) -> 1074
B25: In constant prices | C25: 2024 | D25: 2006 Q1 | E25: 2006 Q2 | F25: 2006 Q3 | G25: 2006 Q4 | H25: 2007 Q1 | I25: 2007 Q2 | J25: 2007 Q3 | K25: 2007 Q4 | L25: 2008 Q1 | M25: 2008 Q2 | N25: 2008 Q3 | O25: 2008 Q4 | P25: 2009 Q1 | Q25: 2009 Q2 | R25: 2009 Q3 | S25: 2009 Q4 | T25: 2010 Q1 | U25: 2010 Q2 | V25: 2010 Q3 | W25: 2010 Q4 | X25: 2011 Q1 | Y25: 2011 Q2 | Z25: 2011 Q3 | AA25: 2011 Q4 | AB25: 2012 Q1 | AC25: 2012 Q2 | AD25: 2012 Q3 | AE25: 2012 Q4 | AF25: 2013 Q1 | AG25: 2013 Q2 | AH25: 2013 Q3 | AI25: 2013 Q4 | AJ25: 2014Q1 | AK25: 2014Q2 | AL25: 2014Q3 | AM25: 2014Q4 | AN25: 2015Q1 | AO25: 2015Q2 | AP25: 2015Q3 | AQ25: 2015Q4 | AR25: 2016Q1 | AS25: 2016Q2 | AT25: 2016Q3 | AU25: 2016Q4 | AV25: 2017Q1 | AW25: 2017Q2 | AX25: 2017Q3 | AY25: 2017Q4 | AZ25: 2018Q1 | BA25: 2018Q2 | BB25: 2018Q3 | BC25: 2018Q4 | BD25: 2019Q1 | BE25: 2019Q2 | BF25: 2019Q3 | BG25: 2019Q4 | BH25: 2020Q1 | BI25: 2020Q2 | BJ25: 2020Q3 | BK25: 2020Q4 | BL25: 2021Q1 | BM25: 2021Q2 | BN25: 2021Q3 | BO25: 2021Q4 | BP25: 2022Q1 | BQ25: 2022Q2 | BR25: 2022Q3 | BS25: 2022Q4 | BT25: 2023Q1 | BU25: 2023Q2 | BV25: 2023Q3 | BW25: 2023Q4 | BX25: 2024Q1 | BY25: 2024Q2 | BZ25: 2024Q3 | CA25: 2024Q4 | CB25: 2025Q1 | CC25: 2025Q2 | CD25: 2025Q3
B26: Gross Domestic Product | C26: 19918 | D26: 1323 | E26: 1421 | F26: 1561 | G26: 1564 | H26: 1500 | I26: 1531 | J26: 1619 | K26: 1666 | L26: 1642 | M26: 1736 | N26: 1810 | O26: 1833 | P26: 1842 | Q26: 1824 | R26: 1874 | S26: 1920 | T26: 1937 | U26: 1940 | V26: 2024 | W26: 2105 | X26: 2101 | Y26: 2055 | Z26: 2234 | AA26: 2254 | AB26: 2277 | AC26: 2275 | AD26: 2393 | AE26: 2445 | AF26: 2384 | AG26: 2456 | AH26: 2455 | AI26: 2539 | AJ26: 2504 | AK26: 2610 | AL26: 2368 | AM26: 2910 | AN26: 2723 | AO26: 2858 | AP26: 2569 | AQ26: 3164 | AR26: 2955 | AS26: 3059 | AT26: 2689 | AU26: 3251 | AV26: 3016 | AW26: 3214 | AX26: 2808 | AY26: 3479 | AZ26: 3264 | BA26: 3433 | BB26: 3026 | BC26: 3804 | BD26: 3468 | BE26: 3885 | BF26: 3383 | BG26: 4046 | BH26: 3621 | BI26: 3451 | BJ26: 3258 | BK26: 4042 | BL26: 3707 | BM26: 4070 | BN26: 3454 | BO26: 4350 | BP26: 4074 | BQ26: 4541 | BR26: 3852 | BS26: 4644 | BT26: 4386 | BU26: 4659 | BV26: 4261 | BW26: 5270 | BX26: 4741 | BY26: 5137 | BZ26: 4550 | CA26: 5489 | CB26: 5052 | CC26: 5540 | CD26: 5089
B28: Total final consumption expenditure | C28: 15959 | D28: 1361 | E28: 1486 | F28: 1685 | G28: 1675 | H28: 1448 | I28: 1506 | J28: 1620 | K28: 1642 | L28: 1501 | M28: 1613 | N28: 1742 | O28: 1766 | P28: 1766 | Q28: 1852 | R28: 1898 | S28: 1974 | T28: 1847 | U28: 1921 | V28: 1981 | W28: 2132 | X28: 1965 | Y28: 2103 | Z28: 2231 | AA28: 2269 | AB28: 2189 | AC28: 2356 | AD28: 2478 | AE28: 2376 | AF28: 2285 | AG28: 2355 | AH28: 2431 | AI28: 2621 | AJ28: 2621 | AK28: 2650 | AL28: 2515 | AM28: 2861 | AN28: 2921 | AO28: 3080 | AP28: 2843 | AQ28: 3354 | AR28: 3064 | AS28: 3341 | AT28: 2950 | AU28: 3382 | AV28: 2933 | AW28: 3135 | AX28: 2826 | AY28: 3407 | AZ28: 3343 | BA28: 3296 | BB28: 2868 | BC28: 3751 | BD28: 3356 | BE28: 3742 | BF28: 3047 | BG28: 3724 | BH28: 3804 | BI28: 3445 | BJ28: 3104 | BK28: 4033 | BL28: 3382 | BM28: 3701 | BN28: 3966 | BO28: 3880 | BP28: 3368 | BQ28: 3649 | BR28: 3134 | BS28: 3837 | BT28: 3731 | BU28: 3917 | BV28: 3280 | BW28: 4329 | BX28: 3687 | BY28: 4161 | BZ28: 3650 | CA28: 4462 | CB28: 3915 | CC28: 4477 | CD28: 3794
B29: Government | C29: 3333 | D29: 178 | E29: 221 | F29: 218 | G29: 199 | H29: 196 | I29: 186 | J29: 213 | K29: 229 | L29: 200 | M29: 199 | N29: 216 | O29: 226 | P29: 231 | Q29: 242 | R29: 232 | S29: 236 | T29: 239 | U29: 261 | V29: 258 | W29: 281 | X29: 210 | Y29: 250 | Z29: 295 | AA29: 322 | AB29: 309 | AC29: 348 | AD29: 279 | AE29: 311 | AF29: 282 | AG29: 335 | AH29: 290 | AI29: 337 | AJ29: 357 | AK29: 425 | AL29: 374 | AM29: 348 | AN29: 388 | AO29: 398 | AP29: 401 | AQ29: 393 | AR29: 455 | AS29: 383 | AT29: 449 | AU29: 438 | AV29: 434 | AW29: 454 | AX29: 492 | AY29: 471 | AZ29: 452 | BA29: 465 | BB29: 515 | BC29: 513 | BD29: 527 | BE29: 693 | BF29: 521 | BG29: 545 | BH29: 606 | BI29: 569 | BJ29: 548 | BK29: 604 | BL29: 612 | BM29: 676 | BN29: 709 | BO29: 652 | BP29: 755 | BQ29: 692 | BR29: 820 | BS29: 644 | BT29: 697 | BU29: 883 | BV29: 706 | BW29: 648 | BX29: 730 | BY29: 890 | BZ29: 765 | CA29: 949 | CB29: 804 | CC29: 885 | CD29: 784
B30: Households and NGOs | C30: 12626 | D30: 1183 | E30: 1264 | F30: 1467 | G30: 1476 | H30: 1252 | I30: 1320 | J30: 1407 | K30: 1412 | L30: 1300 | M30: 1414 | N30: 1526 | O30: 1540 | P30: 1535 | Q30: 1610 | R30: 1665 | S30: 1739 | T30: 1608 | U30: 1659 | V30: 1723 | W30: 1852 | X30: 1755 | Y30: 1853 | Z30: 1936 | AA30: 1947 | AB30: 1880 | AC30: 2008 | AD30: 2199 | AE30: 2065 | AF30: 2002 | AG30: 2020 | AH30: 2140 | AI30: 2285 | AJ30: 2264 | AK30: 2225 | AL30: 2141 | AM30: 2514 | AN30: 2533 | AO30: 2682 | AP30: 2442 | AQ30: 2961 | AR30: 2608 | AS30: 2958 | AT30: 2501 | AU30: 2945 | AV30: 2499 | AW30: 2682 | AX30: 2334 | AY30: 2935 | AZ30: 2891 | BA30: 2831 | BB30: 2354 | BC30: 3238 | BD30: 2829 | BE30: 3050 | BF30: 2526 | BG30: 3179 | BH30: 3198 | BI30: 2876 | BJ30: 2556 | BK30: 3429 | BL30: 2770 | BM30: 3025 | BN30: 3258 | BO30: 3228 | BP30: 2614 | BQ30: 2957 | BR30: 2314 | BS30: 3193 | BT30: 3034 | BU30: 3034 | BV30: 2574 | BW30: 3681 | BX30: 2958 | BY30: 3271 | BZ30: 2885 | CA30: 3513 | CB30: 3112 | CC30: 3592 | CD30: 3010
B32: Gross capital formation | C32: 6916 | D32: 208 | E32: 256 | F32: 262 | G32: 298 | H32: 298 | I32: 312 | J32: 319 | K32: 369 | L32: 343 | M32: 427 | N32: 450 | O32: 491 | P32: 479 | Q32: 446 | R32: 396 | S32: 437 | T32: 470 | U32: 412 | V32: 456 | W32: 547 | X32: 539 | Y32: 450 | Z32: 508 | AA32: 562 | AB32: 597 | AC32: 554 | AD32: 639 | AE32: 727 | AF32: 670 | AG32: 654 | AH32: 652 | AI32: 733 | AJ32: 712 | AK32: 704 | AL32: 618 | AM32: 824 | AN32: 802 | AO32: 816 | AP32: 791 | AQ32: 960 | AR32: 943 | AS32: 916 | AT32: 903 | AU32: 893 | AV32: 868 | AW32: 843 | AX32: 924 | AY32: 895 | AZ32: 853 | BA32: 847 | BB32: 943 | BC32: 1039 | BD32: 1024 | BE32: 1143 | BF32: 1322 | BG32: 1339 | BH32: 1101 | BI32: 906 | BJ32: 1018 | BK32: 1166 | BL32: 1178 | BM32: 1240 | BN32: 1269 | BO32: 1298 | BP32: 1266 | BQ32: 1606 | BR32: 1541 | BS32: 1392 | BT32: 1513 | BU32: 1626 | BV32: 1944 | BW32: 1821 | BX32: 1842 | BY32: 1746 | BZ32: 1653 | CA32: 1675 | CB32: 1904 | CC32: 1672 | CD32: 2007
B33: Construction | C33: 4443 | D33: 145 | E33: 158 | F33: 161 | G33: 175 | H33: 188 | I33: 171 | J33: 183 | K33: 198 | L33: 216 | M33: 226 | N33: 253 | O33: 261 | P33: 274 | Q33: 226 | R33: 216 | S33: 253 | T33: 286 | U33: 234 | V33: 241 | W33: 296 | X33: 357 | Y33: 281 | Z33: 303 | AA33: 376 | AB33: 356 | AC33: 327 | AD33: 379 | AE33: 457 | AF33: 436 | AG33: 384 | AH33: 416 | AI33: 455 | AJ33: 472 | AK33: 406 | AL33: 371 | AM33: 529 | AN33: 532 | AO33: 477 | AP33: 479 | AQ33: 569 | AR33: 557 | AS33: 522 | AT33: 505 | AU33: 525 | AV33: 477 | AW33: 457 | AX33: 480 | AY33: 484 | AZ33: 455 | BA33: 462 | BB33: 515 | BC33: 554 | BD33: 583 | BE33: 630 | BF33: 688 | BG33: 733 | BH33: 615 | BI33: 505 | BJ33: 650 | BK33: 716 | BL33: 778 | BM33: 585 | BN33: 715 | BO33: 780 | BP33: 982 | BQ33: 1021 | BR33: 868 | BS33: 935 | BT33: 923 | BU33: 952 | BV33: 1046 | BW33: 1195 | BX33: 1219 | BY33: 1114 | BZ33: 994 | CA33: 1117 | CB33: 1247 | CC33: 1173 | CD33: 1192
B34: Other | C34: 2472 | D34: 32 | E34: 58 | F34: 54 | G34: 69 | H34: 64 | I34: 90 | J34: 78 | K34: 104 | L34: 72 | M34: 133 | N34: 117 | O34: 143 | P34: 125 | Q34: 147 | R34: 106 | S34: 108 | T34: 108 | U34: 112 | V34: 128 | W34: 156 | X34: 111 | Y34: 111 | Z34: 101 | AA34: 102 | AB34: 143 | AC34: 133 | AD34: 154 | AE34: 153 | AF34: 132 | AG34: 145 | AH34: 135 | AI34: 162 | AJ34: 129 | AK34: 148 | AL34: 145 | AM34: 170 | AN34: 149 | AO34: 184 | AP34: 185 | AQ34: 249 | AR34: 245 | AS34: 266 | AT34: 240 | AU34: 213 | AV34: 232 | AW34: 229 | AX34: 264 | AY34: 243 | AZ34: 248 | BA34: 233 | BB34: 255 | BC34: 288 | BD34: 274 | BE34: 346 | BF34: 350 | BG34: 354 | BH34: 315 | BI34: 250 | BJ34: 249 | BK34: 294 | BL34: 399 | BM34: 655 | BN34: 553 | BO34: 517 | BP34: 284 | BQ34: 585 | BR34: 673 | BS34: 458 | BT34: 590 | BU34: 673 | BV34: 898 | BW34: 625 | BX34: 623 | BY34: 632 | BZ34: 658 | CA34: 558 | CB34: 657 | CC34: 499 | CD34: 815
B36: Resource balance | C36: -2957 | D36: -246 | E36: -321 | F36: -386 | G36: -410 | H36: -246 | I36: -287 | J36: -321 | K36: -345 | L36: -201 | M36: -304 | N36: -382 | O36: -423 | P36: -403 | Q36: -475 | R36: -420 | S36: -492 | T36: -379 | U36: -393 | V36: -413 | W36: -574 | X36: -403 | Y36: -498 | Z36: -505 | AA36: -577 | AB36: -509 | AC36: -635 | AD36: -724 | AE36: -659 | AF36: -570 | AG36: -553 | AH36: -628 | AI36: -816 | AJ36: -830 | AK36: -744 | AL36: -765 | AM36: -775 | AN36: -1000 | AO36: -1038 | AP36: -1065 | AQ36: -1150 | AR36: -1051 | AS36: -1198 | AT36: -1164 | AU36: -1024 | AV36: -785 | AW36: -765 | AX36: -942 | AY36: -823 | AZ36: -932 | BA36: -710 | BB36: -785 | BC36: -987 | BD36: -912 | BE36: -1000 | BF36: -987 | BG36: -1017 | BH36: -1284 | BI36: -901 | BJ36: -864 | BK36: -1157 | BL36: -853 | BM36: -871 | BN36: -1781 | BO36: -827 | BP36: -561 | BQ36: -714 | BR36: -823 | BS36: -585 | BT36: -858 | BU36: -883 | BV36: -964 | BW36: -880 | BX36: -787 | BY36: -769 | BZ36: -752 | CA36: -648 | CB36: -768 | CC36: -608 | CD36: -713
B37: Exports of goods & services | C37: 5661 | D37: 122 | E37: 146 | F37: 116 | G37: 120 | H37: 182 | I37: 191 | J37: 176 | K37: 177 | L37: 172 | M37: 177 | N37: 146 | O37: 146 | P37: 166 | Q37: 157 | R37: 155 | S37: 143 | T37: 163 | U37: 172 | V37: 177 | W37: 161 | X37: 216 | Y37: 186 | Z37: 221 | AA37: 209 | AB37: 237 | AC37: 209 | AD37: 233 | AE37: 227 | AF37: 242 | AG37: 295 | AH37: 284 | AI37: 255 | AJ37: 269 | AK37: 280 | AL37: 305 | AM37: 302 | AN37: 303 | AO37: 307 | AP37: 309 | AQ37: 310 | AR37: 333 | AS37: 310 | AT37: 386 | AU37: 358 | AV37: 451 | AW37: 484 | AX37: 501 | AY37: 532 | AZ37: 497 | BA37: 518 | BB37: 611 | BC37: 556 | BD37: 540 | BE37: 587 | BF37: 744 | BG37: 745 | BH37: 607 | BI37: 445 | BJ37: 786 | BK37: 527 | BL37: 451 | BM37: 554 | BN37: 657 | BO37: 760 | BP37: 816 | BQ37: 958 | BR37: 1066 | BS37: 995 | BT37: 1039 | BU37: 1191 | BV37: 1214 | BW37: 1173 | BX37: 1198 | BY37: 1322 | BZ37: 1622 | CA37: 1519 | CB37: 1187 | CC37: 1127 | CD37: 1289
B38: Goods (fob) | C38: 4238 | D38: 29 | E38: 53 | F38: 34 | G38: 36 | H38: 40 | I38: 48 | J38: 43 | K38: 44 | L38: 55 | M38: 65 | N38: 49 | O38: 49 | P38: 42 | Q38: 40 | R38: 43 | S38: 36 | T38: 44 | U38: 54 | V38: 60 | W38: 47 | X38: 85 | Y38: 65 | Z38: 96 | AA38: 88 | AB38: 110 | AC38: 90 | AD38: 109 | AE38: 102 | AF38: 106 | AG38: 150 | AH38: 139 | AI38: 115 | AJ38: 101 | AK38: 109 | AL38: 128 | AM38: 125 | AN38: 110 | AO38: 113 | AP38: 115 | AQ38: 115 | AR38: 116 | AS38: 115 | AT38: 134 | AU38: 134 | AV38: 232 | AW38: 253 | AX38: 266 | AY38: 272 | AZ38: 286 | BA38: 293 | BB38: 292 | BC38: 290 | BD38: 282 | BE38: 330 | BF38: 410 | BG38: 433 | BH38: 398 | BI38: 350 | BJ38: 616 | BK38: 383 | BL38: 275 | BM38: 380 | BN38: 464 | BO38: 537 | BP38: 607 | BQ38: 685 | BR38: 760 | BS38: 716 | BT38: 778 | BU38: 939 | BV38: 829 | BW38: 827 | BX38: 907 | BY38: 1007 | BZ38: 1165 | CA38: 1159 | CB38: 885 | CC38: 791 | CD38: 839
B39: Services | C39: 1423 | D39: 104 | E39: 99 | F39: 98 | G39: 96 | H39: 160 | I39: 161 | J39: 160 | K39: 159 | L39: 125 | M39: 118 | N39: 110 | O39: 107 | P39: 138 | Q39: 134 | R39: 132 | S39: 129 | T39: 130 | U39: 130 | V39: 132 | W39: 132 | X39: 134 | Y39: 130 | Z39: 128 | AA39: 126 | AB39: 123 | AC39: 121 | AD39: 122 | AE39: 125 | AF39: 137 | AG39: 136 | AH39: 136 | AI39: 138 | AJ39: 179 | AK39: 179 | AL39: 179 | AM39: 180 | AN39: 205 | AO39: 203 | AP39: 205 | AQ39: 206 | AR39: 231 | AS39: 208 | AT39: 267 | AU39: 237 | AV39: 229 | AW39: 240 | AX39: 244 | AY39: 271 | AZ39: 218 | BA39: 235 | BB39: 336 | BC39: 277 | BD39: 270 | BE39: 266 | BF39: 347 | BG39: 322 | BH39: 210 | BI39: 88 | BJ39: 160 | BK39: 141 | BL39: 176 | BM39: 174 | BN39: 193 | BO39: 223 | BP39: 209 | BQ39: 273 | BR39: 306 | BS39: 279 | BT39: 261 | BU39: 251 | BV39: 386 | BW39: 345 | BX39: 291 | BY39: 314 | BZ39: 458 | CA39: 361 | CB39: 302 | CC39: 336 | CD39: 450
B40: Imports of goods & services | C40: 8618 | D40: 345 | E40: 435 | F40: 433 | G40: 456 | H40: 425 | I40: 475 | J40: 477 | K40: 502 | L40: 376 | M40: 469 | N40: 477 | O40: 505 | P40: 519 | Q40: 561 | R40: 515 | S40: 547 | T40: 498 | U40: 523 | V40: 545 | W40: 626 | X40: 587 | Y40: 618 | Z40: 671 | AA40: 706 | AB40: 694 | AC40: 748 | AD40: 837 | AE40: 786 | AF40: 746 | AG40: 816 | AH40: 847 | AI40: 933 | AJ40: 965 | AK40: 921 | AL40: 971 | AM40: 973 | AN40: 1129 | AO40: 1160 | AP40: 1182 | AQ40: 1242 | AR40: 1209 | AS40: 1261 | AT40: 1367 | AU40: 1234 | AV40: 1245 | AW40: 1287 | AX40: 1425 | AY40: 1406 | AZ40: 1413 | BA40: 1314 | BB40: 1516 | BC40: 1545 | BD40: 1474 | BE40: 1606 | BF40: 1863 | BG40: 1884 | BH40: 1814 | BI40: 1303 | BJ40: 1858 | BK40: 1602 | BL40: 1305 | BM40: 1425 | BN40: 2438 | BO40: 1587 | BP40: 1377 | BQ40: 1672 | BR40: 1889 | BS40: 1580 | BT40: 1897 | BU40: 2074 | BV40: 2178 | BW40: 2052 | BX40: 1985 | BY40: 2091 | BZ40: 2374 | CA40: 2168 | CB40: 1955 | CC40: 1735 | CD40: 2002
... B42: Services | C42: 1303 | D42: 195 | E42: 206 | F42: 206 | G42: 215 | H42: 213 | I42: 211 | J42: 195 | K42: 189 | L42: 146 | M42: 141 | N42: 132 | O42: 141 | P42: 169 | Q42: 185 | R42: 159 | S42: 171 | T42: 139 | U42: 148 | V42: 148 | W42: 159 | X42: 156 | Y42: 165 | Z42: 169 | AA42: 171 | AB42: 159 | AC42: 172 | AD42: 187 | AE42: 185 | AF42: 198 | AG42: 213 | AH42: 217 | AI42: 222 | AJ42: 245 | AK42: 241 | AL42: 259 | AM42: 258 | AN42: 369 | AO42: 365 | AP42: 378 | AQ42: 398 | AR42: 374 | AS42: 400 | AT42: 456 | AU42: 413 | AV42: 373 | AW42: 374 | AX42: 447 | AY42: 434 | AZ42: 406 | BA42: 358 | BB42: 434 | BC42: 415 | BD42: 410 | BE42: 360 | BF42: 469 | BG42: 423 | BH42: 358 | BI42: 137 | BJ42: 213 | BK42: 165 | BL42: 177 | BM42: 210 | BN42: 290 | BO42: 237 | BP42: 253 | BQ42: 258 | BR42: 251 | BS42: 326 | BT42: 281 | BU42: 296 | BV42: 312 | BW42: 334 | BX42: 293 | BY42: 311 | BZ42: 365 | CA42: 333 | CB42: 299 | CC42: 366 | CD42: 386
B44: Deflators | C44: 2024 | D44: 2006 Q1 | E44: 2006 Q2 | F44: 2006 Q3 | G44: 2006 Q4 | H44: 2007 Q1 | I44: 2007 Q2 | J44: 2007 Q3 | K44: 2007 Q4 | L44: 2008 Q1 | M44: 2008 Q2 | N44: 2008 Q3 | O44: 2008 Q4 | P44: 2009 Q1 | Q44: 2009 Q2 | R44: 2009 Q3 | S44: 2009 Q4 | T44: 2010 Q1 | U44: 2010 Q2 | V44: 2010 Q3 | W44: 2010 Q4 | X44: 2011 Q1 | Y44: 2011 Q2 | Z44: 2011 Q3 | AA44: 2011 Q4 | AB44: 2012 Q1 | AC44: 2012 Q2 | AD44: 2012 Q3 | AE44: 2012 Q4 | AF44: 2013 Q1 | AG44: 2013 Q2 | AH44: 2013 Q3 | AI44: 2013 Q4 | AJ44: 2014Q1 | AK44: 2014Q2 | AL44: 2014Q3 | AM44: 2014Q4 | AN44: 2015Q1 | AO44: 2015Q2 | AP44: 2015Q3 | AQ44: 2015Q4 | AR44: 2016Q1 | AS44: 2016Q2 | AT44: 2016Q3 | AU44: 2016Q4 | AV44: 2017Q1 | AW44: 2017Q2 | AX44: 2017Q3 | AY44: 2017Q4 | AZ44: 2018Q1 | BA44: 2018Q2 | BB44: 2018Q3 | BC44: 2018Q4 | BD44: 2019Q1 | BE44: 2019Q2 | BF44: 2019Q3 | BG44: 2019Q4 | BH44: 2020Q1 | BI44: 2020Q2 | BJ44: 2020Q3 | BK44: 2020Q4 | BL44: 2021Q1 | BM44: 2021Q2 | BN44: 2021Q3 | BO44: 2021Q4 | BP44: 2022Q1 | BQ44: 2022Q2 | BR44: 2022Q3 | BS44: 2022Q4 | BT44: 2023Q1 | BU44: 2023Q2 | BV44: 2023Q3 | BW44: 2023Q4 | BX44: 2024Q1 | BY44: 2024Q2 | BZ44: 2024Q3 | CA44: 2024Q4 | CB44: 2025Q1 | CC44: 2025Q2 | CD44: 2025Q3
B45: Gross Domestic Product | C45: 100 | D45: 30 | E45: 31 | F45: 30 | G45: 31 | H45: 33 | I45: 35 | J45: 35 | K45: 36 | L45: 37 | M45: 39 | N45: 41 | O45: 43 | P45: 42 | Q45: 42 | R45: 43 | S45: 44 | T45: 43 | U45: 44 | V45: 44 | W45: 45 | X45: 45 | Y45: 48 | Z45: 48 | AA45: 48 | AB45: 48 | AC45: 50 | AD45: 50 | AE45: 50 | AF45: 50 | AG45: 50 | AH45: 51 | AI45: 52 | AJ45: 53 | AK45: 54 | AL45: 55 | AM45: 52 | AN45: 53 | AO45: 53 | AP45: 55 | AQ45: 54 | AR45: 55 | AS45: 56 | AT45: 57 | AU45: 59 | AV45: 61 | AW45: 61 | AX45: 61 | AY45: 61 | AZ45: 62 | BA45: 62 | BB45: 62 | BC45: 60 | BD45: 62 | BE45: 64 | BF45: 65 | BG45: 65 | BH45: 66 | BI45: 70 | BJ45: 68 | BK45: 71 | BL45: 69 | BM45: 70 | BN45: 75 | BO45: 72 | BP45: 76 | BQ45: 78 | BR45: 86 | BS45: 91 | BT45: 92 | BU45: 91 | BV45: 91 | BW45: 95 | BX45: 95 | BY45: 97 | BZ45: 102 | CA45: 105 | CB45: 104 | CC45: 105 | CD45: 109
B47: Total final consumption expenditure | C47: 100 | D47: 28 | E47: 28 | F47: 27 | G47: 28 | H47: 31 | I47: 33 | J47: 32 | K47: 33 | L47: 38 | M47: 39 | N47: 41 | O47: 41 | P47: 41 | Q47: 39 | R47: 41 | S47: 41 | T47: 43 | U47: 42 | V47: 43 | W47: 42 | X47: 44 | Y47: 45 | Z47: 45 | AA47: 44 | AB47: 47 | AC47: 46 | AD47: 46 | AE47: 45 | AF47: 47 | AG47: 47 | AH47: 47 | AI47: 47 | AJ47: 48 | AK47: 49 | AL47: 49 | AM47: 48 | AN47: 47 | AO47: 47 | AP47: 48 | AQ47: 47 | AR47: 48 | AS47: 48 | AT47: 50 | AU47: 51 | AV47: 55 | AW47: 56 | AX47: 54 | AY47: 55 | AZ47: 53 | BA47: 57 | BB47: 55 | BC47: 52 | BD47: 55 | BE47: 57 | BF47: 57 | BG47: 58 | BH47: 56 | BI47: 63 | BJ47: 62 | BK47: 63 | BL47: 67 | BM47: 68 | BN47: 71 | BO47: 68 | BP47: 73 | BQ47: 78 | BR47: 82 | BS47: 88 | BT47: 89 | BU47: 92 | BV47: 88 | BW47: 96 | BX47: 94 | BY47: 98 | BZ47: 100 | CA47: 107 | CB47: 104 | CC47: 108 | CD47: 110
B48: Government | C48: 100 | D48: 36 | E48: 36 | F48: 36 | G48: 36 | H48: 38 | I48: 38 | J48: 38 | K48: 38 | L48: 40 | M48: 41 | N48: 42 | O48: 42 | P48: 43 | Q48: 43 | R48: 44 | S48: 44 | T48: 45 | U48: 46 | V48: 45 | W48: 45 | X48: 45 | Y48: 46 | Z48: 46 | AA48: 46 | AB48: 48 | AC48: 50 | AD48: 48 | AE48: 49 | AF48: 52 | AG48: 52 | AH48: 52 | AI48: 53 | AJ48: 54 | AK48: 54 | AL48: 53 | AM48: 53 | AN48: 53 | AO48: 53 | AP48: 54 | AQ48: 55 | AR48: 58 | AS48: 60 | AT48: 60 | AU48: 61 | AV48: 61 | AW48: 63 | AX48: 63 | AY48: 63 | AZ48: 59 | BA48: 59 | BB48: 60 | BC48: 60 | BD48: 60 | BE48: 60 | BF48: 61 | BG48: 63 | BH48: 62 | BI48: 63 | BJ48: 66 | BK48: 64 | BL48: 72 | BM48: 74 | BN48: 75 | BO48: 75 | BP48: 78 | BQ48: 80 | BR48: 87 | BS48: 92 | BT48: 95 | BU48: 95 | BV48: 98 | BW48: 99 | BX48: 98 | BY48: 99 | BZ48: 101 | CA48: 102 | CB48: 104 | CC48: 103 | CD48: 110
B49: Households and NGOs | C49: 100 | D49: 27 | E49: 27 | F49: 26 | G49: 27 | H49: 30 | I49: 32 | J49: 31 | K49: 33 | L49: 38 | M49: 38 | N49: 40 | O49: 40 | P49: 40 | Q49: 39 | R49: 40 | S49: 40 | T49: 43 | U49: 42 | V49: 43 | W49: 41 | X49: 44 | Y49: 45 | Z49: 45 | AA49: 44 | AB49: 46 | AC49: 45 | AD49: 46 | AE49: 45 | AF49: 47 | AG49: 46 | AH49: 46 | AI49: 46 | AJ49: 47 | AK49: 48 | AL49: 48 | AM49: 47 | AN49: 46 | AO49: 46 | AP49: 47 | AQ49: 46 | AR49: 46 | AS49: 47 | AT49: 48 | AU49: 50 | AV49: 54 | AW49: 55 | AX49: 52 | AY49: 53 | AZ49: 53 | BA49: 57 | BB49: 54 | BC49: 51 | BD49: 54 | BE49: 56 | BF49: 56 | BG49: 57 | BH49: 55 | BI49: 63 | BJ49: 61 | BK49: 63 | BL49: 65 | BM49: 66 | BN49: 70 | BO49: 66 | BP49: 72 | BQ49: 78 | BR49: 81 | BS49: 87 | BT49: 87 | BU49: 91 | BV49: 86 | BW49: 95 | BX49: 93 | BY49: 97 | BZ49: 100 | CA49: 108 | CB49: 104 | CC49: 109 | CD49: 110
B51: Gross capital formation | C51: 100 | D51: 28 | E51: 28 | F51: 26 | G51: 26 | H51: 29 | I51: 28 | J51: 30 | K51: 29 | L51: 32 | M51: 37 | N51: 35 | O51: 37 | P51: 40 | Q51: 38 | R51: 39 | S51: 37 | T51: 40 | U51: 41 | V51: 38 | W51: 38 | X51: 41 | Y51: 43 | Z51: 42 | AA51: 42 | AB51: 43 | AC51: 44 | AD51: 43 | AE51: 44 | AF51: 46 | AG51: 46 | AH51: 45 | AI51: 45 | AJ51: 46 | AK51: 46 | AL51: 45 | AM51: 46 | AN51: 45 | AO51: 44 | AP51: 44 | AQ51: 44 | AR51: 49 | AS51: 48 | AT51: 45 | AU51: 52 | AV51: 51 | AW51: 52 | AX51: 51 | AY51: 54 | AZ51: 42 | BA51: 39 | BB51: 38 | BC51: 43 | BD51: 41 | BE51: 41 | BF51: 44 | BG51: 43 | BH51: 42 | BI51: 46 | BJ51: 44 | BK51: 41 | BL51: 77 | BM51: 75 | BN51: 80 | BO51: 84 | BP51: 90 | BQ51: 84 | BR51: 95 | BS51: 101 | BT51: 97 | BU51: 93 | BV51: 97 | BW51: 95 | BX51: 98 | BY51: 97 | BZ51: 106 | CA51: 99 | CB51: 107 | CC51: 104 | CD51: 103
B52: Construction | C52: 100 | D52: 32 | E52: 34 | F52: 33 | G52: 34 | H52: 35 | I52: 36 | J52: 36 | K52: 36 | L52: 37 | M52: 39 | N52: 42 | O52: 44 | P52: 44 | Q52: 45 | R52: 45 | S52: 46 | T52: 45 | U52: 46 | V52: 46 | W52: 46 | X52: 46 | Y52: 48 | Z52: 48 | AA52: 49 | AB52: 49 | AC52: 51 | AD52: 51 | AE52: 51 | AF52: 51 | AG52: 52 | AH52: 53 | AI52: 53 | AJ52: 53 | AK52: 53 | AL52: 53 | AM52: 54 | AN52: 53 | AO52: 54 | AP52: 54 | AQ52: 54 | AR52: 57 | AS52: 57 | AT52: 57 | AU52: 58 | AV52: 59 | AW52: 60 | AX52: 61 | AY52: 61 | AZ52: 50 | BA52: 50 | BB52: 50 | BC52: 50 | BD52: 51 | BE52: 51 | BF52: 50 | BG52: 49 | BH52: 51 | BI52: 51 | BJ52: 50 | BK52: 51 | BL52: 73 | BM52: 84 | BN52: 87 | BO52: 85 | BP52: 81 | BQ52: 73 | BR52: 88 | BS52: 91 | BT52: 109 | BU52: 85 | BV52: 95 | BW52: 95 | BX52: 96 | BY52: 97 | BZ52: 106 | CA52: 103 | CB52: 100 | CC52: 103 | CD52: 99
B53: Other | C53: 100 | D53: 38 | E53: 33 | F53: 26 | G53: 26 | H53: 31 | I53: 28 | J53: 37 | K53: 33 | L53: 40 | M53: 51 | N53: 44 | O53: 46 | P53: 56 | Q53: 48 | R53: 53 | S53: 43 | T53: 53 | U53: 53 | V53: 48 | W53: 45 | X53: 50 | Y53: 54 | Z53: 64 | AA53: 53 | AB53: 58 | AC53: 59 | AD53: 51 | AE53: 58 | AF53: 61 | AG53: 68 | AH53: 57 | AI53: 57 | AJ53: 60 | AK53: 74 | AL53: 57 | AM53: 54 | AN53: 50 | AO53: 57 | AP53: 50 | AQ53: 44 | AR53: 62 | AS53: 55 | AT53: 48 | AU53: 75 | AV53: 70 | AW53: 71 | AX53: 68 | AY53: 78 | AZ53: 52 | BA53: 42 | BB53: 38 | BC53: 59 | BD53: 45 | BE53: 44 | BF53: 69 | BG53: 59 | BH53: 47 | BI53: 62 | BJ53: 48 | BK53: 38 | BL53: 86 | BM53: 68 | BN53: 70 | BO53: 82 | BP53: 121 | BQ53: 104 | BR53: 103 | BS53: 122 | BT53: 78 | BU53: 104 | BV53: 99 | BW53: 94 | BX53: 104 | BY53: 98 | BZ53: 107 | CA53: 90 | CB53: 118 | CC53: 107 | CD53: 108
B55: Resource balance | C55: 100 | D55: 20 | E55: 15 | F55: 15 | G55: 13 | H55: 15 | I55: 14 | J55: 16 | K55: 18 | L55: 40 | M55: 34 | N55: 32 | O55: 28 | P55: 34 | Q55: 28 | R55: 30 | S55: 26 | T55: 39 | U55: 34 | V55: 32 | W55: 27 | X55: 34 | Y55: 30 | Z55: 30 | AA55: 27 | AB55: 35 | AC55: 31 | AD55: 31 | AE55: 28 | AF55: 33 | AG55: 30 | AH55: 31 | AI55: 30 | AJ55: 29 | AK55: 30 | AL55: 28 | AM55: 29 | AN55: 27 | AO55: 29 | AP55: 27 | AQ55: 25 | AR55: 29 | AS55: 29 | AT55: 28 | AU55: 29 | AV55: 29 | AW55: 30 | AX55: 29 | AY55: 29 | AZ55: 13 | BA55: 10 | BB55: 8 | BC55: 13 | BD55: 12 | BE55: 13 | BF55: 12 | BG55: 10 | BH55: 16 | BI55: 19 | BJ55: 16 | BK55: 15 | BL55: 69 | BM55: 68 | BN55: 69 | BO55: 74 | BP55: 90 | BQ55: 92 | BR55: 90 | BS55: 96 | BT55: 88 | BU55: 95 | BV55: 94 | BW55: 96 | BX55: 97 | BY55: 103 | BZ55: 100 | CA55: 100 | CB55: 107 | CC55: 127 | CD55: 99
B56: Exports of goods & services | C56: 100 | D56: 34 | E56: 40 | F56: 43 | G56: 43 | H56: 38 | I56: 40 | J56: 46 | K56: 44 | L56: 41 | M56: 47 | N56: 56 | O56: 57 | P56: 49 | Q56: 50 | R56: 58 | S56: 59 | T56: 51 | U56: 53 | V56: 60 | W56: 63 | X56: 54 | Y56: 61 | Z56: 69 | AA56: 66 | AB56: 58 | AC56: 59 | AD56: 65 | AE56: 67 | AF56: 62 | AG56: 65 | AH56: 63 | AI56: 63 | AJ56: 65 | AK56: 67 | AL56: 70 | AM56: 68 | AN56: 66 | AO56: 65 | AP56: 68 | AQ56: 66 | AR56: 72 | AS56: 75 | AT56: 78 | AU56: 79 | AV56: 77 | AW56: 80 | AX56: 81 | AY56: 82 | AZ56: 81 | BA56: 83 | BB56: 84 | BC56: 82 | BD56: 81 | BE56: 80 | BF56: 78 | BG56: 80 | BH56: 77 | BI56: 74 | BJ56: 77 | BK56: 84 | BL56: 86 | BM56: 89 | BN56: 89 | BO56: 89 | BP56: 79 | BQ56: 80 | BR56: 80 | BS56: 84 | BT56: 86 | BU56: 84 | BV56: 90 | BW56: 92 | BX56: 92 | BY56: 97 | BZ56: 101 | CA56: 108 | CB56: 104 | CC56: 99 | CD56: 107
B57: Goods (fob) | C57: 100 | D57: 42 | E57: 55 | F57: 62 | G57: 64 | H57: 48 | I57: 56 | J57: 72 | K57: 63 | L57: 54 | M57: 68 | N57: 85 | O57: 85 | P57: 67 | Q57: 63 | R57: 86 | S57: 89 | T57: 70 | U57: 70 | V57: 88 | W57: 98 | X57: 72 | Y57: 89 | Z57: 100 | AA57: 95 | AB57: 73 | AC57: 76 | AD57: 87 | AE57: 92 | AF57: 81 | AG57: 84 | AH57: 81 | AI57: 82 | AJ57: 86 | AK57: 92 | AL57: 97 | AM57: 94 | AN57: 90 | AO57: 86 | AP57: 92 | AQ57: 87 | AR57: 72 | AS57: 76 | AT57: 83 | AU57: 80 | AV57: 78 | AW57: 82 | AX57: 86 | AY57: 87 | AZ57: 78 | BA57: 79 | BB57: 79 | BC57: 77 | BD57: 76 | BE57: 74 | BF57: 70 | BG57: 72 | BH57: 70 | BI57: 71 | BJ57: 74 | BK57: 82 | BL57: 94 | BM57: 96 | BN57: 95 | BO57: 95 | BP57: 79 | BQ57: 78 | BR57: 77 | BS57: 81 | BT57: 84 | BU57: 81 | BV57: 86 | BW57: 90 | BX57: 91 | BY57: 96 | BZ57: 102 | CA57: 109 | CB57: 104 | CC57: 95 | CD57: 106
B58: Services | C58: 100 | D58: 28 | E58: 29 | F58: 30 | G58: 30 | H58: 31 | I58: 31 | J58: 31 | K58: 32 | L58: 32 | M58: 34 | N58: 36 | O58: 38 | P58: 38 | Q58: 39 | R58: 40 | S58: 41 | T58: 41 | U58: 41 | V58: 41 | W58: 42 | X58: 42 | Y58: 43 | Z58: 44 | AA58: 44 | AB58: 45 | AC58: 46 | AD58: 47 | AE58: 46 | AF58: 47 | AG58: 48 | AH58: 49 | AI58: 49 | AJ58: 49 | AK58: 49 | AL58: 49 | AM58: 49 | AN58: 49 | AO58: 50 | AP58: 51 | AQ58: 51 | AR58: 68 | AS58: 70 | AT58: 71 | AU58: 73 | AV58: 73 | AW58: 74 | AX58: 74 | AY58: 74 | AZ58: 82 | BA58: 84 | BB58: 84 | BC58: 83 | BD58: 83 | BE58: 85 | BF58: 85 | BG58: 88 | BH58: 90 | BI58: 91 | BJ58: 93 | BK58: 92 | BL58: 74 | BM58: 74 | BN58: 74 | BO58: 75 | BP58: 78 | BQ58: 83 | BR58: 87 | BS58: 91 | BT58: 94 | BU58: 96 | BV58: 98 | BW58: 99 | BX58: 97 | BY58: 100 | BZ58: 100 | CA58: 103 | CB58: 105 | CC58: 108 | CD58: 109
B59: Imports of goods & services | C59: 100 | D59: 26 | E59: 24 | F59: 25 | G59: 23 | H59: 25 | I59: 25 | J59: 28 | K59: 28 | L59: 40 | M59: 40 | N59: 43 | O59: 40 | P59: 42 | Q59: 37 | R59: 42 | S59: 39 | T59: 46 | U59: 43 | V59: 44 | W59: 41 | X59: 43 | Y59: 43 | Z59: 45 | AA59: 42 | AB59: 45 | AC59: 43 | AD59: 45 | AE59: 43 | AF59: 45 | AG59: 44 | AH59: 44 | AI59: 43 | AJ59: 43 | AK59: 45 | AL59: 44 | AM59: 44 | AN59: 42 | AO59: 43 | AP59: 42 | AQ59: 40 | AR59: 45 | AS59: 46 | AT59: 46 | AU59: 47 | AV59: 47 | AW59: 48 | AX59: 48 | AY59: 48 | AZ59: 37 | BA59: 38 | BB59: 38 | BC59: 38 | BD59: 37 | BE59: 37 | BF59: 37 | BG59: 37 | BH59: 37 | BI59: 39 | BJ59: 40 | BK59: 39 | BL59: 75 | BM59: 76 | BN59: 75 | BO59: 81 | BP59: 83 | BQ59: 85 | BR59: 84 | BS59: 88 | BT59: 87 | BU59: 89 | BV59: 92 | BW59: 94 | BX59: 94 | BY59: 99 | BZ59: 101 | CA59: 105 | CB59: 105 | CC59: 109 | CD59: 104
... B61: Services | C61: 100 | D61: 23 | E61: 21 | F61: 21 | G61: 20 | H61: 23 | I61: 23 | J61: 25 | K61: 25 | L61: 47 | M61: 49 | N61: 52 | O61: 50 | P61: 44 | Q61: 40 | R61: 44 | S61: 42 | T61: 50 | U61: 49 | V61: 49 | W61: 47 | X61: 51 | Y61: 48 | Z61: 50 | AA61: 49 | AB61: 51 | AC61: 49 | AD61: 49 | AE61: 49 | AF61: 51 | AG61: 50 | AH61: 50 | AI61: 50 | AJ61: 52 | AK61: 52 | AL61: 50 | AM61: 50 | AN61: 52 | AO61: 50 | AP61: 49 | AQ61: 47 | AR61: 51 | AS61: 52 | AT61: 52 | AU61: 53 | AV61: 53 | AW61: 54 | AX61: 54 | AY61: 55 | AZ61: 47 | BA61: 48 | BB61: 48 | BC61: 48 | BD61: 47 | BE61: 48 | BF61: 48 | BG61: 47 | BH61: 48 | BI61: 51 | BJ61: 52 | BK61: 51 | BL61: 75 | BM61: 75 | BN61: 74 | BO61: 80 | BP61: 82 | BQ61: 83 | BR61: 82 | BS61: 86 | BT61: 85 | BU61: 87 | BV61: 90 | BW61: 92 | BX61: 94 | BY61: 99 | BZ61: 101 | CA61: 105 | CB61: 103 | CC61: 102 | CD61: 102
B62: Source: National Institute of Statistics of Rwanda
B63: 46007

Sheet T3A GDP XQ
B3: Table 4a
B4: Expenditure on GDP
D6: 2006Q1 | E6: 2006Q2 | F6: 2006Q3 | G6: 2006Q4 | H6: 2007Q1 | I6: 2007Q2 | J6: 2007Q3 | K6: 2007Q4 | L6: 2008Q1 | M6: 2008Q2 | N6: 2008Q3 | O6: 2008Q4 | P6: 2009Q1 | Q6: 2009Q2 | R6: 2009Q3 | S6: 2009Q4 | T6: 2010Q1 | U6: 2010Q2 | V6: 2010Q3 | W6: 2010Q4 | X6: 2011Q1 | Y6: 2011Q2 | Z6: 2011Q3 | AA6: 2011Q4 | AB6: 2012Q1 | AC6: 2012Q2 | AD6: 2012Q3 | AE6: 2012Q4 | AF6: 2013Q1 | AG6: 2013Q2 | AH6: 2013Q3 | AI6: 2013Q4 | AJ6: 2014Q1 | AK6: 2014Q2 | AL6: 2014Q3 | AM6: 2014Q4 | AN6: 2015Q1 | AO6: 2015Q2 | AP6: 2015Q3 | AQ6: 2015Q4 | AR6: 2016Q1 | AS6: 2016Q2 | AT6: 2016Q3 | AU6: 2016Q4 | AV6: 2017Q1 | AW6: 2017Q2 | AX6: 2017Q3 | AY6: 2017Q4 | AZ6: 2018Q1 | BA6: 2018Q2 | BB6: 2018Q3 | BC6: 2018Q4 | BD6: 2019Q1 | BE6: 2019Q2 | BF6: 2019Q3 | BG6: 2019Q4 | BH6: 2020Q1 | BI6: 2020Q2 | BJ6: 2020Q3 | BK6: 2020Q4 | BL6: 2021Q1 | BM6: 2021Q2 | BN6: 2021Q3 | BO6: 2021Q4 | BP6: 2022Q1 | BQ6: 2022Q2 | BR6: 2022Q3 | BS6: 2022Q4 | BT6: 2023Q1 | BU6: 2023Q2 | BV6: 2023Q3 | BW6: 2023Q4 | BX6: 2024Q1 | BY6: 2024Q2 | BZ6: 2024Q3 | CA6: 2024Q4 | CB6: 2025Q1 | CC6: 2025Q2 | CD6: 2025Q3
B7: Percentage of GDP, in current prices
B8: Gross Domestic Product | D8: 1 | E8: 1 | F8: 1 | G8: 1 | H8: 1 | I8: 1 | J8: 1 | K8: 1 | L8: 1 | M8: 1 | N8: 1 | O8: 1 | P8: 1 | Q8: 1 | R8: 1 | S8: 1 | T8: 1 | U8: 1 | V8: 1 | W8: 1 | X8: 1 | Y8: 1 | Z8: 1 | AA8: 1 | AB8: 1 | AC8: 1 | AD8: 1 | AE8: 1 | AF8: 1 | AG8: 1 | AH8: 1 | AI8: 1 | AJ8: 1 | AK8: 1 | AL8: 1 | AM8: 1 | AN8: 1 | AO8: 1 | AP8: 1 | AQ8: 1 | AR8: 1 | AS8: 1 | AT8: 1 | AU8: 1 | AV8: 1 | AW8: 1 | AX8: 1 | AY8: 1 | AZ8: 1 | BA8: 1 | BB8: 1 | BC8: 1 | BD8: 1 | BE8: 1 | BF8: 1 | BG8: 1 | BH8: 1 | BI8: 1 | BJ8: 1 | BK8: 1 | BL8: 1 | BM8: 1 | BN8: 1 | BO8: 1 | BP8: 1 | BQ8: 1 | BR8: 1 | BS8: 1 | BT8: 1 | BU8: 1 | BV8: 1 | BW8: 1 | BX8: 1 | BY8: 1 | BZ8: 1 | CA8: 1 | CB8: 1 | CC8: 1 | CD8: 1
B10: Total final consumption expenditure | D10: 0.97 | E10: 0.95 | F10: 0.98 | G10: 0.95 | H10: 0.9 | I10: 0.92 | J10: 0.92 | K10: 0.93 | L10: 0.95 | M10: 0.92 | N10: 0.95 | O10: 0.92 | P10: 0.93 | Q10: 0.95 | R10: 0.96 | S10: 0.96 | T10: 0.95 | U10: 0.96 | V10: 0.95 | W10: 0.94 | X10: 0.91 | Y10: 0.96 | Z10: 0.94 | AA10: 0.93 | AB10: 0.93 | AC10: 0.96 | AD10: 0.96 | AE10: 0.89 | AF10: 0.9 | AG10: 0.89 | AH10: 0.92 | AI10: 0.93 | AJ10: 0.94 | AK10: 0.93 | AL10: 0.95 | AM10: 0.9 | AN10: 0.94 | AO10: 0.96 | AP10: 0.96 | AQ10: 0.93 | AR10: 0.9 | AS10: 0.94 | AT10: 0.95 | AU10: 0.91 | AV10: 0.88 | AW10: 0.89 | AX10: 0.89 | AY10: 0.88 | AZ10: 0.89 | BA10: 0.88 | BB10: 0.84 | BC10: 0.86 | BD10: 0.86 | BE10: 0.86 | BF10: 0.79 | BG10: 0.82 | BH10: 0.9 | BI10: 0.9 | BJ10: 0.86 | BK10: 0.89 | BL10: 0.88 | BM10: 0.88 | BN10: 1.09 | BO10: 0.85 | BP10: 0.8 | BQ10: 0.81 | BR10: 0.78 | BS10: 0.8 | BT10: 0.82 | BU10: 0.84 | BV10: 0.75 | BW10: 0.82 | BX10: 0.77 | BY10: 0.82 | BZ10: 0.78 | CA10: 0.83 | CB10: 0.77 | CC10: 0.83 | CD10: 0.75
B11: Government | D11: 0.16 | E11: 0.18 | F11: 0.17 | G11: 0.15 | H11: 0.15 | I11: 0.13 | J11: 0.14 | K11: 0.15 | L11: 0.13 | M11: 0.12 | N11: 0.12 | O11: 0.12 | P11: 0.13 | Q11: 0.14 | R11: 0.13 | S11: 0.12 | T11: 0.13 | U11: 0.14 | V11: 0.13 | W11: 0.13 | X11: 0.1 | Y11: 0.12 | Z11: 0.13 | AA11: 0.14 | AB11: 0.13 | AC11: 0.15 | AD11: 0.11 | AE11: 0.13 | AF11: 0.12 | AG11: 0.14 | AH11: 0.12 | AI11: 0.13 | AJ11: 0.14 | AK11: 0.16 | AL11: 0.15 | AM11: 0.12 | AN11: 0.14 | AO11: 0.14 | AP11: 0.15 | AQ11: 0.13 | AR11: 0.16 | AS11: 0.14 | AT11: 0.17 | AU11: 0.14 | AV11: 0.14 | AW11: 0.15 | AX11: 0.18 | AY11: 0.14 | AZ11: 0.13 | BA11: 0.13 | BB11: 0.16 | BC11: 0.13 | BD11: 0.15 | BE11: 0.17 | BF11: 0.14 | BG11: 0.13 | BH11: 0.16 | BI11: 0.15 | BJ11: 0.16 | BK11: 0.14 | BL11: 0.17 | BM11: 0.18 | BN11: 0.2 | BO11: 0.16 | BP11: 0.19 | BQ11: 0.16 | BR11: 0.22 | BS11: 0.14 | BT11: 0.17 | BU11: 0.2 | BV11: 0.18 | BW11: 0.13 | BX11: 0.16 | BY11: 0.18 | BZ11: 0.17 | CA11: 0.17 | CB11: 0.16 | CC11: 0.16 | CD11: 0.16
B12: Households and NGOs | D12: 0.81 | E12: 0.77 | F12: 0.81 | G12: 0.8 | H12: 0.75 | I12: 0.79 | J12: 0.78 | K12: 0.78 | L12: 0.82 | M12: 0.8 | N12: 0.83 | O12: 0.8 | P12: 0.8 | Q12: 0.81 | R12: 0.84 | S12: 0.83 | T12: 0.82 | U12: 0.82 | V12: 0.82 | W12: 0.81 | X12: 0.81 | Y12: 0.84 | Z12: 0.81 | AA12: 0.79 | AB12: 0.79 | AC12: 0.8 | AD12: 0.84 | AE12: 0.76 | AF12: 0.78 | AG12: 0.75 | AH12: 0.8 | AI12: 0.8 | AJ12: 0.79 | AK12: 0.76 | AL12: 0.8 | AM12: 0.78 | AN12: 0.8 | AO12: 0.82 | AP12: 0.8 | AQ12: 0.8 | AR12: 0.74 | AS12: 0.81 | AT12: 0.78 | AU12: 0.77 | AV12: 0.74 | AW12: 0.75 | AX12: 0.7 | AY12: 0.74 | AZ12: 0.75 | BA12: 0.75 | BB12: 0.68 | BC12: 0.73 | BD12: 0.71 | BE12: 0.69 | BF12: 0.64 | BG12: 0.69 | BH12: 0.74 | BI12: 0.75 | BJ12: 0.7 | BK12: 0.76 | BL12: 0.7 | BM12: 0.7 | BN12: 0.88 | BO12: 0.69 | BP12: 0.61 | BQ12: 0.65 | BR12: 0.57 | BS12: 0.66 | BT12: 0.66 | BU12: 0.65 | BV12: 0.57 | BW12: 0.7 | BX12: 0.61 | BY12: 0.64 | BZ12: 0.62 | CA12: 0.66 | CB12: 0.61 | CC12: 0.68 | CD12: 0.6
B14: Gross capital formation | D14: 0.15 | E14: 0.16 | F14: 0.14 | G14: 0.16 | H14: 0.17 | I14: 0.16 | J14: 0.17 | K14: 0.18 | L14: 0.18 | M14: 0.23 | N14: 0.21 | O14: 0.23 | P14: 0.25 | Q14: 0.22 | R14: 0.19 | S14: 0.19 | T14: 0.22 | U14: 0.2 | V14: 0.19 | W14: 0.22 | X14: 0.23 | Y14: 0.2 | Z14: 0.2 | AA14: 0.22 | AB14: 0.23 | AC14: 0.22 | AD14: 0.23 | AE14: 0.26 | AF14: 0.25 | AG14: 0.24 | AH14: 0.24 | AI14: 0.25 | AJ14: 0.24 | AK14: 0.23 | AL14: 0.22 | AM14: 0.25 | AN14: 0.25 | AO14: 0.24 | AP14: 0.25 | AQ14: 0.25 | AR14: 0.29 | AS14: 0.26 | AT14: 0.26 | AU14: 0.24 | AV14: 0.24 | AW14: 0.22 | AX14: 0.27 | AY14: 0.23 | AZ14: 0.18 | BA14: 0.15 | BB14: 0.19 | BC14: 0.2 | BD14: 0.19 | BE14: 0.19 | BF14: 0.27 | BG14: 0.22 | BH14: 0.19 | BI14: 0.17 | BJ14: 0.2 | BK14: 0.17 | BL14: 0.35 | BM14: 0.33 | BN14: 0.39 | BO14: 0.35 | BP14: 0.37 | BQ14: 0.38 | BR14: 0.44 | BS14: 0.33 | BT14: 0.36 | BU14: 0.35 | BV14: 0.49 | BW14: 0.34 | BX14: 0.4 | BY14: 0.34 | BZ14: 0.38 | CA14: 0.29 | CB14: 0.38 | CC14: 0.3 | CD14: 0.37
B15: Construction | D15: 0.12 | E15: 0.12 | F15: 0.11 | G15: 0.12 | H15: 0.13 | I15: 0.11 | J15: 0.12 | K15: 0.12 | L15: 0.13 | M15: 0.13 | N15: 0.14 | O15: 0.15 | P15: 0.16 | Q15: 0.13 | R15: 0.12 | S15: 0.14 | T15: 0.15 | U15: 0.13 | V15: 0.13 | W15: 0.15 | X15: 0.17 | Y15: 0.14 | Z15: 0.14 | AA15: 0.17 | AB15: 0.16 | AC15: 0.15 | AD15: 0.16 | AE15: 0.19 | AF15: 0.19 | AG15: 0.16 | AH15: 0.18 | AI15: 0.18 | AJ15: 0.19 | AK15: 0.15 | AL15: 0.15 | AM15: 0.19 | AN15: 0.2 | AO15: 0.17 | AP15: 0.18 | AQ15: 0.18 | AR15: 0.19 | AS15: 0.17 | AT15: 0.19 | AU15: 0.16 | AV15: 0.15 | AW15: 0.14 | AX15: 0.17 | AY15: 0.14 | AZ15: 0.11 | BA15: 0.11 | BB15: 0.14 | BC15: 0.12 | BD15: 0.14 | BE15: 0.13 | BF15: 0.16 | BG15: 0.14 | BH15: 0.13 | BI15: 0.11 | BJ15: 0.15 | BK15: 0.13 | BL15: 0.22 | BM15: 0.17 | BN15: 0.24 | BO15: 0.21 | BP15: 0.26 | BQ15: 0.21 | BR15: 0.23 | BS15: 0.2 | BT15: 0.25 | BU15: 0.19 | BV15: 0.26 | BW15: 0.23 | BX15: 0.26 | BY15: 0.22 | BZ15: 0.23 | CA15: 0.2 | CB15: 0.24 | CC15: 0.21 | CD15: 0.21
B16: Other | D16: 0.03 | E16: 0.04 | F16: 0.03 | G16: 0.04 | H16: 0.04 | I16: 0.05 | J16: 0.05 | K16: 0.06 | L16: 0.05 | M16: 0.1 | N16: 0.07 | O16: 0.08 | P16: 0.09 | Q16: 0.09 | R16: 0.07 | S16: 0.05 | T16: 0.07 | U16: 0.07 | V16: 0.07 | W16: 0.07 | X16: 0.06 | Y16: 0.06 | Z16: 0.06 | AA16: 0.05 | AB16: 0.08 | AC16: 0.07 | AD16: 0.07 | AE16: 0.07 | AF16: 0.07 | AG16: 0.08 | AH16: 0.06 | AI16: 0.07 | AJ16: 0.06 | AK16: 0.08 | AL16: 0.06 | AM16: 0.06 | AN16: 0.05 | AO16: 0.07 | AP16: 0.07 | AQ16: 0.06 | AR16: 0.09 | AS16: 0.09 | AT16: 0.08 | AU16: 0.08 | AV16: 0.09 | AW16: 0.08 | AX16: 0.1 | AY16: 0.09 | AZ16: 0.06 | BA16: 0.05 | BB16: 0.05 | BC16: 0.07 | BD16: 0.06 | BE16: 0.06 | BF16: 0.11 | BG16: 0.08 | BH16: 0.06 | BI16: 0.06 | BJ16: 0.05 | BK16: 0.04 | BL16: 0.13 | BM16: 0.16 | BN16: 0.15 | BO16: 0.14 | BP16: 0.11 | BQ16: 0.17 | BR16: 0.21 | BS16: 0.13 | BT16: 0.11 | BU16: 0.16 | BV16: 0.23 | BW16: 0.12 | BX16: 0.14 | BY16: 0.13 | BZ16: 0.15 | CA16: 0.09 | CB16: 0.15 | CC16: 0.09 | CD16: 0.16
B18: Resource balance | D18: -0.12 | E18: -0.11 | F18: -0.12 | G18: -0.11 | H18: -0.07 | I18: -0.08 | J18: -0.09 | K18: -0.1 | L18: -0.13 | M18: -0.15 | N18: -0.16 | O18: -0.15 | P18: -0.17 | Q18: -0.17 | R18: -0.16 | S18: -0.15 | T18: -0.17 | U18: -0.16 | V18: -0.15 | W18: -0.16 | X18: -0.14 | Y18: -0.15 | Z18: -0.14 | AA18: -0.15 | AB18: -0.16 | AC18: -0.17 | AD18: -0.18 | AE18: -0.15 | AF18: -0.16 | AG18: -0.13 | AH18: -0.16 | AI18: -0.18 | AJ18: -0.18 | AK18: -0.16 | AL18: -0.17 | AM18: -0.15 | AN18: -0.19 | AO18: -0.2 | AP18: -0.2 | AQ18: -0.17 | AR18: -0.19 | AS18: -0.2 | AT18: -0.21 | AU18: -0.16 | AV18: -0.13 | AW18: -0.12 | AX18: -0.16 | AY18: -0.11 | AZ18: -0.06 | BA18: -0.03 | BB18: -0.03 | BC18: -0.06 | BD18: -0.05 | BE18: -0.05 | BF18: -0.05 | BG18: -0.04 | BH18: -0.09 | BI18: -0.07 | BJ18: -0.06 | BK18: -0.06 | BL18: -0.23 | BM18: -0.21 | BN18: -0.48 | BO18: -0.2 | BP18: -0.16 | BQ18: -0.18 | BR18: -0.22 | BS18: -0.13 | BT18: -0.19 | BU18: -0.2 | BV18: -0.23 | BW18: -0.17 | BX18: -0.17 | BY18: -0.16 | BZ18: -0.16 | CA18: -0.11 | CB18: -0.16 | CC18: -0.13 | CD18: -0.13
B19: Exports of goods & services | D19: 0.1 | E19: 0.13 | F19: 0.11 | G19: 0.11 | H19: 0.14 | I19: 0.14 | J19: 0.14 | K19: 0.13 | L19: 0.12 | M19: 0.12 | N19: 0.11 | O19: 0.11 | P19: 0.1 | Q19: 0.1 | R19: 0.11 | S19: 0.1 | T19: 0.1 | U19: 0.11 | V19: 0.12 | W19: 0.11 | X19: 0.12 | Y19: 0.12 | Z19: 0.14 | AA19: 0.13 | AB19: 0.12 | AC19: 0.11 | AD19: 0.13 | AE19: 0.12 | AF19: 0.13 | AG19: 0.15 | AH19: 0.14 | AI19: 0.12 | AJ19: 0.13 | AK19: 0.13 | AL19: 0.16 | AM19: 0.14 | AN19: 0.14 | AO19: 0.13 | AP19: 0.15 | AQ19: 0.12 | AR19: 0.15 | AS19: 0.14 | AT19: 0.2 | AU19: 0.15 | AV19: 0.19 | AW19: 0.2 | AX19: 0.24 | AY19: 0.21 | AZ19: 0.2 | BA19: 0.2 | BB19: 0.27 | BC19: 0.2 | BD19: 0.2 | BE19: 0.19 | BF19: 0.27 | BG19: 0.22 | BH19: 0.19 | BI19: 0.14 | BJ19: 0.27 | BK19: 0.16 | BL19: 0.15 | BM19: 0.17 | BN19: 0.23 | BO19: 0.22 | BP19: 0.21 | BQ19: 0.21 | BR19: 0.26 | BS19: 0.2 | BT19: 0.22 | BU19: 0.24 | BV19: 0.28 | BW19: 0.22 | BX19: 0.24 | BY19: 0.26 | BZ19: 0.35 | CA19: 0.28 | CB19: 0.23 | CC19: 0.19 | CD19: 0.25
B20: Goods (fob) | D20: 0.03 | E20: 0.07 | F20: 0.04 | G20: 0.05 | H20: 0.04 | I20: 0.05 | J20: 0.05 | K20: 0.05 | L20: 0.05 | M20: 0.06 | N20: 0.06 | O20: 0.05 | P20: 0.04 | Q20: 0.03 | R20: 0.05 | S20: 0.04 | T20: 0.04 | U20: 0.04 | V20: 0.06 | W20: 0.05 | X20: 0.06 | Y20: 0.06 | Z20: 0.09 | AA20: 0.08 | AB20: 0.07 | AC20: 0.06 | AD20: 0.08 | AE20: 0.08 | AF20: 0.07 | AG20: 0.1 | AH20: 0.09 | AI20: 0.07 | AJ20: 0.07 | AK20: 0.07 | AL20: 0.1 | AM20: 0.08 | AN20: 0.07 | AO20: 0.06 | AP20: 0.07 | AQ20: 0.06 | AR20: 0.05 | AS20: 0.05 | AT20: 0.07 | AU20: 0.06 | AV20: 0.1 | AW20: 0.11 | AX20: 0.13 | AY20: 0.11 | AZ20: 0.11 | BA20: 0.11 | BB20: 0.12 | BC20: 0.1 | BD20: 0.1 | BE20: 0.1 | BF20: 0.13 | BG20: 0.12 | BH20: 0.12 | BI20: 0.1 | BJ20: 0.21 | BK20: 0.11 | BL20: 0.1 | BM20: 0.13 | BN20: 0.17 | BO20: 0.16 | BP20: 0.15 | BQ20: 0.15 | BR20: 0.18 | BS20: 0.14 | BT20: 0.16 | BU20: 0.18 | BV20: 0.18 | BW20: 0.15 | BX20: 0.18 | BY20: 0.19 | BZ20: 0.25 | CA20: 0.22 | CB20: 0.17 | CC20: 0.13 | CD20: 0.16
B21: Services | D21: 0.07 | E21: 0.07 | F21: 0.06 | G21: 0.06 | H21: 0.1 | I21: 0.09 | J21: 0.09 | K21: 0.08 | L21: 0.07 | M21: 0.06 | N21: 0.05 | O21: 0.05 | P21: 0.07 | Q21: 0.07 | R21: 0.07 | S21: 0.06 | T21: 0.06 | U21: 0.06 | V21: 0.06 | W21: 0.06 | X21: 0.06 | Y21: 0.06 | Z21: 0.05 | AA21: 0.05 | AB21: 0.05 | AC21: 0.05 | AD21: 0.05 | AE21: 0.05 | AF21: 0.05 | AG21: 0.05 | AH21: 0.05 | AI21: 0.05 | AJ21: 0.07 | AK21: 0.06 | AL21: 0.07 | AM21: 0.06 | AN21: 0.07 | AO21: 0.07 | AP21: 0.07 | AQ21: 0.06 | AR21: 0.1 | AS21: 0.08 | AT21: 0.12 | AU21: 0.09 | AV21: 0.09 | AW21: 0.09 | AX21: 0.1 | AY21: 0.1 | AZ21: 0.09 | BA21: 0.09 | BB21: 0.15 | BC21: 0.1 | BD21: 0.1 | BE21: 0.09 | BF21: 0.14 | BG21: 0.11 | BH21: 0.08 | BI21: 0.03 | BJ21: 0.07 | BK21: 0.05 | BL21: 0.05 | BM21: 0.05 | BN21: 0.06 | BO21: 0.05 | BP21: 0.05 | BQ21: 0.06 | BR21: 0.08 | BS21: 0.06 | BT21: 0.06 | BU21: 0.06 | BV21: 0.1 | BW21: 0.07 | BX21: 0.06 | BY21: 0.06 | BZ21: 0.1 | CA21: 0.06 | CB21: 0.06 | CC21: 0.06 | CD21: 0.09
B22: Imports of goods & services | D22: 0.22 | E22: 0.24 | F22: 0.23 | G22: 0.21 | H22: 0.21 | I22: 0.22 | J22: 0.23 | K22: 0.24 | L22: 0.25 | M22: 0.28 | N22: 0.28 | O22: 0.26 | P22: 0.28 | Q22: 0.27 | R22: 0.27 | S22: 0.25 | T22: 0.27 | U22: 0.27 | V22: 0.27 | W22: 0.27 | X22: 0.27 | Y22: 0.27 | Z22: 0.28 | AA22: 0.27 | AB22: 0.29 | AC22: 0.28 | AD22: 0.31 | AE22: 0.27 | AF22: 0.28 | AG22: 0.29 | AH22: 0.3 | AI22: 0.31 | AJ22: 0.31 | AK22: 0.29 | AL22: 0.33 | AM22: 0.28 | AN22: 0.33 | AO22: 0.33 | AP22: 0.35 | AQ22: 0.29 | AR22: 0.34 | AS22: 0.34 | AT22: 0.41 | AU22: 0.3 | AV22: 0.32 | AW22: 0.31 | AX22: 0.39 | AY22: 0.32 | AZ22: 0.26 | BA22: 0.24 | BB22: 0.3 | BC22: 0.26 | BD22: 0.25 | BE22: 0.24 | BF22: 0.32 | BG22: 0.26 | BH22: 0.28 | BI22: 0.21 | BJ22: 0.33 | BK22: 0.22 | BL22: 0.38 | BM22: 0.38 | BN22: 0.7 | BO22: 0.41 | BP22: 0.37 | BQ22: 0.4 | BR22: 0.48 | BS22: 0.33 | BT22: 0.41 | BU22: 0.43 | BV22: 0.52 | BW22: 0.38 | BX22: 0.41 | BY22: 0.42 | BZ22: 0.51 | CA22: 0.39 | CB22: 0.39 | CC22: 0.33 | CD22: 0.38
... B24: Services | D24: 0.11 | E24: 0.1 | F24: 0.09 | G24: 0.09 | H24: 0.1 | I24: 0.09 | J24: 0.08 | K24: 0.08 | L24: 0.11 | M24: 0.1 | N24: 0.09 | O24: 0.09 | P24: 0.1 | Q24: 0.1 | R24: 0.09 | S24: 0.08 | T24: 0.08 | U24: 0.08 | V24: 0.08 | W24: 0.08 | X24: 0.08 | Y24: 0.08 | Z24: 0.08 | AA24: 0.08 | AB24: 0.07 | AC24: 0.07 | AD24: 0.08 | AE24: 0.07 | AF24: 0.09 | AG24: 0.09 | AH24: 0.09 | AI24: 0.09 | AJ24: 0.1 | AK24: 0.09 | AL24: 0.1 | AM24: 0.09 | AN24: 0.13 | AO24: 0.12 | AP24: 0.13 | AQ24: 0.11 | AR24: 0.12 | AS24: 0.12 | AT24: 0.16 | AU24: 0.12 | AV24: 0.11 | AW24: 0.1 | AX24: 0.14 | AY24: 0.11 | AZ24: 0.1 | BA24: 0.08 | BB24: 0.11 | BC24: 0.09 | BD24: 0.09 | BE24: 0.07 | BF24: 0.1 | BG24: 0.08 | BH24: 0.07 | BI24: 0.03 | BJ24: 0.05 | BK24: 0.03 | BL24: 0.05 | BM24: 0.06 | BN24: 0.08 | BO24: 0.06 | BP24: 0.07 | BQ24: 0.06 | BR24: 0.06 | BS24: 0.07 | BT24: 0.06 | BU24: 0.06 | BV24: 0.07 | BW24: 0.06 | BX24: 0.06 | BY24: 0.06 | BZ24: 0.08 | CA24: 0.06 | CB24: 0.06 | CC24: 0.06 | CD24: 0.07
B27: Growth rates, in constant prices | D27: 2006Q1 | E27: 2006Q2 | F27: 2006Q3 | G27: 2006Q4 | H27: 2007Q1 | I27: 2007Q2 | J27: 2007Q3 | K27: 2007Q4 | L27: 2008Q1 | M27: 2008Q2 | N27: 2008Q3 | O27: 2008Q4 | P27: 2009Q1 | Q27: 2009Q2 | R27: 2009Q3 | S27: 2009Q4 | T27: 2010Q1 | U27: 2010Q2 | V27: 2010Q3 | W27: 2010Q4 | X27: 2011Q1 | Y27: 2011Q2 | Z27: 2011Q3 | AA27: 2011Q4 | AB27: 2012Q1 | AC27: 2012Q2 | AD27: 2012Q3 | AE27: 2012Q4 | AF27: 2013Q1 | AG27: 2013Q2 | AH27: 2013Q3 | AI27: 2013Q4 | AJ27: 2014Q1 | AK27: 2014Q2 | AL27: 2014Q3 | AM27: 2014Q4 | AN27: 2015Q1 | AO27: 2015Q2 | AP27: 2015Q3 | AQ27: 2015Q4 | AR27: 2016Q1 | AS27: 2016Q2 | AT27: 2016Q3 | AU27: 2016Q4 | AV27: 2017Q1 | AW27: 2017Q2 | AX27: 2017Q3 | AY27: 2017Q4 | AZ27: 2018Q1 | BA27: 2018Q2 | BB27: 2018Q3 | BC27: 2018Q4 | BD27: 2019Q1 | BE27: 2019Q2 | BF27: 2019Q3 | BG27: 2019Q4 | BH27: 2020Q1 | BI27: 2020Q2 | BJ27: 2020Q3 | BK27: 2020Q4 | BL27: 2021Q1 | BM27: 2021Q2 | BN27: 2021Q3 | BO27: 2021Q4 | BP27: 2022Q1 | BQ27: 2022Q2 | BR27: 2022Q3 | BS27: 2022Q4 | BT27: 2023Q1 | BU27: 2023Q2 | BV27: 2023Q3 | BW27: 2023Q4 | BX27: 2024Q1 | BY27: 2024Q2 | BZ27: 2024Q3 | CA27: 2024Q4 | CB27: 2025Q1 | CC27: 2025Q2 | CD27: 2025Q3 | CF27: Contributions
B28: Gross Domestic Product | H28: 0.134 | I28: 0.077 | J28: 0.037 | K28: 0.066 | L28: 0.094 | M28: 0.134 | N28: 0.118 | O28: 0.1 | P28: 0.122 | Q28: 0.05 | R28: 0.035 | S28: 0.047 | T28: 0.052 | U28: 0.064 | V28: 0.08 | W28: 0.097 | X28: 0.084 | Y28: 0.059 | Z28: 0.103 | AA28: 0.071 | AB28: 0.084 | AC28: 0.107 | AD28: 0.072 | AE28: 0.085 | AF28: 0.047 | AG28: 0.08 | AH28: 0.026 | AI28: 0.038 | AJ28: 0.05 | AK28: 0.062 | AL28: -0.036 | AM28: 0.146 | AN28: 0.088 | AO28: 0.095 | AP28: 0.085 | AQ28: 0.087 | AR28: 0.085 | AS28: 0.07 | AT28: 0.047 | AU28: 0.028 | AV28: 0.021 | AW28: 0.051 | AX28: 0.044 | AY28: 0.07 | AZ28: 0.082 | BA28: 0.068 | BB28: 0.078 | BC28: 0.093 | BD28: 0.063 | BE28: 0.132 | BF28: 0.118 | BG28: 0.064 | BH28: 0.044 | BI28: -0.112 | BJ28: -0.037 | BK28: -0.001 | BL28: 0.024 | BM28: 0.179 | BN28: 0.06 | BO28: 0.076 | BP28: 0.099 | BQ28: 0.116 | BR28: 0.115 | BS28: 0.068 | BT28: 0.077 | BU28: 0.026 | BV28: 0.106 | BW28: 0.135 | BX28: 0.081 | BY28: 0.103 | BZ28: 0.068 | CA28: 0.042 | CB28: 0.065 | CC28: 0.078 | CD28: 0.118 | CF28: =CB28*CB8 -> 0.065 | CG28: =CC28*CC8 -> 0.078 | CH28: =CD28*CD8 -> 0.118
B30: Total final consumption expenditure | H30: 0.06 | I30: 0.01 | J30: -0.04 | K30: -0.02 | L30: 0.04 | M30: 0.07 | N30: 0.08 | O30: 0.08 | P30: 0.18 | Q30: 0.15 | R30: 0.09 | S30: 0.12 | T30: 0.05 | U30: 0.04 | V30: 0.04 | W30: 0.08 | X30: 0.06 | Y30: 0.1 | Z30: 0.13 | AA30: 0.06 | AB30: 0.11 | AC30: 0.12 | AD30: 0.11 | AE30: 0.05 | AF30: 0.04 | AG30: 0 | AH30: -0.02 | AI30: 0.1 | AJ30: 0.15 | AK30: 0.13 | AL30: 0.03 | AM30: 0.09 | AN30: 0.11 | AO30: 0.16 | AP30: 0.13 | AQ30: 0.17 | AR30: 0.05 | AS30: 0.08 | AT30: 0.04 | AU30: 0.01 | AV30: -0.04 | AW30: -0.06 | AX30: -0.04 | AY30: 0.01 | AZ30: 0.14 | BA30: 0.05 | BB30: 0.01 | BC30: 0.1 | BD30: 0 | BE30: 0.14 | BF30: 0.06 | BG30: -0.01 | BH30: 0.13 | BI30: -0.08 | BJ30: 0.02 | BK30: 0.08 | BL30: -0.11 | BM30: 0.07 | BN30: 0.28 | BO30: -0.04 | BP30: 0 | BQ30: -0.01 | BR30: -0.21 | BS30: -0.01 | BT30: 0.11 | BU30: 0.07 | BV30: 0.05 | BW30: 0.13 | BX30: -0.01 | BY30: 0.06 | BZ30: 0.11 | CA30: 0.03 | CB30: 0.06 | CC30: 0.08 | CD30: 0.04 | CF30: =CB30*CB10 -> 0.0462 | CG30: =CC30*CC10 -> 0.0664 | CH30: =CD30*CD10 -> 0.03
B31: Government | H31: 0.1 | I31: -0.16 | J31: -0.02 | K31: 0.15 | L31: 0.02 | M31: 0.07 | N31: 0.02 | O31: -0.01 | P31: 0.15 | Q31: 0.22 | R31: 0.07 | S31: 0.04 | T31: 0.03 | U31: 0.08 | V31: 0.11 | W31: 0.19 | X31: -0.12 | Y31: -0.04 | Z31: 0.14 | AA31: 0.15 | AB31: 0.47 | AC31: 0.39 | AD31: -0.05 | AE31: -0.03 | AF31: -0.09 | AG31: -0.04 | AH31: 0.04 | AI31: 0.08 | AJ31: 0.27 | AK31: 0.27 | AL31: 0.29 | AM31: 0.03 | AN31: 0.09 | AO31: -0.06 | AP31: 0.07 | AQ31: 0.13 | AR31: 0.17 | AS31: -0.04 | AT31: 0.12 | AU31: 0.11 | AV31: -0.05 | AW31: 0.18 | AX31: 0.1 | AY31: 0.08 | AZ31: 0.04 | BA31: 0.02 | BB31: 0.05 | BC31: 0.09 | BD31: 0.17 | BE31: 0.49 | BF31: 0.01 | BG31: 0.06 | BH31: 0.15 | BI31: -0.18 | BJ31: 0.05 | BK31: 0.11 | BL31: 0.01 | BM31: 0.19 | BN31: 0.29 | BO31: 0.08 | BP31: 0.23 | BQ31: 0.02 | BR31: 0.16 | BS31: -0.01 | BT31: -0.08 | BU31: 0.28 | BV31: -0.14 | BW31: 0.01 | BX31: 0.05 | BY31: 0.01 | BZ31: 0.08 | CA31: 0.46 | CB31: 0.1 | CC31: -0.01 | CD31: 0.02 | CF31: =CB31*CB11 -> 0.016 | CG31: =CC31*CC11 -> -0.0016 | CH31: =CD31*CD11 -> 0.0032
B32: Households and NGOs | H32: 0.06 | I32: 0.04 | J32: -0.04 | K32: -0.04 | L32: 0.04 | M32: 0.07 | N32: 0.08 | O32: 0.09 | P32: 0.18 | Q32: 0.14 | R32: 0.09 | S32: 0.13 | T32: 0.05 | U32: 0.03 | V32: 0.03 | W32: 0.07 | X32: 0.09 | Y32: 0.12 | Z32: 0.12 | AA32: 0.05 | AB32: 0.07 | AC32: 0.08 | AD32: 0.14 | AE32: 0.06 | AF32: 0.07 | AG32: 0.01 | AH32: -0.03 | AI32: 0.11 | AJ32: 0.13 | AK32: 0.1 | AL32: 0 | AM32: 0.1 | AN32: 0.12 | AO32: 0.21 | AP32: 0.14 | AQ32: 0.18 | AR32: 0.03 | AS32: 0.1 | AT32: 0.02 | AU32: -0.01 | AV32: -0.04 | AW32: -0.09 | AX32: -0.07 | AY32: 0 | AZ32: 0.16 | BA32: 0.06 | BB32: 0.01 | BC32: 0.1 | BD32: -0.02 | BE32: 0.08 | BF32: 0.07 | BG32: -0.02 | BH32: 0.13 | BI32: -0.06 | BJ32: 0.01 | BK32: 0.08 | BL32: -0.13 | BM32: 0.05 | BN32: 0.27 | BO32: -0.06 | BP32: -0.06 | BQ32: -0.02 | BR32: -0.29 | BS32: -0.01 | BT32: 0.16 | BU32: 0.03 | BV32: 0.11 | BW32: 0.15 | BX32: -0.03 | BY32: 0.08 | BZ32: 0.12 | CA32: -0.05 | CB32: 0.05 | CC32: 0.1 | CD32: 0.04 | CF32: =CB32*CB12 -> 0.0305 | CG32: =CC32*CC12 -> 0.068 | CH32: =CD32*CD12 -> 0.024
