Workbook

Sheet CPI
B1: 44206 | C1: 44237 | D1: 44265 | E1: 44296 | F1: 44326 | G1: 44357 | H1: 44387 | I1: 44418 | J1: 44449 | K1: 44479 | L1: 44510 | M1: 44540 | N1: 44571 | O1: 44602 | P1: 44630 | Q1: 44661 | R1: 44691 | S1: 44722 | T1: 44752 | U1: 44783 | V1: 44814 | W1: 44844 | X1: 44875 | Y1: 44905 | Z1: 44927 | AA1: 44958 | AB1: 44986 | AC1: 45017 | AD1: 45047 | AE1: 45078 | AF1: 45108 | AG1: 45139 | AH1: 45170 | AI1: 45200 | AJ1: 45231 | AK1: 45261 | AL1: 45292 | AM1: 45323 | AN1: 45352 | AO1: 45383 | AP1: 45413 | AQ1: 45444 | AR1: 45474 | AS1: 45505 | AT1: 45536 | AU1: 45566 | AV1: 45597 | AW1: 45627 | AX1: 45667 | AY1: 45698 | AZ1: 45726 | BA1: 45757 | BB1: 45787 | BC1: 45818 | BD1: 45848 | BE1: 45879 | BF1: 45910 | BG1: 45940 | BH1: 45971 | BI1: 46001 | BJ1: 46032
A2: GENERAL INDEX (CPI) | B2: 126.91145 | C2: 127.37657 | D2: 129.15009 | E2: 129.358 | F2: 128.74001 | G2: 128.4763 | H2: 128.43823 | I2: 128.76423 | J2: 129.54092 | K2: 130.37251 | L2: 129.66066 | M2: 129.70577 | N2: 132.402 | O2: 134.75045 | P2: 138.87804 | Q2: 142.20278 | R2: 144.92668 | S2: 146.0306 | T2: 148.44115 | U2: 149.20045 | V2: 152.4045 | W2: 156.53324 | X2: 157.80845 | Y2: 157.76338 | Z2: 159.79331 | AA2: 162.72619 | AB2: 165.64946 | AC2: 167.51534 | AD2: 165.3675 | AE2: 166.02467 | AF2: 166.07225 | AG2: 167.50281 | AH2: 173.55876 | AI2: 174.03131 | AJ2: 172.256 | AK2: 167.93568 | AL2: 167.71952 | AM2: 170.75183 | AN2: 172.57499 | AO2: 175.03788 | AP2: 175.02122 | AQ2: 174.39977 | AR2: 174.15236 | AS2: 175.79548 | AT2: 177.92631 | AU2: 180.6 | AV2: 180.80922 | AW2: 179.3197 | AX2: 180.21178 | AY2: 181.42933 | AZ2: 183.85347 | BA2: 186.01397 | BB2: 187.08379 | BC2: 186.66722 | BD2: 186.90166 | BE2: 188.28822 | BF2: 190.87421 | BG2: 193.39084 | BH2: 193.74242 | BI2: 193.71329 | BJ2: 196.32439 | BK2: =BI20/AW20-1 -> 0.070368023 | BL2: Deflator CPI food and non-alcoholic beverages - Average Jan Jul 2016/2015 | BM2: =BK3 -> 0.054944104 | BN2: Food crops
A3: Food and non-alcoholic beverages | B3: 139.22677 | C3: 139.78038 | D3: 143.85495 | E3: 144.57344 | F3: 141.27955 | G3: 140.2038 | H3: 140.29021 | I3: 140.06467 | J3: 142.38103 | K3: 143.01947 | L3: 139.19382 | M3: 138.31137 | N3: 145.42646 | O3: 150.79934 | P3: 158.47997 | Q3: 167.24756 | R3: 175.52664 | S3: 175.34164 | T3: 180.41188 | U3: 180.93181 | V3: 189.63584 | W3: 199.77003 | X3: 202.34608 | Y3: 199.64434 | Z3: 205.0317 | AA3: 214.67695 | AB3: 223.96086 | AC3: 228.79356 | AD3: 220.12713 | AE3: 221.23709 | AF3: 221.53487 | AG3: 225.47528 | AH3: 245.83827 | AI3: 245.82165 | AJ3: 237.74033 | AK3: 222.92408 | AL3: 220.1039 | AM3: 228.20113 | AN3: 229.49192 | AO3: 232.37814 | AP3: 230.56297 | AQ3: 228.14728 | AR3: 224.82087 | AS3: 229.04457 | AT3: 234.7133 | AU3: 243.4 | AV3: 242.70685 | AW3: 236.20754 | AX3: 235.89028 | AY3: 238.50491 | AZ3: 244.20308 | BA3: 250.68292 | BB3: 251.84198 | BC3: 248.01315 | BD3: 239.29056 | BE3: 241.36484 | BF3: 244.49837 | BG3: 247.23448 | BH3: 246.21982 | BI3: 244.76651 | BJ3: 248.45718 | BK3: =BI21/AW21-1 -> 0.054944104 | BL3: Deflator general CPI - Average Jan-Jul 2016/2015 | BM3: =BK2 -> 0.070368023 | BN3: Export crops
A4: v Bread and cereals | B4: 133.07469 | C4: 132.72374 | D4: 132.42361 | E4: 130.36768 | F4: 130.55823 | G4: 129.44976 | H4: 129.60427 | I4: 129.15321 | J4: 129.13068 | K4: 129.20901 | L4: 130.68226 | M4: 133.95541 | N4: 136.7585 | O4: 139.09349 | P4: 142.92634 | Q4: 148.46383 | R4: 155.60201 | S4: 159.92205 | T4: 163.69947 | U4: 165.12548 | V4: 176.71331 | W4: 182.11361 | X4: 185.4059 | Y4: 190.27657 | Z4: 191.91464 | AA4: 190.47701 | AB4: 191.94079 | AC4: 194.33395 | AD4: 177.34099 | AE4: 180.81605 | AF4: 182.20393 | AG4: 183.03318 | AH4: 185.23705 | AI4: 187.48473 | AJ4: 189.0618 | AK4: 189.18632 | AL4: 190.49675 | AM4: 188.70338 | AN4: 187.65261 | AO4: 195.89768 | AP4: 186.96302 | AQ4: 182.12067 | AR4: 180.143 | AS4: 182.15219 | AT4: 181.82335 | AU4: 184.3 | AV4: 184.6751 | AW4: 185.82101 | AX4: 187.47398 | AY4: 187.57921 | AZ4: 188.5381 | BA4: 191.04861 | BB4: 195.35128 | BC4: 196.42578 | BD4: 196.19535 | BE4: 197.35373 | BF4: 199.99644 | BG4: 203.32154 | BH4: 208.22167 | BI4: 208.8238 | BJ4: 208.55582 | BK4: =BI22/AW22-1 -> 0.058088447 | BL4: Deflator CPI meat - Average Jan Jul 2016/2015 | BM4: =BK5 -> 0.2688991 | BN4: Livestock & livestock products
A5: v Meat | B5: 153.90139 | C5: 154.60568 | D5: 154.70202 | E5: 154.85221 | F5: 155.31881 | G5: 155.73178 | H5: 155.85834 | I5: 155.32774 | J5: 157.90731 | K5: 162.72687 | L5: 163.16041 | M5: 163.46179 | N5: 165.02677 | O5: 164.71003 | P5: 165.60764 | Q5: 170.58913 | R5: 172.37421 | S5: 181.36261 | T5: 183.889 | U5: 185.4238 | V5: 186.71755 | W5: 187.12997 | X5: 186.54655 | Y5: 188.26232 | Z5: 187.45075 | AA5: 187.84087 | AB5: 193.48714 | AC5: 201.40759 | AD5: 201.39707 | AE5: 205.58786 | AF5: 206.09583 | AG5: 205.72965 | AH5: 207.27789 | AI5: 207.29104 | AJ5: 208.39521 | AK5: 209.63599 | AL5: 215.05793 | AM5: 219.93418 | AN5: 221.2003 | AO5: 223.87064 | AP5: 225.5674 | AQ5: 226.78717 | AR5: 227.81796 | AS5: 237.18729 | AT5: 248.51193 | AU5: 253.8 | AV5: 258.32662 | AW5: 262.96271 | AX5: 280.97382 | AY5: 293.88028 | AZ5: 297.19214 | BA5: 299.6353 | BB5: 298.97139 | BC5: 299.03699 | BD5: 297.64641 | BE5: 297.54567 | BF5: 299.03785 | BG5: 302.45491 | BH5: 305.90247 | BI5: 307.31776 | BJ5: 318.40505 | BK5: =BI23/AW23-1 -> 0.2688991 | BL5: Deflator general CPI - Average Jan Jul 2016/2015 | BM5: =BK2 -> 0.070368023 | BN5: Forestry
A6: v Fish | B6: 125.22699 | C6: 122.72323 | D6: 122.93953 | E6: 122.28343 | F6: 122.86343 | G6: 123.04829 | H6: 122.38021 | I6: 122.85124 | J6: 128.10854 | K6: 137.88027 | L6: 135.98683 | M6: 127.45605 | N6: 128.56009 | O6: 126.39627 | P6: 127.51764 | Q6: 129.19837 | R6: 131.92676 | S6: 134.36405 | T6: 136.0735 | U6: 138.37648 | V6: 166.41446 | W6: 171.90401 | X6: 170.19453 | Y6: 164.55212 | Z6: 159.73191 | AA6: 158.16636 | AB6: 159.7683 | AC6: 160.23161 | AD6: 161.80677 | AE6: 163.27512 | AF6: 164.28383 | AG6: 165.82054 | AH6: 171.9771 | AI6: 176.36277 | AJ6: 177.00451 | AK6: 178.91049 | AL6: 188.06394 | AM6: 194.17537 | AN6: 195.71326 | AO6: 196.55323 | AP6: 197.40643 | AQ6: 197.66193 | AR6: 198.48857 | AS6: 202.41234 | AT6: 201.379 | AU6: 202.4 | AV6: 203.06752 | AW6: 205.07295 | AX6: 206.16158 | AY6: 207.57123 | AZ6: 209.43332 | BA6: 211.86915 | BB6: 212.59539 | BC6: 213.37171 | BD6: 215.26217 | BE6: 216.75453 | BF6: 217.57718 | BG6: 219.17751 | BH6: 219.56362 | BI6: 218.83834 | BJ6: 223.16059 | BK6: =BI24/AW24-1 -> 0.077980856 | BL6: Deflator CPI fish - Average Jan Jul 2016/2015 | BM6: =BK6 -> 0.077980856 | BN6: Fishing
A7: v Vegetables | B7: 144.7282 | C7: 147.08725 | D7: 159.11208 | E7: 158.41916 | F7: 147.26888 | G7: 146.80694 | H7: 149.55691 | I7: 149.75576 | J7: 152.0559 | K7: 148.68278 | L7: 133.54021 | M7: 127.6182 | N7: 142.7081 | O7: 155.64521 | P7: 160.69307 | Q7: 170.20871 | R7: 180.58854 | S7: 187.72014 | T7: 201.0081 | U7: 202.98949 | V7: 216.24781 | W7: 238.659 | X7: 243.68116 | Y7: 230.34516 | Z7: 241.72988 | AA7: 270.99495 | AB7: 294.45646 | AC7: 300.05395 | AD7: 287.89246 | AE7: 289.99454 | AF7: 287.50492 | AG7: 297.25666 | AH7: 341.85223 | AI7: 329.62356 | AJ7: 298.50086 | AK7: 254.09874 | AL7: 241.70451 | AM7: 265.57164 | AN7: 272.04961 | AO7: 272.36882 | AP7: 281.30413 | AQ7: 285.49624 | AR7: 280.69618 | AS7: 283.97154 | AT7: 294.41407 | AU7: 306.9 | AV7: 296.8555 | AW7: 271.5648 | AX7: 259.47116 | AY7: 264.54033 | AZ7: 280.18367 | BA7: 295.54167 | BB7: 287.66249 | BC7: 279.46609 | BD7: 261.78731 | BE7: 269.36375 | BF7: 275.96501 | BG7: 277.62714 | BH7: 266.7763 | BI7: 258.92144 | BJ7: 266.96606 | BK7: =BI25/AW25-1 -> -0.022544887 | BN7: INDUSTRY
A8: v Non-alcoholic beverages | B8: 130.68464 | C8: 131.43065 | D8: 131.07698 | E8: 130.7014 | F8: 130.6736 | G8: 130.79839 | H8: 131.13203 | I8: 131.25853 | J8: 131.84961 | K8: 133.92724 | L8: 133.79459 | M8: 135.08769 | N8: 134.98712 | O8: 135.05469 | P8: 135.64999 | Q8: 136.6267 | R8: 136.83746 | S8: 137.32339 | T8: 144.8172 | U8: 150.30121 | V8: 154.69786 | W8: 159.9411 | X8: 163.80785 | Y8: 164.75423 | Z8: 169.36432 | AA8: 170.87139 | AB8: 172.01708 | AC8: 173.05046 | AD8: 174.11426 | AE8: 175.56167 | AF8: 179.41281 | AG8: 180.99004 | AH8: 182.37004 | AI8: 182.46909 | AJ8: 184.12676 | AK8: 186.61332 | AL8: 188.5661 | AM8: 192.06069 | AN8: 191.96306 | AO8: 191.82902 | AP8: 192.23297 | AQ8: 191.52888 | AR8: 192.09259 | AS8: 192.34009 | AT8: 192.30824 | AU8: 192.5 | AV8: 193.84061 | AW8: 193.54906 | AX8: 195.77464 | AY8: 196.22794 | AZ8: 197.27477 | BA8: 198.05676 | BB8: 200.48192 | BC8: 203.67515 | BD8: 206.08451 | BE8: 208.19342 | BF8: 209.50636 | BG8: 209.33523 | BH8: 211.51412 | BI8: 211.94731 | BJ8: 215.17994 | BK8: =BI26/AW26-1 -> 0.062157279 | BL8: Deflator PPI Mining - Average Jan-Jul 2016/2015 | BM8: =PPI!CB9 -> 0.030580785 | BN8: Mining & quarrying
A9: Alcoholic beverages and tobacco | B9: 170.42403 | C9: 174.83384 | D9: 174.8078 | E9: 174.86321 | F9: 174.69525 | G9: 175.17315 | H9: 174.8323 | I9: 175.957 | J9: 176.07602 | K9: 176.64995 | L9: 177.0705 | M9: 176.54581 | N9: 180.0259 | O9: 180.27397 | P9: 180.93384 | Q9: 183.19149 | R9: 183.56832 | S9: 184.26984 | T9: 193.34435 | U9: 194.92229 | V9: 195.39294 | W9: 202.19727 | X9: 211.13549 | Y9: 217.51455 | Z9: 221.4963 | AA9: 222.02961 | AB9: 223.56593 | AC9: 221.4463 | AD9: 223.02605 | AE9: 226.14 | AF9: 221.03665 | AG9: 218.74306 | AH9: 219.15637 | AI9: 219.18963 | AJ9: 220.06592 | AK9: 221.56608 | AL9: 221.43428 | AM9: 223.55337 | AN9: 223.67397 | AO9: 223.51388 | AP9: 224.34091 | AQ9: 229.86128 | AR9: 229.93799 | AS9: 230.52139 | AT9: 231.14554 | AU9: 231.6 | AV9: 234.46878 | AW9: 232.44719 | AX9: 234.65043 | AY9: 234.64346 | AZ9: 236.08894 | BA9: 238.54795 | BB9: 241.08278 | BC9: 249.10731 | BD9: 258.02406 | BE9: 261.59385 | BF9: 265.87909 | BG9: 268.7265 | BH9: 272.53295 | BI9: 271.30191 | BJ9: 271.18054 | BK9: =BI27/AW27-1 -> 0.10805073 | BN9: TOTAL MANUFACTURING
A10: Clothing and footwear | B10: 128.85754 | C10: 128.81187 | D10: 128.60772 | E10: 129.20979 | F10: 129.28353 | G10: 129.58659 | H10: 129.56038 | I10: 130.42696 | J10: 130.59684 | K10: 132.28452 | L10: 132.6492 | M10: 133.42637 | N10: 133.81308 | O10: 134.795 | P10: 135.39226 | Q10: 136.67181 | R10: 138.18758 | S10: 140.6206 | T10: 142.08787 | U10: 142.92069 | V10: 144.54232 | W10: 145.55949 | X10: 146.11758 | Y10: 147.64419 | Z10: 148.29592 | AA10: 148.4847 | AB10: 148.65197 | AC10: 149.75056 | AD10: 150.13287 | AE10: 151.3707 | AF10: 152.12378 | AG10: 152.64671 | AH10: 153.10277 | AI10: 153.51017 | AJ10: 154.54432 | AK10: 155.14323 | AL10: 156.6621 | AM10: 157.36255 | AN10: 158.21656 | AO10: 158.53039 | AP10: 159.29289 | AQ10: 159.84405 | AR10: 160.03024 | AS10: 160.32669 | AT10: 161.31251 | AU10: 162.1 | AV10: 163.19446 | AW10: 163.83724 | AX10: 164.43865 | AY10: 164.95365 | AZ10: 165.42446 | BA10: 165.90988 | BB10: 166.32574 | BC10: 166.94213 | BD10: 167.65912 | BE10: 168.4272 | BF10: 168.85559 | BG10: 169.7604 | BH10: 170.36336 | BI10: 170.72308 | BJ10: 173.41258 | BK10: =BI28/AW28-1 -> 0.046375346 | BL10: Deflator PPI Manufacturing food - Average Jan Jul 2016/2015 | BM10: =PPI!CB11 -> 0.074333333 | BN10: Manufacturing of food
A11: Housing, water, electricity, gas and other fuels | B11: 120.54146 | C11: 120.76618 | D11: 121.319 | E11: 120.95817 | F11: 121.49804 | G11: 121.66888 | H11: 121.41711 | I11: 121.74393 | J11: 121.85511 | K11: 122.32538 | L11: 122.57169 | M11: 122.68319 | N11: 123.71317 | O11: 126.20824 | P11: 131.11192 | Q11: 131.61477 | R11: 131.22836 | S11: 131.31933 | T11: 130.54301 | U11: 130.89705 | V11: 131.49416 | W11: 133.19655 | X11: 133.40791 | Y11: 133.80766 | Z11: 134.00112 | AA11: 135.18288 | AB11: 135.5758 | AC11: 135.62165 | AD11: 135.9429 | AE11: 135.92363 | AF11: 134.87519 | AG11: 134.56849 | AH11: 135.86769 | AI11: 135.91471 | AJ11: 136.67373 | AK11: 135.84806 | AL11: 136.79854 | AM11: 138.48425 | AN11: 139.18042 | AO11: 138.28372 | AP11: 139.29466 | AQ11: 138.60303 | AR11: 140.8832 | AS11: 141.06109 | AT11: 141.23944 | AU11: 142.4 | AV11: 142.66385 | AW11: 142.29753 | AX11: 142.32077 | AY11: 142.47304 | AZ11: 142.74219 | BA11: 142.87444 | BB11: 143.86833 | BC11: 143.56319 | BD11: 143.38511 | BE11: 144.2593 | BF11: 146.97158 | BG11: 153.02361 | BH11: 153.6608 | BI11: 154.19322 | BJ11: 157.23607 | BK11: =BI29/AW29-1 -> 0.04291356 | BL11: Deflator PPI Beverages (tobacco neglected) - Average Jan Jul 2016/2015 | BM11: =PPI!CB12 -> 0.072422702 | BN11: Manufacturing of beverages & tobacco
A12: Furnishing, household equipment and routine household maintenance | B12: 119.76546 | C12: 119.90489 | D12: 121.17108 | E12: 121.67572 | F12: 122.36931 | G12: 122.30917 | H12: 122.7665 | I12: 123.36768 | J12: 123.84162 | K12: 125.47681 | L12: 127.33105 | M12: 129.77564 | N12: 131.04431 | O12: 130.75147 | P12: 131.60648 | Q12: 132.56657 | R12: 133.53248 | S12: 137.01432 | T12: 142.39538 | U12: 144.00329 | V12: 144.62393 | W12: 145.8997 | X12: 146.64711 | Y12: 147.08966 | Z12: 148.11094 | AA12: 148.42775 | AB12: 149.35878 | AC12: 149.40291 | AD12: 149.77317 | AE12: 150.64208 | AF12: 150.98745 | AG12: 151.22532 | AH12: 151.49833 | AI12: 151.96374 | AJ12: 154.09127 | AK12: 154.5452 | AL12: 154.97066 | AM12: 154.88695 | AN12: 155.08214 | AO12: 155.39392 | AP12: 155.7941 | AQ12: 155.9859 | AR12: 156.06293 | AS12: 157.94882 | AT12: 158.73246 | AU12: 158.9 | AV12: 160.07823 | AW12: 161.52002 | AX12: 162.84174 | AY12: 163.48994 | AZ12: 163.82692 | BA12: 164.77454 | BB12: 165.76022 | BC12: 167.02366 | BD12: 168.29543 | BE12: 173.38376 | BF12: 173.28201 | BG12: 174.70904 | BH12: 174.88882 | BI12: 175.05949 | BJ12: 175.46247 | BK12: =BI30/AW30-1 -> 0.075306426 | BL12: Deflator PPI textiles - Average Jan Jul 2016/2015 | BM12: =PPI!CB13 -> 0 | BN12: Manufacturing of textiles, clothing & leather goods
A13: Health | B13: 107.71089 | C13: 107.67783 | D13: 107.70763 | E13: 107.72178 | F13: 107.73184 | G13: 107.77805 | H13: 107.80875 | I13: 107.8468 | J13: 108.08107 | K13: 108.13786 | L13: 108.64984 | M13: 108.77187 | N13: 108.7409 | O13: 109.01179 | P13: 109.04107 | Q13: 109.07661 | R13: 109.1976 | S13: 109.15957 | T13: 109.11617 | U13: 109.06591 | V13: 109.28388 | W13: 109.26262 | X13: 109.20678 | Y13: 109.33514 | Z13: 109.37526 | AA13: 109.36833 | AB13: 109.67864 | AC13: 109.59177 | AD13: 109.47071 | AE13: 109.57803 | AF13: 109.57935 | AG13: 109.7112 | AH13: 110.1305 | AI13: 109.86205 | AJ13: 109.89618 | AK13: 110.13544 | AL13: 111.0567 | AM13: 111.17857 | AN13: 112.21391 | AO13: 112.54718 | AP13: 113.77578 | AQ13: 113.47052 | AR13: 113.3956 | AS13: 113.40098 | AT13: 113.00122 | AU13: 113 | AV13: 113.43184 | AW13: 113.51212 | AX13: 113.27024 | AY13: 113.31959 | AZ13: 113.48844 | BA13: 114.53374 | BB13: 113.64822 | BC13: 114.10467 | BD13: 193.5764 | BE13: 193.35043 | BF13: 193.39687 | BG13: 193.66271 | BH13: 193.83884 | BI13: 193.83689 | BJ13: 193.77822 | BK13: =BI31/AW31-1 -> 0.36192636 | BL13: Deflator PPI Paper (wood neglected) - Average Jan Jul 2016/2015 | BM13: =PPI!CB14 -> 0 | BN13: Manufacturing of wood & paper; printing
A14: Transport | B14: 127.9925 | C14: 128.24242 | D14: 129.65427 | E14: 129.87782 | F14: 130.30513 | G14: 129.6981 | H14: 129.55711 | I14: 131.23546 | J14: 131.35396 | K14: 131.9169 | L14: 132.21083 | M14: 133.06904 | N14: 133.99678 | O14: 134.39655 | P14: 134.58993 | Q14: 138.98514 | R14: 140.35729 | S14: 144.59728 | T14: 145.65607 | U14: 147.71075 | V14: 150.41939 | W14: 149.8092 | X14: 150.32495 | Y14: 150.18344 | Z14: 150.93605 | AA14: 150.72108 | AB14: 150.75804 | AC14: 150.73026 | AD14: 150.99576 | AE14: 151.86085 | AF14: 154.11466 | AG14: 158.01511 | AH14: 159.27547 | AI14: 162.45341 | AJ14: 162.74039 | AK14: 160.22171 | AL14: 160.64796 | AM14: 162.92084 | AN14: 173.06412 | AO14: 187.26821 | AP14: 188.32766 | AQ14: 187.10922 | AR14: 187.59472 | AS14: 188.05507 | AT14: 188.24208 | AU14: 188.3 | AV14: 188.04776 | AW14: 188.83579 | AX14: 190.39894 | AY14: 191.23467 | AZ14: 193.75002 | BA14: 194.3838 | BB14: 195.23521 | BC14: 195.42919 | BD14: 200.67289 | BE14: 200.96277 | BF14: 204.3858 | BG14: 204.28418 | BH14: 205.52026 | BI14: 206.65304 | BJ14: 206.7521 | BK14: =BI32/AW32-1 -> 0.088875958 | BL14: Deflator PPI Chemicals and chemical products - Average Jan Jul 2016/2015 | BM14: =PPI!CB15 -> 0.07 | BN14: Manufacturing of chemicals, rubber & plastic products
A15: Communication | B15: 105.78212 | C15: 105.78212 | D15: 105.78212 | E15: 105.78212 | F15: 105.78212 | G15: 105.78212 | H15: 105.78212 | I15: 105.78212 | J15: 105.78212 | K15: 105.78212 | L15: 105.78212 | M15: 105.78212 | N15: 105.78212 | O15: 105.78212 | P15: 105.78212 | Q15: 105.78212 | R15: 106.62378 | S15: 108.13873 | T15: 108.13873 | U15: 108.28571 | V15: 108.57477 | W15: 108.57477 | X15: 108.57477 | Y15: 108.57477 | Z15: 108.57477 | AA15: 108.57477 | AB15: 108.57477 | AC15: 108.57477 | AD15: 108.57477 | AE15: 108.57477 | AF15: 108.57477 | AG15: 108.57477 | AH15: 108.57477 | AI15: 108.57477 | AJ15: 108.57477 | AK15: 108.57477 | AL15: 108.57477 | AM15: 108.57477 | AN15: 109.21856 | AO15: 109.9286 | AP15: 109.9286 | AQ15: 109.9286 | AR15: 109.9286 | AS15: 109.9286 | AT15: 109.9286 | AU15: 109.9 | AV15: 109.9286 | AW15: 109.9286 | AX15: 111.57008 | AY15: 113.57126 | AZ15: 113.57126 | BA15: 113.57126 | BB15: 113.57126 | BC15: 113.57126 | BD15: 114.30037 | BE15: 114.30037 | BF15: 114.30037 | BG15: 114.30037 | BH15: 114.30037 | BI15: 114.28777 | BJ15: 114.27289 | BK15: =BI33/AW33-1 -> 0.037637161 | BL15: Deflator PPI non-metallic mineral products - Average Jan Jul 2016/2015 | BM15: =PPI!CB16 -> -0.0057509585 | BN15: Manufacturing of non-metallic mineral products
A16: Recreation and culture | B16: 126.71275 | C16: 127.17772 | D16: 127.34061 | E16: 127.29378 | F16: 127.9607 | G16: 127.98062 | H16: 128.04178 | I16: 128.0247 | J16: 128.0506 | K16: 128.23771 | L16: 129.13146 | M16: 130.32959 | N16: 135.55869 | O16: 135.57663 | P16: 136.56888 | Q16: 136.66645 | R16: 137.749 | S16: 138.88534 | T16: 138.82512 | U16: 138.5286 | V16: 142.27922 | W16: 149.28806 | X16: 152.19148 | Y16: 153.46504 | Z16: 154.1653 | AA16: 154.14328 | AB16: 155.22338 | AC16: 154.52531 | AD16: 155.2189 | AE16: 155.5705 | AF16: 155.51424 | AG16: 155.89072 | AH16: 155.1344 | AI16: 155.47633 | AJ16: 154.44491 | AK16: 153.59942 | AL16: 154.04912 | AM16: 154.24436 | AN16: 153.45161 | AO16: 154.26176 | AP16: 154.20233 | AQ16: 154.22624 | AR16: 155.48751 | AS16: 155.13564 | AT16: 154.62238 | AU16: 152.7 | AV16: 153.79879 | AW16: 154.53701 | AX16: 155.69041 | AY16: 152.74176 | AZ16: 153.66752 | BA16: 152.10991 | BB16: 152.07741 | BC16: 152.24492 | BD16: 153.10094 | BE16: 153.95986 | BF16: 154.22998 | BG16: 155.39584 | BH16: 155.7107 | BI16: 159.90825 | BJ16: 159.90012 | BK16: =BI34/AW34-1 -> 6.5240597e-05 | BL16: Deflator PPI fabricated metal products, except machinery and equipment - Average Jan Jul 2016/2015 | BM16: =PPI!CB17 -> 0 | BN16: Manufacturing of metal products, machinery & equipment
A17: Education | B17: 109.53138 | C17: 109.63883 | D17: 121.26722 | E17: 121.34385 | F17: 121.34638 | G17: 121.34638 | H17: 121.34638 | I17: 121.34638 | J17: 121.34638 | K17: 130.59075 | L17: 130.59075 | M17: 130.59075 | N17: 130.59745 | O17: 130.59745 | P17: 130.59745 | Q17: 130.59745 | R17: 130.51888 | S17: 130.51888 | T17: 130.51888 | U17: 130.51888 | V17: 130.55243 | W17: 141.29962 | X17: 141.29962 | Y17: 141.29962 | Z17: 141.31253 | AA17: 141.31881 | AB17: 141.31881 | AC17: 141.31881 | AD17: 141.31881 | AE17: 141.31881 | AF17: 141.31881 | AG17: 141.31881 | AH17: 141.31881 | AI17: 143.46535 | AJ17: 143.46535 | AK17: 143.46535 | AL17: 143.46535 | AM17: 143.46535 | AN17: 143.46535 | AO17: 143.56419 | AP17: 143.56419 | AQ17: 143.56419 | AR17: 143.56419 | AS17: 143.56419 | AT17: 155.33551 | AU17: 155.3 | AV17: 155.33551 | AW17: 155.33551 | AX17: 155.49129 | AY17: 155.49129 | AZ17: 155.49129 | BA17: 155.49129 | BB17: 155.49129 | BC17: 155.49129 | BD17: 155.49129 | BE17: 155.49129 | BF17: 173.31887 | BG17: 173.31887 | BH17: 173.31887 | BI17: 173.31887 | BJ17: 173.31887 | BK17: =BI35/AW35-1 -> 0.094761223 | BL17: Deflator PPI Furniture - Average Jan Jul 2016/2015 | BM17: =PPI!CB18 -> 0.020581618 | BN17: Furniture & other manufacturing
A18: Restaurants and hotels | B18: 107.60198 | C18: 107.63245 | D18: 107.72667 | E18: 107.74421 | F18: 108.52968 | G18: 108.7972 | H18: 108.82369 | I18: 108.70707 | J18: 109.20934 | K18: 110.3739 | L18: 111.33959 | M18: 111.44296 | N18: 111.70473 | O18: 114.33591 | P18: 123.56837 | Q18: 123.87756 | R18: 123.99999 | S18: 124.37759 | T18: 127.57148 | U18: 128.76882 | V18: 129.70326 | W18: 130.91377 | X18: 130.31502 | Y18: 133.01533 | Z18: 134.42962 | AA18: 134.47575 | AB18: 136.13998 | AC18: 138.54108 | AD18: 138.28575 | AE18: 137.63767 | AF18: 138.48149 | AG18: 138.51407 | AH18: 138.65053 | AI18: 138.31878 | AJ18: 138.63717 | AK18: 139.4026 | AL18: 140.78129 | AM18: 141.02136 | AN18: 141.12858 | AO18: 141.59009 | AP18: 141.77082 | AQ18: 141.90204 | AR18: 142.16034 | AS18: 145.27461 | AT18: 146.02759 | AU18: 146.2 | AV18: 146.36332 | AW18: 148.9644 | AX18: 154.08777 | AY18: 157.32644 | AZ18: 160.99532 | BA18: 162.42644 | BB18: 165.24302 | BC18: 167.20166 | BD18: 170.78899 | BE18: 172.09032 | BF18: 171.92416 | BG18: 174.06077 | BH18: 174.73694 | BI18: 174.90243 | BJ18: 183.63672 | BK18: =BI36/AW36-1 -> 0.16399859 | BL18: Deflator PPI Electricity - Average Jan Jun 2015/2014 | BM18: =PPI!CB19 -> 0.145 | BN18: Electricity
A19: Miscellaneous goods and services | B19: 116.28344 | C19: 116.33892 | D19: 116.34112 | E19: 116.42635 | F19: 116.46853 | G19: 116.54593 | H19: 116.61686 | I19: 116.68954 | J19: 117.09643 | K19: 116.19373 | L19: 116.4347 | M19: 116.51702 | N19: 116.75351 | O19: 116.99622 | P19: 117.33759 | Q19: 118.20827 | R19: 121.03399 | S19: 124.45666 | T19: 125.50292 | U19: 125.70484 | V19: 126.32934 | W19: 126.89501 | X19: 126.09934 | Y19: 125.16232 | Z19: 125.43886 | AA19: 125.87945 | AB19: 125.90477 | AC19: 132.04047 | AD19: 132.1998 | AE19: 133.04402 | AF19: 133.57947 | AG19: 133.71136 | AH19: 134.13516 | AI19: 134.2422 | AJ19: 135.16606 | AK19: 135.64611 | AL19: 136.61906 | AM19: 137.09273 | AN19: 137.45693 | AO19: 138.05674 | AP19: 138.23424 | AQ19: 138.56738 | AR19: 139.261 | AS19: 139.49778 | AT19: 140.0685 | AU19: 141.4 | AV19: 141.72281 | AW19: 142.00883 | AX19: 142.83587 | AY19: 143.67434 | AZ19: 144.384 | BA19: 144.59695 | BB19: 144.93332 | BC19: 145.21052 | BD19: 146.13081 | BE19: 147.07946 | BF19: 147.52454 | BG19: 148.11733 | BH19: 148.92953 | BI19: 149.15083 | BJ19: 149.42655 | BK19: =BI37/AW37-1 -> 0.049450419 | BL19: Deflator PPI Water - Average Jan Jul 2016/2015 | BM19: =PPI!CB20 -> 0 | BN19: Water & waste management
Y20: =AVERAGE(N2:Y2) -> 146.77848 | AK20: =AVERAGE(Z2:AK2) -> 167.36944 | AW20: =AVERAGE(AL2:AW2) -> 175.34236 | BI20: =AVERAGE(AX2:BI2) -> 187.68085 | BL20: Deflator general PPI - Average Jan-Jul 2016/2015 | BM20: =PPI!CB21 -> 0.066916667 | BN20: Construction
Y21: =AVERAGE(N3:Y3) -> 177.13013 | AK21: =AVERAGE(Z3:AK3) -> 226.09681 | AW21: =AVERAGE(AL3:AW3) -> 231.64821 | BI21: =AVERAGE(AX3:BI3) -> 244.37591 | BN21: SERVICES
Y22: =AVERAGE(N4:Y4) -> 162.17505 | AK22: =AVERAGE(Z4:AK4) -> 186.9192 | AW22: =AVERAGE(AL4:AW4) -> 185.89573 | BI22: =AVERAGE(AX4:BI4) -> 196.69412 | BN22: Trade and Transport
Y23: =AVERAGE(N5:Y5) -> 178.13663 | AK23: =AVERAGE(Z5:AK5) -> 201.79974 | AW23: =AVERAGE(AL5:AW5) -> 235.08534 | BI23: =AVERAGE(AX5:BI5) -> 298.29958 | BL23: Deflator general CPI - Average Jan-Jul 2016/2015 | BM23: =BK2 -> 0.070368023 | BN23: Maintenance & repair of motor vehicles
Y24: =AVERAGE(N6:Y6) -> 143.78986 | AK24: =AVERAGE(Z6:AK6) -> 166.44494 | AW24: =AVERAGE(AL6:AW6) -> 198.53288 | BI24: =AVERAGE(AX6:BI6) -> 214.01464 | BL24: Deflator general CPI - Average Jan-Jul 2016/2015 | BM24: =BK2 -> 0.070368023 | BN24: Wholesale & retail trade
Y25: =AVERAGE(N7:Y7) -> 194.20787 | AK25: =AVERAGE(Z7:AK7) -> 291.16327 | AW25: =AVERAGE(AL7:AW7) -> 279.40809 | BI25: =AVERAGE(AX7:BI7) -> 273.10886 | BL25: Deflator CPI Transport - Average Jan Jul 2016/2015 | BM25: =BK14 -> 0.088875958 | BN25: Transport services
Y26: =AVERAGE(N8:Y8) -> 146.23323 | AK26: =AVERAGE(Z8:AK8) -> 177.5801 | AW26: =AVERAGE(AL8:AW8) -> 192.06761 | BI26: =AVERAGE(AX8:BI8) -> 204.00601 | BN26: Other services
Y27: =AVERAGE(N9:Y9) -> 192.23085 | AK27: =AVERAGE(Z9:AK9) -> 221.45516 | AW27: =AVERAGE(AL9:AW9) -> 228.04155 | BI27: =AVERAGE(AX9:BI9) -> 252.6816 | BL27: Deflator CPI Hotels and Restaurants - Average Jan Jul 2016/2015 | BM27: =BK18 -> 0.16399859 | BN27: Hotels & restaurants
Y28: =AVERAGE(N10:Y10) -> 140.69604 | AK28: =AVERAGE(Z10:AK10) -> 151.47981 | AW28: =AVERAGE(AL10:AW10) -> 160.05914 | BI28: =AVERAGE(AX10:BI10) -> 167.48194 | BL28: Deflator CPI Communication - Average Jan Jul 2016/2015 | BM28: =BK15 -> 0.037637161 | BN28: Information & communication
Y29: =AVERAGE(N11:Y11) -> 130.71184 | AK29: =AVERAGE(Z11:AK11) -> 135.49965 | AW29: =AVERAGE(AL11:AW11) -> 140.09914 | BI29: =AVERAGE(AX11:BI11) -> 146.1113 | BL29: Deflator general CPI - Average Jan-Jul 2016/2015 | BM29: =BK2 -> 0.070368023 | BN29: Financial services
Y30: =AVERAGE(N12:Y12) -> 138.93123 | AK30: =AVERAGE(Z12:AK12) -> 150.83558 | AW30: =AVERAGE(AL12:AW12) -> 157.11301 | BI30: =AVERAGE(AX12:BI12) -> 168.94463 | BL30: Deflator general CPI - Average Jan-Jul 2016/2015 | BM30: =BK2 -> 0.070368023 | BN30: Real estate activities
Y31: =AVERAGE(N13:Y13) -> 109.12484 | AK31: =AVERAGE(Z13:AK13) -> 109.69812 | AW31: =AVERAGE(AL13:AW13) -> 112.83203 | BI31: =AVERAGE(AX13:BI13) -> 153.66892 | BL31: Deflator general CPI - Average Jan-Jul 2016/2015 | BM31: =BK2 -> 0.070368023 | BN31: Professional, scientific and technical activities
Y32: =AVERAGE(N14:Y14) -> 143.4189 | AK32: =AVERAGE(Z14:AK14) -> 155.23523 | AW32: =AVERAGE(AL14:AW14) -> 182.36779 | BI32: =AVERAGE(AX14:BI14) -> 198.5759 | BL32: Deflator general CPI - Average Jan-Jul 2016/2015 | BM32: =BK2 -> 0.070368023 | BN32: Administrative and support service activities
Y33: =AVERAGE(N15:Y15) -> 107.38455 | AK33: =AVERAGE(Z15:AK15) -> 108.57477 | AW33: =AVERAGE(AL15:AW15) -> 109.64141 | BI33: =AVERAGE(AX15:BI15) -> 113.768 | BL33: Deflator Increase in govt unit wages cost - linked to annual - comes from Fiscal | BN33: Public administration and defence; compulsory social security
Y34: =AVERAGE(N16:Y16) -> 141.29854 | AK34: =AVERAGE(Z16:AK16) -> 154.90889 | AW34: =AVERAGE(AL16:AW16) -> 154.2264 | BI34: =AVERAGE(AX16:BI16) -> 154.23646 | BL34: Deflator Increase in govt unit wages cost - linked to annual - comes from Fiscal | BN34: Education
Y35: =AVERAGE(N17:Y17) -> 133.24305 | AK35: =AVERAGE(Z17:AK17) -> 141.85492 | AW35: =AVERAGE(AL17:AW17) -> 147.4603 | BI35: =AVERAGE(AX17:BI17) -> 161.43381 | BL35: Deflator Increase in govt unit wages cost - linked to annual - comes from Fiscal | BN35: Human health and social work activities
Y36: =AVERAGE(N18:Y18) -> 125.17932 | AK36: =AVERAGE(Z18:AK18) -> 137.62621 | AW36: =AVERAGE(AL18:AW18) -> 143.5987 | BI36: =AVERAGE(AX18:BI18) -> 167.14869 | BL36: Deflator general CPI - Average Jan-Jul 2016/2015 | BM36: =BK2 -> 0.070368023 | BN36: Cultural, domestic & other services
Y37: =AVERAGE(N19:Y19) -> 122.54 | AK37: =AVERAGE(Z19:AK19) -> 131.74898 | AW37: =AVERAGE(AL19:AW19) -> 139.1655 | BI37: =AVERAGE(AX19:BI19) -> 146.04729
BL38: Deflator - Deflator calculated in the annual (no link to avoid circularity) - considered as a target - exogenous | BN38: Taxes less subsidies on products
B40: 112.95569 | C40: 112.47517 | D40: 113.70262 | E40: 114.38173 | F40: 114.80019 | G40: 114.59573 | H40: 113.72815 | I40: 113.60798 | J40: 113.88428 | K40: 115.11995 | L40: 116.50878 | N40: 113.7073 | O40: 114.5357 | P40: 115.35701 | Q40: 116.80566 | R40: 118.03255 | S40: 116.99557 | T40: 115.84769 | U40: 116.32555 | V40: 116.51866 | W40: 115.8158 | X40: 115.21639 | Y40: 114.99841 | BE40: obald
B41: =B2-B40 -> 13.955762 | C41: =C2-C40 -> 14.901402 | D41: =D2-D40 -> 15.44747 | E41: =E2-E40 -> 14.976271 | F41: =F2-F40 -> 13.939818 | G41: =G2-G40 -> 13.880563 | H41: =H2-H40 -> 14.710079 | I41: =I2-I40 -> 15.156249 | ... L41: =L2-L40 -> 13.151876 | N41: =N2-N40 -> 18.6947 | O41: =O2-O40 -> 20.214751 | P41: =P2-P40 -> 23.52103 | Q41: =Q2-Q40 -> 25.397126 | R41: =R2-R40 -> 26.894131 | S41: =S2-S40 -> 29.035034 | T41: =T2-T40 -> 32.593462 | U41: =U2-U40 -> 32.874898 | ... Y41: =Y2-Y40 -> 42.764969
B42: 112.47517 | C42: 113.70262 | D42: 114.38173 | E42: 114.80019 | F42: 114.59573 | G42: 113.72815 | H42: 113.60798 | I42: 113.88428 | J42: 115.11995 | K42: 116.50878 | L42: 115.12689 | N42: 113.89613 | O42: 114.5357 | P42: 115.35701 | Q42: 116.80566 | R42: 118.03255 | S42: 116.99557 | T42: 115.84769 | U42: 116.32555 | V42: 116.51866 | W42: 115.8158 | X42: 115.21639 | Y42: 114.99841 | BE42: nisr
B43: =B42-B2 -> -14.436278 | C43: =C42-C2 -> -13.673956 | D43: =D42-D2 -> -14.768363 | E43: =E42-E2 -> -14.557809 | F43: =F42-F2 -> -14.144273 | G43: =G42-G2 -> -14.748147 | H43: =H42-H2 -> -14.830251 | I43: =I42-I2 -> -14.879949 | ... L43: =L42-L2 -> -14.533767 | N43: =N42-N2 -> -18.505872 | O43: =O42-O2 -> -20.214751 | P43: =P42-P2 -> -23.52103 | Q43: =Q42-Q2 -> -25.397126 | R43: =R42-R2 -> -26.894131 | S43: =S42-S2 -> -29.035034 | T43: =T42-T2 -> -32.593462 | U43: =U42-U2 -> -32.874898 | ... Y43: =Y42-Y2 -> -42.764969

Sheet PPI
BM1: 2025
B2: 44197 | C2: 44228 | D2: 44256 | E2: 44287 | F2: 44317 | G2: 44348 | H2: 44378 | I2: 44409 | J2: 44440 | K2: 44470 | L2: 44501 | M2: 44531 | N2: 44562 | O2: 44593 | P2: 44621 | Q2: 44652 | R2: 44682 | S2: 44713 | T2: 44743 | U2: 44774 | V2: 44805 | W2: 44835 | X2: 44866 | Y2: 44896 | Z2: 44927 | AA2: 44958 | AB2: 44986 | AC2: 45017 | AD2: 45047 | AE2: 45078 | AF2: 45108 | AG2: 45139 | AH2: 45170 | AI2: 45200 | AJ2: 45231 | AK2: 45261 | AL2: 45292 | AM2: 45323 | AN2: 45352 | AO2: 45383 | AP2: 45413 | AQ2: 45444 | AR2: 45474 | AS2: 45505 | AT2: 45536 | AU2: 45566 | AV2: 45597 | AW2: 45627 | AX2: 45658 | AY2: 45689 | AZ2: 45717 | BA2: 45748 | BB2: 45778 | BC2: 45809 | BD2: 45839 | BE2: 45870 | BF2: 45901 | BG2: 45931 | BH2: 45962 | BI2: 45992 | BJ2: 46023 | BL2: 2024 | BM2: Average tot | BN2: Growth
A3: Rwanda | B3: 71.9 | C3: 72.2 | D3: 72.8 | E3: 72.7 | F3: 73 | G3: 74.7 | H3: 75 | I3: 73.8 | J3: 74.4 | K3: 74.7 | L3: 75.1 | M3: 77.2 | N3: 77.7 | O3: 79.1 | P3: 82.3 | Q3: 83 | R3: 88.4 | S3: 85.6 | T3: 81 | U3: 82.8 | V3: 84.1 | W3: 85 | X3: 84.4 | Y3: 87.1 | Z3: 88.4 | AA3: 88.3 | AB3: 88.3 | AC3: 90.9 | AD3: 92.3 | AE3: 96.2 | AF3: 100.6 | AG3: 101.7 | AH3: 106.7 | AI3: 108.1 | AJ3: 105.6 | AK3: 104.8 | AL3: 105.2 | AM3: 100.6 | AN3: 100.2 | AO3: 100 | AP3: 98.7 | AQ3: 94.4 | AR3: 95.1 | AS3: 96.5 | AT3: 96.8 | AU3: 102 | AV3: 105.5 | AW3: 105 | AX3: 105.9 | AY3: 104.9 | AZ3: 104.3 | BA3: 102.4 | BB3: 105 | BC3: 105.6 | BD3: 107.5 | BE3: 107.1 | BF3: 109.8 | BG3: 108.9 | BH3: 109.1 | BI3: 109.8 | BL3: =AVERAGE(AL3:AW3) -> 100 | BM3: =AVERAGE(AX3:BI3) -> 106.69167 | BN3: =BM3/BL3-1 -> 0.066916667 | CA3: Deflator CPI food and non-alcoholic beverages - Average Jan Jul 2016/2015
A4: Mining and quarrying | B4: 77.3 | C4: 77.3 | D4: 77.4 | E4: 79.6 | F4: 79.7 | G4: 85.9 | H4: 86.2 | I4: 86.4 | J4: 87.5 | K4: 87.7 | L4: 88.9 | M4: 92.7 | N4: 92.7 | O4: 92.7 | P4: 93.5 | Q4: 97.1 | R4: 97 | S4: 96.9 | T4: 97 | U4: 97.1 | V4: 97.1 | W4: 97.2 | X4: 97.3 | Y4: 97.4 | Z4: 97.6 | AA4: 97.7 | AB4: 97.8 | AC4: 97.9 | AD4: 98.1 | AE4: 98.3 | AF4: 98.6 | AG4: 98.7 | AH4: 98.9 | AI4: 99.1 | AJ4: 99.2 | AK4: 99.4 | AL4: 99.6 | AM4: 99.6 | AN4: 99.7 | AO4: 99.8 | AP4: 99.8 | AQ4: 99.9 | AR4: 100 | AS4: 100.1 | AT4: 100.2 | AU4: 100.3 | AV4: 100.5 | AW4: 100.6 | AX4: 100.6 | AY4: 100.8 | AZ4: 100.8 | BA4: 100.9 | BB4: 100.9 | BC4: 101 | BD4: 101.1 | BE4: 101.1 | BF4: 101.2 | BG4: 101.2 | BH4: 106.1 | BI4: 121.1 | BL4: =AVERAGE(AL4:AW4) -> 100.00833 | BM4: =AVERAGE(AX4:BI4) -> 103.06667 | BN4: =BM4/BL4-1 -> 0.030580785 | CA4: Deflator general CPI - Average Jan-Jul 2016/2015
A5: Mining of metal ores | B5: 77.3 | C5: 77.3 | D5: 77.4 | E5: 79.6 | F5: 79.7 | G5: 85.9 | H5: 86.2 | I5: 86.4 | J5: 87.5 | K5: 87.7 | L5: 88.9 | M5: 92.7 | N5: 92.7 | O5: 92.7 | P5: 93.5 | Q5: 97.1 | R5: 97 | S5: 96.9 | T5: 97 | U5: 97.1 | V5: 97.1 | W5: 97.2 | X5: 97.3 | Y5: 97.4 | Z5: 97.6 | AA5: 97.7 | AB5: 97.8 | AC5: 97.9 | AD5: 98.1 | AE5: 98.3 | AF5: 98.6 | AG5: 98.7 | AH5: 98.9 | AI5: 99.1 | AJ5: 99.2 | AK5: 99.4 | AL5: 99.6 | AM5: 99.6 | AN5: 99.7 | AO5: 99.8 | AP5: 99.8 | AQ5: 99.9 | AR5: 100 | AS5: 100.1 | AT5: 100.2 | AU5: 100.3 | AV5: 100.5 | AW5: 100.6 | AX5: 100.6 | AY5: 100.8 | AZ5: 100.8 | BA5: 100.9 | BB5: 100.9 | BC5: 101 | BD5: 101.1 | BE5: 101.1 | BF5: 101.2 | BG5: 101.2 | BH5: 106.1 | BI5: 121.1 | BL5: =AVERAGE(AL5:AW5) -> 100.00833 | BM5: =AVERAGE(AX5:BI5) -> 103.06667 | BN5: =BM5/BL5-1 -> 0.030580785 | CA5: Deflator CPI meat - Average Jan Jul 2016/2015
A6: Mining of non-ferrous metal ores | B6: 118.53429 | C6: 118.62286 | D6: 118.68372 | E6: 122.10674 | F6: 122.30839 | G6: 131.8039 | H6: 132.18022 | I6: 132.49802 | J6: 134.26908 | K6: 134.51234 | L6: 136.41832 | M6: 142.11493 | N6: 142.16608 | O6: 142.21837 | P6: 143.481 | Q6: 148.99731 | R6: 148.76803 | S6: 148.68432 | T6: 148.74425 | U6: 148.97483 | V6: 148.95672 | W6: 149.08412 | X6: 149.22351 | Y6: 149.41082 | Z6: 149.63405 | AA6: 149.82248 | AB6: 149.96023 | AC6: 150.18756 | AD6: 150.41041 | AE6: 150.7875 | AF6: 151.19477 | AG6: 151.41687 | AH6: 151.66714 | AI6: 152.00245 | AJ6: 152.20091 | AK6: 152.48186 | AL6: 152.70899 | AM6: 152.81019 | AN6: 152.94138 | AO6: 153.03332 | AP6: 153.1253 | AQ6: 153.23756 | AR6: 153.42785 | AS6: 153.48813 | AT6: 153.61631 | AU6: 153.90045 | AV6: 154.09669 | AW6: 154.24213 | AX6: 154.37198 | AY6: 154.54115 | AZ6: 154.68591 | BA6: 154.74972 | BB6: 154.79015 | BC6: 154.89487 | BD6: 155.04016 | BL6: =AVERAGE(AL6:AW6) -> 153.38569 | BM6: =AVERAGE(AX6:BI6) -> 154.72485 | BN6: =BM6/BL6-1 -> 0.0087306531 | CA6: Deflator general CPI - Average Jan Jul 2016/2015
A7: Mining of other non-ferrous metal ores | B7: 118.53429 | C7: 118.62286 | D7: 118.68372 | E7: 122.10674 | F7: 122.30839 | G7: 131.8039 | H7: 132.18022 | I7: 132.49802 | J7: 134.26908 | K7: 134.51234 | L7: 136.41832 | M7: 142.11493 | N7: 142.16608 | O7: 142.21837 | P7: 143.481 | Q7: 148.99731 | R7: 148.76803 | S7: 148.68432 | T7: 148.74425 | U7: 148.97483 | V7: 148.95672 | W7: 149.08412 | X7: 149.22351 | Y7: 149.41082 | Z7: 149.63405 | AA7: 149.82248 | AB7: 149.96023 | AC7: 150.18756 | AD7: 150.41041 | AE7: 150.7875 | AF7: 151.19477 | AG7: 151.41687 | AH7: 151.66714 | AI7: 152.00245 | AJ7: 152.20091 | AK7: 152.48186 | AL7: 152.70899 | AM7: 152.81019 | AN7: 152.94138 | AO7: 153.03332 | AP7: 153.1253 | AQ7: 153.23756 | AR7: 153.42785 | AS7: 153.48813 | AT7: 153.61631 | AU7: 153.90045 | AV7: 154.09669 | AW7: 154.24213 | AX7: 154.37198 | AY7: 154.54115 | AZ7: 154.68591 | BA7: 154.74972 | BB7: 154.79015 | BC7: 154.89487 | BD7: 155.04016 | BL7: =AVERAGE(AL7:AW7) -> 153.38569 | BM7: =AVERAGE(AX7:BI7) -> 154.72485 | BN7: =BM7/BL7-1 -> 0.0087306531 | CA7: Deflator CPI fish - Average Jan Jul 2016/2015
A8: Manufacturing | B8: 63.6 | C8: 64 | D8: 64.8 | E8: 64.6 | F8: 64.9 | G8: 67.1 | H8: 67.4 | I8: 65.7 | J8: 66.5 | K8: 66.9 | L8: 67.5 | M8: 70.1 | N8: 70.9 | O8: 72.9 | P8: 77.4 | Q8: 78 | R8: 85.4 | S8: 81.6 | T8: 75.3 | U8: 77.8 | V8: 79.6 | W8: 80.8 | X8: 80 | Y8: 83.6 | Z8: 85.4 | AA8: 85.2 | AB8: 85.2 | AC8: 88.6 | AD8: 90.5 | AE8: 95.3 | AF8: 100.9 | AG8: 102.2 | AH8: 108.4 | AI8: 110 | AJ8: 107 | AK8: 106.1 | AL8: 106.5 | AM8: 100.8 | AN8: 100.2 | AO8: 100 | AP8: 98.5 | AQ8: 93 | AR8: 93.9 | AS8: 95.6 | AT8: 96 | AU8: 102.5 | AV8: 106.8 | AW8: 106.2 | AX8: 107.2 | AY8: 106 | AZ8: 105.3 | BA8: 102.9 | BB8: 106.1 | BC8: 106.8 | BD8: 109.1 | BE8: 106.6 | BF8: 110 | BG8: 108.8 | BH8: 108.8 | BI8: 108.6 | BL8: =AVERAGE(AL8:AW8) -> 100 | BM8: =AVERAGE(AX8:BI8) -> 107.18333 | BN8: =BM8/BL8-1 -> 0.071833333
A9: Manufacture of food products | B9: 60.3 | C9: 60.9 | D9: 62.1 | E9: 61.4 | F9: 61.8 | G9: 64.7 | H9: 65 | I9: 62.4 | J9: 63.5 | K9: 63.9 | L9: 64.8 | M9: 68.6 | N9: 69.7 | O9: 72.1 | P9: 77.6 | Q9: 78.1 | R9: 87.6 | S9: 82.5 | T9: 73.9 | U9: 75.7 | V9: 78.2 | W9: 79 | X9: 77.8 | Y9: 82.9 | Z9: 84.8 | AA9: 84.6 | AB9: 84.5 | AC9: 86.2 | AD9: 88.8 | AE9: 95.4 | AF9: 102.8 | AG9: 104.5 | AH9: 112.1 | AI9: 114.1 | AJ9: 110.3 | AK9: 109.1 | AL9: 109.6 | AM9: 101.7 | AN9: 100.9 | AO9: 100.5 | AP9: 98.3 | AQ9: 90.9 | AR9: 91.3 | AS9: 93.7 | AT9: 94.3 | AU9: 102.9 | AV9: 108.4 | AW9: 107.5 | AX9: 108.4 | AY9: 106.9 | AZ9: 105.9 | BA9: 102.7 | BB9: 106.8 | BC9: 107.8 | BD9: 110.7 | BE9: 105.9 | BF9: 110.5 | BG9: 109 | BH9: 109 | BI9: 105.6 | BL9: =AVERAGE(AL9:AW9) -> 100 | BM9: =AVERAGE(AX9:BI9) -> 107.43333 | BN9: =BM9/BL9-1 -> 0.074333333 | CA9: Deflator PPI Mining - Average Jan-Jul 2016/2015 | CB9: =BN4 -> 0.030580785
A10: Processing and preserving of meat | B10: 163.40075 | C10: 163.40075 | D10: 163.40075 | E10: 163.40075 | F10: 163.40075 | G10: 163.40075 | H10: 163.40075 | I10: 163.40075 | J10: 163.40075 | K10: 163.40075 | L10: 163.40075 | M10: 163.40075 | N10: 163.40075 | O10: 163.40075 | P10: 163.40075 | Q10: 163.40075 | R10: 163.40075 | S10: 163.40075 | T10: 163.40075 | U10: 163.40075 | V10: 163.40075 | W10: 163.40075 | X10: 163.40075 | Y10: 289.0992 | Z10: 289.0992 | AA10: 289.0992 | AB10: 289.0992 | AC10: 289.0992 | AD10: 289.0992 | AE10: 289.0992 | AF10: 343.18899 | AG10: 343.18899 | AH10: 343.18899 | AI10: 343.18899 | AJ10: 343.18899 | AK10: 343.18899 | AL10: 343.18899 | AM10: 343.18899 | AN10: 343.18899 | AO10: 343.18899 | AP10: 343.18899 | AQ10: 343.18899 | AR10: 343.18899 | AS10: 343.18899 | AT10: 343.18899 | AU10: 343.18899 | AV10: 343.18899 | AW10: 343.18899 | AX10: 343.18899 | AY10: 343.18899 | AZ10: 343.18899 | BA10: 343.18899 | BB10: 343.18899 | BC10: 343.18899 | BD10: 343.18899 | BL10: =AVERAGE(AL10:AW10) -> 343.18899 | BM10: =AVERAGE(AX10:BI10) -> 343.18899 | BN10: =BM10/BL10-1 -> 0
A11: Processing and preserving of meat | B11: 163.40075 | C11: 163.40075 | D11: 163.40075 | E11: 163.40075 | F11: 163.40075 | G11: 163.40075 | H11: 163.40075 | I11: 163.40075 | J11: 163.40075 | K11: 163.40075 | L11: 163.40075 | M11: 163.40075 | N11: 163.40075 | O11: 163.40075 | P11: 163.40075 | Q11: 163.40075 | R11: 163.40075 | S11: 163.40075 | T11: 163.40075 | U11: 163.40075 | V11: 163.40075 | W11: 163.40075 | X11: 163.40075 | Y11: 289.0992 | Z11: 289.0992 | AA11: 289.0992 | AB11: 289.0992 | AC11: 289.0992 | AD11: 289.0992 | AE11: 289.0992 | AF11: 343.18899 | AG11: 343.18899 | AH11: 343.18899 | AI11: 343.18899 | AJ11: 343.18899 | AK11: 343.18899 | AL11: 343.18899 | AM11: 343.18899 | AN11: 343.18899 | AO11: 343.18899 | AP11: 343.18899 | AQ11: 343.18899 | AR11: 343.18899 | AS11: 343.18899 | AT11: 343.18899 | AU11: 343.18899 | AV11: 343.18899 | AW11: 343.18899 | AX11: 343.18899 | AY11: 343.18899 | AZ11: 343.18899 | BA11: 343.18899 | BB11: 343.18899 | BC11: 343.18899 | BD11: 343.18899 | BL11: =AVERAGE(AL11:AW11) -> 343.18899 | BM11: =AVERAGE(AX11:BI11) -> 343.18899 | BN11: =BM11/BL11-1 -> 0 | CA11: Deflator PPI Manufacturing food - Average Jan Jul 2016/2015 | CB11: =BN9 -> 0.074333333
A12: Processing and preserving of fruit and vegetables | B12: 163.52202 | C12: 163.52202 | D12: 163.52202 | E12: 171.28688 | F12: 171.28688 | G12: 171.28688 | H12: 171.28688 | I12: 171.28688 | J12: 171.28688 | K12: 171.28688 | L12: 171.28688 | M12: 171.28688 | N12: 171.28688 | O12: 171.28688 | P12: 171.28688 | Q12: 175.96868 | R12: 175.96868 | S12: 175.96868 | T12: 175.96868 | U12: 175.96868 | V12: 175.96868 | W12: 175.96868 | X12: 175.96868 | Y12: 175.96868 | Z12: 175.96868 | AA12: 175.96868 | AB12: 175.96868 | AC12: 175.96868 | AD12: 175.96868 | AE12: 175.96868 | AF12: 175.96868 | AG12: 175.96868 | AH12: 175.96868 | AI12: 175.96868 | AJ12: 175.96868 | AK12: 175.96868 | AL12: 193.45672 | AM12: 193.45672 | AN12: 238.26633 | AO12: 238.26633 | AP12: 250.00427 | AQ12: 250.00427 | AR12: 261.75255 | AS12: 261.75255 | AT12: 261.75255 | AU12: 261.75255 | AV12: 261.75255 | AW12: 261.75255 | AX12: 261.75255 | AY12: 261.75255 | AZ12: 261.75255 | BA12: 261.75255 | BB12: 261.75255 | BC12: 261.75255 | BD12: 261.75255 | BL12: =AVERAGE(AL12:AW12) -> 244.4975 | BM12: =AVERAGE(AX12:BI12) -> 261.75255 | BN12: =BM12/BL12-1 -> 0.070573542 | CA12: Deflator PPI Beverages (tobacco neglected) - Average Jan Jul 2016/2015 | CB12: =BN24 -> 0.072422702
A13: Processing and preserving of fruit and vegetables | B13: 163.52202 | C13: 163.52202 | D13: 163.52202 | E13: 171.28688 | F13: 171.28688 | G13: 171.28688 | H13: 171.28688 | I13: 171.28688 | J13: 171.28688 | K13: 171.28688 | L13: 171.28688 | M13: 171.28688 | N13: 171.28688 | O13: 171.28688 | P13: 171.28688 | Q13: 175.96868 | R13: 175.96868 | S13: 175.96868 | T13: 175.96868 | U13: 175.96868 | V13: 175.96868 | W13: 175.96868 | X13: 175.96868 | Y13: 175.96868 | Z13: 175.96868 | AA13: 175.96868 | AB13: 175.96868 | AC13: 175.96868 | AD13: 175.96868 | AE13: 175.96868 | AF13: 175.96868 | AG13: 175.96868 | AH13: 175.96868 | AI13: 175.96868 | AJ13: 175.96868 | AK13: 175.96868 | AL13: 193.45672 | AM13: 193.45672 | AN13: 238.26633 | AO13: 238.26633 | AP13: 250.00427 | AQ13: 250.00427 | AR13: 261.75255 | AS13: 261.75255 | AT13: 261.75255 | AU13: 261.75255 | AV13: 261.75255 | AW13: 261.75255 | AX13: 261.75255 | AY13: 261.75255 | AZ13: 261.75255 | BA13: 261.75255 | BB13: 261.75255 | BC13: 261.75255 | BD13: 261.75255 | BL13: =AVERAGE(AL13:AW13) -> 244.4975 | BM13: =AVERAGE(AX13:BI13) -> 261.75255 | BN13: =BM13/BL13-1 -> 0.070573542 | CA13: Deflator PPI textiles - Average Jan Jul 2016/2015 | CB13: =BN32 -> 0
A14: Manufacture of dairy products | B14: 101.90809 | C14: 101.90809 | D14: 101.90809 | E14: 105.70085 | F14: 105.70085 | G14: 105.70085 | H14: 105.70085 | I14: 105.70085 | J14: 105.70085 | K14: 105.70085 | L14: 105.70085 | M14: 105.70085 | N14: 105.70085 | O14: 105.70085 | P14: 105.70085 | Q14: 105.70085 | R14: 105.70085 | S14: 105.70085 | T14: 105.70085 | U14: 115.5719 | V14: 115.5719 | W14: 115.5719 | X14: 115.5719 | Y14: 115.5719 | Z14: 115.5719 | AA14: 115.5719 | AB14: 115.5719 | AC14: 115.5719 | AD14: 115.5719 | AE14: 115.5719 | AF14: 115.5719 | AG14: 115.5719 | AH14: 115.5719 | AI14: 115.5719 | AJ14: 115.5719 | AK14: 115.5719 | AL14: 115.5719 | AM14: 115.5719 | AN14: 115.5719 | AO14: 115.5719 | AP14: 131.40544 | AQ14: 131.40544 | AR14: 131.40544 | AS14: 133.22202 | AT14: 133.22202 | AU14: 133.22202 | AV14: 133.22202 | AW14: 133.22202 | AX14: 133.22202 | AY14: 133.22202 | AZ14: 133.22202 | BA14: 133.22202 | BB14: 133.22202 | BC14: 133.22202 | BD14: 133.22202 | BL14: =AVERAGE(AL14:AW14) -> 126.8845 | BM14: =AVERAGE(AX14:BI14) -> 133.22202 | BN14: =BM14/BL14-1 -> 0.049947148 | CA14: Deflator PPI Paper (wood neglected) - Average Jan Jul 2016/2015 | CB14: =BN41 -> 0
A15: Manufacture of dairy products | B15: 101.90809 | C15: 101.90809 | D15: 101.90809 | E15: 105.70085 | F15: 105.70085 | G15: 105.70085 | H15: 105.70085 | I15: 105.70085 | J15: 105.70085 | K15: 105.70085 | L15: 105.70085 | M15: 105.70085 | N15: 105.70085 | O15: 105.70085 | P15: 105.70085 | Q15: 105.70085 | R15: 105.70085 | S15: 105.70085 | T15: 105.70085 | U15: 115.5719 | V15: 115.5719 | W15: 115.5719 | X15: 115.5719 | Y15: 115.5719 | Z15: 115.5719 | AA15: 115.5719 | AB15: 115.5719 | AC15: 115.5719 | AD15: 115.5719 | AE15: 115.5719 | AF15: 115.5719 | AG15: 115.5719 | AH15: 115.5719 | AI15: 115.5719 | AJ15: 115.5719 | AK15: 115.5719 | AL15: 115.5719 | AM15: 115.5719 | AN15: 115.5719 | AO15: 115.5719 | AP15: 131.40544 | AQ15: 131.40544 | AR15: 131.40544 | AS15: 133.22202 | AT15: 133.22202 | AU15: 133.22202 | AV15: 133.22202 | AW15: 133.22202 | AX15: 133.22202 | AY15: 133.22202 | AZ15: 133.22202 | BA15: 133.22202 | BB15: 133.22202 | BC15: 133.22202 | BD15: 133.22202 | BL15: =AVERAGE(AL15:AW15) -> 126.8845 | BM15: =AVERAGE(AX15:BI15) -> 133.22202 | BN15: =BM15/BL15-1 -> 0.049947148 | CA15: Deflator PPI Chemicals and chemical products - Average Jan Jul 2016/2015 | CB15: =BN47 -> 0.07
A16: Manufacture of grain mill products | B16: 111.3634 | C16: 111.36379 | D16: 111.36379 | E16: 111.36379 | F16: 111.31733 | G16: 111.23727 | H16: 111.2407 | I16: 111.23972 | J16: 111.24576 | K16: 111.39268 | L16: 111.39268 | M16: 111.48295 | N16: 111.48295 | O16: 111.48295 | P16: 111.51223 | Q16: 111.51966 | R16: 111.51966 | S16: 111.51966 | T16: 111.76286 | U16: 111.76286 | V16: 111.76783 | W16: 111.84254 | X16: 111.89513 | Y16: 111.89513 | Z16: 112.20178 | AA16: 112.11368 | AB16: 112.11368 | AC16: 112.24729 | AD16: 112.27816 | AE16: 112.27816 | AF16: 112.32478 | AG16: 112.32478 | AH16: 112.43487 | AI16: 112.43487 | AJ16: 112.3932 | AK16: 115.05524 | AL16: 114.75452 | AM16: 114.82859 | AN16: 116.79181 | AO16: 116.83824 | AP16: 118.98169 | AQ16: 119.02347 | AR16: 119.02347 | AS16: 118.97609 | AT16: 118.97609 | AU16: 118.72103 | AV16: 118.72103 | AW16: 118.72103 | AX16: 118.72103 | AY16: 118.72103 | AZ16: 118.72103 | BA16: 118.72103 | BB16: 118.72103 | BC16: 118.72103 | BD16: 118.72103 | BL16: =AVERAGE(AL16:AW16) -> 117.86309 | BM16: =AVERAGE(AX16:BI16) -> 118.72103 | BN16: =BM16/BL16-1 -> 0.0072791654 | CA16: Deflator PPI non-metallic mineral products - Average Jan Jul 2016/2015 | CB16: =BN60 -> -0.0057509585
A17: Manufacture of grain mill products | B17: 111.3634 | C17: 111.36379 | D17: 111.36379 | E17: 111.36379 | F17: 111.31733 | G17: 111.23727 | H17: 111.2407 | I17: 111.23972 | J17: 111.24576 | K17: 111.39268 | L17: 111.39268 | M17: 111.48295 | N17: 111.48295 | O17: 111.48295 | P17: 111.51223 | Q17: 111.51966 | R17: 111.51966 | S17: 111.51966 | T17: 111.76286 | U17: 111.76286 | V17: 111.76783 | W17: 111.84254 | X17: 111.89513 | Y17: 111.89513 | Z17: 112.20178 | AA17: 112.11368 | AB17: 112.11368 | AC17: 112.24729 | AD17: 112.27816 | AE17: 112.27816 | AF17: 112.32478 | AG17: 112.32478 | AH17: 112.43487 | AI17: 112.43487 | AJ17: 112.3932 | AK17: 115.05524 | AL17: 114.75452 | AM17: 114.82859 | AN17: 116.79181 | AO17: 116.83824 | AP17: 118.98169 | AQ17: 119.02347 | AR17: 119.02347 | AS17: 118.97609 | AT17: 118.97609 | AU17: 118.72103 | AV17: 118.72103 | AW17: 118.72103 | AX17: 118.72103 | AY17: 118.72103 | AZ17: 118.72103 | BA17: 118.72103 | BB17: 118.72103 | BC17: 118.72103 | BD17: 118.72103 | BL17: =AVERAGE(AL17:AW17) -> 117.86309 | BM17: =AVERAGE(AX17:BI17) -> 118.72103 | BN17: =BM17/BL17-1 -> 0.0072791654 | CA17: Deflator PPI fabricated metal products, except machinery and equipment - Average Jan Jul 2016/2015 | CB17: =BN63 -> 0
A18: Manufacture of other food products | B18: 144.16452 | C18: 145.81748 | D18: 149.27349 | E18: 147.20471 | F18: 148.22887 | G18: 156.19501 | H18: 157.01115 | I18: 149.97146 | J18: 152.94013 | K18: 154.12268 | L18: 156.50715 | M18: 166.73059 | N18: 169.69865 | O18: 176.20743 | P18: 190.6593 | Q18: 191.97653 | R18: 216.70113 | S18: 203.62074 | T18: 180.91745 | U18: 185.62589 | V18: 192.10447 | W18: 194.26116 | X18: 191.06011 | Y18: 193.33418 | Z18: 198.70683 | AA18: 198.08512 | AB18: 197.96895 | AC18: 202.53721 | AD18: 209.87563 | AE18: 228.13656 | AF18: 241.99857 | AG18: 246.72026 | AH18: 267.61754 | AI18: 272.93154 | AJ18: 262.76041 | AK18: 259.44236 | AL18: 260.83502 | AM18: 239.09846 | AN18: 236.55123 | AO18: 235.33914 | AP18: 229.1611 | AQ18: 207.63257 | AR18: 208.83058 | AS18: 215.90615 | AT18: 217.47029 | AU18: 242.00617 | AV18: 257.18205 | AW18: 254.92124 | AX18: 257.14206 | AY18: 253.04735 | AZ18: 250.51968 | BA18: 241.40789 | BB18: 252.94384 | BC18: 255.70257 | BD18: 263.4615 | BL18: =AVERAGE(AL18:AW18) -> 233.7445 | BM18: =AVERAGE(AX18:BI18) -> 253.4607 | BN18: =BM18/BL18-1 -> 0.084349357 | CA18: Deflator PPI Furniture - Average Jan Jul 2016/2015 | CB18: =BN69 -> 0.020581618
A19: Manufacture of bakery products | B19: 143.6196 | C19: 143.6196 | D19: 143.6196 | E19: 143.6196 | F19: 143.6196 | G19: 143.6196 | H19: 143.6196 | I19: 143.6196 | J19: 143.6196 | K19: 147.24659 | L19: 147.24659 | M19: 151.14079 | N19: 151.14079 | O19: 151.14079 | P19: 151.14079 | Q19: 166.17182 | R19: 166.17182 | S19: 166.17182 | T19: 176.71574 | U19: 176.71574 | V19: 176.71574 | W19: 176.71574 | X19: 176.71574 | Y19: 176.71574 | Z19: 176.71574 | AA19: 176.71574 | AB19: 176.71574 | AC19: 176.71574 | AD19: 176.71574 | AE19: 176.71574 | AF19: 176.71574 | AG19: 176.71574 | AH19: 176.71574 | AI19: 176.71574 | AJ19: 176.71574 | AK19: 176.71574 | AL19: 176.71574 | AM19: 176.71574 | AN19: 176.71574 | AO19: 176.71574 | AP19: 176.71574 | AQ19: 176.71574 | AR19: 176.71574 | AS19: 176.71574 | AT19: 176.71574 | AU19: 176.71574 | AV19: 176.71574 | AW19: 176.71574 | AX19: 176.71574 | AY19: 176.71574 | AZ19: 184.67639 | BA19: 184.67639 | BB19: 184.67639 | BC19: 184.67639 | BD19: 184.67639 | BL19: =AVERAGE(AL19:AW19) -> 176.71574 | BM19: =AVERAGE(AX19:BI19) -> 182.40192 | BN19: =BM19/BL19-1 -> 0.032177018 | CA19: Deflator PPI Electricity - Average Jan Jun 2015/2014 | CB19: =BN73 -> 0.145
A20: Manufacture of sugar | B20: 148.70231 | C20: 151.26559 | D20: 155.85643 | E20: 154.20594 | F20: 154.20594 | G20: 154.20594 | H20: 154.20594 | I20: 145.62157 | J20: 149.52465 | K20: 154.4025 | L20: 156.01508 | M20: 154.05953 | N20: 161.04136 | O20: 171.43488 | P20: 202.29853 | Q20: 207.38293 | R20: 248.70633 | S20: 225.35561 | T20: 186.64206 | U20: 179.4376 | V20: 184.59425 | W20: 189.90333 | X20: 183.57335 | Y20: 190.74311 | Z20: 200.18051 | AA20: 197.66537 | AB20: 198.49573 | AC20: 214.50519 | AD20: 216.12179 | AE20: 237.48646 | AF20: 260.4236 | AG20: 265.80288 | AH20: 295.00381 | AI20: 302.34265 | AJ20: 278.00554 | AK20: 272.31939 | AL20: 273.08356 | AM20: 241.30531 | AN20: 232.08412 | AO20: 238.74604 | AP20: 224.89871 | AQ20: 197.73757 | AR20: 198.56392 | AS20: 192.62706 | AT20: 180.59004 | AU20: 221.95034 | AV20: 244.09322 | AW20: 247.28271 | AX20: 250.51387 | AY20: 242.60901 | AZ20: 226.98865 | BA20: 239.98957 | BB20: 250.95271 | BC20: 246.73252 | BD20: 240.11392 | BL20: =AVERAGE(AL20:AW20) -> 224.41355 | BM20: =AVERAGE(AX20:BI20) -> 242.55718 | BN20: =BM20/BL20-1 -> 0.080849073 | CA20: Deflator PPI Water - Average Jan Jul 2016/2015 | CB20: =BN76 -> 0
A21: Manufacture of other food products n.e.c. (coffee and tea) | B21: 139.54809 | C21: 140.25753 | D21: 142.54429 | E21: 139.93232 | F21: 142.06409 | G21: 158.4003 | H21: 159.96953 | I21: 154.05665 | J21: 156.35604 | K21: 154.07077 | L21: 157.26156 | M21: 177.58957 | N21: 177.6567 | O21: 181.18004 | P21: 179.28421 | Q21: 175.52315 | R21: 175.21683 | S21: 178.76211 | T21: 175.28016 | U21: 191.42149 | V21: 199.1499 | W21: 198.72065 | X21: 198.06497 | Y21: 196.2195 | Z21: 197.93223 | AA21: 199.10164 | AB21: 198.0877 | AC21: 190.29367 | AD21: 204.49052 | AE21: 219.72759 | AF21: 222.90651 | AG21: 227.02815 | AH21: 237.4005 | AI21: 239.96907 | AJ21: 248.46061 | AK21: 247.91024 | AL21: 250.0547 | AM21: 238.48763 | AN21: 242.0376 | AO21: 233.48415 | AP21: 234.32867 | AQ21: 217.08188 | AR21: 218.59981 | AS21: 235.14503 | AT21: 244.34364 | AU21: 259.80692 | AV21: 270.10721 | AW21: 263.42006 | AX21: 264.82773 | AY21: 263.80157 | AZ21: 270.68675 | BA21: 244.12817 | BB21: 256.41779 | BC21: 265.23977 | BD21: 283.87375 | BL21: =AVERAGE(AL21:AW21) -> 242.24144 | BM21: =AVERAGE(AX21:BI21) -> 264.13936 | BN21: =BM21/BL21-1 -> 0.090397074 | CA21: Deflator general PPI - Average Jan-Jul 2016/2015 | CB21: =BN3 -> 0.066916667
A22: Manufacture of coffee products | B22: 120.97934 | C22: 121.28375 | D22: 121.49321 | E22: 121.49321 | F22: 112.32526 | G22: 161.67341 | H22: 168.01647 | I22: 154.39367 | J22: 134.84123 | K22: 135.73944 | L22: 135.74866 | M22: 168.68713 | N22: 168.93011 | O22: 169.17879 | P22: 169.17879 | Q22: 169.04401 | R22: 169.04401 | S22: 169.21619 | T22: 169.48921 | U22: 206.69528 | V22: 207.34824 | W22: 208.0571 | X22: 208.83475 | Y22: 209.88319 | Z22: 211.13783 | AA22: 212.20129 | AB22: 214.60294 | AC22: 215.90467 | AD22: 226.99943 | AE22: 250.34235 | AF22: 253.05255 | AG22: 254.53982 | AH22: 257.07861 | AI22: 258.4924 | AJ22: 273.12657 | AK22: 266.47655 | AL22: 268.06471 | AM22: 255.01587 | AN22: 252.02637 | AO22: 242.62129 | AP22: 243.20399 | AQ22: 238.72743 | AR22: 239.91311 | AS22: 260.06285 | AT22: 260.37408 | AU22: 282.40719 | AV22: 260.3823 | AW22: 259.04696 | AX22: 259.9187 | AY22: 266.74481 | AZ22: 280.64359 | BA22: 251.89175 | BB22: 279.20999 | BC22: 279.96481 | BD22: 298.21188 | BL22: =AVERAGE(AL22:AW22) -> 255.15384 | BM22: =AVERAGE(AX22:BI22) -> 273.79793 | BN22: =BM22/BL22-1 -> 0.073069983
A23: Manufacture of tea products | B23: 151.99022 | C23: 152.92512 | D23: 156.3175 | E23: 152.31371 | F23: 159.67496 | G23: 155.53624 | H23: 152.50658 | I23: 153.7718 | J23: 170.66573 | K23: 166.64076 | L23: 171.58879 | M23: 184.44357 | N23: 184.38705 | O23: 190.1678 | P23: 186.98115 | Q23: 180.6276 | R23: 180.09435 | S23: 186.07012 | T23: 179.87362 | U23: 176.35144 | V23: 191.68446 | W23: 190.11956 | X23: 187.99374 | Y23: 183.02964 | Z23: 185.26294 | AA23: 186.55842 | AB23: 181.66411 | AC23: 161.46484 | AD23: 180.68525 | AE23: 184.81875 | AF23: 188.91305 | AG23: 197.12254 | AH23: 217.85245 | AI23: 221.79594 | AJ23: 223.03275 | AK23: 229.78521 | AL23: 232.58053 | AM23: 222.54372 | AN23: 232.93993 | AO23: 225.19724 | AP23: 226.29917 | AQ23: 194.7451 | AR23: 196.71837 | AS23: 209.05023 | AT23: 229.00016 | AU23: 237.15106 | AV23: 277.78102 | AW23: 266.99186 | AX23: 268.82333 | AY23: 261.272 | AZ23: 261.69814 | BA23: 237.18752 | BB23: 233.47224 | BC23: 251.43765 | BD23: 270.57064 | BL23: =AVERAGE(AL23:AW23) -> 229.24987 | BM23: =AVERAGE(AX23:BI23) -> 254.92308 | BN23: =BM23/BL23-1 -> 0.11198789
A24: Manufacture of beverages | B24: 67.9 | C24: 67.9 | D24: 67.9 | E24: 67.9 | F24: 67.9 | G24: 67.9 | H24: 67.9 | I24: 67.9 | J24: 68.2 | K24: 68.2 | L24: 68.2 | M24: 68.2 | N24: 68.2 | O24: 68.2 | P24: 71.4 | Q24: 71.4 | R24: 71.4 | S24: 71.4 | T24: 71.4 | U24: 78.4 | V24: 78.4 | W24: 82.1 | X24: 82.1 | Y24: 82.1 | Z24: 82.1 | AA24: 82.5 | AB24: 82.5 | AC24: 95.1 | AD24: 95.1 | AE24: 95.1 | AF24: 95.1 | AG24: 95.1 | AH24: 95.1 | AI24: 95.1 | AJ24: 95.1 | AK24: 95.1 | AL24: 95.1 | AM24: 97.5 | AN24: 98.3 | AO24: 98.8 | AP24: 98.8 | AQ24: 98.8 | AR24: 102.1 | AS24: 102.1 | AT24: 102.1 | AU24: 102.1 | AV24: 102.1 | AW24: 102.1 | AX24: 104 | AY24: 104 | AZ24: 104 | BA24: 104 | BB24: 104 | BC24: 104 | BD24: 103.7 | BE24: 109.9 | BF24: 109.9 | BG24: 109.9 | BH24: 109.9 | BI24: 119.5 | BL24: =AVERAGE(AL24:AW24) -> 99.991667 | BM24: =AVERAGE(AX24:BI24) -> 107.23333 | BN24: =BM24/BL24-1 -> 0.072422702 | CA24: Deflator general CPI - Average Jan-Jul 2016/2015
A25: Manufacture of beverages | B25: 127.69045 | C25: 127.69045 | D25: 127.69045 | E25: 127.69045 | F25: 127.69045 | G25: 127.69045 | H25: 127.69045 | I25: 127.69045 | J25: 128.25437 | K25: 128.25437 | L25: 128.25437 | M25: 128.25437 | N25: 128.25437 | O25: 128.25467 | P25: 134.23146 | Q25: 134.23146 | R25: 134.23213 | S25: 134.23213 | T25: 134.23213 | U25: 147.37412 | V25: 147.37412 | W25: 154.41979 | X25: 154.41979 | Y25: 154.41979 | Z25: 154.41979 | AA25: 155.1811 | AB25: 155.1811 | AC25: 178.78215 | AD25: 178.78215 | AE25: 178.78215 | AF25: 178.78215 | AG25: 178.78215 | AH25: 178.78215 | AI25: 178.78215 | AJ25: 178.78215 | AK25: 178.78215 | AL25: 178.78215 | AM25: 183.37444 | AN25: 184.77971 | AO25: 185.80957 | AP25: 185.80957 | AQ25: 185.80957 | AR25: 192.05583 | AS25: 192.05583 | AT25: 192.05583 | AU25: 192.05583 | AV25: 192.05583 | AW25: 192.05583 | AX25: 195.49772 | AY25: 195.49772 | AZ25: 195.49772 | BA25: 195.49822 | BB25: 195.49822 | BC25: 195.49822 | BD25: 195.01001 | BL25: =AVERAGE(AL25:AW25) -> 188.05833 | BM25: =AVERAGE(AX25:BI25) -> 195.42826 | BN25: =BM25/BL25-1 -> 0.039189598 | CA25: Deflator general CPI - Average Jan-Jul 2016/2015
A26: Manufacture of wines | B26: 102.29808 | C26: 102.29808 | D26: 102.29808 | E26: 102.29808 | F26: 102.29808 | G26: 102.29808 | H26: 102.29808 | I26: 102.29808 | J26: 103.61682 | K26: 103.61682 | L26: 103.61682 | M26: 103.61682 | N26: 103.61682 | O26: 103.61682 | P26: 106.32933 | Q26: 106.32933 | R26: 106.32933 | S26: 106.32933 | T26: 106.32933 | U26: 126.37665 | V26: 126.37665 | W26: 128.06569 | X26: 128.06569 | Y26: 128.06569 | Z26: 128.06569 | AA26: 130.1279 | AB26: 130.1279 | AC26: 137.16487 | AD26: 137.16487 | AE26: 137.16487 | AF26: 137.16487 | AG26: 137.16487 | AH26: 137.16487 | AI26: 137.16487 | AJ26: 137.16487 | AK26: 137.16487 | AL26: 137.16487 | AM26: 141.40723 | AN26: 143.86045 | AO26: 146.49083 | AP26: 146.49083 | AQ26: 146.49083 | AR26: 149.12614 | AS26: 149.12614 | AT26: 149.12614 | AU26: 149.12614 | AV26: 149.12614 | AW26: 149.12614 | AX26: 155.99715 | AY26: 155.99715 | AZ26: 155.99715 | BA26: 155.99725 | BB26: 155.99725 | BC26: 155.99725 | BD26: 154.73466 | BL26: =AVERAGE(AL26:AW26) -> 146.38849 | BM26: =AVERAGE(AX26:BI26) -> 155.81684 | BN26: =BM26/BL26-1 -> 0.064406333 | CA26: Deflator CPI Transport - Average Jan Jul 2016/2015
A27: Manufacture of malt liquors and malt | B27: 127.6026 | C27: 127.6026 | D27: 127.6026 | E27: 127.6026 | F27: 127.6026 | G27: 127.6026 | H27: 127.6026 | I27: 127.6026 | J27: 128.17527 | K27: 128.17527 | L27: 128.17527 | M27: 128.17527 | N27: 128.17527 | O27: 128.17527 | P27: 134.31675 | Q27: 134.31675 | R27: 134.31675 | S27: 134.31675 | T27: 134.31675 | U27: 147.58308 | V27: 147.58308 | W27: 154.24335 | X27: 154.24335 | Y27: 154.24335 | Z27: 154.24335 | AA27: 155.00687 | AB27: 155.00687 | AC27: 178.99809 | AD27: 178.99809 | AE27: 178.99809 | AF27: 178.99809 | AG27: 178.99809 | AH27: 178.99809 | AI27: 178.99809 | AJ27: 178.99809 | AK27: 178.99809 | AL27: 178.99809 | AM27: 183.73466 | AN27: 185.16179 | AO27: 186.20176 | AP27: 186.20176 | AQ27: 186.20176 | AR27: 192.56238 | AS27: 192.56238 | AT27: 192.56238 | AU27: 192.56238 | AV27: 192.56238 | AW27: 192.56238 | AX27: 196.04558 | AY27: 196.04558 | AZ27: 196.04558 | BA27: 196.0461 | BB27: 196.0461 | BC27: 196.0461 | BD27: 195.55425 | BL27: =AVERAGE(AL27:AW27) -> 188.48951 | BM27: =AVERAGE(AX27:BI27) -> 195.97561 | BN27: =BM27/BL27-1 -> 0.039716289
A28: Manufacture of soft drinks; production of mineral waters and other bottled waters | B28: 142.36267 | C28: 142.36267 | D28: 142.36267 | E28: 142.36267 | F28: 142.36267 | G28: 142.36267 | H28: 142.36267 | I28: 142.36267 | J28: 142.36267 | K28: 142.36267 | L28: 142.36267 | M28: 142.36267 | N28: 142.36267 | O28: 142.37549 | P28: 142.37549 | Q28: 142.37549 | R28: 142.40644 | S28: 142.40644 | T28: 142.40644 | U28: 147.34857 | V28: 147.34857 | W28: 173.72296 | X28: 173.72296 | Y28: 173.72296 | Z28: 173.72296 | AA28: 174.00549 | AB28: 174.00549 | AC28: 186.25277 | AD28: 186.25277 | AE28: 186.25277 | AF28: 186.25277 | AG28: 186.25277 | AH28: 186.25277 | AI28: 186.25277 | AJ28: 186.25277 | AK28: 186.25277 | AL28: 186.25277 | AM28: 184.09294 | AN28: 184.09294 | AO28: 184.09294 | AP28: 184.09294 | AQ28: 184.09294 | AR28: 185.70753 | AS28: 185.70753 | AT28: 185.70753 | AU28: 185.70753 | AV28: 185.70753 | AW28: 185.70753 | AX28: 185.70753 | AY28: 185.70753 | AZ28: 185.70753 | BA28: 185.70753 | BB28: 185.70753 | BC28: 185.70753 | BD28: 185.70753 | BL28: =AVERAGE(AL28:AW28) -> 185.08022 | BM28: =AVERAGE(AX28:BI28) -> 185.70753 | BN28: =BM28/BL28-1 -> 0.0033893915 | CA28: Deflator CPI Hotels and Restaurants - Average Jan Jul 2016/2015
A29: Manufacture of tobacco products | B29: 100 | C29: 100 | D29: 100 | E29: 100 | F29: 100 | G29: 100 | H29: 100 | I29: 100 | J29: 100 | K29: 100 | L29: 100 | M29: 100 | N29: 100 | O29: 100 | P29: 100 | Q29: 100 | R29: 100 | S29: 100 | T29: 100 | U29: 100 | V29: 100 | W29: 100 | X29: 100 | Y29: 100 | Z29: 100 | AA29: 100 | AB29: 100 | AC29: 100 | AD29: 100 | AE29: 100 | AF29: 100 | AG29: 100 | AH29: 100 | AI29: 100 | AJ29: 100 | AK29: 100 | AL29: 100 | AM29: 100 | AN29: 100 | AO29: 100 | AP29: 100 | AQ29: 100 | AR29: 100 | AS29: 100 | AT29: 100 | AU29: 100 | AV29: 100 | AW29: 100 | AX29: 100 | AY29: 100 | AZ29: 100 | BA29: 100 | BB29: 100 | BC29: 100 | BD29: 100 | BL29: =AVERAGE(AL29:AW29) -> 100 | BM29: =AVERAGE(AX29:BI29) -> 100 | BN29: =BM29/BL29-1 -> 0 | CA29: Deflator CPI Communication - Average Jan Jul 2016/2015
A30: Manufacture of tobacco products | B30: 100 | C30: 100 | D30: 100 | E30: 100 | F30: 100 | G30: 100 | H30: 100 | I30: 100 | J30: 100 | K30: 100 | L30: 100 | M30: 100 | N30: 100 | O30: 100 | P30: 100 | Q30: 100 | R30: 100 | S30: 100 | T30: 100 | U30: 100 | V30: 100 | W30: 100 | X30: 100 | Y30: 100 | Z30: 100 | AA30: 100 | AB30: 100 | AC30: 100 | AD30: 100 | AE30: 100 | AF30: 100 | AG30: 100 | AH30: 100 | AI30: 100 | AJ30: 100 | AK30: 100 | AL30: 100 | AM30: 100 | AN30: 100 | AO30: 100 | AP30: 100 | AQ30: 100 | AR30: 100 | AS30: 100 | AT30: 100 | AU30: 100 | AV30: 100 | AW30: 100 | AX30: 100 | AY30: 100 | AZ30: 100 | BA30: 100 | BB30: 100 | BC30: 100 | BD30: 100 | BL30: =AVERAGE(AL30:AW30) -> 100 | BM30: =AVERAGE(AX30:BI30) -> 100 | BN30: =BM30/BL30-1 -> 0 | CA30: Deflator general CPI - Average Jan-Jul 2016/2015
A31: Manufacture of tobacco products | B31: 100 | C31: 100 | D31: 100 | E31: 100 | F31: 100 | G31: 100 | H31: 100 | I31: 100 | J31: 100 | K31: 100 | L31: 100 | M31: 100 | N31: 100 | O31: 100 | P31: 100 | Q31: 100 | R31: 100 | S31: 100 | T31: 100 | U31: 100 | V31: 100 | W31: 100 | X31: 100 | Y31: 100 | Z31: 100 | AA31: 100 | AB31: 100 | AC31: 100 | AD31: 100 | AE31: 100 | AF31: 100 | AG31: 100 | AH31: 100 | AI31: 100 | AJ31: 100 | AK31: 100 | AL31: 100 | AM31: 100 | AN31: 100 | AO31: 100 | AP31: 100 | AQ31: 100 | AR31: 100 | AS31: 100 | AT31: 100 | AU31: 100 | AV31: 100 | AW31: 100 | AX31: 100 | AY31: 100 | AZ31: 100 | BA31: 100 | BB31: 100 | BC31: 100 | BD31: 100 | BL31: =AVERAGE(AL31:AW31) -> 100 | BM31: =AVERAGE(AX31:BI31) -> 100 | BN31: =BM31/BL31-1 -> 0 | CA31: Deflator general CPI - Average Jan-Jul 2016/2015
A32: Manufacture of textiles | B32: 92.797755 | C32: 92.797755 | D32: 92.797755 | E32: 92.797755 | F32: 92.797755 | G32: 92.797755 | H32: 92.797755 | I32: 92.797755 | J32: 92.797755 | K32: 92.797755 | L32: 92.797755 | M32: 95.704143 | N32: 95.704143 | O32: 95.704143 | P32: 95.704143 | Q32: 95.704143 | R32: 95.704143 | S32: 95.704143 | T32: 95.704143 | U32: 95.704143 | V32: 95.704143 | W32: 95.673132 | X32: 95.673132 | Y32: 95.673132 | Z32: 95.673132 | AA32: 95.673132 | AB32: 95.673132 | AC32: 95.673132 | AD32: 95.673132 | AE32: 95.673132 | AF32: 95.673132 | AG32: 95.673132 | AH32: 95.673132 | AI32: 95.673132 | AJ32: 95.673132 | AK32: 95.673132 | AL32: 95.673132 | AM32: 95.673132 | AN32: 95.673132 | AO32: 95.673132 | AP32: 95.673132 | AQ32: 95.673132 | AR32: 95.673132 | AS32: 95.673132 | AT32: 95.673132 | AU32: 95.673132 | AV32: 95.673132 | AW32: 95.673132 | AX32: 95.673132 | AY32: 95.673132 | AZ32: 95.673132 | BA32: 95.673132 | BB32: 95.673132 | BC32: 95.673132 | BD32: 95.673132 | BL32: =AVERAGE(AL32:AW32) -> 95.673132 | BM32: =AVERAGE(AX32:BI32) -> 95.673132 | BN32: =BM32/BL32-1 -> 0 | CA32: Deflator general CPI - Average Jan-Jul 2016/2015
A33: Manufacture of other textiles | B33: 92.797755 | C33: 92.797755 | D33: 92.797755 | E33: 92.797755 | F33: 92.797755 | G33: 92.797755 | H33: 92.797755 | I33: 92.797755 | J33: 92.797755 | K33: 92.797755 | L33: 92.797755 | M33: 95.704143 | N33: 95.704143 | O33: 95.704143 | P33: 95.704143 | Q33: 95.704143 | R33: 95.704143 | S33: 95.704143 | T33: 95.704143 | U33: 95.704143 | V33: 95.704143 | W33: 95.673132 | X33: 95.673132 | Y33: 95.673132 | Z33: 95.673132 | AA33: 95.673132 | AB33: 95.673132 | AC33: 95.673132 | AD33: 95.673132 | AE33: 95.673132 | AF33: 95.673132 | AG33: 95.673132 | AH33: 95.673132 | AI33: 95.673132 | AJ33: 95.673132 | AK33: 95.673132 | AL33: 95.673132 | AM33: 95.673132 | AN33: 95.673132 | AO33: 95.673132 | AP33: 95.673132 | AQ33: 95.673132 | AR33: 95.673132 | AS33: 95.673132 | AT33: 95.673132 | AU33: 95.673132 | AV33: 95.673132 | AW33: 95.673132 | AX33: 95.673132 | AY33: 95.673132 | AZ33: 95.673132 | BA33: 95.673132 | BB33: 95.673132 | BC33: 95.673132 | BD33: 95.673132 | BL33: =AVERAGE(AL33:AW33) -> 95.673132 | BM33: =AVERAGE(AX33:BI33) -> 95.673132 | BN33: =BM33/BL33-1 -> 0 | CA33: Deflator general CPI - Average Jan-Jul 2016/2015
A34: Manufacture of made-up textile articles, except apparel | B34: 92.797755 | C34: 92.797755 | D34: 92.797755 | E34: 92.797755 | F34: 92.797755 | G34: 92.797755 | H34: 92.797755 | I34: 92.797755 | J34: 92.797755 | K34: 92.797755 | L34: 92.797755 | M34: 95.704143 | N34: 95.704143 | O34: 95.704143 | P34: 95.704143 | Q34: 95.704143 | R34: 95.704143 | S34: 95.704143 | T34: 95.704143 | U34: 95.704143 | V34: 95.704143 | W34: 95.673132 | X34: 95.673132 | Y34: 95.673132 | Z34: 95.673132 | AA34: 95.673132 | AB34: 95.673132 | AC34: 95.673132 | AD34: 95.673132 | AE34: 95.673132 | AF34: 95.673132 | AG34: 95.673132 | AH34: 95.673132 | AI34: 95.673132 | AJ34: 95.673132 | AK34: 95.673132 | AL34: 95.673132 | AM34: 95.673132 | AN34: 95.673132 | AO34: 95.673132 | AP34: 95.673132 | AQ34: 95.673132 | AR34: 95.673132 | AS34: 95.673132 | AT34: 95.673132 | AU34: 95.673132 | AV34: 95.673132 | AW34: 95.673132 | AX34: 95.673132 | AY34: 95.673132 | AZ34: 95.673132 | BA34: 95.673132 | BB34: 95.673132 | BC34: 95.673132 | BD34: 95.673132 | BL34: =AVERAGE(AL34:AW34) -> 95.673132 | BM34: =AVERAGE(AX34:BI34) -> 95.673132 | BN34: =BM34/BL34-1 -> 0 | CA34: Deflator Increase in govt unit wages cost - linked to annual - comes from Fiscal
A35: Manufacture of leather and related products | B35: 97.310635 | C35: 97.310635 | D35: 97.310635 | E35: 97.310635 | F35: 97.310635 | G35: 97.310635 | H35: 97.310635 | I35: 97.310635 | J35: 97.310635 | K35: 97.310635 | L35: 97.310635 | M35: 99.84386 | N35: 99.84386 | O35: 99.84386 | P35: 99.84386 | Q35: 99.84386 | R35: 99.84386 | S35: 99.84386 | T35: 99.84386 | U35: 99.84386 | V35: 99.84386 | W35: 99.816898 | X35: 99.816898 | Y35: 99.816898 | Z35: 99.816898 | AA35: 99.816898 | AB35: 99.816898 | AC35: 99.816898 | AD35: 99.816898 | AE35: 99.816898 | AF35: 99.816898 | AG35: 99.816898 | AH35: 99.816898 | AI35: 99.816898 | AJ35: 99.816898 | AK35: 99.816898 | AL35: 99.816898 | AM35: 99.816898 | AN35: 99.816898 | AO35: 99.816898 | AP35: 99.816898 | AQ35: 99.816898 | AR35: 99.816898 | AS35: 99.816898 | AT35: 99.816898 | AU35: 99.816898 | AV35: 99.816898 | AW35: 99.816898 | AX35: 99.816898 | AY35: 99.816898 | AZ35: 99.816898 | BA35: 99.816898 | BB35: 99.816898 | BC35: 99.816898 | BD35: 99.816898 | BL35: =AVERAGE(AL35:AW35) -> 99.816898 | BM35: =AVERAGE(AX35:BI35) -> 99.816898 | BN35: =BM35/BL35-1 -> 0 | CA35: Deflator Increase in govt unit wages cost - linked to annual - comes from Fiscal
A36: Manufacture of footwear | B36: 97.310635 | C36: 97.310635 | D36: 97.310635 | E36: 97.310635 | F36: 97.310635 | G36: 97.310635 | H36: 97.310635 | I36: 97.310635 | J36: 97.310635 | K36: 97.310635 | L36: 97.310635 | M36: 99.84386 | N36: 99.84386 | O36: 99.84386 | P36: 99.84386 | Q36: 99.84386 | R36: 99.84386 | S36: 99.84386 | T36: 99.84386 | U36: 99.84386 | V36: 99.84386 | W36: 99.816898 | X36: 99.816898 | Y36: 99.816898 | Z36: 99.816898 | AA36: 99.816898 | AB36: 99.816898 | AC36: 99.816898 | AD36: 99.816898 | AE36: 99.816898 | AF36: 99.816898 | AG36: 99.816898 | AH36: 99.816898 | AI36: 99.816898 | AJ36: 99.816898 | AK36: 99.816898 | AL36: 99.816898 | AM36: 99.816898 | AN36: 99.816898 | AO36: 99.816898 | AP36: 99.816898 | AQ36: 99.816898 | AR36: 99.816898 | AS36: 99.816898 | AT36: 99.816898 | AU36: 99.816898 | AV36: 99.816898 | AW36: 99.816898 | AX36: 99.816898 | AY36: 99.816898 | AZ36: 99.816898 | BA36: 99.816898 | BB36: 99.816898 | BC36: 99.816898 | BD36: 99.816898 | BL36: =AVERAGE(AL36:AW36) -> 99.816898 | BM36: =AVERAGE(AX36:BI36) -> 99.816898 | BN36: =BM36/BL36-1 -> 0 | CA36: Deflator Increase in govt unit wages cost - linked to annual - comes from Fiscal
A37: Manufacture of footwear | B37: 97.310635 | C37: 97.310635 | D37: 97.310635 | E37: 97.310635 | F37: 97.310635 | G37: 97.310635 | H37: 97.310635 | I37: 97.310635 | J37: 97.310635 | K37: 97.310635 | L37: 97.310635 | M37: 99.84386 | N37: 99.84386 | O37: 99.84386 | P37: 99.84386 | Q37: 99.84386 | R37: 99.84386 | S37: 99.84386 | T37: 99.84386 | U37: 99.84386 | V37: 99.84386 | W37: 99.816898 | X37: 99.816898 | Y37: 99.816898 | Z37: 99.816898 | AA37: 99.816898 | AB37: 99.816898 | AC37: 99.816898 | AD37: 99.816898 | AE37: 99.816898 | AF37: 99.816898 | AG37: 99.816898 | AH37: 99.816898 | AI37: 99.816898 | AJ37: 99.816898 | AK37: 99.816898 | AL37: 99.816898 | AM37: 99.816898 | AN37: 99.816898 | AO37: 99.816898 | AP37: 99.816898 | AQ37: 99.816898 | AR37: 99.816898 | AS37: 99.816898 | AT37: 99.816898 | AU37: 99.816898 | AV37: 99.816898 | AW37: 99.816898 | AX37: 99.816898 | AY37: 99.816898 | AZ37: 99.816898 | BA37: 99.816898 | BB37: 99.816898 | BC37: 99.816898 | BD37: 99.816898 | BL37: =AVERAGE(AL37:AW37) -> 99.816898 | BM37: =AVERAGE(AX37:BI37) -> 99.816898 | BN37: =BM37/BL37-1 -> 0 | CA37: Deflator general CPI - Average Jan-Jul 2016/2015
A38: Manufacture of wood and of products of wood and cork, except furniture; manufacture of articles of straw and plaiting materials | B38: 112.54704 | C38: 112.54704 | D38: 112.54704 | E38: 112.54704 | F38: 112.54704 | G38: 112.54704 | H38: 112.54704 | I38: 112.54704 | J38: 112.54704 | K38: 112.54704 | L38: 112.54704 | M38: 112.54704 | N38: 112.54704 | O38: 112.54704 | P38: 112.54704 | Q38: 112.54704 | R38: 112.54704 | S38: 112.54704 | T38: 112.54704 | U38: 112.54704 | V38: 112.54704 | W38: 112.54704 | X38: 112.54704 | Y38: 112.54704 | Z38: 112.54704 | AA38: 125.93808 | AB38: 125.93808 | AC38: 125.93808 | AD38: 125.93808 | AE38: 125.93808 | AF38: 125.93808 | AG38: 125.93808 | AH38: 125.93808 | AI38: 125.93808 | AJ38: 125.93808 | AK38: 125.93808 | AL38: 125.93808 | AM38: 125.93808 | AN38: 125.93808 | AO38: 125.93808 | AP38: 125.93808 | AQ38: 125.93808 | AR38: 125.93808 | AS38: 125.93808 | AT38: 125.93808 | AU38: 125.93808 | AV38: 125.93808 | AW38: 125.93808 | AX38: 125.93808 | AY38: 125.93808 | AZ38: 125.93808 | BA38: 125.93808 | BB38: 125.93808 | BC38: 125.93808 | BD38: 125.93808 | BL38: =AVERAGE(AL38:AW38) -> 125.93808 | BM38: =AVERAGE(AX38:BI38) -> 125.93808 | BN38: =BM38/BL38-1 -> 0
A39: Manufacture of other products of wood; manufacture of articles of cork, straw and plaiting materials | B39: 112.54704 | C39: 112.54704 | D39: 112.54704 | E39: 112.54704 | F39: 112.54704 | G39: 112.54704 | H39: 112.54704 | I39: 112.54704 | J39: 112.54704 | K39: 112.54704 | L39: 112.54704 | M39: 112.54704 | N39: 112.54704 | O39: 112.54704 | P39: 112.54704 | Q39: 112.54704 | R39: 112.54704 | S39: 112.54704 | T39: 112.54704 | U39: 112.54704 | V39: 112.54704 | W39: 112.54704 | X39: 112.54704 | Y39: 112.54704 | Z39: 112.54704 | AA39: 125.93808 | AB39: 125.93808 | AC39: 125.93808 | AD39: 125.93808 | AE39: 125.93808 | AF39: 125.93808 | AG39: 125.93808 | AH39: 125.93808 | AI39: 125.93808 | AJ39: 125.93808 | AK39: 125.93808 | AL39: 125.93808 | AM39: 125.93808 | AN39: 125.93808 | AO39: 125.93808 | AP39: 125.93808 | AQ39: 125.93808 | AR39: 125.93808 | AS39: 125.93808 | AT39: 125.93808 | AU39: 125.93808 | AV39: 125.93808 | AW39: 125.93808 | AX39: 125.93808 | AY39: 125.93808 | AZ39: 125.93808 | BA39: 125.93808 | BB39: 125.93808 | BC39: 125.93808 | BD39: 125.93808 | BL39: =AVERAGE(AL39:AW39) -> 125.93808 | BM39: =AVERAGE(AX39:BI39) -> 125.93808 | BN39: =BM39/BL39-1 -> 0 | CA39: Deflator - Deflator calculated in the annual (no link to avoid circularity) - considered as a target - exogenous
A40: Manufacture of other products of wood; manufacture of articles of cork, straw and plaiting materials | B40: 112.54704 | C40: 112.54704 | D40: 112.54704 | E40: 112.54704 | F40: 112.54704 | G40: 112.54704 | H40: 112.54704 | I40: 112.54704 | J40: 112.54704 | K40: 112.54704 | L40: 112.54704 | M40: 112.54704 | N40: 112.54704 | O40: 112.54704 | P40: 112.54704 | Q40: 112.54704 | R40: 112.54704 | S40: 112.54704 | T40: 112.54704 | U40: 112.54704 | V40: 112.54704 | W40: 112.54704 | X40: 112.54704 | Y40: 112.54704 | Z40: 112.54704 | AA40: 125.93808 | AB40: 125.93808 | AC40: 125.93808 | AD40: 125.93808 | AE40: 125.93808 | AF40: 125.93808 | AG40: 125.93808 | AH40: 125.93808 | AI40: 125.93808 | AJ40: 125.93808 | AK40: 125.93808 | AL40: 125.93808 | AM40: 125.93808 | AN40: 125.93808 | AO40: 125.93808 | AP40: 125.93808 | AQ40: 125.93808 | AR40: 125.93808 | AS40: 125.93808 | AT40: 125.93808 | AU40: 125.93808 | AV40: 125.93808 | AW40: 125.93808 | AX40: 125.93808 | AY40: 125.93808 | AZ40: 125.93808 | BA40: 125.93808 | BB40: 125.93808 | BC40: 125.93808 | BD40: 125.93808 | BL40: =AVERAGE(AL40:AW40) -> 125.93808 | BM40: =AVERAGE(AX40:BI40) -> 125.93808 | BN40: =BM40/BL40-1 -> 0
A41: Manufacture of paper and paper products | B41: 136.09054 | C41: 136.09054 | D41: 136.09054 | E41: 136.09054 | F41: 136.09054 | G41: 136.09054 | H41: 136.09054 | I41: 136.09054 | J41: 136.09054 | K41: 136.09054 | L41: 136.09054 | M41: 136.09054 | N41: 136.09054 | O41: 136.09054 | P41: 136.09054 | Q41: 136.09054 | R41: 136.09054 | S41: 136.09054 | T41: 136.09054 | U41: 136.09054 | V41: 136.09054 | W41: 136.09054 | X41: 136.09054 | Y41: 136.09054 | Z41: 136.09054 | AA41: 136.09054 | AB41: 136.09054 | AC41: 136.09054 | AD41: 136.09054 | AE41: 136.09054 | AF41: 136.09054 | AG41: 136.09054 | AH41: 136.09054 | AI41: 136.09054 | AJ41: 136.09054 | AK41: 136.09054 | AL41: 136.09054 | AM41: 136.09054 | AN41: 136.09054 | AO41: 136.09054 | AP41: 136.09054 | AQ41: 136.09054 | AR41: 136.09054 | AS41: 136.09054 | AT41: 136.09054 | AU41: 136.09054 | AV41: 136.09054 | AW41: 136.09054 | AX41: 136.09054 | AY41: 136.09054 | AZ41: 136.09054 | BA41: 136.09054 | BB41: 136.09054 | BC41: 136.09054 | BD41: 136.09054 | BL41: =AVERAGE(AL41:AW41) -> 136.09054 | BM41: =AVERAGE(AX41:BI41) -> 136.09054 | BN41: =BM41/BL41-1 -> 0
A42: Manufacture of paper and paper products | B42: 136.09054 | C42: 136.09054 | D42: 136.09054 | E42: 136.09054 | F42: 136.09054 | G42: 136.09054 | H42: 136.09054 | I42: 136.09054 | J42: 136.09054 | K42: 136.09054 | L42: 136.09054 | M42: 136.09054 | N42: 136.09054 | O42: 136.09054 | P42: 136.09054 | Q42: 136.09054 | R42: 136.09054 | S42: 136.09054 | T42: 136.09054 | U42: 136.09054 | V42: 136.09054 | W42: 136.09054 | X42: 136.09054 | Y42: 136.09054 | Z42: 136.09054 | AA42: 136.09054 | AB42: 136.09054 | AC42: 136.09054 | AD42: 136.09054 | AE42: 136.09054 | AF42: 136.09054 | AG42: 136.09054 | AH42: 136.09054 | AI42: 136.09054 | AJ42: 136.09054 | AK42: 136.09054 | AL42: 136.09054 | AM42: 136.09054 | AN42: 136.09054 | AO42: 136.09054 | AP42: 136.09054 | AQ42: 136.09054 | AR42: 136.09054 | AS42: 136.09054 | AT42: 136.09054 | AU42: 136.09054 | AV42: 136.09054 | AW42: 136.09054 | AX42: 136.09054 | AY42: 136.09054 | AZ42: 136.09054 | BA42: 136.09054 | BB42: 136.09054 | BC42: 136.09054 | BD42: 136.09054 | BL42: =AVERAGE(AL42:AW42) -> 136.09054 | BM42: =AVERAGE(AX42:BI42) -> 136.09054 | BN42: =BM42/BL42-1 -> 0
A43: Manufacture of other articles of paper and paperboard | B43: 136.09054 | C43: 136.09054 | D43: 136.09054 | E43: 136.09054 | F43: 136.09054 | G43: 136.09054 | H43: 136.09054 | I43: 136.09054 | J43: 136.09054 | K43: 136.09054 | L43: 136.09054 | M43: 136.09054 | N43: 136.09054 | O43: 136.09054 | P43: 136.09054 | Q43: 136.09054 | R43: 136.09054 | S43: 136.09054 | T43: 136.09054 | U43: 136.09054 | V43: 136.09054 | W43: 136.09054 | X43: 136.09054 | Y43: 136.09054 | Z43: 136.09054 | AA43: 136.09054 | AB43: 136.09054 | AC43: 136.09054 | AD43: 136.09054 | AE43: 136.09054 | AF43: 136.09054 | AG43: 136.09054 | AH43: 136.09054 | AI43: 136.09054 | AJ43: 136.09054 | AK43: 136.09054 | AL43: 136.09054 | AM43: 136.09054 | AN43: 136.09054 | AO43: 136.09054 | AP43: 136.09054 | AQ43: 136.09054 | AR43: 136.09054 | AS43: 136.09054 | AT43: 136.09054 | AU43: 136.09054 | AV43: 136.09054 | AW43: 136.09054 | AX43: 136.09054 | AY43: 136.09054 | AZ43: 136.09054 | BA43: 136.09054 | BB43: 136.09054 | BC43: 136.09054 | BD43: 136.09054 | BL43: =AVERAGE(AL43:AW43) -> 136.09054 | BM43: =AVERAGE(AX43:BI43) -> 136.09054 | BN43: =BM43/BL43-1 -> 0
A44: Printing and reproduction of recorded media | B44: 89.3 | C44: 89.3 | D44: 93.2 | E44: 93.6 | F44: 93.9 | G44: 93.9 | H44: 93.9 | I44: 93.9 | J44: 93.9 | K44: 93.9 | L44: 93.9 | M44: 93.9 | N44: 93.9 | O44: 93.9 | P44: 93.9 | Q44: 93.9 | R44: 93.9 | S44: 93.9 | T44: 93.9 | U44: 93.9 | V44: 93.9 | W44: 93.9 | X44: 93.9 | Y44: 93.9 | Z44: 93.9 | AA44: 93.9 | AB44: 93.9 | AC44: 93.9 | AD44: 93.9 | AE44: 93.9 | AF44: 93.9 | AG44: 93.9 | AH44: 93.9 | AI44: 93.9 | AJ44: 93.9 | AK44: 93.9 | AL44: 93.9 | AM44: 93.9 | AN44: 98.8 | AO44: 98.8 | AP44: 101.8 | AQ44: 101.8 | AR44: 101.8 | AS44: 101.8 | AT44: 101.8 | AU44: 101.8 | AV44: 101.8 | AW44: 101.8 | AX44: 101.8 | AY44: 101.8 | AZ44: 101.8 | BA44: 101.8 | BB44: 101.8 | BC44: 101.8 | BD44: 101.8 | BE44: 104.3 | BF44: 104.3 | BG44: 104.3 | BH44: 104.3 | BI44: 104.3 | BL44: =AVERAGE(AL44:AW44) -> 99.983333 | BM44: =AVERAGE(AX44:BI44) -> 102.84167 | BN44: =BM44/BL44-1 -> 0.028588098
A45: Printing and service activities related to printing | B45: 101.03374 | C45: 101.03374 | D45: 105.40498 | E45: 105.85578 | F45: 106.21109 | G45: 106.21109 | H45: 106.21109 | I45: 106.21109 | J45: 106.21109 | K45: 106.21109 | L45: 106.21109 | M45: 106.21109 | N45: 106.21109 | O45: 106.21109 | P45: 106.21109 | Q45: 106.21109 | R45: 106.21109 | S45: 106.21109 | T45: 106.21109 | U45: 106.21109 | V45: 106.21109 | W45: 106.21109 | X45: 106.21109 | Y45: 106.21109 | Z45: 106.21109 | AA45: 106.21109 | AB45: 106.21109 | AC45: 106.21109 | AD45: 106.21109 | AE45: 106.21109 | AF45: 106.21109 | AG45: 106.21109 | AH45: 106.21109 | AI45: 106.21109 | AJ45: 106.21109 | AK45: 106.21109 | AL45: 106.21109 | AM45: 106.21109 | AN45: 111.77784 | AO45: 111.77784 | AP45: 115.12427 | AQ45: 115.12427 | AR45: 115.12427 | AS45: 115.12427 | AT45: 115.12427 | AU45: 115.12427 | AV45: 115.12427 | AW45: 115.12427 | AX45: 115.12427 | AY45: 115.12427 | AZ45: 115.12427 | BA45: 115.12427 | BB45: 115.12427 | BC45: 115.12427 | BD45: 115.12427 | BL45: =AVERAGE(AL45:AW45) -> 113.081 | BM45: =AVERAGE(AX45:BI45) -> 115.12427 | BN45: =BM45/BL45-1 -> 0.018069074
A46: Printing and service activities related to printing (to combine 1811 and 1812) | B46: 101.03374 | C46: 101.03374 | D46: 105.40498 | E46: 105.85578 | F46: 106.21109 | G46: 106.21109 | H46: 106.21109 | I46: 106.21109 | J46: 106.21109 | K46: 106.21109 | L46: 106.21109 | M46: 106.21109 | N46: 106.21109 | O46: 106.21109 | P46: 106.21109 | Q46: 106.21109 | R46: 106.21109 | S46: 106.21109 | T46: 106.21109 | U46: 106.21109 | V46: 106.21109 | W46: 106.21109 | X46: 106.21109 | Y46: 106.21109 | Z46: 106.21109 | AA46: 106.21109 | AB46: 106.21109 | AC46: 106.21109 | AD46: 106.21109 | AE46: 106.21109 | AF46: 106.21109 | AG46: 106.21109 | AH46: 106.21109 | AI46: 106.21109 | AJ46: 106.21109 | AK46: 106.21109 | AL46: 106.21109 | AM46: 106.21109 | AN46: 111.77784 | AO46: 111.77784 | AP46: 115.12427 | AQ46: 115.12427 | AR46: 115.12427 | AS46: 115.12427 | AT46: 115.12427 | AU46: 115.12427 | AV46: 115.12427 | AW46: 115.12427 | AX46: 115.12427 | AY46: 115.12427 | AZ46: 115.12427 | BA46: 115.12427 | BB46: 115.12427 | BC46: 115.12427 | BD46: 115.12427 | BL46: =AVERAGE(AL46:AW46) -> 113.081 | BM46: =AVERAGE(AX46:BI46) -> 115.12427 | BN46: =BM46/BL46-1 -> 0.018069074
A47: Manufacture of chemicals and chemical products | B47: 63.4 | C47: 63.4 | D47: 63.4 | E47: 69 | F47: 69.2 | G47: 69.2 | H47: 72.3 | I47: 71.7 | J47: 72.6 | K47: 73.5 | L47: 73.5 | M47: 73.5 | N47: 73.5 | O47: 77.8 | P47: 77.7 | Q47: 81.6 | R47: 85.5 | S47: 85.8 | T47: 87.7 | U47: 90 | V47: 90.1 | W47: 90.2 | X47: 90.4 | Y47: 90.4 | Z47: 96.7 | AA47: 96.6 | AB47: 95.9 | AC47: 96.5 | AD47: 96.6 | AE47: 96.7 | AF47: 96.7 | AG47: 96.1 | AH47: 96.3 | AI47: 98.1 | AJ47: 97.4 | AK47: 97.5 | AL47: 98.4 | AM47: 99.9 | AN47: 98.4 | AO47: 98.5 | AP47: 100 | AQ47: 100.1 | AR47: 99.3 | AS47: 99.4 | AT47: 100.3 | AU47: 101.8 | AV47: 101.9 | AW47: 102 | AX47: 104.6 | AY47: 104.7 | AZ47: 105.3 | BA47: 106.5 | BB47: 106.4 | BC47: 106.4 | BD47: 110 | BE47: 110 | BF47: 110 | BG47: 110.6 | BH47: 109.5 | BI47: 100 | BL47: =AVERAGE(AL47:AW47) -> 100 | BM47: =AVERAGE(AX47:BI47) -> 107 | BN47: =BM47/BL47-1 -> 0.07
A48: Manufacture of other chemical products | B48: 135.34034 | C48: 135.31127 | D48: 135.3932 | E48: 147.40616 | F48: 147.6499 | G48: 147.6499 | H48: 154.35816 | I48: 153.06935 | J48: 154.9888 | K48: 156.91214 | L48: 157.00152 | M48: 156.99059 | N48: 156.99295 | O48: 166.01992 | P48: 166.00209 | Q48: 174.27173 | R48: 182.52914 | S48: 183.23746 | T48: 187.31034 | U48: 192.06792 | V48: 192.48102 | W48: 192.55859 | X48: 193.09785 | Y48: 193.10168 | Z48: 206.37828 | AA48: 206.21254 | AB48: 204.66083 | AC48: 206.04005 | AD48: 206.19532 | AE48: 206.45644 | AF48: 206.40728 | AG48: 205.17572 | AH48: 205.53319 | AI48: 209.44395 | AJ48: 207.97127 | AK48: 208.13448 | AL48: 210.05316 | AM48: 213.39654 | AN48: 210.14804 | AO48: 210.30929 | AP48: 213.49575 | AQ48: 213.82481 | AR48: 212.09136 | AS48: 212.25013 | AT48: 214.21848 | AU48: 217.25682 | AV48: 217.49925 | AW48: 217.69548 | AX48: 223.43429 | AY48: 223.50437 | AZ48: 224.86998 | BA48: 227.37981 | BB48: 227.25086 | BC48: 227.2751 | BD48: 234.84757 | BL48: =AVERAGE(AL48:AW48) -> 213.51993 | BM48: =AVERAGE(AX48:BI48) -> 226.93743 | BN48: =BM48/BL48-1 -> 0.062839573
A49: Manufacture of paints, varnishes and similar coatings, printing ink and mastics | B49: 128.47361 | C49: 128.47361 | D49: 128.47361 | E49: 167.05365 | F49: 167.05365 | G49: 167.05365 | H49: 174.26452 | I49: 174.26452 | J49: 174.26452 | K49: 174.26452 | L49: 174.26452 | M49: 174.26452 | N49: 174.26452 | O49: 174.26452 | P49: 174.26452 | Q49: 174.26452 | R49: 200.01255 | S49: 201.84122 | T49: 201.84122 | U49: 215.32342 | V49: 215.32342 | W49: 215.32342 | X49: 215.32342 | Y49: 215.32342 | Z49: 245.21384 | AA49: 245.21384 | AB49: 245.21384 | AC49: 245.21384 | AD49: 245.21384 | AE49: 245.21384 | AF49: 245.21384 | AG49: 245.21384 | AH49: 245.21384 | AI49: 245.21384 | AJ49: 245.21384 | AK49: 245.21384 | AL49: 245.21384 | AM49: 245.21384 | AN49: 245.21384 | AO49: 245.21384 | AP49: 245.21384 | AQ49: 245.21384 | AR49: 245.21384 | AS49: 245.21384 | AT49: 245.21384 | AU49: 245.21384 | AV49: 245.21384 | AW49: 245.21384 | AX49: 245.21384 | AY49: 245.21384 | AZ49: 247.72425 | BA49: 247.72425 | BB49: 247.72425 | BC49: 247.72425 | BD49: 247.72425 | BL49: =AVERAGE(AL49:AW49) -> 245.21384 | BM49: =AVERAGE(AX49:BI49) -> 247.00699 | BN49: =BM49/BL49-1 -> 0.0073126131
A50: Manufacture of soap and detergents, cleaning and polishing preparations, perfumes and toilet preparations | B50: 138.37307 | C50: 138.37307 | D50: 138.37307 | E50: 139.48346 | F50: 139.48346 | G50: 139.48346 | H50: 146.73024 | I50: 146.73024 | J50: 146.73024 | K50: 149.99142 | L50: 149.99142 | M50: 149.99142 | N50: 149.99142 | O50: 165.12975 | P50: 165.12975 | Q50: 178.20521 | R50: 178.20521 | S50: 178.20521 | T50: 185.69874 | U50: 185.69874 | V50: 185.69874 | W50: 185.69874 | X50: 186.36284 | Y50: 186.36284 | Z50: 186.36284 | AA50: 185.78686 | AB50: 185.78686 | AC50: 185.78686 | AD50: 185.78686 | AE50: 185.78686 | AF50: 185.78686 | AG50: 182.68432 | AH50: 182.68432 | AI50: 190.13559 | AJ50: 190.13559 | AK50: 190.13559 | AL50: 190.13559 | AM50: 196.43744 | AN50: 190.13559 | AO50: 190.13559 | AP50: 196.44662 | AQ50: 196.44662 | AR50: 196.85874 | AS50: 196.85874 | AT50: 196.85874 | AU50: 201.86299 | AV50: 201.86299 | AW50: 201.86299 | AX50: 211.99724 | AY50: 211.99724 | AZ50: 211.99724 | BA50: 216.78363 | BB50: 216.7831 | BC50: 216.7831 | BD50: 229.37164 | BL50: =AVERAGE(AL50:AW50) -> 196.32522 | BM50: =AVERAGE(AX50:BI50) -> 216.53046 | BN50: =BM50/BL50-1 -> 0.10291717
A51: Manufacture of other chemical products n.e.c. | B51: 135.13844 | C51: 134.82081 | D51: 135.71245 | E51: 123.39869 | F51: 127.16154 | G51: 127.16154 | H51: 127.16154 | I51: 96.99138 | J51: 136.79203 | K51: 138.12017 | L51: 139.37884 | M51: 139.22621 | N51: 139.25915 | O51: 140.7347 | P51: 140.45602 | Q51: 140.88247 | R51: 140.66609 | S51: 141.9818 | T51: 132.40703 | U51: 132.40703 | V51: 142.70966 | W51: 144.40862 | X51: 147.63848 | Y51: 147.71652 | Z51: 177.82591 | AA51: 179.65326 | AB51: 152.92604 | AC51: 177.13212 | AD51: 179.40501 | AE51: 183.09168 | AF51: 182.4098 | AG51: 186.5958 | AH51: 191.14079 | AI51: 193.44634 | AJ51: 172.50677 | AK51: 175.11064 | AL51: 200.87296 | AM51: 201.95685 | AN51: 201.98266 | AO51: 203.84223 | AP51: 203.08891 | AQ51: 206.94341 | AR51: 181.46476 | AS51: 183.82953 | AT51: 208.97904 | AU51: 213.41672 | AV51: 216.09816 | AW51: 218.22489 | AX51: 220.65682 | AY51: 221.43283 | AZ51: 226.70492 | BA51: 225.07982 | BB51: 223.64805 | BC51: 223.91906 | BD51: 227.56777 | BL51: =AVERAGE(AL51:AW51) -> 203.39168 | BM51: =AVERAGE(AX51:BI51) -> 224.14418 | BN51: =BM51/BL51-1 -> 0.10203222
A52: Manufacture of pharmaceuticals, medicinal chemical and botanical products | B52: 100.08295 | C52: 100.08295 | D52: 100.08295 | E52: 100.08295 | F52: 100.08295 | G52: 100.08295 | H52: 100.08295 | I52: 100.08295 | J52: 100.08295 | K52: 100.08295 | L52: 100.08295 | M52: 100.08295 | N52: 100.08295 | O52: 100.08295 | P52: 100.08295 | Q52: 100.08295 | R52: 100.08295 | S52: 100.08295 | T52: 100.08295 | U52: 100.08295 | V52: 100.08295 | W52: 100.08295 | X52: 100.08295 | Y52: 100.08295 | Z52: 100.08295 | AA52: 100.08295 | AB52: 100.08295 | AC52: 100.08295 | AD52: 100.08295 | AE52: 100.08295 | AF52: 100.08295 | AG52: 100.08295 | AH52: 100.08295 | AI52: 100.08295 | AJ52: 100.08295 | AK52: 100.08295 | AL52: 100.08295 | AM52: 100.08295 | AN52: 100.08295 | AO52: 100.08295 | AP52: 100.08295 | AQ52: 100.08295 | AR52: 100.08295 | AS52: 100.08295 | AT52: 100.08295 | AU52: 100.08295 | AV52: 100.08295 | AW52: 100.08295 | AX52: 100.08295 | AY52: 100.08295 | AZ52: 100.08295 | BA52: 100.08295 | BB52: 100.08295 | BC52: 100.08295 | BD52: 100.08295 | BL52: =AVERAGE(AL52:AW52) -> 100.08295 | BM52: =AVERAGE(AX52:BI52) -> 100.08295 | BN52: =BM52/BL52-1 -> 0
A53: Manufacture of pharmaceuticals, medicinal chemical and botanical products | B53: 100.08295 | C53: 100.08295 | D53: 100.08295 | E53: 100.08295 | F53: 100.08295 | G53: 100.08295 | H53: 100.08295 | I53: 100.08295 | J53: 100.08295 | K53: 100.08295 | L53: 100.08295 | M53: 100.08295 | N53: 100.08295 | O53: 100.08295 | P53: 100.08295 | Q53: 100.08295 | R53: 100.08295 | S53: 100.08295 | T53: 100.08295 | U53: 100.08295 | V53: 100.08295 | W53: 100.08295 | X53: 100.08295 | Y53: 100.08295 | Z53: 100.08295 | AA53: 100.08295 | AB53: 100.08295 | AC53: 100.08295 | AD53: 100.08295 | AE53: 100.08295 | AF53: 100.08295 | AG53: 100.08295 | AH53: 100.08295 | AI53: 100.08295 | AJ53: 100.08295 | AK53: 100.08295 | AL53: 100.08295 | AM53: 100.08295 | AN53: 100.08295 | AO53: 100.08295 | AP53: 100.08295 | AQ53: 100.08295 | AR53: 100.08295 | AS53: 100.08295 | AT53: 100.08295 | AU53: 100.08295 | AV53: 100.08295 | AW53: 100.08295 | AX53: 100.08295 | AY53: 100.08295 | AZ53: 100.08295 | BA53: 100.08295 | BB53: 100.08295 | BC53: 100.08295 | BD53: 100.08295 | BL53: =AVERAGE(AL53:AW53) -> 100.08295 | BM53: =AVERAGE(AX53:BI53) -> 100.08295 | BN53: =BM53/BL53-1 -> 0
A54: Manufacture of pharmaceuticals, medicinal chemical and botanical products | B54: 100.08295 | C54: 100.08295 | D54: 100.08295 | E54: 100.08295 | F54: 100.08295 | G54: 100.08295 | H54: 100.08295 | I54: 100.08295 | J54: 100.08295 | K54: 100.08295 | L54: 100.08295 | M54: 100.08295 | N54: 100.08295 | O54: 100.08295 | P54: 100.08295 | Q54: 100.08295 | R54: 100.08295 | S54: 100.08295 | T54: 100.08295 | U54: 100.08295 | V54: 100.08295 | W54: 100.08295 | X54: 100.08295 | Y54: 100.08295 | Z54: 100.08295 | AA54: 100.08295 | AB54: 100.08295 | AC54: 100.08295 | AD54: 100.08295 | AE54: 100.08295 | AF54: 100.08295 | AG54: 100.08295 | AH54: 100.08295 | AI54: 100.08295 | AJ54: 100.08295 | AK54: 100.08295 | AL54: 100.08295 | AM54: 100.08295 | AN54: 100.08295 | AO54: 100.08295 | AP54: 100.08295 | AQ54: 100.08295 | AR54: 100.08295 | AS54: 100.08295 | AT54: 100.08295 | AU54: 100.08295 | AV54: 100.08295 | AW54: 100.08295 | AX54: 100.08295 | AY54: 100.08295 | AZ54: 100.08295 | BA54: 100.08295 | BB54: 100.08295 | BC54: 100.08295 | BD54: 100.08295 | BL54: =AVERAGE(AL54:AW54) -> 100.08295 | BM54: =AVERAGE(AX54:BI54) -> 100.08295 | BN54: =BM54/BL54-1 -> 0
A55: Manufacture of rubber and plastics products | B55: 75.6 | C55: 75.6 | D55: 75.7 | E55: 76.8 | F55: 77.7 | G55: 87.1 | H55: 87.1 | I55: 87.4 | J55: 89 | K55: 89.9 | L55: 89.9 | M55: 89.9 | N55: 89.9 | O55: 89.9 | P55: 89.9 | Q55: 91.9 | R55: 93.6 | S55: 94.2 | T55: 94.1 | U55: 94.1 | V55: 94.1 | W55: 94.1 | X55: 94.4 | Y55: 94.4 | Z55: 94.4 | AA55: 94.4 | AB55: 94.9 | AC55: 94.9 | AD55: 94.9 | AE55: 94.9 | AF55: 94.9 | AG55: 94.9 | AH55: 94.9 | AI55: 95.7 | AJ55: 95.7 | AK55: 95.7 | AL55: 95.7 | AM55: 100.3 | AN55: 100.3 | AO55: 100.3 | AP55: 100.4 | AQ55: 100.4 | AR55: 100.4 | AS55: 100.4 | AT55: 100.4 | AU55: 100.4 | AV55: 100.4 | AW55: 100.4 | AX55: 100.4 | AY55: 100.4 | AZ55: 100.4 | BA55: 100.4 | BB55: 100.4 | BC55: 100.4 | BD55: 100.4 | BE55: 100.4 | BF55: 97.8 | BG55: 98.4 | BH55: 98.4 | BI55: 98.4 | BL55: =AVERAGE(AL55:AW55) -> 99.983333 | BM55: =AVERAGE(AX55:BI55) -> 99.683333 | BN55: =BM55/BL55-1 -> -0.0030005001
A56: Manufacture of rubber products | B56: 100 | C56: 100 | D56: 100 | E56: 100 | F56: 100 | G56: 100 | H56: 100 | I56: 100 | J56: 100 | K56: 100 | L56: 100 | M56: 100 | N56: 100 | O56: 100 | P56: 100 | Q56: 100 | R56: 100 | S56: 100 | T56: 100 | U56: 100 | V56: 100 | W56: 100 | X56: 100 | Y56: 100 | Z56: 100 | AA56: 100 | AB56: 100 | AC56: 100 | AD56: 100 | AE56: 100 | AF56: 100 | AG56: 100 | AH56: 100 | AI56: 100 | AJ56: 100 | AK56: 100 | AL56: 100 | AM56: 100 | AN56: 100 | AO56: 100 | AP56: 100 | AQ56: 100 | AR56: 100 | AS56: 100 | AT56: 100 | AU56: 100 | AV56: 100 | AW56: 100 | AX56: 100 | AY56: 100 | AZ56: 100 | BA56: 100 | BB56: 100 | BC56: 100 | BD56: 100 | BL56: =AVERAGE(AL56:AW56) -> 100 | BM56: =AVERAGE(AX56:BI56) -> 100 | BN56: =BM56/BL56-1 -> 0
A57: Manufacture of rubber tyres and tubes; retreading and rebuilding of rubber tyres | B57: 100 | C57: 100 | D57: 100 | E57: 100 | F57: 100 | G57: 100 | H57: 100 | I57: 100 | J57: 100 | K57: 100 | L57: 100 | M57: 100 | N57: 100 | O57: 100 | P57: 100 | Q57: 100 | R57: 100 | S57: 100 | T57: 100 | U57: 100 | V57: 100 | W57: 100 | X57: 100 | Y57: 100 | Z57: 100 | AA57: 100 | AB57: 100 | AC57: 100 | AD57: 100 | AE57: 100 | AF57: 100 | AG57: 100 | AH57: 100 | AI57: 100 | AJ57: 100 | AK57: 100 | AL57: 100 | AM57: 100 | AN57: 100 | AO57: 100 | AP57: 100 | AQ57: 100 | AR57: 100 | AS57: 100 | AT57: 100 | AU57: 100 | AV57: 100 | AW57: 100 | AX57: 100 | AY57: 100 | AZ57: 100 | BA57: 100 | BB57: 100 | BC57: 100 | BD57: 100 | BL57: =AVERAGE(AL57:AW57) -> 100 | BM57: =AVERAGE(AX57:BI57) -> 100 | BN57: =BM57/BL57-1 -> 0
A58: Manufacture of plastics products | B58: 90.734981 | C58: 90.734981 | D58: 90.734981 | E58: 93.894372 | F58: 93.894372 | G58: 117.58199 | H58: 117.58199 | I58: 117.58199 | J58: 121.65257 | K58: 123.87699 | L58: 123.87699 | M58: 123.87699 | N58: 123.87699 | O58: 123.87699 | P58: 123.87699 | Q58: 123.87699 | R58: 123.87699 | S58: 123.87699 | T58: 123.87699 | U58: 123.87699 | V58: 123.87699 | W58: 123.87699 | X58: 123.87699 | Y58: 123.87699 | Z58: 123.87699 | AA58: 123.87699 | AB58: 123.87699 | AC58: 123.87699 | AD58: 123.87699 | AE58: 123.87699 | AF58: 123.87699 | AG58: 123.87699 | AH58: 123.87699 | AI58: 123.87699 | AJ58: 123.87699 | AK58: 123.87699 | AL58: 123.87699 | AM58: 123.87699 | AN58: 123.87699 | AO58: 123.87699 | AP58: 123.87699 | AQ58: 123.87699 | AR58: 123.87699 | AS58: 123.87699 | AT58: 123.87699 | AU58: 123.87699 | AV58: 123.87699 | AW58: 123.87699 | AX58: 123.87699 | AY58: 123.87699 | AZ58: 123.87699 | BA58: 123.87699 | BB58: 123.87699 | BC58: 123.87699 | BD58: 123.87699 | BL58: =AVERAGE(AL58:AW58) -> 123.87699 | BM58: =AVERAGE(AX58:BI58) -> 123.87699 | BN58: =BM58/BL58-1 -> 0
A59: Manufacture of plastics products | B59: 90.734981 | C59: 90.734981 | D59: 90.734981 | E59: 93.894372 | F59: 93.894372 | G59: 117.58199 | H59: 117.58199 | I59: 117.58199 | J59: 121.65257 | K59: 123.87699 | L59: 123.87699 | M59: 123.87699 | N59: 123.87699 | O59: 123.87699 | P59: 123.87699 | Q59: 123.87699 | R59: 123.87699 | S59: 123.87699 | T59: 123.87699 | U59: 123.87699 | V59: 123.87699 | W59: 123.87699 | X59: 123.87699 | Y59: 123.87699 | Z59: 123.87699 | AA59: 123.87699 | AB59: 123.87699 | AC59: 123.87699 | AD59: 123.87699 | AE59: 123.87699 | AF59: 123.87699 | AG59: 123.87699 | AH59: 123.87699 | AI59: 123.87699 | AJ59: 123.87699 | AK59: 123.87699 | AL59: 123.87699 | AM59: 123.87699 | AN59: 123.87699 | AO59: 123.87699 | AP59: 123.87699 | AQ59: 123.87699 | AR59: 123.87699 | AS59: 123.87699 | AT59: 123.87699 | AU59: 123.87699 | AV59: 123.87699 | AW59: 123.87699 | AX59: 123.87699 | AY59: 123.87699 | AZ59: 123.87699 | BA59: 123.87699 | BB59: 123.87699 | BC59: 123.87699 | BD59: 123.87699 | BL59: =AVERAGE(AL59:AW59) -> 123.87699 | BM59: =AVERAGE(AX59:BI59) -> 123.87699 | BN59: =BM59/BL59-1 -> 0
A60: Manufacture of other non-metallic mineral products | B60: 81.3 | C60: 81.3 | D60: 81.5 | E60: 81.3 | F60: 82.8 | G60: 82.8 | H60: 82.8 | I60: 83.2 | J60: 83.2 | K60: 83.2 | L60: 83.2 | M60: 83.2 | N60: 83.2 | O60: 83.2 | P60: 83.2 | Q60: 86.5 | R60: 89.4 | S60: 90.4 | T60: 90.1 | U60: 90.1 | V60: 90.1 | W60: 90.1 | X60: 90.6 | Y60: 90.6 | Z60: 90.6 | AA60: 90.6 | AB60: 91.5 | AC60: 91.5 | AD60: 91.5 | AE60: 91.5 | AF60: 91.5 | AG60: 91.5 | AH60: 91.5 | AI60: 92.9 | AJ60: 92.9 | AK60: 92.9 | AL60: 92.9 | AM60: 100.5 | AN60: 100.5 | AO60: 100.5 | AP60: 100.6 | AQ60: 100.6 | AR60: 100.7 | AS60: 100.7 | AT60: 100.7 | AU60: 100.7 | AV60: 100.7 | AW60: 100.7 | AX60: 100.7 | AY60: 100.7 | AZ60: 100.7 | BA60: 100.7 | BB60: 100.7 | BC60: 100.7 | BD60: 100.7 | BE60: 100.7 | BF60: 96.4 | BG60: 96.4 | BH60: 96.6 | BI60: 97.9 | BL60: =AVERAGE(AL60:AW60) -> 99.983333 | BM60: =AVERAGE(AX60:BI60) -> 99.408333 | BN60: =BM60/BL60-1 -> -0.0057509585
A61: Manufacture of non-metallic mineral products n.e.c. | B61: 112.27796 | C61: 112.27796 | D61: 112.49593 | E61: 112.27796 | F61: 114.27363 | G61: 114.27363 | H61: 114.27363 | I61: 114.85817 | J61: 114.85817 | K61: 114.85817 | L61: 114.85817 | M61: 114.85817 | N61: 114.85817 | O61: 114.85817 | P61: 114.85817 | Q61: 119.40698 | R61: 123.33206 | S61: 124.74154 | T61: 124.42758 | U61: 124.42758 | V61: 124.42758 | W61: 124.42758 | X61: 125.04286 | Y61: 125.04286 | Z61: 125.04286 | AA61: 125.04286 | AB61: 126.35501 | AC61: 126.35501 | AD61: 126.35501 | AE61: 126.35501 | AF61: 126.35501 | AG61: 126.35501 | AH61: 126.35501 | AI61: 128.2045 | AJ61: 128.2045 | AK61: 128.2045 | AL61: 128.2045 | AM61: 138.73431 | AN61: 138.73431 | AO61: 138.73431 | AP61: 138.84868 | AQ61: 138.84868 | AR61: 139.0318 | AS61: 139.0318 | AT61: 139.0318 | AU61: 139.0318 | AV61: 139.0318 | AW61: 139.0318 | AX61: 139.0318 | AY61: 139.0318 | AZ61: 139.0318 | BA61: 139.0318 | BB61: 139.0318 | BC61: 139.0318 | BD61: 139.0318 | BL61: =AVERAGE(AL61:AW61) -> 138.02463 | BM61: =AVERAGE(AX61:BI61) -> 139.0318 | BN61: =BM61/BL61-1 -> 0.0072970185
A62: Manufacture of non-metallic mineral products n.e.c. | B62: 112.27796 | C62: 112.27796 | D62: 112.49593 | E62: 112.27796 | F62: 114.27363 | G62: 114.27363 | H62: 114.27363 | I62: 114.85817 | J62: 114.85817 | K62: 114.85817 | L62: 114.85817 | M62: 114.85817 | N62: 114.85817 | O62: 114.85817 | P62: 114.85817 | Q62: 119.40698 | R62: 123.33206 | S62: 124.74154 | T62: 124.42758 | U62: 124.42758 | V62: 124.42758 | W62: 124.42758 | X62: 125.04286 | Y62: 125.04286 | Z62: 125.04286 | AA62: 125.04286 | AB62: 126.35501 | AC62: 126.35501 | AD62: 126.35501 | AE62: 126.35501 | AF62: 126.35501 | AG62: 126.35501 | AH62: 126.35501 | AI62: 128.2045 | AJ62: 128.2045 | AK62: 128.2045 | AL62: 128.2045 | AM62: 138.73431 | AN62: 138.73431 | AO62: 138.73431 | AP62: 138.84868 | AQ62: 138.84868 | AR62: 139.0318 | AS62: 139.0318 | AT62: 139.0318 | AU62: 139.0318 | AV62: 139.0318 | AW62: 139.0318 | AX62: 139.0318 | AY62: 139.0318 | AZ62: 139.0318 | BA62: 139.0318 | BB62: 139.0318 | BC62: 139.0318 | BD62: 139.0318 | BL62: =AVERAGE(AL62:AW62) -> 138.02463 | BM62: =AVERAGE(AX62:BI62) -> 139.0318 | BN62: =BM62/BL62-1 -> 0.0072970185
A63: Manufacture of fabricated metal products, except machinery and equipment | B63: 144.86183 | C63: 144.86183 | D63: 144.86183 | E63: 144.86183 | F63: 144.86183 | G63: 144.86183 | H63: 144.86183 | I63: 144.86183 | J63: 144.86183 | K63: 144.86183 | L63: 144.86183 | M63: 144.86183 | N63: 144.86183 | O63: 144.86183 | P63: 144.86183 | Q63: 144.86183 | R63: 144.86183 | S63: 144.86183 | T63: 144.86183 | U63: 144.86183 | V63: 144.86183 | W63: 144.86183 | X63: 144.86183 | Y63: 144.86183 | Z63: 144.86183 | AA63: 144.86183 | AB63: 144.86183 | AC63: 144.86183 | AD63: 144.86183 | AE63: 144.86183 | AF63: 144.86183 | AG63: 144.86183 | AH63: 144.86183 | AI63: 144.86183 | AJ63: 144.86183 | AK63: 144.86183 | AL63: 144.86183 | AM63: 144.86183 | AN63: 144.86183 | AO63: 144.86183 | AP63: 144.86183 | AQ63: 144.86183 | AR63: 144.86183 | AS63: 144.86183 | AT63: 144.86183 | AU63: 144.86183 | AV63: 144.86183 | AW63: 144.86183 | AX63: 144.86183 | AY63: 144.86183 | AZ63: 144.86183 | BA63: 144.86183 | BB63: 144.86183 | BC63: 144.86183 | BD63: 144.86183 | BL63: =AVERAGE(AL63:AW63) -> 144.86183 | BM63: =AVERAGE(AX63:BI63) -> 144.86183 | BN63: =BM63/BL63-1 -> 0
A64: Manufacture of fabricated metal products, except machinery and equipment | B64: 144.86183 | C64: 144.86183 | D64: 144.86183 | E64: 144.86183 | F64: 144.86183 | G64: 144.86183 | H64: 144.86183 | I64: 144.86183 | J64: 144.86183 | K64: 144.86183 | L64: 144.86183 | M64: 144.86183 | N64: 144.86183 | O64: 144.86183 | P64: 144.86183 | Q64: 144.86183 | R64: 144.86183 | S64: 144.86183 | T64: 144.86183 | U64: 144.86183 | V64: 144.86183 | W64: 144.86183 | X64: 144.86183 | Y64: 144.86183 | Z64: 144.86183 | AA64: 144.86183 | AB64: 144.86183 | AC64: 144.86183 | AD64: 144.86183 | AE64: 144.86183 | AF64: 144.86183 | AG64: 144.86183 | AH64: 144.86183 | AI64: 144.86183 | AJ64: 144.86183 | AK64: 144.86183 | AL64: 144.86183 | AM64: 144.86183 | AN64: 144.86183 | AO64: 144.86183 | AP64: 144.86183 | AQ64: 144.86183 | AR64: 144.86183 | AS64: 144.86183 | AT64: 144.86183 | AU64: 144.86183 | AV64: 144.86183 | AW64: 144.86183 | AX64: 144.86183 | AY64: 144.86183 | AZ64: 144.86183 | BA64: 144.86183 | BB64: 144.86183 | BC64: 144.86183 | BD64: 144.86183 | BL64: =AVERAGE(AL64:AW64) -> 144.86183 | BM64: =AVERAGE(AX64:BI64) -> 144.86183 | BN64: =BM64/BL64-1 -> 0
A65: Manufacture of fabricated metal products, except machinery and equipment | B65: 144.86183 | C65: 144.86183 | D65: 144.86183 | E65: 144.86183 | F65: 144.86183 | G65: 144.86183 | H65: 144.86183 | I65: 144.86183 | J65: 144.86183 | K65: 144.86183 | L65: 144.86183 | M65: 144.86183 | N65: 144.86183 | O65: 144.86183 | P65: 144.86183 | Q65: 144.86183 | R65: 144.86183 | S65: 144.86183 | T65: 144.86183 | U65: 144.86183 | V65: 144.86183 | W65: 144.86183 | X65: 144.86183 | Y65: 144.86183 | Z65: 144.86183 | AA65: 144.86183 | AB65: 144.86183 | AC65: 144.86183 | AD65: 144.86183 | AE65: 144.86183 | AF65: 144.86183 | AG65: 144.86183 | AH65: 144.86183 | AI65: 144.86183 | AJ65: 144.86183 | AK65: 144.86183 | AL65: 144.86183 | AM65: 144.86183 | AN65: 144.86183 | AO65: 144.86183 | AP65: 144.86183 | AQ65: 144.86183 | AR65: 144.86183 | AS65: 144.86183 | AT65: 144.86183 | AU65: 144.86183 | AV65: 144.86183 | AW65: 144.86183 | AX65: 144.86183 | AY65: 144.86183 | AZ65: 144.86183 | BA65: 144.86183 | BB65: 144.86183 | BC65: 144.86183 | BD65: 144.86183 | BL65: =AVERAGE(AL65:AW65) -> 144.86183 | BM65: =AVERAGE(AX65:BI65) -> 144.86183 | BN65: =BM65/BL65-1 -> 0
A66: Manufacture of electrical equipment | B66: 156.11062 | C66: 156.11062 | D66: 156.11062 | E66: 156.11062 | F66: 156.11062 | G66: 156.11062 | H66: 156.11062 | I66: 156.11062 | J66: 156.11062 | K66: 156.11062 | L66: 156.11062 | M66: 156.11062 | N66: 156.11062 | O66: 156.11062 | P66: 156.11062 | Q66: 156.11062 | R66: 156.11062 | S66: 156.11062 | T66: 156.11062 | U66: 156.11062 | V66: 156.11062 | W66: 156.11062 | X66: 156.11062 | Y66: 156.11062 | Z66: 156.11062 | AA66: 156.11062 | AB66: 156.11062 | AC66: 156.11062 | AD66: 156.11062 | AE66: 156.11062 | AF66: 156.11062 | AG66: 156.11062 | AH66: 156.11062 | AI66: 156.11062 | AJ66: 156.11062 | AK66: 156.11062 | AL66: 156.11062 | AM66: 156.11062 | AN66: 156.11062 | AO66: 156.11062 | AP66: 156.11062 | AQ66: 156.11062 | AR66: 156.11062 | AS66: 156.11062 | AT66: 156.11062 | AU66: 156.11062 | AV66: 156.11062 | AW66: 156.11062 | AX66: 156.11062 | AY66: 156.11062 | AZ66: 156.11062 | BA66: 156.11062 | BB66: 156.11062 | BC66: 156.11062 | BD66: 156.11062 | BL66: =AVERAGE(AL66:AW66) -> 156.11062 | BM66: =AVERAGE(AX66:BI66) -> 156.11062 | BN66: =BM66/BL66-1 -> 0
A67: Manufacture of batteries and accumulators | B67: 156.11062 | C67: 156.11062 | D67: 156.11062 | E67: 156.11062 | F67: 156.11062 | G67: 156.11062 | H67: 156.11062 | I67: 156.11062 | J67: 156.11062 | K67: 156.11062 | L67: 156.11062 | M67: 156.11062 | N67: 156.11062 | O67: 156.11062 | P67: 156.11062 | Q67: 156.11062 | R67: 156.11062 | S67: 156.11062 | T67: 156.11062 | U67: 156.11062 | V67: 156.11062 | W67: 156.11062 | X67: 156.11062 | Y67: 156.11062 | Z67: 156.11062 | AA67: 156.11062 | AB67: 156.11062 | AC67: 156.11062 | AD67: 156.11062 | AE67: 156.11062 | AF67: 156.11062 | AG67: 156.11062 | AH67: 156.11062 | AI67: 156.11062 | AJ67: 156.11062 | AK67: 156.11062 | AL67: 156.11062 | AM67: 156.11062 | AN67: 156.11062 | AO67: 156.11062 | AP67: 156.11062 | AQ67: 156.11062 | AR67: 156.11062 | AS67: 156.11062 | AT67: 156.11062 | AU67: 156.11062 | AV67: 156.11062 | AW67: 156.11062 | AX67: 156.11062 | AY67: 156.11062 | AZ67: 156.11062 | BA67: 156.11062 | BB67: 156.11062 | BC67: 156.11062 | BD67: 156.11062 | BL67: =AVERAGE(AL67:AW67) -> 156.11062 | BM67: =AVERAGE(AX67:BI67) -> 156.11062 | BN67: =BM67/BL67-1 -> 0
A68: Manufacture of batteries and accumulators | B68: 156.11062 | C68: 156.11062 | D68: 156.11062 | E68: 156.11062 | F68: 156.11062 | G68: 156.11062 | H68: 156.11062 | I68: 156.11062 | J68: 156.11062 | K68: 156.11062 | L68: 156.11062 | M68: 156.11062 | N68: 156.11062 | O68: 156.11062 | P68: 156.11062 | Q68: 156.11062 | R68: 156.11062 | S68: 156.11062 | T68: 156.11062 | U68: 156.11062 | V68: 156.11062 | W68: 156.11062 | X68: 156.11062 | Y68: 156.11062 | Z68: 156.11062 | AA68: 156.11062 | AB68: 156.11062 | AC68: 156.11062 | AD68: 156.11062 | AE68: 156.11062 | AF68: 156.11062 | AG68: 156.11062 | AH68: 156.11062 | AI68: 156.11062 | AJ68: 156.11062 | AK68: 156.11062 | AL68: 156.11062 | AM68: 156.11062 | AN68: 156.11062 | AO68: 156.11062 | AP68: 156.11062 | AQ68: 156.11062 | AR68: 156.11062 | AS68: 156.11062 | AT68: 156.11062 | AU68: 156.11062 | AV68: 156.11062 | AW68: 156.11062 | AX68: 156.11062 | AY68: 156.11062 | AZ68: 156.11062 | BA68: 156.11062 | BB68: 156.11062 | BC68: 156.11062 | BD68: 156.11062 | BL68: =AVERAGE(AL68:AW68) -> 156.11062 | BM68: =AVERAGE(AX68:BI68) -> 156.11062 | BN68: =BM68/BL68-1 -> 0
A69: Manufacture of furniture | B69: 82.8 | C69: 82.8 | D69: 82.8 | E69: 82.2 | F69: 87.6 | G69: 87.6 | H69: 87.6 | I69: 87.6 | J69: 87.6 | K69: 87.6 | L69: 87.6 | M69: 88.8 | N69: 88.8 | O69: 91.7 | P69: 92.9 | Q69: 92.9 | R69: 95.6 | S69: 95.6 | T69: 95.6 | U69: 95.6 | V69: 97.3 | W69: 97.3 | X69: 97.3 | Y69: 97.3 | Z69: 97.3 | AA69: 97.3 | AB69: 97.7 | AC69: 97.7 | AD69: 97.7 | AE69: 97.7 | AF69: 97.7 | AG69: 97.7 | AH69: 97.7 | AI69: 96.4 | AJ69: 96.4 | AK69: 97.5 | AL69: 98 | AM69: 98 | AN69: 98.9 | AO69: 98.9 | AP69: 98.9 | AQ69: 101.2 | AR69: 101.2 | AS69: 100.8 | AT69: 100.8 | AU69: 100.8 | AV69: 100.8 | AW69: 101.8 | AX69: 101.8 | AY69: 101.8 | AZ69: 101.8 | BA69: 101.8 | BB69: 101.8 | BC69: 101.8 | BD69: 101.8 | BE69: 101.8 | BF69: 102.6 | BG69: 102.6 | BH69: 102.6 | BI69: 102.6 | BL69: =AVERAGE(AL69:AW69) -> 100.00833 | BM69: =AVERAGE(AX69:BI69) -> 102.06667 | BN69: =BM69/BL69-1 -> 0.020581618
A70: Manufacture of furniture | B70: 115.81244 | C70: 115.81244 | D70: 115.81244 | E70: 114.88487 | F70: 122.46113 | G70: 122.46113 | H70: 122.46113 | I70: 122.46113 | J70: 122.46113 | K70: 122.46113 | L70: 122.46113 | M70: 124.13773 | N70: 124.13773 | O70: 128.18121 | P70: 129.8774 | Q70: 129.8774 | R70: 133.66734 | S70: 133.66734 | T70: 133.66734 | U70: 133.66734 | V70: 136.09934 | W70: 136.09934 | X70: 136.09934 | Y70: 136.09934 | Z70: 136.09934 | AA70: 136.09934 | AB70: 136.60026 | AC70: 136.60026 | AD70: 136.60026 | AE70: 136.60026 | AF70: 136.60026 | AG70: 136.60026 | AH70: 136.60026 | AI70: 134.79613 | AJ70: 134.79613 | AK70: 136.3432 | AL70: 137.09904 | AM70: 137.09904 | AN70: 138.32012 | AO70: 138.32012 | AP70: 138.32012 | AQ70: 141.53293 | AR70: 141.53293 | AS70: 140.89806 | AT70: 140.89806 | AU70: 140.89806 | AV70: 140.89806 | AW70: 142.3143 | AX70: 142.3143 | AY70: 142.39179 | AZ70: 142.39179 | BA70: 142.39179 | BB70: 142.39179 | BC70: 142.39179 | BD70: 142.39179 | BL70: =AVERAGE(AL70:AW70) -> 139.84424 | BM70: =AVERAGE(AX70:BI70) -> 142.38072 | BN70: =BM70/BL70-1 -> 0.018137937
A71: Manufacture of furniture | B71: 115.81244 | C71: 115.81244 | D71: 115.81244 | E71: 114.88487 | F71: 122.46113 | G71: 122.46113 | H71: 122.46113 | I71: 122.46113 | J71: 122.46113 | K71: 122.46113 | L71: 122.46113 | M71: 124.13773 | N71: 124.13773 | O71: 128.18121 | P71: 129.8774 | Q71: 129.8774 | R71: 133.66734 | S71: 133.66734 | T71: 133.66734 | U71: 133.66734 | V71: 136.09934 | W71: 136.09934 | X71: 136.09934 | Y71: 136.09934 | Z71: 136.09934 | AA71: 136.09934 | AB71: 136.60026 | AC71: 136.60026 | AD71: 136.60026 | AE71: 136.60026 | AF71: 136.60026 | AG71: 136.60026 | AH71: 136.60026 | AI71: 134.79613 | AJ71: 134.79613 | AK71: 136.3432 | AL71: 137.09904 | AM71: 137.09904 | AN71: 138.32012 | AO71: 138.32012 | AP71: 138.32012 | AQ71: 141.53293 | AR71: 141.53293 | AS71: 140.89806 | AT71: 140.89806 | AU71: 140.89806 | AV71: 140.89806 | AW71: 142.3143 | AX71: 142.3143 | AY71: 142.39179 | AZ71: 142.39179 | BA71: 142.39179 | BB71: 142.39179 | BC71: 142.39179 | BD71: 142.39179 | BL71: =AVERAGE(AL71:AW71) -> 139.84424 | BM71: =AVERAGE(AX71:BI71) -> 142.38072 | BN71: =BM71/BL71-1 -> 0.018137937
A72: Electricity, gas, steam and air conditioning supply | B72: 179.54165 | C72: 179.54165 | D72: 179.54165 | E72: 179.54165 | F72: 179.54165 | G72: 179.54165 | H72: 179.54165 | I72: 179.54165 | J72: 179.54165 | K72: 179.54165 | L72: 179.54165 | M72: 179.54165 | N72: 179.54165 | O72: 179.54165 | P72: 179.54165 | Q72: 179.54165 | R72: 179.54165 | S72: 179.54165 | T72: 179.54165 | U72: 179.54165 | V72: 179.54165 | W72: 179.54165 | X72: 179.54165 | Y72: 179.54165 | Z72: 179.54165 | AA72: 179.54165 | AB72: 179.54165 | AC72: 179.54165 | AD72: 179.54165 | AE72: 179.54165 | AF72: 179.54165 | AG72: 179.54165 | AH72: 179.54165 | AI72: 179.54165 | AJ72: 179.54165 | AK72: 179.54165 | AL72: 179.54165 | AM72: 179.54165 | AN72: 179.54165 | AO72: 179.54165 | AP72: 179.54165 | AQ72: 179.54165 | AR72: 179.54165 | AS72: 179.54165 | AT72: 179.54165 | AU72: 179.54165 | AV72: 179.54165 | AW72: 179.54165 | AX72: 179.54165 | AY72: 179.54165 | AZ72: 179.54165 | BA72: 179.54165 | BB72: 179.54165 | BC72: 179.54165 | BD72: 179.54165 | BL72: =AVERAGE(AL72:AW72) -> 179.54165 | BM72: =AVERAGE(AX72:BI72) -> 179.54165 | BN72: =BM72/BL72-1 -> 0
A73: Electricity, gas, steam and air conditioning supply | B73: 100 | C73: 100 | D73: 100 | E73: 100 | F73: 100 | G73: 100 | H73: 100 | I73: 100 | J73: 100 | K73: 100 | L73: 100 | M73: 100 | N73: 100 | O73: 100 | P73: 100 | Q73: 100 | R73: 100 | S73: 100 | T73: 100 | U73: 100 | V73: 100 | W73: 100 | X73: 100 | Y73: 100 | Z73: 100 | AA73: 100 | AB73: 100 | AC73: 100 | AD73: 100 | AE73: 100 | AF73: 100 | AG73: 100 | AH73: 100 | AI73: 100 | AJ73: 100 | AK73: 100 | AL73: 100 | AM73: 100 | AN73: 100 | AO73: 100 | AP73: 100 | AQ73: 100 | AR73: 100 | AS73: 100 | AT73: 100 | AU73: 100 | AV73: 100 | AW73: 100 | AX73: 100 | AY73: 100 | AZ73: 100 | BA73: 100 | BB73: 100 | BC73: 100 | BD73: 100 | BE73: 134.8 | BF73: 134.8 | BG73: 134.8 | BH73: 134.8 | BI73: 134.8 | BL73: =AVERAGE(AL73:AW73) -> 100 | BM73: =AVERAGE(AX73:BI73) -> 114.5 | BN73: =BM73/BL73-1 -> 0.145
A74: Electric power generation, transmission and distribution | B74: 179.54165 | C74: 179.54165 | D74: 179.54165 | E74: 179.54165 | F74: 179.54165 | G74: 179.54165 | H74: 179.54165 | I74: 179.54165 | J74: 179.54165 | K74: 179.54165 | L74: 179.54165 | M74: 179.54165 | N74: 179.54165 | O74: 179.54165 | P74: 179.54165 | Q74: 179.54165 | R74: 179.54165 | S74: 179.54165 | T74: 179.54165 | U74: 179.54165 | V74: 179.54165 | W74: 179.54165 | X74: 179.54165 | Y74: 179.54165 | Z74: 179.54165 | AA74: 179.54165 | AB74: 179.54165 | AC74: 179.54165 | AD74: 179.54165 | AE74: 179.54165 | AF74: 179.54165 | AG74: 179.54165 | AH74: 179.54165 | AI74: 179.54165 | AJ74: 179.54165 | AK74: 179.54165 | AL74: 179.54165 | AM74: 179.54165 | AN74: 179.54165 | AO74: 179.54165 | AP74: 179.54165 | AQ74: 179.54165 | AR74: 179.54165 | AS74: 179.54165 | AT74: 179.54165 | AU74: 179.54165 | AV74: 179.54165 | AW74: 179.54165 | AX74: 179.54165 | AY74: 179.54165 | AZ74: 179.54165 | BA74: 179.54165 | BB74: 179.54165 | BC74: 179.54165 | BD74: 179.54165 | BL74: =AVERAGE(AL74:AW74) -> 179.54165 | BM74: =AVERAGE(AX74:BI74) -> 179.54165 | BN74: =BM74/BL74-1 -> 0
A75: Electric power generation, transmission and distribution | B75: 179.54165 | C75: 179.54165 | D75: 179.54165 | E75: 179.54165 | F75: 179.54165 | G75: 179.54165 | H75: 179.54165 | I75: 179.54165 | J75: 179.54165 | K75: 179.54165 | L75: 179.54165 | M75: 179.54165 | N75: 179.54165 | O75: 179.54165 | P75: 179.54165 | Q75: 179.54165 | R75: 179.54165 | S75: 179.54165 | T75: 179.54165 | U75: 179.54165 | V75: 179.54165 | W75: 179.54165 | X75: 179.54165 | Y75: 179.54165 | Z75: 179.54165 | AA75: 179.54165 | AB75: 179.54165 | AC75: 179.54165 | AD75: 179.54165 | AE75: 179.54165 | AF75: 179.54165 | AG75: 179.54165 | AH75: 179.54165 | AI75: 179.54165 | AJ75: 179.54165 | AK75: 179.54165 | AL75: 179.54165 | AM75: 179.54165 | AN75: 179.54165 | AO75: 179.54165 | AP75: 179.54165 | AQ75: 179.54165 | AR75: 179.54165 | AS75: 179.54165 | AT75: 179.54165 | AU75: 179.54165 | AV75: 179.54165 | AW75: 179.54165 | AX75: 179.54165 | AY75: 179.54165 | AZ75: 179.54165 | BA75: 179.54165 | BB75: 179.54165 | BC75: 179.54165 | BD75: 179.54165 | BL75: =AVERAGE(AL75:AW75) -> 179.54165 | BM75: =AVERAGE(AX75:BI75) -> 179.54165 | BN75: =BM75/BL75-1 -> 0
A76: Water supply; sewerage, waste management and remediation activities | B76: 190.58608 | C76: 190.58608 | D76: 190.58608 | E76: 190.58608 | F76: 190.58608 | G76: 190.58608 | H76: 190.58608 | I76: 190.58608 | J76: 190.58608 | K76: 190.58608 | L76: 190.58608 | M76: 190.58608 | N76: 190.58608 | O76: 190.58608 | P76: 190.58608 | Q76: 190.58608 | R76: 190.58608 | S76: 190.58608 | T76: 190.58608 | U76: 190.58608 | V76: 190.58608 | W76: 190.58608 | X76: 190.58608 | Y76: 190.58608 | Z76: 190.58608 | AA76: 190.58608 | AB76: 190.58608 | AC76: 190.58608 | AD76: 190.58608 | AE76: 190.58608 | AF76: 190.58608 | AG76: 190.58608 | AH76: 190.58608 | AI76: 190.58608 | AJ76: 190.58608 | AK76: 190.58608 | AL76: 190.58608 | AM76: 190.58608 | AN76: 190.58608 | AO76: 190.58608 | AP76: 190.58608 | AQ76: 190.58608 | AR76: 190.58608 | AS76: 190.58608 | AT76: 190.58608 | AU76: 190.58608 | AV76: 190.58608 | AW76: 190.58608 | AX76: 190.58608 | AY76: 190.58608 | AZ76: 190.58608 | BA76: 190.58608 | BB76: 190.58608 | BC76: 190.58608 | BD76: 190.58608 | BL76: =AVERAGE(AL76:AW76) -> 190.58608 | BM76: =AVERAGE(AX76:BI76) -> 190.58608 | BN76: =BM76/BL76-1 -> 0
A77: Water collection, treatment and supply | B77: 100 | C77: 100 | D77: 100 | E77: 100 | F77: 100 | G77: 100 | H77: 100 | I77: 100 | J77: 100 | K77: 100 | L77: 100 | M77: 100 | N77: 100 | O77: 100 | P77: 100 | Q77: 100 | R77: 100 | S77: 100 | T77: 100 | U77: 100 | V77: 100 | W77: 100 | X77: 100 | Y77: 100 | Z77: 100 | AA77: 100 | AB77: 100 | AC77: 100 | AD77: 100 | AE77: 100 | AF77: 100 | AG77: 100 | AH77: 100 | AI77: 100 | AJ77: 100 | AK77: 100 | AL77: 100 | AM77: 100 | AN77: 100 | AO77: 100 | AP77: 100 | AQ77: 100 | AR77: 100 | AS77: 100 | AT77: 100 | AU77: 100 | AV77: 100 | AW77: 100 | AX77: 100 | AY77: 100 | AZ77: 100 | BA77: 100 | BB77: 100 | BC77: 100 | BD77: 100 | BE77: 100 | BF77: 100 | BG77: 100 | BH77: 100 | BI77: 100 | BL77: =AVERAGE(AL77:AW77) -> 100 | BM77: =AVERAGE(AX77:BI77) -> 100 | BN77: =BM77/BL77-1 -> 0
A78: Water collection, treatment and supply | B78: 190.58608 | C78: 190.58608 | D78: 190.58608 | E78: 190.58608 | F78: 190.58608 | G78: 190.58608 | H78: 190.58608 | I78: 190.58608 | J78: 190.58608 | K78: 190.58608 | L78: 190.58608 | M78: 190.58608 | N78: 190.58608 | O78: 190.58608 | P78: 190.58608 | Q78: 190.58608 | R78: 190.58608 | S78: 190.58608 | T78: 190.58608 | U78: 190.58608 | V78: 190.58608 | W78: 190.58608 | X78: 190.58608 | Y78: 190.58608 | Z78: 190.58608 | AA78: 190.58608 | AB78: 190.58608 | AC78: 190.58608 | AD78: 190.58608 | AE78: 190.58608 | AF78: 190.58608 | AG78: 190.58608 | AH78: 190.58608 | AI78: 190.58608 | AJ78: 190.58608 | AK78: 190.58608 | AL78: 190.58608 | AM78: 190.58608 | AN78: 190.58608 | AO78: 190.58608 | AP78: 190.58608 | AQ78: 190.58608 | AR78: 190.58608 | AS78: 190.58608 | AT78: 190.58608 | AU78: 190.58608 | AV78: 190.58608 | AW78: 190.58608 | AX78: 190.58608 | AY78: 190.58608 | AZ78: 190.58608 | BA78: 190.58608 | BB78: 190.58608 | BC78: 190.58608 | BD78: 190.58608 | BL78: =AVERAGE(AL78:AW78) -> 190.58608 | BM78: =AVERAGE(AX78:BI78) -> 190.58608 | BN78: =BM78/BL78-1 -> 0
A79: Water collection, treatment and supply | B79: 190.58608 | C79: 190.58608 | D79: 190.58608 | E79: 190.58608 | F79: 190.58608 | G79: 190.58608 | H79: 190.58608 | I79: 190.58608 | J79: 190.58608 | K79: 190.58608 | L79: 190.58608 | M79: 190.58608 | N79: 190.58608 | O79: 190.58608 | P79: 190.58608 | Q79: 190.58608 | R79: 190.58608 | S79: 190.58608 | T79: 190.58608 | U79: 190.58608 | V79: 190.58608 | W79: 190.58608 | X79: 190.58608 | Y79: 190.58608 | Z79: 190.58608 | AA79: 190.58608 | AB79: 190.58608 | AC79: 190.58608 | AD79: 190.58608 | AE79: 190.58608 | AF79: 190.58608 | AG79: 190.58608 | AH79: 190.58608 | AI79: 190.58608 | AJ79: 190.58608 | AK79: 190.58608 | AL79: 190.58608 | AM79: 190.58608 | AN79: 190.58608 | AO79: 190.58608 | AP79: 190.58608 | AQ79: 190.58608 | AR79: 190.58608 | AS79: 190.58608 | AT79: 190.58608 | AU79: 190.58608 | AV79: 190.58608 | AW79: 190.58608 | AX79: 190.58608 | AY79: 190.58608 | AZ79: 190.58608 | BA79: 190.58608 | BB79: 190.58608 | BC79: 190.58608 | BD79: 190.58608 | BL79: =AVERAGE(AL79:AW79) -> 190.58608 | BM79: =AVERAGE(AX79:BI79) -> 190.58608 | BN79: =BM79/BL79-1 -> 0
A80: Information and communication | B80: 197.81178 | C80: 197.81178 | D80: 197.81178 | E80: 197.81178 | F80: 197.81178 | G80: 197.81178 | H80: 197.81178 | I80: 197.81178 | J80: 197.81178 | K80: 197.81178 | L80: 197.81178 | M80: 197.81178 | N80: 197.81178 | O80: 197.81178 | P80: 197.81178 | Q80: 197.81178 | R80: 197.81178 | S80: 197.81178 | T80: 197.81178 | U80: 197.81178 | V80: 197.81178 | W80: 197.81178 | X80: 197.81178 | Y80: 197.81178 | Z80: 197.81178 | AA80: 197.81178 | AB80: 197.81178 | AC80: 197.81178 | AD80: 197.81178 | AE80: 197.81178 | AF80: 197.81178 | AG80: 197.81178 | AH80: 197.81178 | AI80: 197.81178 | AJ80: 197.81178 | AK80: 197.81178 | AL80: 197.81178 | AM80: 197.81178 | AN80: 197.81178 | AO80: 197.81178 | AP80: 197.81178 | AQ80: 197.81178 | AR80: 197.81178 | AS80: 197.81178 | AT80: 197.81178 | AU80: 197.81178 | AV80: 197.81178 | AW80: 197.81178 | AX80: 197.81178 | AY80: 197.81178 | AZ80: 197.81178 | BA80: 197.81178 | BB80: 197.81178 | BC80: 197.81178 | BD80: 197.81178 | BL80: =AVERAGE(AL80:AW80) -> 197.81178 | BM80: =AVERAGE(AX80:BI80) -> 197.81178 | BN80: =BM80/BL80-1 -> 0
A81: Publishing activities | B81: 197.81178 | C81: 197.81178 | D81: 197.81178 | E81: 197.81178 | F81: 197.81178 | G81: 197.81178 | H81: 197.81178 | I81: 197.81178 | J81: 197.81178 | K81: 197.81178 | L81: 197.81178 | M81: 197.81178 | N81: 197.81178 | O81: 197.81178 | P81: 197.81178 | Q81: 197.81178 | R81: 197.81178 | S81: 197.81178 | T81: 197.81178 | U81: 197.81178 | V81: 197.81178 | W81: 197.81178 | X81: 197.81178 | Y81: 197.81178 | Z81: 197.81178 | AA81: 197.81178 | AB81: 197.81178 | AC81: 197.81178 | AD81: 197.81178 | AE81: 197.81178 | AF81: 197.81178 | AG81: 197.81178 | AH81: 197.81178 | AI81: 197.81178 | AJ81: 197.81178 | AK81: 197.81178 | AL81: 197.81178 | AM81: 197.81178 | AN81: 197.81178 | AO81: 197.81178 | AP81: 197.81178 | AQ81: 197.81178 | AR81: 197.81178 | AS81: 197.81178 | AT81: 197.81178 | AU81: 197.81178 | AV81: 197.81178 | AW81: 197.81178 | AX81: 197.81178 | AY81: 197.81178 | AZ81: 197.81178 | BA81: 197.81178 | BB81: 197.81178 | BC81: 197.81178 | BD81: 197.81178 | BL81: =AVERAGE(AL81:AW81) -> 197.81178 | BM81: =AVERAGE(AX81:BI81) -> 197.81178 | BN81: =BM81/BL81-1 -> 0
A82: Publishing of books, periodicals and other publishing activities | B82: 197.81178 | C82: 197.81178 | D82: 197.81178 | E82: 197.81178 | F82: 197.81178 | G82: 197.81178 | H82: 197.81178 | I82: 197.81178 | J82: 197.81178 | K82: 197.81178 | L82: 197.81178 | M82: 197.81178 | N82: 197.81178 | O82: 197.81178 | P82: 197.81178 | Q82: 197.81178 | R82: 197.81178 | S82: 197.81178 | T82: 197.81178 | U82: 197.81178 | V82: 197.81178 | W82: 197.81178 | X82: 197.81178 | Y82: 197.81178 | Z82: 197.81178 | AA82: 197.81178 | AB82: 197.81178 | AC82: 197.81178 | AD82: 197.81178 | AE82: 197.81178 | AF82: 197.81178 | AG82: 197.81178 | AH82: 197.81178 | AI82: 197.81178 | AJ82: 197.81178 | AK82: 197.81178 | AL82: 197.81178 | AM82: 197.81178 | AN82: 197.81178 | AO82: 197.81178 | AP82: 197.81178 | AQ82: 197.81178 | AR82: 197.81178 | AS82: 197.81178 | AT82: 197.81178 | AU82: 197.81178 | AV82: 197.81178 | AW82: 197.81178 | AX82: 197.81178 | AY82: 197.81178 | AZ82: 197.81178 | BA82: 197.81178 | BB82: 197.81178 | BC82: 197.81178 | BD82: 197.81178 | BL82: =AVERAGE(AL82:AW82) -> 197.81178 | BM82: =AVERAGE(AX82:BI82) -> 197.81178 | BN82: =BM82/BL82-1 -> 0
A83: Book publishing | B83: 185.78761 | C83: 185.78761 | D83: 185.78761 | E83: 185.78761 | F83: 185.78761 | G83: 185.78761 | H83: 185.78761 | I83: 185.78761 | J83: 185.78761 | K83: 185.78761 | L83: 185.78761 | M83: 185.78761 | N83: 185.78761 | O83: 185.78761 | P83: 185.78761 | Q83: 185.78761 | R83: 185.78761 | S83: 185.78761 | T83: 185.78761 | U83: 185.78761 | V83: 185.78761 | W83: 185.78761 | X83: 185.78761 | Y83: 185.78761 | Z83: 185.78761 | AA83: 185.78761 | AB83: 185.78761 | AC83: 185.78761 | AD83: 185.78761 | AE83: 185.78761 | AF83: 185.78761 | AG83: 185.78761 | AH83: 185.78761 | AI83: 185.78761 | AJ83: 185.78761 | AK83: 185.78761 | AL83: 185.78761 | AM83: 185.78761 | AN83: 185.78761 | AO83: 185.78761 | AP83: 185.78761 | AQ83: 185.78761 | AR83: 185.78761 | AS83: 185.78761 | AT83: 185.78761 | AU83: 185.78761 | AV83: 185.78761 | AW83: 185.78761 | AX83: 185.78761 | AY83: 185.78761 | AZ83: 185.78761 | BA83: 185.78761 | BB83: 185.78761 | BC83: 185.78761 | BD83: 185.78761 | BL83: =AVERAGE(AL83:AW83) -> 185.78761 | BM83: =AVERAGE(AX83:BI83) -> 185.78761 | BN83: =BM83/BL83-1 -> 0
A84: Publishing of newspapers, journals and periodicals | B84: 200.05204 | C84: 200.05204 | D84: 200.05204 | E84: 200.05204 | F84: 200.05204 | G84: 200.05204 | H84: 200.05204 | I84: 200.05204 | J84: 200.05204 | K84: 200.05204 | L84: 200.05204 | M84: 200.05204 | N84: 200.05204 | O84: 200.05204 | P84: 200.05204 | Q84: 200.05204 | R84: 200.05204 | S84: 200.05204 | T84: 200.05204 | U84: 200.05204 | V84: 200.05204 | W84: 200.05204 | X84: 200.05204 | Y84: 200.05204 | Z84: 200.05204 | AA84: 200.05204 | AB84: 200.05204 | AC84: 200.05204 | AD84: 200.05204 | AE84: 200.05204 | AF84: 200.05204 | AG84: 200.05204 | AH84: 200.05204 | AI84: 200.05204 | AJ84: 200.05204 | AK84: 200.05204 | AL84: 200.05204 | AM84: 200.05204 | AN84: 200.05204 | AO84: 200.05204 | AP84: 200.05204 | AQ84: 200.05204 | AR84: 200.05204 | AS84: 200.05204 | AT84: 200.05204 | AU84: 200.05204 | AV84: 200.05204 | AW84: 200.05204 | AX84: 200.05204 | AY84: 200.05204 | AZ84: 200.05204 | BA84: 200.05204 | BB84: 200.05204 | BC84: 200.05204 | BD84: 200.05204 | BL84: =AVERAGE(AL84:AW84) -> 200.05204 | BM84: =AVERAGE(AX84:BI84) -> 200.05204 | BN84: =BM84/BL84-1 -> 0

Sheet GDP
B1: 2020 | F1: 2021 | J1: 2022 | N1: 2023 | R1: 2024 | W1: 2025
B2: Q1 | C2: Q2 | D2: Q3 | E2: Q4 | F2: Q1 | G2: Q2 | H2: Q3 | I2: Q4 | J2: Q1 | K2: Q2 | L2: Q3 | M2: Q4 | N2: Q1 | O2: Q2 | P2: Q3 | Q2: Q4 | R2: Q1 | S2: Q2 | T2: Q3 | U2: Q4 | V2: Tot | W2: Q1 | X2: Q2 | Y2: Q3 | Z2: Q4 | AA2: Average
A3: GROSS DOMESTIC PRODUCT (GDP) | B3: 3621 | C3: 3451 | D3: 3258 | E3: 4042 | F3: 3707 | G3: 4070 | H3: 3454 | I3: 4350 | J3: 4074 | K3: 4541 | L3: 3852 | M3: 4644 | N3: 4386 | O3: 4659 | P3: 4261 | Q3: 5270 | R3: 4741 | S3: 5137 | T3: 4550 | U3: 5489 | V3: =AVERAGE(R3:T3) -> 4809.3333 | W3: 5052 | X3: 5540 | Y3: 5089 | AA3: =AVERAGE(W3:Y3) -> 5227 | AB3: =AA3/V3-1 -> 0.086845024
A5: AGRICULTURE, FORESTRY & FISHING | B5: 871 | C5: 1069 | D5: 547 | E5: 1181 | F5: 892 | G5: 1112 | H5: 595 | I5: 1210 | J5: 888 | K5: 1121 | L5: 606 | M5: 1211 | N5: 924 | O5: 1138 | P5: 658 | Q5: 1293 | R5: 978 | S5: 1180 | T5: 677 | U5: 1307 | V5: =AVERAGE(R5:T5) -> 945 | W5: 1014 | X5: 1269 | Y5: 747 | AA5: =AVERAGE(W5:Y5) -> 1010 | AB5: =AA5/V5-1 -> 0.068783069
A6: Food crops | B6: 543 | C6: 745 | D6: 189 | E6: 804 | F6: 543 | G6: 750 | H6: 195 | I6: 801 | J6: 537 | K6: 723 | L6: 203 | M6: 778 | N6: 554 | O6: 736 | P6: 242 | Q6: 831 | R6: 574 | S6: 752 | T6: 219 | U6: 828 | V6: =AVERAGE(R6:T6) -> 515 | W6: 583 | X6: 777 | Y6: 228 | AA6: =AVERAGE(W6:Y6) -> 529.33333 | AB6: =AA6/V6-1 -> 0.027831715
A7: Export crops | B7: 59 | C7: 55 | D7: 97 | E7: 99 | F7: 63 | G7: 78 | H7: 101 | I7: 117 | J7: 47 | K7: 84 | L7: 96 | M7: 119 | N7: 57 | O7: 83 | P7: 85 | Q7: 120 | R7: 63 | S7: 81 | T7: 99 | U7: 109 | V7: =AVERAGE(R7:T7) -> 81 | W7: 63 | X7: 115 | Y7: 133 | AA7: =AVERAGE(W7:Y7) -> 103.66667 | AB7: =AA7/V7-1 -> 0.27983539
A8: Livestock & livestock products | B8: 101 | C8: 104 | D8: 107 | E8: 110 | F8: 110 | G8: 107 | H8: 119 | I8: 110 | J8: 117 | K8: 123 | L8: 116 | M8: 120 | N8: 119 | O8: 122 | P8: 130 | Q8: 139 | R8: 137 | S8: 139 | T8: 148 | U8: 157 | V8: =AVERAGE(R8:T8) -> 141.33333 | W8: 152 | X8: 157 | Y8: 157 | AA8: =AVERAGE(W8:Y8) -> 155.33333 | AB8: =AA8/V8-1 -> 0.099056604
A9: Forestry | B9: 154 | C9: 154 | D9: 158 | E9: 160 | F9: 162 | G9: 162 | H9: 166 | I9: 168 | J9: 172 | K9: 175 | L9: 177 | M9: 180 | N9: 180 | O9: 184 | P9: 188 | Q9: 190 | R9: 192 | S9: 194 | T9: 197 | U9: 200 | V9: =AVERAGE(R9:T9) -> 194.33333 | W9: 202 | X9: 205 | Y9: 209 | AA9: =AVERAGE(W9:Y9) -> 205.33333 | AB9: =AA9/V9-1 -> 0.056603774
A10: Fishing | B10: 14 | C10: 7 | D10: 11 | E10: 14 | F10: 14 | G10: 14 | H10: 14 | I10: 14 | J10: 14 | K10: 14 | L10: 14 | M10: 14 | N10: 14 | O10: 14 | P10: 14 | Q10: 13 | R10: 12 | S10: 13 | T10: 14 | U10: 14 | V10: =AVERAGE(R10:T10) -> 13 | W10: 15 | X10: 16 | Y10: 19 | AA10: =AVERAGE(W10:Y10) -> 16.666667 | AB10: =AA10/V10-1 -> 0.28205128
A11: INDUSTRY | B11: 721 | C11: 633 | D11: 771 | E11: 823 | F11: 790 | G11: 731 | H11: 736 | I11: 842 | J11: 943 | K11: 1015 | L11: 849 | M11: 960 | N11: 966 | O11: 989 | P11: 982 | Q11: 1152 | R11: 1136 | S11: 1120 | T11: 993 | U11: 1147 | V11: =AVERAGE(R11:T11) -> 1083 | W11: 1193 | X11: 1198 | Y11: 1159 | AA11: =AVERAGE(W11:Y11) -> 1183.3333 | AB11: =AA11/V11-1 -> 0.09264389
A12: Mining & quarrying | B12: 58 | C12: 42 | D12: 58 | E12: 67 | F12: 60 | G12: 54 | H12: 61 | I12: 63 | J12: 74 | K12: 81 | L12: 72 | M12: 78 | N12: 73 | O12: 78 | P12: 83 | Q12: 93 | R12: 94 | S12: 86 | T12: 87 | U12: 87 | V12: =AVERAGE(R12:T12) -> 89 | W12: 94 | X12: 96 | Y12: 99 | AA12: =AVERAGE(W12:Y12) -> 96.333333 | AB12: =AA12/V12-1 -> 0.082397004
A13: TOTAL MANUFACTURING | B13: 283 | C13: 266 | D13: 310 | E13: 321 | F13: 307 | G13: 342 | H13: 274 | I13: 349 | J13: 338 | K13: 383 | L13: 296 | M13: 373 | N13: 391 | O13: 387 | P13: 329 | Q13: 418 | R13: 388 | S13: 427 | T13: 356 | U13: 448 | V13: =AVERAGE(R13:T13) -> 390.33333 | W13: 422 | X13: 459 | Y13: 406 | AA13: =AVERAGE(W13:Y13) -> 429 | AB13: =AA13/V13-1 -> 0.099060632
A14: Of which: Food | B14: 56 | C14: 56 | D14: 52 | E14: 55 | F14: 60 | G14: 89 | H14: 52 | I14: 92 | J14: 65 | K14: 107 | L14: 58 | M14: 103 | N14: 79 | O14: 109 | P14: 63 | Q14: 125 | R14: 82 | S14: 115 | T14: 67 | U14: 119 | V14: =AVERAGE(R14:T14) -> 88 | W14: 86 | X14: 127 | Y14: 75 | AA14: =AVERAGE(W14:Y14) -> 96 | AB14: =AA14/V14-1 -> 0.090909091
A15: Beverages & tobacco | B15: 117 | C15: 110 | D15: 134 | E15: 132 | F15: 122 | G15: 98 | H15: 76 | I15: 115 | J15: 137 | K15: 122 | L15: 86 | M15: 117 | N15: 139 | O15: 117 | P15: 88 | Q15: 116 | R15: 142 | S15: 125 | T15: 92 | U15: 127 | V15: =AVERAGE(R15:T15) -> 119.66667 | W15: 146 | X15: 121 | Y15: 99 | AA15: =AVERAGE(W15:Y15) -> 122 | AB15: =AA15/V15-1 -> 0.019498607
... A42: Taxes less subsidies on products | B42: 209 | C42: 199 | D42: 199 | E42: 210 | F42: 215 | G42: 252 | H42: 192 | I42: 244 | J42: 230 | K42: 261 | L42: 235 | M42: 224 | N42: 220 | O42: 244 | P42: 231 | Q42: 217 | R42: 229 | S42: 273 | T42: 253 | U42: 230 | V42: =AVERAGE(R42:T42) -> 251.66667 | W42: 245 | X42: 288 | Y42: 305 | AA42: =AVERAGE(W42:Y42) -> 279.33333 | AB42: =AA42/V42-1 -> 0.10993377
B45: 2020 | F45: 2021 | J45: 2022 | N45: 2023
B46: Q1 | C46: Q2 | D46: Q3 | E46: Q4 | F46: Q1 | G46: Q2 | H46: Q3 | I46: Q4 | J46: Q1 | K46: Q2 | L46: Q3 | N46: Q1 | O46: Q2 | P46: Q3
A47: GROSS DOMESTIC PRODUCT (GDP) | B47: 2249 | C47: 2019 | D47: 2238 | E47: 2331 | F47: 2329 | G47: 2435 | H47: 2464 | I47: 2572 | J47: 2510 | K47: 2615 | L47: 2708 | M47: 2708 | N47: 2741 | O47: 2780 | P47: 2910
A49: AGRICULTURE, FORESTRY & FISHING | B49: =B5/B$47*100 -> 38.728324 | C49: =C5/C$47*100 -> 52.947003 | D49: =D5/D$47*100 -> 24.441466 | E49: =E5/E$47*100 -> 50.664951 | F49: =F5/F$47*100 -> 38.299699 | G49: =G5/G$47*100 -> 45.667351 | H49: =H5/H$47*100 -> 24.147727 | I49: =I5/I$47*100 -> 47.045101 | ... M49: =M5/M$47*100 -> 44.71935 | N49: =N5/$N$47*100 -> 33.710325 | O49: =O5/$O$47*100 -> 40.935252 | P49: =P5/$P$47*100 -> 22.611684
A50: Food crops | B50: =B6/B$47*100 -> 24.144064 | C50: =C6/C$47*100 -> 36.899455 | D50: =D6/D$47*100 -> 8.4450402 | E50: =E6/E$47*100 -> 34.491634 | F50: =F6/F$47*100 -> 23.314727 | G50: =G6/G$47*100 -> 30.800821 | H50: =H6/H$47*100 -> 7.913961 | I50: =I6/I$47*100 -> 31.143079 | ... K50: =K6/K$47*100 -> 27.648184 | L50: 13.3 | M50: =M6/M$47*100 -> 28.72969 | N50: =N6/$N$47*100 -> 20.211602 | O50: =O6/$O$47*100 -> 26.47482 | P50: =P6/$P$47*100 -> 8.3161512
A51: Export crops | B51: =B7/B$47*100 -> 2.6233882 | C51: =C7/C$47*100 -> 2.7241209 | D51: =D7/D$47*100 -> 4.334227 | E51: =E7/E$47*100 -> 4.2471042 | F51: =F7/F$47*100 -> 2.7050236 | G51: =G7/G$47*100 -> 3.2032854 | H51: =H7/H$47*100 -> 4.099026 | I51: =I7/I$47*100 -> 4.5489891 | ... K51: =K7/K$47*100 -> 3.2122371 | L51: 1.8 | M51: =M7/M$47*100 -> 4.394387 | N51: =N7/$N$47*100 -> 2.079533 | O51: =O7/$O$47*100 -> 2.9856115 | P51: =P7/$P$47*100 -> 2.9209622
A52: Livestock & livestock products | B52: =B8/B$47*100 -> 4.4908848 | C52: =C8/C$47*100 -> 5.1510649 | D52: =D8/D$47*100 -> 4.7810545 | E52: =E8/E$47*100 -> 4.7190047 | F52: =F8/F$47*100 -> 4.7230571 | G52: =G8/G$47*100 -> 4.3942505 | H52: =H8/H$47*100 -> 4.8295455 | I52: =I8/I$47*100 -> 4.2768274 | ... K52: =K8/K$47*100 -> 4.7036329 | L52: 3.3 | M52: =M8/M$47*100 -> 4.4313146 | N52: =N8/$N$47*100 -> 4.3414812 | O52: =O8/$O$47*100 -> 4.3884892 | P52: =P8/$P$47*100 -> 4.467354
A53: Forestry | B53: =B9/B$47*100 -> 6.8474878 | C53: =C9/C$47*100 -> 7.6275384 | D53: =D9/D$47*100 -> 7.0598749 | E53: =E9/E$47*100 -> 6.8640069 | F53: =F9/F$47*100 -> 6.955775 | G53: =G9/G$47*100 -> 6.6529774 | H53: =H9/H$47*100 -> 6.737013 | I53: =I9/I$47*100 -> 6.5318818 | ... K53: =K9/K$47*100 -> 6.6921606 | L53: 5.5 | M53: =M9/M$47*100 -> 6.6469719 | N53: =N9/$N$47*100 -> 6.5669464 | O53: =O9/$O$47*100 -> 6.618705 | P53: =P9/$P$47*100 -> 6.4604811
A54: Fishing | B54: =B10/B$47*100 -> 0.62249889 | C54: =C10/C$47*100 -> 0.34670629 | D54: =D10/D$47*100 -> 0.49151028 | E54: =E10/E$47*100 -> 0.6006006 | F54: =F10/F$47*100 -> 0.60111636 | G54: =G10/G$47*100 -> 0.57494867 | H54: =H10/H$47*100 -> 0.56818182 | I54: =I10/I$47*100 -> 0.54432348 | ... K54: =K10/K$47*100 -> 0.53537285 | L54: 0.4 | M54: =M10/M$47*100 -> 0.51698671 | N54: =N10/$N$47*100 -> 0.5107625 | O54: =O10/$O$47*100 -> 0.50359712 | P54: =P10/$P$47*100 -> 0.48109966
A55: INDUSTRY | B55: =B11/B$47*100 -> 32.058693 | C55: =C11/C$47*100 -> 31.352155 | D55: =D11/D$47*100 -> 34.450402 | E55: =E11/E$47*100 -> 35.306735 | F55: =F11/F$47*100 -> 33.920137 | G55: =G11/G$47*100 -> 30.020534 | H55: =H11/H$47*100 -> 29.87013 | I55: =I11/I$47*100 -> 32.73717 | ... K55: =K11/K$47*100 -> 38.814532 | L55: 21 | M55: =M11/M$47*100 -> 35.450517 | N55: =N11/$N$47*100 -> 35.242612 | O55: =O11/$O$47*100 -> 35.57554 | P55: =P11/$P$47*100 -> 33.745704
A56: Mining & quarrying | B56: =B12/B$47*100 -> 2.578924 | C56: =C12/C$47*100 -> 2.0802377 | D56: =D12/D$47*100 -> 2.5915996 | E56: =E12/E$47*100 -> 2.8743029 | F56: =F12/F$47*100 -> 2.576213 | G56: =G12/G$47*100 -> 2.2176591 | H56: =H12/H$47*100 -> 2.4756494 | I56: =I12/I$47*100 -> 2.4494557 | ... K56: =K12/K$47*100 -> 3.0975143 | L56: 2.5 | M56: =M12/M$47*100 -> 2.8803545 | N56: =N12/$N$47*100 -> 2.6632616 | O56: =O12/$O$47*100 -> 2.8057554 | P56: =P12/$P$47*100 -> 2.8522337
A57: TOTAL MANUFACTURING | B57: =B13/B$47*100 -> 12.58337 | C57: =C13/C$47*100 -> 13.174839 | D57: =D13/D$47*100 -> 13.851653 | E57: =E13/E$47*100 -> 13.770914 | F57: =F13/F$47*100 -> 13.181623 | G57: =G13/G$47*100 -> 14.045175 | H57: =H13/H$47*100 -> 11.12013 | I57: =I13/I$47*100 -> 13.569207 | ... K57: =K13/K$47*100 -> 14.646272 | L57: 9.7 | M57: =M13/M$47*100 -> 13.774003 | N57: =N13/$N$47*100 -> 14.264867 | O57: =O13/$O$47*100 -> 13.920863 | P57: =P13/$P$47*100 -> 11.305842
A58: Of which: Food | B58: =B14/B$47*100 -> 2.4899956 | C58: =C14/C$47*100 -> 2.7736503 | D58: =D14/D$47*100 -> 2.3235031 | E58: =E14/E$47*100 -> 2.3595024 | F58: =F14/F$47*100 -> 2.576213 | G58: =G14/G$47*100 -> 3.6550308 | H58: =H14/H$47*100 -> 2.1103896 | I58: =I14/I$47*100 -> 3.5769829 | ... K58: =K14/K$47*100 -> 4.0917782 | L58: 3.9 | M58: =M14/M$47*100 -> 3.8035451 | N58: =N14/$N$47*100 -> 2.8821598 | O58: =O14/$O$47*100 -> 3.9208633 | P58: =P14/$P$47*100 -> 2.1649485
A59: Beverages & tobacco | B59: =B15/B$47*100 -> 5.2023121 | C59: =C15/C$47*100 -> 5.4482417 | D59: =D15/D$47*100 -> 5.9874888 | E59: =E15/E$47*100 -> 5.6628057 | F59: =F15/F$47*100 -> 5.2382997 | G59: =G15/G$47*100 -> 4.0246407 | H59: =H15/H$47*100 -> 3.0844156 | I59: =I15/I$47*100 -> 4.4712286 | ... K59: =K15/K$47*100 -> 4.665392 | L59: 2.1 | M59: =M15/M$47*100 -> 4.3205318 | N59: =N15/$N$47*100 -> 5.0711419 | O59: =O15/$O$47*100 -> 4.2086331 | P59: =P15/$P$47*100 -> 3.024055
A60: Textiles, clothing & leather goods | B60: =B16/B$47*100 -> 0.97821254 | C60: =C16/C$47*100 -> 0.94105993 | D60: =D16/D$47*100 -> 1.0723861 | E60: =E16/E$47*100 -> 1.1154011 | F60: =F16/F$47*100 -> 0.94461142 | G60: =G16/G$47*100 -> 1.026694 | H60: =H16/H$47*100 -> 1.0146104 | I60: =I16/I$47*100 -> 1.0497667 | ... K60: =K16/K$47*100 -> 1.0325048 | L60: 0.7 | M60: =M16/M$47*100 -> 1.1078287 | N60: =N16/$N$47*100 -> 0.98504196 | O60: =O16/$O$47*100 -> 1.0791367 | P60: =P16/$P$47*100 -> 1.0996564
A61: Wood & paper; printing | B61: =B17/B$47*100 -> 0.35571365 | C61: =C17/C$47*100 -> 0.34670629 | D61: =D17/D$47*100 -> 0.40214477 | E61: =E17/E$47*100 -> 0.42900043 | F61: =F17/F$47*100 -> 0.38643195 | G61: =G17/G$47*100 -> 0.45174538 | H61: =H17/H$47*100 -> 0.44642857 | I61: =I17/I$47*100 -> 0.46656299 | ... K61: =K17/K$47*100 -> 0.53537285 | L61: 0.3 | M61: =M17/M$47*100 -> 0.62776957 | N61: =N17/$N$47*100 -> 0.5107625 | O61: =O17/$O$47*100 -> 0.61151079 | P61: =P17/$P$47*100 -> 0.6185567
... A86: Taxes less subsidies on products | B86: =B42/B$47*100 -> 9.2930191 | C86: =C42/C$47*100 -> 9.8563645 | D86: =D42/D$47*100 -> 8.8918677 | E86: =E42/E$47*100 -> 9.009009 | F86: =F42/F$47*100 -> 9.2314298 | G86: =G42/G$47*100 -> 10.349076 | H86: =H42/H$47*100 -> 7.7922078 | I86: =I42/I$47*100 -> 9.4867807 | ... K86: =K42/K$47*100 -> 9.9808795 | L86: 7.7 | M86: =M42/M$47*100 -> 8.2717873 | N86: =N42/$N$47*100 -> 8.0262678 | O86: =O42/$O$47*100 -> 8.7769784 | P86: =P42/$P$47*100 -> 7.9381443

Sheet Quarterly IIP_Manu
B1: 2011 Q1 | C1: 2011 Q2 | D1: 2011 Q3 | E1: 2011 Q4 | F1: 2012 Q1 | G1: 2012 Q2 | H1: 2012 Q3 | I1: 2012 Q4 | J1: 2013 Q1 | K1: 2013 Q2 | L1: 2013 Q3 | M1: 2013 Q4 | N1: 2014 Q1 | O1: 2014 Q2 | P1: 2014 Q3 | Q1: 2014 Q4 | R1: 2015 Q1 | S1: 2015 Q2 | T1: 2015 Q3 | U1: 2015 Q4 | V1: 2016 Q1 | W1: 2016 Q2 | X1: 2016 Q3 | Y1: 2016 Q4 | Z1: 2017 Q1 | AA1: 2017 Q2 | AB1: 2017 Q3 | AC1: 2017 Q4 | AD1: 2018 Q1 | AE1: 2018 Q2 | AF1: 2018 Q3 | AG1: 2018 Q4 | AH1: 2019 Q1 | AI1: 2019 Q2 | AJ1: 2019 Q3 | AK1: 2019 Q4 | AL1: 2020 Q1 | AM1: 2020 Q2 | AN1: 2020 Q3 | AO1: 2020 Q4 | AP1: 2021 Q1 | AQ1: 2021 Q2 | AR1: 2021 Q3 | AS1: 2021 Q4 | AT1: 2022 Q1 | AU1: 2022 Q2 | AV1: 2022 Q3 | AW1: 2022 Q4 | AX1: 2023 Q1 | AY1: 2023 Q2 | AZ1: 2023Q3 | BA1: 2023Q4 | BB1: 2024 Q1 | BC1: 2024 Q2 | BD1: 2024Q3 | BE1: 2024Q4 | BF1: 2025Q1 | BG1: 2025Q2 | BH1: 2025Q3 | BI1: 2025Q4 | BJ1: S1 24 | BK1: S2 24 | BL1: Total | BM1: S1 25 | BN1: S2 25 | BO1: Total | BQ1: 2011 Q1 | BR1: 2011 Q2 | BS1: 2011 Q3 | BT1: 2011 Q4 | BU1: 2012 Q1 | BV1: 2012 Q2 | BW1: 2012 Q3 | BX1: 2012 Q4 | BY1: 2013 Q1 | BZ1: 2013 Q2 | CA1: 2013 Q3 | CB1: 2013 Q4 | CC1: 2014 Q1 | CD1: 2014 Q2 | CE1: 2014 Q3 | CF1: 2014 Q4 | CG1: 2015 Q1 | CH1: 2015 Q2 | CI1: 2015 Q3 | CJ1: 2015 Q4 | CK1: 2016 Q1 | CL1: 2016 Q2 | CM1: 2016 Q3 | CN1: 2016 Q4 | CO1: 2017 Q1 | CP1: 2017 Q2 | CQ1: 2017 Q3 | CR1: 2017 Q4 | CS1: 2018 Q1 | CT1: 2018 Q2 | CU1: 2018 Q3 | CV1: 2018 Q4 | CW1: 2019 Q1 | CX1: 2019 Q2 | CY1: 2019 Q3 | CZ1: 2019 Q4 | DA1: 2020 Q1 | DB1: 2020 Q2 | DC1: 2020 Q3 | DD1: 2020 Q4 | DE1: 2021 Q1 | DF1: 2021 Q2 | DG1: 2021 Q3 | DH1: 2021 Q4 | DI1: 2022 Q1 | DJ1: 2022 Q2 | DK1: 2022 Q3 | DL1: 2022 Q4 | DM1: 2023 Q1 | DN1: 2023 Q2 | DO1: 2023Q3 | DP1: 2023Q4 | DQ1: 2024 Q1 | DR1: 2024 Q2 | DS1: 2024 Q3 | DT1: 2024 Q4 | DU1: 2025Q1 | DV1: 2025Q2 | DW1: 2025Q3 | DX1: 2025Q4 | DY1: S1 23 | DZ1: S2 23 | EA1: Total | EB1: S1 24 | EC1: S2 24 | ED1: Total | EE1: S1 25 | EF1: S2 25 | EG1: Total
A2: Mining & quarrying | B2: 83.52177 | C2: 70.546089 | D2: 83.659792 | E2: 96.405702 | F2: 80.704282 | G2: 70.801789 | H2: 82.132373 | I2: 93.503247 | J2: 89.978894 | K2: 93.729827 | L2: 96.901544 | M2: 101.7044 | N2: 104.78437 | O2: 99.10591 | P2: 164.89622 | Q2: 109.90276 | R2: 101.15829 | S2: 101.25922 | T2: 126.68282 | U2: 125.87783 | V2: 111.09509 | W2: 116.16362 | X2: 150.76689 | Y2: 124.42899 | Z2: 145.83337 | AA2: 149.69749 | AB2: 162.26897 | AC2: 158.17283 | AD2: 120.20538 | AE2: 107.30042 | AF2: 92.838874 | AG2: 100.01875 | AH2: 96.195002 | AI2: 121.74139 | AJ2: 125.67417 | AK2: 222.4266 | AL2: 169.99215 | AM2: 67.536598 | AN2: 74.269971 | AO2: 67.710089 | AP2: 64.044032 | AQ2: 99.932548 | AR2: 97.973612 | AS2: 81.73267 | AT2: 58.371933 | AU2: 86.871351 | AV2: 120.17018 | AW2: 152.66649 | AX2: 92.929386 | AY2: 104.62861 | AZ2: 96.600773 | BA2: 103.70563 | BB2: 102.7995 | BC2: 81.369417 | BD2: 98.742319 | BE2: 117.08876 | BF2: 110.06837 | BG2: 89.710588 | BH2: 110.36255 | BI2: 115.35693 | BJ2: 92.084459 | BK2: 107.91554 | BL2: =ED2 -> 100 | BM2: 99.889481 | BN2: 112.85974 | BO2: =EG2 -> 106.37461 | BP2: Mining & quarrying | BQ2: =AVERAGE(BK18:BM18) -> 83.52177 | BR2: =AVERAGE(BN18:BP18) -> 70.546089 | BS2: =AVERAGE(BQ18:BS18) -> 83.659792 | BT2: =AVERAGE(BT18:BV18) -> 96.405702 | BU2: =AVERAGE(BW18:BY18) -> 80.704282 | BV2: =AVERAGE(BZ18:CB18) -> 70.801789 | BW2: =AVERAGE(CC18:CE18) -> 82.132373 | BX2: =AVERAGE(CF18:CH18) -> 93.503247 | BY2: =AVERAGE(CI18:CK18) -> 89.978894 | BZ2: =AVERAGE(CL18:CN18) -> 93.729827 | CA2: =AVERAGE(CO18:CQ18) -> 96.901544 | CB2: =AVERAGE(CR18:CT18) -> 101.7044 | CC2: =AVERAGE(CU18:CW18) -> 104.78437 | CD2: =AVERAGE(CX18:CZ18) -> 99.10591 | CE2: =AVERAGE(DA18:DC18) -> 164.89622 | CF2: =AVERAGE(DD18:DF18) -> 109.90276 | CG2: =AVERAGE(DG18:DI18) -> 101.15829 | CH2: =AVERAGE(DJ18:DL18) -> 101.25922 | CI2: =AVERAGE(DM18:DO18) -> 126.68282 | CJ2: =AVERAGE(DP18:DR18) -> 125.87783 | CK2: =AVERAGE(DS18:DU18) -> 111.09509 | CL2: =AVERAGE(DV18:DX18) -> 116.16362 | CM2: =AVERAGE(DY18:EA18) -> 150.76689 | CN2: =AVERAGE(EB18:ED18) -> 124.42899 | CO2: =AVERAGE(EE18:EG18) -> 145.83337 | CP2: =AVERAGE(EH18:EJ18) -> 149.69749 | CQ2: =AVERAGE(EK18:EM18) -> 162.26897 | CR2: =AVERAGE(EN18:EP18) -> 158.17283 | CS2: =AVERAGE(EQ18:ES18) -> 120.20538 | CT2: =AVERAGE(ET18:EV18) -> 107.30042 | CU2: =AVERAGE(EW18:EY18) -> 92.838874 | CV2: =AVERAGE(EZ18:FB18) -> 100.01875 | CW2: =AVERAGE(FC18:FE18) -> 96.195002 | CX2: =AVERAGE(FF18:FH18) -> 121.74139 | CY2: =AVERAGE(FI18:FK18) -> 125.67417 | CZ2: =AVERAGE(FL18:FN18) -> 222.4266 | DA2: =AVERAGE(FO18:FQ18) -> 169.99215 | DB2: =AVERAGE(FR18:FT18) -> 67.536598 | DC2: =AVERAGE(FU18:FW18) -> 74.269971 | DD2: =AVERAGE(FX18:FZ18) -> 67.710089 | DE2: =AVERAGE(GA18:GC18) -> 64.044032 | DF2: =AVERAGE(GD18:GF18) -> 99.932548 | DG2: =AVERAGE(GG18:GI18) -> 97.973612 | DH2: =AVERAGE(GJ18:GL18) -> 81.73267 | DI2: =AVERAGE(GM18:GO18) -> 58.371933 | DJ2: =AVERAGE(GP18:GR18) -> 86.871351 | DK2: =AVERAGE(GS18:GU18) -> 120.17018 | DL2: =AVERAGE(GV18:GX18) -> 152.66649 | DM2: =AVERAGE(GY18:HA18) -> 92.929386 | DN2: =AVERAGE(HB18:HD18) -> 104.62861 | DO2: =AVERAGE(HE18:HG18) -> 96.600773 | DP2: =AVERAGE(HH18:HJ18) -> 103.70563 | DQ2: =AVERAGE(HK18:HM18) -> 102.7995 | DR2: =AVERAGE(HN18:HP18) -> 81.369417 | DS2: =AVERAGE(HQ18:HS18) -> 98.742319 | DT2: =AVERAGE(HT18:HV18) -> 117.08876 | DU2: =AVERAGE(HW18:HY18) -> 110.06837 | DV2: =AVERAGE(HZ18:IB18) -> 89.710588 | DW2: =AVERAGE(IC18:IE18) -> 110.36255 | DX2: =AVERAGE(IF18:IH18) -> 115.35693 | DY2: =AVERAGE(DM2:DN2) -> 98.778996 | DZ2: =AVERAGE(DO2:DP2) -> 100.1532 | EA2: =AVERAGE(DY2:DZ2) -> 99.466098 | EB2: =AVERAGE(DQ2:DR2) -> 92.084459 | EC2: =AVERAGE(DS2:DT2) -> 107.91554 | ED2: =AVERAGE(EB2:EC2) -> 100 | EE2: =AVERAGE(DU2:DV2) -> 99.889481 | EF2: =AVERAGE(DW2:DX2) -> 112.85974 | EG2: =AVERAGE(EE2:EF2) -> 106.37461
A3: Manufacturing of food | B3: 28.209733 | C3: 30.78608 | D3: 48.682833 | E3: 45.437851 | F3: 39.262379 | G3: 42.302368 | H3: 50.866064 | I3: 53.029554 | J3: 38.844461 | K3: 45.681144 | L3: 55.993281 | M3: 49.589869 | N3: 44.651618 | O3: 45.256646 | P3: 52.901327 | Q3: 59.653651 | R3: 51.29478 | S3: 58.637116 | T3: 63.824228 | U3: 66.203004 | V3: 59.831818 | W3: 56.849026 | X3: 67.266612 | Y3: 58.562541 | Z3: 57.944223 | AA3: 57.303542 | AB3: 63.74641 | AC3: 81.071088 | AD3: 91.217229 | AE3: 89.247225 | AF3: 87.458198 | AG3: 92.696791 | AH3: 81.748594 | AI3: 80.130245 | AJ3: 77.961147 | AK3: 84.126017 | AL3: 68.440119 | AM3: 71.269793 | AN3: 75.615286 | AO3: 74.250933 | AP3: 66.942157 | AQ3: 71.380962 | AR3: 94.886218 | AS3: 108.57056 | AT3: 94.747982 | AU3: 87.838795 | AV3: 114.1702 | AW3: 103.05302 | AX3: 83.957171 | AY3: 86.16382 | AZ3: 96.071847 | BA3: 89.71776 | BB3: 86.5745 | BC3: 107.07182 | BD3: 100.93619 | BE3: 105.41749 | BF3: 94.88154 | BG3: 119.13795 | BH3: 103.09612 | BI3: 108.58213 | BJ3: 96.823158 | BK3: 103.17684 | BL3: =ED3 -> 100 | BM3: 107.00974 | BN3: 105.83912 | BO3: =EG3 -> 106.42443 | BP3: Manufacturing of food | BQ3: =AVERAGE(BK19:BM19) -> 28.209733 | BR3: =AVERAGE(BN19:BP19) -> 30.78608 | BS3: =AVERAGE(BQ19:BS19) -> 48.682833 | BT3: =AVERAGE(BT19:BV19) -> 45.437851 | BU3: =AVERAGE(BW19:BY19) -> 39.262379 | BV3: =AVERAGE(BZ19:CB19) -> 42.302368 | BW3: =AVERAGE(CC19:CE19) -> 50.866064 | BX3: =AVERAGE(CF19:CH19) -> 53.029554 | BY3: =AVERAGE(CI19:CK19) -> 38.844461 | BZ3: =AVERAGE(CL19:CN19) -> 45.681144 | CA3: =AVERAGE(CO19:CQ19) -> 55.993281 | CB3: =AVERAGE(CR19:CT19) -> 49.589869 | CC3: =AVERAGE(CU19:CW19) -> 44.651618 | CD3: =AVERAGE(CX19:CZ19) -> 45.256646 | CE3: =AVERAGE(DA19:DC19) -> 52.901327 | CF3: =AVERAGE(DD19:DF19) -> 59.653651 | CG3: =AVERAGE(DG19:DI19) -> 51.29478 | CH3: =AVERAGE(DJ19:DL19) -> 58.637116 | CI3: =AVERAGE(DM19:DO19) -> 63.824228 | CJ3: =AVERAGE(DP19:DR19) -> 66.203004 | CK3: =AVERAGE(DS19:DU19) -> 59.831818 | CL3: =AVERAGE(DV19:DX19) -> 56.849026 | CM3: =AVERAGE(DY19:EA19) -> 67.266612 | CN3: =AVERAGE(EB19:ED19) -> 58.562541 | CO3: =AVERAGE(EE19:EG19) -> 57.944223 | CP3: =AVERAGE(EH19:EJ19) -> 57.303542 | CQ3: =AVERAGE(EK19:EM19) -> 63.74641 | CR3: =AVERAGE(EN19:EP19) -> 81.071088 | CS3: =AVERAGE(EQ19:ES19) -> 91.217229 | CT3: =AVERAGE(ET19:EV19) -> 89.247225 | CU3: =AVERAGE(EW19:EY19) -> 87.458198 | CV3: =AVERAGE(EZ19:FB19) -> 92.696791 | CW3: =AVERAGE(FC19:FE19) -> 81.748594 | CX3: =AVERAGE(FF19:FH19) -> 80.130245 | CY3: =AVERAGE(FI19:FK19) -> 77.961147 | CZ3: =AVERAGE(FL19:FN19) -> 84.126017 | DA3: =AVERAGE(FO19:FQ19) -> 68.440119 | DB3: =AVERAGE(FR19:FT19) -> 71.269793 | DC3: =AVERAGE(FU19:FW19) -> 75.615286 | DD3: =AVERAGE(FX19:FZ19) -> 74.250933 | DE3: =AVERAGE(GA19:GC19) -> 66.942157 | DF3: =AVERAGE(GD19:GF19) -> 71.380962 | DG3: =AVERAGE(GG19:GI19) -> 94.886218 | DH3: =AVERAGE(GJ19:GL19) -> 108.57056 | DI3: =AVERAGE(GM19:GO19) -> 94.747982 | DJ3: =AVERAGE(GP19:GR19) -> 87.838795 | DK3: =AVERAGE(GS19:GU19) -> 114.1702 | DL3: =AVERAGE(GV19:GX19) -> 103.05302 | DM3: =AVERAGE(GY19:HA19) -> 83.957171 | DN3: =AVERAGE(HB19:HD19) -> 86.16382 | DO3: =AVERAGE(HE19:HG19) -> 96.071847 | DP3: =AVERAGE(HH19:HJ19) -> 89.71776 | DQ3: =AVERAGE(HK19:HM19) -> 86.5745 | DR3: =AVERAGE(HN19:HP19) -> 107.07182 | DS3: =AVERAGE(HQ19:HS19) -> 100.93619 | DT3: =AVERAGE(HT19:HV19) -> 105.41749 | DU3: =AVERAGE(HW19:HY19) -> 94.88154 | DV3: =AVERAGE(HZ19:IB19) -> 119.13795 | DW3: =AVERAGE(IC19:IE19) -> 103.09612 | DX3: =AVERAGE(IF19:IH19) -> 108.58213 | DY3: =AVERAGE(DM3:DN3) -> 85.060495 | DZ3: =AVERAGE(DO3:DP3) -> 92.894804 | EA3: =AVERAGE(DY3:DZ3) -> 88.977649 | EB3: =AVERAGE(DQ3:DR3) -> 96.823158 | EC3: =AVERAGE(DS3:DT3) -> 103.17684 | ED3: =AVERAGE(EB3:EC3) -> 100 | EE3: =AVERAGE(DU3:DV3) -> 107.00974 | EF3: =AVERAGE(DW3:DX3) -> 105.83912 | EG3: =AVERAGE(EE3:EF3) -> 106.42443
A4: Manufacturing of beverages & tobacco | B4: 49.367867 | C4: 54.027455 | D4: 57.8443 | E4: 48.54216 | F4: 55.033194 | G4: 53.634371 | H4: 63.269445 | I4: 57.117863 | J4: 52.239545 | K4: 57.952193 | L4: 65.473363 | M4: 57.112184 | N4: 60.473481 | O4: 57.39401 | P4: 67.933029 | Q4: 66.580476 | R4: 66.667337 | S4: 65.697562 | T4: 74.710516 | U4: 64.799085 | V4: 65.780848 | W4: 67.652886 | X4: 75.855906 | Y4: 61.93582 | Z4: 69.542203 | AA4: 66.343054 | AB4: 61.351683 | AC4: 55.201052 | AD4: 61.144181 | AE4: 64.450945 | AF4: 75.606023 | AG4: 67.855296 | AH4: 69.203416 | AI4: 87.603279 | AJ4: 86.426563 | AK4: 78.926244 | AL4: 73.699695 | AM4: 63.581669 | AN4: 89.019102 | AO4: 86.971238 | AP4: 86.433665 | AQ4: 99.792143 | AR4: 82.224651 | AS4: 89.517586 | AT4: 94.820445 | AU4: 91.982297 | AV4: 89.978801 | AW4: 90.95704 | AX4: 96.628579 | AY4: 88.611344 | AZ4: 104.48146 | BA4: 97.050166 | BB4: 95.484158 | BC4: 91.45942 | BD4: 107.74489 | BE4: 105.31153 | BF4: 99.010517 | BG4: 94.720621 | BH4: 108.72467 | BI4: 112.98123 | BJ4: 93.471789 | BK4: 106.52821 | BL4: =ED4 -> 100 | BM4: 96.865569 | BN4: 110.85295 | BO4: =EG4 -> 103.85926 | BP4: Manufacturing of beverages & tobacco | BQ4: =AVERAGE(BK20:BM20) -> 49.367867 | BR4: =AVERAGE(BN20:BP20) -> 54.027455 | BS4: =AVERAGE(BQ20:BS20) -> 57.8443 | BT4: =AVERAGE(BT20:BV20) -> 48.54216 | BU4: =AVERAGE(BW20:BY20) -> 55.033194 | BV4: =AVERAGE(BZ20:CB20) -> 53.634371 | BW4: =AVERAGE(CC20:CE20) -> 63.269445 | BX4: =AVERAGE(CF20:CH20) -> 57.117863 | BY4: =AVERAGE(CI20:CK20) -> 52.239545 | BZ4: =AVERAGE(CL20:CN20) -> 57.952193 | CA4: =AVERAGE(CO20:CQ20) -> 65.473363 | CB4: =AVERAGE(CR20:CT20) -> 57.112184 | CC4: =AVERAGE(CU20:CW20) -> 60.473481 | CD4: =AVERAGE(CX20:CZ20) -> 57.39401 | CE4: =AVERAGE(DA20:DC20) -> 67.933029 | CF4: =AVERAGE(DD20:DF20) -> 66.580476 | CG4: =AVERAGE(DG20:DI20) -> 66.667337 | CH4: =AVERAGE(DJ20:DL20) -> 65.697562 | CI4: =AVERAGE(DM20:DO20) -> 74.710516 | CJ4: =AVERAGE(DP20:DR20) -> 64.799085 | CK4: =AVERAGE(DS20:DU20) -> 65.780848 | CL4: =AVERAGE(DV20:DX20) -> 67.652886 | CM4: =AVERAGE(DY20:EA20) -> 75.855906 | CN4: =AVERAGE(EB20:ED20) -> 61.93582 | CO4: =AVERAGE(EE20:EG20) -> 69.542203 | CP4: =AVERAGE(EH20:EJ20) -> 66.343054 | CQ4: =AVERAGE(EK20:EM20) -> 61.351683 | CR4: =AVERAGE(EN20:EP20) -> 55.201052 | CS4: =AVERAGE(EQ20:ES20) -> 61.144181 | CT4: =AVERAGE(ET20:EV20) -> 64.450945 | CU4: =AVERAGE(EW20:EY20) -> 75.606023 | CV4: =AVERAGE(EZ20:FB20) -> 67.855296 | CW4: =AVERAGE(FC20:FE20) -> 69.203416 | CX4: =AVERAGE(FF20:FH20) -> 87.603279 | CY4: =AVERAGE(FI20:FK20) -> 86.426563 | CZ4: =AVERAGE(FL20:FN20) -> 78.926244 | DA4: =AVERAGE(FO20:FQ20) -> 73.699695 | DB4: =AVERAGE(FR20:FT20) -> 63.581669 | DC4: =AVERAGE(FU20:FW20) -> 89.019102 | DD4: =AVERAGE(FX20:FZ20) -> 86.971238 | DE4: =AVERAGE(GA20:GC20) -> 86.433665 | DF4: =AVERAGE(GD20:GF20) -> 99.792143 | DG4: =AVERAGE(GG20:GI20) -> 82.224651 | DH4: =AVERAGE(GJ20:GL20) -> 89.517586 | DI4: =AVERAGE(GM20:GO20) -> 94.820445 | DJ4: =AVERAGE(GP20:GR20) -> 91.982297 | DK4: =AVERAGE(GS20:GU20) -> 89.978801 | DL4: =AVERAGE(GV20:GX20) -> 90.95704 | DM4: =AVERAGE(GY20:HA20) -> 96.628579 | DN4: =AVERAGE(HB20:HD20) -> 88.611344 | DO4: =AVERAGE(HE20:HG20) -> 104.48146 | DP4: =AVERAGE(HH20:HJ20) -> 97.050166 | DQ4: =AVERAGE(HK20:HM20) -> 95.484158 | DR4: =AVERAGE(HN20:HP20) -> 91.45942 | DS4: =AVERAGE(HQ20:HS20) -> 107.74489 | DT4: =AVERAGE(HT20:HV20) -> 105.31153 | DU4: =AVERAGE(HW20:HY20) -> 99.010517 | DV4: =AVERAGE(HZ20:IB20) -> 94.720621 | DW4: =AVERAGE(IC20:IE20) -> 108.72467 | DX4: =AVERAGE(IF20:IH20) -> 112.98123 | DY4: =AVERAGE(DM4:DN4) -> 92.619961 | DZ4: =AVERAGE(DO4:DP4) -> 100.76581 | EA4: =AVERAGE(DY4:DZ4) -> 96.692888 | EB4: =AVERAGE(DQ4:DR4) -> 93.471789 | EC4: =AVERAGE(DS4:DT4) -> 106.52821 | ED4: =AVERAGE(EB4:EC4) -> 100 | EE4: =AVERAGE(DU4:DV4) -> 96.865569 | EF4: =AVERAGE(DW4:DX4) -> 110.85295 | EG4: =AVERAGE(EE4:EF4) -> 103.85926
A5: Manufacturing of textiles, clothing & leather goods | B5: 10.72757 | C5: 10.81311 | D5: 11.37383 | E5: 8.7716509 | F5: 7.392126 | G5: 14.760866 | H5: 5.2724204 | I5: 9.3192111 | J5: 6.8381535 | K5: 12.510819 | L5: 11.647296 | M5: 14.26825 | N5: 9.9442638 | O5: 15.132779 | P5: 13.311015 | Q5: 11.904458 | R5: 10.542703 | S5: 13.81063 | T5: 8.8257154 | U5: 11.433929 | V5: 14.540962 | W5: 11.930526 | X5: 8.8221111 | Y5: 20.71781 | Z5: 25.629755 | AA5: 34.062836 | AB5: 26.433576 | AC5: 26.824088 | AD5: 53.440164 | AE5: 59.387821 | AF5: 61.242816 | AG5: 64.113732 | AH5: 60.968082 | AI5: 67.896941 | AJ5: 77.657993 | AK5: 88.734496 | AL5: 68.17615 | AM5: 32.09754 | AN5: 53.69376 | AO5: 105.57327 | AP5: 76.326242 | AQ5: 108.46691 | AR5: 91.966781 | AS5: 106.47206 | AT5: 105.76549 | AU5: 91.706789 | AV5: 101.44085 | AW5: 111.68729 | AX5: 115.16603 | AY5: 104.95221 | AZ5: 99.670251 | BA5: 114.16433 | BB5: 116.91425 | BC5: 104.3922 | BD5: 92.294183 | BE5: 86.399363 | BF5: 103.2972 | BG5: 104.22912 | BH5: 88.774095 | BI5: 88.651943 | BJ5: 110.65323 | BK5: 89.346773 | BL5: =ED5 -> 100 | BM5: 103.76316 | BN5: 88.713019 | BO5: =EG5 -> 96.238091 | BP5: Manufacturing of textiles, clothing & leather goods | BQ5: =AVERAGE(BK21:BM21) -> 10.72757 | BR5: =AVERAGE(BN21:BP21) -> 10.81311 | BS5: =AVERAGE(BQ21:BS21) -> 11.37383 | BT5: =AVERAGE(BT21:BV21) -> 8.7716509 | BU5: =AVERAGE(BW21:BY21) -> 7.392126 | BV5: =AVERAGE(BZ21:CB21) -> 14.760866 | BW5: =AVERAGE(CC21:CE21) -> 5.2724204 | BX5: =AVERAGE(CF21:CH21) -> 9.3192111 | BY5: =AVERAGE(CI21:CK21) -> 6.8381535 | BZ5: =AVERAGE(CL21:CN21) -> 12.510819 | CA5: =AVERAGE(CO21:CQ21) -> 11.647296 | CB5: =AVERAGE(CR21:CT21) -> 14.26825 | CC5: =AVERAGE(CU21:CW21) -> 9.9442638 | CD5: =AVERAGE(CX21:CZ21) -> 15.132779 | CE5: =AVERAGE(DA21:DC21) -> 13.311015 | CF5: =AVERAGE(DD21:DF21) -> 11.904458 | CG5: =AVERAGE(DG21:DI21) -> 10.542703 | CH5: =AVERAGE(DJ21:DL21) -> 13.81063 | CI5: =AVERAGE(DM21:DO21) -> 8.8257154 | CJ5: =AVERAGE(DP21:DR21) -> 11.433929 | CK5: =AVERAGE(DS21:DU21) -> 14.540962 | CL5: =AVERAGE(DV21:DX21) -> 11.930526 | CM5: =AVERAGE(DY21:EA21) -> 8.8221111 | CN5: =AVERAGE(EB21:ED21) -> 20.71781 | CO5: =AVERAGE(EE21:EG21) -> 25.629755 | CP5: =AVERAGE(EH21:EJ21) -> 34.062836 | CQ5: =AVERAGE(EK21:EM21) -> 26.433576 | CR5: =AVERAGE(EN21:EP21) -> 26.824088 | CS5: =AVERAGE(EQ21:ES21) -> 53.440164 | CT5: =AVERAGE(ET21:EV21) -> 59.387821 | CU5: =AVERAGE(EW21:EY21) -> 61.242816 | CV5: =AVERAGE(EZ21:FB21) -> 64.113732 | CW5: =AVERAGE(FC21:FE21) -> 60.968082 | CX5: =AVERAGE(FF21:FH21) -> 67.896941 | CY5: =AVERAGE(FI21:FK21) -> 77.657993 | CZ5: =AVERAGE(FL21:FN21) -> 88.734496 | DA5: =AVERAGE(FO21:FQ21) -> 68.17615 | DB5: =AVERAGE(FR21:FT21) -> 32.09754 | DC5: =AVERAGE(FU21:FW21) -> 53.69376 | DD5: =AVERAGE(FX21:FZ21) -> 105.57327 | DE5: =AVERAGE(GA21:GC21) -> 76.326242 | DF5: =AVERAGE(GD21:GF21) -> 108.46691 | DG5: =AVERAGE(GG21:GI21) -> 91.966781 | DH5: =AVERAGE(GJ21:GL21) -> 106.47206 | DI5: =AVERAGE(GM21:GO21) -> 105.76549 | DJ5: =AVERAGE(GP21:GR21) -> 91.706789 | DK5: =AVERAGE(GS21:GU21) -> 101.44085 | DL5: =AVERAGE(GV21:GX21) -> 111.68729 | DM5: =AVERAGE(GY21:HA21) -> 115.16603 | DN5: =AVERAGE(HB21:HD21) -> 104.95221 | DO5: =AVERAGE(HE21:HG21) -> 99.670251 | DP5: =AVERAGE(HH21:HJ21) -> 114.16433 | DQ5: =AVERAGE(HK21:HM21) -> 116.91425 | DR5: =AVERAGE(HN21:HP21) -> 104.3922 | DS5: =AVERAGE(HQ21:HS21) -> 92.294183 | DT5: =AVERAGE(HT21:HV21) -> 86.399363 | DU5: =AVERAGE(HW21:HY21) -> 103.2972 | DV5: =AVERAGE(HZ21:IB21) -> 104.22912 | DW5: =AVERAGE(IC21:IE21) -> 88.774095 | DX5: =AVERAGE(IF21:IH21) -> 88.651943 | DY5: =AVERAGE(DM5:DN5) -> 110.05912 | DZ5: =AVERAGE(DO5:DP5) -> 106.91729 | EA5: =AVERAGE(DY5:DZ5) -> 108.48821 | EB5: =AVERAGE(DQ5:DR5) -> 110.65323 | EC5: =AVERAGE(DS5:DT5) -> 89.346773 | ED5: =AVERAGE(EB5:EC5) -> 100 | EE5: =AVERAGE(DU5:DV5) -> 103.76316 | EF5: =AVERAGE(DW5:DX5) -> 88.713019 | EG5: =AVERAGE(EE5:EF5) -> 96.238091
A6: Manufacturing of wood & paper; printing | B6: 16.537366 | C6: 16.385345 | D6: 15.435723 | E6: 19.65075 | F6: 15.645197 | G6: 23.122737 | H6: 24.228717 | I6: 26.294056 | J6: 22.709958 | K6: 20.783915 | L6: 35.560464 | M6: 25.836163 | N6: 28.222317 | O6: 29.545676 | P6: 28.423886 | Q6: 29.486391 | R6: 27.031698 | S6: 29.937344 | T6: 28.113386 | U6: 35.423385 | V6: 28.56164 | W6: 29.200666 | X6: 49.003918 | Y6: 37.18102 | Z6: 30.123435 | AA6: 35.931396 | AB6: 30.850977 | AC6: 39.339769 | AD6: 40.541283 | AE6: 39.985974 | AF6: 39.911517 | AG6: 46.819666 | AH6: 48.479974 | AI6: 63.513144 | AJ6: 47.754164 | AK6: 42.491622 | AL6: 35.370937 | AM6: 31.566524 | AN6: 47.5137 | AO6: 55.510729 | AP6: 50.519319 | AQ6: 67.979026 | AR6: 58.722203 | AS6: 58.300989 | AT6: 66.202349 | AU6: 63.476729 | AV6: 85.354082 | AW6: 76.388531 | AX6: 95.067419 | AY6: 101.28558 | AZ6: 103.45131 | BA6: 87.399512 | BB6: 92.471042 | BC6: 130.90675 | BD6: 88.550673 | BE6: 88.071536 | BF6: 90.766587 | BG6: 133.37456 | BH6: 101.0867 | BI6: 85.913574 | BJ6: 111.6889 | BK6: 88.311104 | BL6: =ED6 -> 100 | BM6: 112.07057 | BN6: 93.500139 | BO6: =EG6 -> 102.78536 | BP6: Manufacturing of wood & paper; printing | BQ6: =AVERAGE(BK22:BM22) -> 16.537366 | BR6: =AVERAGE(BN22:BP22) -> 16.385345 | BS6: =AVERAGE(BQ22:BS22) -> 15.435723 | BT6: =AVERAGE(BT22:BV22) -> 19.65075 | BU6: =AVERAGE(BW22:BY22) -> 15.645197 | BV6: =AVERAGE(BZ22:CB22) -> 23.122737 | BW6: =AVERAGE(CC22:CE22) -> 24.228717 | BX6: =AVERAGE(CF22:CH22) -> 26.294056 | BY6: =AVERAGE(CI22:CK22) -> 22.709958 | BZ6: =AVERAGE(CL22:CN22) -> 20.783915 | CA6: =AVERAGE(CO22:CQ22) -> 35.560464 | CB6: =AVERAGE(CR22:CT22) -> 25.836163 | CC6: =AVERAGE(CU22:CW22) -> 28.222317 | CD6: =AVERAGE(CX22:CZ22) -> 29.545676 | CE6: =AVERAGE(DA22:DC22) -> 28.423886 | CF6: =AVERAGE(DD22:DF22) -> 29.486391 | CG6: =AVERAGE(DG22:DI22) -> 27.031698 | CH6: =AVERAGE(DJ22:DL22) -> 29.937344 | CI6: =AVERAGE(DM22:DO22) -> 28.113386 | CJ6: =AVERAGE(DP22:DR22) -> 35.423385 | CK6: =AVERAGE(DS22:DU22) -> 28.56164 | CL6: =AVERAGE(DV22:DX22) -> 29.200666 | CM6: =AVERAGE(DY22:EA22) -> 49.003918 | CN6: =AVERAGE(EB22:ED22) -> 37.18102 | CO6: =AVERAGE(EE22:EG22) -> 30.123435 | CP6: =AVERAGE(EH22:EJ22) -> 35.931396 | CQ6: =AVERAGE(EK22:EM22) -> 30.850977 | CR6: =AVERAGE(EN22:EP22) -> 39.339769 | CS6: =AVERAGE(EQ22:ES22) -> 40.541283 | CT6: =AVERAGE(ET22:EV22) -> 39.985974 | CU6: =AVERAGE(EW22:EY22) -> 39.911517 | CV6: =AVERAGE(EZ22:FB22) -> 46.819666 | CW6: =AVERAGE(FC22:FE22) -> 48.479974 | CX6: =AVERAGE(FF22:FH22) -> 63.513144 | CY6: =AVERAGE(FI22:FK22) -> 47.754164 | CZ6: =AVERAGE(FL22:FN22) -> 42.491622 | DA6: =AVERAGE(FO22:FQ22) -> 35.370937 | DB6: =AVERAGE(FR22:FT22) -> 31.566524 | DC6: =AVERAGE(FU22:FW22) -> 47.5137 | DD6: =AVERAGE(FX22:FZ22) -> 55.510729 | DE6: =AVERAGE(GA22:GC22) -> 50.519319 | DF6: =AVERAGE(GD22:GF22) -> 67.979026 | DG6: =AVERAGE(GG22:GI22) -> 58.722203 | DH6: =AVERAGE(GJ22:GL22) -> 58.300989 | DI6: =AVERAGE(GM22:GO22) -> 66.202349 | DJ6: =AVERAGE(GP22:GR22) -> 63.476729 | DK6: =AVERAGE(GS22:GU22) -> 85.354082 | DL6: =AVERAGE(GV22:GX22) -> 76.388531 | DM6: =AVERAGE(GY22:HA22) -> 95.067419 | DN6: =AVERAGE(HB22:HD22) -> 101.28558 | DO6: =AVERAGE(HE22:HG22) -> 103.45131 | DP6: =AVERAGE(HH22:HJ22) -> 87.399512 | DQ6: =AVERAGE(HK22:HM22) -> 92.471042 | DR6: =AVERAGE(HN22:HP22) -> 130.90675 | DS6: =AVERAGE(HQ22:HS22) -> 88.550673 | DT6: =AVERAGE(HT22:HV22) -> 88.071536 | DU6: =AVERAGE(HW22:HY22) -> 90.766587 | DV6: =AVERAGE(HZ22:IB22) -> 133.37456 | DW6: =AVERAGE(IC22:IE22) -> 101.0867 | DX6: =AVERAGE(IF22:IH22) -> 85.913574 | DY6: =AVERAGE(DM6:DN6) -> 98.176501 | DZ6: =AVERAGE(DO6:DP6) -> 95.425413 | EA6: =AVERAGE(DY6:DZ6) -> 96.800957 | EB6: =AVERAGE(DQ6:DR6) -> 111.6889 | EC6: =AVERAGE(DS6:DT6) -> 88.311104 | ED6: =AVERAGE(EB6:EC6) -> 100 | EE6: =AVERAGE(DU6:DV6) -> 112.07057 | EF6: =AVERAGE(DW6:DX6) -> 93.500139 | EG6: =AVERAGE(EE6:EF6) -> 102.78536
A7: Manufacturing of chemicals, rubber & plastic products | B7: 19.189488 | C7: 20.92835 | D7: 22.561742 | E7: 22.587415 | F7: 25.302379 | G7: 25.277382 | H7: 23.395216 | I7: 24.421463 | J7: 23.314669 | K7: 23.782789 | L7: 22.135134 | M7: 21.105359 | N7: 20.480948 | O7: 23.549029 | P7: 23.712076 | Q7: 22.338792 | R7: 24.9633 | S7: 25.62044 | T7: 28.703159 | U7: 28.058555 | V7: 26.389581 | W7: 29.011611 | X7: 33.203677 | Y7: 30.698301 | Z7: 30.792722 | AA7: 38.088469 | AB7: 36.98241 | AC7: 39.987091 | AD7: 39.00012 | AE7: 42.654094 | AF7: 42.535385 | AG7: 48.031041 | AH7: 48.537974 | AI7: 63.490068 | AJ7: 56.004349 | AK7: 57.380786 | AL7: 57.011369 | AM7: 41.731037 | AN7: 58.788748 | AO7: 67.855508 | AP7: 56.014812 | AQ7: 70.746467 | AR7: 62.489134 | AS7: 66.280716 | AT7: 61.928633 | AU7: 75.373349 | AV7: 86.467887 | AW7: 60.864259 | AX7: 63.222052 | AY7: 83.446009 | AZ7: 113.4276 | BA7: 77.547898 | BB7: 88.315293 | BC7: 117.65216 | BD7: 108.75723 | BE7: 85.275311 | BF7: 90.10373 | BG7: 111.55817 | BH7: 112.94217 | BI7: 88.252922 | BJ7: 102.98373 | BK7: 97.016272 | BL7: =ED7 -> 100 | BM7: 100.83095 | BN7: 100.59755 | BO7: =EG7 -> 100.71425 | BP7: Manufacturing of chemicals, rubber & plastic products | BQ7: =AVERAGE(BK23:BM23) -> 19.189488 | BR7: =AVERAGE(BN23:BP23) -> 20.92835 | BS7: =AVERAGE(BQ23:BS23) -> 22.561742 | BT7: =AVERAGE(BT23:BV23) -> 22.587415 | BU7: =AVERAGE(BW23:BY23) -> 25.302379 | BV7: =AVERAGE(BZ23:CB23) -> 25.277382 | BW7: =AVERAGE(CC23:CE23) -> 23.395216 | BX7: =AVERAGE(CF23:CH23) -> 24.421463 | BY7: =AVERAGE(CI23:CK23) -> 23.314669 | BZ7: =AVERAGE(CL23:CN23) -> 23.782789 | CA7: =AVERAGE(CO23:CQ23) -> 22.135134 | CB7: =AVERAGE(CR23:CT23) -> 21.105359 | CC7: =AVERAGE(CU23:CW23) -> 20.480948 | CD7: =AVERAGE(CX23:CZ23) -> 23.549029 | CE7: =AVERAGE(DA23:DC23) -> 23.712076 | CF7: =AVERAGE(DD23:DF23) -> 22.338792 | CG7: =AVERAGE(DG23:DI23) -> 24.9633 | CH7: =AVERAGE(DJ23:DL23) -> 25.62044 | CI7: =AVERAGE(DM23:DO23) -> 28.703159 | CJ7: =AVERAGE(DP23:DR23) -> 28.058555 | CK7: =AVERAGE(DS23:DU23) -> 26.389581 | CL7: =AVERAGE(DV23:DX23) -> 29.011611 | CM7: =AVERAGE(DY23:EA23) -> 33.203677 | CN7: =AVERAGE(EB23:ED23) -> 30.698301 | CO7: =AVERAGE(EE23:EG23) -> 30.792722 | CP7: =AVERAGE(EH23:EJ23) -> 38.088469 | CQ7: =AVERAGE(EK23:EM23) -> 36.98241 | CR7: =AVERAGE(EN23:EP23) -> 39.987091 | CS7: =AVERAGE(EQ23:ES23) -> 39.00012 | CT7: =AVERAGE(ET23:EV23) -> 42.654094 | CU7: =AVERAGE(EW23:EY23) -> 42.535385 | CV7: =AVERAGE(EZ23:FB23) -> 48.031041 | CW7: =AVERAGE(FC23:FE23) -> 48.537974 | CX7: =AVERAGE(FF23:FH23) -> 63.490068 | CY7: =AVERAGE(FI23:FK23) -> 56.004349 | CZ7: =AVERAGE(FL23:FN23) -> 57.380786 | DA7: =AVERAGE(FO23:FQ23) -> 57.011369 | DB7: =AVERAGE(FR23:FT23) -> 41.731037 | DC7: =AVERAGE(FU23:FW23) -> 58.788748 | DD7: =AVERAGE(FX23:FZ23) -> 67.855508 | DE7: =AVERAGE(GA23:GC23) -> 56.014812 | DF7: =AVERAGE(GD23:GF23) -> 70.746467 | DG7: =AVERAGE(GG23:GI23) -> 62.489134 | DH7: =AVERAGE(GJ23:GL23) -> 66.280716 | DI7: =AVERAGE(GM23:GO23) -> 61.928633 | DJ7: =AVERAGE(GP23:GR23) -> 75.373349 | DK7: =AVERAGE(GS23:GU23) -> 86.467887 | DL7: =AVERAGE(GV23:GX23) -> 60.864259 | DM7: =AVERAGE(GY23:HA23) -> 63.222052 | DN7: =AVERAGE(HB23:HD23) -> 83.446009 | DO7: =AVERAGE(HE23:HG23) -> 113.4276 | DP7: =AVERAGE(HH23:HJ23) -> 77.547898 | DQ7: =AVERAGE(HK23:HM23) -> 88.315293 | DR7: =AVERAGE(HN23:HP23) -> 117.65216 | DS7: =AVERAGE(HQ23:HS23) -> 108.75723 | DT7: =AVERAGE(HT23:HV23) -> 85.275311 | DU7: =AVERAGE(HW23:HY23) -> 90.10373 | DV7: =AVERAGE(HZ23:IB23) -> 111.55817 | DW7: =AVERAGE(IC23:IE23) -> 112.94217 | DX7: =AVERAGE(IF23:IH23) -> 88.252922 | DY7: =AVERAGE(DM7:DN7) -> 73.33403 | DZ7: =AVERAGE(DO7:DP7) -> 95.48775 | EA7: =AVERAGE(DY7:DZ7) -> 84.41089 | EB7: =AVERAGE(DQ7:DR7) -> 102.98373 | EC7: =AVERAGE(DS7:DT7) -> 97.016272 | ED7: =AVERAGE(EB7:EC7) -> 100 | EE7: =AVERAGE(DU7:DV7) -> 100.83095 | EF7: =AVERAGE(DW7:DX7) -> 100.59755 | EG7: =AVERAGE(EE7:EF7) -> 100.71425
A8: Manufacturing of non-metalic mineral products | B8: 15.748849 | C8: 19.880024 | D8: 23.796356 | E8: 21.063021 | F8: 19.737523 | G8: 22.816205 | H8: 24.92737 | I8: 21.010946 | J8: 21.306037 | K8: 21.228334 | L8: 21.487253 | M8: 23.073853 | N8: 23.008964 | O8: 28.385299 | P8: 29.125615 | Q8: 28.537252 | R8: 25.626335 | S8: 24.121801 | T8: 39.844658 | U8: 44.471861 | V8: 39.879466 | W8: 46.515774 | X8: 44.738233 | Y8: 51.958179 | Z8: 46.864498 | AA8: 52.021322 | AB8: 56.961031 | AC8: 57.168441 | AD8: 48.269855 | AE8: 41.472638 | AF8: 78.467085 | AG8: 72.256825 | AH8: 64.335043 | AI8: 69.227678 | AJ8: 73.430864 | AK8: 62.591762 | AL8: 61.639969 | AM8: 60.168934 | AN8: 100.0836 | AO8: 95.745632 | AP8: 77.441131 | AQ8: 103.53374 | AR8: 70.814616 | AS8: 97.264119 | AT8: 83.243861 | AU8: 80.517333 | AV8: 86.717931 | AW8: 109.56512 | AX8: 91.253811 | AY8: 82.770888 | AZ8: 128.87992 | BA8: 91.787155 | BB8: 91.757092 | BC8: 121.85542 | BD8: 96.720003 | BE8: 89.66749 | BF8: 101.26397 | BG8: 124.18164 | BH8: 121.69267 | BI8: 92.736575 | BJ8: 106.80625 | BK8: 93.193746 | BL8: =ED8 -> 100 | BM8: 112.7228 | BN8: 107.21462 | BO8: =EG8 -> 109.96871 | BP8: Manufacturing of non-metalic mineral products | BQ8: =AVERAGE(BK24:BM24) -> 15.748849 | BR8: =AVERAGE(BN24:BP24) -> 19.880024 | BS8: =AVERAGE(BQ24:BS24) -> 23.796356 | BT8: =AVERAGE(BT24:BV24) -> 21.063021 | BU8: =AVERAGE(BW24:BY24) -> 19.737523 | BV8: =AVERAGE(BZ24:CB24) -> 22.816205 | BW8: =AVERAGE(CC24:CE24) -> 24.92737 | BX8: =AVERAGE(CF24:CH24) -> 21.010946 | BY8: =AVERAGE(CI24:CK24) -> 21.306037 | BZ8: =AVERAGE(CL24:CN24) -> 21.228334 | CA8: =AVERAGE(CO24:CQ24) -> 21.487253 | CB8: =AVERAGE(CR24:CT24) -> 23.073853 | CC8: =AVERAGE(CU24:CW24) -> 23.008964 | CD8: =AVERAGE(CX24:CZ24) -> 28.385299 | CE8: =AVERAGE(DA24:DC24) -> 29.125615 | CF8: =AVERAGE(DD24:DF24) -> 28.537252 | CG8: =AVERAGE(DG24:DI24) -> 25.626335 | CH8: =AVERAGE(DJ24:DL24) -> 24.121801 | CI8: =AVERAGE(DM24:DO24) -> 39.844658 | CJ8: =AVERAGE(DP24:DR24) -> 44.471861 | CK8: =AVERAGE(DS24:DU24) -> 39.879466 | CL8: =AVERAGE(DV24:DX24) -> 46.515774 | CM8: =AVERAGE(DY24:EA24) -> 44.738233 | CN8: =AVERAGE(EB24:ED24) -> 51.958179 | CO8: =AVERAGE(EE24:EG24) -> 46.864498 | CP8: =AVERAGE(EH24:EJ24) -> 52.021322 | CQ8: =AVERAGE(EK24:EM24) -> 56.961031 | CR8: =AVERAGE(EN24:EP24) -> 57.168441 | CS8: =AVERAGE(EQ24:ES24) -> 48.269855 | CT8: =AVERAGE(ET24:EV24) -> 41.472638 | CU8: =AVERAGE(EW24:EY24) -> 78.467085 | CV8: =AVERAGE(EZ24:FB24) -> 72.256825 | CW8: =AVERAGE(FC24:FE24) -> 64.335043 | CX8: =AVERAGE(FF24:FH24) -> 69.227678 | CY8: =AVERAGE(FI24:FK24) -> 73.430864 | CZ8: =AVERAGE(FL24:FN24) -> 62.591762 | DA8: =AVERAGE(FO24:FQ24) -> 61.639969 | DB8: =AVERAGE(FR24:FT24) -> 60.168934 | DC8: =AVERAGE(FU24:FW24) -> 100.0836 | DD8: =AVERAGE(FX24:FZ24) -> 95.745632 | DE8: =AVERAGE(GA24:GC24) -> 77.441131 | DF8: =AVERAGE(GD24:GF24) -> 103.53374 | DG8: =AVERAGE(GG24:GI24) -> 70.814616 | DH8: =AVERAGE(GJ24:GL24) -> 97.264119 | DI8: =AVERAGE(GM24:GO24) -> 83.243861 | DJ8: =AVERAGE(GP24:GR24) -> 80.517333 | DK8: =AVERAGE(GS24:GU24) -> 86.717931 | DL8: =AVERAGE(GV24:GX24) -> 109.56512 | DM8: =AVERAGE(GY24:HA24) -> 91.253811 | DN8: =AVERAGE(HB24:HD24) -> 82.770888 | DO8: =AVERAGE(HE24:HG24) -> 128.87992 | DP8: =AVERAGE(HH24:HJ24) -> 91.787155 | DQ8: =AVERAGE(HK24:HM24) -> 91.757092 | DR8: =AVERAGE(HN24:HP24) -> 121.85542 | DS8: =AVERAGE(HQ24:HS24) -> 96.720003 | DT8: =AVERAGE(HT24:HV24) -> 89.66749 | DU8: =AVERAGE(HW24:HY24) -> 101.26397 | DV8: =AVERAGE(HZ24:IB24) -> 124.18164 | DW8: =AVERAGE(IC24:IE24) -> 121.69267 | DX8: =AVERAGE(IF24:IH24) -> 92.736575 | DY8: =AVERAGE(DM8:DN8) -> 87.01235 | DZ8: =AVERAGE(DO8:DP8) -> 110.33354 | EA8: =AVERAGE(DY8:DZ8) -> 98.672944 | EB8: =AVERAGE(DQ8:DR8) -> 106.80625 | EC8: =AVERAGE(DS8:DT8) -> 93.193746 | ED8: =AVERAGE(EB8:EC8) -> 100 | EE8: =AVERAGE(DU8:DV8) -> 112.7228 | EF8: =AVERAGE(DW8:DX8) -> 107.21462 | EG8: =AVERAGE(EE8:EF8) -> 109.96871
A9: Manufacturing of metal products, machinery & equipment | B9: 9.1038728 | C9: 16.101369 | D9: 23.453847 | E9: 19.294162 | F9: 21.089889 | G9: 20.612934 | H9: 24.846587 | I9: 22.727719 | J9: 14.837217 | K9: 19.224685 | L9: 21.513532 | M9: 17.327068 | N9: 20.081114 | O9: 24.318115 | P9: 28.174825 | Q9: 25.396939 | R9: 29.817553 | S9: 34.032918 | T9: 42.343716 | U9: 34.336547 | V9: 36.866485 | W9: 45.856384 | X9: 43.164795 | Y9: 39.865622 | Z9: 37.96989 | AA9: 42.979983 | AB9: 42.367991 | AC9: 41.789302 | AD9: 41.960644 | AE9: 58.833115 | AF9: 59.951792 | AG9: 47.725987 | AH9: 49.233038 | AI9: 74.563045 | AJ9: 64.382306 | AK9: 57.943378 | AL9: 54.925423 | AM9: 46.645219 | AN9: 89.097898 | AO9: 93.213443 | AP9: 65.213991 | AQ9: 73.680449 | AR9: 73.88131 | AS9: 73.572649 | AT9: 70.372749 | AU9: 68.793422 | AV9: 86.626899 | AW9: 79.582753 | AX9: 82.866824 | AY9: 83.535928 | AZ9: 95.598534 | BA9: 79.975359 | BB9: 90.064799 | BC9: 111.71067 | BD9: 102.57705 | BE9: 95.647479 | BF9: 100.64573 | BG9: 110.40601 | BH9: 114.20639 | BI9: 97.604756 | BJ9: 100.88773 | BK9: 99.112266 | BL9: =ED9 -> 100 | BM9: 105.52587 | BN9: 105.90557 | BO9: =EG9 -> 105.71572 | BP9: Manufacturing of metal products, machinery & equipment | BQ9: =AVERAGE(BK25:BM25) -> 9.1038728 | BR9: =AVERAGE(BN25:BP25) -> 16.101369 | BS9: =AVERAGE(BQ25:BS25) -> 23.453847 | BT9: =AVERAGE(BT25:BV25) -> 19.294162 | BU9: =AVERAGE(BW25:BY25) -> 21.089889 | BV9: =AVERAGE(BZ25:CB25) -> 20.612934 | BW9: =AVERAGE(CC25:CE25) -> 24.846587 | BX9: =AVERAGE(CF25:CH25) -> 22.727719 | BY9: =AVERAGE(CI25:CK25) -> 14.837217 | BZ9: =AVERAGE(CL25:CN25) -> 19.224685 | CA9: =AVERAGE(CO25:CQ25) -> 21.513532 | CB9: =AVERAGE(CR25:CT25) -> 17.327068 | CC9: =AVERAGE(CU25:CW25) -> 20.081114 | CD9: =AVERAGE(CX25:CZ25) -> 24.318115 | CE9: =AVERAGE(DA25:DC25) -> 28.174825 | CF9: =AVERAGE(DD25:DF25) -> 25.396939 | CG9: =AVERAGE(DG25:DI25) -> 29.817553 | CH9: =AVERAGE(DJ25:DL25) -> 34.032918 | CI9: =AVERAGE(DM25:DO25) -> 42.343716 | CJ9: =AVERAGE(DP25:DR25) -> 34.336547 | CK9: =AVERAGE(DS25:DU25) -> 36.866485 | CL9: =AVERAGE(DV25:DX25) -> 45.856384 | CM9: =AVERAGE(DY25:EA25) -> 43.164795 | CN9: =AVERAGE(EB25:ED25) -> 39.865622 | CO9: =AVERAGE(EE25:EG25) -> 37.96989 | CP9: =AVERAGE(EH25:EJ25) -> 42.979983 | CQ9: =AVERAGE(EK25:EM25) -> 42.367991 | CR9: =AVERAGE(EN25:EP25) -> 41.789302 | CS9: =AVERAGE(EQ25:ES25) -> 41.960644 | CT9: =AVERAGE(ET25:EV25) -> 58.833115 | CU9: =AVERAGE(EW25:EY25) -> 59.951792 | CV9: =AVERAGE(EZ25:FB25) -> 47.725987 | CW9: =AVERAGE(FC25:FE25) -> 49.233038 | CX9: =AVERAGE(FF25:FH25) -> 74.563045 | CY9: =AVERAGE(FI25:FK25) -> 64.382306 | CZ9: =AVERAGE(FL25:FN25) -> 57.943378 | DA9: =AVERAGE(FO25:FQ25) -> 54.925423 | DB9: =AVERAGE(FR25:FT25) -> 46.645219 | DC9: =AVERAGE(FU25:FW25) -> 89.097898 | DD9: =AVERAGE(FX25:FZ25) -> 93.213443 | DE9: =AVERAGE(GA25:GC25) -> 65.213991 | DF9: =AVERAGE(GD25:GF25) -> 73.680449 | DG9: =AVERAGE(GG25:GI25) -> 73.88131 | DH9: =AVERAGE(GJ25:GL25) -> 73.572649 | DI9: =AVERAGE(GM25:GO25) -> 70.372749 | DJ9: =AVERAGE(GP25:GR25) -> 68.793422 | DK9: =AVERAGE(GS25:GU25) -> 86.626899 | DL9: =AVERAGE(GV25:GX25) -> 79.582753 | DM9: =AVERAGE(GY25:HA25) -> 82.866824 | DN9: =AVERAGE(HB25:HD25) -> 83.535928 | DO9: =AVERAGE(HE25:HG25) -> 95.598534 | DP9: =AVERAGE(HH25:HJ25) -> 79.975359 | DQ9: =AVERAGE(HK25:HM25) -> 90.064799 | DR9: =AVERAGE(HN25:HP25) -> 111.71067 | DS9: =AVERAGE(HQ25:HS25) -> 102.57705 | DT9: =AVERAGE(HT25:HV25) -> 95.647479 | DU9: =AVERAGE(HW25:HY25) -> 100.64573 | DV9: =AVERAGE(HZ25:IB25) -> 110.40601 | DW9: =AVERAGE(IC25:IE25) -> 114.20639 | DX9: =AVERAGE(IF25:IH25) -> 97.604756 | DY9: =AVERAGE(DM9:DN9) -> 83.201376 | DZ9: =AVERAGE(DO9:DP9) -> 87.786947 | EA9: =AVERAGE(DY9:DZ9) -> 85.494161 | EB9: =AVERAGE(DQ9:DR9) -> 100.88773 | EC9: =AVERAGE(DS9:DT9) -> 99.112266 | ED9: =AVERAGE(EB9:EC9) -> 100 | EE9: =AVERAGE(DU9:DV9) -> 105.52587 | EF9: =AVERAGE(DW9:DX9) -> 105.90557 | EG9: =AVERAGE(EE9:EF9) -> 105.71572
A10: Furniture & other manufacturing | B10: 23.180951 | C10: 27.13487 | D10: 31.722288 | E10: 38.477645 | F10: 35.956154 | G10: 49.887771 | H10: 38.68488 | I10: 37.543117 | J10: 33.429662 | K10: 46.769763 | L10: 43.205662 | M10: 44.256491 | N10: 48.566642 | O10: 53.158169 | P10: 58.085025 | Q10: 54.572376 | R10: 59.155327 | S10: 68.166162 | T10: 62.573292 | U10: 63.651276 | V10: 56.34603 | W10: 61.249483 | X10: 59.639295 | Y10: 52.818731 | Z10: 56.178169 | AA10: 62.497526 | AB10: 69.015782 | AC10: 76.573145 | AD10: 76.554727 | AE10: 71.013474 | AF10: 74.91027 | AG10: 68.846414 | AH10: 78.371829 | AI10: 87.160226 | AJ10: 89.724937 | AK10: 86.969455 | AL10: 70.980798 | AM10: 68.607811 | AN10: 91.772329 | AO10: 86.768299 | AP10: 74.479956 | AQ10: 109.22996 | AR10: 93.312956 | AS10: 93.776651 | AT10: 95.192073 | AU10: 96.632776 | AV10: 144.13316 | AW10: 77.939732 | AX10: 86.934352 | AY10: 106.78519 | AZ10: 105.96969 | BA10: 103.93166 | BB10: 85.568527 | BC10: 88.413549 | BD10: 105.88792 | BE10: 120.13001 | BF10: 99.871697 | BG10: 92.289531 | BH10: 132.44243 | BI10: 121.67698 | BJ10: 86.991038 | BK10: 113.00896 | BL10: =ED10 -> 100 | BM10: 96.080614 | BN10: 127.05971 | BO10: =EG10 -> 111.57016 | BP10: Furniture & other manufacturing | BQ10: =AVERAGE(BK26:BM26) -> 23.180951 | BR10: =AVERAGE(BN26:BP26) -> 27.13487 | BS10: =AVERAGE(BQ26:BS26) -> 31.722288 | BT10: =AVERAGE(BT26:BV26) -> 38.477645 | BU10: =AVERAGE(BW26:BY26) -> 35.956154 | BV10: =AVERAGE(BZ26:CB26) -> 49.887771 | BW10: =AVERAGE(CC26:CE26) -> 38.68488 | BX10: =AVERAGE(CF26:CH26) -> 37.543117 | BY10: =AVERAGE(CI26:CK26) -> 33.429662 | BZ10: =AVERAGE(CL26:CN26) -> 46.769763 | CA10: =AVERAGE(CO26:CQ26) -> 43.205662 | CB10: =AVERAGE(CR26:CT26) -> 44.256491 | CC10: =AVERAGE(CU26:CW26) -> 48.566642 | CD10: =AVERAGE(CX26:CZ26) -> 53.158169 | CE10: =AVERAGE(DA26:DC26) -> 58.085025 | CF10: =AVERAGE(DD26:DF26) -> 54.572376 | CG10: =AVERAGE(DG26:DI26) -> 59.155327 | CH10: =AVERAGE(DJ26:DL26) -> 68.166162 | CI10: =AVERAGE(DM26:DO26) -> 62.573292 | CJ10: =AVERAGE(DP26:DR26) -> 63.651276 | CK10: =AVERAGE(DS26:DU26) -> 56.34603 | CL10: =AVERAGE(DV26:DX26) -> 61.249483 | CM10: =AVERAGE(DY26:EA26) -> 59.639295 | CN10: =AVERAGE(EB26:ED26) -> 52.818731 | CO10: =AVERAGE(EE26:EG26) -> 56.178169 | CP10: =AVERAGE(EH26:EJ26) -> 62.497526 | CQ10: =AVERAGE(EK26:EM26) -> 69.015782 | CR10: =AVERAGE(EN26:EP26) -> 76.573145 | CS10: =AVERAGE(EQ26:ES26) -> 76.554727 | CT10: =AVERAGE(ET26:EV26) -> 71.013474 | CU10: =AVERAGE(EW26:EY26) -> 74.91027 | CV10: =AVERAGE(EZ26:FB26) -> 68.846414 | CW10: =AVERAGE(FC26:FE26) -> 78.371829 | CX10: =AVERAGE(FF26:FH26) -> 87.160226 | CY10: =AVERAGE(FI26:FK26) -> 89.724937 | CZ10: =AVERAGE(FL26:FN26) -> 86.969455 | DA10: =AVERAGE(FO26:FQ26) -> 70.980798 | DB10: =AVERAGE(FR26:FT26) -> 68.607811 | DC10: =AVERAGE(FU26:FW26) -> 91.772329 | DD10: =AVERAGE(FX26:FZ26) -> 86.768299 | DE10: =AVERAGE(GA26:GC26) -> 74.479956 | DF10: =AVERAGE(GD26:GF26) -> 109.22996 | DG10: =AVERAGE(GG26:GI26) -> 93.312956 | DH10: =AVERAGE(GJ26:GL26) -> 93.776651 | DI10: =AVERAGE(GM26:GO26) -> 95.192073 | DJ10: =AVERAGE(GP26:GR26) -> 96.632776 | DK10: =AVERAGE(GS26:GU26) -> 144.13316 | DL10: =AVERAGE(GV26:GX26) -> 77.939732 | DM10: =AVERAGE(GY26:HA26) -> 86.934352 | DN10: =AVERAGE(HB26:HD26) -> 106.78519 | DO10: =AVERAGE(HE26:HG26) -> 105.96969 | DP10: =AVERAGE(HH26:HJ26) -> 103.93166 | DQ10: =AVERAGE(HK26:HM26) -> 85.568527 | DR10: =AVERAGE(HN26:HP26) -> 88.413549 | DS10: =AVERAGE(HQ26:HS26) -> 105.88792 | DT10: =AVERAGE(HT26:HV26) -> 120.13001 | DU10: =AVERAGE(HW26:HY26) -> 99.871697 | DV10: =AVERAGE(HZ26:IB26) -> 92.289531 | DW10: =AVERAGE(IC26:IE26) -> 132.44243 | DX10: =AVERAGE(IF26:IH26) -> 121.67698 | DY10: =AVERAGE(DM10:DN10) -> 96.859771 | DZ10: =AVERAGE(DO10:DP10) -> 104.95067 | EA10: =AVERAGE(DY10:DZ10) -> 100.90522 | EB10: =AVERAGE(DQ10:DR10) -> 86.991038 | EC10: =AVERAGE(DS10:DT10) -> 113.00896 | ED10: =AVERAGE(EB10:EC10) -> 100 | EE10: =AVERAGE(DU10:DV10) -> 96.080614 | EF10: =AVERAGE(DW10:DX10) -> 127.05971 | EG10: =AVERAGE(EE10:EF10) -> 111.57016
A11: Manufacturing Total | B11: 24.692933 | C11: 27.822918 | D11: 34.358834 | E11: 31.250036 | F11: 31.364425 | G11: 33.254296 | H11: 36.738041 | I11: 35.851309 | J11: 29.983942 | K11: 34.076961 | L11: 38.642921 | M11: 34.56037 | N11: 34.359338 | O11: 35.77135 | P11: 40.333274 | Q11: 40.877093 | R11: 39.621971 | S11: 42.257702 | T11: 47.457528 | U11: 45.793786 | V11: 43.758122 | W11: 45.483032 | X11: 50.628376 | Y11: 45.268758 | Z11: 46.081838 | AA11: 48.418299 | AB11: 48.410918 | AC11: 52.98859 | AD11: 59.366436 | AE11: 61.242029 | AF11: 65.995348 | AG11: 65.57446 | AH11: 62.592334 | AI11: 71.865199 | AJ11: 70.02785 | AK11: 69.984799 | AL11: 61.577621 | AM11: 56.69493 | AN11: 77.594188 | AO11: 77.421066 | AP11: 64.676379 | AQ11: 75.048421 | AR11: 76.211867 | AS11: 83.592009 | AT11: 81.63221 | AU11: 76.13153 | AV11: 95.469485 | AW11: 86.702351 | AX11: 84.022209 | AY11: 85.511409 | AZ11: 97.296992 | BA11: 85.222904 | BB11: 90.934359 | BC11: 113.51619 | BD11: 97.580894 | BE11: 97.968554 | BF11: 93.657777 | BG11: 116.91314 | BH11: 102.58079 | BI11: 102.06798 | BJ11: 102.22528 | BK11: 97.774724 | BL11: =ED11 -> 100 | BM11: 105.28546 | BN11: 102.32439 | BO11: =EG11 -> 103.80492 | BP11: Manufacturing Total | BQ11: =AVERAGE(BK27:BM27) -> 24.692933 | BR11: =AVERAGE(BN27:BP27) -> 27.822918 | BS11: =AVERAGE(BQ27:BS27) -> 34.358834 | BT11: =AVERAGE(BT27:BV27) -> 31.250036 | BU11: =AVERAGE(BW27:BY27) -> 31.364425 | BV11: =AVERAGE(BZ27:CB27) -> 33.254296 | BW11: =AVERAGE(CC27:CE27) -> 36.738041 | BX11: =AVERAGE(CF27:CH27) -> 35.851309 | BY11: =AVERAGE(CI27:CK27) -> 29.983942 | BZ11: =AVERAGE(CL27:CN27) -> 34.076961 | CA11: =AVERAGE(CO27:CQ27) -> 38.642921 | CB11: =AVERAGE(CR27:CT27) -> 34.56037 | CC11: =AVERAGE(CU27:CW27) -> 34.359338 | CD11: =AVERAGE(CX27:CZ27) -> 35.77135 | CE11: =AVERAGE(DA27:DC27) -> 40.333274 | CF11: =AVERAGE(DD27:DF27) -> 40.877093 | CG11: =AVERAGE(DG27:DI27) -> 39.621971 | CH11: =AVERAGE(DJ27:DL27) -> 42.257702 | CI11: =AVERAGE(DM27:DO27) -> 47.457528 | CJ11: =AVERAGE(DP27:DR27) -> 45.793786 | CK11: =AVERAGE(DS27:DU27) -> 43.758122 | CL11: =AVERAGE(DV27:DX27) -> 45.483032 | CM11: =AVERAGE(DY27:EA27) -> 50.628376 | CN11: =AVERAGE(EB27:ED27) -> 45.268758 | CO11: =AVERAGE(EE27:EG27) -> 46.081838 | CP11: =AVERAGE(EH27:EJ27) -> 48.418299 | CQ11: =AVERAGE(EK27:EM27) -> 48.410918 | CR11: =AVERAGE(EN27:EP27) -> 52.98859 | CS11: =AVERAGE(EQ27:ES27) -> 59.366436 | CT11: =AVERAGE(ET27:EV27) -> 61.242029 | CU11: =AVERAGE(EW27:EY27) -> 65.995348 | CV11: =AVERAGE(EZ27:FB27) -> 65.57446 | CW11: =AVERAGE(FC27:FE27) -> 62.592334 | CX11: =AVERAGE(FF27:FH27) -> 71.865199 | CY11: =AVERAGE(FI27:FK27) -> 70.02785 | CZ11: =AVERAGE(FL27:FN27) -> 69.984799 | DA11: =AVERAGE(FO27:FQ27) -> 61.577621 | DB11: =AVERAGE(FR27:FT27) -> 56.69493 | DC11: =AVERAGE(FU27:FW27) -> 77.594188 | DD11: =AVERAGE(FX27:FZ27) -> 77.421066 | DE11: =AVERAGE(GA27:GC27) -> 64.676379 | DF11: =AVERAGE(GD27:GF27) -> 75.048421 | DG11: =AVERAGE(GG27:GI27) -> 76.211867 | DH11: =AVERAGE(GJ27:GL27) -> 83.592009 | DI11: =AVERAGE(GM27:GO27) -> 81.63221 | DJ11: =AVERAGE(GP27:GR27) -> 76.13153 | DK11: =AVERAGE(GS27:GU27) -> 95.469485 | DL11: =AVERAGE(GV27:GX27) -> 86.702351 | DM11: =AVERAGE(GY27:HA27) -> 84.022209 | DN11: =AVERAGE(HB27:HD27) -> 85.511409 | DO11: =AVERAGE(HE27:HG27) -> 97.296992 | DP11: =AVERAGE(HH27:HJ27) -> 85.222904 | DQ11: =AVERAGE(HK27:HM27) -> 90.934359 | DR11: =AVERAGE(HN27:HP27) -> 113.51619 | DS11: =AVERAGE(HQ27:HS27) -> 97.580894 | DT11: =AVERAGE(HT27:HV27) -> 97.968554 | DU11: =AVERAGE(HW27:HY27) -> 93.657777 | DV11: =AVERAGE(HZ27:IB27) -> 116.91314 | DW11: =AVERAGE(IC27:IE27) -> 102.58079 | DX11: =AVERAGE(IF27:IH27) -> 102.06798 | DY11: =AVERAGE(DM11:DN11) -> 84.766809 | DZ11: =AVERAGE(DO11:DP11) -> 91.259948 | EA11: =AVERAGE(DY11:DZ11) -> 88.013378 | EB11: =AVERAGE(DQ11:DR11) -> 102.22528 | EC11: =AVERAGE(DS11:DT11) -> 97.774724 | ED11: =AVERAGE(EB11:EC11) -> 100 | EE11: =AVERAGE(DU11:DV11) -> 105.28546 | EF11: =AVERAGE(DW11:DX11) -> 102.32439 | EG11: =AVERAGE(EE11:EF11) -> 103.80492
A12: Electricity | B12: 24.676895 | C12: 28.400867 | D12: 29.985025 | E12: 31.913503 | F12: 31.45559 | G12: 33.499234 | H12: 34.055412 | I12: 35.084441 | J12: 34.462228 | K12: 35.833873 | L12: 36.180027 | M12: 38.208342 | N12: 37.442663 | O12: 39.197671 | P12: 39.126135 | Q12: 41.456974 | R12: 40.250938 | S12: 42.81211 | T12: 42.397302 | U12: 44.340979 | V12: 46.799824 | W12: 48.24104 | X12: 48.22427 | Y12: 49.72379 | Z12: 49.120001 | AA12: 51.262247 | AB12: 53.778394 | AC12: 54.107794 | AD12: 54.527034 | AE12: 56.019577 | AF12: 59.552445 | AG12: 58.6528 | AH12: 58.691964 | AI12: 60.942265 | AJ12: 63.418467 | AK12: 62.234701 | AL12: 61.327678 | AM12: 57.027824 | AN12: 64.812997 | AO12: 67.149938 | AP12: 65.426436 | AQ12: 71.01589 | AR12: 73.031146 | AS12: 74.436362 | AT12: 75.305723 | AU12: 78.549878 | AV12: 81.661304 | AW12: 81.621384 | AX12: 85.560772 | AY12: 82.172822 | AZ12: 71.092328 | BA12: 89.839732 | BB12: 91.263267 | BC12: 96.755496 | BD12: 106.21346 | BE12: 105.76778 | BF12: 105.54219 | BG12: 101.94379 | BH12: 116.76131 | BI12: 118.72507 | BJ12: 94.009382 | BK12: 105.99062 | BL12: =ED12 -> 100 | BM12: 103.74299 | BN12: 117.74319 | BO12: =EG12 -> 110.74309 | BP12: Electricity | BQ12: =AVERAGE(BK28:BM28) -> 24.676895 | BR12: =AVERAGE(BN28:BP28) -> 28.400867 | BS12: =AVERAGE(BQ28:BS28) -> 29.985025 | BT12: =AVERAGE(BT28:BV28) -> 31.913503 | BU12: =AVERAGE(BW28:BY28) -> 31.45559 | BV12: =AVERAGE(BZ28:CB28) -> 33.499234 | BW12: =AVERAGE(CC28:CE28) -> 34.055412 | BX12: =AVERAGE(CF28:CH28) -> 35.084441 | BY12: =AVERAGE(CI28:CK28) -> 34.462228 | BZ12: =AVERAGE(CL28:CN28) -> 35.833873 | CA12: =AVERAGE(CO28:CQ28) -> 36.180027 | CB12: =AVERAGE(CR28:CT28) -> 38.208342 | CC12: =AVERAGE(CU28:CW28) -> 37.442663 | CD12: =AVERAGE(CX28:CZ28) -> 39.197671 | CE12: =AVERAGE(DA28:DC28) -> 39.126135 | CF12: =AVERAGE(DD28:DF28) -> 41.456974 | CG12: =AVERAGE(DG28:DI28) -> 40.250938 | CH12: =AVERAGE(DJ28:DL28) -> 42.81211 | CI12: =AVERAGE(DM28:DO28) -> 42.397302 | CJ12: =AVERAGE(DP28:DR28) -> 44.340979 | CK12: =AVERAGE(DS28:DU28) -> 46.799824 | CL12: =AVERAGE(DV28:DX28) -> 48.24104 | CM12: =AVERAGE(DY28:EA28) -> 48.22427 | CN12: =AVERAGE(EB28:ED28) -> 49.72379 | CO12: =AVERAGE(EE28:EG28) -> 49.120001 | CP12: =AVERAGE(EH28:EJ28) -> 51.262247 | CQ12: =AVERAGE(EK28:EM28) -> 53.778394 | CR12: =AVERAGE(EN28:EP28) -> 54.107794 | CS12: =AVERAGE(EQ28:ES28) -> 54.527034 | CT12: =AVERAGE(ET28:EV28) -> 56.019577 | CU12: =AVERAGE(EW28:EY28) -> 59.552445 | CV12: =AVERAGE(EZ28:FB28) -> 58.6528 | CW12: =AVERAGE(FC28:FE28) -> 58.691964 | CX12: =AVERAGE(FF28:FH28) -> 60.942265 | CY12: =AVERAGE(FI28:FK28) -> 63.418467 | CZ12: =AVERAGE(FL28:FN28) -> 62.234701 | DA12: =AVERAGE(FO28:FQ28) -> 61.327678 | DB12: =AVERAGE(FR28:FT28) -> 57.027824 | DC12: =AVERAGE(FU28:FW28) -> 64.812997 | DD12: =AVERAGE(FX28:FZ28) -> 67.149938 | DE12: =AVERAGE(GA28:GC28) -> 65.426436 | DF12: =AVERAGE(GD28:GF28) -> 71.01589 | DG12: =AVERAGE(GG28:GI28) -> 73.031146 | DH12: =AVERAGE(GJ28:GL28) -> 74.436362 | DI12: =AVERAGE(GM28:GO28) -> 75.305723 | DJ12: =AVERAGE(GP28:GR28) -> 78.549878 | DK12: =AVERAGE(GS28:GU28) -> 81.661304 | DL12: =AVERAGE(GV28:GX28) -> 81.621384 | DM12: =AVERAGE(GY28:HA28) -> 85.560772 | DN12: =AVERAGE(HB28:HD28) -> 82.172822 | DO12: =AVERAGE(HE28:HG28) -> 71.092328 | DP12: =AVERAGE(HH28:HJ28) -> 89.839732 | DQ12: =AVERAGE(HK28:HM28) -> 91.263267 | DR12: =AVERAGE(HN28:HP28) -> 96.755496 | DS12: =AVERAGE(HQ28:HS28) -> 106.21346 | DT12: =AVERAGE(HT28:HV28) -> 105.76778 | DU12: =AVERAGE(HW28:HY28) -> 105.54219 | DV12: =AVERAGE(HZ28:IB28) -> 101.94379 | DW12: =AVERAGE(IC28:IE28) -> 116.76131 | DX12: =AVERAGE(IF28:IH28) -> 118.72507 | DY12: =AVERAGE(DM12:DN12) -> 83.866797 | DZ12: =AVERAGE(DO12:DP12) -> 80.46603 | EA12: =AVERAGE(DY12:DZ12) -> 82.166414 | EB12: =AVERAGE(DQ12:DR12) -> 94.009382 | EC12: =AVERAGE(DS12:DT12) -> 105.99062 | ED12: =AVERAGE(EB12:EC12) -> 100 | EE12: =AVERAGE(DU12:DV12) -> 103.74299 | EF12: =AVERAGE(DW12:DX12) -> 117.74319 | EG12: =AVERAGE(EE12:EF12) -> 110.74309
A13: Water & waste management | B13: 34.327041 | C13: 36.524572 | D13: 40.037681 | E13: 41.11076 | F13: 43.071707 | G13: 41.471889 | H13: 46.555749 | I13: 46.491703 | J13: 46.366651 | K13: 47.336985 | L13: 50.375066 | M13: 48.69988 | N13: 49.664975 | O13: 51.304843 | P13: 51.781898 | Q13: 50.035061 | R13: 50.733661 | S13: 49.939582 | T13: 50.819 | U13: 50.216555 | V13: 52.803098 | W13: 55.845911 | X13: 59.033716 | Y13: 56.68342 | Z13: 54.886968 | AA13: 58.006993 | AB13: 59.995701 | AC13: 57.467814 | AD13: 56.465798 | AE13: 57.137629 | AF13: 63.968342 | AG13: 62.736079 | AH13: 61.334498 | AI13: 62.283175 | AJ13: 65.741783 | AK13: 61.649489 | AL13: 61.719611 | AM13: 61.89866 | AN13: 70.88629 | AO13: 68.517474 | AP13: 67.931015 | AQ13: 75.790553 | AR13: 79.944086 | AS13: 82.481214 | AT13: 82.648968 | AU13: 84.454403 | AV13: 89.73526 | AW13: 87.018742 | AX13: 87.797085 | AY13: 87.911557 | AZ13: 95.548172 | BA13: 92.399529 | BB13: 90.764467 | BC13: 97.393107 | BD13: 107.39502 | BE13: 104.44741 | BF13: 102.13746 | BG13: 101.45225 | BH13: 110.76405 | BI13: 110.50326 | BJ13: 94.078787 | BK13: 105.92121 | BL13: =ED13 -> 100 | BM13: 101.79485 | BN13: 110.63365 | BO13: =EG13 -> 106.21425 | BP13: Water & waste management | BQ13: =AVERAGE(BK29:BM29) -> 34.327041 | BR13: =AVERAGE(BN29:BP29) -> 36.524572 | BS13: =AVERAGE(BQ29:BS29) -> 40.037681 | BT13: =AVERAGE(BT29:BV29) -> 41.11076 | BU13: =AVERAGE(BW29:BY29) -> 43.071707 | BV13: =AVERAGE(BZ29:CB29) -> 41.471889 | BW13: =AVERAGE(CC29:CE29) -> 46.555749 | BX13: =AVERAGE(CF29:CH29) -> 46.491703 | BY13: =AVERAGE(CI29:CK29) -> 46.366651 | BZ13: =AVERAGE(CL29:CN29) -> 47.336985 | CA13: =AVERAGE(CO29:CQ29) -> 50.375066 | CB13: =AVERAGE(CR29:CT29) -> 48.69988 | CC13: =AVERAGE(CU29:CW29) -> 49.664975 | CD13: =AVERAGE(CX29:CZ29) -> 51.304843 | CE13: =AVERAGE(DA29:DC29) -> 51.781898 | CF13: =AVERAGE(DD29:DF29) -> 50.035061 | CG13: =AVERAGE(DG29:DI29) -> 50.733661 | CH13: =AVERAGE(DJ29:DL29) -> 49.939582 | CI13: =AVERAGE(DM29:DO29) -> 50.819 | CJ13: =AVERAGE(DP29:DR29) -> 50.216555 | CK13: =AVERAGE(DS29:DU29) -> 52.803098 | CL13: =AVERAGE(DV29:DX29) -> 55.845911 | CM13: =AVERAGE(DY29:EA29) -> 59.033716 | CN13: =AVERAGE(EB29:ED29) -> 56.68342 | CO13: =AVERAGE(EE29:EG29) -> 54.886968 | CP13: =AVERAGE(EH29:EJ29) -> 58.006993 | CQ13: =AVERAGE(EK29:EM29) -> 59.995701 | CR13: =AVERAGE(EN29:EP29) -> 57.467814 | CS13: =AVERAGE(EQ29:ES29) -> 56.465798 | CT13: =AVERAGE(ET29:EV29) -> 57.137629 | CU13: =AVERAGE(EW29:EY29) -> 63.968342 | CV13: =AVERAGE(EZ29:FB29) -> 62.736079 | CW13: =AVERAGE(FC29:FE29) -> 61.334498 | CX13: =AVERAGE(FF29:FH29) -> 62.283175 | CY13: =AVERAGE(FI29:FK29) -> 65.741783 | CZ13: =AVERAGE(FL29:FN29) -> 61.649489 | DA13: =AVERAGE(FO29:FQ29) -> 61.719611 | DB13: =AVERAGE(FR29:FT29) -> 61.89866 | DC13: =AVERAGE(FU29:FW29) -> 70.88629 | DD13: =AVERAGE(FX29:FZ29) -> 68.517474 | DE13: =AVERAGE(GA29:GC29) -> 67.931015 | DF13: =AVERAGE(GD29:GF29) -> 75.790553 | DG13: =AVERAGE(GG29:GI29) -> 79.944086 | DH13: =AVERAGE(GJ29:GL29) -> 82.481214 | DI13: =AVERAGE(GM29:GO29) -> 82.648968 | DJ13: =AVERAGE(GP29:GR29) -> 84.454403 | DK13: =AVERAGE(GS29:GU29) -> 89.73526 | DL13: =AVERAGE(GV29:GX29) -> 87.018742 | DM13: =AVERAGE(GY29:HA29) -> 87.797085 | DN13: =AVERAGE(HB29:HD29) -> 87.911557 | DO13: =AVERAGE(HE29:HG29) -> 95.548172 | DP13: =AVERAGE(HH29:HJ29) -> 92.399529 | DQ13: =AVERAGE(HK29:HM29) -> 90.764467 | DR13: =AVERAGE(HN29:HP29) -> 97.393107 | DS13: =AVERAGE(HQ29:HS29) -> 107.39502 | DT13: =AVERAGE(HT29:HV29) -> 104.44741 | DU13: =AVERAGE(HW29:HY29) -> 102.13746 | DV13: =AVERAGE(HZ29:IB29) -> 101.45225 | DW13: =AVERAGE(IC29:IE29) -> 110.76405 | DX13: =AVERAGE(IF29:IH29) -> 110.50326 | DY13: =AVERAGE(DM13:DN13) -> 87.854321 | DZ13: =AVERAGE(DO13:DP13) -> 93.973851 | EA13: =AVERAGE(DY13:DZ13) -> 90.914086 | EB13: =AVERAGE(DQ13:DR13) -> 94.078787 | EC13: =AVERAGE(DS13:DT13) -> 105.92121 | ED13: =AVERAGE(EB13:EC13) -> 100 | EE13: =AVERAGE(DU13:DV13) -> 101.79485 | EF13: =AVERAGE(DW13:DX13) -> 110.63365 | EG13: =AVERAGE(EE13:EF13) -> 106.21425
A14: Index of Industrial Production (formal acvtivity) | B14: 29.516317 | C14: 29.710065 | D14: 35.269025 | E14: 35.980022 | F14: 33.64372 | G14: 33.332429 | H14: 37.004076 | I14: 38.44034 | J14: 34.907127 | K14: 37.731255 | L14: 40.610699 | M14: 39.570462 | N14: 39.851743 | O14: 39.995619 | P14: 52.231598 | Q14: 44.456675 | R14: 42.350457 | S14: 44.025486 | T14: 50.416371 | U14: 49.74171 | V14: 46.930674 | W14: 48.852412 | X14: 56.735169 | Y14: 50.243366 | Z14: 53.650001 | AA14: 56.133411 | AB14: 57.279079 | AC14: 60.664652 | AD14: 63.859546 | AE14: 65.012062 | AF14: 68.828666 | AG14: 68.643938 | AH14: 66.136668 | AI14: 75.03148 | AJ14: 74.355693 | AK14: 78.666106 | AL14: 68.958569 | AM14: 56.740282 | AN14: 73.264454 | AO14: 78.525056 | AP14: 69.357529 | AQ14: 83.261491 | AR14: 81.011201 | AS14: 87.606512 | AT14: 83.560964 | AU14: 83.330333 | AV14: 96.504069 | AW14: 92.982891 | AX14: 88.617608 | AY14: 89.00109 | AZ14: 96.437225 | BA14: 92.542927 | BB14: 93.3804 | BC14: 103.43879 | BD14: 102.44654 | BE14: 100.73427 | BF14: 99.565591 | BG14: 107.71016 | BH14: 110.23099 | BI14: 108.66771 | BJ14: 98.409593 | BK14: 101.59041 | BL14: =ED14 -> 100 | BM14: 103.63788 | BN14: 109.44935 | BO14: =EG14 -> 106.54362 | BP14: Index of Industrial Production (formal acvtivity) | BQ14: =AVERAGE(BK30:BM30) -> 29.516317 | BR14: =AVERAGE(BN30:BP30) -> 29.710065 | BS14: =AVERAGE(BQ30:BS30) -> 35.269025 | BT14: =AVERAGE(BT30:BV30) -> 35.980022 | BU14: =AVERAGE(BW30:BY30) -> 33.64372 | BV14: =AVERAGE(BZ30:CB30) -> 33.332429 | BW14: =AVERAGE(CC30:CE30) -> 37.004076 | BX14: =AVERAGE(CF30:CH30) -> 38.44034 | BY14: =AVERAGE(CI30:CK30) -> 34.907127 | BZ14: =AVERAGE(CL30:CN30) -> 37.731255 | CA14: =AVERAGE(CO30:CQ30) -> 40.610699 | CB14: =AVERAGE(CR30:CT30) -> 39.570462 | CC14: =AVERAGE(CU30:CW30) -> 39.851743 | CD14: =AVERAGE(CX30:CZ30) -> 39.995619 | CE14: =AVERAGE(DA30:DC30) -> 52.231598 | CF14: =AVERAGE(DD30:DF30) -> 44.456675 | CG14: =AVERAGE(DG30:DI30) -> 42.350457 | CH14: =AVERAGE(DJ30:DL30) -> 44.025486 | CI14: =AVERAGE(DM30:DO30) -> 50.416371 | CJ14: =AVERAGE(DP30:DR30) -> 49.74171 | CK14: =AVERAGE(DS30:DU30) -> 46.930674 | CL14: =AVERAGE(DV30:DX30) -> 48.852412 | CM14: =AVERAGE(DY30:EA30) -> 56.735169 | CN14: =AVERAGE(EB30:ED30) -> 50.243366 | CO14: =AVERAGE(EE30:EG30) -> 53.650001 | CP14: =AVERAGE(EH30:EJ30) -> 56.133411 | CQ14: =AVERAGE(EK30:EM30) -> 57.279079 | CR14: =AVERAGE(EN30:EP30) -> 60.664652 | CS14: =AVERAGE(EQ30:ES30) -> 63.859546 | CT14: =AVERAGE(ET30:EV30) -> 65.012062 | CU14: =AVERAGE(EW30:EY30) -> 68.828666 | CV14: =AVERAGE(EZ30:FB30) -> 68.643938 | CW14: =AVERAGE(FC30:FE30) -> 66.136668 | CX14: =AVERAGE(FF30:FH30) -> 75.03148 | CY14: =AVERAGE(FI30:FK30) -> 74.355693 | CZ14: =AVERAGE(FL30:FN30) -> 78.666106 | DA14: =AVERAGE(FO30:FQ30) -> 68.958569 | DB14: =AVERAGE(FR30:FT30) -> 56.740282 | DC14: =AVERAGE(FU30:FW30) -> 73.264454 | DD14: =AVERAGE(FX30:FZ30) -> 78.525056 | DE14: =AVERAGE(GA30:GC30) -> 69.357529 | DF14: =AVERAGE(GD30:GF30) -> 83.261491 | DG14: =AVERAGE(GG30:GI30) -> 81.011201 | DH14: =AVERAGE(GJ30:GL30) -> 87.606512 | DI14: =AVERAGE(GM30:GO30) -> 83.560964 | DJ14: =AVERAGE(GP30:GR30) -> 83.330333 | DK14: =AVERAGE(GS30:GU30) -> 96.504069 | DL14: =AVERAGE(GV30:GX30) -> 92.982891 | DM14: =AVERAGE(GY30:HA30) -> 88.617608 | DN14: =AVERAGE(HB30:HD30) -> 89.00109 | DO14: =AVERAGE(HE30:HG30) -> 96.437225 | DP14: =AVERAGE(HH30:HJ30) -> 92.542927 | DQ14: =AVERAGE(HK30:HM30) -> 93.3804 | DR14: =AVERAGE(HN30:HP30) -> 103.43879 | DS14: =AVERAGE(HQ30:HS30) -> 102.44654 | DT14: =AVERAGE(HT30:HV30) -> 100.73427 | DU14: =AVERAGE(HW30:HY30) -> 99.565591 | DV14: =AVERAGE(HZ30:IB30) -> 107.71016 | DW14: =AVERAGE(IC30:IE30) -> 110.23099 | DX14: =AVERAGE(IF30:IH30) -> 108.66771 | DY14: =AVERAGE(DM14:DN14) -> 88.809349 | DZ14: =AVERAGE(DO14:DP14) -> 94.490076 | EA14: =AVERAGE(DY14:DZ14) -> 91.649712 | EB14: =AVERAGE(DQ14:DR14) -> 98.409593 | EC14: =AVERAGE(DS14:DT14) -> 101.59041 | ED14: =AVERAGE(EB14:EC14) -> 100 | EE14: =AVERAGE(DU14:DV14) -> 103.63788 | EF14: =AVERAGE(DW14:DX14) -> 109.44935 | EG14: =AVERAGE(EE14:EF14) -> 106.54362
A15: IIP Qo y-o-y Growth rates | DU15: =AVERAGE(HY31:IA31) -> #DIV/0!
A16: Mining & quarrying | F16: =F2/B2-1 -> -0.03373357 | G16: =G2/C2-1 -> 0.0036245816 | H16: =H2/D2-1 -> -0.018257503 | I16: =I2/E2-1 -> -0.030106673 | J16: =J2/F2-1 -> 0.11492094 | K16: =K2/G2-1 -> 0.32383415 | L16: =L2/H2-1 -> 0.17982156 | M16: =M2/I2-1 -> 0.087709793 | ... BI16: =BI2/BE2-1 -> -0.014790788 | DU16: =AVERAGE(HY32:IA32) -> #DIV/0!
A17: Manufacturing of food | F17: =F3/B3-1 -> 0.39180258 | G17: =G3/C3-1 -> 0.3740745 | H17: =H3/D3-1 -> 0.044846002 | I17: =I3/E3-1 -> 0.16707883 | J17: =J3/F3-1 -> -0.010644241 | K17: =K3/G3-1 -> 0.079872052 | L17: =L3/H3-1 -> 0.10079839 | M17: =M3/I3-1 -> -0.064863541 | ... BI17: =BI3/BE3-1 -> 0.030020035 | BK17: Jan 2011 | BL17: Feb 2011 | BM17: Mar 2011 | BN17: Apr 2011 | BO17: May 2011 | BP17: Jun 2011 | BQ17: Jul 2011 | BR17: Aug 2011 | BS17: Sep 2011 | BT17: Oct 2011 | BU17: Nov 2011 | BV17: Dec 2011 | BW17: Jan 2012 | BX17: Feb 2012 | BY17: Mar 2012 | BZ17: Apr 2012 | CA17: May 2012 | CB17: Jun 2012 | CC17: Jul 2012 | CD17: Aug 2012 | CE17: Sep 2012 | CF17: Oct 2012 | CG17: Nov 2012 | CH17: Dec 2012 | CI17: Jan 2013 | CJ17: Feb 2013 | CK17: Mar 2013 | CL17: Apr 2013 | CM17: May 2013 | CN17: Jun 2013 | CO17: Jul 2013 | CP17: Aug 2013 | CQ17: Sep 2013 | CR17: Oct 2013 | CS17: Nov 2013 | CT17: Dec 2013 | CU17: Jan 2014 | CV17: Feb 2014 | CW17: Mar 2014 | CX17: Apr 2014 | CY17: May 2014 | CZ17: Jun 2014 | DA17: Jul 2014 | DB17: Aug 2014 | DC17: Sep 2014 | DD17: Oct 2014 | DE17: Nov 2014 | DF17: Dec 2014 | DG17: Jan 2015 | DH17: Feb 2015 | DI17: Mar 2015 | DJ17: Apr 2015 | DK17: May 2015 | DL17: Jun 2015 | DM17: Jul 2015 | DN17: Aug 2015 | DO17: Sep 2015 | DP17: Oct 2015 | DQ17: Nov 2015 | DR17: Dec 2015 | DS17: Jan 2016 | DT17: Feb 2016 | DU17: Mar 2016 | DV17: Apr 2016 | DW17: May 2016 | DX17: Jun 2016 | DY17: Jul 2016 | DZ17: Aug 2016 | EA17: Sep 2016 | EB17: Oct 2016 | EC17: Nov 2016 | ED17: Dec 2016 | EE17: Jan 2017 | EF17: Feb 2017 | EG17: Mar 2017 | EH17: Apr 2017 | EI17: May 2017 | EJ17: Jun 2017 | EK17: Jul 2017 | EL17: Aug 2017 | EM17: Sep 2017 | EN17: Oct 2017 | EO17: Nov 2017 | EP17: Dec 2017 | EQ17: Jan 2018 | ER17: Feb 2018 | ES17: Mar 2018 | ET17: Apr 2018 | EU17: May 2018 | EV17: Jun 2018 | EW17: Jul 2018 | EX17: Aug 2018 | EY17: Sep 2018 | EZ17: Oct 2018 | FA17: Nov 2018 | FB17: Dec 2018 | FC17: Jan 2019 | FD17: Feb 2019 | FE17: Mar 2019 | FF17: Apr 2019 | FG17: May 2019 | FH17: Jun 2019 | FI17: Jul 2019 | FJ17: Aug 2019 | FK17: Sep 2019 | FL17: Oct 2019 | FM17: Nov 2019 | FN17: Dec 2019 | FO17: Jan 2020 | FP17: Feb 2020 | FQ17: Mar 2020 | FR17: Apr 2020 | FS17: May 2020 | FT17: June 2020 | FU17: Jul 2020 | FV17: Aug 2020 | FW17: Sept 2020 | FX17: Oct 2020 | FY17: Nov 2020 | FZ17: Dec 2020 | GA17: Jan 2021 | GB17: Feb 2021 | GC17: Mar 2021 | GD17: Apr 2021 | GE17: May 2021 | GF17: June 2021 | GG17: Jul 2021 | GH17: Augst 2021 | GI17: Sept 2021 | GJ17: Oct 2021 | GK17: Nov 2021 | GL17: Dec 2021 | GM17: Jan 2022 | GN17: Feb 2022 | GO17: Mar 2022 | GP17: Apr 2022 | GQ17: May 2021 | GR17: Jun 2022 | GS17: Jul 2022 | GT17: Aug 2022 | GU17: Sept 2022 | GV17: Oct 2022 | GW17: Nov 2022 | GX17: Dec 2022 | GY17: Jan 2023 | GZ17: Feb 2023 | HA17: Mar 2023 | HB17: Apr 2023 | HC17: May 2023 | HD17: Jun 2023 | HE17: Jul 2023 | HF17: Aug 2023 | HG17: Sep 2023 | HH17: Oct 2023 | HI17: Nov 2023 | HJ17: Dec 2023 | HK17: Jan 2024 | HL17: Feb 2024 | HM17: Mar 2024 | HN17: Apr 2024 | HO17: May 2024 | HP17: Jun 2024 | HQ17: Jul 2024 | HR17: Aug 2024 | HS17: Sep 2024 | HT17: Oct 2024 | HU17: Nov 2024 | HV17: Dec 2024 | HW17: Jan 2025 | HX17: Feb 2025 | HY17: Mar 2025 | HZ17: Apr 2025 | IA17: May 2025 | IB17: Jun 2025 | IC17: Jul 2025 | ID17: Aug 2025 | IE17: Sep 2025 | IF17: Oct 2025 | IG17: Nov 2025 | IH17: Dec 2025
A18: Manufacturing of beverages & tobacco | F18: =F4/B4-1 -> 0.11475738 | G18: =G4/C4-1 -> -0.0072756292 | H18: =H4/D4-1 -> 0.093788745 | I18: =I4/E4-1 -> 0.17666505 | J18: =J4/F4-1 -> -0.050762993 | K18: =K4/G4-1 -> 0.080504753 | L18: =L4/H4-1 -> 0.034833859 | M18: =M4/I4-1 -> -9.9418585e-05 | ... BI18: =BI4/BE4-1 -> 0.072828666 | BJ18: Mining & quarrying | BK18: 72.605252 | BL18: 75.774178 | BM18: 102.18588 | BN18: 57.837677 | BO18: 70.430805 | BP18: 83.369786 | BQ18: 81.678815 | BR18: 80.890173 | BS18: 88.410388 | BT18: 93.31217 | BU18: 98.443723 | BV18: 97.461212 | BW18: 77.034328 | BX18: 85.373102 | BY18: 79.705417 | BZ18: 68.145062 | CA18: 71.86807 | CB18: 72.392235 | CC18: 71.981759 | CD18: 85.596889 | CE18: 88.818471 | CF18: 95.538077 | CG18: 95.126404 | CH18: 89.84526 | CI18: 94.742255 | CJ18: 76.486229 | CK18: 98.708199 | CL18: 104.31844 | CM18: 94.3605 | CN18: 82.510538 | CO18: 96.451177 | CP18: 95.223338 | CQ18: 99.030118 | CR18: 99.100724 | CS18: 100.08084 | CT18: 105.93163 | CU18: 105.55346 | CV18: 102.40847 | CW18: 106.39117 | CX18: 93.738204 | CY18: 102.59875 | CZ18: 100.98078 | DA18: 184.93696 | DB18: 205.95143 | DC18: 103.80026 | DD18: 114.79217 | DE18: 112.20844 | DF18: 102.70765 | DG18: 102.33667 | DH18: 100.69596 | DI18: 100.44225 | DJ18: 98.702215 | DK18: 96.77908 | DL18: 108.29635 | DM18: 123.90044 | DN18: 131.66 | DO18: 124.48803 | DP18: 139.20774 | DQ18: 110.48636 | DR18: 127.93938 | DS18: 107.66568 | DT18: 108.8265 | DU18: 116.79309 | DV18: 93.652039 | DW18: 112.20725 | DX18: 142.63156 | DY18: 161.82582 | DZ18: 158.20932 | EA18: 132.26554 | EB18: 100.42909 | EC18: 136.7365 | ED18: 136.12139 | EE18: 146.82576 | EF18: 115.47961 | EG18: 175.19475 | EH18: 109.10327 | EI18: 215.61461 | EJ18: 124.37459 | EK18: 183.20348 | EL18: 167.87882 | EM18: 135.7246 | EN18: 185.38803 | EO18: 153.0079 | EP18: 136.12256 | EQ18: 130.78695 | ER18: 124.32497 | ES18: 105.50422 | ET18: 105.92898 | EU18: 123.15084 | EV18: 92.821426 | EW18: 83.728364 | EX18: 91.284231 | EY18: 103.50403 | EZ18: 93.601274 | FA18: 97.38156 | FB18: 109.07342 | FC18: 108.43161 | FD18: 97.110157 | FE18: 83.043243 | FF18: 126.22678 | FG18: 158.56997 | FH18: 80.427411 | FI18: 100.37805 | FJ18: 125.41104 | FK18: 151.23342 | FL18: 187.46375 | FM18: 276.72889 | FN18: 203.08715 | FO18: 218.46914 | FP18: 192.89679 | FQ18: 98.610515 | FR18: 51.186124 | FS18: 43.264335 | FT18: 108.15933 | FU18: 82.019468 | FV18: 64.145675 | FW18: 76.64477 | FX18: 71.324898 | FY18: 76.850185 | FZ18: 54.955184 | GA18: 65.668409 | GB18: 59.383895 | GC18: 67.079792 | GD18: 86.842787 | GE18: 72.691544 | GF18: 140.26331 | GG18: 30.299425 | GH18: 103.59182 | GI18: 160.02959 | GJ18: 107.42232 | GK18: 68.754103 | GL18: 69.021587 | GM18: 68.35612 | GN18: 59.382786 | GO18: 47.376894 | GP18: 42.765356 | GQ18: 104.39737 | GR18: 113.45133 | GS18: 144.57763 | GT18: 140.02038 | GU18: 75.91253 | GV18: 132.81499 | GW18: 145.43911 | GX18: 179.74538 | GY18: 77.232251 | GZ18: 99.80405 | HA18: 101.75186 | HB18: 99.99171 | HC18: 120.48811 | HD18: 93.405998 | HE18: 90.75056 | HF18: 93.593013 | HG18: 105.45874 | HH18: 121.65121 | HI18: 94.414667 | HJ18: 95.050999 | HK18: 102.88583 | HL18: 89.999669 | HM18: 115.513 | HN18: 83.818776 | HO18: 79.265397 | HP18: 81.024079 | HQ18: 115.13811 | HR18: 74.266756 | HS18: 106.82209 | HT18: 116.75612 | HU18: 137.05356 | HV18: 97.456613 | HW18: 107.32997 | HX18: 102.60291 | HY18: 120.27224 | HZ18: 86.822136 | IA18: 86.932663 | IB18: 95.376964 | IC18: 119.5194 | ID18: 94.967756 | IE18: 116.60048 | IF18: 101.26838 | IG18: 142.67872 | IH18: 102.12368
A19: Manufacturing of textiles, clothing & leather goods | F19: =F5/B5-1 -> -0.31092263 | G19: =G5/C5-1 -> 0.36508982 | H19: =H5/D5-1 -> -0.53644283 | I19: =I5/E5-1 -> 0.062423852 | J19: =J5/F5-1 -> -0.074940894 | K19: =K5/G5-1 -> -0.15243328 | L19: =L5/H5-1 -> 1.2090984 | M19: =M5/I5-1 -> 0.53105774 | ... BI19: =BI5/BE5-1 -> 0.026071721 | BJ19: Manufacturing of food | BK19: 27.615503 | BL19: 27.217156 | BM19: 29.79654 | BN19: 23.244318 | BO19: 30.747106 | BP19: 38.366816 | BQ19: 41.430088 | BR19: 54.42672 | BS19: 50.191692 | BT19: 44.884113 | BU19: 48.025333 | BV19: 43.404106 | BW19: 34.591886 | BX19: 37.888496 | BY19: 45.306756 | BZ19: 38.221043 | CA19: 37.045743 | CB19: 51.640317 | CC19: 46.976067 | CD19: 50.55157 | CE19: 55.070554 | CF19: 55.415754 | CG19: 54.01825 | CH19: 49.654658 | CI19: 42.111377 | CJ19: 35.90638 | CK19: 38.515627 | CL19: 41.889173 | CM19: 46.400564 | CN19: 48.753695 | CO19: 48.667142 | CP19: 49.851553 | CQ19: 69.461147 | CR19: 49.190004 | CS19: 46.223409 | CT19: 53.356195 | CU19: 45.222227 | CV19: 44.434645 | CW19: 44.297982 | CX19: 45.530478 | CY19: 46.585312 | CZ19: 43.654148 | DA19: 49.181399 | DB19: 51.706118 | DC19: 57.816464 | DD19: 64.037152 | DE19: 46.96645 | DF19: 67.95735 | DG19: 46.306419 | DH19: 52.879394 | DI19: 54.698527 | DJ19: 53.344047 | DK19: 54.470756 | DL19: 68.096543 | DM19: 64.378809 | DN19: 64.389945 | DO19: 62.703931 | DP19: 70.796899 | DQ19: 56.18309 | DR19: 71.629024 | DS19: 56.845652 | DT19: 58.170269 | DU19: 64.479535 | DV19: 48.335102 | DW19: 63.132141 | DX19: 59.079836 | DY19: 61.031583 | DZ19: 71.42656 | EA19: 69.341693 | EB19: 58.467384 | EC19: 56.904872 | ED19: 60.315368 | EE19: 61.167911 | EF19: 52.087462 | EG19: 60.577296 | EH19: 55.769877 | EI19: 59.96341 | EJ19: 56.177338 | EK19: 61.855427 | EL19: 62.115924 | EM19: 67.267878 | EN19: 77.817903 | EO19: 77.057176 | EP19: 88.338187 | EQ19: 88.952796 | ER19: 91.560979 | ES19: 93.137912 | ET19: 93.370169 | EU19: 94.214385 | EV19: 80.157121 | EW19: 85.604535 | EX19: 92.491325 | EY19: 84.278734 | EZ19: 87.899991 | FA19: 98.395056 | FB19: 91.795325 | FC19: 83.985447 | FD19: 77.540358 | FE19: 83.719978 | FF19: 87.322148 | FG19: 81.883743 | FH19: 71.184844 | FI19: 73.80366 | FJ19: 85.276943 | FK19: 74.802837 | FL19: 85.832794 | FM19: 88.719101 | FN19: 77.826155 | FO19: 75.825001 | FP19: 63.932278 | FQ19: 65.563078 | FR19: 54.640347 | FS19: 72.173604 | FT19: 86.995427 | FU19: 81.054465 | FV19: 65.788244 | FW19: 80.003149 | FX19: 78.340928 | FY19: 66.847094 | FZ19: 77.564778 | GA19: 58.388691 | GB19: 58.22578 | GC19: 84.212 | GD19: 75.99438 | GE19: 66.252612 | GF19: 71.895892 | GG19: 76.294731 | GH19: 102.14032 | GI19: 106.2236 | GJ19: 103.24991 | GK19: 109.80101 | GL19: 112.66076 | GM19: 87.120947 | GN19: 95.519358 | GO19: 101.60364 | GP19: 87.254961 | GQ19: 85.856285 | GR19: 90.405139 | GS19: 113.48222 | GT19: 115.99164 | GU19: 113.03675 | GV19: 112.02766 | GW19: 100.7658 | GX19: 96.365601 | GY19: 84.93111 | GZ19: 80.243649 | HA19: 86.696754 | HB19: 77.400336 | HC19: 87.968086 | HD19: 93.123037 | HE19: 95.239734 | HF19: 101.28227 | HG19: 91.693538 | HH19: 80.651726 | HI19: 87.616044 | HJ19: 100.88551 | HK19: 78.760988 | HL19: 91.070816 | HM19: 89.891696 | HN19: 113.30636 | HO19: 112.88969 | HP19: 95.019398 | HQ19: 86.871904 | HR19: 111.3299 | HS19: 104.60677 | HT19: 94.049966 | HU19: 110.69331 | HV19: 111.50919 | HW19: 91.894767 | HX19: 95.839931 | HY19: 96.909922 | HZ19: 118.42126 | IA19: 120.61873 | IB19: 118.37385 | IC19: 99.616506 | ID19: 104.45299 | IE19: 105.21885 | IF19: 105.32595 | IG19: 111.09106 | IH19: 109.32938
